package com.skyhookwireless;

import android.content.ContentResolver;
import android.content.Context;
import android.net.NetworkInfo.DetailedState;
import android.net.wifi.ScanResult;
import android.net.wifi.SupplicantState;
import android.net.wifi.WifiInfo;
import android.net.wifi.WifiManager;
import android.provider.Settings.System;
import java.lang.reflect.InvocationTargetException;
import java.lang.reflect.Method;
import java.util.ArrayList;
import java.util.Iterator;
import java.util.List;
import java.util.ListIterator;
import java.util.concurrent.FutureTask;

final class _sdkfd extends _sdkdd
{
  private static final _sdknc _sdke;
  static final boolean _sdkt;
  private static final String[] z;
  private final _sdkhb _sdkf;
  private final Context _sdkg;
  private final _sdkb _sdkh;
  private final _sdkmc _sdki;
  private WifiManager _sdkj;
  private Method _sdkk;
  private _sdklc _sdkl;
  private final ArrayList<_sdkjc> _sdkm;
  private boolean _sdkn;
  private _sdkec _sdko;
  private long _sdkp;
  private boolean _sdkq;
  private boolean _sdkr;
  private FutureTask<Void> _sdks;

  // ERROR //
  static
  {
    // Byte code:
    //   0: iconst_1
    //   1: istore_0
    //   2: bipush 75
    //   4: anewarray 41	java/lang/String
    //   7: astore_1
    //   8: ldc 43
    //   10: invokevirtual 47	java/lang/String:toCharArray	()[C
    //   13: astore_2
    //   14: aload_2
    //   15: arraylength
    //   16: istore_3
    //   17: iload_3
    //   18: iload_0
    //   19: if_icmpgt +19577 -> 19596
    //   22: iconst_0
    //   23: istore 4
    //   25: aload_2
    //   26: astore 5
    //   28: iload 4
    //   30: istore 6
    //   32: iload_3
    //   33: istore 7
    //   35: aload_2
    //   36: astore 8
    //   38: iload 7
    //   40: istore 9
    //   42: aload 8
    //   44: iload 4
    //   46: caload
    //   47: istore 10
    //   49: iload 6
    //   51: iconst_5
    //   52: irem
    //   53: tableswitch	default:+31 -> 84, 0:+16479->16532, 1:+16486->16539, 2:+16493->16546, 3:+16500->16553
    //   85: dup_x1
    //   86: istore 11
    //   88: iload 11
    //   90: iload 10
    //   92: ixor
    //   93: i2c
    //   94: istore 12
    //   96: aload 8
    //   98: iload 4
    //   100: iload 12
    //   102: castore
    //   103: iload 6
    //   105: iconst_1
    //   106: iadd
    //   107: istore 4
    //   109: iload 9
    //   111: ifne +18 -> 129
    //   114: aload 5
    //   116: astore 8
    //   118: iload 4
    //   120: istore 6
    //   122: iload 9
    //   124: istore 4
    //   126: goto -84 -> 42
    //   129: iload 9
    //   131: istore_3
    //   132: aload 5
    //   134: astore_2
    //   135: iload_3
    //   136: iload 4
    //   138: if_icmpgt -113 -> 25
    //   141: new 41	java/lang/String
    //   144: dup
    //   145: aload_2
    //   146: invokespecial 51	java/lang/String:<init>	([C)V
    //   149: invokevirtual 55	java/lang/String:intern	()Ljava/lang/String;
    //   152: astore 13
    //   154: aload_1
    //   155: iconst_0
    //   156: aload 13
    //   158: aastore
    //   159: ldc 57
    //   161: invokevirtual 47	java/lang/String:toCharArray	()[C
    //   164: astore 14
    //   166: aload 14
    //   168: arraylength
    //   169: istore 15
    //   171: iload 15
    //   173: iconst_1
    //   174: if_icmpgt +19416 -> 19590
    //   177: iconst_0
    //   178: istore 16
    //   180: aload 14
    //   182: astore 5
    //   184: iload 16
    //   186: istore 6
    //   188: iload 15
    //   190: istore 17
    //   192: aload 14
    //   194: astore 18
    //   196: iload 17
    //   198: istore 19
    //   200: aload 18
    //   202: iload 16
    //   204: caload
    //   205: istore 10
    //   207: iload 6
    //   209: iconst_5
    //   210: irem
    //   211: tableswitch	default:+29 -> 240, 0:+16349->16560, 1:+16356->16567, 2:+16363->16574, 3:+16370->16581
    //   241: dup_x1
    //   242: istore 20
    //   244: iload 20
    //   246: iload 10
    //   248: ixor
    //   249: i2c
    //   250: istore 21
    //   252: aload 18
    //   254: iload 16
    //   256: iload 21
    //   258: castore
    //   259: iload 6
    //   261: iconst_1
    //   262: iadd
    //   263: istore 16
    //   265: iload 19
    //   267: ifne +18 -> 285
    //   270: aload 5
    //   272: astore 18
    //   274: iload 16
    //   276: istore 22
    //   278: iload 19
    //   280: istore 16
    //   282: goto -82 -> 200
    //   285: iload 19
    //   287: istore 15
    //   289: aload 5
    //   291: astore 14
    //   293: iload 15
    //   295: iload 16
    //   297: if_icmpgt -117 -> 180
    //   300: new 41	java/lang/String
    //   303: dup
    //   304: aload 14
    //   306: invokespecial 51	java/lang/String:<init>	([C)V
    //   309: invokevirtual 55	java/lang/String:intern	()Ljava/lang/String;
    //   312: astore 23
    //   314: aload_1
    //   315: iconst_1
    //   316: aload 23
    //   318: aastore
    //   319: iconst_2
    //   320: istore 24
    //   322: ldc 59
    //   324: invokevirtual 47	java/lang/String:toCharArray	()[C
    //   327: astore 25
    //   329: aload 25
    //   331: arraylength
    //   332: istore 26
    //   334: iload 26
    //   336: iconst_1
    //   337: if_icmpgt +19247 -> 19584
    //   340: iconst_0
    //   341: istore 27
    //   343: aload 25
    //   345: astore 5
    //   347: iload 27
    //   349: istore 6
    //   351: iload 26
    //   353: istore 28
    //   355: aload 25
    //   357: astore 29
    //   359: iload 28
    //   361: istore 30
    //   363: aload 29
    //   365: iload 27
    //   367: caload
    //   368: istore 31
    //   370: iload 6
    //   372: iconst_5
    //   373: irem
    //   374: tableswitch	default:+30 -> 404, 0:+16214->16588, 1:+16221->16595, 2:+16228->16602, 3:+16235->16609
    //   405: dup_x1
    //   406: istore 32
    //   408: iload 32
    //   410: iload 31
    //   412: ixor
    //   413: i2c
    //   414: istore 33
    //   416: aload 29
    //   418: iload 27
    //   420: iload 33
    //   422: castore
    //   423: iload 6
    //   425: iconst_1
    //   426: iadd
    //   427: istore 27
    //   429: iload 30
    //   431: ifne +18 -> 449
    //   434: aload 5
    //   436: astore 29
    //   438: iload 27
    //   440: istore 34
    //   442: iload 30
    //   444: istore 27
    //   446: goto -83 -> 363
    //   449: iload 30
    //   451: istore 26
    //   453: aload 5
    //   455: astore 25
    //   457: iload 26
    //   459: iload 27
    //   461: if_icmpgt -118 -> 343
    //   464: new 41	java/lang/String
    //   467: dup
    //   468: aload 25
    //   470: invokespecial 51	java/lang/String:<init>	([C)V
    //   473: invokevirtual 55	java/lang/String:intern	()Ljava/lang/String;
    //   476: astore 35
    //   478: aload_1
    //   479: iload 24
    //   481: aload 35
    //   483: aastore
    //   484: iconst_3
    //   485: istore 36
    //   487: ldc 61
    //   489: invokevirtual 47	java/lang/String:toCharArray	()[C
    //   492: astore 37
    //   494: aload 37
    //   496: arraylength
    //   497: istore 38
    //   499: iload 38
    //   501: iconst_1
    //   502: if_icmpgt +19076 -> 19578
    //   505: iconst_0
    //   506: istore 39
    //   508: aload 37
    //   510: astore 5
    //   512: iload 39
    //   514: istore 6
    //   516: iload 38
    //   518: istore 40
    //   520: aload 37
    //   522: astore 41
    //   524: iload 40
    //   526: istore 42
    //   528: aload 41
    //   530: iload 39
    //   532: caload
    //   533: istore 31
    //   535: iload 6
    //   537: iconst_5
    //   538: irem
    //   539: tableswitch	default:+29 -> 568, 0:+16077->16616, 1:+16084->16623, 2:+16091->16630, 3:+16098->16637
    //   569: dup_x1
    //   570: istore 43
    //   572: iload 43
    //   574: iload 31
    //   576: ixor
    //   577: i2c
    //   578: istore 44
    //   580: aload 41
    //   582: iload 39
    //   584: iload 44
    //   586: castore
    //   587: iload 6
    //   589: iconst_1
    //   590: iadd
    //   591: istore 39
    //   593: iload 42
    //   595: ifne +18 -> 613
    //   598: aload 5
    //   600: astore 41
    //   602: iload 39
    //   604: istore 45
    //   606: iload 42
    //   608: istore 39
    //   610: goto -82 -> 528
    //   613: iload 42
    //   615: istore 38
    //   617: aload 5
    //   619: astore 37
    //   621: iload 38
    //   623: iload 39
    //   625: if_icmpgt -117 -> 508
    //   628: new 41	java/lang/String
    //   631: dup
    //   632: aload 37
    //   634: invokespecial 51	java/lang/String:<init>	([C)V
    //   637: invokevirtual 55	java/lang/String:intern	()Ljava/lang/String;
    //   640: astore 46
    //   642: aload_1
    //   643: iload 36
    //   645: aload 46
    //   647: aastore
    //   648: iconst_4
    //   649: istore 47
    //   651: ldc 63
    //   653: invokevirtual 47	java/lang/String:toCharArray	()[C
    //   656: astore 48
    //   658: aload 48
    //   660: arraylength
    //   661: istore 49
    //   663: iload 49
    //   665: iconst_1
    //   666: if_icmpgt +18906 -> 19572
    //   669: iconst_0
    //   670: istore 50
    //   672: aload 48
    //   674: astore 5
    //   676: iload 50
    //   678: istore 6
    //   680: iload 49
    //   682: istore 51
    //   684: aload 48
    //   686: astore 52
    //   688: iload 51
    //   690: istore 53
    //   692: aload 52
    //   694: iload 50
    //   696: caload
    //   697: istore 31
    //   699: iload 6
    //   701: iconst_5
    //   702: irem
    //   703: tableswitch	default:+29 -> 732, 0:+15941->16644, 1:+15948->16651, 2:+15955->16658, 3:+15962->16665
    //   733: dup_x1
    //   734: istore 54
    //   736: iload 54
    //   738: iload 31
    //   740: ixor
    //   741: i2c
    //   742: istore 55
    //   744: aload 52
    //   746: iload 50
    //   748: iload 55
    //   750: castore
    //   751: iload 6
    //   753: iconst_1
    //   754: iadd
    //   755: istore 50
    //   757: iload 53
    //   759: ifne +18 -> 777
    //   762: aload 5
    //   764: astore 52
    //   766: iload 50
    //   768: istore 56
    //   770: iload 53
    //   772: istore 50
    //   774: goto -82 -> 692
    //   777: iload 53
    //   779: istore 49
    //   781: aload 5
    //   783: astore 48
    //   785: iload 49
    //   787: iload 50
    //   789: if_icmpgt -117 -> 672
    //   792: new 41	java/lang/String
    //   795: dup
    //   796: aload 48
    //   798: invokespecial 51	java/lang/String:<init>	([C)V
    //   801: invokevirtual 55	java/lang/String:intern	()Ljava/lang/String;
    //   804: astore 57
    //   806: aload_1
    //   807: iload 47
    //   809: aload 57
    //   811: aastore
    //   812: iconst_5
    //   813: istore 58
    //   815: ldc 65
    //   817: invokevirtual 47	java/lang/String:toCharArray	()[C
    //   820: astore 59
    //   822: aload 59
    //   824: arraylength
    //   825: istore 60
    //   827: iload 60
    //   829: iconst_1
    //   830: if_icmpgt +18736 -> 19566
    //   833: iconst_0
    //   834: istore 61
    //   836: aload 59
    //   838: astore 5
    //   840: iload 61
    //   842: istore 6
    //   844: iload 60
    //   846: istore 62
    //   848: aload 59
    //   850: astore 63
    //   852: iload 62
    //   854: istore 64
    //   856: aload 63
    //   858: iload 61
    //   860: caload
    //   861: istore 31
    //   863: iload 6
    //   865: iconst_5
    //   866: irem
    //   867: tableswitch	default:+29 -> 896, 0:+15805->16672, 1:+15812->16679, 2:+15819->16686, 3:+15826->16693
    //   897: dup_x1
    //   898: istore 65
    //   900: iload 65
    //   902: iload 31
    //   904: ixor
    //   905: i2c
    //   906: istore 66
    //   908: aload 63
    //   910: iload 61
    //   912: iload 66
    //   914: castore
    //   915: iload 6
    //   917: iconst_1
    //   918: iadd
    //   919: istore 61
    //   921: iload 64
    //   923: ifne +18 -> 941
    //   926: aload 5
    //   928: astore 63
    //   930: iload 61
    //   932: istore 67
    //   934: iload 64
    //   936: istore 61
    //   938: goto -82 -> 856
    //   941: iload 64
    //   943: istore 60
    //   945: aload 5
    //   947: astore 59
    //   949: iload 60
    //   951: iload 61
    //   953: if_icmpgt -117 -> 836
    //   956: new 41	java/lang/String
    //   959: dup
    //   960: aload 59
    //   962: invokespecial 51	java/lang/String:<init>	([C)V
    //   965: invokevirtual 55	java/lang/String:intern	()Ljava/lang/String;
    //   968: astore 68
    //   970: aload_1
    //   971: iload 58
    //   973: aload 68
    //   975: aastore
    //   976: bipush 6
    //   978: istore 69
    //   980: ldc 67
    //   982: invokevirtual 47	java/lang/String:toCharArray	()[C
    //   985: astore 70
    //   987: aload 70
    //   989: arraylength
    //   990: istore 71
    //   992: iload 71
    //   994: iconst_1
    //   995: if_icmpgt +18565 -> 19560
    //   998: iconst_0
    //   999: istore 72
    //   1001: aload 70
    //   1003: astore 5
    //   1005: iload 72
    //   1007: istore 6
    //   1009: iload 71
    //   1011: istore 73
    //   1013: aload 70
    //   1015: astore 74
    //   1017: iload 73
    //   1019: istore 75
    //   1021: aload 74
    //   1023: iload 72
    //   1025: caload
    //   1026: istore 31
    //   1028: iload 6
    //   1030: iconst_5
    //   1031: irem
    //   1032: tableswitch	default:+32 -> 1064, 0:+15668->16700, 1:+15675->16707, 2:+15682->16714, 3:+15689->16721
    //   1065: dup_x1
    //   1066: istore 76
    //   1068: iload 76
    //   1070: iload 31
    //   1072: ixor
    //   1073: i2c
    //   1074: istore 77
    //   1076: aload 74
    //   1078: iload 72
    //   1080: iload 77
    //   1082: castore
    //   1083: iload 6
    //   1085: iconst_1
    //   1086: iadd
    //   1087: istore 72
    //   1089: iload 75
    //   1091: ifne +18 -> 1109
    //   1094: aload 5
    //   1096: astore 74
    //   1098: iload 72
    //   1100: istore 78
    //   1102: iload 75
    //   1104: istore 72
    //   1106: goto -85 -> 1021
    //   1109: iload 75
    //   1111: istore 71
    //   1113: aload 5
    //   1115: astore 70
    //   1117: iload 71
    //   1119: iload 72
    //   1121: if_icmpgt -120 -> 1001
    //   1124: new 41	java/lang/String
    //   1127: dup
    //   1128: aload 70
    //   1130: invokespecial 51	java/lang/String:<init>	([C)V
    //   1133: invokevirtual 55	java/lang/String:intern	()Ljava/lang/String;
    //   1136: astore 79
    //   1138: aload_1
    //   1139: iload 69
    //   1141: aload 79
    //   1143: aastore
    //   1144: ldc 69
    //   1146: invokevirtual 47	java/lang/String:toCharArray	()[C
    //   1149: astore 80
    //   1151: aload 80
    //   1153: arraylength
    //   1154: istore 81
    //   1156: iload 81
    //   1158: iconst_1
    //   1159: if_icmpgt +18395 -> 19554
    //   1162: iconst_0
    //   1163: istore 82
    //   1165: aload 80
    //   1167: astore 5
    //   1169: iload 82
    //   1171: istore 6
    //   1173: iload 81
    //   1175: istore 83
    //   1177: aload 80
    //   1179: astore 84
    //   1181: iload 83
    //   1183: istore 85
    //   1185: aload 84
    //   1187: iload 82
    //   1189: caload
    //   1190: istore 69
    //   1192: iload 6
    //   1194: iconst_5
    //   1195: irem
    //   1196: tableswitch	default:+32 -> 1228, 0:+15532->16728, 1:+15539->16735, 2:+15546->16742, 3:+15553->16749
    //   1229: dup_x1
    //   1230: istore 86
    //   1232: iload 86
    //   1234: iload 69
    //   1236: ixor
    //   1237: i2c
    //   1238: istore 87
    //   1240: aload 84
    //   1242: iload 82
    //   1244: iload 87
    //   1246: castore
    //   1247: iload 6
    //   1249: iconst_1
    //   1250: iadd
    //   1251: istore 82
    //   1253: iload 85
    //   1255: ifne +18 -> 1273
    //   1258: aload 5
    //   1260: astore 84
    //   1262: iload 82
    //   1264: istore 88
    //   1266: iload 85
    //   1268: istore 82
    //   1270: goto -85 -> 1185
    //   1273: iload 85
    //   1275: istore 81
    //   1277: aload 5
    //   1279: astore 80
    //   1281: iload 81
    //   1283: iload 82
    //   1285: if_icmpgt -120 -> 1165
    //   1288: new 41	java/lang/String
    //   1291: dup
    //   1292: aload 80
    //   1294: invokespecial 51	java/lang/String:<init>	([C)V
    //   1297: invokevirtual 55	java/lang/String:intern	()Ljava/lang/String;
    //   1300: astore 89
    //   1302: aload_1
    //   1303: bipush 7
    //   1305: aload 89
    //   1307: aastore
    //   1308: bipush 8
    //   1310: istore 90
    //   1312: ldc 71
    //   1314: invokevirtual 47	java/lang/String:toCharArray	()[C
    //   1317: astore 91
    //   1319: aload 91
    //   1321: arraylength
    //   1322: istore 92
    //   1324: iload 92
    //   1326: iconst_1
    //   1327: if_icmpgt +18221 -> 19548
    //   1330: iconst_0
    //   1331: istore 93
    //   1333: aload 91
    //   1335: astore 5
    //   1337: iload 93
    //   1339: istore 6
    //   1341: iload 92
    //   1343: istore 94
    //   1345: aload 91
    //   1347: astore 95
    //   1349: iload 94
    //   1351: istore 96
    //   1353: aload 95
    //   1355: iload 93
    //   1357: caload
    //   1358: istore 31
    //   1360: iload 6
    //   1362: iconst_5
    //   1363: irem
    //   1364: tableswitch	default:+32 -> 1396, 0:+15392->16756, 1:+15399->16763, 2:+15406->16770, 3:+15413->16777
    //   1397: dup_x1
    //   1398: istore 97
    //   1400: iload 97
    //   1402: iload 31
    //   1404: ixor
    //   1405: i2c
    //   1406: istore 98
    //   1408: aload 95
    //   1410: iload 93
    //   1412: iload 98
    //   1414: castore
    //   1415: iload 6
    //   1417: iconst_1
    //   1418: iadd
    //   1419: istore 93
    //   1421: iload 96
    //   1423: ifne +18 -> 1441
    //   1426: aload 5
    //   1428: astore 95
    //   1430: iload 93
    //   1432: istore 99
    //   1434: iload 96
    //   1436: istore 93
    //   1438: goto -85 -> 1353
    //   1441: iload 96
    //   1443: istore 92
    //   1445: aload 5
    //   1447: astore 91
    //   1449: iload 92
    //   1451: iload 93
    //   1453: if_icmpgt -120 -> 1333
    //   1456: new 41	java/lang/String
    //   1459: dup
    //   1460: aload 91
    //   1462: invokespecial 51	java/lang/String:<init>	([C)V
    //   1465: invokevirtual 55	java/lang/String:intern	()Ljava/lang/String;
    //   1468: astore 100
    //   1470: aload_1
    //   1471: iload 90
    //   1473: aload 100
    //   1475: aastore
    //   1476: bipush 9
    //   1478: istore 101
    //   1480: ldc 73
    //   1482: invokevirtual 47	java/lang/String:toCharArray	()[C
    //   1485: astore 102
    //   1487: aload 102
    //   1489: arraylength
    //   1490: istore 103
    //   1492: iload 103
    //   1494: iconst_1
    //   1495: if_icmpgt +18047 -> 19542
    //   1498: iconst_0
    //   1499: istore 104
    //   1501: aload 102
    //   1503: astore 5
    //   1505: iload 104
    //   1507: istore 6
    //   1509: iload 103
    //   1511: istore 105
    //   1513: aload 102
    //   1515: astore 106
    //   1517: iload 105
    //   1519: istore 107
    //   1521: aload 106
    //   1523: iload 104
    //   1525: caload
    //   1526: istore 31
    //   1528: iload 6
    //   1530: iconst_5
    //   1531: irem
    //   1532: tableswitch	default:+32 -> 1564, 0:+15252->16784, 1:+15259->16791, 2:+15266->16798, 3:+15273->16805
    //   1565: dup_x1
    //   1566: istore 108
    //   1568: iload 108
    //   1570: iload 31
    //   1572: ixor
    //   1573: i2c
    //   1574: istore 109
    //   1576: aload 106
    //   1578: iload 104
    //   1580: iload 109
    //   1582: castore
    //   1583: iload 6
    //   1585: iconst_1
    //   1586: iadd
    //   1587: istore 104
    //   1589: iload 107
    //   1591: ifne +18 -> 1609
    //   1594: aload 5
    //   1596: astore 106
    //   1598: iload 104
    //   1600: istore 110
    //   1602: iload 107
    //   1604: istore 104
    //   1606: goto -85 -> 1521
    //   1609: iload 107
    //   1611: istore 103
    //   1613: aload 5
    //   1615: astore 102
    //   1617: iload 103
    //   1619: iload 104
    //   1621: if_icmpgt -120 -> 1501
    //   1624: new 41	java/lang/String
    //   1627: dup
    //   1628: aload 102
    //   1630: invokespecial 51	java/lang/String:<init>	([C)V
    //   1633: invokevirtual 55	java/lang/String:intern	()Ljava/lang/String;
    //   1636: astore 111
    //   1638: aload_1
    //   1639: iload 101
    //   1641: aload 111
    //   1643: aastore
    //   1644: bipush 10
    //   1646: istore 112
    //   1648: ldc 75
    //   1650: invokevirtual 47	java/lang/String:toCharArray	()[C
    //   1653: astore 113
    //   1655: aload 113
    //   1657: arraylength
    //   1658: istore 114
    //   1660: iload 114
    //   1662: iconst_1
    //   1663: if_icmpgt +17873 -> 19536
    //   1666: iconst_0
    //   1667: istore 115
    //   1669: aload 113
    //   1671: astore 5
    //   1673: iload 115
    //   1675: istore 6
    //   1677: iload 114
    //   1679: istore 116
    //   1681: aload 113
    //   1683: astore 117
    //   1685: iload 116
    //   1687: istore 118
    //   1689: aload 117
    //   1691: iload 115
    //   1693: caload
    //   1694: istore 31
    //   1696: iload 6
    //   1698: iconst_5
    //   1699: irem
    //   1700: tableswitch	default:+32 -> 1732, 0:+15112->16812, 1:+15119->16819, 2:+15126->16826, 3:+15133->16833
    //   1733: dup_x1
    //   1734: istore 119
    //   1736: iload 119
    //   1738: iload 31
    //   1740: ixor
    //   1741: i2c
    //   1742: istore 120
    //   1744: aload 117
    //   1746: iload 115
    //   1748: iload 120
    //   1750: castore
    //   1751: iload 6
    //   1753: iconst_1
    //   1754: iadd
    //   1755: istore 115
    //   1757: iload 118
    //   1759: ifne +18 -> 1777
    //   1762: aload 5
    //   1764: astore 117
    //   1766: iload 115
    //   1768: istore 121
    //   1770: iload 118
    //   1772: istore 115
    //   1774: goto -85 -> 1689
    //   1777: iload 118
    //   1779: istore 114
    //   1781: aload 5
    //   1783: astore 113
    //   1785: iload 114
    //   1787: iload 115
    //   1789: if_icmpgt -120 -> 1669
    //   1792: new 41	java/lang/String
    //   1795: dup
    //   1796: aload 113
    //   1798: invokespecial 51	java/lang/String:<init>	([C)V
    //   1801: invokevirtual 55	java/lang/String:intern	()Ljava/lang/String;
    //   1804: astore 122
    //   1806: aload_1
    //   1807: iload 112
    //   1809: aload 122
    //   1811: aastore
    //   1812: bipush 11
    //   1814: istore 123
    //   1816: ldc 77
    //   1818: invokevirtual 47	java/lang/String:toCharArray	()[C
    //   1821: astore 124
    //   1823: aload 124
    //   1825: arraylength
    //   1826: istore 125
    //   1828: iload 125
    //   1830: iconst_1
    //   1831: if_icmpgt +17699 -> 19530
    //   1834: iconst_0
    //   1835: istore 126
    //   1837: aload 124
    //   1839: astore 5
    //   1841: iload 126
    //   1843: istore 6
    //   1845: iload 125
    //   1847: istore 127
    //   1849: aload 124
    //   1851: astore 128
    //   1853: iload 127
    //   1855: istore 129
    //   1857: aload 128
    //   1859: iload 126
    //   1861: caload
    //   1862: istore 31
    //   1864: iload 6
    //   1866: iconst_5
    //   1867: irem
    //   1868: tableswitch	default:+32 -> 1900, 0:+14972->16840, 1:+14979->16847, 2:+14986->16854, 3:+14993->16861
    //   1901: dup_x1
    //   1902: istore 130
    //   1904: iload 130
    //   1906: iload 31
    //   1908: ixor
    //   1909: i2c
    //   1910: istore 131
    //   1912: aload 128
    //   1914: iload 126
    //   1916: iload 131
    //   1918: castore
    //   1919: iload 6
    //   1921: iconst_1
    //   1922: iadd
    //   1923: istore 126
    //   1925: iload 129
    //   1927: ifne +18 -> 1945
    //   1930: aload 5
    //   1932: astore 128
    //   1934: iload 126
    //   1936: istore 132
    //   1938: iload 129
    //   1940: istore 126
    //   1942: goto -85 -> 1857
    //   1945: iload 129
    //   1947: istore 125
    //   1949: aload 5
    //   1951: astore 124
    //   1953: iload 125
    //   1955: iload 126
    //   1957: if_icmpgt -120 -> 1837
    //   1960: new 41	java/lang/String
    //   1963: dup
    //   1964: aload 124
    //   1966: invokespecial 51	java/lang/String:<init>	([C)V
    //   1969: invokevirtual 55	java/lang/String:intern	()Ljava/lang/String;
    //   1972: astore 133
    //   1974: aload_1
    //   1975: iload 123
    //   1977: aload 133
    //   1979: aastore
    //   1980: bipush 12
    //   1982: istore 134
    //   1984: ldc 79
    //   1986: invokevirtual 47	java/lang/String:toCharArray	()[C
    //   1989: astore 135
    //   1991: aload 135
    //   1993: arraylength
    //   1994: istore 136
    //   1996: iload 136
    //   1998: iconst_1
    //   1999: if_icmpgt +17525 -> 19524
    //   2002: iconst_0
    //   2003: istore 137
    //   2005: aload 135
    //   2007: astore 5
    //   2009: iload 137
    //   2011: istore 6
    //   2013: iload 136
    //   2015: istore 138
    //   2017: aload 135
    //   2019: astore 139
    //   2021: iload 138
    //   2023: istore 140
    //   2025: aload 139
    //   2027: iload 137
    //   2029: caload
    //   2030: istore 31
    //   2032: iload 6
    //   2034: iconst_5
    //   2035: irem
    //   2036: tableswitch	default:+32 -> 2068, 0:+14832->16868, 1:+14839->16875, 2:+14846->16882, 3:+14853->16889
    //   2069: dup_x1
    //   2070: istore 141
    //   2072: iload 141
    //   2074: iload 31
    //   2076: ixor
    //   2077: i2c
    //   2078: istore 142
    //   2080: aload 139
    //   2082: iload 137
    //   2084: iload 142
    //   2086: castore
    //   2087: iload 6
    //   2089: iconst_1
    //   2090: iadd
    //   2091: istore 137
    //   2093: iload 140
    //   2095: ifne +18 -> 2113
    //   2098: aload 5
    //   2100: astore 139
    //   2102: iload 137
    //   2104: istore 143
    //   2106: iload 140
    //   2108: istore 137
    //   2110: goto -85 -> 2025
    //   2113: iload 140
    //   2115: istore 136
    //   2117: aload 5
    //   2119: astore 135
    //   2121: iload 136
    //   2123: iload 137
    //   2125: if_icmpgt -120 -> 2005
    //   2128: new 41	java/lang/String
    //   2131: dup
    //   2132: aload 135
    //   2134: invokespecial 51	java/lang/String:<init>	([C)V
    //   2137: invokevirtual 55	java/lang/String:intern	()Ljava/lang/String;
    //   2140: astore 144
    //   2142: aload_1
    //   2143: iload 134
    //   2145: aload 144
    //   2147: aastore
    //   2148: bipush 13
    //   2150: istore 145
    //   2152: ldc 81
    //   2154: invokevirtual 47	java/lang/String:toCharArray	()[C
    //   2157: astore 146
    //   2159: aload 146
    //   2161: arraylength
    //   2162: istore 147
    //   2164: iload 147
    //   2166: iconst_1
    //   2167: if_icmpgt +17351 -> 19518
    //   2170: iconst_0
    //   2171: istore 148
    //   2173: aload 146
    //   2175: astore 5
    //   2177: iload 148
    //   2179: istore 6
    //   2181: iload 147
    //   2183: istore 149
    //   2185: aload 146
    //   2187: astore 150
    //   2189: iload 149
    //   2191: istore 151
    //   2193: aload 150
    //   2195: iload 148
    //   2197: caload
    //   2198: istore 31
    //   2200: iload 6
    //   2202: iconst_5
    //   2203: irem
    //   2204: tableswitch	default:+32 -> 2236, 0:+14692->16896, 1:+14699->16903, 2:+14706->16910, 3:+14713->16917
    //   2237: dup_x1
    //   2238: istore 152
    //   2240: iload 152
    //   2242: iload 31
    //   2244: ixor
    //   2245: i2c
    //   2246: istore 153
    //   2248: aload 150
    //   2250: iload 148
    //   2252: iload 153
    //   2254: castore
    //   2255: iload 6
    //   2257: iconst_1
    //   2258: iadd
    //   2259: istore 148
    //   2261: iload 151
    //   2263: ifne +18 -> 2281
    //   2266: aload 5
    //   2268: astore 150
    //   2270: iload 148
    //   2272: istore 154
    //   2274: iload 151
    //   2276: istore 148
    //   2278: goto -85 -> 2193
    //   2281: iload 151
    //   2283: istore 147
    //   2285: aload 5
    //   2287: astore 146
    //   2289: iload 147
    //   2291: iload 148
    //   2293: if_icmpgt -120 -> 2173
    //   2296: new 41	java/lang/String
    //   2299: dup
    //   2300: aload 146
    //   2302: invokespecial 51	java/lang/String:<init>	([C)V
    //   2305: invokevirtual 55	java/lang/String:intern	()Ljava/lang/String;
    //   2308: astore 155
    //   2310: aload_1
    //   2311: iload 145
    //   2313: aload 155
    //   2315: aastore
    //   2316: bipush 14
    //   2318: istore 156
    //   2320: ldc 83
    //   2322: invokevirtual 47	java/lang/String:toCharArray	()[C
    //   2325: astore 157
    //   2327: aload 157
    //   2329: arraylength
    //   2330: istore 158
    //   2332: iload 158
    //   2334: iconst_1
    //   2335: if_icmpgt +17177 -> 19512
    //   2338: iconst_0
    //   2339: istore 159
    //   2341: aload 157
    //   2343: astore 5
    //   2345: iload 159
    //   2347: istore 6
    //   2349: iload 158
    //   2351: istore 160
    //   2353: aload 157
    //   2355: astore 161
    //   2357: iload 160
    //   2359: istore 162
    //   2361: aload 161
    //   2363: iload 159
    //   2365: caload
    //   2366: istore 31
    //   2368: iload 6
    //   2370: iconst_5
    //   2371: irem
    //   2372: tableswitch	default:+32 -> 2404, 0:+14552->16924, 1:+14559->16931, 2:+14566->16938, 3:+14573->16945
    //   2405: dup_x1
    //   2406: istore 163
    //   2408: iload 163
    //   2410: iload 31
    //   2412: ixor
    //   2413: i2c
    //   2414: istore 164
    //   2416: aload 161
    //   2418: iload 159
    //   2420: iload 164
    //   2422: castore
    //   2423: iload 6
    //   2425: iconst_1
    //   2426: iadd
    //   2427: istore 159
    //   2429: iload 162
    //   2431: ifne +18 -> 2449
    //   2434: aload 5
    //   2436: astore 161
    //   2438: iload 159
    //   2440: istore 165
    //   2442: iload 162
    //   2444: istore 159
    //   2446: goto -85 -> 2361
    //   2449: iload 162
    //   2451: istore 158
    //   2453: aload 5
    //   2455: astore 157
    //   2457: iload 158
    //   2459: iload 159
    //   2461: if_icmpgt -120 -> 2341
    //   2464: new 41	java/lang/String
    //   2467: dup
    //   2468: aload 157
    //   2470: invokespecial 51	java/lang/String:<init>	([C)V
    //   2473: invokevirtual 55	java/lang/String:intern	()Ljava/lang/String;
    //   2476: astore 166
    //   2478: aload_1
    //   2479: iload 156
    //   2481: aload 166
    //   2483: aastore
    //   2484: bipush 15
    //   2486: istore 167
    //   2488: ldc 85
    //   2490: invokevirtual 47	java/lang/String:toCharArray	()[C
    //   2493: astore 168
    //   2495: aload 168
    //   2497: arraylength
    //   2498: istore 169
    //   2500: iload 169
    //   2502: iconst_1
    //   2503: if_icmpgt +17003 -> 19506
    //   2506: iconst_0
    //   2507: istore 170
    //   2509: aload 168
    //   2511: astore 5
    //   2513: iload 170
    //   2515: istore 6
    //   2517: iload 169
    //   2519: istore 171
    //   2521: aload 168
    //   2523: astore 172
    //   2525: iload 171
    //   2527: istore 173
    //   2529: aload 172
    //   2531: iload 170
    //   2533: caload
    //   2534: istore 31
    //   2536: iload 6
    //   2538: iconst_5
    //   2539: irem
    //   2540: tableswitch	default:+32 -> 2572, 0:+14412->16952, 1:+14419->16959, 2:+14426->16966, 3:+14433->16973
    //   2573: dup_x1
    //   2574: istore 174
    //   2576: iload 174
    //   2578: iload 31
    //   2580: ixor
    //   2581: i2c
    //   2582: istore 175
    //   2584: aload 172
    //   2586: iload 170
    //   2588: iload 175
    //   2590: castore
    //   2591: iload 6
    //   2593: iconst_1
    //   2594: iadd
    //   2595: istore 170
    //   2597: iload 173
    //   2599: ifne +18 -> 2617
    //   2602: aload 5
    //   2604: astore 172
    //   2606: iload 170
    //   2608: istore 176
    //   2610: iload 173
    //   2612: istore 170
    //   2614: goto -85 -> 2529
    //   2617: iload 173
    //   2619: istore 169
    //   2621: aload 5
    //   2623: astore 168
    //   2625: iload 169
    //   2627: iload 170
    //   2629: if_icmpgt -120 -> 2509
    //   2632: new 41	java/lang/String
    //   2635: dup
    //   2636: aload 168
    //   2638: invokespecial 51	java/lang/String:<init>	([C)V
    //   2641: invokevirtual 55	java/lang/String:intern	()Ljava/lang/String;
    //   2644: astore 177
    //   2646: aload_1
    //   2647: iload 167
    //   2649: aload 177
    //   2651: aastore
    //   2652: bipush 16
    //   2654: istore 178
    //   2656: ldc 87
    //   2658: invokevirtual 47	java/lang/String:toCharArray	()[C
    //   2661: astore 179
    //   2663: aload 179
    //   2665: arraylength
    //   2666: istore 180
    //   2668: iload 180
    //   2670: iconst_1
    //   2671: if_icmpgt +16829 -> 19500
    //   2674: iconst_0
    //   2675: istore 181
    //   2677: aload 179
    //   2679: astore 5
    //   2681: iload 181
    //   2683: istore 6
    //   2685: iload 180
    //   2687: istore 182
    //   2689: aload 179
    //   2691: astore 183
    //   2693: iload 182
    //   2695: istore 184
    //   2697: aload 183
    //   2699: iload 181
    //   2701: caload
    //   2702: istore 31
    //   2704: iload 6
    //   2706: iconst_5
    //   2707: irem
    //   2708: tableswitch	default:+32 -> 2740, 0:+14272->16980, 1:+14279->16987, 2:+14286->16994, 3:+14293->17001
    //   2741: dup_x1
    //   2742: istore 185
    //   2744: iload 185
    //   2746: iload 31
    //   2748: ixor
    //   2749: i2c
    //   2750: istore 186
    //   2752: aload 183
    //   2754: iload 181
    //   2756: iload 186
    //   2758: castore
    //   2759: iload 6
    //   2761: iconst_1
    //   2762: iadd
    //   2763: istore 181
    //   2765: iload 184
    //   2767: ifne +18 -> 2785
    //   2770: aload 5
    //   2772: astore 183
    //   2774: iload 181
    //   2776: istore 187
    //   2778: iload 184
    //   2780: istore 181
    //   2782: goto -85 -> 2697
    //   2785: iload 184
    //   2787: istore 180
    //   2789: aload 5
    //   2791: astore 179
    //   2793: iload 180
    //   2795: iload 181
    //   2797: if_icmpgt -120 -> 2677
    //   2800: new 41	java/lang/String
    //   2803: dup
    //   2804: aload 179
    //   2806: invokespecial 51	java/lang/String:<init>	([C)V
    //   2809: invokevirtual 55	java/lang/String:intern	()Ljava/lang/String;
    //   2812: astore 188
    //   2814: aload_1
    //   2815: iload 178
    //   2817: aload 188
    //   2819: aastore
    //   2820: bipush 17
    //   2822: istore 189
    //   2824: ldc 89
    //   2826: invokevirtual 47	java/lang/String:toCharArray	()[C
    //   2829: astore 190
    //   2831: aload 190
    //   2833: arraylength
    //   2834: istore 191
    //   2836: iload 191
    //   2838: iconst_1
    //   2839: if_icmpgt +16655 -> 19494
    //   2842: iconst_0
    //   2843: istore 192
    //   2845: aload 190
    //   2847: astore 5
    //   2849: iload 192
    //   2851: istore 6
    //   2853: iload 191
    //   2855: istore 193
    //   2857: aload 190
    //   2859: astore 194
    //   2861: iload 193
    //   2863: istore 195
    //   2865: aload 194
    //   2867: iload 192
    //   2869: caload
    //   2870: istore 31
    //   2872: iload 6
    //   2874: iconst_5
    //   2875: irem
    //   2876: tableswitch	default:+32 -> 2908, 0:+14132->17008, 1:+14139->17015, 2:+14146->17022, 3:+14153->17029
    //   2909: dup_x1
    //   2910: istore 196
    //   2912: iload 196
    //   2914: iload 31
    //   2916: ixor
    //   2917: i2c
    //   2918: istore 197
    //   2920: aload 194
    //   2922: iload 192
    //   2924: iload 197
    //   2926: castore
    //   2927: iload 6
    //   2929: iconst_1
    //   2930: iadd
    //   2931: istore 192
    //   2933: iload 195
    //   2935: ifne +18 -> 2953
    //   2938: aload 5
    //   2940: astore 194
    //   2942: iload 192
    //   2944: istore 198
    //   2946: iload 195
    //   2948: istore 192
    //   2950: goto -85 -> 2865
    //   2953: iload 195
    //   2955: istore 191
    //   2957: aload 5
    //   2959: astore 190
    //   2961: iload 191
    //   2963: iload 192
    //   2965: if_icmpgt -120 -> 2845
    //   2968: new 41	java/lang/String
    //   2971: dup
    //   2972: aload 190
    //   2974: invokespecial 51	java/lang/String:<init>	([C)V
    //   2977: invokevirtual 55	java/lang/String:intern	()Ljava/lang/String;
    //   2980: astore 199
    //   2982: aload_1
    //   2983: iload 189
    //   2985: aload 199
    //   2987: aastore
    //   2988: bipush 18
    //   2990: istore 200
    //   2992: ldc 91
    //   2994: invokevirtual 47	java/lang/String:toCharArray	()[C
    //   2997: astore 201
    //   2999: aload 201
    //   3001: arraylength
    //   3002: istore 202
    //   3004: iload 202
    //   3006: iconst_1
    //   3007: if_icmpgt +16481 -> 19488
    //   3010: iconst_0
    //   3011: istore 203
    //   3013: aload 201
    //   3015: astore 5
    //   3017: iload 203
    //   3019: istore 6
    //   3021: iload 202
    //   3023: istore 204
    //   3025: aload 201
    //   3027: astore 205
    //   3029: iload 204
    //   3031: istore 206
    //   3033: aload 205
    //   3035: iload 203
    //   3037: caload
    //   3038: istore 31
    //   3040: iload 6
    //   3042: iconst_5
    //   3043: irem
    //   3044: tableswitch	default:+32 -> 3076, 0:+13992->17036, 1:+13999->17043, 2:+14006->17050, 3:+14013->17057
    //   3077: dup_x1
    //   3078: istore 207
    //   3080: iload 207
    //   3082: iload 31
    //   3084: ixor
    //   3085: i2c
    //   3086: istore 208
    //   3088: aload 205
    //   3090: iload 203
    //   3092: iload 208
    //   3094: castore
    //   3095: iload 6
    //   3097: iconst_1
    //   3098: iadd
    //   3099: istore 203
    //   3101: iload 206
    //   3103: ifne +18 -> 3121
    //   3106: aload 5
    //   3108: astore 205
    //   3110: iload 203
    //   3112: istore 209
    //   3114: iload 206
    //   3116: istore 203
    //   3118: goto -85 -> 3033
    //   3121: iload 206
    //   3123: istore 202
    //   3125: aload 5
    //   3127: astore 201
    //   3129: iload 202
    //   3131: iload 203
    //   3133: if_icmpgt -120 -> 3013
    //   3136: new 41	java/lang/String
    //   3139: dup
    //   3140: aload 201
    //   3142: invokespecial 51	java/lang/String:<init>	([C)V
    //   3145: invokevirtual 55	java/lang/String:intern	()Ljava/lang/String;
    //   3148: astore 210
    //   3150: aload_1
    //   3151: iload 200
    //   3153: aload 210
    //   3155: aastore
    //   3156: bipush 19
    //   3158: istore 211
    //   3160: ldc 93
    //   3162: invokevirtual 47	java/lang/String:toCharArray	()[C
    //   3165: astore 212
    //   3167: aload 212
    //   3169: arraylength
    //   3170: istore 213
    //   3172: iload 213
    //   3174: iconst_1
    //   3175: if_icmpgt +16307 -> 19482
    //   3178: iconst_0
    //   3179: istore 214
    //   3181: aload 212
    //   3183: astore 5
    //   3185: iload 214
    //   3187: istore 6
    //   3189: iload 213
    //   3191: istore 215
    //   3193: aload 212
    //   3195: astore 216
    //   3197: iload 215
    //   3199: istore 217
    //   3201: aload 216
    //   3203: iload 214
    //   3205: caload
    //   3206: istore 31
    //   3208: iload 6
    //   3210: iconst_5
    //   3211: irem
    //   3212: tableswitch	default:+32 -> 3244, 0:+13852->17064, 1:+13859->17071, 2:+13866->17078, 3:+13873->17085
    //   3245: dup_x1
    //   3246: istore 218
    //   3248: iload 218
    //   3250: iload 31
    //   3252: ixor
    //   3253: i2c
    //   3254: istore 219
    //   3256: aload 216
    //   3258: iload 214
    //   3260: iload 219
    //   3262: castore
    //   3263: iload 6
    //   3265: iconst_1
    //   3266: iadd
    //   3267: istore 214
    //   3269: iload 217
    //   3271: ifne +18 -> 3289
    //   3274: aload 5
    //   3276: astore 216
    //   3278: iload 214
    //   3280: istore 220
    //   3282: iload 217
    //   3284: istore 214
    //   3286: goto -85 -> 3201
    //   3289: iload 217
    //   3291: istore 213
    //   3293: aload 5
    //   3295: astore 212
    //   3297: iload 213
    //   3299: iload 214
    //   3301: if_icmpgt -120 -> 3181
    //   3304: new 41	java/lang/String
    //   3307: dup
    //   3308: aload 212
    //   3310: invokespecial 51	java/lang/String:<init>	([C)V
    //   3313: invokevirtual 55	java/lang/String:intern	()Ljava/lang/String;
    //   3316: astore 221
    //   3318: aload_1
    //   3319: iload 211
    //   3321: aload 221
    //   3323: aastore
    //   3324: bipush 20
    //   3326: istore 222
    //   3328: ldc 95
    //   3330: invokevirtual 47	java/lang/String:toCharArray	()[C
    //   3333: astore 223
    //   3335: aload 223
    //   3337: arraylength
    //   3338: istore 224
    //   3340: iload 224
    //   3342: iconst_1
    //   3343: if_icmpgt +16133 -> 19476
    //   3346: iconst_0
    //   3347: istore 225
    //   3349: aload 223
    //   3351: astore 5
    //   3353: iload 225
    //   3355: istore 6
    //   3357: iload 224
    //   3359: istore 226
    //   3361: aload 223
    //   3363: astore 227
    //   3365: iload 226
    //   3367: istore 228
    //   3369: aload 227
    //   3371: iload 225
    //   3373: caload
    //   3374: istore 31
    //   3376: iload 6
    //   3378: iconst_5
    //   3379: irem
    //   3380: tableswitch	default:+32 -> 3412, 0:+13712->17092, 1:+13719->17099, 2:+13726->17106, 3:+13733->17113
    //   3413: dup_x1
    //   3414: istore 229
    //   3416: iload 229
    //   3418: iload 31
    //   3420: ixor
    //   3421: i2c
    //   3422: istore 230
    //   3424: aload 227
    //   3426: iload 225
    //   3428: iload 230
    //   3430: castore
    //   3431: iload 6
    //   3433: iconst_1
    //   3434: iadd
    //   3435: istore 225
    //   3437: iload 228
    //   3439: ifne +18 -> 3457
    //   3442: aload 5
    //   3444: astore 227
    //   3446: iload 225
    //   3448: istore 231
    //   3450: iload 228
    //   3452: istore 225
    //   3454: goto -85 -> 3369
    //   3457: iload 228
    //   3459: istore 224
    //   3461: aload 5
    //   3463: astore 223
    //   3465: iload 224
    //   3467: iload 225
    //   3469: if_icmpgt -120 -> 3349
    //   3472: new 41	java/lang/String
    //   3475: dup
    //   3476: aload 223
    //   3478: invokespecial 51	java/lang/String:<init>	([C)V
    //   3481: invokevirtual 55	java/lang/String:intern	()Ljava/lang/String;
    //   3484: astore 232
    //   3486: aload_1
    //   3487: iload 222
    //   3489: aload 232
    //   3491: aastore
    //   3492: bipush 21
    //   3494: istore 233
    //   3496: ldc 97
    //   3498: invokevirtual 47	java/lang/String:toCharArray	()[C
    //   3501: astore 234
    //   3503: aload 234
    //   3505: arraylength
    //   3506: istore 235
    //   3508: iload 235
    //   3510: iconst_1
    //   3511: if_icmpgt +15959 -> 19470
    //   3514: iconst_0
    //   3515: istore 236
    //   3517: aload 234
    //   3519: astore 5
    //   3521: iload 236
    //   3523: istore 6
    //   3525: iload 235
    //   3527: istore 237
    //   3529: aload 234
    //   3531: astore 238
    //   3533: iload 237
    //   3535: istore 239
    //   3537: aload 238
    //   3539: iload 236
    //   3541: caload
    //   3542: istore 31
    //   3544: iload 6
    //   3546: iconst_5
    //   3547: irem
    //   3548: tableswitch	default:+32 -> 3580, 0:+13572->17120, 1:+13579->17127, 2:+13586->17134, 3:+13593->17141
    //   3581: dup_x1
    //   3582: istore 240
    //   3584: iload 240
    //   3586: iload 31
    //   3588: ixor
    //   3589: i2c
    //   3590: istore 241
    //   3592: aload 238
    //   3594: iload 236
    //   3596: iload 241
    //   3598: castore
    //   3599: iload 6
    //   3601: iconst_1
    //   3602: iadd
    //   3603: istore 236
    //   3605: iload 239
    //   3607: ifne +18 -> 3625
    //   3610: aload 5
    //   3612: astore 238
    //   3614: iload 236
    //   3616: istore 242
    //   3618: iload 239
    //   3620: istore 236
    //   3622: goto -85 -> 3537
    //   3625: iload 239
    //   3627: istore 235
    //   3629: aload 5
    //   3631: astore 234
    //   3633: iload 235
    //   3635: iload 236
    //   3637: if_icmpgt -120 -> 3517
    //   3640: new 41	java/lang/String
    //   3643: dup
    //   3644: aload 234
    //   3646: invokespecial 51	java/lang/String:<init>	([C)V
    //   3649: invokevirtual 55	java/lang/String:intern	()Ljava/lang/String;
    //   3652: astore 243
    //   3654: aload_1
    //   3655: iload 233
    //   3657: aload 243
    //   3659: aastore
    //   3660: bipush 22
    //   3662: istore 244
    //   3664: ldc 99
    //   3666: invokevirtual 47	java/lang/String:toCharArray	()[C
    //   3669: astore 245
    //   3671: aload 245
    //   3673: arraylength
    //   3674: istore 246
    //   3676: iload 246
    //   3678: iconst_1
    //   3679: if_icmpgt +15785 -> 19464
    //   3682: iconst_0
    //   3683: istore 247
    //   3685: aload 245
    //   3687: astore 5
    //   3689: iload 247
    //   3691: istore 6
    //   3693: iload 246
    //   3695: istore 248
    //   3697: aload 245
    //   3699: astore 249
    //   3701: iload 248
    //   3703: istore 250
    //   3705: aload 249
    //   3707: iload 247
    //   3709: caload
    //   3710: istore 31
    //   3712: iload 6
    //   3714: iconst_5
    //   3715: irem
    //   3716: tableswitch	default:+32 -> 3748, 0:+13432->17148, 1:+13439->17155, 2:+13446->17162, 3:+13453->17169
    //   3749: dup_x1
    //   3750: istore 251
    //   3752: iload 251
    //   3754: iload 31
    //   3756: ixor
    //   3757: i2c
    //   3758: istore 252
    //   3760: aload 249
    //   3762: iload 247
    //   3764: iload 252
    //   3766: castore
    //   3767: iload 6
    //   3769: iconst_1
    //   3770: iadd
    //   3771: istore 247
    //   3773: iload 250
    //   3775: ifne +18 -> 3793
    //   3778: aload 5
    //   3780: astore 249
    //   3782: iload 247
    //   3784: istore 253
    //   3786: iload 250
    //   3788: istore 247
    //   3790: goto -85 -> 3705
    //   3793: iload 250
    //   3795: istore 246
    //   3797: aload 5
    //   3799: astore 245
    //   3801: iload 246
    //   3803: iload 247
    //   3805: if_icmpgt -120 -> 3685
    //   3808: new 41	java/lang/String
    //   3811: dup
    //   3812: aload 245
    //   3814: invokespecial 51	java/lang/String:<init>	([C)V
    //   3817: invokevirtual 55	java/lang/String:intern	()Ljava/lang/String;
    //   3820: astore 254
    //   3822: aload_1
    //   3823: iload 244
    //   3825: aload 254
    //   3827: aastore
    //   3828: bipush 23
    //   3830: istore 255
    //   3832: ldc 101
    //   3834: invokevirtual 47	java/lang/String:toCharArray	()[C
    //   3837: wide
    //   3841: wide
    //   3845: arraylength
    //   3846: wide
    //   3850: wide
    //   3854: iconst_1
    //   3855: if_icmpgt +15601 -> 19456
    //   3858: iconst_0
    //   3859: wide
    //   3863: wide
    //   3867: astore 5
    //   3869: wide
    //   3873: istore 6
    //   3875: wide
    //   3879: wide
    //   3883: wide
    //   3887: wide
    //   3891: wide
    //   3895: wide
    //   3899: wide
    //   3903: wide
    //   3907: caload
    //   3908: istore 31
    //   3910: iload 6
    //   3912: iconst_5
    //   3913: irem
    //   3914: tableswitch	default:+30 -> 3944, 0:+13262->17176, 1:+13271->17185, 2:+13280->17194, 3:+13289->17203
    //   3945: dup_x1
    //   3946: wide
    //   3950: wide
    //   3954: iload 31
    //   3956: ixor
    //   3957: i2c
    //   3958: wide
    //   3962: wide
    //   3966: wide
    //   3970: wide
    //   3974: castore
    //   3975: iload 6
    //   3977: iconst_1
    //   3978: iadd
    //   3979: wide
    //   3983: wide
    //   3987: ifne +28 -> 4015
    //   3990: aload 5
    //   3992: wide
    //   3996: wide
    //   4000: wide
    //   4004: wide
    //   4008: wide
    //   4012: goto -113 -> 3899
    //   4015: wide
    //   4019: wide
    //   4023: aload 5
    //   4025: wide
    //   4029: wide
    //   4033: wide
    //   4037: if_icmpgt -174 -> 3863
    //   4040: new 41	java/lang/String
    //   4043: dup
    //   4044: wide
    //   4048: invokespecial 51	java/lang/String:<init>	([C)V
    //   4051: invokevirtual 55	java/lang/String:intern	()Ljava/lang/String;
    //   4054: wide
    //   4058: aload_1
    //   4059: iload 255
    //   4061: wide
    //   4065: aastore
    //   4066: bipush 24
    //   4068: wide
    //   4072: ldc 103
    //   4074: invokevirtual 47	java/lang/String:toCharArray	()[C
    //   4077: wide
    //   4081: wide
    //   4085: arraylength
    //   4086: wide
    //   4090: wide
    //   4094: iconst_1
    //   4095: if_icmpgt +15353 -> 19448
    //   4098: iconst_0
    //   4099: wide
    //   4103: wide
    //   4107: astore 5
    //   4109: wide
    //   4113: istore 6
    //   4115: wide
    //   4119: wide
    //   4123: wide
    //   4127: wide
    //   4131: wide
    //   4135: wide
    //   4139: wide
    //   4143: wide
    //   4147: caload
    //   4148: istore 31
    //   4150: iload 6
    //   4152: iconst_5
    //   4153: irem
    //   4154: tableswitch	default:+30 -> 4184, 0:+13058->17212, 1:+13067->17221, 2:+13076->17230, 3:+13085->17239
    //   4185: dup_x1
    //   4186: wide
    //   4190: wide
    //   4194: iload 31
    //   4196: ixor
    //   4197: i2c
    //   4198: wide
    //   4202: wide
    //   4206: wide
    //   4210: wide
    //   4214: castore
    //   4215: iload 6
    //   4217: iconst_1
    //   4218: iadd
    //   4219: wide
    //   4223: wide
    //   4227: ifne +28 -> 4255
    //   4230: aload 5
    //   4232: wide
    //   4236: wide
    //   4240: wide
    //   4244: wide
    //   4248: wide
    //   4252: goto -113 -> 4139
    //   4255: wide
    //   4259: wide
    //   4263: aload 5
    //   4265: wide
    //   4269: wide
    //   4273: wide
    //   4277: if_icmpgt -174 -> 4103
    //   4280: new 41	java/lang/String
    //   4283: dup
    //   4284: wide
    //   4288: invokespecial 51	java/lang/String:<init>	([C)V
    //   4291: invokevirtual 55	java/lang/String:intern	()Ljava/lang/String;
    //   4294: wide
    //   4298: aload_1
    //   4299: wide
    //   4303: wide
    //   4307: aastore
    //   4308: bipush 25
    //   4310: wide
    //   4314: ldc 105
    //   4316: invokevirtual 47	java/lang/String:toCharArray	()[C
    //   4319: wide
    //   4323: wide
    //   4327: arraylength
    //   4328: wide
    //   4332: wide
    //   4336: iconst_1
    //   4337: if_icmpgt +15103 -> 19440
    //   4340: iconst_0
    //   4341: wide
    //   4345: wide
    //   4349: astore 5
    //   4351: wide
    //   4355: istore 6
    //   4357: wide
    //   4361: wide
    //   4365: wide
    //   4369: wide
    //   4373: wide
    //   4377: wide
    //   4381: wide
    //   4385: wide
    //   4389: caload
    //   4390: istore 31
    //   4392: iload 6
    //   4394: iconst_5
    //   4395: irem
    //   4396: tableswitch	default:+32 -> 4428, 0:+12852->17248, 1:+12861->17257, 2:+12870->17266, 3:+12879->17275
    //   4429: dup_x1
    //   4430: wide
    //   4434: wide
    //   4438: iload 31
    //   4440: ixor
    //   4441: i2c
    //   4442: wide
    //   4446: wide
    //   4450: wide
    //   4454: wide
    //   4458: castore
    //   4459: iload 6
    //   4461: iconst_1
    //   4462: iadd
    //   4463: wide
    //   4467: wide
    //   4471: ifne +28 -> 4499
    //   4474: aload 5
    //   4476: wide
    //   4480: wide
    //   4484: wide
    //   4488: wide
    //   4492: wide
    //   4496: goto -115 -> 4381
    //   4499: wide
    //   4503: wide
    //   4507: aload 5
    //   4509: wide
    //   4513: wide
    //   4517: wide
    //   4521: if_icmpgt -176 -> 4345
    //   4524: new 41	java/lang/String
    //   4527: dup
    //   4528: wide
    //   4532: invokespecial 51	java/lang/String:<init>	([C)V
    //   4535: invokevirtual 55	java/lang/String:intern	()Ljava/lang/String;
    //   4538: wide
    //   4542: aload_1
    //   4543: wide
    //   4547: wide
    //   4551: aastore
    //   4552: bipush 26
    //   4554: wide
    //   4558: ldc 107
    //   4560: invokevirtual 47	java/lang/String:toCharArray	()[C
    //   4563: wide
    //   4567: wide
    //   4571: arraylength
    //   4572: wide
    //   4576: wide
    //   4580: iconst_1
    //   4581: if_icmpgt +14851 -> 19432
    //   4584: iconst_0
    //   4585: wide
    //   4589: wide
    //   4593: astore 5
    //   4595: wide
    //   4599: istore 6
    //   4601: wide
    //   4605: wide
    //   4609: wide
    //   4613: wide
    //   4617: wide
    //   4621: wide
    //   4625: wide
    //   4629: wide
    //   4633: caload
    //   4634: istore 31
    //   4636: iload 6
    //   4638: iconst_5
    //   4639: irem
    //   4640: tableswitch	default:+32 -> 4672, 0:+12644->17284, 1:+12653->17293, 2:+12662->17302, 3:+12671->17311
    //   4673: dup_x1
    //   4674: wide
    //   4678: wide
    //   4682: iload 31
    //   4684: ixor
    //   4685: i2c
    //   4686: wide
    //   4690: wide
    //   4694: wide
    //   4698: wide
    //   4702: castore
    //   4703: iload 6
    //   4705: iconst_1
    //   4706: iadd
    //   4707: wide
    //   4711: wide
    //   4715: ifne +28 -> 4743
    //   4718: aload 5
    //   4720: wide
    //   4724: wide
    //   4728: wide
    //   4732: wide
    //   4736: wide
    //   4740: goto -115 -> 4625
    //   4743: wide
    //   4747: wide
    //   4751: aload 5
    //   4753: wide
    //   4757: wide
    //   4761: wide
    //   4765: if_icmpgt -176 -> 4589
    //   4768: new 41	java/lang/String
    //   4771: dup
    //   4772: wide
    //   4776: invokespecial 51	java/lang/String:<init>	([C)V
    //   4779: invokevirtual 55	java/lang/String:intern	()Ljava/lang/String;
    //   4782: wide
    //   4786: aload_1
    //   4787: wide
    //   4791: wide
    //   4795: aastore
    //   4796: bipush 27
    //   4798: wide
    //   4802: ldc 109
    //   4804: invokevirtual 47	java/lang/String:toCharArray	()[C
    //   4807: wide
    //   4811: wide
    //   4815: arraylength
    //   4816: wide
    //   4820: wide
    //   4824: iconst_1
    //   4825: if_icmpgt +14599 -> 19424
    //   4828: iconst_0
    //   4829: wide
    //   4833: wide
    //   4837: astore 5
    //   4839: wide
    //   4843: istore 6
    //   4845: wide
    //   4849: wide
    //   4853: wide
    //   4857: wide
    //   4861: wide
    //   4865: wide
    //   4869: wide
    //   4873: wide
    //   4877: caload
    //   4878: istore 31
    //   4880: iload 6
    //   4882: iconst_5
    //   4883: irem
    //   4884: tableswitch	default:+32 -> 4916, 0:+12436->17320, 1:+12445->17329, 2:+12454->17338, 3:+12463->17347
    //   4917: dup_x1
    //   4918: wide
    //   4922: wide
    //   4926: iload 31
    //   4928: ixor
    //   4929: i2c
    //   4930: wide
    //   4934: wide
    //   4938: wide
    //   4942: wide
    //   4946: castore
    //   4947: iload 6
    //   4949: iconst_1
    //   4950: iadd
    //   4951: wide
    //   4955: wide
    //   4959: ifne +28 -> 4987
    //   4962: aload 5
    //   4964: wide
    //   4968: wide
    //   4972: wide
    //   4976: wide
    //   4980: wide
    //   4984: goto -115 -> 4869
    //   4987: wide
    //   4991: wide
    //   4995: aload 5
    //   4997: wide
    //   5001: wide
    //   5005: wide
    //   5009: if_icmpgt -176 -> 4833
    //   5012: new 41	java/lang/String
    //   5015: dup
    //   5016: wide
    //   5020: invokespecial 51	java/lang/String:<init>	([C)V
    //   5023: invokevirtual 55	java/lang/String:intern	()Ljava/lang/String;
    //   5026: wide
    //   5030: aload_1
    //   5031: wide
    //   5035: wide
    //   5039: aastore
    //   5040: bipush 28
    //   5042: wide
    //   5046: ldc 111
    //   5048: invokevirtual 47	java/lang/String:toCharArray	()[C
    //   5051: wide
    //   5055: wide
    //   5059: arraylength
    //   5060: wide
    //   5064: wide
    //   5068: iconst_1
    //   5069: if_icmpgt +14347 -> 19416
    //   5072: iconst_0
    //   5073: wide
    //   5077: wide
    //   5081: astore 5
    //   5083: wide
    //   5087: istore 6
    //   5089: wide
    //   5093: wide
    //   5097: wide
    //   5101: wide
    //   5105: wide
    //   5109: wide
    //   5113: wide
    //   5117: wide
    //   5121: caload
    //   5122: istore 31
    //   5124: iload 6
    //   5126: iconst_5
    //   5127: irem
    //   5128: tableswitch	default:+32 -> 5160, 0:+12228->17356, 1:+12237->17365, 2:+12246->17374, 3:+12255->17383
    //   5161: dup_x1
    //   5162: wide
    //   5166: wide
    //   5170: iload 31
    //   5172: ixor
    //   5173: i2c
    //   5174: wide
    //   5178: wide
    //   5182: wide
    //   5186: wide
    //   5190: castore
    //   5191: iload 6
    //   5193: iconst_1
    //   5194: iadd
    //   5195: wide
    //   5199: wide
    //   5203: ifne +28 -> 5231
    //   5206: aload 5
    //   5208: wide
    //   5212: wide
    //   5216: wide
    //   5220: wide
    //   5224: wide
    //   5228: goto -115 -> 5113
    //   5231: wide
    //   5235: wide
    //   5239: aload 5
    //   5241: wide
    //   5245: wide
    //   5249: wide
    //   5253: if_icmpgt -176 -> 5077
    //   5256: new 41	java/lang/String
    //   5259: dup
    //   5260: wide
    //   5264: invokespecial 51	java/lang/String:<init>	([C)V
    //   5267: invokevirtual 55	java/lang/String:intern	()Ljava/lang/String;
    //   5270: wide
    //   5274: aload_1
    //   5275: wide
    //   5279: wide
    //   5283: aastore
    //   5284: bipush 29
    //   5286: wide
    //   5290: ldc 113
    //   5292: invokevirtual 47	java/lang/String:toCharArray	()[C
    //   5295: wide
    //   5299: wide
    //   5303: arraylength
    //   5304: wide
    //   5308: wide
    //   5312: iconst_1
    //   5313: if_icmpgt +14095 -> 19408
    //   5316: iconst_0
    //   5317: wide
    //   5321: wide
    //   5325: astore 5
    //   5327: wide
    //   5331: istore 6
    //   5333: wide
    //   5337: wide
    //   5341: wide
    //   5345: wide
    //   5349: wide
    //   5353: wide
    //   5357: wide
    //   5361: wide
    //   5365: caload
    //   5366: istore 31
    //   5368: iload 6
    //   5370: iconst_5
    //   5371: irem
    //   5372: tableswitch	default:+32 -> 5404, 0:+12020->17392, 1:+12029->17401, 2:+12038->17410, 3:+12047->17419
    //   5405: dup_x1
    //   5406: wide
    //   5410: wide
    //   5414: iload 31
    //   5416: ixor
    //   5417: i2c
    //   5418: wide
    //   5422: wide
    //   5426: wide
    //   5430: wide
    //   5434: castore
    //   5435: iload 6
    //   5437: iconst_1
    //   5438: iadd
    //   5439: wide
    //   5443: wide
    //   5447: ifne +28 -> 5475
    //   5450: aload 5
    //   5452: wide
    //   5456: wide
    //   5460: wide
    //   5464: wide
    //   5468: wide
    //   5472: goto -115 -> 5357
    //   5475: wide
    //   5479: wide
    //   5483: aload 5
    //   5485: wide
    //   5489: wide
    //   5493: wide
    //   5497: if_icmpgt -176 -> 5321
    //   5500: new 41	java/lang/String
    //   5503: dup
    //   5504: wide
    //   5508: invokespecial 51	java/lang/String:<init>	([C)V
    //   5511: invokevirtual 55	java/lang/String:intern	()Ljava/lang/String;
    //   5514: wide
    //   5518: aload_1
    //   5519: wide
    //   5523: wide
    //   5527: aastore
    //   5528: bipush 30
    //   5530: wide
    //   5534: ldc 115
    //   5536: invokevirtual 47	java/lang/String:toCharArray	()[C
    //   5539: wide
    //   5543: wide
    //   5547: arraylength
    //   5548: wide
    //   5552: wide
    //   5556: iconst_1
    //   5557: if_icmpgt +13843 -> 19400
    //   5560: iconst_0
    //   5561: wide
    //   5565: wide
    //   5569: astore 5
    //   5571: wide
    //   5575: istore 6
    //   5577: wide
    //   5581: wide
    //   5585: wide
    //   5589: wide
    //   5593: wide
    //   5597: wide
    //   5601: wide
    //   5605: wide
    //   5609: caload
    //   5610: istore 31
    //   5612: iload 6
    //   5614: iconst_5
    //   5615: irem
    //   5616: tableswitch	default:+32 -> 5648, 0:+11812->17428, 1:+11821->17437, 2:+11830->17446, 3:+11839->17455
    //   5649: dup_x1
    //   5650: wide
    //   5654: wide
    //   5658: iload 31
    //   5660: ixor
    //   5661: i2c
    //   5662: wide
    //   5666: wide
    //   5670: wide
    //   5674: wide
    //   5678: castore
    //   5679: iload 6
    //   5681: iconst_1
    //   5682: iadd
    //   5683: wide
    //   5687: wide
    //   5691: ifne +28 -> 5719
    //   5694: aload 5
    //   5696: wide
    //   5700: wide
    //   5704: wide
    //   5708: wide
    //   5712: wide
    //   5716: goto -115 -> 5601
    //   5719: wide
    //   5723: wide
    //   5727: aload 5
    //   5729: wide
    //   5733: wide
    //   5737: wide
    //   5741: if_icmpgt -176 -> 5565
    //   5744: new 41	java/lang/String
    //   5747: dup
    //   5748: wide
    //   5752: invokespecial 51	java/lang/String:<init>	([C)V
    //   5755: invokevirtual 55	java/lang/String:intern	()Ljava/lang/String;
    //   5758: wide
    //   5762: aload_1
    //   5763: wide
    //   5767: wide
    //   5771: aastore
    //   5772: bipush 31
    //   5774: wide
    //   5778: ldc 117
    //   5780: invokevirtual 47	java/lang/String:toCharArray	()[C
    //   5783: wide
    //   5787: wide
    //   5791: arraylength
    //   5792: wide
    //   5796: wide
    //   5800: iconst_1
    //   5801: if_icmpgt +13591 -> 19392
    //   5804: iconst_0
    //   5805: wide
    //   5809: wide
    //   5813: astore 5
    //   5815: wide
    //   5819: istore 6
    //   5821: wide
    //   5825: wide
    //   5829: wide
    //   5833: wide
    //   5837: wide
    //   5841: wide
    //   5845: wide
    //   5849: wide
    //   5853: caload
    //   5854: istore 31
    //   5856: iload 6
    //   5858: iconst_5
    //   5859: irem
    //   5860: tableswitch	default:+32 -> 5892, 0:+11604->17464, 1:+11613->17473, 2:+11622->17482, 3:+11631->17491
    //   5893: dup_x1
    //   5894: wide
    //   5898: wide
    //   5902: iload 31
    //   5904: ixor
    //   5905: i2c
    //   5906: wide
    //   5910: wide
    //   5914: wide
    //   5918: wide
    //   5922: castore
    //   5923: iload 6
    //   5925: iconst_1
    //   5926: iadd
    //   5927: wide
    //   5931: wide
    //   5935: ifne +28 -> 5963
    //   5938: aload 5
    //   5940: wide
    //   5944: wide
    //   5948: wide
    //   5952: wide
    //   5956: wide
    //   5960: goto -115 -> 5845
    //   5963: wide
    //   5967: wide
    //   5971: aload 5
    //   5973: wide
    //   5977: wide
    //   5981: wide
    //   5985: if_icmpgt -176 -> 5809
    //   5988: new 41	java/lang/String
    //   5991: dup
    //   5992: wide
    //   5996: invokespecial 51	java/lang/String:<init>	([C)V
    //   5999: invokevirtual 55	java/lang/String:intern	()Ljava/lang/String;
    //   6002: wide
    //   6006: aload_1
    //   6007: wide
    //   6011: wide
    //   6015: aastore
    //   6016: bipush 32
    //   6018: wide
    //   6022: ldc 119
    //   6024: invokevirtual 47	java/lang/String:toCharArray	()[C
    //   6027: wide
    //   6031: wide
    //   6035: arraylength
    //   6036: wide
    //   6040: wide
    //   6044: iconst_1
    //   6045: if_icmpgt +13339 -> 19384
    //   6048: iconst_0
    //   6049: wide
    //   6053: wide
    //   6057: astore 5
    //   6059: wide
    //   6063: istore 6
    //   6065: wide
    //   6069: wide
    //   6073: wide
    //   6077: wide
    //   6081: wide
    //   6085: wide
    //   6089: wide
    //   6093: wide
    //   6097: caload
    //   6098: istore 31
    //   6100: iload 6
    //   6102: iconst_5
    //   6103: irem
    //   6104: tableswitch	default:+32 -> 6136, 0:+11396->17500, 1:+11405->17509, 2:+11414->17518, 3:+11423->17527
    //   6137: dup_x1
    //   6138: wide
    //   6142: wide
    //   6146: iload 31
    //   6148: ixor
    //   6149: i2c
    //   6150: wide
    //   6154: wide
    //   6158: wide
    //   6162: wide
    //   6166: castore
    //   6167: iload 6
    //   6169: iconst_1
    //   6170: iadd
    //   6171: wide
    //   6175: wide
    //   6179: ifne +28 -> 6207
    //   6182: aload 5
    //   6184: wide
    //   6188: wide
    //   6192: wide
    //   6196: wide
    //   6200: wide
    //   6204: goto -115 -> 6089
    //   6207: wide
    //   6211: wide
    //   6215: aload 5
    //   6217: wide
    //   6221: wide
    //   6225: wide
    //   6229: if_icmpgt -176 -> 6053
    //   6232: new 41	java/lang/String
    //   6235: dup
    //   6236: wide
    //   6240: invokespecial 51	java/lang/String:<init>	([C)V
    //   6243: invokevirtual 55	java/lang/String:intern	()Ljava/lang/String;
    //   6246: wide
    //   6250: aload_1
    //   6251: wide
    //   6255: wide
    //   6259: aastore
    //   6260: bipush 33
    //   6262: wide
    //   6266: ldc 121
    //   6268: invokevirtual 47	java/lang/String:toCharArray	()[C
    //   6271: wide
    //   6275: wide
    //   6279: arraylength
    //   6280: wide
    //   6284: wide
    //   6288: iconst_1
    //   6289: if_icmpgt +13087 -> 19376
    //   6292: iconst_0
    //   6293: wide
    //   6297: wide
    //   6301: astore 5
    //   6303: wide
    //   6307: istore 6
    //   6309: wide
    //   6313: wide
    //   6317: wide
    //   6321: wide
    //   6325: wide
    //   6329: wide
    //   6333: wide
    //   6337: wide
    //   6341: caload
    //   6342: istore 31
    //   6344: iload 6
    //   6346: iconst_5
    //   6347: irem
    //   6348: tableswitch	default:+32 -> 6380, 0:+11188->17536, 1:+11197->17545, 2:+11206->17554, 3:+11215->17563
    //   6381: dup_x1
    //   6382: wide
    //   6386: wide
    //   6390: iload 31
    //   6392: ixor
    //   6393: i2c
    //   6394: wide
    //   6398: wide
    //   6402: wide
    //   6406: wide
    //   6410: castore
    //   6411: iload 6
    //   6413: iconst_1
    //   6414: iadd
    //   6415: wide
    //   6419: wide
    //   6423: ifne +28 -> 6451
    //   6426: aload 5
    //   6428: wide
    //   6432: wide
    //   6436: wide
    //   6440: wide
    //   6444: wide
    //   6448: goto -115 -> 6333
    //   6451: wide
    //   6455: wide
    //   6459: aload 5
    //   6461: wide
    //   6465: wide
    //   6469: wide
    //   6473: if_icmpgt -176 -> 6297
    //   6476: new 41	java/lang/String
    //   6479: dup
    //   6480: wide
    //   6484: invokespecial 51	java/lang/String:<init>	([C)V
    //   6487: invokevirtual 55	java/lang/String:intern	()Ljava/lang/String;
    //   6490: wide
    //   6494: aload_1
    //   6495: wide
    //   6499: wide
    //   6503: aastore
    //   6504: bipush 34
    //   6506: wide
    //   6510: ldc 123
    //   6512: invokevirtual 47	java/lang/String:toCharArray	()[C
    //   6515: wide
    //   6519: wide
    //   6523: arraylength
    //   6524: wide
    //   6528: wide
    //   6532: iconst_1
    //   6533: if_icmpgt +12835 -> 19368
    //   6536: iconst_0
    //   6537: wide
    //   6541: wide
    //   6545: astore 5
    //   6547: wide
    //   6551: istore 6
    //   6553: wide
    //   6557: wide
    //   6561: wide
    //   6565: wide
    //   6569: wide
    //   6573: wide
    //   6577: wide
    //   6581: wide
    //   6585: caload
    //   6586: istore 31
    //   6588: iload 6
    //   6590: iconst_5
    //   6591: irem
    //   6592: tableswitch	default:+32 -> 6624, 0:+10980->17572, 1:+10989->17581, 2:+10998->17590, 3:+11007->17599
    //   6625: dup_x1
    //   6626: wide
    //   6630: wide
    //   6634: iload 31
    //   6636: ixor
    //   6637: i2c
    //   6638: wide
    //   6642: wide
    //   6646: wide
    //   6650: wide
    //   6654: castore
    //   6655: iload 6
    //   6657: iconst_1
    //   6658: iadd
    //   6659: wide
    //   6663: wide
    //   6667: ifne +28 -> 6695
    //   6670: aload 5
    //   6672: wide
    //   6676: wide
    //   6680: wide
    //   6684: wide
    //   6688: wide
    //   6692: goto -115 -> 6577
    //   6695: wide
    //   6699: wide
    //   6703: aload 5
    //   6705: wide
    //   6709: wide
    //   6713: wide
    //   6717: if_icmpgt -176 -> 6541
    //   6720: new 41	java/lang/String
    //   6723: dup
    //   6724: wide
    //   6728: invokespecial 51	java/lang/String:<init>	([C)V
    //   6731: invokevirtual 55	java/lang/String:intern	()Ljava/lang/String;
    //   6734: wide
    //   6738: aload_1
    //   6739: wide
    //   6743: wide
    //   6747: aastore
    //   6748: bipush 35
    //   6750: wide
    //   6754: ldc 125
    //   6756: invokevirtual 47	java/lang/String:toCharArray	()[C
    //   6759: wide
    //   6763: wide
    //   6767: arraylength
    //   6768: wide
    //   6772: wide
    //   6776: iconst_1
    //   6777: if_icmpgt +12583 -> 19360
    //   6780: iconst_0
    //   6781: wide
    //   6785: wide
    //   6789: astore 5
    //   6791: wide
    //   6795: istore 6
    //   6797: wide
    //   6801: wide
    //   6805: wide
    //   6809: wide
    //   6813: wide
    //   6817: wide
    //   6821: wide
    //   6825: wide
    //   6829: caload
    //   6830: istore 31
    //   6832: iload 6
    //   6834: iconst_5
    //   6835: irem
    //   6836: tableswitch	default:+32 -> 6868, 0:+10772->17608, 1:+10781->17617, 2:+10790->17626, 3:+10799->17635
    //   6869: dup_x1
    //   6870: wide
    //   6874: wide
    //   6878: iload 31
    //   6880: ixor
    //   6881: i2c
    //   6882: wide
    //   6886: wide
    //   6890: wide
    //   6894: wide
    //   6898: castore
    //   6899: iload 6
    //   6901: iconst_1
    //   6902: iadd
    //   6903: wide
    //   6907: wide
    //   6911: ifne +28 -> 6939
    //   6914: aload 5
    //   6916: wide
    //   6920: wide
    //   6924: wide
    //   6928: wide
    //   6932: wide
    //   6936: goto -115 -> 6821
    //   6939: wide
    //   6943: wide
    //   6947: aload 5
    //   6949: wide
    //   6953: wide
    //   6957: wide
    //   6961: if_icmpgt -176 -> 6785
    //   6964: new 41	java/lang/String
    //   6967: dup
    //   6968: wide
    //   6972: invokespecial 51	java/lang/String:<init>	([C)V
    //   6975: invokevirtual 55	java/lang/String:intern	()Ljava/lang/String;
    //   6978: wide
    //   6982: aload_1
    //   6983: wide
    //   6987: wide
    //   6991: aastore
    //   6992: bipush 36
    //   6994: wide
    //   6998: ldc 127
    //   7000: invokevirtual 47	java/lang/String:toCharArray	()[C
    //   7003: wide
    //   7007: wide
    //   7011: arraylength
    //   7012: wide
    //   7016: wide
    //   7020: iconst_1
    //   7021: if_icmpgt +12331 -> 19352
    //   7024: iconst_0
    //   7025: wide
    //   7029: wide
    //   7033: astore 5
    //   7035: wide
    //   7039: istore 6
    //   7041: wide
    //   7045: wide
    //   7049: wide
    //   7053: wide
    //   7057: wide
    //   7061: wide
    //   7065: wide
    //   7069: wide
    //   7073: caload
    //   7074: istore 31
    //   7076: iload 6
    //   7078: iconst_5
    //   7079: irem
    //   7080: tableswitch	default:+32 -> 7112, 0:+10564->17644, 1:+10573->17653, 2:+10582->17662, 3:+10591->17671
    //   7113: dup_x1
    //   7114: wide
    //   7118: wide
    //   7122: iload 31
    //   7124: ixor
    //   7125: i2c
    //   7126: wide
    //   7130: wide
    //   7134: wide
    //   7138: wide
    //   7142: castore
    //   7143: iload 6
    //   7145: iconst_1
    //   7146: iadd
    //   7147: wide
    //   7151: wide
    //   7155: ifne +28 -> 7183
    //   7158: aload 5
    //   7160: wide
    //   7164: wide
    //   7168: wide
    //   7172: wide
    //   7176: wide
    //   7180: goto -115 -> 7065
    //   7183: wide
    //   7187: wide
    //   7191: aload 5
    //   7193: wide
    //   7197: wide
    //   7201: wide
    //   7205: if_icmpgt -176 -> 7029
    //   7208: new 41	java/lang/String
    //   7211: dup
    //   7212: wide
    //   7216: invokespecial 51	java/lang/String:<init>	([C)V
    //   7219: invokevirtual 55	java/lang/String:intern	()Ljava/lang/String;
    //   7222: wide
    //   7226: aload_1
    //   7227: wide
    //   7231: wide
    //   7235: aastore
    //   7236: bipush 37
    //   7238: wide
    //   7242: ldc 129
    //   7244: invokevirtual 47	java/lang/String:toCharArray	()[C
    //   7247: wide
    //   7251: wide
    //   7255: arraylength
    //   7256: wide
    //   7260: wide
    //   7264: iconst_1
    //   7265: if_icmpgt +12079 -> 19344
    //   7268: iconst_0
    //   7269: wide
    //   7273: wide
    //   7277: astore 5
    //   7279: wide
    //   7283: istore 6
    //   7285: wide
    //   7289: wide
    //   7293: wide
    //   7297: wide
    //   7301: wide
    //   7305: wide
    //   7309: wide
    //   7313: wide
    //   7317: caload
    //   7318: istore 31
    //   7320: iload 6
    //   7322: iconst_5
    //   7323: irem
    //   7324: tableswitch	default:+32 -> 7356, 0:+10356->17680, 1:+10365->17689, 2:+10374->17698, 3:+10383->17707
    //   7357: dup_x1
    //   7358: wide
    //   7362: wide
    //   7366: iload 31
    //   7368: ixor
    //   7369: i2c
    //   7370: wide
    //   7374: wide
    //   7378: wide
    //   7382: wide
    //   7386: castore
    //   7387: iload 6
    //   7389: iconst_1
    //   7390: iadd
    //   7391: wide
    //   7395: wide
    //   7399: ifne +28 -> 7427
    //   7402: aload 5
    //   7404: wide
    //   7408: wide
    //   7412: wide
    //   7416: wide
    //   7420: wide
    //   7424: goto -115 -> 7309
    //   7427: wide
    //   7431: wide
    //   7435: aload 5
    //   7437: wide
    //   7441: wide
    //   7445: wide
    //   7449: if_icmpgt -176 -> 7273
    //   7452: new 41	java/lang/String
    //   7455: dup
    //   7456: wide
    //   7460: invokespecial 51	java/lang/String:<init>	([C)V
    //   7463: invokevirtual 55	java/lang/String:intern	()Ljava/lang/String;
    //   7466: wide
    //   7470: aload_1
    //   7471: wide
    //   7475: wide
    //   7479: aastore
    //   7480: bipush 38
    //   7482: wide
    //   7486: ldc 131
    //   7488: invokevirtual 47	java/lang/String:toCharArray	()[C
    //   7491: wide
    //   7495: wide
    //   7499: arraylength
    //   7500: wide
    //   7504: wide
    //   7508: iconst_1
    //   7509: if_icmpgt +11827 -> 19336
    //   7512: iconst_0
    //   7513: wide
    //   7517: wide
    //   7521: astore 5
    //   7523: wide
    //   7527: istore 6
    //   7529: wide
    //   7533: wide
    //   7537: wide
    //   7541: wide
    //   7545: wide
    //   7549: wide
    //   7553: wide
    //   7557: wide
    //   7561: caload
    //   7562: istore 31
    //   7564: iload 6
    //   7566: iconst_5
    //   7567: irem
    //   7568: tableswitch	default:+32 -> 7600, 0:+10148->17716, 1:+10157->17725, 2:+10166->17734, 3:+10175->17743
    //   7601: dup_x1
    //   7602: wide
    //   7606: wide
    //   7610: iload 31
    //   7612: ixor
    //   7613: i2c
    //   7614: wide
    //   7618: wide
    //   7622: wide
    //   7626: wide
    //   7630: castore
    //   7631: iload 6
    //   7633: iconst_1
    //   7634: iadd
    //   7635: wide
    //   7639: wide
    //   7643: ifne +28 -> 7671
    //   7646: aload 5
    //   7648: wide
    //   7652: wide
    //   7656: wide
    //   7660: wide
    //   7664: wide
    //   7668: goto -115 -> 7553
    //   7671: wide
    //   7675: wide
    //   7679: aload 5
    //   7681: wide
    //   7685: wide
    //   7689: wide
    //   7693: if_icmpgt -176 -> 7517
    //   7696: new 41	java/lang/String
    //   7699: dup
    //   7700: wide
    //   7704: invokespecial 51	java/lang/String:<init>	([C)V
    //   7707: invokevirtual 55	java/lang/String:intern	()Ljava/lang/String;
    //   7710: wide
    //   7714: aload_1
    //   7715: wide
    //   7719: wide
    //   7723: aastore
    //   7724: bipush 39
    //   7726: wide
    //   7730: ldc 133
    //   7732: invokevirtual 47	java/lang/String:toCharArray	()[C
    //   7735: wide
    //   7739: wide
    //   7743: arraylength
    //   7744: wide
    //   7748: wide
    //   7752: iconst_1
    //   7753: if_icmpgt +11575 -> 19328
    //   7756: iconst_0
    //   7757: wide
    //   7761: wide
    //   7765: astore 5
    //   7767: wide
    //   7771: istore 6
    //   7773: wide
    //   7777: wide
    //   7781: wide
    //   7785: wide
    //   7789: wide
    //   7793: wide
    //   7797: wide
    //   7801: wide
    //   7805: caload
    //   7806: istore 31
    //   7808: iload 6
    //   7810: iconst_5
    //   7811: irem
    //   7812: tableswitch	default:+32 -> 7844, 0:+9940->17752, 1:+9949->17761, 2:+9958->17770, 3:+9967->17779
    //   7845: dup_x1
    //   7846: wide
    //   7850: wide
    //   7854: iload 31
    //   7856: ixor
    //   7857: i2c
    //   7858: wide
    //   7862: wide
    //   7866: wide
    //   7870: wide
    //   7874: castore
    //   7875: iload 6
    //   7877: iconst_1
    //   7878: iadd
    //   7879: wide
    //   7883: wide
    //   7887: ifne +28 -> 7915
    //   7890: aload 5
    //   7892: wide
    //   7896: wide
    //   7900: wide
    //   7904: wide
    //   7908: wide
    //   7912: goto -115 -> 7797
    //   7915: wide
    //   7919: wide
    //   7923: aload 5
    //   7925: wide
    //   7929: wide
    //   7933: wide
    //   7937: if_icmpgt -176 -> 7761
    //   7940: new 41	java/lang/String
    //   7943: dup
    //   7944: wide
    //   7948: invokespecial 51	java/lang/String:<init>	([C)V
    //   7951: invokevirtual 55	java/lang/String:intern	()Ljava/lang/String;
    //   7954: wide
    //   7958: aload_1
    //   7959: wide
    //   7963: wide
    //   7967: aastore
    //   7968: bipush 40
    //   7970: wide
    //   7974: ldc 135
    //   7976: invokevirtual 47	java/lang/String:toCharArray	()[C
    //   7979: wide
    //   7983: wide
    //   7987: arraylength
    //   7988: wide
    //   7992: wide
    //   7996: iconst_1
    //   7997: if_icmpgt +11323 -> 19320
    //   8000: iconst_0
    //   8001: wide
    //   8005: wide
    //   8009: astore 5
    //   8011: wide
    //   8015: istore 6
    //   8017: wide
    //   8021: wide
    //   8025: wide
    //   8029: wide
    //   8033: wide
    //   8037: wide
    //   8041: wide
    //   8045: wide
    //   8049: caload
    //   8050: istore 31
    //   8052: iload 6
    //   8054: iconst_5
    //   8055: irem
    //   8056: tableswitch	default:+32 -> 8088, 0:+9732->17788, 1:+9741->17797, 2:+9750->17806, 3:+9759->17815
    //   8089: dup_x1
    //   8090: wide
    //   8094: wide
    //   8098: iload 31
    //   8100: ixor
    //   8101: i2c
    //   8102: wide
    //   8106: wide
    //   8110: wide
    //   8114: wide
    //   8118: castore
    //   8119: iload 6
    //   8121: iconst_1
    //   8122: iadd
    //   8123: wide
    //   8127: wide
    //   8131: ifne +28 -> 8159
    //   8134: aload 5
    //   8136: wide
    //   8140: wide
    //   8144: wide
    //   8148: wide
    //   8152: wide
    //   8156: goto -115 -> 8041
    //   8159: wide
    //   8163: wide
    //   8167: aload 5
    //   8169: wide
    //   8173: wide
    //   8177: wide
    //   8181: if_icmpgt -176 -> 8005
    //   8184: new 41	java/lang/String
    //   8187: dup
    //   8188: wide
    //   8192: invokespecial 51	java/lang/String:<init>	([C)V
    //   8195: invokevirtual 55	java/lang/String:intern	()Ljava/lang/String;
    //   8198: wide
    //   8202: aload_1
    //   8203: wide
    //   8207: wide
    //   8211: aastore
    //   8212: bipush 41
    //   8214: wide
    //   8218: ldc 137
    //   8220: invokevirtual 47	java/lang/String:toCharArray	()[C
    //   8223: wide
    //   8227: wide
    //   8231: arraylength
    //   8232: wide
    //   8236: wide
    //   8240: iconst_1
    //   8241: if_icmpgt +11071 -> 19312
    //   8244: iconst_0
    //   8245: wide
    //   8249: wide
    //   8253: astore 5
    //   8255: wide
    //   8259: istore 6
    //   8261: wide
    //   8265: wide
    //   8269: wide
    //   8273: wide
    //   8277: wide
    //   8281: wide
    //   8285: wide
    //   8289: wide
    //   8293: caload
    //   8294: istore 31
    //   8296: iload 6
    //   8298: iconst_5
    //   8299: irem
    //   8300: tableswitch	default:+32 -> 8332, 0:+9524->17824, 1:+9533->17833, 2:+9542->17842, 3:+9551->17851
    //   8333: dup_x1
    //   8334: wide
    //   8338: wide
    //   8342: iload 31
    //   8344: ixor
    //   8345: i2c
    //   8346: wide
    //   8350: wide
    //   8354: wide
    //   8358: wide
    //   8362: castore
    //   8363: iload 6
    //   8365: iconst_1
    //   8366: iadd
    //   8367: wide
    //   8371: wide
    //   8375: ifne +28 -> 8403
    //   8378: aload 5
    //   8380: wide
    //   8384: wide
    //   8388: wide
    //   8392: wide
    //   8396: wide
    //   8400: goto -115 -> 8285
    //   8403: wide
    //   8407: wide
    //   8411: aload 5
    //   8413: wide
    //   8417: wide
    //   8421: wide
    //   8425: if_icmpgt -176 -> 8249
    //   8428: new 41	java/lang/String
    //   8431: dup
    //   8432: wide
    //   8436: invokespecial 51	java/lang/String:<init>	([C)V
    //   8439: invokevirtual 55	java/lang/String:intern	()Ljava/lang/String;
    //   8442: wide
    //   8446: aload_1
    //   8447: wide
    //   8451: wide
    //   8455: aastore
    //   8456: bipush 42
    //   8458: wide
    //   8462: ldc 139
    //   8464: invokevirtual 47	java/lang/String:toCharArray	()[C
    //   8467: wide
    //   8471: wide
    //   8475: arraylength
    //   8476: wide
    //   8480: wide
    //   8484: iconst_1
    //   8485: if_icmpgt +10819 -> 19304
    //   8488: iconst_0
    //   8489: wide
    //   8493: wide
    //   8497: astore 5
    //   8499: wide
    //   8503: istore 6
    //   8505: wide
    //   8509: wide
    //   8513: wide
    //   8517: wide
    //   8521: wide
    //   8525: wide
    //   8529: wide
    //   8533: wide
    //   8537: caload
    //   8538: istore 31
    //   8540: iload 6
    //   8542: iconst_5
    //   8543: irem
    //   8544: tableswitch	default:+32 -> 8576, 0:+9316->17860, 1:+9325->17869, 2:+9334->17878, 3:+9343->17887
    //   8577: dup_x1
    //   8578: wide
    //   8582: wide
    //   8586: iload 31
    //   8588: ixor
    //   8589: i2c
    //   8590: wide
    //   8594: wide
    //   8598: wide
    //   8602: wide
    //   8606: castore
    //   8607: iload 6
    //   8609: iconst_1
    //   8610: iadd
    //   8611: wide
    //   8615: wide
    //   8619: ifne +28 -> 8647
    //   8622: aload 5
    //   8624: wide
    //   8628: wide
    //   8632: wide
    //   8636: wide
    //   8640: wide
    //   8644: goto -115 -> 8529
    //   8647: wide
    //   8651: wide
    //   8655: aload 5
    //   8657: wide
    //   8661: wide
    //   8665: wide
    //   8669: if_icmpgt -176 -> 8493
    //   8672: new 41	java/lang/String
    //   8675: dup
    //   8676: wide
    //   8680: invokespecial 51	java/lang/String:<init>	([C)V
    //   8683: invokevirtual 55	java/lang/String:intern	()Ljava/lang/String;
    //   8686: wide
    //   8690: aload_1
    //   8691: wide
    //   8695: wide
    //   8699: aastore
    //   8700: bipush 43
    //   8702: wide
    //   8706: ldc 141
    //   8708: invokevirtual 47	java/lang/String:toCharArray	()[C
    //   8711: wide
    //   8715: wide
    //   8719: arraylength
    //   8720: wide
    //   8724: wide
    //   8728: iconst_1
    //   8729: if_icmpgt +10567 -> 19296
    //   8732: iconst_0
    //   8733: wide
    //   8737: wide
    //   8741: astore 5
    //   8743: wide
    //   8747: istore 6
    //   8749: wide
    //   8753: wide
    //   8757: wide
    //   8761: wide
    //   8765: wide
    //   8769: wide
    //   8773: wide
    //   8777: wide
    //   8781: caload
    //   8782: istore 31
    //   8784: iload 6
    //   8786: iconst_5
    //   8787: irem
    //   8788: tableswitch	default:+32 -> 8820, 0:+9108->17896, 1:+9117->17905, 2:+9126->17914, 3:+9135->17923
    //   8821: dup_x1
    //   8822: wide
    //   8826: wide
    //   8830: iload 31
    //   8832: ixor
    //   8833: i2c
    //   8834: wide
    //   8838: wide
    //   8842: wide
    //   8846: wide
    //   8850: castore
    //   8851: iload 6
    //   8853: iconst_1
    //   8854: iadd
    //   8855: wide
    //   8859: wide
    //   8863: ifne +28 -> 8891
    //   8866: aload 5
    //   8868: wide
    //   8872: wide
    //   8876: wide
    //   8880: wide
    //   8884: wide
    //   8888: goto -115 -> 8773
    //   8891: wide
    //   8895: wide
    //   8899: aload 5
    //   8901: wide
    //   8905: wide
    //   8909: wide
    //   8913: if_icmpgt -176 -> 8737
    //   8916: new 41	java/lang/String
    //   8919: dup
    //   8920: wide
    //   8924: invokespecial 51	java/lang/String:<init>	([C)V
    //   8927: invokevirtual 55	java/lang/String:intern	()Ljava/lang/String;
    //   8930: wide
    //   8934: aload_1
    //   8935: wide
    //   8939: wide
    //   8943: aastore
    //   8944: bipush 44
    //   8946: wide
    //   8950: ldc 143
    //   8952: invokevirtual 47	java/lang/String:toCharArray	()[C
    //   8955: wide
    //   8959: wide
    //   8963: arraylength
    //   8964: wide
    //   8968: wide
    //   8972: iconst_1
    //   8973: if_icmpgt +10315 -> 19288
    //   8976: iconst_0
    //   8977: wide
    //   8981: wide
    //   8985: astore 5
    //   8987: wide
    //   8991: istore 6
    //   8993: wide
    //   8997: wide
    //   9001: wide
    //   9005: wide
    //   9009: wide
    //   9013: wide
    //   9017: wide
    //   9021: wide
    //   9025: caload
    //   9026: istore 31
    //   9028: iload 6
    //   9030: iconst_5
    //   9031: irem
    //   9032: tableswitch	default:+32 -> 9064, 0:+8900->17932, 1:+8909->17941, 2:+8918->17950, 3:+8927->17959
    //   9065: dup_x1
    //   9066: wide
    //   9070: wide
    //   9074: iload 31
    //   9076: ixor
    //   9077: i2c
    //   9078: wide
    //   9082: wide
    //   9086: wide
    //   9090: wide
    //   9094: castore
    //   9095: iload 6
    //   9097: iconst_1
    //   9098: iadd
    //   9099: wide
    //   9103: wide
    //   9107: ifne +28 -> 9135
    //   9110: aload 5
    //   9112: wide
    //   9116: wide
    //   9120: wide
    //   9124: wide
    //   9128: wide
    //   9132: goto -115 -> 9017
    //   9135: wide
    //   9139: wide
    //   9143: aload 5
    //   9145: wide
    //   9149: wide
    //   9153: wide
    //   9157: if_icmpgt -176 -> 8981
    //   9160: new 41	java/lang/String
    //   9163: dup
    //   9164: wide
    //   9168: invokespecial 51	java/lang/String:<init>	([C)V
    //   9171: invokevirtual 55	java/lang/String:intern	()Ljava/lang/String;
    //   9174: wide
    //   9178: aload_1
    //   9179: wide
    //   9183: wide
    //   9187: aastore
    //   9188: bipush 45
    //   9190: wide
    //   9194: ldc 145
    //   9196: invokevirtual 47	java/lang/String:toCharArray	()[C
    //   9199: wide
    //   9203: wide
    //   9207: arraylength
    //   9208: wide
    //   9212: wide
    //   9216: iconst_1
    //   9217: if_icmpgt +10063 -> 19280
    //   9220: iconst_0
    //   9221: wide
    //   9225: wide
    //   9229: astore 5
    //   9231: wide
    //   9235: istore 6
    //   9237: wide
    //   9241: wide
    //   9245: wide
    //   9249: wide
    //   9253: wide
    //   9257: wide
    //   9261: wide
    //   9265: wide
    //   9269: caload
    //   9270: istore 31
    //   9272: iload 6
    //   9274: iconst_5
    //   9275: irem
    //   9276: tableswitch	default:+32 -> 9308, 0:+8692->17968, 1:+8701->17977, 2:+8710->17986, 3:+8719->17995
    //   9309: dup_x1
    //   9310: wide
    //   9314: wide
    //   9318: iload 31
    //   9320: ixor
    //   9321: i2c
    //   9322: wide
    //   9326: wide
    //   9330: wide
    //   9334: wide
    //   9338: castore
    //   9339: iload 6
    //   9341: iconst_1
    //   9342: iadd
    //   9343: wide
    //   9347: wide
    //   9351: ifne +28 -> 9379
    //   9354: aload 5
    //   9356: wide
    //   9360: wide
    //   9364: wide
    //   9368: wide
    //   9372: wide
    //   9376: goto -115 -> 9261
    //   9379: wide
    //   9383: wide
    //   9387: aload 5
    //   9389: wide
    //   9393: wide
    //   9397: wide
    //   9401: if_icmpgt -176 -> 9225
    //   9404: new 41	java/lang/String
    //   9407: dup
    //   9408: wide
    //   9412: invokespecial 51	java/lang/String:<init>	([C)V
    //   9415: invokevirtual 55	java/lang/String:intern	()Ljava/lang/String;
    //   9418: wide
    //   9422: aload_1
    //   9423: wide
    //   9427: wide
    //   9431: aastore
    //   9432: bipush 46
    //   9434: wide
    //   9438: ldc 147
    //   9440: invokevirtual 47	java/lang/String:toCharArray	()[C
    //   9443: wide
    //   9447: wide
    //   9451: arraylength
    //   9452: wide
    //   9456: wide
    //   9460: iconst_1
    //   9461: if_icmpgt +9811 -> 19272
    //   9464: iconst_0
    //   9465: wide
    //   9469: wide
    //   9473: astore 5
    //   9475: wide
    //   9479: istore 6
    //   9481: wide
    //   9485: wide
    //   9489: wide
    //   9493: wide
    //   9497: wide
    //   9501: wide
    //   9505: wide
    //   9509: wide
    //   9513: caload
    //   9514: istore 31
    //   9516: iload 6
    //   9518: iconst_5
    //   9519: irem
    //   9520: tableswitch	default:+32 -> 9552, 0:+8484->18004, 1:+8493->18013, 2:+8502->18022, 3:+8511->18031
    //   9553: dup_x1
    //   9554: wide
    //   9558: wide
    //   9562: iload 31
    //   9564: ixor
    //   9565: i2c
    //   9566: wide
    //   9570: wide
    //   9574: wide
    //   9578: wide
    //   9582: castore
    //   9583: iload 6
    //   9585: iconst_1
    //   9586: iadd
    //   9587: wide
    //   9591: wide
    //   9595: ifne +28 -> 9623
    //   9598: aload 5
    //   9600: wide
    //   9604: wide
    //   9608: wide
    //   9612: wide
    //   9616: wide
    //   9620: goto -115 -> 9505
    //   9623: wide
    //   9627: wide
    //   9631: aload 5
    //   9633: wide
    //   9637: wide
    //   9641: wide
    //   9645: if_icmpgt -176 -> 9469
    //   9648: new 41	java/lang/String
    //   9651: dup
    //   9652: wide
    //   9656: invokespecial 51	java/lang/String:<init>	([C)V
    //   9659: invokevirtual 55	java/lang/String:intern	()Ljava/lang/String;
    //   9662: wide
    //   9666: aload_1
    //   9667: wide
    //   9671: wide
    //   9675: aastore
    //   9676: bipush 47
    //   9678: wide
    //   9682: ldc 149
    //   9684: invokevirtual 47	java/lang/String:toCharArray	()[C
    //   9687: wide
    //   9691: wide
    //   9695: arraylength
    //   9696: wide
    //   9700: wide
    //   9704: iconst_1
    //   9705: if_icmpgt +9559 -> 19264
    //   9708: iconst_0
    //   9709: wide
    //   9713: wide
    //   9717: astore 5
    //   9719: wide
    //   9723: istore 6
    //   9725: wide
    //   9729: wide
    //   9733: wide
    //   9737: wide
    //   9741: wide
    //   9745: wide
    //   9749: wide
    //   9753: wide
    //   9757: caload
    //   9758: istore 31
    //   9760: iload 6
    //   9762: iconst_5
    //   9763: irem
    //   9764: tableswitch	default:+32 -> 9796, 0:+8276->18040, 1:+8285->18049, 2:+8294->18058, 3:+8303->18067
    //   9797: dup_x1
    //   9798: wide
    //   9802: wide
    //   9806: iload 31
    //   9808: ixor
    //   9809: i2c
    //   9810: wide
    //   9814: wide
    //   9818: wide
    //   9822: wide
    //   9826: castore
    //   9827: iload 6
    //   9829: iconst_1
    //   9830: iadd
    //   9831: wide
    //   9835: wide
    //   9839: ifne +28 -> 9867
    //   9842: aload 5
    //   9844: wide
    //   9848: wide
    //   9852: wide
    //   9856: wide
    //   9860: wide
    //   9864: goto -115 -> 9749
    //   9867: wide
    //   9871: wide
    //   9875: aload 5
    //   9877: wide
    //   9881: wide
    //   9885: wide
    //   9889: if_icmpgt -176 -> 9713
    //   9892: new 41	java/lang/String
    //   9895: dup
    //   9896: wide
    //   9900: invokespecial 51	java/lang/String:<init>	([C)V
    //   9903: invokevirtual 55	java/lang/String:intern	()Ljava/lang/String;
    //   9906: wide
    //   9910: aload_1
    //   9911: wide
    //   9915: wide
    //   9919: aastore
    //   9920: bipush 48
    //   9922: wide
    //   9926: ldc 151
    //   9928: invokevirtual 47	java/lang/String:toCharArray	()[C
    //   9931: wide
    //   9935: wide
    //   9939: arraylength
    //   9940: wide
    //   9944: wide
    //   9948: iconst_1
    //   9949: if_icmpgt +9307 -> 19256
    //   9952: iconst_0
    //   9953: wide
    //   9957: wide
    //   9961: astore 5
    //   9963: wide
    //   9967: istore 6
    //   9969: wide
    //   9973: wide
    //   9977: wide
    //   9981: wide
    //   9985: wide
    //   9989: wide
    //   9993: wide
    //   9997: wide
    //   10001: caload
    //   10002: istore 31
    //   10004: iload 6
    //   10006: iconst_5
    //   10007: irem
    //   10008: tableswitch	default:+32 -> 10040, 0:+8068->18076, 1:+8077->18085, 2:+8086->18094, 3:+8095->18103
    //   10041: dup_x1
    //   10042: wide
    //   10046: wide
    //   10050: iload 31
    //   10052: ixor
    //   10053: i2c
    //   10054: wide
    //   10058: wide
    //   10062: wide
    //   10066: wide
    //   10070: castore
    //   10071: iload 6
    //   10073: iconst_1
    //   10074: iadd
    //   10075: wide
    //   10079: wide
    //   10083: ifne +28 -> 10111
    //   10086: aload 5
    //   10088: wide
    //   10092: wide
    //   10096: wide
    //   10100: wide
    //   10104: wide
    //   10108: goto -115 -> 9993
    //   10111: wide
    //   10115: wide
    //   10119: aload 5
    //   10121: wide
    //   10125: wide
    //   10129: wide
    //   10133: if_icmpgt -176 -> 9957
    //   10136: new 41	java/lang/String
    //   10139: dup
    //   10140: wide
    //   10144: invokespecial 51	java/lang/String:<init>	([C)V
    //   10147: invokevirtual 55	java/lang/String:intern	()Ljava/lang/String;
    //   10150: wide
    //   10154: aload_1
    //   10155: wide
    //   10159: wide
    //   10163: aastore
    //   10164: bipush 49
    //   10166: wide
    //   10170: ldc 153
    //   10172: invokevirtual 47	java/lang/String:toCharArray	()[C
    //   10175: wide
    //   10179: wide
    //   10183: arraylength
    //   10184: wide
    //   10188: wide
    //   10192: iconst_1
    //   10193: if_icmpgt +9055 -> 19248
    //   10196: iconst_0
    //   10197: wide
    //   10201: wide
    //   10205: astore 5
    //   10207: wide
    //   10211: istore 6
    //   10213: wide
    //   10217: wide
    //   10221: wide
    //   10225: wide
    //   10229: wide
    //   10233: wide
    //   10237: wide
    //   10241: wide
    //   10245: caload
    //   10246: istore 31
    //   10248: iload 6
    //   10250: iconst_5
    //   10251: irem
    //   10252: tableswitch	default:+32 -> 10284, 0:+7860->18112, 1:+7869->18121, 2:+7878->18130, 3:+7887->18139
    //   10285: dup_x1
    //   10286: wide
    //   10290: wide
    //   10294: iload 31
    //   10296: ixor
    //   10297: i2c
    //   10298: wide
    //   10302: wide
    //   10306: wide
    //   10310: wide
    //   10314: castore
    //   10315: iload 6
    //   10317: iconst_1
    //   10318: iadd
    //   10319: wide
    //   10323: wide
    //   10327: ifne +28 -> 10355
    //   10330: aload 5
    //   10332: wide
    //   10336: wide
    //   10340: wide
    //   10344: wide
    //   10348: wide
    //   10352: goto -115 -> 10237
    //   10355: wide
    //   10359: wide
    //   10363: aload 5
    //   10365: wide
    //   10369: wide
    //   10373: wide
    //   10377: if_icmpgt -176 -> 10201
    //   10380: new 41	java/lang/String
    //   10383: dup
    //   10384: wide
    //   10388: invokespecial 51	java/lang/String:<init>	([C)V
    //   10391: invokevirtual 55	java/lang/String:intern	()Ljava/lang/String;
    //   10394: wide
    //   10398: aload_1
    //   10399: wide
    //   10403: wide
    //   10407: aastore
    //   10408: bipush 50
    //   10410: wide
    //   10414: ldc 155
    //   10416: invokevirtual 47	java/lang/String:toCharArray	()[C
    //   10419: wide
    //   10423: wide
    //   10427: arraylength
    //   10428: wide
    //   10432: wide
    //   10436: iconst_1
    //   10437: if_icmpgt +8803 -> 19240
    //   10440: iconst_0
    //   10441: wide
    //   10445: wide
    //   10449: astore 5
    //   10451: wide
    //   10455: istore 6
    //   10457: wide
    //   10461: wide
    //   10465: wide
    //   10469: wide
    //   10473: wide
    //   10477: wide
    //   10481: wide
    //   10485: wide
    //   10489: caload
    //   10490: istore 31
    //   10492: iload 6
    //   10494: iconst_5
    //   10495: irem
    //   10496: tableswitch	default:+32 -> 10528, 0:+7652->18148, 1:+7661->18157, 2:+7670->18166, 3:+7679->18175
    //   10529: dup_x1
    //   10530: wide
    //   10534: wide
    //   10538: iload 31
    //   10540: ixor
    //   10541: i2c
    //   10542: wide
    //   10546: wide
    //   10550: wide
    //   10554: wide
    //   10558: castore
    //   10559: iload 6
    //   10561: iconst_1
    //   10562: iadd
    //   10563: wide
    //   10567: wide
    //   10571: ifne +28 -> 10599
    //   10574: aload 5
    //   10576: wide
    //   10580: wide
    //   10584: wide
    //   10588: wide
    //   10592: wide
    //   10596: goto -115 -> 10481
    //   10599: wide
    //   10603: wide
    //   10607: aload 5
    //   10609: wide
    //   10613: wide
    //   10617: wide
    //   10621: if_icmpgt -176 -> 10445
    //   10624: new 41	java/lang/String
    //   10627: dup
    //   10628: wide
    //   10632: invokespecial 51	java/lang/String:<init>	([C)V
    //   10635: invokevirtual 55	java/lang/String:intern	()Ljava/lang/String;
    //   10638: wide
    //   10642: aload_1
    //   10643: wide
    //   10647: wide
    //   10651: aastore
    //   10652: ldc 157
    //   10654: invokevirtual 47	java/lang/String:toCharArray	()[C
    //   10657: wide
    //   10661: wide
    //   10665: arraylength
    //   10666: wide
    //   10670: wide
    //   10674: iconst_1
    //   10675: if_icmpgt +8557 -> 19232
    //   10678: iconst_0
    //   10679: wide
    //   10683: wide
    //   10687: astore 5
    //   10689: wide
    //   10693: istore 6
    //   10695: wide
    //   10699: wide
    //   10703: wide
    //   10707: wide
    //   10711: wide
    //   10715: wide
    //   10719: wide
    //   10723: wide
    //   10727: caload
    //   10728: wide
    //   10732: iload 6
    //   10734: iconst_5
    //   10735: irem
    //   10736: tableswitch	default:+32 -> 10768, 0:+7448->18184, 1:+7457->18193, 2:+7466->18202, 3:+7475->18211
    //   10769: dup_x1
    //   10770: wide
    //   10774: wide
    //   10778: wide
    //   10782: ixor
    //   10783: i2c
    //   10784: wide
    //   10788: wide
    //   10792: wide
    //   10796: wide
    //   10800: castore
    //   10801: iload 6
    //   10803: iconst_1
    //   10804: iadd
    //   10805: wide
    //   10809: wide
    //   10813: ifne +28 -> 10841
    //   10816: aload 5
    //   10818: wide
    //   10822: wide
    //   10826: wide
    //   10830: wide
    //   10834: wide
    //   10838: goto -119 -> 10719
    //   10841: wide
    //   10845: wide
    //   10849: aload 5
    //   10851: wide
    //   10855: wide
    //   10859: wide
    //   10863: if_icmpgt -180 -> 10683
    //   10866: new 41	java/lang/String
    //   10869: dup
    //   10870: wide
    //   10874: invokespecial 51	java/lang/String:<init>	([C)V
    //   10877: invokevirtual 55	java/lang/String:intern	()Ljava/lang/String;
    //   10880: wide
    //   10884: aload_1
    //   10885: bipush 51
    //   10887: wide
    //   10891: aastore
    //   10892: bipush 52
    //   10894: wide
    //   10898: ldc 159
    //   10900: invokevirtual 47	java/lang/String:toCharArray	()[C
    //   10903: wide
    //   10907: wide
    //   10911: arraylength
    //   10912: wide
    //   10916: wide
    //   10920: iconst_1
    //   10921: if_icmpgt +8303 -> 19224
    //   10924: iconst_0
    //   10925: wide
    //   10929: wide
    //   10933: astore 5
    //   10935: wide
    //   10939: istore 6
    //   10941: wide
    //   10945: wide
    //   10949: wide
    //   10953: wide
    //   10957: wide
    //   10961: wide
    //   10965: wide
    //   10969: wide
    //   10973: caload
    //   10974: istore 31
    //   10976: iload 6
    //   10978: iconst_5
    //   10979: irem
    //   10980: tableswitch	default:+32 -> 11012, 0:+7240->18220, 1:+7249->18229, 2:+7258->18238, 3:+7267->18247
    //   11013: dup_x1
    //   11014: wide
    //   11018: wide
    //   11022: iload 31
    //   11024: ixor
    //   11025: i2c
    //   11026: wide
    //   11030: wide
    //   11034: wide
    //   11038: wide
    //   11042: castore
    //   11043: iload 6
    //   11045: iconst_1
    //   11046: iadd
    //   11047: wide
    //   11051: wide
    //   11055: ifne +28 -> 11083
    //   11058: aload 5
    //   11060: wide
    //   11064: wide
    //   11068: wide
    //   11072: wide
    //   11076: wide
    //   11080: goto -115 -> 10965
    //   11083: wide
    //   11087: wide
    //   11091: aload 5
    //   11093: wide
    //   11097: wide
    //   11101: wide
    //   11105: if_icmpgt -176 -> 10929
    //   11108: new 41	java/lang/String
    //   11111: dup
    //   11112: wide
    //   11116: invokespecial 51	java/lang/String:<init>	([C)V
    //   11119: invokevirtual 55	java/lang/String:intern	()Ljava/lang/String;
    //   11122: wide
    //   11126: aload_1
    //   11127: wide
    //   11131: wide
    //   11135: aastore
    //   11136: bipush 53
    //   11138: wide
    //   11142: ldc 161
    //   11144: invokevirtual 47	java/lang/String:toCharArray	()[C
    //   11147: wide
    //   11151: wide
    //   11155: arraylength
    //   11156: wide
    //   11160: wide
    //   11164: iconst_1
    //   11165: if_icmpgt +8051 -> 19216
    //   11168: iconst_0
    //   11169: wide
    //   11173: wide
    //   11177: astore 5
    //   11179: wide
    //   11183: istore 6
    //   11185: wide
    //   11189: wide
    //   11193: wide
    //   11197: wide
    //   11201: wide
    //   11205: wide
    //   11209: wide
    //   11213: wide
    //   11217: caload
    //   11218: istore 31
    //   11220: iload 6
    //   11222: iconst_5
    //   11223: irem
    //   11224: tableswitch	default:+32 -> 11256, 0:+7032->18256, 1:+7041->18265, 2:+7050->18274, 3:+7059->18283
    //   11257: dup_x1
    //   11258: wide
    //   11262: wide
    //   11266: iload 31
    //   11268: ixor
    //   11269: i2c
    //   11270: wide
    //   11274: wide
    //   11278: wide
    //   11282: wide
    //   11286: castore
    //   11287: iload 6
    //   11289: iconst_1
    //   11290: iadd
    //   11291: wide
    //   11295: wide
    //   11299: ifne +28 -> 11327
    //   11302: aload 5
    //   11304: wide
    //   11308: wide
    //   11312: wide
    //   11316: wide
    //   11320: wide
    //   11324: goto -115 -> 11209
    //   11327: wide
    //   11331: wide
    //   11335: aload 5
    //   11337: wide
    //   11341: wide
    //   11345: wide
    //   11349: if_icmpgt -176 -> 11173
    //   11352: new 41	java/lang/String
    //   11355: dup
    //   11356: wide
    //   11360: invokespecial 51	java/lang/String:<init>	([C)V
    //   11363: invokevirtual 55	java/lang/String:intern	()Ljava/lang/String;
    //   11366: wide
    //   11370: aload_1
    //   11371: wide
    //   11375: wide
    //   11379: aastore
    //   11380: bipush 54
    //   11382: wide
    //   11386: ldc 163
    //   11388: invokevirtual 47	java/lang/String:toCharArray	()[C
    //   11391: wide
    //   11395: wide
    //   11399: arraylength
    //   11400: wide
    //   11404: wide
    //   11408: iconst_1
    //   11409: if_icmpgt +7799 -> 19208
    //   11412: iconst_0
    //   11413: wide
    //   11417: wide
    //   11421: astore 5
    //   11423: wide
    //   11427: istore 6
    //   11429: wide
    //   11433: wide
    //   11437: wide
    //   11441: wide
    //   11445: wide
    //   11449: wide
    //   11453: wide
    //   11457: wide
    //   11461: caload
    //   11462: istore 31
    //   11464: iload 6
    //   11466: iconst_5
    //   11467: irem
    //   11468: tableswitch	default:+32 -> 11500, 0:+6824->18292, 1:+6833->18301, 2:+6842->18310, 3:+6851->18319
    //   11501: dup_x1
    //   11502: wide
    //   11506: wide
    //   11510: iload 31
    //   11512: ixor
    //   11513: i2c
    //   11514: wide
    //   11518: wide
    //   11522: wide
    //   11526: wide
    //   11530: castore
    //   11531: iload 6
    //   11533: iconst_1
    //   11534: iadd
    //   11535: wide
    //   11539: wide
    //   11543: ifne +28 -> 11571
    //   11546: aload 5
    //   11548: wide
    //   11552: wide
    //   11556: wide
    //   11560: wide
    //   11564: wide
    //   11568: goto -115 -> 11453
    //   11571: wide
    //   11575: wide
    //   11579: aload 5
    //   11581: wide
    //   11585: wide
    //   11589: wide
    //   11593: if_icmpgt -176 -> 11417
    //   11596: new 41	java/lang/String
    //   11599: dup
    //   11600: wide
    //   11604: invokespecial 51	java/lang/String:<init>	([C)V
    //   11607: invokevirtual 55	java/lang/String:intern	()Ljava/lang/String;
    //   11610: wide
    //   11614: aload_1
    //   11615: wide
    //   11619: wide
    //   11623: aastore
    //   11624: bipush 55
    //   11626: wide
    //   11630: ldc 165
    //   11632: invokevirtual 47	java/lang/String:toCharArray	()[C
    //   11635: wide
    //   11639: wide
    //   11643: arraylength
    //   11644: wide
    //   11648: wide
    //   11652: iconst_1
    //   11653: if_icmpgt +7547 -> 19200
    //   11656: iconst_0
    //   11657: wide
    //   11661: wide
    //   11665: astore 5
    //   11667: wide
    //   11671: istore 6
    //   11673: wide
    //   11677: wide
    //   11681: wide
    //   11685: wide
    //   11689: wide
    //   11693: wide
    //   11697: wide
    //   11701: wide
    //   11705: caload
    //   11706: istore 31
    //   11708: iload 6
    //   11710: iconst_5
    //   11711: irem
    //   11712: tableswitch	default:+32 -> 11744, 0:+6616->18328, 1:+6625->18337, 2:+6634->18346, 3:+6643->18355
    //   11745: dup_x1
    //   11746: wide
    //   11750: wide
    //   11754: iload 31
    //   11756: ixor
    //   11757: i2c
    //   11758: wide
    //   11762: wide
    //   11766: wide
    //   11770: wide
    //   11774: castore
    //   11775: iload 6
    //   11777: iconst_1
    //   11778: iadd
    //   11779: wide
    //   11783: wide
    //   11787: ifne +28 -> 11815
    //   11790: aload 5
    //   11792: wide
    //   11796: wide
    //   11800: wide
    //   11804: wide
    //   11808: wide
    //   11812: goto -115 -> 11697
    //   11815: wide
    //   11819: wide
    //   11823: aload 5
    //   11825: wide
    //   11829: wide
    //   11833: wide
    //   11837: if_icmpgt -176 -> 11661
    //   11840: new 41	java/lang/String
    //   11843: dup
    //   11844: wide
    //   11848: invokespecial 51	java/lang/String:<init>	([C)V
    //   11851: invokevirtual 55	java/lang/String:intern	()Ljava/lang/String;
    //   11854: wide
    //   11858: aload_1
    //   11859: wide
    //   11863: wide
    //   11867: aastore
    //   11868: bipush 56
    //   11870: wide
    //   11874: ldc 167
    //   11876: invokevirtual 47	java/lang/String:toCharArray	()[C
    //   11879: wide
    //   11883: wide
    //   11887: arraylength
    //   11888: wide
    //   11892: wide
    //   11896: iconst_1
    //   11897: if_icmpgt +7295 -> 19192
    //   11900: iconst_0
    //   11901: wide
    //   11905: wide
    //   11909: astore 5
    //   11911: wide
    //   11915: istore 6
    //   11917: wide
    //   11921: wide
    //   11925: wide
    //   11929: wide
    //   11933: wide
    //   11937: wide
    //   11941: wide
    //   11945: wide
    //   11949: caload
    //   11950: istore 31
    //   11952: iload 6
    //   11954: iconst_5
    //   11955: irem
    //   11956: tableswitch	default:+32 -> 11988, 0:+6408->18364, 1:+6417->18373, 2:+6426->18382, 3:+6435->18391
    //   11989: dup_x1
    //   11990: wide
    //   11994: wide
    //   11998: iload 31
    //   12000: ixor
    //   12001: i2c
    //   12002: wide
    //   12006: wide
    //   12010: wide
    //   12014: wide
    //   12018: castore
    //   12019: iload 6
    //   12021: iconst_1
    //   12022: iadd
    //   12023: wide
    //   12027: wide
    //   12031: ifne +28 -> 12059
    //   12034: aload 5
    //   12036: wide
    //   12040: wide
    //   12044: wide
    //   12048: wide
    //   12052: wide
    //   12056: goto -115 -> 11941
    //   12059: wide
    //   12063: wide
    //   12067: aload 5
    //   12069: wide
    //   12073: wide
    //   12077: wide
    //   12081: if_icmpgt -176 -> 11905
    //   12084: new 41	java/lang/String
    //   12087: dup
    //   12088: wide
    //   12092: invokespecial 51	java/lang/String:<init>	([C)V
    //   12095: invokevirtual 55	java/lang/String:intern	()Ljava/lang/String;
    //   12098: wide
    //   12102: aload_1
    //   12103: wide
    //   12107: wide
    //   12111: aastore
    //   12112: bipush 57
    //   12114: wide
    //   12118: ldc 169
    //   12120: invokevirtual 47	java/lang/String:toCharArray	()[C
    //   12123: wide
    //   12127: wide
    //   12131: arraylength
    //   12132: wide
    //   12136: wide
    //   12140: iconst_1
    //   12141: if_icmpgt +7043 -> 19184
    //   12144: iconst_0
    //   12145: wide
    //   12149: wide
    //   12153: astore 5
    //   12155: wide
    //   12159: istore 6
    //   12161: wide
    //   12165: wide
    //   12169: wide
    //   12173: wide
    //   12177: wide
    //   12181: wide
    //   12185: wide
    //   12189: wide
    //   12193: caload
    //   12194: istore 31
    //   12196: iload 6
    //   12198: iconst_5
    //   12199: irem
    //   12200: tableswitch	default:+32 -> 12232, 0:+6200->18400, 1:+6209->18409, 2:+6218->18418, 3:+6227->18427
    //   12233: dup_x1
    //   12234: wide
    //   12238: wide
    //   12242: iload 31
    //   12244: ixor
    //   12245: i2c
    //   12246: wide
    //   12250: wide
    //   12254: wide
    //   12258: wide
    //   12262: castore
    //   12263: iload 6
    //   12265: iconst_1
    //   12266: iadd
    //   12267: wide
    //   12271: wide
    //   12275: ifne +28 -> 12303
    //   12278: aload 5
    //   12280: wide
    //   12284: wide
    //   12288: wide
    //   12292: wide
    //   12296: wide
    //   12300: goto -115 -> 12185
    //   12303: wide
    //   12307: wide
    //   12311: aload 5
    //   12313: wide
    //   12317: wide
    //   12321: wide
    //   12325: if_icmpgt -176 -> 12149
    //   12328: new 41	java/lang/String
    //   12331: dup
    //   12332: wide
    //   12336: invokespecial 51	java/lang/String:<init>	([C)V
    //   12339: invokevirtual 55	java/lang/String:intern	()Ljava/lang/String;
    //   12342: wide
    //   12346: aload_1
    //   12347: wide
    //   12351: wide
    //   12355: aastore
    //   12356: bipush 58
    //   12358: wide
    //   12362: ldc 171
    //   12364: invokevirtual 47	java/lang/String:toCharArray	()[C
    //   12367: wide
    //   12371: wide
    //   12375: arraylength
    //   12376: wide
    //   12380: wide
    //   12384: iconst_1
    //   12385: if_icmpgt +6791 -> 19176
    //   12388: iconst_0
    //   12389: wide
    //   12393: wide
    //   12397: astore 5
    //   12399: wide
    //   12403: istore 6
    //   12405: wide
    //   12409: wide
    //   12413: wide
    //   12417: wide
    //   12421: wide
    //   12425: wide
    //   12429: wide
    //   12433: wide
    //   12437: caload
    //   12438: istore 31
    //   12440: iload 6
    //   12442: iconst_5
    //   12443: irem
    //   12444: tableswitch	default:+32 -> 12476, 0:+5992->18436, 1:+6001->18445, 2:+6010->18454, 3:+6019->18463
    //   12477: dup_x1
    //   12478: wide
    //   12482: wide
    //   12486: iload 31
    //   12488: ixor
    //   12489: i2c
    //   12490: wide
    //   12494: wide
    //   12498: wide
    //   12502: wide
    //   12506: castore
    //   12507: iload 6
    //   12509: iconst_1
    //   12510: iadd
    //   12511: wide
    //   12515: wide
    //   12519: ifne +28 -> 12547
    //   12522: aload 5
    //   12524: wide
    //   12528: wide
    //   12532: wide
    //   12536: wide
    //   12540: wide
    //   12544: goto -115 -> 12429
    //   12547: wide
    //   12551: wide
    //   12555: aload 5
    //   12557: wide
    //   12561: wide
    //   12565: wide
    //   12569: if_icmpgt -176 -> 12393
    //   12572: new 41	java/lang/String
    //   12575: dup
    //   12576: wide
    //   12580: invokespecial 51	java/lang/String:<init>	([C)V
    //   12583: invokevirtual 55	java/lang/String:intern	()Ljava/lang/String;
    //   12586: wide
    //   12590: aload_1
    //   12591: wide
    //   12595: wide
    //   12599: aastore
    //   12600: bipush 59
    //   12602: wide
    //   12606: ldc 173
    //   12608: invokevirtual 47	java/lang/String:toCharArray	()[C
    //   12611: wide
    //   12615: wide
    //   12619: arraylength
    //   12620: wide
    //   12624: wide
    //   12628: iconst_1
    //   12629: if_icmpgt +6539 -> 19168
    //   12632: iconst_0
    //   12633: wide
    //   12637: wide
    //   12641: astore 5
    //   12643: wide
    //   12647: istore 6
    //   12649: wide
    //   12653: wide
    //   12657: wide
    //   12661: wide
    //   12665: wide
    //   12669: wide
    //   12673: wide
    //   12677: wide
    //   12681: caload
    //   12682: istore 31
    //   12684: iload 6
    //   12686: iconst_5
    //   12687: irem
    //   12688: tableswitch	default:+32 -> 12720, 0:+5784->18472, 1:+5793->18481, 2:+5802->18490, 3:+5811->18499
    //   12721: dup_x1
    //   12722: wide
    //   12726: wide
    //   12730: iload 31
    //   12732: ixor
    //   12733: i2c
    //   12734: wide
    //   12738: wide
    //   12742: wide
    //   12746: wide
    //   12750: castore
    //   12751: iload 6
    //   12753: iconst_1
    //   12754: iadd
    //   12755: wide
    //   12759: wide
    //   12763: ifne +28 -> 12791
    //   12766: aload 5
    //   12768: wide
    //   12772: wide
    //   12776: wide
    //   12780: wide
    //   12784: wide
    //   12788: goto -115 -> 12673
    //   12791: wide
    //   12795: wide
    //   12799: aload 5
    //   12801: wide
    //   12805: wide
    //   12809: wide
    //   12813: if_icmpgt -176 -> 12637
    //   12816: new 41	java/lang/String
    //   12819: dup
    //   12820: wide
    //   12824: invokespecial 51	java/lang/String:<init>	([C)V
    //   12827: invokevirtual 55	java/lang/String:intern	()Ljava/lang/String;
    //   12830: wide
    //   12834: aload_1
    //   12835: wide
    //   12839: wide
    //   12843: aastore
    //   12844: bipush 60
    //   12846: wide
    //   12850: ldc 175
    //   12852: invokevirtual 47	java/lang/String:toCharArray	()[C
    //   12855: wide
    //   12859: wide
    //   12863: arraylength
    //   12864: wide
    //   12868: wide
    //   12872: iconst_1
    //   12873: if_icmpgt +6287 -> 19160
    //   12876: iconst_0
    //   12877: wide
    //   12881: wide
    //   12885: astore 5
    //   12887: wide
    //   12891: istore 6
    //   12893: wide
    //   12897: wide
    //   12901: wide
    //   12905: wide
    //   12909: wide
    //   12913: wide
    //   12917: wide
    //   12921: wide
    //   12925: caload
    //   12926: istore 31
    //   12928: iload 6
    //   12930: iconst_5
    //   12931: irem
    //   12932: tableswitch	default:+32 -> 12964, 0:+5576->18508, 1:+5585->18517, 2:+5594->18526, 3:+5603->18535
    //   12965: dup_x1
    //   12966: wide
    //   12970: wide
    //   12974: iload 31
    //   12976: ixor
    //   12977: i2c
    //   12978: wide
    //   12982: wide
    //   12986: wide
    //   12990: wide
    //   12994: castore
    //   12995: iload 6
    //   12997: iconst_1
    //   12998: iadd
    //   12999: wide
    //   13003: wide
    //   13007: ifne +28 -> 13035
    //   13010: aload 5
    //   13012: wide
    //   13016: wide
    //   13020: wide
    //   13024: wide
    //   13028: wide
    //   13032: goto -115 -> 12917
    //   13035: wide
    //   13039: wide
    //   13043: aload 5
    //   13045: wide
    //   13049: wide
    //   13053: wide
    //   13057: if_icmpgt -176 -> 12881
    //   13060: new 41	java/lang/String
    //   13063: dup
    //   13064: wide
    //   13068: invokespecial 51	java/lang/String:<init>	([C)V
    //   13071: invokevirtual 55	java/lang/String:intern	()Ljava/lang/String;
    //   13074: wide
    //   13078: aload_1
    //   13079: wide
    //   13083: wide
    //   13087: aastore
    //   13088: bipush 61
    //   13090: wide
    //   13094: ldc 177
    //   13096: invokevirtual 47	java/lang/String:toCharArray	()[C
    //   13099: wide
    //   13103: wide
    //   13107: arraylength
    //   13108: wide
    //   13112: wide
    //   13116: iconst_1
    //   13117: if_icmpgt +6035 -> 19152
    //   13120: iconst_0
    //   13121: wide
    //   13125: wide
    //   13129: astore 5
    //   13131: wide
    //   13135: istore 6
    //   13137: wide
    //   13141: wide
    //   13145: wide
    //   13149: wide
    //   13153: wide
    //   13157: wide
    //   13161: wide
    //   13165: wide
    //   13169: caload
    //   13170: istore 31
    //   13172: iload 6
    //   13174: iconst_5
    //   13175: irem
    //   13176: tableswitch	default:+32 -> 13208, 0:+5368->18544, 1:+5377->18553, 2:+5386->18562, 3:+5395->18571
    //   13209: dup_x1
    //   13210: wide
    //   13214: wide
    //   13218: iload 31
    //   13220: ixor
    //   13221: i2c
    //   13222: wide
    //   13226: wide
    //   13230: wide
    //   13234: wide
    //   13238: castore
    //   13239: iload 6
    //   13241: iconst_1
    //   13242: iadd
    //   13243: wide
    //   13247: wide
    //   13251: ifne +28 -> 13279
    //   13254: aload 5
    //   13256: wide
    //   13260: wide
    //   13264: wide
    //   13268: wide
    //   13272: wide
    //   13276: goto -115 -> 13161
    //   13279: wide
    //   13283: wide
    //   13287: aload 5
    //   13289: wide
    //   13293: wide
    //   13297: wide
    //   13301: if_icmpgt -176 -> 13125
    //   13304: new 41	java/lang/String
    //   13307: dup
    //   13308: wide
    //   13312: invokespecial 51	java/lang/String:<init>	([C)V
    //   13315: invokevirtual 55	java/lang/String:intern	()Ljava/lang/String;
    //   13318: wide
    //   13322: aload_1
    //   13323: wide
    //   13327: wide
    //   13331: aastore
    //   13332: bipush 62
    //   13334: wide
    //   13338: ldc 179
    //   13340: invokevirtual 47	java/lang/String:toCharArray	()[C
    //   13343: wide
    //   13347: wide
    //   13351: arraylength
    //   13352: wide
    //   13356: wide
    //   13360: iconst_1
    //   13361: if_icmpgt +5783 -> 19144
    //   13364: iconst_0
    //   13365: wide
    //   13369: wide
    //   13373: astore 5
    //   13375: wide
    //   13379: istore 6
    //   13381: wide
    //   13385: wide
    //   13389: wide
    //   13393: wide
    //   13397: wide
    //   13401: wide
    //   13405: wide
    //   13409: wide
    //   13413: caload
    //   13414: istore 31
    //   13416: iload 6
    //   13418: iconst_5
    //   13419: irem
    //   13420: tableswitch	default:+32 -> 13452, 0:+5160->18580, 1:+5169->18589, 2:+5178->18598, 3:+5187->18607
    //   13453: dup_x1
    //   13454: wide
    //   13458: wide
    //   13462: iload 31
    //   13464: ixor
    //   13465: i2c
    //   13466: wide
    //   13470: wide
    //   13474: wide
    //   13478: wide
    //   13482: castore
    //   13483: iload 6
    //   13485: iconst_1
    //   13486: iadd
    //   13487: wide
    //   13491: wide
    //   13495: ifne +28 -> 13523
    //   13498: aload 5
    //   13500: wide
    //   13504: wide
    //   13508: wide
    //   13512: wide
    //   13516: wide
    //   13520: goto -115 -> 13405
    //   13523: wide
    //   13527: wide
    //   13531: aload 5
    //   13533: wide
    //   13537: wide
    //   13541: wide
    //   13545: if_icmpgt -176 -> 13369
    //   13548: new 41	java/lang/String
    //   13551: dup
    //   13552: wide
    //   13556: invokespecial 51	java/lang/String:<init>	([C)V
    //   13559: invokevirtual 55	java/lang/String:intern	()Ljava/lang/String;
    //   13562: wide
    //   13566: aload_1
    //   13567: wide
    //   13571: wide
    //   13575: aastore
    //   13576: bipush 63
    //   13578: wide
    //   13582: ldc 181
    //   13584: invokevirtual 47	java/lang/String:toCharArray	()[C
    //   13587: wide
    //   13591: wide
    //   13595: arraylength
    //   13596: wide
    //   13600: wide
    //   13604: iconst_1
    //   13605: if_icmpgt +5531 -> 19136
    //   13608: iconst_0
    //   13609: wide
    //   13613: wide
    //   13617: astore 5
    //   13619: wide
    //   13623: istore 6
    //   13625: wide
    //   13629: wide
    //   13633: wide
    //   13637: wide
    //   13641: wide
    //   13645: wide
    //   13649: wide
    //   13653: wide
    //   13657: caload
    //   13658: istore 31
    //   13660: iload 6
    //   13662: iconst_5
    //   13663: irem
    //   13664: tableswitch	default:+32 -> 13696, 0:+4952->18616, 1:+4961->18625, 2:+4970->18634, 3:+4979->18643
    //   13697: dup_x1
    //   13698: wide
    //   13702: wide
    //   13706: iload 31
    //   13708: ixor
    //   13709: i2c
    //   13710: wide
    //   13714: wide
    //   13718: wide
    //   13722: wide
    //   13726: castore
    //   13727: iload 6
    //   13729: iconst_1
    //   13730: iadd
    //   13731: wide
    //   13735: wide
    //   13739: ifne +28 -> 13767
    //   13742: aload 5
    //   13744: wide
    //   13748: wide
    //   13752: wide
    //   13756: wide
    //   13760: wide
    //   13764: goto -115 -> 13649
    //   13767: wide
    //   13771: wide
    //   13775: aload 5
    //   13777: wide
    //   13781: wide
    //   13785: wide
    //   13789: if_icmpgt -176 -> 13613
    //   13792: new 41	java/lang/String
    //   13795: dup
    //   13796: wide
    //   13800: invokespecial 51	java/lang/String:<init>	([C)V
    //   13803: invokevirtual 55	java/lang/String:intern	()Ljava/lang/String;
    //   13806: wide
    //   13810: aload_1
    //   13811: wide
    //   13815: wide
    //   13819: aastore
    //   13820: bipush 64
    //   13822: wide
    //   13826: ldc 183
    //   13828: invokevirtual 47	java/lang/String:toCharArray	()[C
    //   13831: wide
    //   13835: wide
    //   13839: arraylength
    //   13840: wide
    //   13844: wide
    //   13848: iconst_1
    //   13849: if_icmpgt +5279 -> 19128
    //   13852: iconst_0
    //   13853: wide
    //   13857: wide
    //   13861: astore 5
    //   13863: wide
    //   13867: istore 6
    //   13869: wide
    //   13873: wide
    //   13877: wide
    //   13881: wide
    //   13885: wide
    //   13889: wide
    //   13893: wide
    //   13897: wide
    //   13901: caload
    //   13902: istore 31
    //   13904: iload 6
    //   13906: iconst_5
    //   13907: irem
    //   13908: tableswitch	default:+32 -> 13940, 0:+4744->18652, 1:+4753->18661, 2:+4762->18670, 3:+4771->18679
    //   13941: dup_x1
    //   13942: wide
    //   13946: wide
    //   13950: iload 31
    //   13952: ixor
    //   13953: i2c
    //   13954: wide
    //   13958: wide
    //   13962: wide
    //   13966: wide
    //   13970: castore
    //   13971: iload 6
    //   13973: iconst_1
    //   13974: iadd
    //   13975: wide
    //   13979: wide
    //   13983: ifne +28 -> 14011
    //   13986: aload 5
    //   13988: wide
    //   13992: wide
    //   13996: wide
    //   14000: wide
    //   14004: wide
    //   14008: goto -115 -> 13893
    //   14011: wide
    //   14015: wide
    //   14019: aload 5
    //   14021: wide
    //   14025: wide
    //   14029: wide
    //   14033: if_icmpgt -176 -> 13857
    //   14036: new 41	java/lang/String
    //   14039: dup
    //   14040: wide
    //   14044: invokespecial 51	java/lang/String:<init>	([C)V
    //   14047: invokevirtual 55	java/lang/String:intern	()Ljava/lang/String;
    //   14050: wide
    //   14054: aload_1
    //   14055: wide
    //   14059: wide
    //   14063: aastore
    //   14064: bipush 65
    //   14066: wide
    //   14070: ldc 185
    //   14072: invokevirtual 47	java/lang/String:toCharArray	()[C
    //   14075: wide
    //   14079: wide
    //   14083: arraylength
    //   14084: wide
    //   14088: wide
    //   14092: iconst_1
    //   14093: if_icmpgt +5027 -> 19120
    //   14096: iconst_0
    //   14097: wide
    //   14101: wide
    //   14105: astore 5
    //   14107: wide
    //   14111: istore 6
    //   14113: wide
    //   14117: wide
    //   14121: wide
    //   14125: wide
    //   14129: wide
    //   14133: wide
    //   14137: wide
    //   14141: wide
    //   14145: caload
    //   14146: istore 31
    //   14148: iload 6
    //   14150: iconst_5
    //   14151: irem
    //   14152: tableswitch	default:+32 -> 14184, 0:+4536->18688, 1:+4545->18697, 2:+4554->18706, 3:+4563->18715
    //   14185: dup_x1
    //   14186: wide
    //   14190: wide
    //   14194: iload 31
    //   14196: ixor
    //   14197: i2c
    //   14198: wide
    //   14202: wide
    //   14206: wide
    //   14210: wide
    //   14214: castore
    //   14215: iload 6
    //   14217: iconst_1
    //   14218: iadd
    //   14219: wide
    //   14223: wide
    //   14227: ifne +28 -> 14255
    //   14230: aload 5
    //   14232: wide
    //   14236: wide
    //   14240: wide
    //   14244: wide
    //   14248: wide
    //   14252: goto -115 -> 14137
    //   14255: wide
    //   14259: wide
    //   14263: aload 5
    //   14265: wide
    //   14269: wide
    //   14273: wide
    //   14277: if_icmpgt -176 -> 14101
    //   14280: new 41	java/lang/String
    //   14283: dup
    //   14284: wide
    //   14288: invokespecial 51	java/lang/String:<init>	([C)V
    //   14291: invokevirtual 55	java/lang/String:intern	()Ljava/lang/String;
    //   14294: wide
    //   14298: aload_1
    //   14299: wide
    //   14303: wide
    //   14307: aastore
    //   14308: bipush 66
    //   14310: wide
    //   14314: ldc 187
    //   14316: invokevirtual 47	java/lang/String:toCharArray	()[C
    //   14319: wide
    //   14323: wide
    //   14327: arraylength
    //   14328: wide
    //   14332: wide
    //   14336: iconst_1
    //   14337: if_icmpgt +4775 -> 19112
    //   14340: iconst_0
    //   14341: wide
    //   14345: wide
    //   14349: astore 5
    //   14351: wide
    //   14355: istore 6
    //   14357: wide
    //   14361: wide
    //   14365: wide
    //   14369: wide
    //   14373: wide
    //   14377: wide
    //   14381: wide
    //   14385: wide
    //   14389: caload
    //   14390: istore 31
    //   14392: iload 6
    //   14394: iconst_5
    //   14395: irem
    //   14396: tableswitch	default:+32 -> 14428, 0:+4328->18724, 1:+4337->18733, 2:+4346->18742, 3:+4355->18751
    //   14429: dup_x1
    //   14430: wide
    //   14434: wide
    //   14438: iload 31
    //   14440: ixor
    //   14441: i2c
    //   14442: wide
    //   14446: wide
    //   14450: wide
    //   14454: wide
    //   14458: castore
    //   14459: iload 6
    //   14461: iconst_1
    //   14462: iadd
    //   14463: wide
    //   14467: wide
    //   14471: ifne +28 -> 14499
    //   14474: aload 5
    //   14476: wide
    //   14480: wide
    //   14484: wide
    //   14488: wide
    //   14492: wide
    //   14496: goto -115 -> 14381
    //   14499: wide
    //   14503: wide
    //   14507: aload 5
    //   14509: wide
    //   14513: wide
    //   14517: wide
    //   14521: if_icmpgt -176 -> 14345
    //   14524: new 41	java/lang/String
    //   14527: dup
    //   14528: wide
    //   14532: invokespecial 51	java/lang/String:<init>	([C)V
    //   14535: invokevirtual 55	java/lang/String:intern	()Ljava/lang/String;
    //   14538: wide
    //   14542: aload_1
    //   14543: wide
    //   14547: wide
    //   14551: aastore
    //   14552: bipush 67
    //   14554: wide
    //   14558: ldc 189
    //   14560: invokevirtual 47	java/lang/String:toCharArray	()[C
    //   14563: wide
    //   14567: wide
    //   14571: arraylength
    //   14572: wide
    //   14576: wide
    //   14580: iconst_1
    //   14581: if_icmpgt +4523 -> 19104
    //   14584: iconst_0
    //   14585: wide
    //   14589: wide
    //   14593: astore 5
    //   14595: wide
    //   14599: istore 6
    //   14601: wide
    //   14605: wide
    //   14609: wide
    //   14613: wide
    //   14617: wide
    //   14621: wide
    //   14625: wide
    //   14629: wide
    //   14633: caload
    //   14634: istore 31
    //   14636: iload 6
    //   14638: iconst_5
    //   14639: irem
    //   14640: tableswitch	default:+32 -> 14672, 0:+4120->18760, 1:+4129->18769, 2:+4138->18778, 3:+4147->18787
    //   14673: dup_x1
    //   14674: wide
    //   14678: wide
    //   14682: iload 31
    //   14684: ixor
    //   14685: i2c
    //   14686: wide
    //   14690: wide
    //   14694: wide
    //   14698: wide
    //   14702: castore
    //   14703: iload 6
    //   14705: iconst_1
    //   14706: iadd
    //   14707: wide
    //   14711: wide
    //   14715: ifne +28 -> 14743
    //   14718: aload 5
    //   14720: wide
    //   14724: wide
    //   14728: wide
    //   14732: wide
    //   14736: wide
    //   14740: goto -115 -> 14625
    //   14743: wide
    //   14747: wide
    //   14751: aload 5
    //   14753: wide
    //   14757: wide
    //   14761: wide
    //   14765: if_icmpgt -176 -> 14589
    //   14768: new 41	java/lang/String
    //   14771: dup
    //   14772: wide
    //   14776: invokespecial 51	java/lang/String:<init>	([C)V
    //   14779: invokevirtual 55	java/lang/String:intern	()Ljava/lang/String;
    //   14782: wide
    //   14786: aload_1
    //   14787: wide
    //   14791: wide
    //   14795: aastore
    //   14796: bipush 68
    //   14798: wide
    //   14802: ldc 191
    //   14804: invokevirtual 47	java/lang/String:toCharArray	()[C
    //   14807: wide
    //   14811: wide
    //   14815: arraylength
    //   14816: wide
    //   14820: wide
    //   14824: iconst_1
    //   14825: if_icmpgt +4271 -> 19096
    //   14828: iconst_0
    //   14829: wide
    //   14833: wide
    //   14837: astore 5
    //   14839: wide
    //   14843: istore 6
    //   14845: wide
    //   14849: wide
    //   14853: wide
    //   14857: wide
    //   14861: wide
    //   14865: wide
    //   14869: wide
    //   14873: wide
    //   14877: caload
    //   14878: istore 31
    //   14880: iload 6
    //   14882: iconst_5
    //   14883: irem
    //   14884: tableswitch	default:+32 -> 14916, 0:+3912->18796, 1:+3921->18805, 2:+3930->18814, 3:+3939->18823
    //   14917: dup_x1
    //   14918: wide
    //   14922: wide
    //   14926: iload 31
    //   14928: ixor
    //   14929: i2c
    //   14930: wide
    //   14934: wide
    //   14938: wide
    //   14942: wide
    //   14946: castore
    //   14947: iload 6
    //   14949: iconst_1
    //   14950: iadd
    //   14951: wide
    //   14955: wide
    //   14959: ifne +28 -> 14987
    //   14962: aload 5
    //   14964: wide
    //   14968: wide
    //   14972: wide
    //   14976: wide
    //   14980: wide
    //   14984: goto -115 -> 14869
    //   14987: wide
    //   14991: wide
    //   14995: aload 5
    //   14997: wide
    //   15001: wide
    //   15005: wide
    //   15009: if_icmpgt -176 -> 14833
    //   15012: new 41	java/lang/String
    //   15015: dup
    //   15016: wide
    //   15020: invokespecial 51	java/lang/String:<init>	([C)V
    //   15023: invokevirtual 55	java/lang/String:intern	()Ljava/lang/String;
    //   15026: wide
    //   15030: aload_1
    //   15031: wide
    //   15035: wide
    //   15039: aastore
    //   15040: bipush 69
    //   15042: wide
    //   15046: ldc 193
    //   15048: invokevirtual 47	java/lang/String:toCharArray	()[C
    //   15051: wide
    //   15055: wide
    //   15059: arraylength
    //   15060: wide
    //   15064: wide
    //   15068: iconst_1
    //   15069: if_icmpgt +4019 -> 19088
    //   15072: iconst_0
    //   15073: wide
    //   15077: wide
    //   15081: astore 5
    //   15083: wide
    //   15087: istore 6
    //   15089: wide
    //   15093: wide
    //   15097: wide
    //   15101: wide
    //   15105: wide
    //   15109: wide
    //   15113: wide
    //   15117: wide
    //   15121: caload
    //   15122: istore 31
    //   15124: iload 6
    //   15126: iconst_5
    //   15127: irem
    //   15128: tableswitch	default:+32 -> 15160, 0:+3704->18832, 1:+3713->18841, 2:+3722->18850, 3:+3731->18859
    //   15161: dup_x1
    //   15162: wide
    //   15166: wide
    //   15170: iload 31
    //   15172: ixor
    //   15173: i2c
    //   15174: wide
    //   15178: wide
    //   15182: wide
    //   15186: wide
    //   15190: castore
    //   15191: iload 6
    //   15193: iconst_1
    //   15194: iadd
    //   15195: wide
    //   15199: wide
    //   15203: ifne +28 -> 15231
    //   15206: aload 5
    //   15208: wide
    //   15212: wide
    //   15216: wide
    //   15220: wide
    //   15224: wide
    //   15228: goto -115 -> 15113
    //   15231: wide
    //   15235: wide
    //   15239: aload 5
    //   15241: wide
    //   15245: wide
    //   15249: wide
    //   15253: if_icmpgt -176 -> 15077
    //   15256: new 41	java/lang/String
    //   15259: dup
    //   15260: wide
    //   15264: invokespecial 51	java/lang/String:<init>	([C)V
    //   15267: invokevirtual 55	java/lang/String:intern	()Ljava/lang/String;
    //   15270: wide
    //   15274: aload_1
    //   15275: wide
    //   15279: wide
    //   15283: aastore
    //   15284: ldc 195
    //   15286: invokevirtual 47	java/lang/String:toCharArray	()[C
    //   15289: wide
    //   15293: wide
    //   15297: arraylength
    //   15298: wide
    //   15302: wide
    //   15306: iconst_1
    //   15307: if_icmpgt +3773 -> 19080
    //   15310: iconst_0
    //   15311: wide
    //   15315: wide
    //   15319: astore 5
    //   15321: wide
    //   15325: istore 6
    //   15327: wide
    //   15331: wide
    //   15335: wide
    //   15339: wide
    //   15343: wide
    //   15347: wide
    //   15351: wide
    //   15355: wide
    //   15359: caload
    //   15360: wide
    //   15364: iload 6
    //   15366: iconst_5
    //   15367: irem
    //   15368: tableswitch	default:+32 -> 15400, 0:+3500->18868, 1:+3509->18877, 2:+3518->18886, 3:+3527->18895
    //   15401: dup_x1
    //   15402: wide
    //   15406: wide
    //   15410: wide
    //   15414: ixor
    //   15415: i2c
    //   15416: wide
    //   15420: wide
    //   15424: wide
    //   15428: wide
    //   15432: castore
    //   15433: iload 6
    //   15435: iconst_1
    //   15436: iadd
    //   15437: wide
    //   15441: wide
    //   15445: ifne +28 -> 15473
    //   15448: aload 5
    //   15450: wide
    //   15454: wide
    //   15458: wide
    //   15462: wide
    //   15466: wide
    //   15470: goto -119 -> 15351
    //   15473: wide
    //   15477: wide
    //   15481: aload 5
    //   15483: wide
    //   15487: wide
    //   15491: wide
    //   15495: if_icmpgt -180 -> 15315
    //   15498: new 41	java/lang/String
    //   15501: dup
    //   15502: wide
    //   15506: invokespecial 51	java/lang/String:<init>	([C)V
    //   15509: invokevirtual 55	java/lang/String:intern	()Ljava/lang/String;
    //   15512: wide
    //   15516: aload_1
    //   15517: bipush 70
    //   15519: wide
    //   15523: aastore
    //   15524: bipush 71
    //   15526: wide
    //   15530: ldc 197
    //   15532: invokevirtual 47	java/lang/String:toCharArray	()[C
    //   15535: wide
    //   15539: wide
    //   15543: arraylength
    //   15544: wide
    //   15548: wide
    //   15552: iconst_1
    //   15553: if_icmpgt +3519 -> 19072
    //   15556: iconst_0
    //   15557: wide
    //   15561: wide
    //   15565: astore 5
    //   15567: wide
    //   15571: istore 6
    //   15573: wide
    //   15577: wide
    //   15581: wide
    //   15585: wide
    //   15589: wide
    //   15593: wide
    //   15597: wide
    //   15601: wide
    //   15605: caload
    //   15606: istore 31
    //   15608: iload 6
    //   15610: iconst_5
    //   15611: irem
    //   15612: tableswitch	default:+32 -> 15644, 0:+3292->18904, 1:+3301->18913, 2:+3310->18922, 3:+3319->18931
    //   15645: dup_x1
    //   15646: wide
    //   15650: wide
    //   15654: iload 31
    //   15656: ixor
    //   15657: i2c
    //   15658: wide
    //   15662: wide
    //   15666: wide
    //   15670: wide
    //   15674: castore
    //   15675: iload 6
    //   15677: iconst_1
    //   15678: iadd
    //   15679: wide
    //   15683: wide
    //   15687: ifne +28 -> 15715
    //   15690: aload 5
    //   15692: wide
    //   15696: wide
    //   15700: wide
    //   15704: wide
    //   15708: wide
    //   15712: goto -115 -> 15597
    //   15715: wide
    //   15719: wide
    //   15723: aload 5
    //   15725: wide
    //   15729: wide
    //   15733: wide
    //   15737: if_icmpgt -176 -> 15561
    //   15740: new 41	java/lang/String
    //   15743: dup
    //   15744: wide
    //   15748: invokespecial 51	java/lang/String:<init>	([C)V
    //   15751: invokevirtual 55	java/lang/String:intern	()Ljava/lang/String;
    //   15754: wide
    //   15758: aload_1
    //   15759: wide
    //   15763: wide
    //   15767: aastore
    //   15768: bipush 72
    //   15770: wide
    //   15774: ldc 199
    //   15776: invokevirtual 47	java/lang/String:toCharArray	()[C
    //   15779: wide
    //   15783: wide
    //   15787: arraylength
    //   15788: wide
    //   15792: wide
    //   15796: iconst_1
    //   15797: if_icmpgt +3267 -> 19064
    //   15800: iconst_0
    //   15801: wide
    //   15805: wide
    //   15809: astore 5
    //   15811: wide
    //   15815: istore 6
    //   15817: wide
    //   15821: wide
    //   15825: wide
    //   15829: wide
    //   15833: wide
    //   15837: wide
    //   15841: wide
    //   15845: wide
    //   15849: caload
    //   15850: istore 31
    //   15852: iload 6
    //   15854: iconst_5
    //   15855: irem
    //   15856: tableswitch	default:+32 -> 15888, 0:+3084->18940, 1:+3093->18949, 2:+3102->18958, 3:+3111->18967
    //   15889: dup_x1
    //   15890: wide
    //   15894: wide
    //   15898: iload 31
    //   15900: ixor
    //   15901: i2c
    //   15902: wide
    //   15906: wide
    //   15910: wide
    //   15914: wide
    //   15918: castore
    //   15919: iload 6
    //   15921: iconst_1
    //   15922: iadd
    //   15923: wide
    //   15927: wide
    //   15931: ifne +28 -> 15959
    //   15934: aload 5
    //   15936: wide
    //   15940: wide
    //   15944: wide
    //   15948: wide
    //   15952: wide
    //   15956: goto -115 -> 15841
    //   15959: wide
    //   15963: wide
    //   15967: aload 5
    //   15969: wide
    //   15973: wide
    //   15977: wide
    //   15981: if_icmpgt -176 -> 15805
    //   15984: new 41	java/lang/String
    //   15987: dup
    //   15988: wide
    //   15992: invokespecial 51	java/lang/String:<init>	([C)V
    //   15995: invokevirtual 55	java/lang/String:intern	()Ljava/lang/String;
    //   15998: wide
    //   16002: aload_1
    //   16003: wide
    //   16007: wide
    //   16011: aastore
    //   16012: bipush 73
    //   16014: wide
    //   16018: ldc 201
    //   16020: invokevirtual 47	java/lang/String:toCharArray	()[C
    //   16023: wide
    //   16027: wide
    //   16031: arraylength
    //   16032: wide
    //   16036: wide
    //   16040: iconst_1
    //   16041: if_icmpgt +3015 -> 19056
    //   16044: iconst_0
    //   16045: wide
    //   16049: wide
    //   16053: astore 5
    //   16055: wide
    //   16059: istore 6
    //   16061: wide
    //   16065: wide
    //   16069: wide
    //   16073: wide
    //   16077: wide
    //   16081: wide
    //   16085: wide
    //   16089: wide
    //   16093: caload
    //   16094: istore 31
    //   16096: iload 6
    //   16098: iconst_5
    //   16099: irem
    //   16100: tableswitch	default:+32 -> 16132, 0:+2876->18976, 1:+2885->18985, 2:+2894->18994, 3:+2903->19003
    //   16133: dup_x1
    //   16134: wide
    //   16138: wide
    //   16142: iload 31
    //   16144: ixor
    //   16145: i2c
    //   16146: wide
    //   16150: wide
    //   16154: wide
    //   16158: wide
    //   16162: castore
    //   16163: iload 6
    //   16165: iconst_1
    //   16166: iadd
    //   16167: wide
    //   16171: wide
    //   16175: ifne +28 -> 16203
    //   16178: aload 5
    //   16180: wide
    //   16184: wide
    //   16188: wide
    //   16192: wide
    //   16196: wide
    //   16200: goto -115 -> 16085
    //   16203: wide
    //   16207: wide
    //   16211: aload 5
    //   16213: wide
    //   16217: wide
    //   16221: wide
    //   16225: if_icmpgt -176 -> 16049
    //   16228: new 41	java/lang/String
    //   16231: dup
    //   16232: wide
    //   16236: invokespecial 51	java/lang/String:<init>	([C)V
    //   16239: invokevirtual 55	java/lang/String:intern	()Ljava/lang/String;
    //   16242: wide
    //   16246: aload_1
    //   16247: wide
    //   16251: wide
    //   16255: aastore
    //   16256: bipush 74
    //   16258: wide
    //   16262: ldc 203
    //   16264: invokevirtual 47	java/lang/String:toCharArray	()[C
    //   16267: wide
    //   16271: wide
    //   16275: arraylength
    //   16276: wide
    //   16280: wide
    //   16284: iconst_1
    //   16285: if_icmpgt +2763 -> 19048
    //   16288: iconst_0
    //   16289: wide
    //   16293: wide
    //   16297: astore 5
    //   16299: wide
    //   16303: istore 6
    //   16305: wide
    //   16309: wide
    //   16313: wide
    //   16317: wide
    //   16321: wide
    //   16325: wide
    //   16329: wide
    //   16333: wide
    //   16337: caload
    //   16338: istore 31
    //   16340: iload 6
    //   16342: iconst_5
    //   16343: irem
    //   16344: tableswitch	default:+32 -> 16376, 0:+2668->19012, 1:+2677->19021, 2:+2686->19030, 3:+2695->19039
    //   16377: dup_x1
    //   16378: wide
    //   16382: wide
    //   16386: iload 31
    //   16388: ixor
    //   16389: i2c
    //   16390: wide
    //   16394: wide
    //   16398: wide
    //   16402: wide
    //   16406: castore
    //   16407: iload 6
    //   16409: iconst_1
    //   16410: iadd
    //   16411: wide
    //   16415: wide
    //   16419: ifne +28 -> 16447
    //   16422: aload 5
    //   16424: wide
    //   16428: wide
    //   16432: wide
    //   16436: wide
    //   16440: wide
    //   16444: goto -115 -> 16329
    //   16447: wide
    //   16451: wide
    //   16455: aload 5
    //   16457: wide
    //   16461: wide
    //   16465: wide
    //   16469: if_icmpgt -176 -> 16293
    //   16472: new 41	java/lang/String
    //   16475: dup
    //   16476: wide
    //   16480: invokespecial 51	java/lang/String:<init>	([C)V
    //   16483: invokevirtual 55	java/lang/String:intern	()Ljava/lang/String;
    //   16486: wide
    //   16490: aload_1
    //   16491: wide
    //   16495: wide
    //   16499: aastore
    //   16500: aload_1
    //   16501: putstatic 205	com/skyhookwireless/_sdkfd:z	[Ljava/lang/String;
    //   16504: ldc 2
    //   16506: invokevirtual 211	java/lang/Class:desiredAssertionStatus	()Z
    //   16509: ifne +18 -> 16527
    //   16512: iload_0
    //   16513: putstatic 213	com/skyhookwireless/_sdkfd:_sdkt	Z
    //   16516: new 215	com/skyhookwireless/_sdknc
    //   16519: dup
    //   16520: invokespecial 217	com/skyhookwireless/_sdknc:<init>	()V
    //   16523: putstatic 219	com/skyhookwireless/_sdkfd:_sdke	Lcom/skyhookwireless/_sdknc;
    //   16526: return
    //   16527: iconst_0
    //   16528: istore_0
    //   16529: goto -17 -> 16512
    //   16532: bipush 7
    //   16534: istore 11
    //   16536: goto -16448 -> 88
    //   16539: bipush 70
    //   16541: istore 11
    //   16543: goto -16455 -> 88
    //   16546: bipush 51
    //   16548: istore 11
    //   16550: goto -16462 -> 88
    //   16553: bipush 73
    //   16555: istore 11
    //   16557: goto -16469 -> 88
    //   16560: bipush 7
    //   16562: istore 20
    //   16564: goto -16320 -> 244
    //   16567: bipush 70
    //   16569: istore 20
    //   16571: goto -16327 -> 244
    //   16574: bipush 51
    //   16576: istore 20
    //   16578: goto -16334 -> 244
    //   16581: bipush 73
    //   16583: istore 20
    //   16585: goto -16341 -> 244
    //   16588: bipush 7
    //   16590: istore 32
    //   16592: goto -16184 -> 408
    //   16595: bipush 70
    //   16597: istore 32
    //   16599: goto -16191 -> 408
    //   16602: bipush 51
    //   16604: istore 32
    //   16606: goto -16198 -> 408
    //   16609: bipush 73
    //   16611: istore 32
    //   16613: goto -16205 -> 408
    //   16616: bipush 7
    //   16618: istore 43
    //   16620: goto -16048 -> 572
    //   16623: bipush 70
    //   16625: istore 43
    //   16627: goto -16055 -> 572
    //   16630: bipush 51
    //   16632: istore 43
    //   16634: goto -16062 -> 572
    //   16637: bipush 73
    //   16639: istore 43
    //   16641: goto -16069 -> 572
    //   16644: bipush 7
    //   16646: istore 54
    //   16648: goto -15912 -> 736
    //   16651: bipush 70
    //   16653: istore 54
    //   16655: goto -15919 -> 736
    //   16658: bipush 51
    //   16660: istore 54
    //   16662: goto -15926 -> 736
    //   16665: bipush 73
    //   16667: istore 54
    //   16669: goto -15933 -> 736
    //   16672: bipush 7
    //   16674: istore 65
    //   16676: goto -15776 -> 900
    //   16679: bipush 70
    //   16681: istore 65
    //   16683: goto -15783 -> 900
    //   16686: bipush 51
    //   16688: istore 65
    //   16690: goto -15790 -> 900
    //   16693: bipush 73
    //   16695: istore 65
    //   16697: goto -15797 -> 900
    //   16700: bipush 7
    //   16702: istore 76
    //   16704: goto -15636 -> 1068
    //   16707: bipush 70
    //   16709: istore 76
    //   16711: goto -15643 -> 1068
    //   16714: bipush 51
    //   16716: istore 76
    //   16718: goto -15650 -> 1068
    //   16721: bipush 73
    //   16723: istore 76
    //   16725: goto -15657 -> 1068
    //   16728: bipush 7
    //   16730: istore 86
    //   16732: goto -15500 -> 1232
    //   16735: bipush 70
    //   16737: istore 86
    //   16739: goto -15507 -> 1232
    //   16742: bipush 51
    //   16744: istore 86
    //   16746: goto -15514 -> 1232
    //   16749: bipush 73
    //   16751: istore 86
    //   16753: goto -15521 -> 1232
    //   16756: bipush 7
    //   16758: istore 97
    //   16760: goto -15360 -> 1400
    //   16763: bipush 70
    //   16765: istore 97
    //   16767: goto -15367 -> 1400
    //   16770: bipush 51
    //   16772: istore 97
    //   16774: goto -15374 -> 1400
    //   16777: bipush 73
    //   16779: istore 97
    //   16781: goto -15381 -> 1400
    //   16784: bipush 7
    //   16786: istore 108
    //   16788: goto -15220 -> 1568
    //   16791: bipush 70
    //   16793: istore 108
    //   16795: goto -15227 -> 1568
    //   16798: bipush 51
    //   16800: istore 108
    //   16802: goto -15234 -> 1568
    //   16805: bipush 73
    //   16807: istore 108
    //   16809: goto -15241 -> 1568
    //   16812: bipush 7
    //   16814: istore 119
    //   16816: goto -15080 -> 1736
    //   16819: bipush 70
    //   16821: istore 119
    //   16823: goto -15087 -> 1736
    //   16826: bipush 51
    //   16828: istore 119
    //   16830: goto -15094 -> 1736
    //   16833: bipush 73
    //   16835: istore 119
    //   16837: goto -15101 -> 1736
    //   16840: bipush 7
    //   16842: istore 130
    //   16844: goto -14940 -> 1904
    //   16847: bipush 70
    //   16849: istore 130
    //   16851: goto -14947 -> 1904
    //   16854: bipush 51
    //   16856: istore 130
    //   16858: goto -14954 -> 1904
    //   16861: bipush 73
    //   16863: istore 130
    //   16865: goto -14961 -> 1904
    //   16868: bipush 7
    //   16870: istore 141
    //   16872: goto -14800 -> 2072
    //   16875: bipush 70
    //   16877: istore 141
    //   16879: goto -14807 -> 2072
    //   16882: bipush 51
    //   16884: istore 141
    //   16886: goto -14814 -> 2072
    //   16889: bipush 73
    //   16891: istore 141
    //   16893: goto -14821 -> 2072
    //   16896: bipush 7
    //   16898: istore 152
    //   16900: goto -14660 -> 2240
    //   16903: bipush 70
    //   16905: istore 152
    //   16907: goto -14667 -> 2240
    //   16910: bipush 51
    //   16912: istore 152
    //   16914: goto -14674 -> 2240
    //   16917: bipush 73
    //   16919: istore 152
    //   16921: goto -14681 -> 2240
    //   16924: bipush 7
    //   16926: istore 163
    //   16928: goto -14520 -> 2408
    //   16931: bipush 70
    //   16933: istore 163
    //   16935: goto -14527 -> 2408
    //   16938: bipush 51
    //   16940: istore 163
    //   16942: goto -14534 -> 2408
    //   16945: bipush 73
    //   16947: istore 163
    //   16949: goto -14541 -> 2408
    //   16952: bipush 7
    //   16954: istore 174
    //   16956: goto -14380 -> 2576
    //   16959: bipush 70
    //   16961: istore 174
    //   16963: goto -14387 -> 2576
    //   16966: bipush 51
    //   16968: istore 174
    //   16970: goto -14394 -> 2576
    //   16973: bipush 73
    //   16975: istore 174
    //   16977: goto -14401 -> 2576
    //   16980: bipush 7
    //   16982: istore 185
    //   16984: goto -14240 -> 2744
    //   16987: bipush 70
    //   16989: istore 185
    //   16991: goto -14247 -> 2744
    //   16994: bipush 51
    //   16996: istore 185
    //   16998: goto -14254 -> 2744
    //   17001: bipush 73
    //   17003: istore 185
    //   17005: goto -14261 -> 2744
    //   17008: bipush 7
    //   17010: istore 196
    //   17012: goto -14100 -> 2912
    //   17015: bipush 70
    //   17017: istore 196
    //   17019: goto -14107 -> 2912
    //   17022: bipush 51
    //   17024: istore 196
    //   17026: goto -14114 -> 2912
    //   17029: bipush 73
    //   17031: istore 196
    //   17033: goto -14121 -> 2912
    //   17036: bipush 7
    //   17038: istore 207
    //   17040: goto -13960 -> 3080
    //   17043: bipush 70
    //   17045: istore 207
    //   17047: goto -13967 -> 3080
    //   17050: bipush 51
    //   17052: istore 207
    //   17054: goto -13974 -> 3080
    //   17057: bipush 73
    //   17059: istore 207
    //   17061: goto -13981 -> 3080
    //   17064: bipush 7
    //   17066: istore 218
    //   17068: goto -13820 -> 3248
    //   17071: bipush 70
    //   17073: istore 218
    //   17075: goto -13827 -> 3248
    //   17078: bipush 51
    //   17080: istore 218
    //   17082: goto -13834 -> 3248
    //   17085: bipush 73
    //   17087: istore 218
    //   17089: goto -13841 -> 3248
    //   17092: bipush 7
    //   17094: istore 229
    //   17096: goto -13680 -> 3416
    //   17099: bipush 70
    //   17101: istore 229
    //   17103: goto -13687 -> 3416
    //   17106: bipush 51
    //   17108: istore 229
    //   17110: goto -13694 -> 3416
    //   17113: bipush 73
    //   17115: istore 229
    //   17117: goto -13701 -> 3416
    //   17120: bipush 7
    //   17122: istore 240
    //   17124: goto -13540 -> 3584
    //   17127: bipush 70
    //   17129: istore 240
    //   17131: goto -13547 -> 3584
    //   17134: bipush 51
    //   17136: istore 240
    //   17138: goto -13554 -> 3584
    //   17141: bipush 73
    //   17143: istore 240
    //   17145: goto -13561 -> 3584
    //   17148: bipush 7
    //   17150: istore 251
    //   17152: goto -13400 -> 3752
    //   17155: bipush 70
    //   17157: istore 251
    //   17159: goto -13407 -> 3752
    //   17162: bipush 51
    //   17164: istore 251
    //   17166: goto -13414 -> 3752
    //   17169: bipush 73
    //   17171: istore 251
    //   17173: goto -13421 -> 3752
    //   17176: bipush 7
    //   17178: wide
    //   17182: goto -13232 -> 3950
    //   17185: bipush 70
    //   17187: wide
    //   17191: goto -13241 -> 3950
    //   17194: bipush 51
    //   17196: wide
    //   17200: goto -13250 -> 3950
    //   17203: bipush 73
    //   17205: wide
    //   17209: goto -13259 -> 3950
    //   17212: bipush 7
    //   17214: wide
    //   17218: goto -13028 -> 4190
    //   17221: bipush 70
    //   17223: wide
    //   17227: goto -13037 -> 4190
    //   17230: bipush 51
    //   17232: wide
    //   17236: goto -13046 -> 4190
    //   17239: bipush 73
    //   17241: wide
    //   17245: goto -13055 -> 4190
    //   17248: bipush 7
    //   17250: wide
    //   17254: goto -12820 -> 4434
    //   17257: bipush 70
    //   17259: wide
    //   17263: goto -12829 -> 4434
    //   17266: bipush 51
    //   17268: wide
    //   17272: goto -12838 -> 4434
    //   17275: bipush 73
    //   17277: wide
    //   17281: goto -12847 -> 4434
    //   17284: bipush 7
    //   17286: wide
    //   17290: goto -12612 -> 4678
    //   17293: bipush 70
    //   17295: wide
    //   17299: goto -12621 -> 4678
    //   17302: bipush 51
    //   17304: wide
    //   17308: goto -12630 -> 4678
    //   17311: bipush 73
    //   17313: wide
    //   17317: goto -12639 -> 4678
    //   17320: bipush 7
    //   17322: wide
    //   17326: goto -12404 -> 4922
    //   17329: bipush 70
    //   17331: wide
    //   17335: goto -12413 -> 4922
    //   17338: bipush 51
    //   17340: wide
    //   17344: goto -12422 -> 4922
    //   17347: bipush 73
    //   17349: wide
    //   17353: goto -12431 -> 4922
    //   17356: bipush 7
    //   17358: wide
    //   17362: goto -12196 -> 5166
    //   17365: bipush 70
    //   17367: wide
    //   17371: goto -12205 -> 5166
    //   17374: bipush 51
    //   17376: wide
    //   17380: goto -12214 -> 5166
    //   17383: bipush 73
    //   17385: wide
    //   17389: goto -12223 -> 5166
    //   17392: bipush 7
    //   17394: wide
    //   17398: goto -11988 -> 5410
    //   17401: bipush 70
    //   17403: wide
    //   17407: goto -11997 -> 5410
    //   17410: bipush 51
    //   17412: wide
    //   17416: goto -12006 -> 5410
    //   17419: bipush 73
    //   17421: wide
    //   17425: goto -12015 -> 5410
    //   17428: bipush 7
    //   17430: wide
    //   17434: goto -11780 -> 5654
    //   17437: bipush 70
    //   17439: wide
    //   17443: goto -11789 -> 5654
    //   17446: bipush 51
    //   17448: wide
    //   17452: goto -11798 -> 5654
    //   17455: bipush 73
    //   17457: wide
    //   17461: goto -11807 -> 5654
    //   17464: bipush 7
    //   17466: wide
    //   17470: goto -11572 -> 5898
    //   17473: bipush 70
    //   17475: wide
    //   17479: goto -11581 -> 5898
    //   17482: bipush 51
    //   17484: wide
    //   17488: goto -11590 -> 5898
    //   17491: bipush 73
    //   17493: wide
    //   17497: goto -11599 -> 5898
    //   17500: bipush 7
    //   17502: wide
    //   17506: goto -11364 -> 6142
    //   17509: bipush 70
    //   17511: wide
    //   17515: goto -11373 -> 6142
    //   17518: bipush 51
    //   17520: wide
    //   17524: goto -11382 -> 6142
    //   17527: bipush 73
    //   17529: wide
    //   17533: goto -11391 -> 6142
    //   17536: bipush 7
    //   17538: wide
    //   17542: goto -11156 -> 6386
    //   17545: bipush 70
    //   17547: wide
    //   17551: goto -11165 -> 6386
    //   17554: bipush 51
    //   17556: wide
    //   17560: goto -11174 -> 6386
    //   17563: bipush 73
    //   17565: wide
    //   17569: goto -11183 -> 6386
    //   17572: bipush 7
    //   17574: wide
    //   17578: goto -10948 -> 6630
    //   17581: bipush 70
    //   17583: wide
    //   17587: goto -10957 -> 6630
    //   17590: bipush 51
    //   17592: wide
    //   17596: goto -10966 -> 6630
    //   17599: bipush 73
    //   17601: wide
    //   17605: goto -10975 -> 6630
    //   17608: bipush 7
    //   17610: wide
    //   17614: goto -10740 -> 6874
    //   17617: bipush 70
    //   17619: wide
    //   17623: goto -10749 -> 6874
    //   17626: bipush 51
    //   17628: wide
    //   17632: goto -10758 -> 6874
    //   17635: bipush 73
    //   17637: wide
    //   17641: goto -10767 -> 6874
    //   17644: bipush 7
    //   17646: wide
    //   17650: goto -10532 -> 7118
    //   17653: bipush 70
    //   17655: wide
    //   17659: goto -10541 -> 7118
    //   17662: bipush 51
    //   17664: wide
    //   17668: goto -10550 -> 7118
    //   17671: bipush 73
    //   17673: wide
    //   17677: goto -10559 -> 7118
    //   17680: bipush 7
    //   17682: wide
    //   17686: goto -10324 -> 7362
    //   17689: bipush 70
    //   17691: wide
    //   17695: goto -10333 -> 7362
    //   17698: bipush 51
    //   17700: wide
    //   17704: goto -10342 -> 7362
    //   17707: bipush 73
    //   17709: wide
    //   17713: goto -10351 -> 7362
    //   17716: bipush 7
    //   17718: wide
    //   17722: goto -10116 -> 7606
    //   17725: bipush 70
    //   17727: wide
    //   17731: goto -10125 -> 7606
    //   17734: bipush 51
    //   17736: wide
    //   17740: goto -10134 -> 7606
    //   17743: bipush 73
    //   17745: wide
    //   17749: goto -10143 -> 7606
    //   17752: bipush 7
    //   17754: wide
    //   17758: goto -9908 -> 7850
    //   17761: bipush 70
    //   17763: wide
    //   17767: goto -9917 -> 7850
    //   17770: bipush 51
    //   17772: wide
    //   17776: goto -9926 -> 7850
    //   17779: bipush 73
    //   17781: wide
    //   17785: goto -9935 -> 7850
    //   17788: bipush 7
    //   17790: wide
    //   17794: goto -9700 -> 8094
    //   17797: bipush 70
    //   17799: wide
    //   17803: goto -9709 -> 8094
    //   17806: bipush 51
    //   17808: wide
    //   17812: goto -9718 -> 8094
    //   17815: bipush 73
    //   17817: wide
    //   17821: goto -9727 -> 8094
    //   17824: bipush 7
    //   17826: wide
    //   17830: goto -9492 -> 8338
    //   17833: bipush 70
    //   17835: wide
    //   17839: goto -9501 -> 8338
    //   17842: bipush 51
    //   17844: wide
    //   17848: goto -9510 -> 8338
    //   17851: bipush 73
    //   17853: wide
    //   17857: goto -9519 -> 8338
    //   17860: bipush 7
    //   17862: wide
    //   17866: goto -9284 -> 8582
    //   17869: bipush 70
    //   17871: wide
    //   17875: goto -9293 -> 8582
    //   17878: bipush 51
    //   17880: wide
    //   17884: goto -9302 -> 8582
    //   17887: bipush 73
    //   17889: wide
    //   17893: goto -9311 -> 8582
    //   17896: bipush 7
    //   17898: wide
    //   17902: goto -9076 -> 8826
    //   17905: bipush 70
    //   17907: wide
    //   17911: goto -9085 -> 8826
    //   17914: bipush 51
    //   17916: wide
    //   17920: goto -9094 -> 8826
    //   17923: bipush 73
    //   17925: wide
    //   17929: goto -9103 -> 8826
    //   17932: bipush 7
    //   17934: wide
    //   17938: goto -8868 -> 9070
    //   17941: bipush 70
    //   17943: wide
    //   17947: goto -8877 -> 9070
    //   17950: bipush 51
    //   17952: wide
    //   17956: goto -8886 -> 9070
    //   17959: bipush 73
    //   17961: wide
    //   17965: goto -8895 -> 9070
    //   17968: bipush 7
    //   17970: wide
    //   17974: goto -8660 -> 9314
    //   17977: bipush 70
    //   17979: wide
    //   17983: goto -8669 -> 9314
    //   17986: bipush 51
    //   17988: wide
    //   17992: goto -8678 -> 9314
    //   17995: bipush 73
    //   17997: wide
    //   18001: goto -8687 -> 9314
    //   18004: bipush 7
    //   18006: wide
    //   18010: goto -8452 -> 9558
    //   18013: bipush 70
    //   18015: wide
    //   18019: goto -8461 -> 9558
    //   18022: bipush 51
    //   18024: wide
    //   18028: goto -8470 -> 9558
    //   18031: bipush 73
    //   18033: wide
    //   18037: goto -8479 -> 9558
    //   18040: bipush 7
    //   18042: wide
    //   18046: goto -8244 -> 9802
    //   18049: bipush 70
    //   18051: wide
    //   18055: goto -8253 -> 9802
    //   18058: bipush 51
    //   18060: wide
    //   18064: goto -8262 -> 9802
    //   18067: bipush 73
    //   18069: wide
    //   18073: goto -8271 -> 9802
    //   18076: bipush 7
    //   18078: wide
    //   18082: goto -8036 -> 10046
    //   18085: bipush 70
    //   18087: wide
    //   18091: goto -8045 -> 10046
    //   18094: bipush 51
    //   18096: wide
    //   18100: goto -8054 -> 10046
    //   18103: bipush 73
    //   18105: wide
    //   18109: goto -8063 -> 10046
    //   18112: bipush 7
    //   18114: wide
    //   18118: goto -7828 -> 10290
    //   18121: bipush 70
    //   18123: wide
    //   18127: goto -7837 -> 10290
    //   18130: bipush 51
    //   18132: wide
    //   18136: goto -7846 -> 10290
    //   18139: bipush 73
    //   18141: wide
    //   18145: goto -7855 -> 10290
    //   18148: bipush 7
    //   18150: wide
    //   18154: goto -7620 -> 10534
    //   18157: bipush 70
    //   18159: wide
    //   18163: goto -7629 -> 10534
    //   18166: bipush 51
    //   18168: wide
    //   18172: goto -7638 -> 10534
    //   18175: bipush 73
    //   18177: wide
    //   18181: goto -7647 -> 10534
    //   18184: bipush 7
    //   18186: wide
    //   18190: goto -7416 -> 10774
    //   18193: bipush 70
    //   18195: wide
    //   18199: goto -7425 -> 10774
    //   18202: bipush 51
    //   18204: wide
    //   18208: goto -7434 -> 10774
    //   18211: bipush 73
    //   18213: wide
    //   18217: goto -7443 -> 10774
    //   18220: bipush 7
    //   18222: wide
    //   18226: goto -7208 -> 11018
    //   18229: bipush 70
    //   18231: wide
    //   18235: goto -7217 -> 11018
    //   18238: bipush 51
    //   18240: wide
    //   18244: goto -7226 -> 11018
    //   18247: bipush 73
    //   18249: wide
    //   18253: goto -7235 -> 11018
    //   18256: bipush 7
    //   18258: wide
    //   18262: goto -7000 -> 11262
    //   18265: bipush 70
    //   18267: wide
    //   18271: goto -7009 -> 11262
    //   18274: bipush 51
    //   18276: wide
    //   18280: goto -7018 -> 11262
    //   18283: bipush 73
    //   18285: wide
    //   18289: goto -7027 -> 11262
    //   18292: bipush 7
    //   18294: wide
    //   18298: goto -6792 -> 11506
    //   18301: bipush 70
    //   18303: wide
    //   18307: goto -6801 -> 11506
    //   18310: bipush 51
    //   18312: wide
    //   18316: goto -6810 -> 11506
    //   18319: bipush 73
    //   18321: wide
    //   18325: goto -6819 -> 11506
    //   18328: bipush 7
    //   18330: wide
    //   18334: goto -6584 -> 11750
    //   18337: bipush 70
    //   18339: wide
    //   18343: goto -6593 -> 11750
    //   18346: bipush 51
    //   18348: wide
    //   18352: goto -6602 -> 11750
    //   18355: bipush 73
    //   18357: wide
    //   18361: goto -6611 -> 11750
    //   18364: bipush 7
    //   18366: wide
    //   18370: goto -6376 -> 11994
    //   18373: bipush 70
    //   18375: wide
    //   18379: goto -6385 -> 11994
    //   18382: bipush 51
    //   18384: wide
    //   18388: goto -6394 -> 11994
    //   18391: bipush 73
    //   18393: wide
    //   18397: goto -6403 -> 11994
    //   18400: bipush 7
    //   18402: wide
    //   18406: goto -6168 -> 12238
    //   18409: bipush 70
    //   18411: wide
    //   18415: goto -6177 -> 12238
    //   18418: bipush 51
    //   18420: wide
    //   18424: goto -6186 -> 12238
    //   18427: bipush 73
    //   18429: wide
    //   18433: goto -6195 -> 12238
    //   18436: bipush 7
    //   18438: wide
    //   18442: goto -5960 -> 12482
    //   18445: bipush 70
    //   18447: wide
    //   18451: goto -5969 -> 12482
    //   18454: bipush 51
    //   18456: wide
    //   18460: goto -5978 -> 12482
    //   18463: bipush 73
    //   18465: wide
    //   18469: goto -5987 -> 12482
    //   18472: bipush 7
    //   18474: wide
    //   18478: goto -5752 -> 12726
    //   18481: bipush 70
    //   18483: wide
    //   18487: goto -5761 -> 12726
    //   18490: bipush 51
    //   18492: wide
    //   18496: goto -5770 -> 12726
    //   18499: bipush 73
    //   18501: wide
    //   18505: goto -5779 -> 12726
    //   18508: bipush 7
    //   18510: wide
    //   18514: goto -5544 -> 12970
    //   18517: bipush 70
    //   18519: wide
    //   18523: goto -5553 -> 12970
    //   18526: bipush 51
    //   18528: wide
    //   18532: goto -5562 -> 12970
    //   18535: bipush 73
    //   18537: wide
    //   18541: goto -5571 -> 12970
    //   18544: bipush 7
    //   18546: wide
    //   18550: goto -5336 -> 13214
    //   18553: bipush 70
    //   18555: wide
    //   18559: goto -5345 -> 13214
    //   18562: bipush 51
    //   18564: wide
    //   18568: goto -5354 -> 13214
    //   18571: bipush 73
    //   18573: wide
    //   18577: goto -5363 -> 13214
    //   18580: bipush 7
    //   18582: wide
    //   18586: goto -5128 -> 13458
    //   18589: bipush 70
    //   18591: wide
    //   18595: goto -5137 -> 13458
    //   18598: bipush 51
    //   18600: wide
    //   18604: goto -5146 -> 13458
    //   18607: bipush 73
    //   18609: wide
    //   18613: goto -5155 -> 13458
    //   18616: bipush 7
    //   18618: wide
    //   18622: goto -4920 -> 13702
    //   18625: bipush 70
    //   18627: wide
    //   18631: goto -4929 -> 13702
    //   18634: bipush 51
    //   18636: wide
    //   18640: goto -4938 -> 13702
    //   18643: bipush 73
    //   18645: wide
    //   18649: goto -4947 -> 13702
    //   18652: bipush 7
    //   18654: wide
    //   18658: goto -4712 -> 13946
    //   18661: bipush 70
    //   18663: wide
    //   18667: goto -4721 -> 13946
    //   18670: bipush 51
    //   18672: wide
    //   18676: goto -4730 -> 13946
    //   18679: bipush 73
    //   18681: wide
    //   18685: goto -4739 -> 13946
    //   18688: bipush 7
    //   18690: wide
    //   18694: goto -4504 -> 14190
    //   18697: bipush 70
    //   18699: wide
    //   18703: goto -4513 -> 14190
    //   18706: bipush 51
    //   18708: wide
    //   18712: goto -4522 -> 14190
    //   18715: bipush 73
    //   18717: wide
    //   18721: goto -4531 -> 14190
    //   18724: bipush 7
    //   18726: wide
    //   18730: goto -4296 -> 14434
    //   18733: bipush 70
    //   18735: wide
    //   18739: goto -4305 -> 14434
    //   18742: bipush 51
    //   18744: wide
    //   18748: goto -4314 -> 14434
    //   18751: bipush 73
    //   18753: wide
    //   18757: goto -4323 -> 14434
    //   18760: bipush 7
    //   18762: wide
    //   18766: goto -4088 -> 14678
    //   18769: bipush 70
    //   18771: wide
    //   18775: goto -4097 -> 14678
    //   18778: bipush 51
    //   18780: wide
    //   18784: goto -4106 -> 14678
    //   18787: bipush 73
    //   18789: wide
    //   18793: goto -4115 -> 14678
    //   18796: bipush 7
    //   18798: wide
    //   18802: goto -3880 -> 14922
    //   18805: bipush 70
    //   18807: wide
    //   18811: goto -3889 -> 14922
    //   18814: bipush 51
    //   18816: wide
    //   18820: goto -3898 -> 14922
    //   18823: bipush 73
    //   18825: wide
    //   18829: goto -3907 -> 14922
    //   18832: bipush 7
    //   18834: wide
    //   18838: goto -3672 -> 15166
    //   18841: bipush 70
    //   18843: wide
    //   18847: goto -3681 -> 15166
    //   18850: bipush 51
    //   18852: wide
    //   18856: goto -3690 -> 15166
    //   18859: bipush 73
    //   18861: wide
    //   18865: goto -3699 -> 15166
    //   18868: bipush 7
    //   18870: wide
    //   18874: goto -3468 -> 15406
    //   18877: bipush 70
    //   18879: wide
    //   18883: goto -3477 -> 15406
    //   18886: bipush 51
    //   18888: wide
    //   18892: goto -3486 -> 15406
    //   18895: bipush 73
    //   18897: wide
    //   18901: goto -3495 -> 15406
    //   18904: bipush 7
    //   18906: wide
    //   18910: goto -3260 -> 15650
    //   18913: bipush 70
    //   18915: wide
    //   18919: goto -3269 -> 15650
    //   18922: bipush 51
    //   18924: wide
    //   18928: goto -3278 -> 15650
    //   18931: bipush 73
    //   18933: wide
    //   18937: goto -3287 -> 15650
    //   18940: bipush 7
    //   18942: wide
    //   18946: goto -3052 -> 15894
    //   18949: bipush 70
    //   18951: wide
    //   18955: goto -3061 -> 15894
    //   18958: bipush 51
    //   18960: wide
    //   18964: goto -3070 -> 15894
    //   18967: bipush 73
    //   18969: wide
    //   18973: goto -3079 -> 15894
    //   18976: bipush 7
    //   18978: wide
    //   18982: goto -2844 -> 16138
    //   18985: bipush 70
    //   18987: wide
    //   18991: goto -2853 -> 16138
    //   18994: bipush 51
    //   18996: wide
    //   19000: goto -2862 -> 16138
    //   19003: bipush 73
    //   19005: wide
    //   19009: goto -2871 -> 16138
    //   19012: bipush 7
    //   19014: wide
    //   19018: goto -2636 -> 16382
    //   19021: bipush 70
    //   19023: wide
    //   19027: goto -2645 -> 16382
    //   19030: bipush 51
    //   19032: wide
    //   19036: goto -2654 -> 16382
    //   19039: bipush 73
    //   19041: wide
    //   19045: goto -2663 -> 16382
    //   19048: iconst_0
    //   19049: wide
    //   19053: goto -2592 -> 16461
    //   19056: iconst_0
    //   19057: wide
    //   19061: goto -2844 -> 16217
    //   19064: iconst_0
    //   19065: wide
    //   19069: goto -3096 -> 15973
    //   19072: iconst_0
    //   19073: wide
    //   19077: goto -3348 -> 15729
    //   19080: iconst_0
    //   19081: wide
    //   19085: goto -3598 -> 15487
    //   19088: iconst_0
    //   19089: wide
    //   19093: goto -3848 -> 15245
    //   19096: iconst_0
    //   19097: wide
    //   19101: goto -4100 -> 15001
    //   19104: iconst_0
    //   19105: wide
    //   19109: goto -4352 -> 14757
    //   19112: iconst_0
    //   19113: wide
    //   19117: goto -4604 -> 14513
    //   19120: iconst_0
    //   19121: wide
    //   19125: goto -4856 -> 14269
    //   19128: iconst_0
    //   19129: wide
    //   19133: goto -5108 -> 14025
    //   19136: iconst_0
    //   19137: wide
    //   19141: goto -5360 -> 13781
    //   19144: iconst_0
    //   19145: wide
    //   19149: goto -5612 -> 13537
    //   19152: iconst_0
    //   19153: wide
    //   19157: goto -5864 -> 13293
    //   19160: iconst_0
    //   19161: wide
    //   19165: goto -6116 -> 13049
    //   19168: iconst_0
    //   19169: wide
    //   19173: goto -6368 -> 12805
    //   19176: iconst_0
    //   19177: wide
    //   19181: goto -6620 -> 12561
    //   19184: iconst_0
    //   19185: wide
    //   19189: goto -6872 -> 12317
    //   19192: iconst_0
    //   19193: wide
    //   19197: goto -7124 -> 12073
    //   19200: iconst_0
    //   19201: wide
    //   19205: goto -7376 -> 11829
    //   19208: iconst_0
    //   19209: wide
    //   19213: goto -7628 -> 11585
    //   19216: iconst_0
    //   19217: wide
    //   19221: goto -7880 -> 11341
    //   19224: iconst_0
    //   19225: wide
    //   19229: goto -8132 -> 11097
    //   19232: iconst_0
    //   19233: wide
    //   19237: goto -8382 -> 10855
    //   19240: iconst_0
    //   19241: wide
    //   19245: goto -8632 -> 10613
    //   19248: iconst_0
    //   19249: wide
    //   19253: goto -8884 -> 10369
    //   19256: iconst_0
    //   19257: wide
    //   19261: goto -9136 -> 10125
    //   19264: iconst_0
    //   19265: wide
    //   19269: goto -9388 -> 9881
    //   19272: iconst_0
    //   19273: wide
    //   19277: goto -9640 -> 9637
    //   19280: iconst_0
    //   19281: wide
    //   19285: goto -9892 -> 9393
    //   19288: iconst_0
    //   19289: wide
    //   19293: goto -10144 -> 9149
    //   19296: iconst_0
    //   19297: wide
    //   19301: goto -10396 -> 8905
    //   19304: iconst_0
    //   19305: wide
    //   19309: goto -10648 -> 8661
    //   19312: iconst_0
    //   19313: wide
    //   19317: goto -10900 -> 8417
    //   19320: iconst_0
    //   19321: wide
    //   19325: goto -11152 -> 8173
    //   19328: iconst_0
    //   19329: wide
    //   19333: goto -11404 -> 7929
    //   19336: iconst_0
    //   19337: wide
    //   19341: goto -11656 -> 7685
    //   19344: iconst_0
    //   19345: wide
    //   19349: goto -11908 -> 7441
    //   19352: iconst_0
    //   19353: wide
    //   19357: goto -12160 -> 7197
    //   19360: iconst_0
    //   19361: wide
    //   19365: goto -12412 -> 6953
    //   19368: iconst_0
    //   19369: wide
    //   19373: goto -12664 -> 6709
    //   19376: iconst_0
    //   19377: wide
    //   19381: goto -12916 -> 6465
    //   19384: iconst_0
    //   19385: wide
    //   19389: goto -13168 -> 6221
    //   19392: iconst_0
    //   19393: wide
    //   19397: goto -13420 -> 5977
    //   19400: iconst_0
    //   19401: wide
    //   19405: goto -13672 -> 5733
    //   19408: iconst_0
    //   19409: wide
    //   19413: goto -13924 -> 5489
    //   19416: iconst_0
    //   19417: wide
    //   19421: goto -14176 -> 5245
    //   19424: iconst_0
    //   19425: wide
    //   19429: goto -14428 -> 5001
    //   19432: iconst_0
    //   19433: wide
    //   19437: goto -14680 -> 4757
    //   19440: iconst_0
    //   19441: wide
    //   19445: goto -14932 -> 4513
    //   19448: iconst_0
    //   19449: wide
    //   19453: goto -15184 -> 4269
    //   19456: iconst_0
    //   19457: wide
    //   19461: goto -15432 -> 4029
    //   19464: iconst_0
    //   19465: istore 247
    //   19467: goto -15666 -> 3801
    //   19470: iconst_0
    //   19471: istore 236
    //   19473: goto -15840 -> 3633
    //   19476: iconst_0
    //   19477: istore 225
    //   19479: goto -16014 -> 3465
    //   19482: iconst_0
    //   19483: istore 214
    //   19485: goto -16188 -> 3297
    //   19488: iconst_0
    //   19489: istore 203
    //   19491: goto -16362 -> 3129
    //   19494: iconst_0
    //   19495: istore 192
    //   19497: goto -16536 -> 2961
    //   19500: iconst_0
    //   19501: istore 181
    //   19503: goto -16710 -> 2793
    //   19506: iconst_0
    //   19507: istore 170
    //   19509: goto -16884 -> 2625
    //   19512: iconst_0
    //   19513: istore 159
    //   19515: goto -17058 -> 2457
    //   19518: iconst_0
    //   19519: istore 148
    //   19521: goto -17232 -> 2289
    //   19524: iconst_0
    //   19525: istore 137
    //   19527: goto -17406 -> 2121
    //   19530: iconst_0
    //   19531: istore 126
    //   19533: goto -17580 -> 1953
    //   19536: iconst_0
    //   19537: istore 115
    //   19539: goto -17754 -> 1785
    //   19542: iconst_0
    //   19543: istore 104
    //   19545: goto -17928 -> 1617
    //   19548: iconst_0
    //   19549: istore 93
    //   19551: goto -18102 -> 1449
    //   19554: iconst_0
    //   19555: istore 82
    //   19557: goto -18276 -> 1281
    //   19560: iconst_0
    //   19561: istore 72
    //   19563: goto -18446 -> 1117
    //   19566: iconst_0
    //   19567: istore 61
    //   19569: goto -18620 -> 949
    //   19572: iconst_0
    //   19573: istore 50
    //   19575: goto -18790 -> 785
    //   19578: iconst_0
    //   19579: istore 39
    //   19581: goto -18960 -> 621
    //   19584: iconst_0
    //   19585: istore 27
    //   19587: goto -19130 -> 457
    //   19590: iconst_0
    //   19591: istore 16
    //   19593: goto -19300 -> 293
    //   19596: iconst_0
    //   19597: istore 4
    //   19599: goto -19464 -> 135
  }

  public _sdkfd(_sdkt param_sdkt)
    throws _sdkn
  {
    _sdkhb local_sdkhb = _sdkhb._sdkb(_sdkfd.class);
    this._sdkf = local_sdkhb;
    Context localContext = ((_sdkq)param_sdkt)._sdka();
    this._sdkg = localContext;
    _sdkb local_sdkb = new _sdkb(this, null);
    this._sdkh = local_sdkb;
    ArrayList localArrayList = new ArrayList();
    this._sdkm = localArrayList;
    _sdkmc local_sdkmc = new _sdkmc(this, null);
    this._sdki = local_sdkmc;
    this._sdkk = null;
    this._sdkq = bool1;
    this._sdkr = true;
    _sdkb();
    if (!bool2)
      return;
    if (_sdkhb._sdkd);
    while (true)
    {
      _sdkhb._sdkd = bool1;
      return;
      bool1 = true;
    }
  }

  static _sdkhb _sdka(_sdkfd param_sdkfd)
  {
    return param_sdkfd._sdkf;
  }

  private _sdkjc _sdka(WifiInfo paramWifiInfo, long paramLong, _sdkec param_sdkec)
  {
    _sdkic local_sdkic;
    int i;
    long l;
    _sdkec local_sdkec;
    if (_sdka(paramWifiInfo))
    {
      String str = paramWifiInfo.getBSSID();
      local_sdkic = new _sdkic(str);
      i = paramWifiInfo.getRssi();
      l = paramLong;
      local_sdkec = param_sdkec;
    }
    for (_sdkjc local_sdkjc = new _sdkjc(local_sdkic, i, l, local_sdkec); ; local_sdkjc = null)
      return local_sdkjc;
  }

  static _sdkjc _sdka(_sdkfd param_sdkfd, WifiInfo paramWifiInfo, long paramLong, _sdkec param_sdkec)
  {
    return param_sdkfd._sdka(paramWifiInfo, paramLong, param_sdkec);
  }

  private FutureTask<Void> _sdka(long paramLong)
  {
    Object localObject = null;
    _sdkkc local_sdkkc = new _sdkkc(this);
    FutureTask localFutureTask = new FutureTask(local_sdkkc, localObject);
    if (!_sdkr._sdka(localFutureTask, paramLong));
    while (true)
    {
      return localObject;
      localObject = localFutureTask;
    }
  }

  static FutureTask _sdka(_sdkfd param_sdkfd, FutureTask paramFutureTask)
  {
    param_sdkfd._sdks = paramFutureTask;
    return paramFutureTask;
  }

  static void _sdka(_sdkfd param_sdkfd, List paramList, long paramLong, _sdkec param_sdkec, ArrayList paramArrayList)
  {
    param_sdkfd._sdka(paramList, paramLong, param_sdkec, paramArrayList);
  }

  static void _sdka(_sdkfd param_sdkfd, boolean paramBoolean)
  {
    param_sdkfd._sdka(paramBoolean);
  }

  private void _sdka(List<ScanResult> paramList, long paramLong, _sdkec param_sdkec, ArrayList<_sdkjc> paramArrayList)
  {
    boolean bool1 = _sdkic._sdkc;
    StringBuffer localStringBuffer1 = new StringBuffer();
    Iterator localIterator = paramList.iterator();
    while (true)
    {
      ScanResult localScanResult;
      if (localIterator.hasNext())
      {
        localScanResult = (ScanResult)localIterator.next();
        if ((localScanResult == null) || (localScanResult.BSSID == null));
      }
      else
      {
        try
        {
          String str1 = localScanResult.BSSID;
          _sdkic local_sdkic = new _sdkic(str1);
          if (localScanResult.capabilities != null)
          {
            String str2 = localScanResult.capabilities;
            String str3 = z[42];
            if (str2.contains(str3))
            {
              if (!this._sdkf._sdkb())
                continue;
              _sdkhb local_sdkhb1 = this._sdkf;
              StringBuilder localStringBuilder1 = new StringBuilder();
              String str4 = z[41];
              String str5 = str4 + local_sdkic;
              local_sdkhb1._sdkb(str5);
              if (!bool1)
                continue;
            }
          }
          else
          {
            int i = localScanResult.level;
            long l = paramLong;
            _sdkec local_sdkec = param_sdkec;
            _sdkjc local_sdkjc = new _sdkjc(local_sdkic, i, l, local_sdkec);
            boolean bool2 = paramArrayList.add(local_sdkjc);
            if (this._sdkf._sdkb())
            {
              String str6 = z[38];
              StringBuffer localStringBuffer2 = localStringBuffer1.append(str6).append(local_sdkic);
              String str7 = z[43];
              StringBuffer localStringBuffer3 = localStringBuffer2.append(str7);
              String str8 = localScanResult.SSID;
              StringBuffer localStringBuffer4 = localStringBuffer3.append(str8).append("]");
            }
            if (bool1)
            {
              if (localStringBuffer1.length() <= 0)
                return;
              String str9 = z[40];
              StringBuffer localStringBuffer5 = localStringBuffer1.insert(0, str9);
              _sdkhb local_sdkhb2 = this._sdkf;
              String str10 = localStringBuffer1.toString();
              local_sdkhb2._sdkb(str10);
              return;
            }
          }
        }
        catch (Throwable localThrowable)
        {
          _sdkhb local_sdkhb3 = this._sdkf;
          StringBuilder localStringBuilder2 = new StringBuilder();
          String str11 = z[39];
          StringBuilder localStringBuilder3 = localStringBuilder2.append(str11);
          String str12 = localScanResult.BSSID;
          String str13 = str12;
          local_sdkhb3._sdke(str13, localThrowable);
        }
      }
    }
  }

  private void _sdka(boolean paramBoolean)
  {
    if (this._sdkf._sdkb())
    {
      _sdkhb local_sdkhb1 = this._sdkf;
      StringBuilder localStringBuilder1 = new StringBuilder();
      String str1 = z[47];
      String str2 = str1 + paramBoolean + ")";
      local_sdkhb1._sdkb(str2);
    }
    if (this._sdkr)
    {
      _sdkhb local_sdkhb2 = this._sdkf;
      String str3 = z[49];
      local_sdkhb2._sdkb(str3);
      return;
    }
    if ((!_sdkt) && (!_sdkd()))
      throw new AssertionError();
    if ((!_sdkt) && (this._sdks != null))
      throw new AssertionError();
    if ((!_sdkt) && (!this._sdkn) && (!paramBoolean))
      throw new AssertionError();
    if (!paramBoolean)
    {
      _sdkhb local_sdkhb3 = this._sdkf;
      String str4 = z[44];
      local_sdkhb3._sdkb(str4);
      _sdkk();
      return;
    }
    long l = _sdki();
    if (l <= 60000L)
    {
      _sdkhb local_sdkhb4 = this._sdkf;
      String str5 = z[46];
      local_sdkhb4._sdkb(str5);
      return;
    }
    FutureTask localFutureTask = _sdka(l);
    this._sdks = localFutureTask;
    if (this._sdks == null)
    {
      _sdkhb local_sdkhb5 = this._sdkf;
      String str6 = z[48];
      local_sdkhb5._sdkd(str6);
      return;
    }
    if (this._sdkf._sdkb())
    {
      _sdkhb local_sdkhb6 = this._sdkf;
      StringBuilder localStringBuilder2 = new StringBuilder();
      String str7 = z[45];
      String str8 = str7 + l;
      local_sdkhb6._sdkb(str8);
    }
    _sdkk();
  }

  static boolean _sdka(WifiInfo paramWifiInfo)
  {
    if ((paramWifiInfo != null) && (paramWifiInfo.getBSSID() != null) && (paramWifiInfo.getNetworkId() != -1))
    {
      SupplicantState localSupplicantState1 = paramWifiInfo.getSupplicantState();
      SupplicantState localSupplicantState2 = SupplicantState.COMPLETED;
      if (localSupplicantState1 != localSupplicantState2);
    }
    for (boolean bool = true; ; bool = false)
      return bool;
  }

  private static boolean _sdka(List<_sdkjc> paramList, _sdkjc param_sdkjc)
  {
    ListIterator localListIterator = paramList.listIterator();
    while (localListIterator.hasNext())
    {
      _sdkic local_sdkic1 = ((_sdkjc)localListIterator.next())._sdka();
      _sdkic local_sdkic2 = param_sdkjc._sdka();
      if (local_sdkic1.equals(local_sdkic2))
        localListIterator.set(param_sdkjc);
    }
    for (boolean bool = true; ; bool = false)
      return bool;
  }

  /** @deprecated */
  // ERROR //
  private void _sdkb()
    throws _sdkn
  {
    // Byte code:
    //   0: aload_0
    //   1: monitorenter
    //   2: aload_0
    //   3: getfield 236	com/skyhookwireless/_sdkfd:_sdkf	Lcom/skyhookwireless/_sdkhb;
    //   6: astore_1
    //   7: getstatic 205	com/skyhookwireless/_sdkfd:z	[Ljava/lang/String;
    //   10: bipush 13
    //   12: aaload
    //   13: astore_2
    //   14: aload_1
    //   15: aload_2
    //   16: invokevirtual 374	com/skyhookwireless/_sdkhb:_sdkb	(Ljava/lang/String;)V
    //   19: aload_0
    //   20: invokespecial 464	com/skyhookwireless/_sdkfd:_sdkf	()Z
    //   23: ifeq +25 -> 48
    //   26: aload_0
    //   27: getfield 236	com/skyhookwireless/_sdkfd:_sdkf	Lcom/skyhookwireless/_sdkhb;
    //   30: astore_3
    //   31: getstatic 205	com/skyhookwireless/_sdkfd:z	[Ljava/lang/String;
    //   34: bipush 14
    //   36: aaload
    //   37: astore 4
    //   39: aload_3
    //   40: aload 4
    //   42: invokevirtual 374	com/skyhookwireless/_sdkhb:_sdkb	(Ljava/lang/String;)V
    //   45: aload_0
    //   46: monitorexit
    //   47: return
    //   48: aload_0
    //   49: getfield 261	com/skyhookwireless/_sdkfd:_sdki	Lcom/skyhookwireless/_sdkmc;
    //   52: invokestatic 467	com/skyhookwireless/_sdkr:_sdka	(Ljava/util/concurrent/Callable;)Ljava/util/concurrent/Future;
    //   55: astore 5
    //   57: getstatic 473	java/util/concurrent/TimeUnit:MILLISECONDS	Ljava/util/concurrent/TimeUnit;
    //   60: astore 6
    //   62: aload 5
    //   64: ldc2_w 474
    //   67: aload 6
    //   69: invokeinterface 481 4 0
    //   74: checkcast 483	android/net/wifi/WifiManager
    //   77: astore 7
    //   79: aload 7
    //   81: ifnonnull +50 -> 131
    //   84: getstatic 205	com/skyhookwireless/_sdkfd:z	[Ljava/lang/String;
    //   87: bipush 12
    //   89: aaload
    //   90: astore 8
    //   92: new 222	com/skyhookwireless/_sdkn
    //   95: dup
    //   96: aload 8
    //   98: invokespecial 484	com/skyhookwireless/_sdkn:<init>	(Ljava/lang/String;)V
    //   101: athrow
    //   102: astore 9
    //   104: aload_0
    //   105: monitorexit
    //   106: aload 9
    //   108: athrow
    //   109: astore 7
    //   111: getstatic 205	com/skyhookwireless/_sdkfd:z	[Ljava/lang/String;
    //   114: bipush 12
    //   116: aaload
    //   117: astore 10
    //   119: new 222	com/skyhookwireless/_sdkn
    //   122: dup
    //   123: aload 10
    //   125: aload 7
    //   127: invokespecial 486	com/skyhookwireless/_sdkn:<init>	(Ljava/lang/String;Ljava/lang/Throwable;)V
    //   130: athrow
    //   131: aload_0
    //   132: getfield 256	com/skyhookwireless/_sdkfd:_sdkm	Ljava/util/ArrayList;
    //   135: invokevirtual 489	java/util/ArrayList:clear	()V
    //   138: new 491	com/skyhookwireless/_sdklc
    //   141: dup
    //   142: aload_0
    //   143: aload 7
    //   145: invokespecial 494	com/skyhookwireless/_sdklc:<init>	(Lcom/skyhookwireless/_sdkfd;Landroid/net/wifi/WifiManager;)V
    //   148: astore 11
    //   150: aload_0
    //   151: aload 11
    //   153: putfield 496	com/skyhookwireless/_sdkfd:_sdkl	Lcom/skyhookwireless/_sdklc;
    //   156: new 498	android/content/IntentFilter
    //   159: dup
    //   160: invokespecial 499	android/content/IntentFilter:<init>	()V
    //   163: astore 12
    //   165: getstatic 205	com/skyhookwireless/_sdkfd:z	[Ljava/lang/String;
    //   168: bipush 9
    //   170: aaload
    //   171: astore 13
    //   173: aload 12
    //   175: aload 13
    //   177: invokevirtual 502	android/content/IntentFilter:addAction	(Ljava/lang/String;)V
    //   180: getstatic 205	com/skyhookwireless/_sdkfd:z	[Ljava/lang/String;
    //   183: bipush 10
    //   185: aaload
    //   186: astore 14
    //   188: aload 12
    //   190: aload 14
    //   192: invokevirtual 502	android/content/IntentFilter:addAction	(Ljava/lang/String;)V
    //   195: aload_0
    //   196: getfield 236	com/skyhookwireless/_sdkfd:_sdkf	Lcom/skyhookwireless/_sdkhb;
    //   199: astore 15
    //   201: getstatic 205	com/skyhookwireless/_sdkfd:z	[Ljava/lang/String;
    //   204: bipush 11
    //   206: aaload
    //   207: astore 16
    //   209: aload 15
    //   211: aload 16
    //   213: invokevirtual 374	com/skyhookwireless/_sdkhb:_sdkb	(Ljava/lang/String;)V
    //   216: aload_0
    //   217: getfield 244	com/skyhookwireless/_sdkfd:_sdkg	Landroid/content/Context;
    //   220: astore 17
    //   222: aload_0
    //   223: getfield 251	com/skyhookwireless/_sdkfd:_sdkh	Lcom/skyhookwireless/_sdkb;
    //   226: astore 18
    //   228: aload 17
    //   230: aload 18
    //   232: aload 12
    //   234: invokevirtual 508	android/content/Context:registerReceiver	(Landroid/content/BroadcastReceiver;Landroid/content/IntentFilter;)Landroid/content/Intent;
    //   237: astore 19
    //   239: aload_0
    //   240: aload 7
    //   242: putfield 510	com/skyhookwireless/_sdkfd:_sdkj	Landroid/net/wifi/WifiManager;
    //   245: goto -200 -> 45
    //
    // Exception table:
    //   from	to	target	type
    //   2	45	102	finally
    //   48	79	102	finally
    //   84	102	102	finally
    //   111	245	102	finally
    //   48	79	109	java/lang/Throwable
  }

  static void _sdkb(_sdkfd param_sdkfd)
  {
    param_sdkfd._sdkh();
  }

  static boolean _sdkb(_sdkfd param_sdkfd, boolean paramBoolean)
  {
    param_sdkfd._sdkn = paramBoolean;
    return paramBoolean;
  }

  static boolean _sdkb(List paramList, _sdkjc param_sdkjc)
  {
    return _sdka(paramList, param_sdkjc);
  }

  private boolean _sdkc()
  {
    if (this._sdkn)
    {
      _sdkec local_sdkec = _sdkec._sdkd();
      this._sdko = local_sdkec;
      _sdkhb local_sdkhb1 = this._sdkf;
      String str1 = z[73];
      local_sdkhb1._sdkb(str1);
      if (!_sdkic._sdkc);
    }
    else
    {
      _sdkhb local_sdkhb2 = this._sdkf;
      String str2 = z[74];
      local_sdkhb2._sdkb(str2);
      this._sdkl._sdkb();
    }
    return this._sdkn;
  }

  static boolean _sdkc(_sdkfd param_sdkfd)
  {
    return param_sdkfd._sdkf();
  }

  static WifiManager _sdkd(_sdkfd param_sdkfd)
  {
    return param_sdkfd._sdkj;
  }

  static _sdkec _sdke(_sdkfd param_sdkfd)
  {
    return param_sdkfd._sdko;
  }

  private boolean _sdkf()
  {
    if (this._sdkj != null);
    for (boolean bool = true; ; bool = false)
      return bool;
  }

  static boolean _sdkf(_sdkfd param_sdkfd)
  {
    return param_sdkfd._sdkn;
  }

  static ArrayList _sdkg(_sdkfd param_sdkfd)
  {
    return param_sdkfd._sdkm;
  }

  static _sdklc _sdkh(_sdkfd param_sdkfd)
  {
    return param_sdkfd._sdkl;
  }

  private void _sdkh()
  {
    int i = 0;
    _sdkhb local_sdkhb1 = this._sdkf;
    String str1 = z[34];
    local_sdkhb1._sdkb(str1);
    if (!this._sdkr)
    {
      _sdkhb local_sdkhb2 = this._sdkf;
      String str2 = z[36];
      local_sdkhb2._sdkb(str2);
      _sdknc local_sdknc = _sdke;
      WifiManager localWifiManager = this._sdkj;
      local_sdknc._sdkb(localWifiManager);
      return;
    }
    if ((!_sdkt) && (!_sdkd()))
      throw new AssertionError();
    ContentResolver localContentResolver = this._sdkg.getContentResolver();
    String str3 = z[32];
    if (Settings.System.getInt(localContentResolver, str3, 0) != 0)
      i = 1;
    if (i != 0)
    {
      _sdkhb local_sdkhb3 = this._sdkf;
      String str4 = z[33];
      local_sdkhb3._sdkb(str4);
      return;
    }
    _sdkl();
    _sdkhb local_sdkhb4 = this._sdkf;
    String str5 = z[35];
    local_sdkhb4._sdkb(str5);
    _sdkj();
  }

  static void _sdki(_sdkfd param_sdkfd)
  {
    param_sdkfd._sdka();
  }

  static Context _sdkj(_sdkfd param_sdkfd)
  {
    return param_sdkfd._sdkg;
  }

  private void _sdkj()
  {
    _sdknc local_sdknc = _sdke;
    WifiManager localWifiManager = this._sdkj;
    local_sdknc._sdka(localWifiManager);
    this._sdkr = false;
  }

  private void _sdkk()
  {
    _sdknc local_sdknc = _sdke;
    WifiManager localWifiManager = this._sdkj;
    local_sdknc._sdkc(localWifiManager);
    this._sdkr = true;
  }

  private void _sdkl()
  {
    _sdkhb local_sdkhb = this._sdkf;
    String str = z[3];
    local_sdkhb._sdkb(str);
    if (this._sdks == null)
      return;
    boolean bool = this._sdks.cancel(false);
    this._sdks = null;
  }

  protected _sdkdd _sdka(_sdkt param_sdkt)
    throws _sdkn
  {
    return new _sdkfd(param_sdkt);
  }

  /** @deprecated */
  // ERROR //
  public void _sdka(long paramLong)
  {
    // Byte code:
    //   0: aload_0
    //   1: monitorenter
    //   2: aload_0
    //   3: getfield 236	com/skyhookwireless/_sdkfd:_sdkf	Lcom/skyhookwireless/_sdkhb;
    //   6: invokevirtual 359	com/skyhookwireless/_sdkhb:_sdkb	()Z
    //   9: ifeq +53 -> 62
    //   12: aload_0
    //   13: getfield 236	com/skyhookwireless/_sdkfd:_sdkf	Lcom/skyhookwireless/_sdkhb;
    //   16: astore_3
    //   17: new 361	java/lang/StringBuilder
    //   20: dup
    //   21: invokespecial 362	java/lang/StringBuilder:<init>	()V
    //   24: astore 4
    //   26: getstatic 205	com/skyhookwireless/_sdkfd:z	[Ljava/lang/String;
    //   29: bipush 18
    //   31: aaload
    //   32: astore 5
    //   34: aload 4
    //   36: aload 5
    //   38: invokevirtual 366	java/lang/StringBuilder:append	(Ljava/lang/String;)Ljava/lang/StringBuilder;
    //   41: lload_1
    //   42: invokevirtual 430	java/lang/StringBuilder:append	(J)Ljava/lang/StringBuilder;
    //   45: ldc_w 409
    //   48: invokevirtual 366	java/lang/StringBuilder:append	(Ljava/lang/String;)Ljava/lang/StringBuilder;
    //   51: invokevirtual 372	java/lang/StringBuilder:toString	()Ljava/lang/String;
    //   54: astore 6
    //   56: aload_3
    //   57: aload 6
    //   59: invokevirtual 374	com/skyhookwireless/_sdkhb:_sdkb	(Ljava/lang/String;)V
    //   62: aload_0
    //   63: invokespecial 269	com/skyhookwireless/_sdkfd:_sdkb	()V
    //   66: getstatic 213	com/skyhookwireless/_sdkfd:_sdkt	Z
    //   69: ifne +25 -> 94
    //   72: aload_0
    //   73: invokespecial 464	com/skyhookwireless/_sdkfd:_sdkf	()Z
    //   76: ifne +18 -> 94
    //   79: new 413	java/lang/AssertionError
    //   82: dup
    //   83: invokespecial 414	java/lang/AssertionError:<init>	()V
    //   86: athrow
    //   87: astore 7
    //   89: aload_0
    //   90: monitorexit
    //   91: aload 7
    //   93: athrow
    //   94: aload_0
    //   95: invokespecial 464	com/skyhookwireless/_sdkfd:_sdkf	()Z
    //   98: istore 8
    //   100: iload 8
    //   102: ifne +6 -> 108
    //   105: aload_0
    //   106: monitorexit
    //   107: return
    //   108: aload_0
    //   109: getfield 566	com/skyhookwireless/_sdkfd:_sdkp	J
    //   112: lstore 9
    //   114: aload_0
    //   115: lload_1
    //   116: putfield 566	com/skyhookwireless/_sdkfd:_sdkp	J
    //   119: aload_0
    //   120: invokevirtual 411	com/skyhookwireless/_sdkfd:_sdkd	()Z
    //   123: ifeq +410 -> 533
    //   126: aload_0
    //   127: getfield 236	com/skyhookwireless/_sdkfd:_sdkf	Lcom/skyhookwireless/_sdkhb;
    //   130: astore 11
    //   132: getstatic 205	com/skyhookwireless/_sdkfd:z	[Ljava/lang/String;
    //   135: bipush 19
    //   137: aaload
    //   138: astore 12
    //   140: aload 11
    //   142: aload 12
    //   144: invokevirtual 374	com/skyhookwireless/_sdkhb:_sdkb	(Ljava/lang/String;)V
    //   147: aload_0
    //   148: getfield 566	com/skyhookwireless/_sdkfd:_sdkp	J
    //   151: lload 9
    //   153: lcmp
    //   154: ifne +27 -> 181
    //   157: aload_0
    //   158: getfield 236	com/skyhookwireless/_sdkfd:_sdkf	Lcom/skyhookwireless/_sdkhb;
    //   161: astore 13
    //   163: getstatic 205	com/skyhookwireless/_sdkfd:z	[Ljava/lang/String;
    //   166: bipush 26
    //   168: aaload
    //   169: astore 14
    //   171: aload 13
    //   173: aload 14
    //   175: invokevirtual 374	com/skyhookwireless/_sdkhb:_sdkb	(Ljava/lang/String;)V
    //   178: goto -73 -> 105
    //   181: aload_0
    //   182: getfield 416	com/skyhookwireless/_sdkfd:_sdkn	Z
    //   185: ifeq +27 -> 212
    //   188: aload_0
    //   189: getfield 236	com/skyhookwireless/_sdkfd:_sdkf	Lcom/skyhookwireless/_sdkhb;
    //   192: astore 15
    //   194: getstatic 205	com/skyhookwireless/_sdkfd:z	[Ljava/lang/String;
    //   197: bipush 27
    //   199: aaload
    //   200: astore 16
    //   202: aload 15
    //   204: aload 16
    //   206: invokevirtual 374	com/skyhookwireless/_sdkhb:_sdkb	(Ljava/lang/String;)V
    //   209: goto -104 -> 105
    //   212: aload_0
    //   213: getfield 267	com/skyhookwireless/_sdkfd:_sdkr	Z
    //   216: ifne +32 -> 248
    //   219: aload_0
    //   220: getfield 236	com/skyhookwireless/_sdkfd:_sdkf	Lcom/skyhookwireless/_sdkhb;
    //   223: astore 17
    //   225: getstatic 205	com/skyhookwireless/_sdkfd:z	[Ljava/lang/String;
    //   228: bipush 25
    //   230: aaload
    //   231: astore 18
    //   233: aload 17
    //   235: aload 18
    //   237: invokevirtual 374	com/skyhookwireless/_sdkhb:_sdkb	(Ljava/lang/String;)V
    //   240: aload_0
    //   241: iconst_1
    //   242: invokespecial 324	com/skyhookwireless/_sdkfd:_sdka	(Z)V
    //   245: goto -140 -> 105
    //   248: aload_0
    //   249: getfield 316	com/skyhookwireless/_sdkfd:_sdks	Ljava/util/concurrent/FutureTask;
    //   252: ifnonnull +27 -> 279
    //   255: aload_0
    //   256: getfield 236	com/skyhookwireless/_sdkfd:_sdkf	Lcom/skyhookwireless/_sdkhb;
    //   259: astore 19
    //   261: getstatic 205	com/skyhookwireless/_sdkfd:z	[Ljava/lang/String;
    //   264: bipush 21
    //   266: aaload
    //   267: astore 20
    //   269: aload 19
    //   271: aload 20
    //   273: invokevirtual 374	com/skyhookwireless/_sdkhb:_sdkb	(Ljava/lang/String;)V
    //   276: goto -171 -> 105
    //   279: aload_0
    //   280: invokevirtual 421	com/skyhookwireless/_sdkfd:_sdki	()J
    //   283: astore 21
    //   285: aload_0
    //   286: getfield 236	com/skyhookwireless/_sdkfd:_sdkf	Lcom/skyhookwireless/_sdkhb;
    //   289: invokevirtual 359	com/skyhookwireless/_sdkhb:_sdkb	()Z
    //   292: ifeq +50 -> 342
    //   295: aload_0
    //   296: getfield 236	com/skyhookwireless/_sdkfd:_sdkf	Lcom/skyhookwireless/_sdkhb;
    //   299: astore 22
    //   301: new 361	java/lang/StringBuilder
    //   304: dup
    //   305: invokespecial 362	java/lang/StringBuilder:<init>	()V
    //   308: astore 23
    //   310: getstatic 205	com/skyhookwireless/_sdkfd:z	[Ljava/lang/String;
    //   313: bipush 30
    //   315: aaload
    //   316: astore 24
    //   318: aload 23
    //   320: aload 24
    //   322: invokevirtual 366	java/lang/StringBuilder:append	(Ljava/lang/String;)Ljava/lang/StringBuilder;
    //   325: aload 21
    //   327: invokevirtual 430	java/lang/StringBuilder:append	(J)Ljava/lang/StringBuilder;
    //   330: invokevirtual 372	java/lang/StringBuilder:toString	()Ljava/lang/String;
    //   333: astore 25
    //   335: aload 22
    //   337: aload 25
    //   339: invokevirtual 374	com/skyhookwireless/_sdkhb:_sdkb	(Ljava/lang/String;)V
    //   342: aload 21
    //   344: ldc2_w 567
    //   347: lcmp
    //   348: ifgt +31 -> 379
    //   351: aload_0
    //   352: getfield 236	com/skyhookwireless/_sdkfd:_sdkf	Lcom/skyhookwireless/_sdkhb;
    //   355: astore 26
    //   357: getstatic 205	com/skyhookwireless/_sdkfd:z	[Ljava/lang/String;
    //   360: bipush 23
    //   362: aaload
    //   363: astore 27
    //   365: aload 26
    //   367: aload 27
    //   369: invokevirtual 374	com/skyhookwireless/_sdkhb:_sdkb	(Ljava/lang/String;)V
    //   372: aload_0
    //   373: invokespecial 512	com/skyhookwireless/_sdkfd:_sdkh	()V
    //   376: goto -271 -> 105
    //   379: aload_0
    //   380: aload 21
    //   382: invokespecial 425	com/skyhookwireless/_sdkfd:_sdka	(J)Ljava/util/concurrent/FutureTask;
    //   385: astore 21
    //   387: aload 21
    //   389: ifnull +37 -> 426
    //   392: aload_0
    //   393: getfield 236	com/skyhookwireless/_sdkfd:_sdkf	Lcom/skyhookwireless/_sdkhb;
    //   396: astore 28
    //   398: getstatic 205	com/skyhookwireless/_sdkfd:z	[Ljava/lang/String;
    //   401: bipush 17
    //   403: aaload
    //   404: astore 29
    //   406: aload 28
    //   408: aload 29
    //   410: invokevirtual 374	com/skyhookwireless/_sdkhb:_sdkb	(Ljava/lang/String;)V
    //   413: aload_0
    //   414: invokespecial 543	com/skyhookwireless/_sdkfd:_sdkl	()V
    //   417: aload_0
    //   418: aload 21
    //   420: putfield 316	com/skyhookwireless/_sdkfd:_sdks	Ljava/util/concurrent/FutureTask;
    //   423: goto -318 -> 105
    //   426: aload_0
    //   427: getfield 236	com/skyhookwireless/_sdkfd:_sdkf	Lcom/skyhookwireless/_sdkhb;
    //   430: astore 30
    //   432: getstatic 205	com/skyhookwireless/_sdkfd:z	[Ljava/lang/String;
    //   435: bipush 20
    //   437: aaload
    //   438: astore 31
    //   440: aload 30
    //   442: aload 31
    //   444: invokevirtual 427	com/skyhookwireless/_sdkhb:_sdkd	(Ljava/lang/String;)V
    //   447: aload_0
    //   448: getfield 566	com/skyhookwireless/_sdkfd:_sdkp	J
    //   451: lload 9
    //   453: lcmp
    //   454: ifle +27 -> 481
    //   457: aload_0
    //   458: getfield 236	com/skyhookwireless/_sdkfd:_sdkf	Lcom/skyhookwireless/_sdkhb;
    //   461: astore 32
    //   463: getstatic 205	com/skyhookwireless/_sdkfd:z	[Ljava/lang/String;
    //   466: bipush 22
    //   468: aaload
    //   469: astore 33
    //   471: aload 32
    //   473: aload 33
    //   475: invokevirtual 374	com/skyhookwireless/_sdkhb:_sdkb	(Ljava/lang/String;)V
    //   478: goto -373 -> 105
    //   481: getstatic 213	com/skyhookwireless/_sdkfd:_sdkt	Z
    //   484: ifne +21 -> 505
    //   487: aload_0
    //   488: getfield 566	com/skyhookwireless/_sdkfd:_sdkp	J
    //   491: lload 9
    //   493: lcmp
    //   494: iflt +11 -> 505
    //   497: new 413	java/lang/AssertionError
    //   500: dup
    //   501: invokespecial 414	java/lang/AssertionError:<init>	()V
    //   504: athrow
    //   505: aload_0
    //   506: getfield 236	com/skyhookwireless/_sdkfd:_sdkf	Lcom/skyhookwireless/_sdkhb;
    //   509: astore 34
    //   511: getstatic 205	com/skyhookwireless/_sdkfd:z	[Ljava/lang/String;
    //   514: bipush 16
    //   516: aaload
    //   517: astore 35
    //   519: aload 34
    //   521: aload 35
    //   523: invokevirtual 374	com/skyhookwireless/_sdkhb:_sdkb	(Ljava/lang/String;)V
    //   526: aload_0
    //   527: invokespecial 512	com/skyhookwireless/_sdkfd:_sdkh	()V
    //   530: goto -425 -> 105
    //   533: aload_0
    //   534: iconst_1
    //   535: putfield 265	com/skyhookwireless/_sdkfd:_sdkq	Z
    //   538: aload_0
    //   539: invokespecial 512	com/skyhookwireless/_sdkfd:_sdkh	()V
    //   542: aload_0
    //   543: getfield 510	com/skyhookwireless/_sdkfd:_sdkj	Landroid/net/wifi/WifiManager;
    //   546: invokevirtual 574	java/lang/Object:getClass	()Ljava/lang/Class;
    //   549: astore 36
    //   551: getstatic 205	com/skyhookwireless/_sdkfd:z	[Ljava/lang/String;
    //   554: bipush 15
    //   556: aaload
    //   557: astore 37
    //   559: iconst_0
    //   560: anewarray 207	java/lang/Class
    //   563: astore 38
    //   565: aload 36
    //   567: aload 37
    //   569: aload 38
    //   571: invokevirtual 578	java/lang/Class:getMethod	(Ljava/lang/String;[Ljava/lang/Class;)Ljava/lang/reflect/Method;
    //   574: astore 39
    //   576: aload_0
    //   577: aload 39
    //   579: putfield 263	com/skyhookwireless/_sdkfd:_sdkk	Ljava/lang/reflect/Method;
    //   582: aload_0
    //   583: getfield 263	com/skyhookwireless/_sdkfd:_sdkk	Ljava/lang/reflect/Method;
    //   586: invokevirtual 583	java/lang/reflect/Method:isAccessible	()Z
    //   589: ifne +11 -> 600
    //   592: aload_0
    //   593: getfield 263	com/skyhookwireless/_sdkfd:_sdkk	Ljava/lang/reflect/Method;
    //   596: iconst_1
    //   597: invokevirtual 586	java/lang/reflect/Method:setAccessible	(Z)V
    //   600: aload_0
    //   601: getfield 236	com/skyhookwireless/_sdkfd:_sdkf	Lcom/skyhookwireless/_sdkhb;
    //   604: astore 40
    //   606: getstatic 205	com/skyhookwireless/_sdkfd:z	[Ljava/lang/String;
    //   609: bipush 29
    //   611: aaload
    //   612: astore 41
    //   614: aload 40
    //   616: aload 41
    //   618: invokevirtual 374	com/skyhookwireless/_sdkhb:_sdkb	(Ljava/lang/String;)V
    //   621: goto -516 -> 105
    //   624: astore 42
    //   626: aload_0
    //   627: getfield 236	com/skyhookwireless/_sdkfd:_sdkf	Lcom/skyhookwireless/_sdkhb;
    //   630: astore 43
    //   632: getstatic 205	com/skyhookwireless/_sdkfd:z	[Ljava/lang/String;
    //   635: bipush 24
    //   637: aaload
    //   638: astore 44
    //   640: aload 43
    //   642: aload 44
    //   644: invokevirtual 374	com/skyhookwireless/_sdkhb:_sdkb	(Ljava/lang/String;)V
    //   647: goto -542 -> 105
    //   650: astore 45
    //   652: aload_0
    //   653: aconst_null
    //   654: putfield 263	com/skyhookwireless/_sdkfd:_sdkk	Ljava/lang/reflect/Method;
    //   657: aload_0
    //   658: getfield 236	com/skyhookwireless/_sdkfd:_sdkf	Lcom/skyhookwireless/_sdkhb;
    //   661: astore 46
    //   663: getstatic 205	com/skyhookwireless/_sdkfd:z	[Ljava/lang/String;
    //   666: bipush 28
    //   668: aaload
    //   669: astore 47
    //   671: aload 46
    //   673: aload 47
    //   675: invokevirtual 374	com/skyhookwireless/_sdkhb:_sdkb	(Ljava/lang/String;)V
    //   678: goto -573 -> 105
    //   681: astore 48
    //   683: goto -578 -> 105
    //
    // Exception table:
    //   from	to	target	type
    //   2	62	87	finally
    //   62	66	87	finally
    //   66	87	87	finally
    //   94	100	87	finally
    //   108	542	87	finally
    //   542	621	87	finally
    //   626	678	87	finally
    //   542	621	624	java/lang/NoSuchMethodException
    //   542	621	650	java/lang/SecurityException
    //   62	66	681	com/skyhookwireless/_sdkn
  }

  /** @deprecated */
  public void _sdka(ArrayList<_sdkjc> paramArrayList)
  {
    try
    {
      ArrayList localArrayList = this._sdkm;
      boolean bool = paramArrayList.addAll(localArrayList);
      _sdkhb local_sdkhb = this._sdkf;
      String str = z[37];
      local_sdkhb._sdkb(str);
      this._sdkm.clear();
      return;
    }
    finally
    {
      localObject = finally;
      throw localObject;
    }
  }

  /** @deprecated */
  public boolean _sdka()
  {
    while (true)
    {
      boolean bool1;
      boolean bool2;
      boolean bool3;
      WifiInfo localWifiInfo;
      try
      {
        bool1 = _sdkic._sdkc;
        _sdkhb local_sdkhb1 = this._sdkf;
        String str1 = z[56];
        local_sdkhb1._sdkb(str1);
        bool2 = this._sdkf._sdkb();
        if (!_sdkd())
        {
          _sdkhb local_sdkhb2 = this._sdkf;
          String str2 = z[58];
          local_sdkhb2._sdkb(str2);
          bool3 = false;
          return bool3;
        }
        _sdkh();
        if (!_sdke())
        {
          _sdkhb local_sdkhb3 = this._sdkf;
          StringBuilder localStringBuilder1 = new StringBuilder();
          String str3 = z[54];
          StringBuilder localStringBuilder2 = localStringBuilder1.append(str3);
          int i = this._sdkj.getWifiState();
          StringBuilder localStringBuilder3 = localStringBuilder2.append(i);
          String str4 = z[51];
          String str5 = str4;
          local_sdkhb3._sdkb(str5);
          bool3 = false;
          continue;
        }
        localWifiInfo = this._sdkj.getConnectionInfo();
        if ((!_sdkt) && (localWifiInfo == null))
          throw new AssertionError();
      }
      finally
      {
      }
      long l1 = System.currentTimeMillis();
      _sdkec local_sdkec1 = _sdkec._sdkd();
      _sdkjc local_sdkjc = _sdka(localWifiInfo, l1, local_sdkec1);
      int j;
      if (local_sdkjc != null)
        j = 1;
      Object localObject2;
      while (true)
        if (j != 0)
        {
          if (bool2)
          {
            _sdkhb local_sdkhb4 = this._sdkf;
            StringBuilder localStringBuilder4 = new StringBuilder();
            String str6 = z[55];
            String str7 = str6 + j;
            local_sdkhb4._sdkb(str7);
          }
          localObject2 = this._sdkj.getScanResults();
          if ((localObject2 != null) && (!((List)localObject2).isEmpty()))
          {
            ArrayList localArrayList1 = this._sdkm;
            _sdka((List)localObject2, l1, local_sdkec1, localArrayList1);
            if (bool2)
            {
              _sdkhb local_sdkhb5 = this._sdkf;
              StringBuilder localStringBuilder5 = new StringBuilder();
              String str8 = z[61];
              StringBuilder localStringBuilder6 = localStringBuilder5.append(str8);
              ArrayList localArrayList2 = this._sdkm;
              String str9 = localArrayList2;
              local_sdkhb5._sdkb(str9);
              if (!bool1);
            }
          }
          else
          {
            _sdkhb local_sdkhb6 = this._sdkf;
            String str10 = z[66];
            local_sdkhb6._sdkb(str10);
          }
          if (_sdka(this._sdkm, j))
          {
            _sdkhb local_sdkhb7 = this._sdkf;
            String str11 = z[65];
            local_sdkhb7._sdkb(str11);
            _sdkec local_sdkec2 = _sdkec._sdkd();
            this._sdko = local_sdkec2;
            _sdka(true);
            _sdka();
            bool3 = true;
            break;
            j = 0;
            continue;
          }
          _sdkhb local_sdkhb8 = this._sdkf;
          String str12 = z[57];
          local_sdkhb8._sdkb(str12);
        }
      SupplicantState localSupplicantState1 = localWifiInfo.getSupplicantState();
      if (SupplicantState.isValidState(localSupplicantState1))
      {
        localObject2 = WifiInfo.getDetailedStateOf(localSupplicantState1);
        if (bool2)
        {
          _sdkhb local_sdkhb9 = this._sdkf;
          StringBuilder localStringBuilder7 = new StringBuilder();
          String str13 = z[63];
          StringBuilder localStringBuilder8 = localStringBuilder7.append(str13).append(localObject2);
          String str14 = z[64];
          String str15 = str14 + localSupplicantState1 + ")";
          local_sdkhb9._sdkb(str15);
        }
        NetworkInfo.DetailedState localDetailedState1 = NetworkInfo.DetailedState.SCANNING;
        if ((localObject2 == localDetailedState1) && (_sdkb()))
        {
          _sdkhb local_sdkhb10 = this._sdkf;
          String str16 = z[60];
          local_sdkhb10._sdkb(str16);
          bool3 = true;
          continue;
        }
        NetworkInfo.DetailedState localDetailedState2 = NetworkInfo.DetailedState.AUTHENTICATING;
        if (localObject2 != localDetailedState2)
        {
          NetworkInfo.DetailedState localDetailedState3 = NetworkInfo.DetailedState.CONNECTING;
          if (localObject2 != localDetailedState3)
          {
            NetworkInfo.DetailedState localDetailedState4 = NetworkInfo.DetailedState.OBTAINING_IPADDR;
            if ((localObject2 != localDetailedState4) || (localWifiInfo.getIpAddress() != 0))
              break label718;
          }
        }
        _sdkhb local_sdkhb11 = this._sdkf;
        String str17 = z[50];
        local_sdkhb11._sdkb(str17);
        bool3 = false;
        continue;
        label718: SupplicantState localSupplicantState2 = SupplicantState.ASSOCIATING;
        if (localSupplicantState1 != localSupplicantState2)
        {
          SupplicantState localSupplicantState3 = SupplicantState.FOUR_WAY_HANDSHAKE;
          if (localSupplicantState1 != localSupplicantState3)
          {
            SupplicantState localSupplicantState4 = SupplicantState.GROUP_HANDSHAKE;
            if (localSupplicantState1 != localSupplicantState4)
              break label781;
          }
        }
        _sdkhb local_sdkhb12 = this._sdkf;
        String str18 = z[53];
        local_sdkhb12._sdkb(str18);
        bool3 = false;
        continue;
      }
      label781: if (_sdkb())
      {
        long l2 = this._sdko._sdka();
        if (bool2)
        {
          _sdkhb local_sdkhb13 = this._sdkf;
          StringBuilder localStringBuilder9 = new StringBuilder();
          String str19 = z[52];
          String str20 = str19 + l2;
          local_sdkhb13._sdkb(str20);
        }
        bool3 = true;
        continue;
      }
      if (!this._sdkl._sdkc())
      {
        this._sdkl._sdka();
        if (!bool1);
      }
      else
      {
        _sdkhb local_sdkhb14 = this._sdkf;
        String str21 = z[67];
        local_sdkhb14._sdkb(str21);
      }
      this._sdkn = false;
      Method localMethod1 = this._sdkk;
      if ((localMethod1 != null) && (j == 0));
      try
      {
        Method localMethod2 = this._sdkk;
        WifiManager localWifiManager = this._sdkj;
        Object[] arrayOfObject = new Object[0];
        boolean bool4 = ((Boolean)localMethod2.invoke(localWifiManager, arrayOfObject)).booleanValue();
        this._sdkn = bool4;
        boolean bool5 = _sdkc();
        bool3 = bool5;
      }
      catch (IllegalAccessException localIllegalAccessException)
      {
        _sdkhb local_sdkhb15 = this._sdkf;
        String str22 = z[28];
        local_sdkhb15._sdkb(str22, localIllegalAccessException);
        this._sdkk = null;
        if ((!_sdkt) && (this._sdkn))
          throw new AssertionError();
      }
      catch (SecurityException localSecurityException)
      {
        while (true)
        {
          _sdkhb local_sdkhb16 = this._sdkf;
          String str23 = z[28];
          local_sdkhb16._sdkb(str23, localSecurityException);
          this._sdkk = null;
        }
      }
      catch (InvocationTargetException localInvocationTargetException)
      {
        while (true)
        {
          _sdkhb local_sdkhb17 = this._sdkf;
          String str24 = z[62];
          Throwable localThrowable = localInvocationTargetException.getTargetException();
          local_sdkhb17._sdkb(str24, localThrowable);
        }
      }
      catch (ClassCastException localClassCastException)
      {
        while (true)
        {
          _sdkhb local_sdkhb18 = this._sdkf;
          String str25 = localClassCastException.toString();
          local_sdkhb18._sdkb(str25);
        }
      }
      catch (IllegalArgumentException localIllegalArgumentException)
      {
        while (true)
        {
          _sdkhb local_sdkhb19 = this._sdkf;
          String str26 = localIllegalArgumentException.toString();
          local_sdkhb19._sdkb(str26);
        }
      }
      try
      {
        boolean bool6 = this._sdkj.startScan();
        this._sdkn = bool6;
        bool3 = _sdkc();
      }
      catch (Exception localException)
      {
        while (true)
        {
          _sdkhb local_sdkhb20 = this._sdkf;
          String str27 = z[59];
          local_sdkhb20._sdkd(str27);
        }
      }
    }
  }

  /** @deprecated */
  public boolean _sdkb()
  {
    try
    {
      if (this._sdkn)
      {
        long l = this._sdko._sdka();
        if (l < 20000L)
        {
          bool = true;
          return bool;
        }
      }
      boolean bool = false;
    }
    finally
    {
    }
  }

  /** @deprecated */
  public String _sdkc()
  {
    Object localObject1 = null;
    try
    {
      _sdkhb local_sdkhb1 = this._sdkf;
      String str1 = z[4];
      local_sdkhb1._sdkb(str1);
      if (!_sdkf())
      {
        _sdkhb local_sdkhb2 = this._sdkf;
        String str2 = z[7];
        local_sdkhb2._sdke(str2);
      }
      while (true)
      {
        return localObject1;
        try
        {
          String str3 = this._sdkj.getConnectionInfo().getMacAddress().replaceAll(":", "");
          if (this._sdkf._sdkb())
          {
            _sdkhb local_sdkhb3 = this._sdkf;
            StringBuilder localStringBuilder = new StringBuilder();
            String str4 = z[5];
            String str5 = str4 + str3;
            local_sdkhb3._sdkb(str5);
          }
          localObject1 = str3;
        }
        catch (NullPointerException localNullPointerException)
        {
          _sdkhb local_sdkhb4 = this._sdkf;
          String str6 = z[6];
          local_sdkhb4._sdke(str6, localNullPointerException);
        }
      }
    }
    finally
    {
    }
  }

  /** @deprecated */
  public boolean _sdkd()
  {
    try
    {
      boolean bool = this._sdkq;
      return bool;
    }
    finally
    {
      localObject = finally;
      throw localObject;
    }
  }

  /** @deprecated */
  public boolean _sdke()
  {
    boolean bool = false;
    try
    {
      if (!_sdkd())
      {
        _sdkhb local_sdkhb = this._sdkf;
        String str = z[8];
        local_sdkhb._sdkb(str);
      }
      while (true)
      {
        return bool;
        int i = this._sdkj.getWifiState();
        if (i == 3)
          bool = true;
      }
    }
    finally
    {
    }
  }

  /** @deprecated */
  public void _sdkf()
  {
    try
    {
      _sdkhb local_sdkhb1 = this._sdkf;
      String str1 = z[2];
      local_sdkhb1._sdkb(str1);
      if (!_sdkd())
      {
        _sdkhb local_sdkhb2 = this._sdkf;
        String str2 = z[0];
        local_sdkhb2._sdkb(str2);
      }
      while (true)
      {
        return;
        _sdkhb local_sdkhb3 = this._sdkf;
        String str3 = z[1];
        local_sdkhb3._sdkb(str3);
        _sdkl();
        _sdka(false);
        this._sdkl._sdkb();
        this._sdkn = false;
        this._sdkq = false;
      }
    }
    finally
    {
    }
  }

  /** @deprecated */
  // ERROR //
  public void _sdkg()
  {
    // Byte code:
    //   0: aload_0
    //   1: monitorenter
    //   2: aload_0
    //   3: getfield 236	com/skyhookwireless/_sdkfd:_sdkf	Lcom/skyhookwireless/_sdkhb;
    //   6: astore_1
    //   7: getstatic 205	com/skyhookwireless/_sdkfd:z	[Ljava/lang/String;
    //   10: bipush 71
    //   12: aaload
    //   13: astore_2
    //   14: aload_1
    //   15: aload_2
    //   16: invokevirtual 374	com/skyhookwireless/_sdkhb:_sdkb	(Ljava/lang/String;)V
    //   19: aload_0
    //   20: invokevirtual 706	com/skyhookwireless/_sdkfd:_sdkf	()V
    //   23: aload_0
    //   24: invokespecial 464	com/skyhookwireless/_sdkfd:_sdkf	()Z
    //   27: ifne +25 -> 52
    //   30: aload_0
    //   31: getfield 236	com/skyhookwireless/_sdkfd:_sdkf	Lcom/skyhookwireless/_sdkhb;
    //   34: astore_3
    //   35: getstatic 205	com/skyhookwireless/_sdkfd:z	[Ljava/lang/String;
    //   38: bipush 70
    //   40: aaload
    //   41: astore 4
    //   43: aload_3
    //   44: aload 4
    //   46: invokevirtual 374	com/skyhookwireless/_sdkhb:_sdkb	(Ljava/lang/String;)V
    //   49: aload_0
    //   50: monitorexit
    //   51: return
    //   52: aload_0
    //   53: getfield 236	com/skyhookwireless/_sdkfd:_sdkf	Lcom/skyhookwireless/_sdkhb;
    //   56: astore 5
    //   58: getstatic 205	com/skyhookwireless/_sdkfd:z	[Ljava/lang/String;
    //   61: bipush 69
    //   63: aaload
    //   64: astore 6
    //   66: aload 5
    //   68: aload 6
    //   70: invokevirtual 374	com/skyhookwireless/_sdkhb:_sdkb	(Ljava/lang/String;)V
    //   73: aload_0
    //   74: getfield 244	com/skyhookwireless/_sdkfd:_sdkg	Landroid/content/Context;
    //   77: astore 7
    //   79: aload_0
    //   80: getfield 251	com/skyhookwireless/_sdkfd:_sdkh	Lcom/skyhookwireless/_sdkb;
    //   83: astore 8
    //   85: aload 7
    //   87: aload 8
    //   89: invokevirtual 710	android/content/Context:unregisterReceiver	(Landroid/content/BroadcastReceiver;)V
    //   92: aload_0
    //   93: getfield 236	com/skyhookwireless/_sdkfd:_sdkf	Lcom/skyhookwireless/_sdkhb;
    //   96: astore 9
    //   98: getstatic 205	com/skyhookwireless/_sdkfd:z	[Ljava/lang/String;
    //   101: bipush 72
    //   103: aaload
    //   104: astore 10
    //   106: aload 9
    //   108: aload 10
    //   110: invokevirtual 374	com/skyhookwireless/_sdkhb:_sdkb	(Ljava/lang/String;)V
    //   113: aload_0
    //   114: getfield 256	com/skyhookwireless/_sdkfd:_sdkm	Ljava/util/ArrayList;
    //   117: invokevirtual 489	java/util/ArrayList:clear	()V
    //   120: aload_0
    //   121: aconst_null
    //   122: putfield 496	com/skyhookwireless/_sdkfd:_sdkl	Lcom/skyhookwireless/_sdklc;
    //   125: aload_0
    //   126: aconst_null
    //   127: putfield 510	com/skyhookwireless/_sdkfd:_sdkj	Landroid/net/wifi/WifiManager;
    //   130: goto -81 -> 49
    //   133: astore 11
    //   135: aload_0
    //   136: monitorexit
    //   137: aload 11
    //   139: athrow
    //   140: astore 12
    //   142: aload_0
    //   143: getfield 236	com/skyhookwireless/_sdkfd:_sdkf	Lcom/skyhookwireless/_sdkhb;
    //   146: astore 13
    //   148: getstatic 205	com/skyhookwireless/_sdkfd:z	[Ljava/lang/String;
    //   151: bipush 68
    //   153: aaload
    //   154: astore 14
    //   156: aload 13
    //   158: aload 14
    //   160: aload 12
    //   162: invokevirtual 712	com/skyhookwireless/_sdkhb:_sdkd	(Ljava/lang/String;Ljava/lang/Throwable;)V
    //   165: aload_0
    //   166: getfield 256	com/skyhookwireless/_sdkfd:_sdkm	Ljava/util/ArrayList;
    //   169: invokevirtual 489	java/util/ArrayList:clear	()V
    //   172: aload_0
    //   173: aconst_null
    //   174: putfield 496	com/skyhookwireless/_sdkfd:_sdkl	Lcom/skyhookwireless/_sdklc;
    //   177: aload_0
    //   178: aconst_null
    //   179: putfield 510	com/skyhookwireless/_sdkfd:_sdkj	Landroid/net/wifi/WifiManager;
    //   182: goto -133 -> 49
    //   185: astore 15
    //   187: aload_0
    //   188: getfield 256	com/skyhookwireless/_sdkfd:_sdkm	Ljava/util/ArrayList;
    //   191: invokevirtual 489	java/util/ArrayList:clear	()V
    //   194: aload_0
    //   195: aconst_null
    //   196: putfield 496	com/skyhookwireless/_sdkfd:_sdkl	Lcom/skyhookwireless/_sdklc;
    //   199: aload_0
    //   200: aconst_null
    //   201: putfield 510	com/skyhookwireless/_sdkfd:_sdkj	Landroid/net/wifi/WifiManager;
    //   204: aload 15
    //   206: athrow
    //
    // Exception table:
    //   from	to	target	type
    //   2	49	133	finally
    //   52	73	133	finally
    //   113	130	133	finally
    //   165	207	133	finally
    //   73	113	140	java/lang/IllegalArgumentException
    //   73	113	185	finally
    //   142	165	185	finally
  }

  public String _sdkh()
  {
    return z[31];
  }

  long _sdki()
  {
    if (this._sdko == null);
    long l2;
    long l3;
    for (long l1 = 0L; ; l1 = l2 - l3 - 10000L)
    {
      return l1;
      l2 = this._sdkp;
      l3 = this._sdko._sdka();
    }
  }

  /** @deprecated */
  public boolean _sdki()
  {
    boolean bool1 = false;
    try
    {
      boolean bool2 = _sdkf();
      if (bool2 == null);
      while (true)
      {
        return bool1;
        WifiInfo localWifiInfo = this._sdkj.getConnectionInfo();
        long l = System.currentTimeMillis();
        _sdkec local_sdkec = _sdkec._sdkd();
        _sdkjc local_sdkjc = _sdka(localWifiInfo, l, local_sdkec);
        if (local_sdkjc != null)
          bool1 = true;
      }
    }
    finally
    {
    }
  }

  public String toString()
  {
    return _sdkh();
  }
}

/* Location:           D:\Tools\extractapktools\extractapktools\dex2jar-0.0.7.11-SNAPSHOT\classes_dex2jar.jar
 * Qualified Name:     com.skyhookwireless._sdkfd
 * JD-Core Version:    0.6.2
 */