package com.skyhookwireless.wps;

import com.skyhookwireless._sdkdd;
import com.skyhookwireless._sdkec;
import com.skyhookwireless._sdkhb;
import com.skyhookwireless._sdkp;
import com.skyhookwireless._sdkpb;
import com.skyhookwireless._sdkt;
import com.skyhookwireless._sdktb;
import com.skyhookwireless._sdktd;
import java.io.UnsupportedEncodingException;
import java.security.MessageDigest;
import java.security.NoSuchAlgorithmException;
import java.util.ArrayList;
import java.util.List;

abstract class _sdkf
  implements _sdkw
{
  static final boolean _sdkl;
  private static final String[] z;
  protected final _sdkhb _sdka;
  private final _sdkm _sdkb;
  private final _sdkm _sdkc;
  protected _sdkt _sdkd;
  protected final _sdknb _sdke;
  private final _sdkqb _sdkf;
  private final String _sdkg;
  private volatile _sdktd<WPSAuthentication, WPSAuthentication> _sdkh;
  private volatile _sdktd<WPSAuthentication, WPSAuthentication> _sdki;
  private _sdkec _sdkj;
  private _sdkec _sdkk;

  // ERROR //
  static
  {
    // Byte code:
    //   0: iconst_1
    //   1: istore_0
    //   2: bipush 63
    //   4: anewarray 34	java/lang/String
    //   7: astore_1
    //   8: ldc 36
    //   10: invokevirtual 40	java/lang/String:toCharArray	()[C
    //   13: astore_2
    //   14: aload_2
    //   15: arraylength
    //   16: istore_3
    //   17: iload_3
    //   18: iload_0
    //   19: if_icmpgt +16115 -> 16134
    //   22: iconst_0
    //   23: istore 4
    //   25: aload_2
    //   26: astore 5
    //   28: iload 4
    //   30: istore 6
    //   32: iload_3
    //   33: istore 7
    //   35: aload_2
    //   36: astore 8
    //   38: iload 7
    //   40: istore 9
    //   42: aload 8
    //   44: iload 4
    //   46: caload
    //   47: istore 10
    //   49: iload 6
    //   51: iconst_5
    //   52: irem
    //   53: tableswitch	default:+31 -> 84, 0:+13545->13598, 1:+13552->13605, 2:+13559->13612, 3:+13566->13619
    //   85: lconst_1
    //   86: istore 11
    //   88: iload 11
    //   90: iload 10
    //   92: ixor
    //   93: i2c
    //   94: istore 12
    //   96: aload 8
    //   98: iload 4
    //   100: iload 12
    //   102: castore
    //   103: iload 6
    //   105: iconst_1
    //   106: iadd
    //   107: istore 4
    //   109: iload 9
    //   111: ifne +18 -> 129
    //   114: aload 5
    //   116: astore 8
    //   118: iload 4
    //   120: istore 6
    //   122: iload 9
    //   124: istore 4
    //   126: goto -84 -> 42
    //   129: iload 9
    //   131: istore_3
    //   132: aload 5
    //   134: astore_2
    //   135: iload_3
    //   136: iload 4
    //   138: if_icmpgt -113 -> 25
    //   141: new 34	java/lang/String
    //   144: dup
    //   145: aload_2
    //   146: invokespecial 44	java/lang/String:<init>	([C)V
    //   149: invokevirtual 48	java/lang/String:intern	()Ljava/lang/String;
    //   152: astore 13
    //   154: aload_1
    //   155: iconst_0
    //   156: aload 13
    //   158: aastore
    //   159: ldc 50
    //   161: invokevirtual 40	java/lang/String:toCharArray	()[C
    //   164: astore 14
    //   166: aload 14
    //   168: arraylength
    //   169: istore 15
    //   171: iload 15
    //   173: iconst_1
    //   174: if_icmpgt +15954 -> 16128
    //   177: iconst_0
    //   178: istore 16
    //   180: aload 14
    //   182: astore 5
    //   184: iload 16
    //   186: istore 6
    //   188: iload 15
    //   190: istore 17
    //   192: aload 14
    //   194: astore 18
    //   196: iload 17
    //   198: istore 19
    //   200: aload 18
    //   202: iload 16
    //   204: caload
    //   205: istore 10
    //   207: iload 6
    //   209: iconst_5
    //   210: irem
    //   211: tableswitch	default:+29 -> 240, 0:+13415->13626, 1:+13422->13633, 2:+13429->13640, 3:+13436->13647
    //   241: lconst_1
    //   242: istore 20
    //   244: iload 20
    //   246: iload 10
    //   248: ixor
    //   249: i2c
    //   250: istore 21
    //   252: aload 18
    //   254: iload 16
    //   256: iload 21
    //   258: castore
    //   259: iload 6
    //   261: iconst_1
    //   262: iadd
    //   263: istore 16
    //   265: iload 19
    //   267: ifne +18 -> 285
    //   270: aload 5
    //   272: astore 18
    //   274: iload 16
    //   276: istore 22
    //   278: iload 19
    //   280: istore 16
    //   282: goto -82 -> 200
    //   285: iload 19
    //   287: istore 15
    //   289: aload 5
    //   291: astore 14
    //   293: iload 15
    //   295: iload 16
    //   297: if_icmpgt -117 -> 180
    //   300: new 34	java/lang/String
    //   303: dup
    //   304: aload 14
    //   306: invokespecial 44	java/lang/String:<init>	([C)V
    //   309: invokevirtual 48	java/lang/String:intern	()Ljava/lang/String;
    //   312: astore 23
    //   314: aload_1
    //   315: iconst_1
    //   316: aload 23
    //   318: aastore
    //   319: iconst_2
    //   320: istore 24
    //   322: ldc 52
    //   324: invokevirtual 40	java/lang/String:toCharArray	()[C
    //   327: astore 25
    //   329: aload 25
    //   331: arraylength
    //   332: istore 26
    //   334: iload 26
    //   336: iconst_1
    //   337: if_icmpgt +15785 -> 16122
    //   340: iconst_0
    //   341: istore 27
    //   343: aload 25
    //   345: astore 5
    //   347: iload 27
    //   349: istore 6
    //   351: iload 26
    //   353: istore 28
    //   355: aload 25
    //   357: astore 29
    //   359: iload 28
    //   361: istore 30
    //   363: aload 29
    //   365: iload 27
    //   367: caload
    //   368: istore 31
    //   370: iload 6
    //   372: iconst_5
    //   373: irem
    //   374: tableswitch	default:+30 -> 404, 0:+13280->13654, 1:+13287->13661, 2:+13294->13668, 3:+13301->13675
    //   405: lconst_1
    //   406: istore 32
    //   408: iload 32
    //   410: iload 31
    //   412: ixor
    //   413: i2c
    //   414: istore 33
    //   416: aload 29
    //   418: iload 27
    //   420: iload 33
    //   422: castore
    //   423: iload 6
    //   425: iconst_1
    //   426: iadd
    //   427: istore 27
    //   429: iload 30
    //   431: ifne +18 -> 449
    //   434: aload 5
    //   436: astore 29
    //   438: iload 27
    //   440: istore 34
    //   442: iload 30
    //   444: istore 27
    //   446: goto -83 -> 363
    //   449: iload 30
    //   451: istore 26
    //   453: aload 5
    //   455: astore 25
    //   457: iload 26
    //   459: iload 27
    //   461: if_icmpgt -118 -> 343
    //   464: new 34	java/lang/String
    //   467: dup
    //   468: aload 25
    //   470: invokespecial 44	java/lang/String:<init>	([C)V
    //   473: invokevirtual 48	java/lang/String:intern	()Ljava/lang/String;
    //   476: astore 35
    //   478: aload_1
    //   479: iload 24
    //   481: aload 35
    //   483: aastore
    //   484: iconst_3
    //   485: istore 36
    //   487: ldc 54
    //   489: invokevirtual 40	java/lang/String:toCharArray	()[C
    //   492: astore 37
    //   494: aload 37
    //   496: arraylength
    //   497: istore 38
    //   499: iload 38
    //   501: iconst_1
    //   502: if_icmpgt +15614 -> 16116
    //   505: iconst_0
    //   506: istore 39
    //   508: aload 37
    //   510: astore 5
    //   512: iload 39
    //   514: istore 6
    //   516: iload 38
    //   518: istore 40
    //   520: aload 37
    //   522: astore 41
    //   524: iload 40
    //   526: istore 42
    //   528: aload 41
    //   530: iload 39
    //   532: caload
    //   533: istore 31
    //   535: iload 6
    //   537: iconst_5
    //   538: irem
    //   539: tableswitch	default:+29 -> 568, 0:+13143->13682, 1:+13150->13689, 2:+13157->13696, 3:+13164->13703
    //   569: lconst_1
    //   570: istore 43
    //   572: iload 43
    //   574: iload 31
    //   576: ixor
    //   577: i2c
    //   578: istore 44
    //   580: aload 41
    //   582: iload 39
    //   584: iload 44
    //   586: castore
    //   587: iload 6
    //   589: iconst_1
    //   590: iadd
    //   591: istore 39
    //   593: iload 42
    //   595: ifne +18 -> 613
    //   598: aload 5
    //   600: astore 41
    //   602: iload 39
    //   604: istore 45
    //   606: iload 42
    //   608: istore 39
    //   610: goto -82 -> 528
    //   613: iload 42
    //   615: istore 38
    //   617: aload 5
    //   619: astore 37
    //   621: iload 38
    //   623: iload 39
    //   625: if_icmpgt -117 -> 508
    //   628: new 34	java/lang/String
    //   631: dup
    //   632: aload 37
    //   634: invokespecial 44	java/lang/String:<init>	([C)V
    //   637: invokevirtual 48	java/lang/String:intern	()Ljava/lang/String;
    //   640: astore 46
    //   642: aload_1
    //   643: iload 36
    //   645: aload 46
    //   647: aastore
    //   648: iconst_4
    //   649: istore 47
    //   651: ldc 56
    //   653: invokevirtual 40	java/lang/String:toCharArray	()[C
    //   656: astore 48
    //   658: aload 48
    //   660: arraylength
    //   661: istore 49
    //   663: iload 49
    //   665: iconst_1
    //   666: if_icmpgt +15444 -> 16110
    //   669: iconst_0
    //   670: istore 50
    //   672: aload 48
    //   674: astore 5
    //   676: iload 50
    //   678: istore 6
    //   680: iload 49
    //   682: istore 51
    //   684: aload 48
    //   686: astore 52
    //   688: iload 51
    //   690: istore 53
    //   692: aload 52
    //   694: iload 50
    //   696: caload
    //   697: istore 31
    //   699: iload 6
    //   701: iconst_5
    //   702: irem
    //   703: tableswitch	default:+29 -> 732, 0:+13007->13710, 1:+13014->13717, 2:+13021->13724, 3:+13028->13731
    //   733: lconst_1
    //   734: istore 54
    //   736: iload 54
    //   738: iload 31
    //   740: ixor
    //   741: i2c
    //   742: istore 55
    //   744: aload 52
    //   746: iload 50
    //   748: iload 55
    //   750: castore
    //   751: iload 6
    //   753: iconst_1
    //   754: iadd
    //   755: istore 50
    //   757: iload 53
    //   759: ifne +18 -> 777
    //   762: aload 5
    //   764: astore 52
    //   766: iload 50
    //   768: istore 56
    //   770: iload 53
    //   772: istore 50
    //   774: goto -82 -> 692
    //   777: iload 53
    //   779: istore 49
    //   781: aload 5
    //   783: astore 48
    //   785: iload 49
    //   787: iload 50
    //   789: if_icmpgt -117 -> 672
    //   792: new 34	java/lang/String
    //   795: dup
    //   796: aload 48
    //   798: invokespecial 44	java/lang/String:<init>	([C)V
    //   801: invokevirtual 48	java/lang/String:intern	()Ljava/lang/String;
    //   804: astore 57
    //   806: aload_1
    //   807: iload 47
    //   809: aload 57
    //   811: aastore
    //   812: iconst_5
    //   813: istore 58
    //   815: ldc 58
    //   817: invokevirtual 40	java/lang/String:toCharArray	()[C
    //   820: astore 59
    //   822: aload 59
    //   824: arraylength
    //   825: istore 60
    //   827: iload 60
    //   829: iconst_1
    //   830: if_icmpgt +15274 -> 16104
    //   833: iconst_0
    //   834: istore 61
    //   836: aload 59
    //   838: astore 5
    //   840: iload 61
    //   842: istore 6
    //   844: iload 60
    //   846: istore 62
    //   848: aload 59
    //   850: astore 63
    //   852: iload 62
    //   854: istore 64
    //   856: aload 63
    //   858: iload 61
    //   860: caload
    //   861: istore 31
    //   863: iload 6
    //   865: iconst_5
    //   866: irem
    //   867: tableswitch	default:+29 -> 896, 0:+12871->13738, 1:+12878->13745, 2:+12885->13752, 3:+12892->13759
    //   897: lconst_1
    //   898: istore 65
    //   900: iload 65
    //   902: iload 31
    //   904: ixor
    //   905: i2c
    //   906: istore 66
    //   908: aload 63
    //   910: iload 61
    //   912: iload 66
    //   914: castore
    //   915: iload 6
    //   917: iconst_1
    //   918: iadd
    //   919: istore 61
    //   921: iload 64
    //   923: ifne +18 -> 941
    //   926: aload 5
    //   928: astore 63
    //   930: iload 61
    //   932: istore 67
    //   934: iload 64
    //   936: istore 61
    //   938: goto -82 -> 856
    //   941: iload 64
    //   943: istore 60
    //   945: aload 5
    //   947: astore 59
    //   949: iload 60
    //   951: iload 61
    //   953: if_icmpgt -117 -> 836
    //   956: new 34	java/lang/String
    //   959: dup
    //   960: aload 59
    //   962: invokespecial 44	java/lang/String:<init>	([C)V
    //   965: invokevirtual 48	java/lang/String:intern	()Ljava/lang/String;
    //   968: astore 68
    //   970: aload_1
    //   971: iload 58
    //   973: aload 68
    //   975: aastore
    //   976: bipush 6
    //   978: istore 69
    //   980: ldc 60
    //   982: invokevirtual 40	java/lang/String:toCharArray	()[C
    //   985: astore 70
    //   987: aload 70
    //   989: arraylength
    //   990: istore 71
    //   992: iload 71
    //   994: iconst_1
    //   995: if_icmpgt +15103 -> 16098
    //   998: iconst_0
    //   999: istore 72
    //   1001: aload 70
    //   1003: astore 5
    //   1005: iload 72
    //   1007: istore 6
    //   1009: iload 71
    //   1011: istore 73
    //   1013: aload 70
    //   1015: astore 74
    //   1017: iload 73
    //   1019: istore 75
    //   1021: aload 74
    //   1023: iload 72
    //   1025: caload
    //   1026: istore 31
    //   1028: iload 6
    //   1030: iconst_5
    //   1031: irem
    //   1032: tableswitch	default:+32 -> 1064, 0:+12734->13766, 1:+12741->13773, 2:+12748->13780, 3:+12755->13787
    //   1065: lconst_1
    //   1066: istore 76
    //   1068: iload 76
    //   1070: iload 31
    //   1072: ixor
    //   1073: i2c
    //   1074: istore 77
    //   1076: aload 74
    //   1078: iload 72
    //   1080: iload 77
    //   1082: castore
    //   1083: iload 6
    //   1085: iconst_1
    //   1086: iadd
    //   1087: istore 72
    //   1089: iload 75
    //   1091: ifne +18 -> 1109
    //   1094: aload 5
    //   1096: astore 74
    //   1098: iload 72
    //   1100: istore 78
    //   1102: iload 75
    //   1104: istore 72
    //   1106: goto -85 -> 1021
    //   1109: iload 75
    //   1111: istore 71
    //   1113: aload 5
    //   1115: astore 70
    //   1117: iload 71
    //   1119: iload 72
    //   1121: if_icmpgt -120 -> 1001
    //   1124: new 34	java/lang/String
    //   1127: dup
    //   1128: aload 70
    //   1130: invokespecial 44	java/lang/String:<init>	([C)V
    //   1133: invokevirtual 48	java/lang/String:intern	()Ljava/lang/String;
    //   1136: astore 79
    //   1138: aload_1
    //   1139: iload 69
    //   1141: aload 79
    //   1143: aastore
    //   1144: bipush 7
    //   1146: istore 80
    //   1148: ldc 62
    //   1150: invokevirtual 40	java/lang/String:toCharArray	()[C
    //   1153: astore 81
    //   1155: aload 81
    //   1157: arraylength
    //   1158: istore 82
    //   1160: iload 82
    //   1162: iconst_1
    //   1163: if_icmpgt +14929 -> 16092
    //   1166: iconst_0
    //   1167: istore 83
    //   1169: aload 81
    //   1171: astore 5
    //   1173: iload 83
    //   1175: istore 6
    //   1177: iload 82
    //   1179: istore 84
    //   1181: aload 81
    //   1183: astore 85
    //   1185: iload 84
    //   1187: istore 86
    //   1189: aload 85
    //   1191: iload 83
    //   1193: caload
    //   1194: istore 31
    //   1196: iload 6
    //   1198: iconst_5
    //   1199: irem
    //   1200: tableswitch	default:+32 -> 1232, 0:+12594->13794, 1:+12601->13801, 2:+12608->13808, 3:+12615->13815
    //   1233: lconst_1
    //   1234: istore 87
    //   1236: iload 87
    //   1238: iload 31
    //   1240: ixor
    //   1241: i2c
    //   1242: istore 88
    //   1244: aload 85
    //   1246: iload 83
    //   1248: iload 88
    //   1250: castore
    //   1251: iload 6
    //   1253: iconst_1
    //   1254: iadd
    //   1255: istore 83
    //   1257: iload 86
    //   1259: ifne +18 -> 1277
    //   1262: aload 5
    //   1264: astore 85
    //   1266: iload 83
    //   1268: istore 89
    //   1270: iload 86
    //   1272: istore 83
    //   1274: goto -85 -> 1189
    //   1277: iload 86
    //   1279: istore 82
    //   1281: aload 5
    //   1283: astore 81
    //   1285: iload 82
    //   1287: iload 83
    //   1289: if_icmpgt -120 -> 1169
    //   1292: new 34	java/lang/String
    //   1295: dup
    //   1296: aload 81
    //   1298: invokespecial 44	java/lang/String:<init>	([C)V
    //   1301: invokevirtual 48	java/lang/String:intern	()Ljava/lang/String;
    //   1304: astore 90
    //   1306: aload_1
    //   1307: iload 80
    //   1309: aload 90
    //   1311: aastore
    //   1312: bipush 8
    //   1314: istore 91
    //   1316: ldc 64
    //   1318: invokevirtual 40	java/lang/String:toCharArray	()[C
    //   1321: astore 92
    //   1323: aload 92
    //   1325: arraylength
    //   1326: istore 93
    //   1328: iload 93
    //   1330: iconst_1
    //   1331: if_icmpgt +14755 -> 16086
    //   1334: iconst_0
    //   1335: istore 94
    //   1337: aload 92
    //   1339: astore 5
    //   1341: iload 94
    //   1343: istore 6
    //   1345: iload 93
    //   1347: istore 95
    //   1349: aload 92
    //   1351: astore 96
    //   1353: iload 95
    //   1355: istore 97
    //   1357: aload 96
    //   1359: iload 94
    //   1361: caload
    //   1362: istore 31
    //   1364: iload 6
    //   1366: iconst_5
    //   1367: irem
    //   1368: tableswitch	default:+32 -> 1400, 0:+12454->13822, 1:+12461->13829, 2:+12468->13836, 3:+12475->13843
    //   1401: lconst_1
    //   1402: istore 98
    //   1404: iload 98
    //   1406: iload 31
    //   1408: ixor
    //   1409: i2c
    //   1410: istore 99
    //   1412: aload 96
    //   1414: iload 94
    //   1416: iload 99
    //   1418: castore
    //   1419: iload 6
    //   1421: iconst_1
    //   1422: iadd
    //   1423: istore 94
    //   1425: iload 97
    //   1427: ifne +18 -> 1445
    //   1430: aload 5
    //   1432: astore 96
    //   1434: iload 94
    //   1436: istore 100
    //   1438: iload 97
    //   1440: istore 94
    //   1442: goto -85 -> 1357
    //   1445: iload 97
    //   1447: istore 93
    //   1449: aload 5
    //   1451: astore 92
    //   1453: iload 93
    //   1455: iload 94
    //   1457: if_icmpgt -120 -> 1337
    //   1460: new 34	java/lang/String
    //   1463: dup
    //   1464: aload 92
    //   1466: invokespecial 44	java/lang/String:<init>	([C)V
    //   1469: invokevirtual 48	java/lang/String:intern	()Ljava/lang/String;
    //   1472: astore 101
    //   1474: aload_1
    //   1475: iload 91
    //   1477: aload 101
    //   1479: aastore
    //   1480: bipush 9
    //   1482: istore 102
    //   1484: ldc 66
    //   1486: invokevirtual 40	java/lang/String:toCharArray	()[C
    //   1489: astore 103
    //   1491: aload 103
    //   1493: arraylength
    //   1494: istore 104
    //   1496: iload 104
    //   1498: iconst_1
    //   1499: if_icmpgt +14581 -> 16080
    //   1502: iconst_0
    //   1503: istore 105
    //   1505: aload 103
    //   1507: astore 5
    //   1509: iload 105
    //   1511: istore 6
    //   1513: iload 104
    //   1515: istore 106
    //   1517: aload 103
    //   1519: astore 107
    //   1521: iload 106
    //   1523: istore 108
    //   1525: aload 107
    //   1527: iload 105
    //   1529: caload
    //   1530: istore 31
    //   1532: iload 6
    //   1534: iconst_5
    //   1535: irem
    //   1536: tableswitch	default:+32 -> 1568, 0:+12314->13850, 1:+12321->13857, 2:+12328->13864, 3:+12335->13871
    //   1569: lconst_1
    //   1570: istore 109
    //   1572: iload 109
    //   1574: iload 31
    //   1576: ixor
    //   1577: i2c
    //   1578: istore 110
    //   1580: aload 107
    //   1582: iload 105
    //   1584: iload 110
    //   1586: castore
    //   1587: iload 6
    //   1589: iconst_1
    //   1590: iadd
    //   1591: istore 105
    //   1593: iload 108
    //   1595: ifne +18 -> 1613
    //   1598: aload 5
    //   1600: astore 107
    //   1602: iload 105
    //   1604: istore 111
    //   1606: iload 108
    //   1608: istore 105
    //   1610: goto -85 -> 1525
    //   1613: iload 108
    //   1615: istore 104
    //   1617: aload 5
    //   1619: astore 103
    //   1621: iload 104
    //   1623: iload 105
    //   1625: if_icmpgt -120 -> 1505
    //   1628: new 34	java/lang/String
    //   1631: dup
    //   1632: aload 103
    //   1634: invokespecial 44	java/lang/String:<init>	([C)V
    //   1637: invokevirtual 48	java/lang/String:intern	()Ljava/lang/String;
    //   1640: astore 112
    //   1642: aload_1
    //   1643: iload 102
    //   1645: aload 112
    //   1647: aastore
    //   1648: ldc 68
    //   1650: invokevirtual 40	java/lang/String:toCharArray	()[C
    //   1653: astore 113
    //   1655: aload 113
    //   1657: arraylength
    //   1658: istore 114
    //   1660: iload 114
    //   1662: iconst_1
    //   1663: if_icmpgt +14411 -> 16074
    //   1666: iconst_0
    //   1667: istore 115
    //   1669: aload 113
    //   1671: astore 5
    //   1673: iload 115
    //   1675: istore 6
    //   1677: iload 114
    //   1679: istore 116
    //   1681: aload 113
    //   1683: astore 117
    //   1685: iload 116
    //   1687: istore 118
    //   1689: aload 117
    //   1691: iload 115
    //   1693: caload
    //   1694: istore 102
    //   1696: iload 6
    //   1698: iconst_5
    //   1699: irem
    //   1700: tableswitch	default:+32 -> 1732, 0:+12178->13878, 1:+12185->13885, 2:+12192->13892, 3:+12199->13899
    //   1733: lconst_1
    //   1734: istore 119
    //   1736: iload 119
    //   1738: iload 102
    //   1740: ixor
    //   1741: i2c
    //   1742: istore 120
    //   1744: aload 117
    //   1746: iload 115
    //   1748: iload 120
    //   1750: castore
    //   1751: iload 6
    //   1753: iconst_1
    //   1754: iadd
    //   1755: istore 115
    //   1757: iload 118
    //   1759: ifne +18 -> 1777
    //   1762: aload 5
    //   1764: astore 117
    //   1766: iload 115
    //   1768: istore 121
    //   1770: iload 118
    //   1772: istore 115
    //   1774: goto -85 -> 1689
    //   1777: iload 118
    //   1779: istore 114
    //   1781: aload 5
    //   1783: astore 113
    //   1785: iload 114
    //   1787: iload 115
    //   1789: if_icmpgt -120 -> 1669
    //   1792: new 34	java/lang/String
    //   1795: dup
    //   1796: aload 113
    //   1798: invokespecial 44	java/lang/String:<init>	([C)V
    //   1801: invokevirtual 48	java/lang/String:intern	()Ljava/lang/String;
    //   1804: astore 122
    //   1806: aload_1
    //   1807: bipush 10
    //   1809: aload 122
    //   1811: aastore
    //   1812: bipush 11
    //   1814: istore 123
    //   1816: ldc 70
    //   1818: invokevirtual 40	java/lang/String:toCharArray	()[C
    //   1821: astore 124
    //   1823: aload 124
    //   1825: arraylength
    //   1826: istore 125
    //   1828: iload 125
    //   1830: iconst_1
    //   1831: if_icmpgt +14237 -> 16068
    //   1834: iconst_0
    //   1835: istore 126
    //   1837: aload 124
    //   1839: astore 5
    //   1841: iload 126
    //   1843: istore 6
    //   1845: iload 125
    //   1847: istore 127
    //   1849: aload 124
    //   1851: astore 128
    //   1853: iload 127
    //   1855: istore 129
    //   1857: aload 128
    //   1859: iload 126
    //   1861: caload
    //   1862: istore 31
    //   1864: iload 6
    //   1866: iconst_5
    //   1867: irem
    //   1868: tableswitch	default:+32 -> 1900, 0:+12038->13906, 1:+12045->13913, 2:+12052->13920, 3:+12059->13927
    //   1901: lconst_1
    //   1902: istore 130
    //   1904: iload 130
    //   1906: iload 31
    //   1908: ixor
    //   1909: i2c
    //   1910: istore 131
    //   1912: aload 128
    //   1914: iload 126
    //   1916: iload 131
    //   1918: castore
    //   1919: iload 6
    //   1921: iconst_1
    //   1922: iadd
    //   1923: istore 126
    //   1925: iload 129
    //   1927: ifne +18 -> 1945
    //   1930: aload 5
    //   1932: astore 128
    //   1934: iload 126
    //   1936: istore 132
    //   1938: iload 129
    //   1940: istore 126
    //   1942: goto -85 -> 1857
    //   1945: iload 129
    //   1947: istore 125
    //   1949: aload 5
    //   1951: astore 124
    //   1953: iload 125
    //   1955: iload 126
    //   1957: if_icmpgt -120 -> 1837
    //   1960: new 34	java/lang/String
    //   1963: dup
    //   1964: aload 124
    //   1966: invokespecial 44	java/lang/String:<init>	([C)V
    //   1969: invokevirtual 48	java/lang/String:intern	()Ljava/lang/String;
    //   1972: astore 133
    //   1974: aload_1
    //   1975: iload 123
    //   1977: aload 133
    //   1979: aastore
    //   1980: bipush 12
    //   1982: istore 134
    //   1984: ldc 72
    //   1986: invokevirtual 40	java/lang/String:toCharArray	()[C
    //   1989: astore 135
    //   1991: aload 135
    //   1993: arraylength
    //   1994: istore 136
    //   1996: iload 136
    //   1998: iconst_1
    //   1999: if_icmpgt +14063 -> 16062
    //   2002: iconst_0
    //   2003: istore 137
    //   2005: aload 135
    //   2007: astore 5
    //   2009: iload 137
    //   2011: istore 6
    //   2013: iload 136
    //   2015: istore 138
    //   2017: aload 135
    //   2019: astore 139
    //   2021: iload 138
    //   2023: istore 140
    //   2025: aload 139
    //   2027: iload 137
    //   2029: caload
    //   2030: istore 31
    //   2032: iload 6
    //   2034: iconst_5
    //   2035: irem
    //   2036: tableswitch	default:+32 -> 2068, 0:+11898->13934, 1:+11905->13941, 2:+11912->13948, 3:+11919->13955
    //   2069: lconst_1
    //   2070: istore 141
    //   2072: iload 141
    //   2074: iload 31
    //   2076: ixor
    //   2077: i2c
    //   2078: istore 142
    //   2080: aload 139
    //   2082: iload 137
    //   2084: iload 142
    //   2086: castore
    //   2087: iload 6
    //   2089: iconst_1
    //   2090: iadd
    //   2091: istore 137
    //   2093: iload 140
    //   2095: ifne +18 -> 2113
    //   2098: aload 5
    //   2100: astore 139
    //   2102: iload 137
    //   2104: istore 143
    //   2106: iload 140
    //   2108: istore 137
    //   2110: goto -85 -> 2025
    //   2113: iload 140
    //   2115: istore 136
    //   2117: aload 5
    //   2119: astore 135
    //   2121: iload 136
    //   2123: iload 137
    //   2125: if_icmpgt -120 -> 2005
    //   2128: new 34	java/lang/String
    //   2131: dup
    //   2132: aload 135
    //   2134: invokespecial 44	java/lang/String:<init>	([C)V
    //   2137: invokevirtual 48	java/lang/String:intern	()Ljava/lang/String;
    //   2140: astore 144
    //   2142: aload_1
    //   2143: iload 134
    //   2145: aload 144
    //   2147: aastore
    //   2148: bipush 13
    //   2150: istore 145
    //   2152: ldc 74
    //   2154: invokevirtual 40	java/lang/String:toCharArray	()[C
    //   2157: astore 146
    //   2159: aload 146
    //   2161: arraylength
    //   2162: istore 147
    //   2164: iload 147
    //   2166: iconst_1
    //   2167: if_icmpgt +13889 -> 16056
    //   2170: iconst_0
    //   2171: istore 148
    //   2173: aload 146
    //   2175: astore 5
    //   2177: iload 148
    //   2179: istore 6
    //   2181: iload 147
    //   2183: istore 149
    //   2185: aload 146
    //   2187: astore 150
    //   2189: iload 149
    //   2191: istore 151
    //   2193: aload 150
    //   2195: iload 148
    //   2197: caload
    //   2198: istore 31
    //   2200: iload 6
    //   2202: iconst_5
    //   2203: irem
    //   2204: tableswitch	default:+32 -> 2236, 0:+11758->13962, 1:+11765->13969, 2:+11772->13976, 3:+11779->13983
    //   2237: lconst_1
    //   2238: istore 152
    //   2240: iload 152
    //   2242: iload 31
    //   2244: ixor
    //   2245: i2c
    //   2246: istore 153
    //   2248: aload 150
    //   2250: iload 148
    //   2252: iload 153
    //   2254: castore
    //   2255: iload 6
    //   2257: iconst_1
    //   2258: iadd
    //   2259: istore 148
    //   2261: iload 151
    //   2263: ifne +18 -> 2281
    //   2266: aload 5
    //   2268: astore 150
    //   2270: iload 148
    //   2272: istore 154
    //   2274: iload 151
    //   2276: istore 148
    //   2278: goto -85 -> 2193
    //   2281: iload 151
    //   2283: istore 147
    //   2285: aload 5
    //   2287: astore 146
    //   2289: iload 147
    //   2291: iload 148
    //   2293: if_icmpgt -120 -> 2173
    //   2296: new 34	java/lang/String
    //   2299: dup
    //   2300: aload 146
    //   2302: invokespecial 44	java/lang/String:<init>	([C)V
    //   2305: invokevirtual 48	java/lang/String:intern	()Ljava/lang/String;
    //   2308: astore 155
    //   2310: aload_1
    //   2311: iload 145
    //   2313: aload 155
    //   2315: aastore
    //   2316: bipush 14
    //   2318: istore 156
    //   2320: ldc 76
    //   2322: invokevirtual 40	java/lang/String:toCharArray	()[C
    //   2325: astore 157
    //   2327: aload 157
    //   2329: arraylength
    //   2330: istore 158
    //   2332: iload 158
    //   2334: iconst_1
    //   2335: if_icmpgt +13715 -> 16050
    //   2338: iconst_0
    //   2339: istore 159
    //   2341: aload 157
    //   2343: astore 5
    //   2345: iload 159
    //   2347: istore 6
    //   2349: iload 158
    //   2351: istore 160
    //   2353: aload 157
    //   2355: astore 161
    //   2357: iload 160
    //   2359: istore 162
    //   2361: aload 161
    //   2363: iload 159
    //   2365: caload
    //   2366: istore 31
    //   2368: iload 6
    //   2370: iconst_5
    //   2371: irem
    //   2372: tableswitch	default:+32 -> 2404, 0:+11618->13990, 1:+11625->13997, 2:+11632->14004, 3:+11639->14011
    //   2405: lconst_1
    //   2406: istore 163
    //   2408: iload 163
    //   2410: iload 31
    //   2412: ixor
    //   2413: i2c
    //   2414: istore 164
    //   2416: aload 161
    //   2418: iload 159
    //   2420: iload 164
    //   2422: castore
    //   2423: iload 6
    //   2425: iconst_1
    //   2426: iadd
    //   2427: istore 159
    //   2429: iload 162
    //   2431: ifne +18 -> 2449
    //   2434: aload 5
    //   2436: astore 161
    //   2438: iload 159
    //   2440: istore 165
    //   2442: iload 162
    //   2444: istore 159
    //   2446: goto -85 -> 2361
    //   2449: iload 162
    //   2451: istore 158
    //   2453: aload 5
    //   2455: astore 157
    //   2457: iload 158
    //   2459: iload 159
    //   2461: if_icmpgt -120 -> 2341
    //   2464: new 34	java/lang/String
    //   2467: dup
    //   2468: aload 157
    //   2470: invokespecial 44	java/lang/String:<init>	([C)V
    //   2473: invokevirtual 48	java/lang/String:intern	()Ljava/lang/String;
    //   2476: astore 166
    //   2478: aload_1
    //   2479: iload 156
    //   2481: aload 166
    //   2483: aastore
    //   2484: bipush 15
    //   2486: istore 167
    //   2488: ldc 78
    //   2490: invokevirtual 40	java/lang/String:toCharArray	()[C
    //   2493: astore 168
    //   2495: aload 168
    //   2497: arraylength
    //   2498: istore 169
    //   2500: iload 169
    //   2502: iconst_1
    //   2503: if_icmpgt +13541 -> 16044
    //   2506: iconst_0
    //   2507: istore 170
    //   2509: aload 168
    //   2511: astore 5
    //   2513: iload 170
    //   2515: istore 6
    //   2517: iload 169
    //   2519: istore 171
    //   2521: aload 168
    //   2523: astore 172
    //   2525: iload 171
    //   2527: istore 173
    //   2529: aload 172
    //   2531: iload 170
    //   2533: caload
    //   2534: istore 31
    //   2536: iload 6
    //   2538: iconst_5
    //   2539: irem
    //   2540: tableswitch	default:+32 -> 2572, 0:+11478->14018, 1:+11485->14025, 2:+11492->14032, 3:+11499->14039
    //   2573: lconst_1
    //   2574: istore 174
    //   2576: iload 174
    //   2578: iload 31
    //   2580: ixor
    //   2581: i2c
    //   2582: istore 175
    //   2584: aload 172
    //   2586: iload 170
    //   2588: iload 175
    //   2590: castore
    //   2591: iload 6
    //   2593: iconst_1
    //   2594: iadd
    //   2595: istore 170
    //   2597: iload 173
    //   2599: ifne +18 -> 2617
    //   2602: aload 5
    //   2604: astore 172
    //   2606: iload 170
    //   2608: istore 176
    //   2610: iload 173
    //   2612: istore 170
    //   2614: goto -85 -> 2529
    //   2617: iload 173
    //   2619: istore 169
    //   2621: aload 5
    //   2623: astore 168
    //   2625: iload 169
    //   2627: iload 170
    //   2629: if_icmpgt -120 -> 2509
    //   2632: new 34	java/lang/String
    //   2635: dup
    //   2636: aload 168
    //   2638: invokespecial 44	java/lang/String:<init>	([C)V
    //   2641: invokevirtual 48	java/lang/String:intern	()Ljava/lang/String;
    //   2644: astore 177
    //   2646: aload_1
    //   2647: iload 167
    //   2649: aload 177
    //   2651: aastore
    //   2652: bipush 16
    //   2654: istore 178
    //   2656: ldc 80
    //   2658: invokevirtual 40	java/lang/String:toCharArray	()[C
    //   2661: astore 179
    //   2663: aload 179
    //   2665: arraylength
    //   2666: istore 180
    //   2668: iload 180
    //   2670: iconst_1
    //   2671: if_icmpgt +13367 -> 16038
    //   2674: iconst_0
    //   2675: istore 181
    //   2677: aload 179
    //   2679: astore 5
    //   2681: iload 181
    //   2683: istore 6
    //   2685: iload 180
    //   2687: istore 182
    //   2689: aload 179
    //   2691: astore 183
    //   2693: iload 182
    //   2695: istore 184
    //   2697: aload 183
    //   2699: iload 181
    //   2701: caload
    //   2702: istore 31
    //   2704: iload 6
    //   2706: iconst_5
    //   2707: irem
    //   2708: tableswitch	default:+32 -> 2740, 0:+11338->14046, 1:+11345->14053, 2:+11352->14060, 3:+11359->14067
    //   2741: lconst_1
    //   2742: istore 185
    //   2744: iload 185
    //   2746: iload 31
    //   2748: ixor
    //   2749: i2c
    //   2750: istore 186
    //   2752: aload 183
    //   2754: iload 181
    //   2756: iload 186
    //   2758: castore
    //   2759: iload 6
    //   2761: iconst_1
    //   2762: iadd
    //   2763: istore 181
    //   2765: iload 184
    //   2767: ifne +18 -> 2785
    //   2770: aload 5
    //   2772: astore 183
    //   2774: iload 181
    //   2776: istore 187
    //   2778: iload 184
    //   2780: istore 181
    //   2782: goto -85 -> 2697
    //   2785: iload 184
    //   2787: istore 180
    //   2789: aload 5
    //   2791: astore 179
    //   2793: iload 180
    //   2795: iload 181
    //   2797: if_icmpgt -120 -> 2677
    //   2800: new 34	java/lang/String
    //   2803: dup
    //   2804: aload 179
    //   2806: invokespecial 44	java/lang/String:<init>	([C)V
    //   2809: invokevirtual 48	java/lang/String:intern	()Ljava/lang/String;
    //   2812: astore 188
    //   2814: aload_1
    //   2815: iload 178
    //   2817: aload 188
    //   2819: aastore
    //   2820: bipush 17
    //   2822: istore 189
    //   2824: ldc 82
    //   2826: invokevirtual 40	java/lang/String:toCharArray	()[C
    //   2829: astore 190
    //   2831: aload 190
    //   2833: arraylength
    //   2834: istore 191
    //   2836: iload 191
    //   2838: iconst_1
    //   2839: if_icmpgt +13193 -> 16032
    //   2842: iconst_0
    //   2843: istore 192
    //   2845: aload 190
    //   2847: astore 5
    //   2849: iload 192
    //   2851: istore 6
    //   2853: iload 191
    //   2855: istore 193
    //   2857: aload 190
    //   2859: astore 194
    //   2861: iload 193
    //   2863: istore 195
    //   2865: aload 194
    //   2867: iload 192
    //   2869: caload
    //   2870: istore 31
    //   2872: iload 6
    //   2874: iconst_5
    //   2875: irem
    //   2876: tableswitch	default:+32 -> 2908, 0:+11198->14074, 1:+11205->14081, 2:+11212->14088, 3:+11219->14095
    //   2909: lconst_1
    //   2910: istore 196
    //   2912: iload 196
    //   2914: iload 31
    //   2916: ixor
    //   2917: i2c
    //   2918: istore 197
    //   2920: aload 194
    //   2922: iload 192
    //   2924: iload 197
    //   2926: castore
    //   2927: iload 6
    //   2929: iconst_1
    //   2930: iadd
    //   2931: istore 192
    //   2933: iload 195
    //   2935: ifne +18 -> 2953
    //   2938: aload 5
    //   2940: astore 194
    //   2942: iload 192
    //   2944: istore 198
    //   2946: iload 195
    //   2948: istore 192
    //   2950: goto -85 -> 2865
    //   2953: iload 195
    //   2955: istore 191
    //   2957: aload 5
    //   2959: astore 190
    //   2961: iload 191
    //   2963: iload 192
    //   2965: if_icmpgt -120 -> 2845
    //   2968: new 34	java/lang/String
    //   2971: dup
    //   2972: aload 190
    //   2974: invokespecial 44	java/lang/String:<init>	([C)V
    //   2977: invokevirtual 48	java/lang/String:intern	()Ljava/lang/String;
    //   2980: astore 199
    //   2982: aload_1
    //   2983: iload 189
    //   2985: aload 199
    //   2987: aastore
    //   2988: bipush 18
    //   2990: istore 200
    //   2992: ldc 84
    //   2994: invokevirtual 40	java/lang/String:toCharArray	()[C
    //   2997: astore 201
    //   2999: aload 201
    //   3001: arraylength
    //   3002: istore 202
    //   3004: iload 202
    //   3006: iconst_1
    //   3007: if_icmpgt +13019 -> 16026
    //   3010: iconst_0
    //   3011: istore 203
    //   3013: aload 201
    //   3015: astore 5
    //   3017: iload 203
    //   3019: istore 6
    //   3021: iload 202
    //   3023: istore 204
    //   3025: aload 201
    //   3027: astore 205
    //   3029: iload 204
    //   3031: istore 206
    //   3033: aload 205
    //   3035: iload 203
    //   3037: caload
    //   3038: istore 31
    //   3040: iload 6
    //   3042: iconst_5
    //   3043: irem
    //   3044: tableswitch	default:+32 -> 3076, 0:+11058->14102, 1:+11065->14109, 2:+11072->14116, 3:+11079->14123
    //   3077: lconst_1
    //   3078: istore 207
    //   3080: iload 207
    //   3082: iload 31
    //   3084: ixor
    //   3085: i2c
    //   3086: istore 208
    //   3088: aload 205
    //   3090: iload 203
    //   3092: iload 208
    //   3094: castore
    //   3095: iload 6
    //   3097: iconst_1
    //   3098: iadd
    //   3099: istore 203
    //   3101: iload 206
    //   3103: ifne +18 -> 3121
    //   3106: aload 5
    //   3108: astore 205
    //   3110: iload 203
    //   3112: istore 209
    //   3114: iload 206
    //   3116: istore 203
    //   3118: goto -85 -> 3033
    //   3121: iload 206
    //   3123: istore 202
    //   3125: aload 5
    //   3127: astore 201
    //   3129: iload 202
    //   3131: iload 203
    //   3133: if_icmpgt -120 -> 3013
    //   3136: new 34	java/lang/String
    //   3139: dup
    //   3140: aload 201
    //   3142: invokespecial 44	java/lang/String:<init>	([C)V
    //   3145: invokevirtual 48	java/lang/String:intern	()Ljava/lang/String;
    //   3148: astore 210
    //   3150: aload_1
    //   3151: iload 200
    //   3153: aload 210
    //   3155: aastore
    //   3156: bipush 19
    //   3158: istore 211
    //   3160: ldc 86
    //   3162: invokevirtual 40	java/lang/String:toCharArray	()[C
    //   3165: astore 212
    //   3167: aload 212
    //   3169: arraylength
    //   3170: istore 213
    //   3172: iload 213
    //   3174: iconst_1
    //   3175: if_icmpgt +12845 -> 16020
    //   3178: iconst_0
    //   3179: istore 214
    //   3181: aload 212
    //   3183: astore 5
    //   3185: iload 214
    //   3187: istore 6
    //   3189: iload 213
    //   3191: istore 215
    //   3193: aload 212
    //   3195: astore 216
    //   3197: iload 215
    //   3199: istore 217
    //   3201: aload 216
    //   3203: iload 214
    //   3205: caload
    //   3206: istore 31
    //   3208: iload 6
    //   3210: iconst_5
    //   3211: irem
    //   3212: tableswitch	default:+32 -> 3244, 0:+10918->14130, 1:+10925->14137, 2:+10932->14144, 3:+10939->14151
    //   3245: lconst_1
    //   3246: istore 218
    //   3248: iload 218
    //   3250: iload 31
    //   3252: ixor
    //   3253: i2c
    //   3254: istore 219
    //   3256: aload 216
    //   3258: iload 214
    //   3260: iload 219
    //   3262: castore
    //   3263: iload 6
    //   3265: iconst_1
    //   3266: iadd
    //   3267: istore 214
    //   3269: iload 217
    //   3271: ifne +18 -> 3289
    //   3274: aload 5
    //   3276: astore 216
    //   3278: iload 214
    //   3280: istore 220
    //   3282: iload 217
    //   3284: istore 214
    //   3286: goto -85 -> 3201
    //   3289: iload 217
    //   3291: istore 213
    //   3293: aload 5
    //   3295: astore 212
    //   3297: iload 213
    //   3299: iload 214
    //   3301: if_icmpgt -120 -> 3181
    //   3304: new 34	java/lang/String
    //   3307: dup
    //   3308: aload 212
    //   3310: invokespecial 44	java/lang/String:<init>	([C)V
    //   3313: invokevirtual 48	java/lang/String:intern	()Ljava/lang/String;
    //   3316: astore 221
    //   3318: aload_1
    //   3319: iload 211
    //   3321: aload 221
    //   3323: aastore
    //   3324: bipush 20
    //   3326: istore 222
    //   3328: ldc 88
    //   3330: invokevirtual 40	java/lang/String:toCharArray	()[C
    //   3333: astore 223
    //   3335: aload 223
    //   3337: arraylength
    //   3338: istore 224
    //   3340: iload 224
    //   3342: iconst_1
    //   3343: if_icmpgt +12671 -> 16014
    //   3346: iconst_0
    //   3347: istore 225
    //   3349: aload 223
    //   3351: astore 5
    //   3353: iload 225
    //   3355: istore 6
    //   3357: iload 224
    //   3359: istore 226
    //   3361: aload 223
    //   3363: astore 227
    //   3365: iload 226
    //   3367: istore 228
    //   3369: aload 227
    //   3371: iload 225
    //   3373: caload
    //   3374: istore 31
    //   3376: iload 6
    //   3378: iconst_5
    //   3379: irem
    //   3380: tableswitch	default:+32 -> 3412, 0:+10778->14158, 1:+10785->14165, 2:+10792->14172, 3:+10799->14179
    //   3413: lconst_1
    //   3414: istore 229
    //   3416: iload 229
    //   3418: iload 31
    //   3420: ixor
    //   3421: i2c
    //   3422: istore 230
    //   3424: aload 227
    //   3426: iload 225
    //   3428: iload 230
    //   3430: castore
    //   3431: iload 6
    //   3433: iconst_1
    //   3434: iadd
    //   3435: istore 225
    //   3437: iload 228
    //   3439: ifne +18 -> 3457
    //   3442: aload 5
    //   3444: astore 227
    //   3446: iload 225
    //   3448: istore 231
    //   3450: iload 228
    //   3452: istore 225
    //   3454: goto -85 -> 3369
    //   3457: iload 228
    //   3459: istore 224
    //   3461: aload 5
    //   3463: astore 223
    //   3465: iload 224
    //   3467: iload 225
    //   3469: if_icmpgt -120 -> 3349
    //   3472: new 34	java/lang/String
    //   3475: dup
    //   3476: aload 223
    //   3478: invokespecial 44	java/lang/String:<init>	([C)V
    //   3481: invokevirtual 48	java/lang/String:intern	()Ljava/lang/String;
    //   3484: astore 232
    //   3486: aload_1
    //   3487: iload 222
    //   3489: aload 232
    //   3491: aastore
    //   3492: bipush 21
    //   3494: istore 233
    //   3496: ldc 90
    //   3498: invokevirtual 40	java/lang/String:toCharArray	()[C
    //   3501: astore 234
    //   3503: aload 234
    //   3505: arraylength
    //   3506: istore 235
    //   3508: iload 235
    //   3510: iconst_1
    //   3511: if_icmpgt +12497 -> 16008
    //   3514: iconst_0
    //   3515: istore 236
    //   3517: aload 234
    //   3519: astore 5
    //   3521: iload 236
    //   3523: istore 6
    //   3525: iload 235
    //   3527: istore 237
    //   3529: aload 234
    //   3531: astore 238
    //   3533: iload 237
    //   3535: istore 239
    //   3537: aload 238
    //   3539: iload 236
    //   3541: caload
    //   3542: istore 31
    //   3544: iload 6
    //   3546: iconst_5
    //   3547: irem
    //   3548: tableswitch	default:+32 -> 3580, 0:+10638->14186, 1:+10645->14193, 2:+10652->14200, 3:+10659->14207
    //   3581: lconst_1
    //   3582: istore 240
    //   3584: iload 240
    //   3586: iload 31
    //   3588: ixor
    //   3589: i2c
    //   3590: istore 241
    //   3592: aload 238
    //   3594: iload 236
    //   3596: iload 241
    //   3598: castore
    //   3599: iload 6
    //   3601: iconst_1
    //   3602: iadd
    //   3603: istore 236
    //   3605: iload 239
    //   3607: ifne +18 -> 3625
    //   3610: aload 5
    //   3612: astore 238
    //   3614: iload 236
    //   3616: istore 242
    //   3618: iload 239
    //   3620: istore 236
    //   3622: goto -85 -> 3537
    //   3625: iload 239
    //   3627: istore 235
    //   3629: aload 5
    //   3631: astore 234
    //   3633: iload 235
    //   3635: iload 236
    //   3637: if_icmpgt -120 -> 3517
    //   3640: new 34	java/lang/String
    //   3643: dup
    //   3644: aload 234
    //   3646: invokespecial 44	java/lang/String:<init>	([C)V
    //   3649: invokevirtual 48	java/lang/String:intern	()Ljava/lang/String;
    //   3652: astore 243
    //   3654: aload_1
    //   3655: iload 233
    //   3657: aload 243
    //   3659: aastore
    //   3660: bipush 22
    //   3662: istore 244
    //   3664: ldc 92
    //   3666: invokevirtual 40	java/lang/String:toCharArray	()[C
    //   3669: astore 245
    //   3671: aload 245
    //   3673: arraylength
    //   3674: istore 246
    //   3676: iload 246
    //   3678: iconst_1
    //   3679: if_icmpgt +12323 -> 16002
    //   3682: iconst_0
    //   3683: istore 247
    //   3685: aload 245
    //   3687: astore 5
    //   3689: iload 247
    //   3691: istore 6
    //   3693: iload 246
    //   3695: istore 248
    //   3697: aload 245
    //   3699: astore 249
    //   3701: iload 248
    //   3703: istore 250
    //   3705: aload 249
    //   3707: iload 247
    //   3709: caload
    //   3710: istore 31
    //   3712: iload 6
    //   3714: iconst_5
    //   3715: irem
    //   3716: tableswitch	default:+32 -> 3748, 0:+10498->14214, 1:+10505->14221, 2:+10512->14228, 3:+10519->14235
    //   3749: lconst_1
    //   3750: istore 251
    //   3752: iload 251
    //   3754: iload 31
    //   3756: ixor
    //   3757: i2c
    //   3758: istore 252
    //   3760: aload 249
    //   3762: iload 247
    //   3764: iload 252
    //   3766: castore
    //   3767: iload 6
    //   3769: iconst_1
    //   3770: iadd
    //   3771: istore 247
    //   3773: iload 250
    //   3775: ifne +18 -> 3793
    //   3778: aload 5
    //   3780: astore 249
    //   3782: iload 247
    //   3784: istore 253
    //   3786: iload 250
    //   3788: istore 247
    //   3790: goto -85 -> 3705
    //   3793: iload 250
    //   3795: istore 246
    //   3797: aload 5
    //   3799: astore 245
    //   3801: iload 246
    //   3803: iload 247
    //   3805: if_icmpgt -120 -> 3685
    //   3808: new 34	java/lang/String
    //   3811: dup
    //   3812: aload 245
    //   3814: invokespecial 44	java/lang/String:<init>	([C)V
    //   3817: invokevirtual 48	java/lang/String:intern	()Ljava/lang/String;
    //   3820: astore 254
    //   3822: aload_1
    //   3823: iload 244
    //   3825: aload 254
    //   3827: aastore
    //   3828: bipush 23
    //   3830: istore 255
    //   3832: ldc 94
    //   3834: invokevirtual 40	java/lang/String:toCharArray	()[C
    //   3837: wide
    //   3841: wide
    //   3845: arraylength
    //   3846: wide
    //   3850: wide
    //   3854: iconst_1
    //   3855: if_icmpgt +12139 -> 15994
    //   3858: iconst_0
    //   3859: wide
    //   3863: wide
    //   3867: astore 5
    //   3869: wide
    //   3873: istore 6
    //   3875: wide
    //   3879: wide
    //   3883: wide
    //   3887: wide
    //   3891: wide
    //   3895: wide
    //   3899: wide
    //   3903: wide
    //   3907: caload
    //   3908: istore 31
    //   3910: iload 6
    //   3912: iconst_5
    //   3913: irem
    //   3914: tableswitch	default:+30 -> 3944, 0:+10328->14242, 1:+10337->14251, 2:+10346->14260, 3:+10355->14269
    //   3945: lconst_1
    //   3946: wide
    //   3950: wide
    //   3954: iload 31
    //   3956: ixor
    //   3957: i2c
    //   3958: wide
    //   3962: wide
    //   3966: wide
    //   3970: wide
    //   3974: castore
    //   3975: iload 6
    //   3977: iconst_1
    //   3978: iadd
    //   3979: wide
    //   3983: wide
    //   3987: ifne +28 -> 4015
    //   3990: aload 5
    //   3992: wide
    //   3996: wide
    //   4000: wide
    //   4004: wide
    //   4008: wide
    //   4012: goto -113 -> 3899
    //   4015: wide
    //   4019: wide
    //   4023: aload 5
    //   4025: wide
    //   4029: wide
    //   4033: wide
    //   4037: if_icmpgt -174 -> 3863
    //   4040: new 34	java/lang/String
    //   4043: dup
    //   4044: wide
    //   4048: invokespecial 44	java/lang/String:<init>	([C)V
    //   4051: invokevirtual 48	java/lang/String:intern	()Ljava/lang/String;
    //   4054: wide
    //   4058: aload_1
    //   4059: iload 255
    //   4061: wide
    //   4065: aastore
    //   4066: bipush 24
    //   4068: wide
    //   4072: ldc 96
    //   4074: invokevirtual 40	java/lang/String:toCharArray	()[C
    //   4077: wide
    //   4081: wide
    //   4085: arraylength
    //   4086: wide
    //   4090: wide
    //   4094: iconst_1
    //   4095: if_icmpgt +11891 -> 15986
    //   4098: iconst_0
    //   4099: wide
    //   4103: wide
    //   4107: astore 5
    //   4109: wide
    //   4113: istore 6
    //   4115: wide
    //   4119: wide
    //   4123: wide
    //   4127: wide
    //   4131: wide
    //   4135: wide
    //   4139: wide
    //   4143: wide
    //   4147: caload
    //   4148: istore 31
    //   4150: iload 6
    //   4152: iconst_5
    //   4153: irem
    //   4154: tableswitch	default:+30 -> 4184, 0:+10124->14278, 1:+10133->14287, 2:+10142->14296, 3:+10151->14305
    //   4185: lconst_1
    //   4186: wide
    //   4190: wide
    //   4194: iload 31
    //   4196: ixor
    //   4197: i2c
    //   4198: wide
    //   4202: wide
    //   4206: wide
    //   4210: wide
    //   4214: castore
    //   4215: iload 6
    //   4217: iconst_1
    //   4218: iadd
    //   4219: wide
    //   4223: wide
    //   4227: ifne +28 -> 4255
    //   4230: aload 5
    //   4232: wide
    //   4236: wide
    //   4240: wide
    //   4244: wide
    //   4248: wide
    //   4252: goto -113 -> 4139
    //   4255: wide
    //   4259: wide
    //   4263: aload 5
    //   4265: wide
    //   4269: wide
    //   4273: wide
    //   4277: if_icmpgt -174 -> 4103
    //   4280: new 34	java/lang/String
    //   4283: dup
    //   4284: wide
    //   4288: invokespecial 44	java/lang/String:<init>	([C)V
    //   4291: invokevirtual 48	java/lang/String:intern	()Ljava/lang/String;
    //   4294: wide
    //   4298: aload_1
    //   4299: wide
    //   4303: wide
    //   4307: aastore
    //   4308: bipush 25
    //   4310: wide
    //   4314: ldc 98
    //   4316: invokevirtual 40	java/lang/String:toCharArray	()[C
    //   4319: wide
    //   4323: wide
    //   4327: arraylength
    //   4328: wide
    //   4332: wide
    //   4336: iconst_1
    //   4337: if_icmpgt +11641 -> 15978
    //   4340: iconst_0
    //   4341: wide
    //   4345: wide
    //   4349: astore 5
    //   4351: wide
    //   4355: istore 6
    //   4357: wide
    //   4361: wide
    //   4365: wide
    //   4369: wide
    //   4373: wide
    //   4377: wide
    //   4381: wide
    //   4385: wide
    //   4389: caload
    //   4390: istore 31
    //   4392: iload 6
    //   4394: iconst_5
    //   4395: irem
    //   4396: tableswitch	default:+32 -> 4428, 0:+9918->14314, 1:+9927->14323, 2:+9936->14332, 3:+9945->14341
    //   4429: lconst_1
    //   4430: wide
    //   4434: wide
    //   4438: iload 31
    //   4440: ixor
    //   4441: i2c
    //   4442: wide
    //   4446: wide
    //   4450: wide
    //   4454: wide
    //   4458: castore
    //   4459: iload 6
    //   4461: iconst_1
    //   4462: iadd
    //   4463: wide
    //   4467: wide
    //   4471: ifne +28 -> 4499
    //   4474: aload 5
    //   4476: wide
    //   4480: wide
    //   4484: wide
    //   4488: wide
    //   4492: wide
    //   4496: goto -115 -> 4381
    //   4499: wide
    //   4503: wide
    //   4507: aload 5
    //   4509: wide
    //   4513: wide
    //   4517: wide
    //   4521: if_icmpgt -176 -> 4345
    //   4524: new 34	java/lang/String
    //   4527: dup
    //   4528: wide
    //   4532: invokespecial 44	java/lang/String:<init>	([C)V
    //   4535: invokevirtual 48	java/lang/String:intern	()Ljava/lang/String;
    //   4538: wide
    //   4542: aload_1
    //   4543: wide
    //   4547: wide
    //   4551: aastore
    //   4552: bipush 26
    //   4554: wide
    //   4558: ldc 100
    //   4560: invokevirtual 40	java/lang/String:toCharArray	()[C
    //   4563: wide
    //   4567: wide
    //   4571: arraylength
    //   4572: wide
    //   4576: wide
    //   4580: iconst_1
    //   4581: if_icmpgt +11389 -> 15970
    //   4584: iconst_0
    //   4585: wide
    //   4589: wide
    //   4593: astore 5
    //   4595: wide
    //   4599: istore 6
    //   4601: wide
    //   4605: wide
    //   4609: wide
    //   4613: wide
    //   4617: wide
    //   4621: wide
    //   4625: wide
    //   4629: wide
    //   4633: caload
    //   4634: istore 31
    //   4636: iload 6
    //   4638: iconst_5
    //   4639: irem
    //   4640: tableswitch	default:+32 -> 4672, 0:+9710->14350, 1:+9719->14359, 2:+9728->14368, 3:+9737->14377
    //   4673: lconst_1
    //   4674: wide
    //   4678: wide
    //   4682: iload 31
    //   4684: ixor
    //   4685: i2c
    //   4686: wide
    //   4690: wide
    //   4694: wide
    //   4698: wide
    //   4702: castore
    //   4703: iload 6
    //   4705: iconst_1
    //   4706: iadd
    //   4707: wide
    //   4711: wide
    //   4715: ifne +28 -> 4743
    //   4718: aload 5
    //   4720: wide
    //   4724: wide
    //   4728: wide
    //   4732: wide
    //   4736: wide
    //   4740: goto -115 -> 4625
    //   4743: wide
    //   4747: wide
    //   4751: aload 5
    //   4753: wide
    //   4757: wide
    //   4761: wide
    //   4765: if_icmpgt -176 -> 4589
    //   4768: new 34	java/lang/String
    //   4771: dup
    //   4772: wide
    //   4776: invokespecial 44	java/lang/String:<init>	([C)V
    //   4779: invokevirtual 48	java/lang/String:intern	()Ljava/lang/String;
    //   4782: wide
    //   4786: aload_1
    //   4787: wide
    //   4791: wide
    //   4795: aastore
    //   4796: bipush 27
    //   4798: wide
    //   4802: ldc 102
    //   4804: invokevirtual 40	java/lang/String:toCharArray	()[C
    //   4807: wide
    //   4811: wide
    //   4815: arraylength
    //   4816: wide
    //   4820: wide
    //   4824: iconst_1
    //   4825: if_icmpgt +11137 -> 15962
    //   4828: iconst_0
    //   4829: wide
    //   4833: wide
    //   4837: astore 5
    //   4839: wide
    //   4843: istore 6
    //   4845: wide
    //   4849: wide
    //   4853: wide
    //   4857: wide
    //   4861: wide
    //   4865: wide
    //   4869: wide
    //   4873: wide
    //   4877: caload
    //   4878: istore 31
    //   4880: iload 6
    //   4882: iconst_5
    //   4883: irem
    //   4884: tableswitch	default:+32 -> 4916, 0:+9502->14386, 1:+9511->14395, 2:+9520->14404, 3:+9529->14413
    //   4917: lconst_1
    //   4918: wide
    //   4922: wide
    //   4926: iload 31
    //   4928: ixor
    //   4929: i2c
    //   4930: wide
    //   4934: wide
    //   4938: wide
    //   4942: wide
    //   4946: castore
    //   4947: iload 6
    //   4949: iconst_1
    //   4950: iadd
    //   4951: wide
    //   4955: wide
    //   4959: ifne +28 -> 4987
    //   4962: aload 5
    //   4964: wide
    //   4968: wide
    //   4972: wide
    //   4976: wide
    //   4980: wide
    //   4984: goto -115 -> 4869
    //   4987: wide
    //   4991: wide
    //   4995: aload 5
    //   4997: wide
    //   5001: wide
    //   5005: wide
    //   5009: if_icmpgt -176 -> 4833
    //   5012: new 34	java/lang/String
    //   5015: dup
    //   5016: wide
    //   5020: invokespecial 44	java/lang/String:<init>	([C)V
    //   5023: invokevirtual 48	java/lang/String:intern	()Ljava/lang/String;
    //   5026: wide
    //   5030: aload_1
    //   5031: wide
    //   5035: wide
    //   5039: aastore
    //   5040: bipush 28
    //   5042: wide
    //   5046: ldc 104
    //   5048: invokevirtual 40	java/lang/String:toCharArray	()[C
    //   5051: wide
    //   5055: wide
    //   5059: arraylength
    //   5060: wide
    //   5064: wide
    //   5068: iconst_1
    //   5069: if_icmpgt +10885 -> 15954
    //   5072: iconst_0
    //   5073: wide
    //   5077: wide
    //   5081: astore 5
    //   5083: wide
    //   5087: istore 6
    //   5089: wide
    //   5093: wide
    //   5097: wide
    //   5101: wide
    //   5105: wide
    //   5109: wide
    //   5113: wide
    //   5117: wide
    //   5121: caload
    //   5122: istore 31
    //   5124: iload 6
    //   5126: iconst_5
    //   5127: irem
    //   5128: tableswitch	default:+32 -> 5160, 0:+9294->14422, 1:+9303->14431, 2:+9312->14440, 3:+9321->14449
    //   5161: lconst_1
    //   5162: wide
    //   5166: wide
    //   5170: iload 31
    //   5172: ixor
    //   5173: i2c
    //   5174: wide
    //   5178: wide
    //   5182: wide
    //   5186: wide
    //   5190: castore
    //   5191: iload 6
    //   5193: iconst_1
    //   5194: iadd
    //   5195: wide
    //   5199: wide
    //   5203: ifne +28 -> 5231
    //   5206: aload 5
    //   5208: wide
    //   5212: wide
    //   5216: wide
    //   5220: wide
    //   5224: wide
    //   5228: goto -115 -> 5113
    //   5231: wide
    //   5235: wide
    //   5239: aload 5
    //   5241: wide
    //   5245: wide
    //   5249: wide
    //   5253: if_icmpgt -176 -> 5077
    //   5256: new 34	java/lang/String
    //   5259: dup
    //   5260: wide
    //   5264: invokespecial 44	java/lang/String:<init>	([C)V
    //   5267: invokevirtual 48	java/lang/String:intern	()Ljava/lang/String;
    //   5270: wide
    //   5274: aload_1
    //   5275: wide
    //   5279: wide
    //   5283: aastore
    //   5284: bipush 29
    //   5286: wide
    //   5290: ldc 106
    //   5292: invokevirtual 40	java/lang/String:toCharArray	()[C
    //   5295: wide
    //   5299: wide
    //   5303: arraylength
    //   5304: wide
    //   5308: wide
    //   5312: iconst_1
    //   5313: if_icmpgt +10633 -> 15946
    //   5316: iconst_0
    //   5317: wide
    //   5321: wide
    //   5325: astore 5
    //   5327: wide
    //   5331: istore 6
    //   5333: wide
    //   5337: wide
    //   5341: wide
    //   5345: wide
    //   5349: wide
    //   5353: wide
    //   5357: wide
    //   5361: wide
    //   5365: caload
    //   5366: istore 31
    //   5368: iload 6
    //   5370: iconst_5
    //   5371: irem
    //   5372: tableswitch	default:+32 -> 5404, 0:+9086->14458, 1:+9095->14467, 2:+9104->14476, 3:+9113->14485
    //   5405: lconst_1
    //   5406: wide
    //   5410: wide
    //   5414: iload 31
    //   5416: ixor
    //   5417: i2c
    //   5418: wide
    //   5422: wide
    //   5426: wide
    //   5430: wide
    //   5434: castore
    //   5435: iload 6
    //   5437: iconst_1
    //   5438: iadd
    //   5439: wide
    //   5443: wide
    //   5447: ifne +28 -> 5475
    //   5450: aload 5
    //   5452: wide
    //   5456: wide
    //   5460: wide
    //   5464: wide
    //   5468: wide
    //   5472: goto -115 -> 5357
    //   5475: wide
    //   5479: wide
    //   5483: aload 5
    //   5485: wide
    //   5489: wide
    //   5493: wide
    //   5497: if_icmpgt -176 -> 5321
    //   5500: new 34	java/lang/String
    //   5503: dup
    //   5504: wide
    //   5508: invokespecial 44	java/lang/String:<init>	([C)V
    //   5511: invokevirtual 48	java/lang/String:intern	()Ljava/lang/String;
    //   5514: wide
    //   5518: aload_1
    //   5519: wide
    //   5523: wide
    //   5527: aastore
    //   5528: bipush 30
    //   5530: wide
    //   5534: ldc 108
    //   5536: invokevirtual 40	java/lang/String:toCharArray	()[C
    //   5539: wide
    //   5543: wide
    //   5547: arraylength
    //   5548: wide
    //   5552: wide
    //   5556: iconst_1
    //   5557: if_icmpgt +10381 -> 15938
    //   5560: iconst_0
    //   5561: wide
    //   5565: wide
    //   5569: astore 5
    //   5571: wide
    //   5575: istore 6
    //   5577: wide
    //   5581: wide
    //   5585: wide
    //   5589: wide
    //   5593: wide
    //   5597: wide
    //   5601: wide
    //   5605: wide
    //   5609: caload
    //   5610: istore 31
    //   5612: iload 6
    //   5614: iconst_5
    //   5615: irem
    //   5616: tableswitch	default:+32 -> 5648, 0:+8878->14494, 1:+8887->14503, 2:+8896->14512, 3:+8905->14521
    //   5649: lconst_1
    //   5650: wide
    //   5654: wide
    //   5658: iload 31
    //   5660: ixor
    //   5661: i2c
    //   5662: wide
    //   5666: wide
    //   5670: wide
    //   5674: wide
    //   5678: castore
    //   5679: iload 6
    //   5681: iconst_1
    //   5682: iadd
    //   5683: wide
    //   5687: wide
    //   5691: ifne +28 -> 5719
    //   5694: aload 5
    //   5696: wide
    //   5700: wide
    //   5704: wide
    //   5708: wide
    //   5712: wide
    //   5716: goto -115 -> 5601
    //   5719: wide
    //   5723: wide
    //   5727: aload 5
    //   5729: wide
    //   5733: wide
    //   5737: wide
    //   5741: if_icmpgt -176 -> 5565
    //   5744: new 34	java/lang/String
    //   5747: dup
    //   5748: wide
    //   5752: invokespecial 44	java/lang/String:<init>	([C)V
    //   5755: invokevirtual 48	java/lang/String:intern	()Ljava/lang/String;
    //   5758: wide
    //   5762: aload_1
    //   5763: wide
    //   5767: wide
    //   5771: aastore
    //   5772: bipush 31
    //   5774: wide
    //   5778: ldc 110
    //   5780: invokevirtual 40	java/lang/String:toCharArray	()[C
    //   5783: wide
    //   5787: wide
    //   5791: arraylength
    //   5792: wide
    //   5796: wide
    //   5800: iconst_1
    //   5801: if_icmpgt +10129 -> 15930
    //   5804: iconst_0
    //   5805: wide
    //   5809: wide
    //   5813: astore 5
    //   5815: wide
    //   5819: istore 6
    //   5821: wide
    //   5825: wide
    //   5829: wide
    //   5833: wide
    //   5837: wide
    //   5841: wide
    //   5845: wide
    //   5849: wide
    //   5853: caload
    //   5854: istore 31
    //   5856: iload 6
    //   5858: iconst_5
    //   5859: irem
    //   5860: tableswitch	default:+32 -> 5892, 0:+8670->14530, 1:+8679->14539, 2:+8688->14548, 3:+8697->14557
    //   5893: lconst_1
    //   5894: wide
    //   5898: wide
    //   5902: iload 31
    //   5904: ixor
    //   5905: i2c
    //   5906: wide
    //   5910: wide
    //   5914: wide
    //   5918: wide
    //   5922: castore
    //   5923: iload 6
    //   5925: iconst_1
    //   5926: iadd
    //   5927: wide
    //   5931: wide
    //   5935: ifne +28 -> 5963
    //   5938: aload 5
    //   5940: wide
    //   5944: wide
    //   5948: wide
    //   5952: wide
    //   5956: wide
    //   5960: goto -115 -> 5845
    //   5963: wide
    //   5967: wide
    //   5971: aload 5
    //   5973: wide
    //   5977: wide
    //   5981: wide
    //   5985: if_icmpgt -176 -> 5809
    //   5988: new 34	java/lang/String
    //   5991: dup
    //   5992: wide
    //   5996: invokespecial 44	java/lang/String:<init>	([C)V
    //   5999: invokevirtual 48	java/lang/String:intern	()Ljava/lang/String;
    //   6002: wide
    //   6006: aload_1
    //   6007: wide
    //   6011: wide
    //   6015: aastore
    //   6016: bipush 32
    //   6018: wide
    //   6022: ldc 112
    //   6024: invokevirtual 40	java/lang/String:toCharArray	()[C
    //   6027: wide
    //   6031: wide
    //   6035: arraylength
    //   6036: wide
    //   6040: wide
    //   6044: iconst_1
    //   6045: if_icmpgt +9877 -> 15922
    //   6048: iconst_0
    //   6049: wide
    //   6053: wide
    //   6057: astore 5
    //   6059: wide
    //   6063: istore 6
    //   6065: wide
    //   6069: wide
    //   6073: wide
    //   6077: wide
    //   6081: wide
    //   6085: wide
    //   6089: wide
    //   6093: wide
    //   6097: caload
    //   6098: istore 31
    //   6100: iload 6
    //   6102: iconst_5
    //   6103: irem
    //   6104: tableswitch	default:+32 -> 6136, 0:+8462->14566, 1:+8471->14575, 2:+8480->14584, 3:+8489->14593
    //   6137: lconst_1
    //   6138: wide
    //   6142: wide
    //   6146: iload 31
    //   6148: ixor
    //   6149: i2c
    //   6150: wide
    //   6154: wide
    //   6158: wide
    //   6162: wide
    //   6166: castore
    //   6167: iload 6
    //   6169: iconst_1
    //   6170: iadd
    //   6171: wide
    //   6175: wide
    //   6179: ifne +28 -> 6207
    //   6182: aload 5
    //   6184: wide
    //   6188: wide
    //   6192: wide
    //   6196: wide
    //   6200: wide
    //   6204: goto -115 -> 6089
    //   6207: wide
    //   6211: wide
    //   6215: aload 5
    //   6217: wide
    //   6221: wide
    //   6225: wide
    //   6229: if_icmpgt -176 -> 6053
    //   6232: new 34	java/lang/String
    //   6235: dup
    //   6236: wide
    //   6240: invokespecial 44	java/lang/String:<init>	([C)V
    //   6243: invokevirtual 48	java/lang/String:intern	()Ljava/lang/String;
    //   6246: wide
    //   6250: aload_1
    //   6251: wide
    //   6255: wide
    //   6259: aastore
    //   6260: bipush 33
    //   6262: wide
    //   6266: ldc 114
    //   6268: invokevirtual 40	java/lang/String:toCharArray	()[C
    //   6271: wide
    //   6275: wide
    //   6279: arraylength
    //   6280: wide
    //   6284: wide
    //   6288: iconst_1
    //   6289: if_icmpgt +9625 -> 15914
    //   6292: iconst_0
    //   6293: wide
    //   6297: wide
    //   6301: astore 5
    //   6303: wide
    //   6307: istore 6
    //   6309: wide
    //   6313: wide
    //   6317: wide
    //   6321: wide
    //   6325: wide
    //   6329: wide
    //   6333: wide
    //   6337: wide
    //   6341: caload
    //   6342: istore 31
    //   6344: iload 6
    //   6346: iconst_5
    //   6347: irem
    //   6348: tableswitch	default:+32 -> 6380, 0:+8254->14602, 1:+8263->14611, 2:+8272->14620, 3:+8281->14629
    //   6381: lconst_1
    //   6382: wide
    //   6386: wide
    //   6390: iload 31
    //   6392: ixor
    //   6393: i2c
    //   6394: wide
    //   6398: wide
    //   6402: wide
    //   6406: wide
    //   6410: castore
    //   6411: iload 6
    //   6413: iconst_1
    //   6414: iadd
    //   6415: wide
    //   6419: wide
    //   6423: ifne +28 -> 6451
    //   6426: aload 5
    //   6428: wide
    //   6432: wide
    //   6436: wide
    //   6440: wide
    //   6444: wide
    //   6448: goto -115 -> 6333
    //   6451: wide
    //   6455: wide
    //   6459: aload 5
    //   6461: wide
    //   6465: wide
    //   6469: wide
    //   6473: if_icmpgt -176 -> 6297
    //   6476: new 34	java/lang/String
    //   6479: dup
    //   6480: wide
    //   6484: invokespecial 44	java/lang/String:<init>	([C)V
    //   6487: invokevirtual 48	java/lang/String:intern	()Ljava/lang/String;
    //   6490: wide
    //   6494: aload_1
    //   6495: wide
    //   6499: wide
    //   6503: aastore
    //   6504: bipush 34
    //   6506: wide
    //   6510: ldc 116
    //   6512: invokevirtual 40	java/lang/String:toCharArray	()[C
    //   6515: wide
    //   6519: wide
    //   6523: arraylength
    //   6524: wide
    //   6528: wide
    //   6532: iconst_1
    //   6533: if_icmpgt +9373 -> 15906
    //   6536: iconst_0
    //   6537: wide
    //   6541: wide
    //   6545: astore 5
    //   6547: wide
    //   6551: istore 6
    //   6553: wide
    //   6557: wide
    //   6561: wide
    //   6565: wide
    //   6569: wide
    //   6573: wide
    //   6577: wide
    //   6581: wide
    //   6585: caload
    //   6586: istore 31
    //   6588: iload 6
    //   6590: iconst_5
    //   6591: irem
    //   6592: tableswitch	default:+32 -> 6624, 0:+8046->14638, 1:+8055->14647, 2:+8064->14656, 3:+8073->14665
    //   6625: lconst_1
    //   6626: wide
    //   6630: wide
    //   6634: iload 31
    //   6636: ixor
    //   6637: i2c
    //   6638: wide
    //   6642: wide
    //   6646: wide
    //   6650: wide
    //   6654: castore
    //   6655: iload 6
    //   6657: iconst_1
    //   6658: iadd
    //   6659: wide
    //   6663: wide
    //   6667: ifne +28 -> 6695
    //   6670: aload 5
    //   6672: wide
    //   6676: wide
    //   6680: wide
    //   6684: wide
    //   6688: wide
    //   6692: goto -115 -> 6577
    //   6695: wide
    //   6699: wide
    //   6703: aload 5
    //   6705: wide
    //   6709: wide
    //   6713: wide
    //   6717: if_icmpgt -176 -> 6541
    //   6720: new 34	java/lang/String
    //   6723: dup
    //   6724: wide
    //   6728: invokespecial 44	java/lang/String:<init>	([C)V
    //   6731: invokevirtual 48	java/lang/String:intern	()Ljava/lang/String;
    //   6734: wide
    //   6738: aload_1
    //   6739: wide
    //   6743: wide
    //   6747: aastore
    //   6748: bipush 35
    //   6750: wide
    //   6754: ldc 118
    //   6756: invokevirtual 40	java/lang/String:toCharArray	()[C
    //   6759: wide
    //   6763: wide
    //   6767: arraylength
    //   6768: wide
    //   6772: wide
    //   6776: iconst_1
    //   6777: if_icmpgt +9121 -> 15898
    //   6780: iconst_0
    //   6781: wide
    //   6785: wide
    //   6789: astore 5
    //   6791: wide
    //   6795: istore 6
    //   6797: wide
    //   6801: wide
    //   6805: wide
    //   6809: wide
    //   6813: wide
    //   6817: wide
    //   6821: wide
    //   6825: wide
    //   6829: caload
    //   6830: istore 31
    //   6832: iload 6
    //   6834: iconst_5
    //   6835: irem
    //   6836: tableswitch	default:+32 -> 6868, 0:+7838->14674, 1:+7847->14683, 2:+7856->14692, 3:+7865->14701
    //   6869: lconst_1
    //   6870: wide
    //   6874: wide
    //   6878: iload 31
    //   6880: ixor
    //   6881: i2c
    //   6882: wide
    //   6886: wide
    //   6890: wide
    //   6894: wide
    //   6898: castore
    //   6899: iload 6
    //   6901: iconst_1
    //   6902: iadd
    //   6903: wide
    //   6907: wide
    //   6911: ifne +28 -> 6939
    //   6914: aload 5
    //   6916: wide
    //   6920: wide
    //   6924: wide
    //   6928: wide
    //   6932: wide
    //   6936: goto -115 -> 6821
    //   6939: wide
    //   6943: wide
    //   6947: aload 5
    //   6949: wide
    //   6953: wide
    //   6957: wide
    //   6961: if_icmpgt -176 -> 6785
    //   6964: new 34	java/lang/String
    //   6967: dup
    //   6968: wide
    //   6972: invokespecial 44	java/lang/String:<init>	([C)V
    //   6975: invokevirtual 48	java/lang/String:intern	()Ljava/lang/String;
    //   6978: wide
    //   6982: aload_1
    //   6983: wide
    //   6987: wide
    //   6991: aastore
    //   6992: bipush 36
    //   6994: wide
    //   6998: ldc 120
    //   7000: invokevirtual 40	java/lang/String:toCharArray	()[C
    //   7003: wide
    //   7007: wide
    //   7011: arraylength
    //   7012: wide
    //   7016: wide
    //   7020: iconst_1
    //   7021: if_icmpgt +8869 -> 15890
    //   7024: iconst_0
    //   7025: wide
    //   7029: wide
    //   7033: astore 5
    //   7035: wide
    //   7039: istore 6
    //   7041: wide
    //   7045: wide
    //   7049: wide
    //   7053: wide
    //   7057: wide
    //   7061: wide
    //   7065: wide
    //   7069: wide
    //   7073: caload
    //   7074: istore 31
    //   7076: iload 6
    //   7078: iconst_5
    //   7079: irem
    //   7080: tableswitch	default:+32 -> 7112, 0:+7630->14710, 1:+7639->14719, 2:+7648->14728, 3:+7657->14737
    //   7113: lconst_1
    //   7114: wide
    //   7118: wide
    //   7122: iload 31
    //   7124: ixor
    //   7125: i2c
    //   7126: wide
    //   7130: wide
    //   7134: wide
    //   7138: wide
    //   7142: castore
    //   7143: iload 6
    //   7145: iconst_1
    //   7146: iadd
    //   7147: wide
    //   7151: wide
    //   7155: ifne +28 -> 7183
    //   7158: aload 5
    //   7160: wide
    //   7164: wide
    //   7168: wide
    //   7172: wide
    //   7176: wide
    //   7180: goto -115 -> 7065
    //   7183: wide
    //   7187: wide
    //   7191: aload 5
    //   7193: wide
    //   7197: wide
    //   7201: wide
    //   7205: if_icmpgt -176 -> 7029
    //   7208: new 34	java/lang/String
    //   7211: dup
    //   7212: wide
    //   7216: invokespecial 44	java/lang/String:<init>	([C)V
    //   7219: invokevirtual 48	java/lang/String:intern	()Ljava/lang/String;
    //   7222: wide
    //   7226: aload_1
    //   7227: wide
    //   7231: wide
    //   7235: aastore
    //   7236: bipush 37
    //   7238: wide
    //   7242: ldc 122
    //   7244: invokevirtual 40	java/lang/String:toCharArray	()[C
    //   7247: wide
    //   7251: wide
    //   7255: arraylength
    //   7256: wide
    //   7260: wide
    //   7264: iconst_1
    //   7265: if_icmpgt +8617 -> 15882
    //   7268: iconst_0
    //   7269: wide
    //   7273: wide
    //   7277: astore 5
    //   7279: wide
    //   7283: istore 6
    //   7285: wide
    //   7289: wide
    //   7293: wide
    //   7297: wide
    //   7301: wide
    //   7305: wide
    //   7309: wide
    //   7313: wide
    //   7317: caload
    //   7318: istore 31
    //   7320: iload 6
    //   7322: iconst_5
    //   7323: irem
    //   7324: tableswitch	default:+32 -> 7356, 0:+7422->14746, 1:+7431->14755, 2:+7440->14764, 3:+7449->14773
    //   7357: lconst_1
    //   7358: wide
    //   7362: wide
    //   7366: iload 31
    //   7368: ixor
    //   7369: i2c
    //   7370: wide
    //   7374: wide
    //   7378: wide
    //   7382: wide
    //   7386: castore
    //   7387: iload 6
    //   7389: iconst_1
    //   7390: iadd
    //   7391: wide
    //   7395: wide
    //   7399: ifne +28 -> 7427
    //   7402: aload 5
    //   7404: wide
    //   7408: wide
    //   7412: wide
    //   7416: wide
    //   7420: wide
    //   7424: goto -115 -> 7309
    //   7427: wide
    //   7431: wide
    //   7435: aload 5
    //   7437: wide
    //   7441: wide
    //   7445: wide
    //   7449: if_icmpgt -176 -> 7273
    //   7452: new 34	java/lang/String
    //   7455: dup
    //   7456: wide
    //   7460: invokespecial 44	java/lang/String:<init>	([C)V
    //   7463: invokevirtual 48	java/lang/String:intern	()Ljava/lang/String;
    //   7466: wide
    //   7470: aload_1
    //   7471: wide
    //   7475: wide
    //   7479: aastore
    //   7480: bipush 38
    //   7482: wide
    //   7486: ldc 124
    //   7488: invokevirtual 40	java/lang/String:toCharArray	()[C
    //   7491: wide
    //   7495: wide
    //   7499: arraylength
    //   7500: wide
    //   7504: wide
    //   7508: iconst_1
    //   7509: if_icmpgt +8365 -> 15874
    //   7512: iconst_0
    //   7513: wide
    //   7517: wide
    //   7521: astore 5
    //   7523: wide
    //   7527: istore 6
    //   7529: wide
    //   7533: wide
    //   7537: wide
    //   7541: wide
    //   7545: wide
    //   7549: wide
    //   7553: wide
    //   7557: wide
    //   7561: caload
    //   7562: istore 31
    //   7564: iload 6
    //   7566: iconst_5
    //   7567: irem
    //   7568: tableswitch	default:+32 -> 7600, 0:+7214->14782, 1:+7223->14791, 2:+7232->14800, 3:+7241->14809
    //   7601: lconst_1
    //   7602: wide
    //   7606: wide
    //   7610: iload 31
    //   7612: ixor
    //   7613: i2c
    //   7614: wide
    //   7618: wide
    //   7622: wide
    //   7626: wide
    //   7630: castore
    //   7631: iload 6
    //   7633: iconst_1
    //   7634: iadd
    //   7635: wide
    //   7639: wide
    //   7643: ifne +28 -> 7671
    //   7646: aload 5
    //   7648: wide
    //   7652: wide
    //   7656: wide
    //   7660: wide
    //   7664: wide
    //   7668: goto -115 -> 7553
    //   7671: wide
    //   7675: wide
    //   7679: aload 5
    //   7681: wide
    //   7685: wide
    //   7689: wide
    //   7693: if_icmpgt -176 -> 7517
    //   7696: new 34	java/lang/String
    //   7699: dup
    //   7700: wide
    //   7704: invokespecial 44	java/lang/String:<init>	([C)V
    //   7707: invokevirtual 48	java/lang/String:intern	()Ljava/lang/String;
    //   7710: wide
    //   7714: aload_1
    //   7715: wide
    //   7719: wide
    //   7723: aastore
    //   7724: bipush 39
    //   7726: wide
    //   7730: ldc 126
    //   7732: invokevirtual 40	java/lang/String:toCharArray	()[C
    //   7735: wide
    //   7739: wide
    //   7743: arraylength
    //   7744: wide
    //   7748: wide
    //   7752: iconst_1
    //   7753: if_icmpgt +8113 -> 15866
    //   7756: iconst_0
    //   7757: wide
    //   7761: wide
    //   7765: astore 5
    //   7767: wide
    //   7771: istore 6
    //   7773: wide
    //   7777: wide
    //   7781: wide
    //   7785: wide
    //   7789: wide
    //   7793: wide
    //   7797: wide
    //   7801: wide
    //   7805: caload
    //   7806: istore 31
    //   7808: iload 6
    //   7810: iconst_5
    //   7811: irem
    //   7812: tableswitch	default:+32 -> 7844, 0:+7006->14818, 1:+7015->14827, 2:+7024->14836, 3:+7033->14845
    //   7845: lconst_1
    //   7846: wide
    //   7850: wide
    //   7854: iload 31
    //   7856: ixor
    //   7857: i2c
    //   7858: wide
    //   7862: wide
    //   7866: wide
    //   7870: wide
    //   7874: castore
    //   7875: iload 6
    //   7877: iconst_1
    //   7878: iadd
    //   7879: wide
    //   7883: wide
    //   7887: ifne +28 -> 7915
    //   7890: aload 5
    //   7892: wide
    //   7896: wide
    //   7900: wide
    //   7904: wide
    //   7908: wide
    //   7912: goto -115 -> 7797
    //   7915: wide
    //   7919: wide
    //   7923: aload 5
    //   7925: wide
    //   7929: wide
    //   7933: wide
    //   7937: if_icmpgt -176 -> 7761
    //   7940: new 34	java/lang/String
    //   7943: dup
    //   7944: wide
    //   7948: invokespecial 44	java/lang/String:<init>	([C)V
    //   7951: invokevirtual 48	java/lang/String:intern	()Ljava/lang/String;
    //   7954: wide
    //   7958: aload_1
    //   7959: wide
    //   7963: wide
    //   7967: aastore
    //   7968: bipush 40
    //   7970: wide
    //   7974: ldc 128
    //   7976: invokevirtual 40	java/lang/String:toCharArray	()[C
    //   7979: wide
    //   7983: wide
    //   7987: arraylength
    //   7988: wide
    //   7992: wide
    //   7996: iconst_1
    //   7997: if_icmpgt +7861 -> 15858
    //   8000: iconst_0
    //   8001: wide
    //   8005: wide
    //   8009: astore 5
    //   8011: wide
    //   8015: istore 6
    //   8017: wide
    //   8021: wide
    //   8025: wide
    //   8029: wide
    //   8033: wide
    //   8037: wide
    //   8041: wide
    //   8045: wide
    //   8049: caload
    //   8050: istore 31
    //   8052: iload 6
    //   8054: iconst_5
    //   8055: irem
    //   8056: tableswitch	default:+32 -> 8088, 0:+6798->14854, 1:+6807->14863, 2:+6816->14872, 3:+6825->14881
    //   8089: lconst_1
    //   8090: wide
    //   8094: wide
    //   8098: iload 31
    //   8100: ixor
    //   8101: i2c
    //   8102: wide
    //   8106: wide
    //   8110: wide
    //   8114: wide
    //   8118: castore
    //   8119: iload 6
    //   8121: iconst_1
    //   8122: iadd
    //   8123: wide
    //   8127: wide
    //   8131: ifne +28 -> 8159
    //   8134: aload 5
    //   8136: wide
    //   8140: wide
    //   8144: wide
    //   8148: wide
    //   8152: wide
    //   8156: goto -115 -> 8041
    //   8159: wide
    //   8163: wide
    //   8167: aload 5
    //   8169: wide
    //   8173: wide
    //   8177: wide
    //   8181: if_icmpgt -176 -> 8005
    //   8184: new 34	java/lang/String
    //   8187: dup
    //   8188: wide
    //   8192: invokespecial 44	java/lang/String:<init>	([C)V
    //   8195: invokevirtual 48	java/lang/String:intern	()Ljava/lang/String;
    //   8198: wide
    //   8202: aload_1
    //   8203: wide
    //   8207: wide
    //   8211: aastore
    //   8212: ldc 130
    //   8214: invokevirtual 40	java/lang/String:toCharArray	()[C
    //   8217: wide
    //   8221: wide
    //   8225: arraylength
    //   8226: wide
    //   8230: wide
    //   8234: iconst_1
    //   8235: if_icmpgt +7615 -> 15850
    //   8238: iconst_0
    //   8239: wide
    //   8243: wide
    //   8247: astore 5
    //   8249: wide
    //   8253: istore 6
    //   8255: wide
    //   8259: wide
    //   8263: wide
    //   8267: wide
    //   8271: wide
    //   8275: wide
    //   8279: wide
    //   8283: wide
    //   8287: caload
    //   8288: wide
    //   8292: iload 6
    //   8294: iconst_5
    //   8295: irem
    //   8296: tableswitch	default:+32 -> 8328, 0:+6594->14890, 1:+6603->14899, 2:+6612->14908, 3:+6621->14917
    //   8329: lconst_1
    //   8330: wide
    //   8334: wide
    //   8338: wide
    //   8342: ixor
    //   8343: i2c
    //   8344: wide
    //   8348: wide
    //   8352: wide
    //   8356: wide
    //   8360: castore
    //   8361: iload 6
    //   8363: iconst_1
    //   8364: iadd
    //   8365: wide
    //   8369: wide
    //   8373: ifne +28 -> 8401
    //   8376: aload 5
    //   8378: wide
    //   8382: wide
    //   8386: wide
    //   8390: wide
    //   8394: wide
    //   8398: goto -119 -> 8279
    //   8401: wide
    //   8405: wide
    //   8409: aload 5
    //   8411: wide
    //   8415: wide
    //   8419: wide
    //   8423: if_icmpgt -180 -> 8243
    //   8426: new 34	java/lang/String
    //   8429: dup
    //   8430: wide
    //   8434: invokespecial 44	java/lang/String:<init>	([C)V
    //   8437: invokevirtual 48	java/lang/String:intern	()Ljava/lang/String;
    //   8440: wide
    //   8444: aload_1
    //   8445: bipush 41
    //   8447: wide
    //   8451: aastore
    //   8452: bipush 42
    //   8454: wide
    //   8458: ldc 132
    //   8460: invokevirtual 40	java/lang/String:toCharArray	()[C
    //   8463: wide
    //   8467: wide
    //   8471: arraylength
    //   8472: wide
    //   8476: wide
    //   8480: iconst_1
    //   8481: if_icmpgt +7361 -> 15842
    //   8484: iconst_0
    //   8485: wide
    //   8489: wide
    //   8493: astore 5
    //   8495: wide
    //   8499: istore 6
    //   8501: wide
    //   8505: wide
    //   8509: wide
    //   8513: wide
    //   8517: wide
    //   8521: wide
    //   8525: wide
    //   8529: wide
    //   8533: caload
    //   8534: istore 31
    //   8536: iload 6
    //   8538: iconst_5
    //   8539: irem
    //   8540: tableswitch	default:+32 -> 8572, 0:+6386->14926, 1:+6395->14935, 2:+6404->14944, 3:+6413->14953
    //   8573: lconst_1
    //   8574: wide
    //   8578: wide
    //   8582: iload 31
    //   8584: ixor
    //   8585: i2c
    //   8586: wide
    //   8590: wide
    //   8594: wide
    //   8598: wide
    //   8602: castore
    //   8603: iload 6
    //   8605: iconst_1
    //   8606: iadd
    //   8607: wide
    //   8611: wide
    //   8615: ifne +28 -> 8643
    //   8618: aload 5
    //   8620: wide
    //   8624: wide
    //   8628: wide
    //   8632: wide
    //   8636: wide
    //   8640: goto -115 -> 8525
    //   8643: wide
    //   8647: wide
    //   8651: aload 5
    //   8653: wide
    //   8657: wide
    //   8661: wide
    //   8665: if_icmpgt -176 -> 8489
    //   8668: new 34	java/lang/String
    //   8671: dup
    //   8672: wide
    //   8676: invokespecial 44	java/lang/String:<init>	([C)V
    //   8679: invokevirtual 48	java/lang/String:intern	()Ljava/lang/String;
    //   8682: wide
    //   8686: aload_1
    //   8687: wide
    //   8691: wide
    //   8695: aastore
    //   8696: bipush 43
    //   8698: wide
    //   8702: ldc 134
    //   8704: invokevirtual 40	java/lang/String:toCharArray	()[C
    //   8707: wide
    //   8711: wide
    //   8715: arraylength
    //   8716: wide
    //   8720: wide
    //   8724: iconst_1
    //   8725: if_icmpgt +7109 -> 15834
    //   8728: iconst_0
    //   8729: wide
    //   8733: wide
    //   8737: astore 5
    //   8739: wide
    //   8743: istore 6
    //   8745: wide
    //   8749: wide
    //   8753: wide
    //   8757: wide
    //   8761: wide
    //   8765: wide
    //   8769: wide
    //   8773: wide
    //   8777: caload
    //   8778: istore 31
    //   8780: iload 6
    //   8782: iconst_5
    //   8783: irem
    //   8784: tableswitch	default:+32 -> 8816, 0:+6178->14962, 1:+6187->14971, 2:+6196->14980, 3:+6205->14989
    //   8817: lconst_1
    //   8818: wide
    //   8822: wide
    //   8826: iload 31
    //   8828: ixor
    //   8829: i2c
    //   8830: wide
    //   8834: wide
    //   8838: wide
    //   8842: wide
    //   8846: castore
    //   8847: iload 6
    //   8849: iconst_1
    //   8850: iadd
    //   8851: wide
    //   8855: wide
    //   8859: ifne +28 -> 8887
    //   8862: aload 5
    //   8864: wide
    //   8868: wide
    //   8872: wide
    //   8876: wide
    //   8880: wide
    //   8884: goto -115 -> 8769
    //   8887: wide
    //   8891: wide
    //   8895: aload 5
    //   8897: wide
    //   8901: wide
    //   8905: wide
    //   8909: if_icmpgt -176 -> 8733
    //   8912: new 34	java/lang/String
    //   8915: dup
    //   8916: wide
    //   8920: invokespecial 44	java/lang/String:<init>	([C)V
    //   8923: invokevirtual 48	java/lang/String:intern	()Ljava/lang/String;
    //   8926: wide
    //   8930: aload_1
    //   8931: wide
    //   8935: wide
    //   8939: aastore
    //   8940: bipush 44
    //   8942: wide
    //   8946: ldc 136
    //   8948: invokevirtual 40	java/lang/String:toCharArray	()[C
    //   8951: wide
    //   8955: wide
    //   8959: arraylength
    //   8960: wide
    //   8964: wide
    //   8968: iconst_1
    //   8969: if_icmpgt +6857 -> 15826
    //   8972: iconst_0
    //   8973: wide
    //   8977: wide
    //   8981: astore 5
    //   8983: wide
    //   8987: istore 6
    //   8989: wide
    //   8993: wide
    //   8997: wide
    //   9001: wide
    //   9005: wide
    //   9009: wide
    //   9013: wide
    //   9017: wide
    //   9021: caload
    //   9022: istore 31
    //   9024: iload 6
    //   9026: iconst_5
    //   9027: irem
    //   9028: tableswitch	default:+32 -> 9060, 0:+5970->14998, 1:+5979->15007, 2:+5988->15016, 3:+5997->15025
    //   9061: lconst_1
    //   9062: wide
    //   9066: wide
    //   9070: iload 31
    //   9072: ixor
    //   9073: i2c
    //   9074: wide
    //   9078: wide
    //   9082: wide
    //   9086: wide
    //   9090: castore
    //   9091: iload 6
    //   9093: iconst_1
    //   9094: iadd
    //   9095: wide
    //   9099: wide
    //   9103: ifne +28 -> 9131
    //   9106: aload 5
    //   9108: wide
    //   9112: wide
    //   9116: wide
    //   9120: wide
    //   9124: wide
    //   9128: goto -115 -> 9013
    //   9131: wide
    //   9135: wide
    //   9139: aload 5
    //   9141: wide
    //   9145: wide
    //   9149: wide
    //   9153: if_icmpgt -176 -> 8977
    //   9156: new 34	java/lang/String
    //   9159: dup
    //   9160: wide
    //   9164: invokespecial 44	java/lang/String:<init>	([C)V
    //   9167: invokevirtual 48	java/lang/String:intern	()Ljava/lang/String;
    //   9170: wide
    //   9174: aload_1
    //   9175: wide
    //   9179: wide
    //   9183: aastore
    //   9184: bipush 45
    //   9186: wide
    //   9190: ldc 138
    //   9192: invokevirtual 40	java/lang/String:toCharArray	()[C
    //   9195: wide
    //   9199: wide
    //   9203: arraylength
    //   9204: wide
    //   9208: wide
    //   9212: iconst_1
    //   9213: if_icmpgt +6605 -> 15818
    //   9216: iconst_0
    //   9217: wide
    //   9221: wide
    //   9225: astore 5
    //   9227: wide
    //   9231: istore 6
    //   9233: wide
    //   9237: wide
    //   9241: wide
    //   9245: wide
    //   9249: wide
    //   9253: wide
    //   9257: wide
    //   9261: wide
    //   9265: caload
    //   9266: istore 31
    //   9268: iload 6
    //   9270: iconst_5
    //   9271: irem
    //   9272: tableswitch	default:+32 -> 9304, 0:+5762->15034, 1:+5771->15043, 2:+5780->15052, 3:+5789->15061
    //   9305: lconst_1
    //   9306: wide
    //   9310: wide
    //   9314: iload 31
    //   9316: ixor
    //   9317: i2c
    //   9318: wide
    //   9322: wide
    //   9326: wide
    //   9330: wide
    //   9334: castore
    //   9335: iload 6
    //   9337: iconst_1
    //   9338: iadd
    //   9339: wide
    //   9343: wide
    //   9347: ifne +28 -> 9375
    //   9350: aload 5
    //   9352: wide
    //   9356: wide
    //   9360: wide
    //   9364: wide
    //   9368: wide
    //   9372: goto -115 -> 9257
    //   9375: wide
    //   9379: wide
    //   9383: aload 5
    //   9385: wide
    //   9389: wide
    //   9393: wide
    //   9397: if_icmpgt -176 -> 9221
    //   9400: new 34	java/lang/String
    //   9403: dup
    //   9404: wide
    //   9408: invokespecial 44	java/lang/String:<init>	([C)V
    //   9411: invokevirtual 48	java/lang/String:intern	()Ljava/lang/String;
    //   9414: wide
    //   9418: aload_1
    //   9419: wide
    //   9423: wide
    //   9427: aastore
    //   9428: bipush 46
    //   9430: wide
    //   9434: ldc 140
    //   9436: invokevirtual 40	java/lang/String:toCharArray	()[C
    //   9439: wide
    //   9443: wide
    //   9447: arraylength
    //   9448: wide
    //   9452: wide
    //   9456: iconst_1
    //   9457: if_icmpgt +6353 -> 15810
    //   9460: iconst_0
    //   9461: wide
    //   9465: wide
    //   9469: astore 5
    //   9471: wide
    //   9475: istore 6
    //   9477: wide
    //   9481: wide
    //   9485: wide
    //   9489: wide
    //   9493: wide
    //   9497: wide
    //   9501: wide
    //   9505: wide
    //   9509: caload
    //   9510: istore 31
    //   9512: iload 6
    //   9514: iconst_5
    //   9515: irem
    //   9516: tableswitch	default:+32 -> 9548, 0:+5554->15070, 1:+5563->15079, 2:+5572->15088, 3:+5581->15097
    //   9549: lconst_1
    //   9550: wide
    //   9554: wide
    //   9558: iload 31
    //   9560: ixor
    //   9561: i2c
    //   9562: wide
    //   9566: wide
    //   9570: wide
    //   9574: wide
    //   9578: castore
    //   9579: iload 6
    //   9581: iconst_1
    //   9582: iadd
    //   9583: wide
    //   9587: wide
    //   9591: ifne +28 -> 9619
    //   9594: aload 5
    //   9596: wide
    //   9600: wide
    //   9604: wide
    //   9608: wide
    //   9612: wide
    //   9616: goto -115 -> 9501
    //   9619: wide
    //   9623: wide
    //   9627: aload 5
    //   9629: wide
    //   9633: wide
    //   9637: wide
    //   9641: if_icmpgt -176 -> 9465
    //   9644: new 34	java/lang/String
    //   9647: dup
    //   9648: wide
    //   9652: invokespecial 44	java/lang/String:<init>	([C)V
    //   9655: invokevirtual 48	java/lang/String:intern	()Ljava/lang/String;
    //   9658: wide
    //   9662: aload_1
    //   9663: wide
    //   9667: wide
    //   9671: aastore
    //   9672: bipush 47
    //   9674: wide
    //   9678: ldc 142
    //   9680: invokevirtual 40	java/lang/String:toCharArray	()[C
    //   9683: wide
    //   9687: wide
    //   9691: arraylength
    //   9692: wide
    //   9696: wide
    //   9700: iconst_1
    //   9701: if_icmpgt +6101 -> 15802
    //   9704: iconst_0
    //   9705: wide
    //   9709: wide
    //   9713: astore 5
    //   9715: wide
    //   9719: istore 6
    //   9721: wide
    //   9725: wide
    //   9729: wide
    //   9733: wide
    //   9737: wide
    //   9741: wide
    //   9745: wide
    //   9749: wide
    //   9753: caload
    //   9754: istore 31
    //   9756: iload 6
    //   9758: iconst_5
    //   9759: irem
    //   9760: tableswitch	default:+32 -> 9792, 0:+5346->15106, 1:+5355->15115, 2:+5364->15124, 3:+5373->15133
    //   9793: lconst_1
    //   9794: wide
    //   9798: wide
    //   9802: iload 31
    //   9804: ixor
    //   9805: i2c
    //   9806: wide
    //   9810: wide
    //   9814: wide
    //   9818: wide
    //   9822: castore
    //   9823: iload 6
    //   9825: iconst_1
    //   9826: iadd
    //   9827: wide
    //   9831: wide
    //   9835: ifne +28 -> 9863
    //   9838: aload 5
    //   9840: wide
    //   9844: wide
    //   9848: wide
    //   9852: wide
    //   9856: wide
    //   9860: goto -115 -> 9745
    //   9863: wide
    //   9867: wide
    //   9871: aload 5
    //   9873: wide
    //   9877: wide
    //   9881: wide
    //   9885: if_icmpgt -176 -> 9709
    //   9888: new 34	java/lang/String
    //   9891: dup
    //   9892: wide
    //   9896: invokespecial 44	java/lang/String:<init>	([C)V
    //   9899: invokevirtual 48	java/lang/String:intern	()Ljava/lang/String;
    //   9902: wide
    //   9906: aload_1
    //   9907: wide
    //   9911: wide
    //   9915: aastore
    //   9916: bipush 48
    //   9918: wide
    //   9922: ldc 144
    //   9924: invokevirtual 40	java/lang/String:toCharArray	()[C
    //   9927: wide
    //   9931: wide
    //   9935: arraylength
    //   9936: wide
    //   9940: wide
    //   9944: iconst_1
    //   9945: if_icmpgt +5849 -> 15794
    //   9948: iconst_0
    //   9949: wide
    //   9953: wide
    //   9957: astore 5
    //   9959: wide
    //   9963: istore 6
    //   9965: wide
    //   9969: wide
    //   9973: wide
    //   9977: wide
    //   9981: wide
    //   9985: wide
    //   9989: wide
    //   9993: wide
    //   9997: caload
    //   9998: istore 31
    //   10000: iload 6
    //   10002: iconst_5
    //   10003: irem
    //   10004: tableswitch	default:+32 -> 10036, 0:+5138->15142, 1:+5147->15151, 2:+5156->15160, 3:+5165->15169
    //   10037: lconst_1
    //   10038: wide
    //   10042: wide
    //   10046: iload 31
    //   10048: ixor
    //   10049: i2c
    //   10050: wide
    //   10054: wide
    //   10058: wide
    //   10062: wide
    //   10066: castore
    //   10067: iload 6
    //   10069: iconst_1
    //   10070: iadd
    //   10071: wide
    //   10075: wide
    //   10079: ifne +28 -> 10107
    //   10082: aload 5
    //   10084: wide
    //   10088: wide
    //   10092: wide
    //   10096: wide
    //   10100: wide
    //   10104: goto -115 -> 9989
    //   10107: wide
    //   10111: wide
    //   10115: aload 5
    //   10117: wide
    //   10121: wide
    //   10125: wide
    //   10129: if_icmpgt -176 -> 9953
    //   10132: new 34	java/lang/String
    //   10135: dup
    //   10136: wide
    //   10140: invokespecial 44	java/lang/String:<init>	([C)V
    //   10143: invokevirtual 48	java/lang/String:intern	()Ljava/lang/String;
    //   10146: wide
    //   10150: aload_1
    //   10151: wide
    //   10155: wide
    //   10159: aastore
    //   10160: bipush 49
    //   10162: wide
    //   10166: ldc 146
    //   10168: invokevirtual 40	java/lang/String:toCharArray	()[C
    //   10171: wide
    //   10175: wide
    //   10179: arraylength
    //   10180: wide
    //   10184: wide
    //   10188: iconst_1
    //   10189: if_icmpgt +5597 -> 15786
    //   10192: iconst_0
    //   10193: wide
    //   10197: wide
    //   10201: astore 5
    //   10203: wide
    //   10207: istore 6
    //   10209: wide
    //   10213: wide
    //   10217: wide
    //   10221: wide
    //   10225: wide
    //   10229: wide
    //   10233: wide
    //   10237: wide
    //   10241: caload
    //   10242: istore 31
    //   10244: iload 6
    //   10246: iconst_5
    //   10247: irem
    //   10248: tableswitch	default:+32 -> 10280, 0:+4930->15178, 1:+4939->15187, 2:+4948->15196, 3:+4957->15205
    //   10281: lconst_1
    //   10282: wide
    //   10286: wide
    //   10290: iload 31
    //   10292: ixor
    //   10293: i2c
    //   10294: wide
    //   10298: wide
    //   10302: wide
    //   10306: wide
    //   10310: castore
    //   10311: iload 6
    //   10313: iconst_1
    //   10314: iadd
    //   10315: wide
    //   10319: wide
    //   10323: ifne +28 -> 10351
    //   10326: aload 5
    //   10328: wide
    //   10332: wide
    //   10336: wide
    //   10340: wide
    //   10344: wide
    //   10348: goto -115 -> 10233
    //   10351: wide
    //   10355: wide
    //   10359: aload 5
    //   10361: wide
    //   10365: wide
    //   10369: wide
    //   10373: if_icmpgt -176 -> 10197
    //   10376: new 34	java/lang/String
    //   10379: dup
    //   10380: wide
    //   10384: invokespecial 44	java/lang/String:<init>	([C)V
    //   10387: invokevirtual 48	java/lang/String:intern	()Ljava/lang/String;
    //   10390: wide
    //   10394: aload_1
    //   10395: wide
    //   10399: wide
    //   10403: aastore
    //   10404: bipush 50
    //   10406: wide
    //   10410: ldc 148
    //   10412: invokevirtual 40	java/lang/String:toCharArray	()[C
    //   10415: wide
    //   10419: wide
    //   10423: arraylength
    //   10424: wide
    //   10428: wide
    //   10432: iconst_1
    //   10433: if_icmpgt +5345 -> 15778
    //   10436: iconst_0
    //   10437: wide
    //   10441: wide
    //   10445: astore 5
    //   10447: wide
    //   10451: istore 6
    //   10453: wide
    //   10457: wide
    //   10461: wide
    //   10465: wide
    //   10469: wide
    //   10473: wide
    //   10477: wide
    //   10481: wide
    //   10485: caload
    //   10486: istore 31
    //   10488: iload 6
    //   10490: iconst_5
    //   10491: irem
    //   10492: tableswitch	default:+32 -> 10524, 0:+4722->15214, 1:+4731->15223, 2:+4740->15232, 3:+4749->15241
    //   10525: lconst_1
    //   10526: wide
    //   10530: wide
    //   10534: iload 31
    //   10536: ixor
    //   10537: i2c
    //   10538: wide
    //   10542: wide
    //   10546: wide
    //   10550: wide
    //   10554: castore
    //   10555: iload 6
    //   10557: iconst_1
    //   10558: iadd
    //   10559: wide
    //   10563: wide
    //   10567: ifne +28 -> 10595
    //   10570: aload 5
    //   10572: wide
    //   10576: wide
    //   10580: wide
    //   10584: wide
    //   10588: wide
    //   10592: goto -115 -> 10477
    //   10595: wide
    //   10599: wide
    //   10603: aload 5
    //   10605: wide
    //   10609: wide
    //   10613: wide
    //   10617: if_icmpgt -176 -> 10441
    //   10620: new 34	java/lang/String
    //   10623: dup
    //   10624: wide
    //   10628: invokespecial 44	java/lang/String:<init>	([C)V
    //   10631: invokevirtual 48	java/lang/String:intern	()Ljava/lang/String;
    //   10634: wide
    //   10638: aload_1
    //   10639: wide
    //   10643: wide
    //   10647: aastore
    //   10648: bipush 51
    //   10650: wide
    //   10654: ldc 150
    //   10656: invokevirtual 40	java/lang/String:toCharArray	()[C
    //   10659: wide
    //   10663: wide
    //   10667: arraylength
    //   10668: wide
    //   10672: wide
    //   10676: iconst_1
    //   10677: if_icmpgt +5093 -> 15770
    //   10680: iconst_0
    //   10681: wide
    //   10685: wide
    //   10689: astore 5
    //   10691: wide
    //   10695: istore 6
    //   10697: wide
    //   10701: wide
    //   10705: wide
    //   10709: wide
    //   10713: wide
    //   10717: wide
    //   10721: wide
    //   10725: wide
    //   10729: caload
    //   10730: istore 31
    //   10732: iload 6
    //   10734: iconst_5
    //   10735: irem
    //   10736: tableswitch	default:+32 -> 10768, 0:+4514->15250, 1:+4523->15259, 2:+4532->15268, 3:+4541->15277
    //   10769: lconst_1
    //   10770: wide
    //   10774: wide
    //   10778: iload 31
    //   10780: ixor
    //   10781: i2c
    //   10782: wide
    //   10786: wide
    //   10790: wide
    //   10794: wide
    //   10798: castore
    //   10799: iload 6
    //   10801: iconst_1
    //   10802: iadd
    //   10803: wide
    //   10807: wide
    //   10811: ifne +28 -> 10839
    //   10814: aload 5
    //   10816: wide
    //   10820: wide
    //   10824: wide
    //   10828: wide
    //   10832: wide
    //   10836: goto -115 -> 10721
    //   10839: wide
    //   10843: wide
    //   10847: aload 5
    //   10849: wide
    //   10853: wide
    //   10857: wide
    //   10861: if_icmpgt -176 -> 10685
    //   10864: new 34	java/lang/String
    //   10867: dup
    //   10868: wide
    //   10872: invokespecial 44	java/lang/String:<init>	([C)V
    //   10875: invokevirtual 48	java/lang/String:intern	()Ljava/lang/String;
    //   10878: wide
    //   10882: aload_1
    //   10883: wide
    //   10887: wide
    //   10891: aastore
    //   10892: bipush 52
    //   10894: wide
    //   10898: ldc 152
    //   10900: invokevirtual 40	java/lang/String:toCharArray	()[C
    //   10903: wide
    //   10907: wide
    //   10911: arraylength
    //   10912: wide
    //   10916: wide
    //   10920: iconst_1
    //   10921: if_icmpgt +4841 -> 15762
    //   10924: iconst_0
    //   10925: wide
    //   10929: wide
    //   10933: astore 5
    //   10935: wide
    //   10939: istore 6
    //   10941: wide
    //   10945: wide
    //   10949: wide
    //   10953: wide
    //   10957: wide
    //   10961: wide
    //   10965: wide
    //   10969: wide
    //   10973: caload
    //   10974: istore 31
    //   10976: iload 6
    //   10978: iconst_5
    //   10979: irem
    //   10980: tableswitch	default:+32 -> 11012, 0:+4306->15286, 1:+4315->15295, 2:+4324->15304, 3:+4333->15313
    //   11013: lconst_1
    //   11014: wide
    //   11018: wide
    //   11022: iload 31
    //   11024: ixor
    //   11025: i2c
    //   11026: wide
    //   11030: wide
    //   11034: wide
    //   11038: wide
    //   11042: castore
    //   11043: iload 6
    //   11045: iconst_1
    //   11046: iadd
    //   11047: wide
    //   11051: wide
    //   11055: ifne +28 -> 11083
    //   11058: aload 5
    //   11060: wide
    //   11064: wide
    //   11068: wide
    //   11072: wide
    //   11076: wide
    //   11080: goto -115 -> 10965
    //   11083: wide
    //   11087: wide
    //   11091: aload 5
    //   11093: wide
    //   11097: wide
    //   11101: wide
    //   11105: if_icmpgt -176 -> 10929
    //   11108: new 34	java/lang/String
    //   11111: dup
    //   11112: wide
    //   11116: invokespecial 44	java/lang/String:<init>	([C)V
    //   11119: invokevirtual 48	java/lang/String:intern	()Ljava/lang/String;
    //   11122: wide
    //   11126: aload_1
    //   11127: wide
    //   11131: wide
    //   11135: aastore
    //   11136: bipush 53
    //   11138: wide
    //   11142: ldc 154
    //   11144: invokevirtual 40	java/lang/String:toCharArray	()[C
    //   11147: wide
    //   11151: wide
    //   11155: arraylength
    //   11156: wide
    //   11160: wide
    //   11164: iconst_1
    //   11165: if_icmpgt +4589 -> 15754
    //   11168: iconst_0
    //   11169: wide
    //   11173: wide
    //   11177: astore 5
    //   11179: wide
    //   11183: istore 6
    //   11185: wide
    //   11189: wide
    //   11193: wide
    //   11197: wide
    //   11201: wide
    //   11205: wide
    //   11209: wide
    //   11213: wide
    //   11217: caload
    //   11218: istore 31
    //   11220: iload 6
    //   11222: iconst_5
    //   11223: irem
    //   11224: tableswitch	default:+32 -> 11256, 0:+4098->15322, 1:+4107->15331, 2:+4116->15340, 3:+4125->15349
    //   11257: lconst_1
    //   11258: wide
    //   11262: wide
    //   11266: iload 31
    //   11268: ixor
    //   11269: i2c
    //   11270: wide
    //   11274: wide
    //   11278: wide
    //   11282: wide
    //   11286: castore
    //   11287: iload 6
    //   11289: iconst_1
    //   11290: iadd
    //   11291: wide
    //   11295: wide
    //   11299: ifne +28 -> 11327
    //   11302: aload 5
    //   11304: wide
    //   11308: wide
    //   11312: wide
    //   11316: wide
    //   11320: wide
    //   11324: goto -115 -> 11209
    //   11327: wide
    //   11331: wide
    //   11335: aload 5
    //   11337: wide
    //   11341: wide
    //   11345: wide
    //   11349: if_icmpgt -176 -> 11173
    //   11352: new 34	java/lang/String
    //   11355: dup
    //   11356: wide
    //   11360: invokespecial 44	java/lang/String:<init>	([C)V
    //   11363: invokevirtual 48	java/lang/String:intern	()Ljava/lang/String;
    //   11366: wide
    //   11370: aload_1
    //   11371: wide
    //   11375: wide
    //   11379: aastore
    //   11380: bipush 54
    //   11382: wide
    //   11386: ldc 156
    //   11388: invokevirtual 40	java/lang/String:toCharArray	()[C
    //   11391: wide
    //   11395: wide
    //   11399: arraylength
    //   11400: wide
    //   11404: wide
    //   11408: iconst_1
    //   11409: if_icmpgt +4337 -> 15746
    //   11412: iconst_0
    //   11413: wide
    //   11417: wide
    //   11421: astore 5
    //   11423: wide
    //   11427: istore 6
    //   11429: wide
    //   11433: wide
    //   11437: wide
    //   11441: wide
    //   11445: wide
    //   11449: wide
    //   11453: wide
    //   11457: wide
    //   11461: caload
    //   11462: istore 31
    //   11464: iload 6
    //   11466: iconst_5
    //   11467: irem
    //   11468: tableswitch	default:+32 -> 11500, 0:+3890->15358, 1:+3899->15367, 2:+3908->15376, 3:+3917->15385
    //   11501: lconst_1
    //   11502: wide
    //   11506: wide
    //   11510: iload 31
    //   11512: ixor
    //   11513: i2c
    //   11514: wide
    //   11518: wide
    //   11522: wide
    //   11526: wide
    //   11530: castore
    //   11531: iload 6
    //   11533: iconst_1
    //   11534: iadd
    //   11535: wide
    //   11539: wide
    //   11543: ifne +28 -> 11571
    //   11546: aload 5
    //   11548: wide
    //   11552: wide
    //   11556: wide
    //   11560: wide
    //   11564: wide
    //   11568: goto -115 -> 11453
    //   11571: wide
    //   11575: wide
    //   11579: aload 5
    //   11581: wide
    //   11585: wide
    //   11589: wide
    //   11593: if_icmpgt -176 -> 11417
    //   11596: new 34	java/lang/String
    //   11599: dup
    //   11600: wide
    //   11604: invokespecial 44	java/lang/String:<init>	([C)V
    //   11607: invokevirtual 48	java/lang/String:intern	()Ljava/lang/String;
    //   11610: wide
    //   11614: aload_1
    //   11615: wide
    //   11619: wide
    //   11623: aastore
    //   11624: bipush 55
    //   11626: wide
    //   11630: ldc 158
    //   11632: invokevirtual 40	java/lang/String:toCharArray	()[C
    //   11635: wide
    //   11639: wide
    //   11643: arraylength
    //   11644: wide
    //   11648: wide
    //   11652: iconst_1
    //   11653: if_icmpgt +4085 -> 15738
    //   11656: iconst_0
    //   11657: wide
    //   11661: wide
    //   11665: astore 5
    //   11667: wide
    //   11671: istore 6
    //   11673: wide
    //   11677: wide
    //   11681: wide
    //   11685: wide
    //   11689: wide
    //   11693: wide
    //   11697: wide
    //   11701: wide
    //   11705: caload
    //   11706: istore 31
    //   11708: iload 6
    //   11710: iconst_5
    //   11711: irem
    //   11712: tableswitch	default:+32 -> 11744, 0:+3682->15394, 1:+3691->15403, 2:+3700->15412, 3:+3709->15421
    //   11745: lconst_1
    //   11746: wide
    //   11750: wide
    //   11754: iload 31
    //   11756: ixor
    //   11757: i2c
    //   11758: wide
    //   11762: wide
    //   11766: wide
    //   11770: wide
    //   11774: castore
    //   11775: iload 6
    //   11777: iconst_1
    //   11778: iadd
    //   11779: wide
    //   11783: wide
    //   11787: ifne +28 -> 11815
    //   11790: aload 5
    //   11792: wide
    //   11796: wide
    //   11800: wide
    //   11804: wide
    //   11808: wide
    //   11812: goto -115 -> 11697
    //   11815: wide
    //   11819: wide
    //   11823: aload 5
    //   11825: wide
    //   11829: wide
    //   11833: wide
    //   11837: if_icmpgt -176 -> 11661
    //   11840: new 34	java/lang/String
    //   11843: dup
    //   11844: wide
    //   11848: invokespecial 44	java/lang/String:<init>	([C)V
    //   11851: invokevirtual 48	java/lang/String:intern	()Ljava/lang/String;
    //   11854: wide
    //   11858: aload_1
    //   11859: wide
    //   11863: wide
    //   11867: aastore
    //   11868: bipush 56
    //   11870: wide
    //   11874: ldc 160
    //   11876: invokevirtual 40	java/lang/String:toCharArray	()[C
    //   11879: wide
    //   11883: wide
    //   11887: arraylength
    //   11888: wide
    //   11892: wide
    //   11896: iconst_1
    //   11897: if_icmpgt +3833 -> 15730
    //   11900: iconst_0
    //   11901: wide
    //   11905: wide
    //   11909: astore 5
    //   11911: wide
    //   11915: istore 6
    //   11917: wide
    //   11921: wide
    //   11925: wide
    //   11929: wide
    //   11933: wide
    //   11937: wide
    //   11941: wide
    //   11945: wide
    //   11949: caload
    //   11950: istore 31
    //   11952: iload 6
    //   11954: iconst_5
    //   11955: irem
    //   11956: tableswitch	default:+32 -> 11988, 0:+3474->15430, 1:+3483->15439, 2:+3492->15448, 3:+3501->15457
    //   11989: lconst_1
    //   11990: wide
    //   11994: wide
    //   11998: iload 31
    //   12000: ixor
    //   12001: i2c
    //   12002: wide
    //   12006: wide
    //   12010: wide
    //   12014: wide
    //   12018: castore
    //   12019: iload 6
    //   12021: iconst_1
    //   12022: iadd
    //   12023: wide
    //   12027: wide
    //   12031: ifne +28 -> 12059
    //   12034: aload 5
    //   12036: wide
    //   12040: wide
    //   12044: wide
    //   12048: wide
    //   12052: wide
    //   12056: goto -115 -> 11941
    //   12059: wide
    //   12063: wide
    //   12067: aload 5
    //   12069: wide
    //   12073: wide
    //   12077: wide
    //   12081: if_icmpgt -176 -> 11905
    //   12084: new 34	java/lang/String
    //   12087: dup
    //   12088: wide
    //   12092: invokespecial 44	java/lang/String:<init>	([C)V
    //   12095: invokevirtual 48	java/lang/String:intern	()Ljava/lang/String;
    //   12098: wide
    //   12102: aload_1
    //   12103: wide
    //   12107: wide
    //   12111: aastore
    //   12112: bipush 57
    //   12114: wide
    //   12118: ldc 162
    //   12120: invokevirtual 40	java/lang/String:toCharArray	()[C
    //   12123: wide
    //   12127: wide
    //   12131: arraylength
    //   12132: wide
    //   12136: wide
    //   12140: iconst_1
    //   12141: if_icmpgt +3581 -> 15722
    //   12144: iconst_0
    //   12145: wide
    //   12149: wide
    //   12153: astore 5
    //   12155: wide
    //   12159: istore 6
    //   12161: wide
    //   12165: wide
    //   12169: wide
    //   12173: wide
    //   12177: wide
    //   12181: wide
    //   12185: wide
    //   12189: wide
    //   12193: caload
    //   12194: istore 31
    //   12196: iload 6
    //   12198: iconst_5
    //   12199: irem
    //   12200: tableswitch	default:+32 -> 12232, 0:+3266->15466, 1:+3275->15475, 2:+3284->15484, 3:+3293->15493
    //   12233: lconst_1
    //   12234: wide
    //   12238: wide
    //   12242: iload 31
    //   12244: ixor
    //   12245: i2c
    //   12246: wide
    //   12250: wide
    //   12254: wide
    //   12258: wide
    //   12262: castore
    //   12263: iload 6
    //   12265: iconst_1
    //   12266: iadd
    //   12267: wide
    //   12271: wide
    //   12275: ifne +28 -> 12303
    //   12278: aload 5
    //   12280: wide
    //   12284: wide
    //   12288: wide
    //   12292: wide
    //   12296: wide
    //   12300: goto -115 -> 12185
    //   12303: wide
    //   12307: wide
    //   12311: aload 5
    //   12313: wide
    //   12317: wide
    //   12321: wide
    //   12325: if_icmpgt -176 -> 12149
    //   12328: new 34	java/lang/String
    //   12331: dup
    //   12332: wide
    //   12336: invokespecial 44	java/lang/String:<init>	([C)V
    //   12339: invokevirtual 48	java/lang/String:intern	()Ljava/lang/String;
    //   12342: wide
    //   12346: aload_1
    //   12347: wide
    //   12351: wide
    //   12355: aastore
    //   12356: bipush 58
    //   12358: wide
    //   12362: ldc 164
    //   12364: invokevirtual 40	java/lang/String:toCharArray	()[C
    //   12367: wide
    //   12371: wide
    //   12375: arraylength
    //   12376: wide
    //   12380: wide
    //   12384: iconst_1
    //   12385: if_icmpgt +3329 -> 15714
    //   12388: iconst_0
    //   12389: wide
    //   12393: wide
    //   12397: astore 5
    //   12399: wide
    //   12403: istore 6
    //   12405: wide
    //   12409: wide
    //   12413: wide
    //   12417: wide
    //   12421: wide
    //   12425: wide
    //   12429: wide
    //   12433: wide
    //   12437: caload
    //   12438: istore 31
    //   12440: iload 6
    //   12442: iconst_5
    //   12443: irem
    //   12444: tableswitch	default:+32 -> 12476, 0:+3058->15502, 1:+3067->15511, 2:+3076->15520, 3:+3085->15529
    //   12477: lconst_1
    //   12478: wide
    //   12482: wide
    //   12486: iload 31
    //   12488: ixor
    //   12489: i2c
    //   12490: wide
    //   12494: wide
    //   12498: wide
    //   12502: wide
    //   12506: castore
    //   12507: iload 6
    //   12509: iconst_1
    //   12510: iadd
    //   12511: wide
    //   12515: wide
    //   12519: ifne +28 -> 12547
    //   12522: aload 5
    //   12524: wide
    //   12528: wide
    //   12532: wide
    //   12536: wide
    //   12540: wide
    //   12544: goto -115 -> 12429
    //   12547: wide
    //   12551: wide
    //   12555: aload 5
    //   12557: wide
    //   12561: wide
    //   12565: wide
    //   12569: if_icmpgt -176 -> 12393
    //   12572: new 34	java/lang/String
    //   12575: dup
    //   12576: wide
    //   12580: invokespecial 44	java/lang/String:<init>	([C)V
    //   12583: invokevirtual 48	java/lang/String:intern	()Ljava/lang/String;
    //   12586: wide
    //   12590: aload_1
    //   12591: wide
    //   12595: wide
    //   12599: aastore
    //   12600: bipush 59
    //   12602: wide
    //   12606: ldc 166
    //   12608: invokevirtual 40	java/lang/String:toCharArray	()[C
    //   12611: wide
    //   12615: wide
    //   12619: arraylength
    //   12620: wide
    //   12624: wide
    //   12628: iconst_1
    //   12629: if_icmpgt +3077 -> 15706
    //   12632: iconst_0
    //   12633: wide
    //   12637: wide
    //   12641: astore 5
    //   12643: wide
    //   12647: istore 6
    //   12649: wide
    //   12653: wide
    //   12657: wide
    //   12661: wide
    //   12665: wide
    //   12669: wide
    //   12673: wide
    //   12677: wide
    //   12681: caload
    //   12682: istore 31
    //   12684: iload 6
    //   12686: iconst_5
    //   12687: irem
    //   12688: tableswitch	default:+32 -> 12720, 0:+2850->15538, 1:+2859->15547, 2:+2868->15556, 3:+2877->15565
    //   12721: lconst_1
    //   12722: wide
    //   12726: wide
    //   12730: iload 31
    //   12732: ixor
    //   12733: i2c
    //   12734: wide
    //   12738: wide
    //   12742: wide
    //   12746: wide
    //   12750: castore
    //   12751: iload 6
    //   12753: iconst_1
    //   12754: iadd
    //   12755: wide
    //   12759: wide
    //   12763: ifne +28 -> 12791
    //   12766: aload 5
    //   12768: wide
    //   12772: wide
    //   12776: wide
    //   12780: wide
    //   12784: wide
    //   12788: goto -115 -> 12673
    //   12791: wide
    //   12795: wide
    //   12799: aload 5
    //   12801: wide
    //   12805: wide
    //   12809: wide
    //   12813: if_icmpgt -176 -> 12637
    //   12816: new 34	java/lang/String
    //   12819: dup
    //   12820: wide
    //   12824: invokespecial 44	java/lang/String:<init>	([C)V
    //   12827: invokevirtual 48	java/lang/String:intern	()Ljava/lang/String;
    //   12830: wide
    //   12834: aload_1
    //   12835: wide
    //   12839: wide
    //   12843: aastore
    //   12844: bipush 60
    //   12846: wide
    //   12850: ldc 168
    //   12852: invokevirtual 40	java/lang/String:toCharArray	()[C
    //   12855: wide
    //   12859: wide
    //   12863: arraylength
    //   12864: wide
    //   12868: wide
    //   12872: iconst_1
    //   12873: if_icmpgt +2825 -> 15698
    //   12876: iconst_0
    //   12877: wide
    //   12881: wide
    //   12885: astore 5
    //   12887: wide
    //   12891: istore 6
    //   12893: wide
    //   12897: wide
    //   12901: wide
    //   12905: wide
    //   12909: wide
    //   12913: wide
    //   12917: wide
    //   12921: wide
    //   12925: caload
    //   12926: istore 31
    //   12928: iload 6
    //   12930: iconst_5
    //   12931: irem
    //   12932: tableswitch	default:+32 -> 12964, 0:+2642->15574, 1:+2651->15583, 2:+2660->15592, 3:+2669->15601
    //   12965: lconst_1
    //   12966: wide
    //   12970: wide
    //   12974: iload 31
    //   12976: ixor
    //   12977: i2c
    //   12978: wide
    //   12982: wide
    //   12986: wide
    //   12990: wide
    //   12994: castore
    //   12995: iload 6
    //   12997: iconst_1
    //   12998: iadd
    //   12999: wide
    //   13003: wide
    //   13007: ifne +28 -> 13035
    //   13010: aload 5
    //   13012: wide
    //   13016: wide
    //   13020: wide
    //   13024: wide
    //   13028: wide
    //   13032: goto -115 -> 12917
    //   13035: wide
    //   13039: wide
    //   13043: aload 5
    //   13045: wide
    //   13049: wide
    //   13053: wide
    //   13057: if_icmpgt -176 -> 12881
    //   13060: new 34	java/lang/String
    //   13063: dup
    //   13064: wide
    //   13068: invokespecial 44	java/lang/String:<init>	([C)V
    //   13071: invokevirtual 48	java/lang/String:intern	()Ljava/lang/String;
    //   13074: wide
    //   13078: aload_1
    //   13079: wide
    //   13083: wide
    //   13087: aastore
    //   13088: bipush 61
    //   13090: wide
    //   13094: ldc 170
    //   13096: invokevirtual 40	java/lang/String:toCharArray	()[C
    //   13099: wide
    //   13103: wide
    //   13107: arraylength
    //   13108: wide
    //   13112: wide
    //   13116: iconst_1
    //   13117: if_icmpgt +2573 -> 15690
    //   13120: iconst_0
    //   13121: wide
    //   13125: wide
    //   13129: astore 5
    //   13131: wide
    //   13135: istore 6
    //   13137: wide
    //   13141: wide
    //   13145: wide
    //   13149: wide
    //   13153: wide
    //   13157: wide
    //   13161: wide
    //   13165: wide
    //   13169: caload
    //   13170: istore 31
    //   13172: iload 6
    //   13174: iconst_5
    //   13175: irem
    //   13176: tableswitch	default:+32 -> 13208, 0:+2434->15610, 1:+2443->15619, 2:+2452->15628, 3:+2461->15637
    //   13209: lconst_1
    //   13210: wide
    //   13214: wide
    //   13218: iload 31
    //   13220: ixor
    //   13221: i2c
    //   13222: wide
    //   13226: wide
    //   13230: wide
    //   13234: wide
    //   13238: castore
    //   13239: iload 6
    //   13241: iconst_1
    //   13242: iadd
    //   13243: wide
    //   13247: wide
    //   13251: ifne +28 -> 13279
    //   13254: aload 5
    //   13256: wide
    //   13260: wide
    //   13264: wide
    //   13268: wide
    //   13272: wide
    //   13276: goto -115 -> 13161
    //   13279: wide
    //   13283: wide
    //   13287: aload 5
    //   13289: wide
    //   13293: wide
    //   13297: wide
    //   13301: if_icmpgt -176 -> 13125
    //   13304: new 34	java/lang/String
    //   13307: dup
    //   13308: wide
    //   13312: invokespecial 44	java/lang/String:<init>	([C)V
    //   13315: invokevirtual 48	java/lang/String:intern	()Ljava/lang/String;
    //   13318: wide
    //   13322: aload_1
    //   13323: wide
    //   13327: wide
    //   13331: aastore
    //   13332: bipush 62
    //   13334: wide
    //   13338: ldc 172
    //   13340: invokevirtual 40	java/lang/String:toCharArray	()[C
    //   13343: wide
    //   13347: wide
    //   13351: arraylength
    //   13352: wide
    //   13356: wide
    //   13360: iconst_1
    //   13361: if_icmpgt +2321 -> 15682
    //   13364: iconst_0
    //   13365: wide
    //   13369: wide
    //   13373: astore 5
    //   13375: wide
    //   13379: istore 6
    //   13381: wide
    //   13385: wide
    //   13389: wide
    //   13393: wide
    //   13397: wide
    //   13401: wide
    //   13405: wide
    //   13409: wide
    //   13413: caload
    //   13414: istore 31
    //   13416: iload 6
    //   13418: iconst_5
    //   13419: irem
    //   13420: tableswitch	default:+32 -> 13452, 0:+2226->15646, 1:+2235->15655, 2:+2244->15664, 3:+2253->15673
    //   13453: lconst_1
    //   13454: wide
    //   13458: wide
    //   13462: iload 31
    //   13464: ixor
    //   13465: i2c
    //   13466: wide
    //   13470: wide
    //   13474: wide
    //   13478: wide
    //   13482: castore
    //   13483: iload 6
    //   13485: iconst_1
    //   13486: iadd
    //   13487: wide
    //   13491: wide
    //   13495: ifne +28 -> 13523
    //   13498: aload 5
    //   13500: wide
    //   13504: wide
    //   13508: wide
    //   13512: wide
    //   13516: wide
    //   13520: goto -115 -> 13405
    //   13523: wide
    //   13527: wide
    //   13531: aload 5
    //   13533: wide
    //   13537: wide
    //   13541: wide
    //   13545: if_icmpgt -176 -> 13369
    //   13548: new 34	java/lang/String
    //   13551: dup
    //   13552: wide
    //   13556: invokespecial 44	java/lang/String:<init>	([C)V
    //   13559: invokevirtual 48	java/lang/String:intern	()Ljava/lang/String;
    //   13562: wide
    //   13566: aload_1
    //   13567: wide
    //   13571: wide
    //   13575: aastore
    //   13576: aload_1
    //   13577: putstatic 174	com/skyhookwireless/wps/_sdkf:z	[Ljava/lang/String;
    //   13580: ldc 2
    //   13582: invokevirtual 180	java/lang/Class:desiredAssertionStatus	()Z
    //   13585: ifne +8 -> 13593
    //   13588: iload_0
    //   13589: putstatic 182	com/skyhookwireless/wps/_sdkf:_sdkl	Z
    //   13592: return
    //   13593: iconst_0
    //   13594: istore_0
    //   13595: goto -7 -> 13588
    //   13598: bipush 63
    //   13600: istore 11
    //   13602: goto -13514 -> 88
    //   13605: bipush 91
    //   13607: istore 11
    //   13609: goto -13521 -> 88
    //   13612: bipush 41
    //   13614: istore 11
    //   13616: goto -13528 -> 88
    //   13619: bipush 83
    //   13621: istore 11
    //   13623: goto -13535 -> 88
    //   13626: bipush 63
    //   13628: istore 20
    //   13630: goto -13386 -> 244
    //   13633: bipush 91
    //   13635: istore 20
    //   13637: goto -13393 -> 244
    //   13640: bipush 41
    //   13642: istore 20
    //   13644: goto -13400 -> 244
    //   13647: bipush 83
    //   13649: istore 20
    //   13651: goto -13407 -> 244
    //   13654: bipush 63
    //   13656: istore 32
    //   13658: goto -13250 -> 408
    //   13661: bipush 91
    //   13663: istore 32
    //   13665: goto -13257 -> 408
    //   13668: bipush 41
    //   13670: istore 32
    //   13672: goto -13264 -> 408
    //   13675: bipush 83
    //   13677: istore 32
    //   13679: goto -13271 -> 408
    //   13682: bipush 63
    //   13684: istore 43
    //   13686: goto -13114 -> 572
    //   13689: bipush 91
    //   13691: istore 43
    //   13693: goto -13121 -> 572
    //   13696: bipush 41
    //   13698: istore 43
    //   13700: goto -13128 -> 572
    //   13703: bipush 83
    //   13705: istore 43
    //   13707: goto -13135 -> 572
    //   13710: bipush 63
    //   13712: istore 54
    //   13714: goto -12978 -> 736
    //   13717: bipush 91
    //   13719: istore 54
    //   13721: goto -12985 -> 736
    //   13724: bipush 41
    //   13726: istore 54
    //   13728: goto -12992 -> 736
    //   13731: bipush 83
    //   13733: istore 54
    //   13735: goto -12999 -> 736
    //   13738: bipush 63
    //   13740: istore 65
    //   13742: goto -12842 -> 900
    //   13745: bipush 91
    //   13747: istore 65
    //   13749: goto -12849 -> 900
    //   13752: bipush 41
    //   13754: istore 65
    //   13756: goto -12856 -> 900
    //   13759: bipush 83
    //   13761: istore 65
    //   13763: goto -12863 -> 900
    //   13766: bipush 63
    //   13768: istore 76
    //   13770: goto -12702 -> 1068
    //   13773: bipush 91
    //   13775: istore 76
    //   13777: goto -12709 -> 1068
    //   13780: bipush 41
    //   13782: istore 76
    //   13784: goto -12716 -> 1068
    //   13787: bipush 83
    //   13789: istore 76
    //   13791: goto -12723 -> 1068
    //   13794: bipush 63
    //   13796: istore 87
    //   13798: goto -12562 -> 1236
    //   13801: bipush 91
    //   13803: istore 87
    //   13805: goto -12569 -> 1236
    //   13808: bipush 41
    //   13810: istore 87
    //   13812: goto -12576 -> 1236
    //   13815: bipush 83
    //   13817: istore 87
    //   13819: goto -12583 -> 1236
    //   13822: bipush 63
    //   13824: istore 98
    //   13826: goto -12422 -> 1404
    //   13829: bipush 91
    //   13831: istore 98
    //   13833: goto -12429 -> 1404
    //   13836: bipush 41
    //   13838: istore 98
    //   13840: goto -12436 -> 1404
    //   13843: bipush 83
    //   13845: istore 98
    //   13847: goto -12443 -> 1404
    //   13850: bipush 63
    //   13852: istore 109
    //   13854: goto -12282 -> 1572
    //   13857: bipush 91
    //   13859: istore 109
    //   13861: goto -12289 -> 1572
    //   13864: bipush 41
    //   13866: istore 109
    //   13868: goto -12296 -> 1572
    //   13871: bipush 83
    //   13873: istore 109
    //   13875: goto -12303 -> 1572
    //   13878: bipush 63
    //   13880: istore 119
    //   13882: goto -12146 -> 1736
    //   13885: bipush 91
    //   13887: istore 119
    //   13889: goto -12153 -> 1736
    //   13892: bipush 41
    //   13894: istore 119
    //   13896: goto -12160 -> 1736
    //   13899: bipush 83
    //   13901: istore 119
    //   13903: goto -12167 -> 1736
    //   13906: bipush 63
    //   13908: istore 130
    //   13910: goto -12006 -> 1904
    //   13913: bipush 91
    //   13915: istore 130
    //   13917: goto -12013 -> 1904
    //   13920: bipush 41
    //   13922: istore 130
    //   13924: goto -12020 -> 1904
    //   13927: bipush 83
    //   13929: istore 130
    //   13931: goto -12027 -> 1904
    //   13934: bipush 63
    //   13936: istore 141
    //   13938: goto -11866 -> 2072
    //   13941: bipush 91
    //   13943: istore 141
    //   13945: goto -11873 -> 2072
    //   13948: bipush 41
    //   13950: istore 141
    //   13952: goto -11880 -> 2072
    //   13955: bipush 83
    //   13957: istore 141
    //   13959: goto -11887 -> 2072
    //   13962: bipush 63
    //   13964: istore 152
    //   13966: goto -11726 -> 2240
    //   13969: bipush 91
    //   13971: istore 152
    //   13973: goto -11733 -> 2240
    //   13976: bipush 41
    //   13978: istore 152
    //   13980: goto -11740 -> 2240
    //   13983: bipush 83
    //   13985: istore 152
    //   13987: goto -11747 -> 2240
    //   13990: bipush 63
    //   13992: istore 163
    //   13994: goto -11586 -> 2408
    //   13997: bipush 91
    //   13999: istore 163
    //   14001: goto -11593 -> 2408
    //   14004: bipush 41
    //   14006: istore 163
    //   14008: goto -11600 -> 2408
    //   14011: bipush 83
    //   14013: istore 163
    //   14015: goto -11607 -> 2408
    //   14018: bipush 63
    //   14020: istore 174
    //   14022: goto -11446 -> 2576
    //   14025: bipush 91
    //   14027: istore 174
    //   14029: goto -11453 -> 2576
    //   14032: bipush 41
    //   14034: istore 174
    //   14036: goto -11460 -> 2576
    //   14039: bipush 83
    //   14041: istore 174
    //   14043: goto -11467 -> 2576
    //   14046: bipush 63
    //   14048: istore 185
    //   14050: goto -11306 -> 2744
    //   14053: bipush 91
    //   14055: istore 185
    //   14057: goto -11313 -> 2744
    //   14060: bipush 41
    //   14062: istore 185
    //   14064: goto -11320 -> 2744
    //   14067: bipush 83
    //   14069: istore 185
    //   14071: goto -11327 -> 2744
    //   14074: bipush 63
    //   14076: istore 196
    //   14078: goto -11166 -> 2912
    //   14081: bipush 91
    //   14083: istore 196
    //   14085: goto -11173 -> 2912
    //   14088: bipush 41
    //   14090: istore 196
    //   14092: goto -11180 -> 2912
    //   14095: bipush 83
    //   14097: istore 196
    //   14099: goto -11187 -> 2912
    //   14102: bipush 63
    //   14104: istore 207
    //   14106: goto -11026 -> 3080
    //   14109: bipush 91
    //   14111: istore 207
    //   14113: goto -11033 -> 3080
    //   14116: bipush 41
    //   14118: istore 207
    //   14120: goto -11040 -> 3080
    //   14123: bipush 83
    //   14125: istore 207
    //   14127: goto -11047 -> 3080
    //   14130: bipush 63
    //   14132: istore 218
    //   14134: goto -10886 -> 3248
    //   14137: bipush 91
    //   14139: istore 218
    //   14141: goto -10893 -> 3248
    //   14144: bipush 41
    //   14146: istore 218
    //   14148: goto -10900 -> 3248
    //   14151: bipush 83
    //   14153: istore 218
    //   14155: goto -10907 -> 3248
    //   14158: bipush 63
    //   14160: istore 229
    //   14162: goto -10746 -> 3416
    //   14165: bipush 91
    //   14167: istore 229
    //   14169: goto -10753 -> 3416
    //   14172: bipush 41
    //   14174: istore 229
    //   14176: goto -10760 -> 3416
    //   14179: bipush 83
    //   14181: istore 229
    //   14183: goto -10767 -> 3416
    //   14186: bipush 63
    //   14188: istore 240
    //   14190: goto -10606 -> 3584
    //   14193: bipush 91
    //   14195: istore 240
    //   14197: goto -10613 -> 3584
    //   14200: bipush 41
    //   14202: istore 240
    //   14204: goto -10620 -> 3584
    //   14207: bipush 83
    //   14209: istore 240
    //   14211: goto -10627 -> 3584
    //   14214: bipush 63
    //   14216: istore 251
    //   14218: goto -10466 -> 3752
    //   14221: bipush 91
    //   14223: istore 251
    //   14225: goto -10473 -> 3752
    //   14228: bipush 41
    //   14230: istore 251
    //   14232: goto -10480 -> 3752
    //   14235: bipush 83
    //   14237: istore 251
    //   14239: goto -10487 -> 3752
    //   14242: bipush 63
    //   14244: wide
    //   14248: goto -10298 -> 3950
    //   14251: bipush 91
    //   14253: wide
    //   14257: goto -10307 -> 3950
    //   14260: bipush 41
    //   14262: wide
    //   14266: goto -10316 -> 3950
    //   14269: bipush 83
    //   14271: wide
    //   14275: goto -10325 -> 3950
    //   14278: bipush 63
    //   14280: wide
    //   14284: goto -10094 -> 4190
    //   14287: bipush 91
    //   14289: wide
    //   14293: goto -10103 -> 4190
    //   14296: bipush 41
    //   14298: wide
    //   14302: goto -10112 -> 4190
    //   14305: bipush 83
    //   14307: wide
    //   14311: goto -10121 -> 4190
    //   14314: bipush 63
    //   14316: wide
    //   14320: goto -9886 -> 4434
    //   14323: bipush 91
    //   14325: wide
    //   14329: goto -9895 -> 4434
    //   14332: bipush 41
    //   14334: wide
    //   14338: goto -9904 -> 4434
    //   14341: bipush 83
    //   14343: wide
    //   14347: goto -9913 -> 4434
    //   14350: bipush 63
    //   14352: wide
    //   14356: goto -9678 -> 4678
    //   14359: bipush 91
    //   14361: wide
    //   14365: goto -9687 -> 4678
    //   14368: bipush 41
    //   14370: wide
    //   14374: goto -9696 -> 4678
    //   14377: bipush 83
    //   14379: wide
    //   14383: goto -9705 -> 4678
    //   14386: bipush 63
    //   14388: wide
    //   14392: goto -9470 -> 4922
    //   14395: bipush 91
    //   14397: wide
    //   14401: goto -9479 -> 4922
    //   14404: bipush 41
    //   14406: wide
    //   14410: goto -9488 -> 4922
    //   14413: bipush 83
    //   14415: wide
    //   14419: goto -9497 -> 4922
    //   14422: bipush 63
    //   14424: wide
    //   14428: goto -9262 -> 5166
    //   14431: bipush 91
    //   14433: wide
    //   14437: goto -9271 -> 5166
    //   14440: bipush 41
    //   14442: wide
    //   14446: goto -9280 -> 5166
    //   14449: bipush 83
    //   14451: wide
    //   14455: goto -9289 -> 5166
    //   14458: bipush 63
    //   14460: wide
    //   14464: goto -9054 -> 5410
    //   14467: bipush 91
    //   14469: wide
    //   14473: goto -9063 -> 5410
    //   14476: bipush 41
    //   14478: wide
    //   14482: goto -9072 -> 5410
    //   14485: bipush 83
    //   14487: wide
    //   14491: goto -9081 -> 5410
    //   14494: bipush 63
    //   14496: wide
    //   14500: goto -8846 -> 5654
    //   14503: bipush 91
    //   14505: wide
    //   14509: goto -8855 -> 5654
    //   14512: bipush 41
    //   14514: wide
    //   14518: goto -8864 -> 5654
    //   14521: bipush 83
    //   14523: wide
    //   14527: goto -8873 -> 5654
    //   14530: bipush 63
    //   14532: wide
    //   14536: goto -8638 -> 5898
    //   14539: bipush 91
    //   14541: wide
    //   14545: goto -8647 -> 5898
    //   14548: bipush 41
    //   14550: wide
    //   14554: goto -8656 -> 5898
    //   14557: bipush 83
    //   14559: wide
    //   14563: goto -8665 -> 5898
    //   14566: bipush 63
    //   14568: wide
    //   14572: goto -8430 -> 6142
    //   14575: bipush 91
    //   14577: wide
    //   14581: goto -8439 -> 6142
    //   14584: bipush 41
    //   14586: wide
    //   14590: goto -8448 -> 6142
    //   14593: bipush 83
    //   14595: wide
    //   14599: goto -8457 -> 6142
    //   14602: bipush 63
    //   14604: wide
    //   14608: goto -8222 -> 6386
    //   14611: bipush 91
    //   14613: wide
    //   14617: goto -8231 -> 6386
    //   14620: bipush 41
    //   14622: wide
    //   14626: goto -8240 -> 6386
    //   14629: bipush 83
    //   14631: wide
    //   14635: goto -8249 -> 6386
    //   14638: bipush 63
    //   14640: wide
    //   14644: goto -8014 -> 6630
    //   14647: bipush 91
    //   14649: wide
    //   14653: goto -8023 -> 6630
    //   14656: bipush 41
    //   14658: wide
    //   14662: goto -8032 -> 6630
    //   14665: bipush 83
    //   14667: wide
    //   14671: goto -8041 -> 6630
    //   14674: bipush 63
    //   14676: wide
    //   14680: goto -7806 -> 6874
    //   14683: bipush 91
    //   14685: wide
    //   14689: goto -7815 -> 6874
    //   14692: bipush 41
    //   14694: wide
    //   14698: goto -7824 -> 6874
    //   14701: bipush 83
    //   14703: wide
    //   14707: goto -7833 -> 6874
    //   14710: bipush 63
    //   14712: wide
    //   14716: goto -7598 -> 7118
    //   14719: bipush 91
    //   14721: wide
    //   14725: goto -7607 -> 7118
    //   14728: bipush 41
    //   14730: wide
    //   14734: goto -7616 -> 7118
    //   14737: bipush 83
    //   14739: wide
    //   14743: goto -7625 -> 7118
    //   14746: bipush 63
    //   14748: wide
    //   14752: goto -7390 -> 7362
    //   14755: bipush 91
    //   14757: wide
    //   14761: goto -7399 -> 7362
    //   14764: bipush 41
    //   14766: wide
    //   14770: goto -7408 -> 7362
    //   14773: bipush 83
    //   14775: wide
    //   14779: goto -7417 -> 7362
    //   14782: bipush 63
    //   14784: wide
    //   14788: goto -7182 -> 7606
    //   14791: bipush 91
    //   14793: wide
    //   14797: goto -7191 -> 7606
    //   14800: bipush 41
    //   14802: wide
    //   14806: goto -7200 -> 7606
    //   14809: bipush 83
    //   14811: wide
    //   14815: goto -7209 -> 7606
    //   14818: bipush 63
    //   14820: wide
    //   14824: goto -6974 -> 7850
    //   14827: bipush 91
    //   14829: wide
    //   14833: goto -6983 -> 7850
    //   14836: bipush 41
    //   14838: wide
    //   14842: goto -6992 -> 7850
    //   14845: bipush 83
    //   14847: wide
    //   14851: goto -7001 -> 7850
    //   14854: bipush 63
    //   14856: wide
    //   14860: goto -6766 -> 8094
    //   14863: bipush 91
    //   14865: wide
    //   14869: goto -6775 -> 8094
    //   14872: bipush 41
    //   14874: wide
    //   14878: goto -6784 -> 8094
    //   14881: bipush 83
    //   14883: wide
    //   14887: goto -6793 -> 8094
    //   14890: bipush 63
    //   14892: wide
    //   14896: goto -6562 -> 8334
    //   14899: bipush 91
    //   14901: wide
    //   14905: goto -6571 -> 8334
    //   14908: bipush 41
    //   14910: wide
    //   14914: goto -6580 -> 8334
    //   14917: bipush 83
    //   14919: wide
    //   14923: goto -6589 -> 8334
    //   14926: bipush 63
    //   14928: wide
    //   14932: goto -6354 -> 8578
    //   14935: bipush 91
    //   14937: wide
    //   14941: goto -6363 -> 8578
    //   14944: bipush 41
    //   14946: wide
    //   14950: goto -6372 -> 8578
    //   14953: bipush 83
    //   14955: wide
    //   14959: goto -6381 -> 8578
    //   14962: bipush 63
    //   14964: wide
    //   14968: goto -6146 -> 8822
    //   14971: bipush 91
    //   14973: wide
    //   14977: goto -6155 -> 8822
    //   14980: bipush 41
    //   14982: wide
    //   14986: goto -6164 -> 8822
    //   14989: bipush 83
    //   14991: wide
    //   14995: goto -6173 -> 8822
    //   14998: bipush 63
    //   15000: wide
    //   15004: goto -5938 -> 9066
    //   15007: bipush 91
    //   15009: wide
    //   15013: goto -5947 -> 9066
    //   15016: bipush 41
    //   15018: wide
    //   15022: goto -5956 -> 9066
    //   15025: bipush 83
    //   15027: wide
    //   15031: goto -5965 -> 9066
    //   15034: bipush 63
    //   15036: wide
    //   15040: goto -5730 -> 9310
    //   15043: bipush 91
    //   15045: wide
    //   15049: goto -5739 -> 9310
    //   15052: bipush 41
    //   15054: wide
    //   15058: goto -5748 -> 9310
    //   15061: bipush 83
    //   15063: wide
    //   15067: goto -5757 -> 9310
    //   15070: bipush 63
    //   15072: wide
    //   15076: goto -5522 -> 9554
    //   15079: bipush 91
    //   15081: wide
    //   15085: goto -5531 -> 9554
    //   15088: bipush 41
    //   15090: wide
    //   15094: goto -5540 -> 9554
    //   15097: bipush 83
    //   15099: wide
    //   15103: goto -5549 -> 9554
    //   15106: bipush 63
    //   15108: wide
    //   15112: goto -5314 -> 9798
    //   15115: bipush 91
    //   15117: wide
    //   15121: goto -5323 -> 9798
    //   15124: bipush 41
    //   15126: wide
    //   15130: goto -5332 -> 9798
    //   15133: bipush 83
    //   15135: wide
    //   15139: goto -5341 -> 9798
    //   15142: bipush 63
    //   15144: wide
    //   15148: goto -5106 -> 10042
    //   15151: bipush 91
    //   15153: wide
    //   15157: goto -5115 -> 10042
    //   15160: bipush 41
    //   15162: wide
    //   15166: goto -5124 -> 10042
    //   15169: bipush 83
    //   15171: wide
    //   15175: goto -5133 -> 10042
    //   15178: bipush 63
    //   15180: wide
    //   15184: goto -4898 -> 10286
    //   15187: bipush 91
    //   15189: wide
    //   15193: goto -4907 -> 10286
    //   15196: bipush 41
    //   15198: wide
    //   15202: goto -4916 -> 10286
    //   15205: bipush 83
    //   15207: wide
    //   15211: goto -4925 -> 10286
    //   15214: bipush 63
    //   15216: wide
    //   15220: goto -4690 -> 10530
    //   15223: bipush 91
    //   15225: wide
    //   15229: goto -4699 -> 10530
    //   15232: bipush 41
    //   15234: wide
    //   15238: goto -4708 -> 10530
    //   15241: bipush 83
    //   15243: wide
    //   15247: goto -4717 -> 10530
    //   15250: bipush 63
    //   15252: wide
    //   15256: goto -4482 -> 10774
    //   15259: bipush 91
    //   15261: wide
    //   15265: goto -4491 -> 10774
    //   15268: bipush 41
    //   15270: wide
    //   15274: goto -4500 -> 10774
    //   15277: bipush 83
    //   15279: wide
    //   15283: goto -4509 -> 10774
    //   15286: bipush 63
    //   15288: wide
    //   15292: goto -4274 -> 11018
    //   15295: bipush 91
    //   15297: wide
    //   15301: goto -4283 -> 11018
    //   15304: bipush 41
    //   15306: wide
    //   15310: goto -4292 -> 11018
    //   15313: bipush 83
    //   15315: wide
    //   15319: goto -4301 -> 11018
    //   15322: bipush 63
    //   15324: wide
    //   15328: goto -4066 -> 11262
    //   15331: bipush 91
    //   15333: wide
    //   15337: goto -4075 -> 11262
    //   15340: bipush 41
    //   15342: wide
    //   15346: goto -4084 -> 11262
    //   15349: bipush 83
    //   15351: wide
    //   15355: goto -4093 -> 11262
    //   15358: bipush 63
    //   15360: wide
    //   15364: goto -3858 -> 11506
    //   15367: bipush 91
    //   15369: wide
    //   15373: goto -3867 -> 11506
    //   15376: bipush 41
    //   15378: wide
    //   15382: goto -3876 -> 11506
    //   15385: bipush 83
    //   15387: wide
    //   15391: goto -3885 -> 11506
    //   15394: bipush 63
    //   15396: wide
    //   15400: goto -3650 -> 11750
    //   15403: bipush 91
    //   15405: wide
    //   15409: goto -3659 -> 11750
    //   15412: bipush 41
    //   15414: wide
    //   15418: goto -3668 -> 11750
    //   15421: bipush 83
    //   15423: wide
    //   15427: goto -3677 -> 11750
    //   15430: bipush 63
    //   15432: wide
    //   15436: goto -3442 -> 11994
    //   15439: bipush 91
    //   15441: wide
    //   15445: goto -3451 -> 11994
    //   15448: bipush 41
    //   15450: wide
    //   15454: goto -3460 -> 11994
    //   15457: bipush 83
    //   15459: wide
    //   15463: goto -3469 -> 11994
    //   15466: bipush 63
    //   15468: wide
    //   15472: goto -3234 -> 12238
    //   15475: bipush 91
    //   15477: wide
    //   15481: goto -3243 -> 12238
    //   15484: bipush 41
    //   15486: wide
    //   15490: goto -3252 -> 12238
    //   15493: bipush 83
    //   15495: wide
    //   15499: goto -3261 -> 12238
    //   15502: bipush 63
    //   15504: wide
    //   15508: goto -3026 -> 12482
    //   15511: bipush 91
    //   15513: wide
    //   15517: goto -3035 -> 12482
    //   15520: bipush 41
    //   15522: wide
    //   15526: goto -3044 -> 12482
    //   15529: bipush 83
    //   15531: wide
    //   15535: goto -3053 -> 12482
    //   15538: bipush 63
    //   15540: wide
    //   15544: goto -2818 -> 12726
    //   15547: bipush 91
    //   15549: wide
    //   15553: goto -2827 -> 12726
    //   15556: bipush 41
    //   15558: wide
    //   15562: goto -2836 -> 12726
    //   15565: bipush 83
    //   15567: wide
    //   15571: goto -2845 -> 12726
    //   15574: bipush 63
    //   15576: wide
    //   15580: goto -2610 -> 12970
    //   15583: bipush 91
    //   15585: wide
    //   15589: goto -2619 -> 12970
    //   15592: bipush 41
    //   15594: wide
    //   15598: goto -2628 -> 12970
    //   15601: bipush 83
    //   15603: wide
    //   15607: goto -2637 -> 12970
    //   15610: bipush 63
    //   15612: wide
    //   15616: goto -2402 -> 13214
    //   15619: bipush 91
    //   15621: wide
    //   15625: goto -2411 -> 13214
    //   15628: bipush 41
    //   15630: wide
    //   15634: goto -2420 -> 13214
    //   15637: bipush 83
    //   15639: wide
    //   15643: goto -2429 -> 13214
    //   15646: bipush 63
    //   15648: wide
    //   15652: goto -2194 -> 13458
    //   15655: bipush 91
    //   15657: wide
    //   15661: goto -2203 -> 13458
    //   15664: bipush 41
    //   15666: wide
    //   15670: goto -2212 -> 13458
    //   15673: bipush 83
    //   15675: wide
    //   15679: goto -2221 -> 13458
    //   15682: iconst_0
    //   15683: wide
    //   15687: goto -2150 -> 13537
    //   15690: iconst_0
    //   15691: wide
    //   15695: goto -2402 -> 13293
    //   15698: iconst_0
    //   15699: wide
    //   15703: goto -2654 -> 13049
    //   15706: iconst_0
    //   15707: wide
    //   15711: goto -2906 -> 12805
    //   15714: iconst_0
    //   15715: wide
    //   15719: goto -3158 -> 12561
    //   15722: iconst_0
    //   15723: wide
    //   15727: goto -3410 -> 12317
    //   15730: iconst_0
    //   15731: wide
    //   15735: goto -3662 -> 12073
    //   15738: iconst_0
    //   15739: wide
    //   15743: goto -3914 -> 11829
    //   15746: iconst_0
    //   15747: wide
    //   15751: goto -4166 -> 11585
    //   15754: iconst_0
    //   15755: wide
    //   15759: goto -4418 -> 11341
    //   15762: iconst_0
    //   15763: wide
    //   15767: goto -4670 -> 11097
    //   15770: iconst_0
    //   15771: wide
    //   15775: goto -4922 -> 10853
    //   15778: iconst_0
    //   15779: wide
    //   15783: goto -5174 -> 10609
    //   15786: iconst_0
    //   15787: wide
    //   15791: goto -5426 -> 10365
    //   15794: iconst_0
    //   15795: wide
    //   15799: goto -5678 -> 10121
    //   15802: iconst_0
    //   15803: wide
    //   15807: goto -5930 -> 9877
    //   15810: iconst_0
    //   15811: wide
    //   15815: goto -6182 -> 9633
    //   15818: iconst_0
    //   15819: wide
    //   15823: goto -6434 -> 9389
    //   15826: iconst_0
    //   15827: wide
    //   15831: goto -6686 -> 9145
    //   15834: iconst_0
    //   15835: wide
    //   15839: goto -6938 -> 8901
    //   15842: iconst_0
    //   15843: wide
    //   15847: goto -7190 -> 8657
    //   15850: iconst_0
    //   15851: wide
    //   15855: goto -7440 -> 8415
    //   15858: iconst_0
    //   15859: wide
    //   15863: goto -7690 -> 8173
    //   15866: iconst_0
    //   15867: wide
    //   15871: goto -7942 -> 7929
    //   15874: iconst_0
    //   15875: wide
    //   15879: goto -8194 -> 7685
    //   15882: iconst_0
    //   15883: wide
    //   15887: goto -8446 -> 7441
    //   15890: iconst_0
    //   15891: wide
    //   15895: goto -8698 -> 7197
    //   15898: iconst_0
    //   15899: wide
    //   15903: goto -8950 -> 6953
    //   15906: iconst_0
    //   15907: wide
    //   15911: goto -9202 -> 6709
    //   15914: iconst_0
    //   15915: wide
    //   15919: goto -9454 -> 6465
    //   15922: iconst_0
    //   15923: wide
    //   15927: goto -9706 -> 6221
    //   15930: iconst_0
    //   15931: wide
    //   15935: goto -9958 -> 5977
    //   15938: iconst_0
    //   15939: wide
    //   15943: goto -10210 -> 5733
    //   15946: iconst_0
    //   15947: wide
    //   15951: goto -10462 -> 5489
    //   15954: iconst_0
    //   15955: wide
    //   15959: goto -10714 -> 5245
    //   15962: iconst_0
    //   15963: wide
    //   15967: goto -10966 -> 5001
    //   15970: iconst_0
    //   15971: wide
    //   15975: goto -11218 -> 4757
    //   15978: iconst_0
    //   15979: wide
    //   15983: goto -11470 -> 4513
    //   15986: iconst_0
    //   15987: wide
    //   15991: goto -11722 -> 4269
    //   15994: iconst_0
    //   15995: wide
    //   15999: goto -11970 -> 4029
    //   16002: iconst_0
    //   16003: istore 247
    //   16005: goto -12204 -> 3801
    //   16008: iconst_0
    //   16009: istore 236
    //   16011: goto -12378 -> 3633
    //   16014: iconst_0
    //   16015: istore 225
    //   16017: goto -12552 -> 3465
    //   16020: iconst_0
    //   16021: istore 214
    //   16023: goto -12726 -> 3297
    //   16026: iconst_0
    //   16027: istore 203
    //   16029: goto -12900 -> 3129
    //   16032: iconst_0
    //   16033: istore 192
    //   16035: goto -13074 -> 2961
    //   16038: iconst_0
    //   16039: istore 181
    //   16041: goto -13248 -> 2793
    //   16044: iconst_0
    //   16045: istore 170
    //   16047: goto -13422 -> 2625
    //   16050: iconst_0
    //   16051: istore 159
    //   16053: goto -13596 -> 2457
    //   16056: iconst_0
    //   16057: istore 148
    //   16059: goto -13770 -> 2289
    //   16062: iconst_0
    //   16063: istore 137
    //   16065: goto -13944 -> 2121
    //   16068: iconst_0
    //   16069: istore 126
    //   16071: goto -14118 -> 1953
    //   16074: iconst_0
    //   16075: istore 115
    //   16077: goto -14292 -> 1785
    //   16080: iconst_0
    //   16081: istore 105
    //   16083: goto -14462 -> 1621
    //   16086: iconst_0
    //   16087: istore 94
    //   16089: goto -14636 -> 1453
    //   16092: iconst_0
    //   16093: istore 83
    //   16095: goto -14810 -> 1285
    //   16098: iconst_0
    //   16099: istore 72
    //   16101: goto -14984 -> 1117
    //   16104: iconst_0
    //   16105: istore 61
    //   16107: goto -15158 -> 949
    //   16110: iconst_0
    //   16111: istore 50
    //   16113: goto -15328 -> 785
    //   16116: iconst_0
    //   16117: istore 39
    //   16119: goto -15498 -> 621
    //   16122: iconst_0
    //   16123: istore 27
    //   16125: goto -15668 -> 457
    //   16128: iconst_0
    //   16129: istore 16
    //   16131: goto -15838 -> 293
    //   16134: iconst_0
    //   16135: istore 4
    //   16137: goto -16002 -> 135
  }

  protected _sdkf(_sdkt param_sdkt)
  {
    _sdkm local_sdkm1 = new _sdkm(null);
    this._sdkb = local_sdkm1;
    _sdkm local_sdkm2 = new _sdkm(null);
    this._sdkc = local_sdkm2;
    _sdkrc local_sdkrc = _sdkrc.NULL_TILING_PARAMETERS;
    _sdknb local_sdknb = new _sdknb(null, null, local_sdkrc);
    this._sdke = local_sdknb;
    _sdkqb local_sdkqb = new _sdkqb();
    this._sdkf = local_sdkqb;
    _sdkhb local_sdkhb1 = _sdkhb._sdkb(getClass());
    this._sdka = local_sdkhb1;
    this._sdkd = param_sdkt;
    _sdkhb local_sdkhb2 = this._sdka;
    String str1 = _sdksc._sdkc();
    local_sdkhb2._sdkb(str1);
    _sdkhb local_sdkhb3 = this._sdka;
    String str2 = _sdkp._sdka();
    local_sdkhb3._sdkb(str2);
    this._sdkh = null;
    this._sdki = null;
    _sdke();
    String str3 = _sdkb(param_sdkt);
    this._sdkg = str3;
    _sdkhb local_sdkhb4 = this._sdka;
    StringBuilder localStringBuilder1 = new StringBuilder();
    String str4 = z[0];
    StringBuilder localStringBuilder2 = localStringBuilder1.append(str4);
    String str5 = this._sdkg;
    String str6 = str5;
    local_sdkhb4._sdkb(str6);
  }

  private _sdktd<WPSAuthentication, RegistrationCallback> _sdka(WPSAuthentication paramWPSAuthentication, RegistrationCallback paramRegistrationCallback)
  {
    Object localObject = null;
    WPSAuthentication localWPSAuthentication1 = _sdke(paramWPSAuthentication);
    WPSAuthentication localWPSAuthentication2 = _sdkd(paramWPSAuthentication);
    if (this._sdka._sdkb())
    {
      _sdkhb local_sdkhb1 = this._sdka;
      StringBuilder localStringBuilder1 = new StringBuilder();
      String str1 = z[35];
      String str2 = str1 + localWPSAuthentication1;
      local_sdkhb1._sdkb(str2);
      _sdkhb local_sdkhb2 = this._sdka;
      StringBuilder localStringBuilder2 = new StringBuilder();
      String str3 = z[57];
      String str4 = str3 + localWPSAuthentication2;
      local_sdkhb2._sdkb(str4);
    }
    if ((localWPSAuthentication1 == null) && (localWPSAuthentication2 == null))
    {
      _sdkhb local_sdkhb3 = this._sdka;
      String str5 = z[60];
      local_sdkhb3._sdke(str5);
      String str6 = paramWPSAuthentication.getRealm();
      WPSAuthentication localWPSAuthentication3 = new WPSAuthentication("", str6);
      _sdka(paramWPSAuthentication, localWPSAuthentication3);
      WPSReturnCode localWPSReturnCode = WPSReturnCode.WPS_ERROR;
      _sdkb(paramRegistrationCallback, localWPSReturnCode);
    }
    while (true)
    {
      return localObject;
      if (localWPSAuthentication2 == null)
      {
        _sdkhb local_sdkhb4 = this._sdka;
        String str7 = z[58];
        local_sdkhb4._sdkd(str7);
        _sdka(paramRegistrationCallback);
        _sdka(paramRegistrationCallback);
      }
      else if (localWPSAuthentication2.equals(localWPSAuthentication1))
      {
        _sdkhb local_sdkhb5 = this._sdka;
        String str8 = z[62];
        local_sdkhb5._sdkb(str8);
        _sdka(paramRegistrationCallback);
        _sdka(paramRegistrationCallback);
      }
      else
      {
        if (localWPSAuthentication1 != null)
        {
          _sdkhb local_sdkhb6 = this._sdka;
          String str9 = z[59];
          local_sdkhb6._sdkd(str9);
        }
        _sdkhb local_sdkhb7 = this._sdka;
        String str10 = z[61];
        local_sdkhb7._sdkb(str10);
        _sdka(paramWPSAuthentication, localWPSAuthentication2);
        _sdkh local_sdkh = new _sdkh(this, paramWPSAuthentication, localWPSAuthentication2, paramRegistrationCallback);
        localObject = new _sdktd(localWPSAuthentication2, local_sdkh);
      }
    }
  }

  static _sdktd _sdka(_sdkf param_sdkf, _sdkzb param_sdkzb)
  {
    return param_sdkf._sdka(param_sdkzb);
  }

  private _sdktd<WPSReturnCode, _sdkib> _sdka(_sdkzb param_sdkzb)
  {
    _sdkhb local_sdkhb1 = this._sdka;
    String str1 = z[13];
    local_sdkhb1._sdkb(str1);
    Object localObject;
    if (!param_sdkzb.hasBeacons())
    {
      _sdkhb local_sdkhb2 = this._sdka;
      String str2 = z[10];
      local_sdkhb2._sdkb(str2);
      localObject = _sdktd._sdka(WPSReturnCode.WPS_ERROR_NO_WIFI_IN_RANGE, null);
    }
    while (true)
    {
      return localObject;
      _sdkib local_sdkib1 = this._sdkf.get(param_sdkzb, 0.8F);
      if (local_sdkib1 == null)
      {
        _sdkhb local_sdkhb3 = this._sdka;
        String str3 = z[12];
        local_sdkhb3._sdkb(str3);
        localObject = _sdktd._sdka(WPSReturnCode.WPS_ERROR, null);
      }
      else if (local_sdkib1._sdkc())
      {
        if ((!_sdkl) && (local_sdkib1.getSatellites() != 0))
          throw new AssertionError();
        _sdkhb local_sdkhb4 = this._sdka;
        String str4 = z[11];
        local_sdkhb4._sdkb(str4);
        localObject = _sdktd._sdka(WPSReturnCode.WPS_ERROR_LOCATION_CANNOT_BE_DETERMINED, null);
      }
      else
      {
        if (this._sdka._sdkb())
        {
          _sdkhb local_sdkhb5 = this._sdka;
          StringBuilder localStringBuilder1 = new StringBuilder();
          int i = local_sdkib1.getNAP();
          StringBuilder localStringBuilder2 = localStringBuilder1.append(i);
          String str5 = z[7];
          StringBuilder localStringBuilder3 = localStringBuilder2.append(str5);
          int j = local_sdkib1.getNCell();
          StringBuilder localStringBuilder4 = localStringBuilder3.append(j);
          String str6 = z[14];
          String str7 = str6;
          local_sdkhb5._sdkb(str7);
        }
        WPSReturnCode localWPSReturnCode = WPSReturnCode.WPS_OK;
        _sdkib local_sdkib2 = local_sdkib1.clone();
        _sdktd local_sdktd = _sdktd._sdka(localWPSReturnCode, local_sdkib2);
        ((_sdkib)local_sdktd.second).updateAgeBasedOn(param_sdkzb);
        ((_sdkib)local_sdktd.second)._sdkp = param_sdkzb;
        _sdknb local_sdknb = this._sdke;
        _sdkib local_sdkib3 = (_sdkib)local_sdktd.second;
        local_sdknb._sdka(local_sdkib3);
        localObject = local_sdktd;
      }
    }
  }

  private static _sdkib _sdka(_sdktd<WPSReturnCode, _sdkib> param_sdktd)
  {
    Object localObject = param_sdktd.first;
    WPSReturnCode localWPSReturnCode = WPSReturnCode.WPS_OK;
    if (localObject == localWPSReturnCode);
    for (_sdkib local_sdkib = (_sdkib)param_sdktd.second; ; local_sdkib = null)
      return local_sdkib;
  }

  private String _sdka(_sdkt param_sdkt)
  {
    String str1 = _sdkc(param_sdkt);
    String str2;
    if ((str1 != null) && (str1.length() >= 12))
      str2 = _sdka(str1);
    while (true)
    {
      return str2;
      _sdkhb local_sdkhb1 = this._sdka;
      String str3 = z[1];
      local_sdkhb1._sdkd(str3);
      String str4 = _sdkd(param_sdkt);
      if ((str4 != null) && (str4.length() >= 12))
      {
        str2 = _sdka(str4);
      }
      else
      {
        _sdkhb local_sdkhb2 = this._sdka;
        String str5 = z[2];
        local_sdkhb2._sdke(str5);
        str2 = null;
      }
    }
  }

  private String _sdka(String paramString)
  {
    String str1 = null;
    int i = Location._sdki;
    try
    {
      MessageDigest localMessageDigest = MessageDigest.getInstance(z[29]);
      String str2 = z[28];
      byte[] arrayOfByte1 = paramString.getBytes(str2);
      localMessageDigest.update(arrayOfByte1);
      StringBuilder localStringBuilder1 = new StringBuilder(32);
      byte[] arrayOfByte2 = localMessageDigest.digest();
      int j = 0;
      do
      {
        int k = arrayOfByte2.length;
        if (j >= k)
          break;
        String str3 = z[26];
        Object[] arrayOfObject = new Object[1];
        Byte localByte = Byte.valueOf(arrayOfByte2[j]);
        arrayOfObject[0] = localByte;
        String str4 = String.format(str3, arrayOfObject);
        StringBuilder localStringBuilder2 = localStringBuilder1.append(str4);
        j += 1;
      }
      while (i == 0);
      str1 = localStringBuilder1.toString();
      return str1;
    }
    catch (NoSuchAlgorithmException localNoSuchAlgorithmException)
    {
      while (true)
      {
        _sdkhb local_sdkhb1 = this._sdka;
        String str5 = z[27];
        local_sdkhb1._sdke(str5, localNoSuchAlgorithmException);
      }
    }
    catch (UnsupportedEncodingException localUnsupportedEncodingException)
    {
      while (true)
      {
        _sdkhb local_sdkhb2 = this._sdka;
        String str6 = z[27];
        local_sdkhb2._sdke(str6, localUnsupportedEncodingException);
      }
    }
  }

  /** @deprecated */
  private void _sdka(_sdkec param_sdkec)
  {
    try
    {
      _sdkec local_sdkec1 = this._sdkk;
      if (param_sdkec._sdkc(local_sdkec1) < 0)
      {
        _sdkhb local_sdkhb1 = this._sdka;
        String str1 = z[50];
        local_sdkhb1._sdkb(str1);
        _sdkec local_sdkec2 = _sdkec._sdkd();
        this._sdkj = local_sdkec2;
        if (Location._sdki == 0);
      }
      else
      {
        _sdkhb local_sdkhb2 = this._sdka;
        String str2 = z[51];
        local_sdkhb2._sdkb(str2);
      }
      return;
    }
    finally
    {
      localObject = finally;
      throw localObject;
    }
  }

  private void _sdka(_sdktd<WPSReturnCode, _sdkib> param_sdktd, _sdkzb param_sdkzb)
  {
    if (this._sdka._sdkb())
    {
      _sdkhb local_sdkhb1 = this._sdka;
      StringBuilder localStringBuilder1 = new StringBuilder();
      String str1 = z[3];
      StringBuilder localStringBuilder2 = localStringBuilder1.append(str1);
      int i = param_sdkzb.getAPs().size();
      StringBuilder localStringBuilder3 = localStringBuilder2.append(i);
      String str2 = z[7];
      StringBuilder localStringBuilder4 = localStringBuilder3.append(str2);
      int j = param_sdkzb.getCells().size();
      StringBuilder localStringBuilder5 = localStringBuilder4.append(j);
      String str3 = z[4];
      String str4 = str3;
      local_sdkhb1._sdkb(str4);
    }
    if (!param_sdkzb.hasBeacons())
    {
      _sdkhb local_sdkhb2 = this._sdka;
      String str5 = z[8];
      local_sdkhb2._sdkb(str5);
      return;
    }
    Object localObject1 = param_sdktd.first;
    WPSReturnCode localWPSReturnCode1 = WPSReturnCode.WPS_OK;
    if (localObject1 == localWPSReturnCode1)
    {
      _sdkhb local_sdkhb3 = this._sdka;
      String str6 = z[6];
      local_sdkhb3._sdkb(str6);
      _sdknb local_sdknb = this._sdke;
      _sdkib local_sdkib1 = (_sdkib)param_sdktd.second;
      local_sdknb._sdka(local_sdkib1);
      _sdkqb local_sdkqb1 = this._sdkf;
      _sdkib local_sdkib2 = (_sdkib)param_sdktd.second;
      local_sdkqb1.add(param_sdkzb, local_sdkib2);
      return;
    }
    Object localObject2 = param_sdktd.first;
    WPSReturnCode localWPSReturnCode2 = WPSReturnCode.WPS_ERROR_LOCATION_CANNOT_BE_DETERMINED;
    if (localObject2 == localWPSReturnCode2)
    {
      _sdkhb local_sdkhb4 = this._sdka;
      String str7 = z[5];
      local_sdkhb4._sdkb(str7);
      _sdkqb local_sdkqb2 = this._sdkf;
      _sdkib local_sdkib3 = new _sdkib();
      local_sdkqb2.add(param_sdkzb, local_sdkib3);
      return;
    }
    if (!this._sdka._sdkb())
      return;
    _sdkhb local_sdkhb5 = this._sdka;
    StringBuilder localStringBuilder6 = new StringBuilder();
    String str8 = z[9];
    StringBuilder localStringBuilder7 = localStringBuilder6.append(str8);
    Object localObject3 = param_sdktd.first;
    String str9 = localObject3;
    local_sdkhb5._sdkb(str9);
  }

  private static final void _sdka(RegistrationCallback paramRegistrationCallback)
  {
    try
    {
      paramRegistrationCallback.handleSuccess();
      return;
    }
    catch (Throwable localThrowable)
    {
    }
  }

  private void _sdka(WPSAuthentication paramWPSAuthentication1, WPSAuthentication paramWPSAuthentication2)
  {
    _sdktd local_sdktd = _sdktd._sdka(paramWPSAuthentication1, paramWPSAuthentication2);
    this._sdki = local_sdktd;
  }

  static void _sdka(_sdkf param_sdkf)
  {
    param_sdkf._sdke();
  }

  static void _sdka(_sdkf param_sdkf, _sdkec param_sdkec)
  {
    param_sdkf._sdka(param_sdkec);
  }

  static void _sdka(_sdkf param_sdkf, _sdktd param_sdktd, _sdkzb param_sdkzb)
  {
    param_sdkf._sdka(param_sdktd, param_sdkzb);
  }

  protected static final void _sdka(_sdkuc param_sdkuc)
  {
    _sdkb(param_sdkuc, null);
  }

  private static final void _sdka(_sdkuc param_sdkuc, WPSReturnCode paramWPSReturnCode)
  {
    WPSReturnCode localWPSReturnCode = WPSReturnCode.WPS_OK;
    if (paramWPSReturnCode == localWPSReturnCode)
    {
      if (_sdkl)
        return;
      throw new AssertionError();
    }
    try
    {
      WPSContinuation localWPSContinuation = param_sdkuc.handleError(paramWPSReturnCode);
      return;
    }
    catch (Throwable localThrowable)
    {
    }
  }

  // ERROR //
  private void _sdka(boolean paramBoolean1, boolean paramBoolean2)
  {
    // Byte code:
    //   0: aconst_null
    //   1: astore_3
    //   2: getstatic 402	com/skyhookwireless/wps/Location:_sdki	I
    //   5: istore 4
    //   7: iload_1
    //   8: ifeq +7 -> 15
    //   11: aload_0
    //   12: invokespecial 490	com/skyhookwireless/wps/_sdkf:_sdkd	()V
    //   15: iconst_2
    //   16: anewarray 492	com/skyhookwireless/wps/_sdkxc
    //   19: astore 5
    //   21: aload_0
    //   22: monitorenter
    //   23: iload_1
    //   24: ifeq +32 -> 56
    //   27: iconst_0
    //   28: istore 6
    //   30: aload_0
    //   31: getfield 194	com/skyhookwireless/wps/_sdkf:_sdkc	Lcom/skyhookwireless/wps/_sdkm;
    //   34: invokestatic 495	com/skyhookwireless/wps/_sdkm:_sdka	(Lcom/skyhookwireless/wps/_sdkm;)Lcom/skyhookwireless/wps/_sdkxc;
    //   37: astore 7
    //   39: aload 5
    //   41: iload 6
    //   43: aload 7
    //   45: aastore
    //   46: aload_0
    //   47: getfield 194	com/skyhookwireless/wps/_sdkf:_sdkc	Lcom/skyhookwireless/wps/_sdkm;
    //   50: aconst_null
    //   51: invokestatic 498	com/skyhookwireless/wps/_sdkm:_sdka	(Lcom/skyhookwireless/wps/_sdkm;Lcom/skyhookwireless/wps/_sdkxc;)Lcom/skyhookwireless/wps/_sdkxc;
    //   54: astore 8
    //   56: iload_2
    //   57: ifeq +28 -> 85
    //   60: aload_0
    //   61: getfield 192	com/skyhookwireless/wps/_sdkf:_sdkb	Lcom/skyhookwireless/wps/_sdkm;
    //   64: invokestatic 495	com/skyhookwireless/wps/_sdkm:_sdka	(Lcom/skyhookwireless/wps/_sdkm;)Lcom/skyhookwireless/wps/_sdkxc;
    //   67: astore 9
    //   69: aload 5
    //   71: iconst_1
    //   72: aload 9
    //   74: aastore
    //   75: aload_0
    //   76: getfield 192	com/skyhookwireless/wps/_sdkf:_sdkb	Lcom/skyhookwireless/wps/_sdkm;
    //   79: aconst_null
    //   80: invokestatic 498	com/skyhookwireless/wps/_sdkm:_sdka	(Lcom/skyhookwireless/wps/_sdkm;Lcom/skyhookwireless/wps/_sdkxc;)Lcom/skyhookwireless/wps/_sdkxc;
    //   83: astore 10
    //   85: aload_0
    //   86: monitorexit
    //   87: aload 5
    //   89: arraylength
    //   90: astore 11
    //   92: iconst_0
    //   93: istore 6
    //   95: iload 6
    //   97: aload 11
    //   99: if_icmpge +34 -> 133
    //   102: aload 5
    //   104: iload 6
    //   106: aaload
    //   107: astore 12
    //   109: aload 12
    //   111: ifnull +11 -> 122
    //   114: aload 12
    //   116: invokevirtual 501	com/skyhookwireless/wps/_sdkxc:isAlive	()Z
    //   119: ifne +64 -> 183
    //   122: iload 6
    //   124: iconst_1
    //   125: iadd
    //   126: istore 6
    //   128: iload 4
    //   130: ifeq -35 -> 95
    //   133: aload 5
    //   135: arraylength
    //   136: istore 6
    //   138: aload_3
    //   139: iload 6
    //   141: if_icmplt +4 -> 145
    //   144: return
    //   145: aload 5
    //   147: aload_3
    //   148: aaload
    //   149: astore 11
    //   151: aload 11
    //   153: ifnull +15 -> 168
    //   156: aload 11
    //   158: invokevirtual 501	com/skyhookwireless/wps/_sdkxc:isAlive	()Z
    //   161: istore 13
    //   163: iload 13
    //   165: ifne +120 -> 285
    //   168: aload_3
    //   169: iconst_1
    //   170: iadd
    //   171: istore_3
    //   172: iload 4
    //   174: ifeq -36 -> 138
    //   177: return
    //   178: astore_3
    //   179: aload_0
    //   180: monitorexit
    //   181: aload_3
    //   182: athrow
    //   183: invokestatic 507	java/lang/Thread:currentThread	()Ljava/lang/Thread;
    //   186: astore 14
    //   188: aload 12
    //   190: aload 14
    //   192: invokevirtual 508	java/lang/Object:equals	(Ljava/lang/Object;)Z
    //   195: ifeq +35 -> 230
    //   198: aload_0
    //   199: getfield 223	com/skyhookwireless/wps/_sdkf:_sdka	Lcom/skyhookwireless/_sdkhb;
    //   202: astore 15
    //   204: getstatic 174	com/skyhookwireless/wps/_sdkf:z	[Ljava/lang/String;
    //   207: bipush 22
    //   209: aaload
    //   210: astore 16
    //   212: new 510	java/lang/IllegalStateException
    //   215: dup
    //   216: invokespecial 511	java/lang/IllegalStateException:<init>	()V
    //   219: astore 17
    //   221: aload 15
    //   223: aload 16
    //   225: aload 17
    //   227: invokevirtual 513	com/skyhookwireless/_sdkhb:_sdkd	(Ljava/lang/String;Ljava/lang/Throwable;)V
    //   230: aload_0
    //   231: getfield 223	com/skyhookwireless/wps/_sdkf:_sdka	Lcom/skyhookwireless/_sdkhb;
    //   234: astore 18
    //   236: getstatic 174	com/skyhookwireless/wps/_sdkf:z	[Ljava/lang/String;
    //   239: bipush 21
    //   241: aaload
    //   242: astore 19
    //   244: aload 18
    //   246: aload 19
    //   248: invokevirtual 232	com/skyhookwireless/_sdkhb:_sdkb	(Ljava/lang/String;)V
    //   251: aload 12
    //   253: invokevirtual 516	com/skyhookwireless/wps/_sdkxc:abort	()V
    //   256: goto -134 -> 122
    //   259: astore 20
    //   261: aload_0
    //   262: getfield 223	com/skyhookwireless/wps/_sdkf:_sdka	Lcom/skyhookwireless/_sdkhb;
    //   265: astore 21
    //   267: getstatic 174	com/skyhookwireless/wps/_sdkf:z	[Ljava/lang/String;
    //   270: bipush 25
    //   272: aaload
    //   273: astore 22
    //   275: aload 21
    //   277: aload 22
    //   279: aload 20
    //   281: invokevirtual 436	com/skyhookwireless/_sdkhb:_sdke	(Ljava/lang/String;Ljava/lang/Throwable;)V
    //   284: return
    //   285: aload_0
    //   286: getfield 223	com/skyhookwireless/wps/_sdkf:_sdka	Lcom/skyhookwireless/_sdkhb;
    //   289: astore 23
    //   291: new 249	java/lang/StringBuilder
    //   294: dup
    //   295: invokespecial 250	java/lang/StringBuilder:<init>	()V
    //   298: astore 24
    //   300: getstatic 174	com/skyhookwireless/wps/_sdkf:z	[Ljava/lang/String;
    //   303: bipush 23
    //   305: aaload
    //   306: astore 25
    //   308: aload 24
    //   310: aload 25
    //   312: invokevirtual 254	java/lang/StringBuilder:append	(Ljava/lang/String;)Ljava/lang/StringBuilder;
    //   315: aload 11
    //   317: invokevirtual 268	java/lang/StringBuilder:append	(Ljava/lang/Object;)Ljava/lang/StringBuilder;
    //   320: invokevirtual 257	java/lang/StringBuilder:toString	()Ljava/lang/String;
    //   323: astore 26
    //   325: aload 23
    //   327: aload 26
    //   329: invokevirtual 232	com/skyhookwireless/_sdkhb:_sdkb	(Ljava/lang/String;)V
    //   332: aload 11
    //   334: invokevirtual 519	com/skyhookwireless/wps/_sdkxc:join	()V
    //   337: aload_0
    //   338: getfield 223	com/skyhookwireless/wps/_sdkf:_sdka	Lcom/skyhookwireless/_sdkhb;
    //   341: astore 27
    //   343: getstatic 174	com/skyhookwireless/wps/_sdkf:z	[Ljava/lang/String;
    //   346: bipush 24
    //   348: aaload
    //   349: astore 28
    //   351: aload 27
    //   353: aload 28
    //   355: invokevirtual 232	com/skyhookwireless/_sdkhb:_sdkb	(Ljava/lang/String;)V
    //   358: goto -190 -> 168
    //
    // Exception table:
    //   from	to	target	type
    //   30	87	178	finally
    //   179	181	178	finally
    //   87	163	259	java/lang/Throwable
    //   183	256	259	java/lang/Throwable
    //   285	358	259	java/lang/Throwable
  }

  private boolean _sdka(WPSAuthentication paramWPSAuthentication)
  {
    try
    {
      try
      {
        this._sdke._sdka(paramWPSAuthentication);
        bool = true;
        return bool;
      }
      finally
      {
      }
    }
    catch (Throwable localThrowable)
    {
      while (true)
      {
        _sdkhb local_sdkhb = this._sdka;
        String str = z[45];
        local_sdkhb._sdke(str, localThrowable);
        boolean bool = false;
      }
    }
  }

  protected static final boolean _sdka(WPSAuthentication paramWPSAuthentication, _sdkuc param_sdkuc)
  {
    WPSReturnCode localWPSReturnCode = WPSReturnCode.WPS_ERROR_UNAUTHORIZED;
    return _sdka(paramWPSAuthentication, param_sdkuc, localWPSReturnCode);
  }

  protected static final boolean _sdka(WPSAuthentication paramWPSAuthentication, _sdkuc param_sdkuc, WPSReturnCode paramWPSReturnCode)
  {
    if ((paramWPSAuthentication == null) || (paramWPSAuthentication.getUsername() == null) || (paramWPSAuthentication.getUsername().length() == 0) || (paramWPSAuthentication.getRealm() == null) || (paramWPSAuthentication.getRealm().length() == 0))
      _sdkb(param_sdkuc, paramWPSReturnCode);
    for (boolean bool = false; ; bool = true)
      return bool;
  }

  static boolean _sdka(_sdkf param_sdkf, WPSAuthentication paramWPSAuthentication1, WPSAuthentication paramWPSAuthentication2)
  {
    return param_sdkf._sdkb(paramWPSAuthentication1, paramWPSAuthentication2);
  }

  // ERROR //
  private boolean _sdka(_sdkm param_sdkm, _sdkuc param_sdkuc, _sdke param_sdke)
  {
    // Byte code:
    //   0: iconst_0
    //   1: istore 4
    //   3: aload_0
    //   4: monitorenter
    //   5: aload_1
    //   6: invokestatic 495	com/skyhookwireless/wps/_sdkm:_sdka	(Lcom/skyhookwireless/wps/_sdkm;)Lcom/skyhookwireless/wps/_sdkxc;
    //   9: ifnull +50 -> 59
    //   12: aload_1
    //   13: invokestatic 495	com/skyhookwireless/wps/_sdkm:_sdka	(Lcom/skyhookwireless/wps/_sdkm;)Lcom/skyhookwireless/wps/_sdkxc;
    //   16: invokevirtual 501	com/skyhookwireless/wps/_sdkxc:isAlive	()Z
    //   19: ifeq +40 -> 59
    //   22: aload_0
    //   23: getfield 223	com/skyhookwireless/wps/_sdkf:_sdka	Lcom/skyhookwireless/_sdkhb;
    //   26: astore 5
    //   28: getstatic 174	com/skyhookwireless/wps/_sdkf:z	[Ljava/lang/String;
    //   31: bipush 52
    //   33: aaload
    //   34: astore 6
    //   36: aload 5
    //   38: aload 6
    //   40: invokevirtual 294	com/skyhookwireless/_sdkhb:_sdkd	(Ljava/lang/String;)V
    //   43: aload_0
    //   44: monitorexit
    //   45: getstatic 289	com/skyhookwireless/wps/WPSReturnCode:WPS_ERROR	Lcom/skyhookwireless/wps/WPSReturnCode;
    //   48: astore 7
    //   50: aload_2
    //   51: aload 7
    //   53: invokestatic 292	com/skyhookwireless/wps/_sdkf:_sdkb	(Lcom/skyhookwireless/wps/_sdkuc;Lcom/skyhookwireless/wps/WPSReturnCode;)V
    //   56: iload 4
    //   58: ireturn
    //   59: new 492	com/skyhookwireless/wps/_sdkxc
    //   62: dup
    //   63: aload_3
    //   64: invokespecial 541	com/skyhookwireless/wps/_sdkxc:<init>	(Lcom/skyhookwireless/wps/_sdke;)V
    //   67: astore 8
    //   69: aload 8
    //   71: invokevirtual 544	com/skyhookwireless/wps/_sdkxc:start	()V
    //   74: aload_1
    //   75: aload 8
    //   77: invokestatic 498	com/skyhookwireless/wps/_sdkm:_sdka	(Lcom/skyhookwireless/wps/_sdkm;Lcom/skyhookwireless/wps/_sdkxc;)Lcom/skyhookwireless/wps/_sdkxc;
    //   80: astore 9
    //   82: aconst_null
    //   83: astore 7
    //   85: aload_0
    //   86: monitorexit
    //   87: aload 7
    //   89: astore 4
    //   91: goto -35 -> 56
    //   94: astore 10
    //   96: aconst_null
    //   97: astore 11
    //   99: aload_0
    //   100: monitorexit
    //   101: aload 10
    //   103: athrow
    //   104: astore 10
    //   106: aload_0
    //   107: getfield 223	com/skyhookwireless/wps/_sdkf:_sdka	Lcom/skyhookwireless/_sdkhb;
    //   110: astore 12
    //   112: new 249	java/lang/StringBuilder
    //   115: dup
    //   116: invokespecial 250	java/lang/StringBuilder:<init>	()V
    //   119: astore 13
    //   121: getstatic 174	com/skyhookwireless/wps/_sdkf:z	[Ljava/lang/String;
    //   124: bipush 53
    //   126: aaload
    //   127: astore 14
    //   129: aload 13
    //   131: aload 14
    //   133: invokevirtual 254	java/lang/StringBuilder:append	(Ljava/lang/String;)Ljava/lang/StringBuilder;
    //   136: aload_3
    //   137: invokevirtual 268	java/lang/StringBuilder:append	(Ljava/lang/Object;)Ljava/lang/StringBuilder;
    //   140: invokevirtual 257	java/lang/StringBuilder:toString	()Ljava/lang/String;
    //   143: astore 15
    //   145: aload 12
    //   147: aload 15
    //   149: aload 10
    //   151: invokevirtual 436	com/skyhookwireless/_sdkhb:_sdke	(Ljava/lang/String;Ljava/lang/Throwable;)V
    //   154: getstatic 289	com/skyhookwireless/wps/WPSReturnCode:WPS_ERROR	Lcom/skyhookwireless/wps/WPSReturnCode;
    //   157: astore 7
    //   159: goto -109 -> 50
    //   162: astore 16
    //   164: aconst_null
    //   165: astore 11
    //   167: aload 16
    //   169: astore 17
    //   171: aload 11
    //   173: ifnonnull +14 -> 187
    //   176: getstatic 289	com/skyhookwireless/wps/WPSReturnCode:WPS_ERROR	Lcom/skyhookwireless/wps/WPSReturnCode;
    //   179: astore 18
    //   181: aload_2
    //   182: aload 18
    //   184: invokestatic 292	com/skyhookwireless/wps/_sdkf:_sdkb	(Lcom/skyhookwireless/wps/_sdkuc;Lcom/skyhookwireless/wps/WPSReturnCode;)V
    //   187: aload 17
    //   189: athrow
    //   190: astore 17
    //   192: goto -21 -> 171
    //   195: astore 10
    //   197: aconst_null
    //   198: astore 11
    //   200: goto -94 -> 106
    //   203: astore 19
    //   205: aload 7
    //   207: astore 11
    //   209: aload 19
    //   211: astore 10
    //   213: goto -114 -> 99
    //   216: astore 10
    //   218: goto -119 -> 99
    //
    // Exception table:
    //   from	to	target	type
    //   5	45	94	finally
    //   59	82	94	finally
    //   101	104	104	java/lang/Throwable
    //   3	5	162	finally
    //   101	104	190	finally
    //   106	154	190	finally
    //   3	5	195	java/lang/Throwable
    //   85	87	203	finally
    //   99	101	216	finally
  }

  private WPSAuthentication _sdkb(WPSAuthentication paramWPSAuthentication)
  {
    WPSAuthentication localWPSAuthentication1 = _sdkc(paramWPSAuthentication);
    if (this._sdka._sdkb())
    {
      _sdkhb local_sdkhb1 = this._sdka;
      StringBuilder localStringBuilder1 = new StringBuilder();
      String str1 = z[38];
      String str2 = str1 + localWPSAuthentication1;
      local_sdkhb1._sdkb(str2);
    }
    if (localWPSAuthentication1 != null)
    {
      _sdkhb local_sdkhb2 = this._sdka;
      String str3 = z[37];
      local_sdkhb2._sdkb(str3);
      paramWPSAuthentication = localWPSAuthentication1;
    }
    while (true)
    {
      return paramWPSAuthentication;
      localWPSAuthentication1 = _sdke(paramWPSAuthentication);
      if (this._sdka._sdkb())
      {
        _sdkhb local_sdkhb3 = this._sdka;
        StringBuilder localStringBuilder2 = new StringBuilder();
        String str4 = z[35];
        String str5 = str4 + localWPSAuthentication1;
        local_sdkhb3._sdkb(str5);
      }
      if (localWPSAuthentication1 != null)
      {
        _sdkhb local_sdkhb4 = this._sdka;
        String str6 = z[34];
        local_sdkhb4._sdkb(str6);
        WPSAuthentication localWPSAuthentication2 = localWPSAuthentication1;
      }
      else
      {
        _sdkhb local_sdkhb5 = this._sdka;
        String str7 = z[36];
        local_sdkhb5._sdkb(str7);
      }
    }
  }

  static _sdkib _sdkb(_sdktd param_sdktd)
  {
    return _sdka(param_sdktd);
  }

  private String _sdkb(_sdkt param_sdkt)
  {
    String str1 = _sdka(param_sdkt);
    if (str1 == null);
    StringBuilder localStringBuilder;
    String str4;
    for (String str2 = null; ; str2 = str4)
    {
      return str2;
      localStringBuilder = new StringBuilder().append(str1).append('-');
      String str3 = z[43];
      Object[] arrayOfObject = new Object[1];
      Short localShort = Short.valueOf(_sdkb(str1));
      arrayOfObject[0] = localShort;
      str4 = String.format(str3, arrayOfObject);
    }
  }

  private static short _sdkb(String paramString)
  {
    int i = Location._sdki;
    int j = 65535;
    byte[] arrayOfByte = paramString.getBytes();
    int k = 0;
    do
    {
      int m = arrayOfByte.length;
      if (k >= m)
        break;
      int n = arrayOfByte[k] ^ j;
      int i1 = 7;
      j = n;
      int i2 = i1;
      do
      {
        if (i2 < 0)
          break;
        int i3 = -(j & 0x1);
        int i4 = j >>> 1;
        int i5 = i3 & 0x8408;
        int i6 = i4 ^ i5;
        int i7 = i2 + -1;
      }
      while (i == 0);
      k += 1;
    }
    while (i == 0);
    return (short)(j ^ 0xFFFFFFFF);
  }

  private void _sdkb()
  {
    _sdkhb local_sdkhb = this._sdka;
    String str = z[49];
    local_sdkhb._sdkb(str);
    _sdka(false, true);
  }

  static void _sdkb(RegistrationCallback paramRegistrationCallback)
  {
    _sdka(paramRegistrationCallback);
  }

  protected static final void _sdkb(_sdkuc param_sdkuc, WPSReturnCode paramWPSReturnCode)
  {
    if (paramWPSReturnCode != null)
      _sdka(param_sdkuc, paramWPSReturnCode);
    try
    {
      param_sdkuc.done();
      return;
    }
    catch (Throwable localThrowable)
    {
    }
  }

  /** @deprecated */
  private boolean _sdkb(_sdkec param_sdkec)
  {
    try
    {
      if (this._sdkj != null)
      {
        long l = this._sdkj._sdka(param_sdkec);
        if (l < 3600000L)
        {
          bool = true;
          return bool;
        }
      }
      boolean bool = false;
    }
    finally
    {
    }
  }

  private boolean _sdkb(WPSAuthentication paramWPSAuthentication1, WPSAuthentication paramWPSAuthentication2)
  {
    if (!_sdkl)
    {
      String str1 = paramWPSAuthentication1.getRealm();
      String str2 = paramWPSAuthentication2.getRealm();
      if (str1 != str2)
        throw new AssertionError();
    }
    _sdktd local_sdktd = _sdktd._sdka(paramWPSAuthentication1, paramWPSAuthentication2);
    this._sdkh = local_sdktd;
    _sdkpb local_sdkpb = _sdkpb._sdkb(this._sdkd);
    String str3 = paramWPSAuthentication1.getRealm();
    if (!local_sdkpb._sdka(str3))
    {
      _sdkhb local_sdkhb = this._sdka;
      String str4 = z[32];
      local_sdkhb._sdke(str4);
    }
    String str7;
    String str8;
    for (boolean bool = false; ; bool = local_sdkpb._sdka(str7, str8))
    {
      return bool;
      StringBuilder localStringBuilder1 = new StringBuilder();
      String str5 = z[33];
      StringBuilder localStringBuilder2 = localStringBuilder1.append(str5);
      String str6 = paramWPSAuthentication1.getUsername();
      str7 = str6;
      str8 = paramWPSAuthentication2.getUsername();
    }
  }

  static boolean _sdkb(_sdkf param_sdkf, _sdkec param_sdkec)
  {
    return param_sdkf._sdkb(param_sdkec);
  }

  private WPSAuthentication _sdkc(WPSAuthentication paramWPSAuthentication)
  {
    Object localObject1 = null;
    _sdktd local_sdktd = this._sdki;
    if (local_sdktd == null)
    {
      _sdkhb local_sdkhb1 = this._sdka;
      String str1 = z[54];
      local_sdkhb1._sdkb(str1);
      return localObject1;
    }
    if (this._sdka._sdkb())
    {
      _sdkhb local_sdkhb2 = this._sdka;
      StringBuilder localStringBuilder1 = new StringBuilder();
      String str2 = z[55];
      StringBuilder localStringBuilder2 = localStringBuilder1.append(str2);
      Object localObject2 = local_sdktd.first;
      String str3 = localObject2;
      local_sdkhb2._sdkb(str3);
    }
    if (((WPSAuthentication)local_sdktd.first).equals(paramWPSAuthentication));
    for (WPSAuthentication localWPSAuthentication = (WPSAuthentication)local_sdktd.second; ; localWPSAuthentication = null)
    {
      localObject1 = localWPSAuthentication;
      break;
    }
  }

  private static String _sdkc(_sdkt param_sdkt)
  {
    try
    {
      com.skyhookwireless._sdkzb local_sdkzb = com.skyhookwireless._sdkzb._sdkb(param_sdkt);
      str = local_sdkzb._sdkb();
      return str;
    }
    catch (com.skyhookwireless._sdkm local_sdkm)
    {
      while (true)
        String str = null;
    }
  }

  private void _sdkc()
  {
    _sdkhb local_sdkhb = this._sdka;
    String str = z[44];
    local_sdkhb._sdkb(str);
    _sdka(true, false);
  }

  static void _sdkc(_sdkuc param_sdkuc, WPSReturnCode paramWPSReturnCode)
  {
    _sdka(param_sdkuc, paramWPSReturnCode);
  }

  private WPSAuthentication _sdkd(WPSAuthentication paramWPSAuthentication)
  {
    if (this._sdkg == null);
    String str1;
    String str2;
    for (WPSAuthentication localWPSAuthentication = null; ; localWPSAuthentication = new WPSAuthentication(str1, str2))
    {
      return localWPSAuthentication;
      str1 = this._sdkg;
      str2 = paramWPSAuthentication.getRealm();
    }
  }

  private static String _sdkd(_sdkt param_sdkt)
  {
    try
    {
      _sdkdd local_sdkdd = _sdkdd._sdkb(param_sdkt);
      str = local_sdkdd._sdkc();
      return str;
    }
    catch (com.skyhookwireless._sdkn local_sdkn)
    {
      while (true)
        String str = null;
    }
  }

  private void _sdkd()
  {
    this._sdki = null;
  }

  private WPSAuthentication _sdke(WPSAuthentication paramWPSAuthentication)
  {
    _sdktd local_sdktd1 = this._sdkh;
    WPSAuthentication localWPSAuthentication1;
    if ((local_sdktd1 != null) && (((WPSAuthentication)local_sdktd1.first).equals(paramWPSAuthentication)))
    {
      _sdkhb local_sdkhb1 = this._sdka;
      String str1 = z[42];
      local_sdkhb1._sdkb(str1);
      localWPSAuthentication1 = (WPSAuthentication)local_sdktd1.second;
    }
    while (true)
    {
      return localWPSAuthentication1;
      _sdkpb local_sdkpb = _sdkpb._sdkb(this._sdkd);
      String str2 = paramWPSAuthentication.getRealm();
      if (!local_sdkpb._sdka(str2))
      {
        _sdkhb local_sdkhb2 = this._sdka;
        String str3 = z[39];
        local_sdkhb2._sdke(str3);
        localWPSAuthentication1 = null;
      }
      else
      {
        StringBuilder localStringBuilder1 = new StringBuilder();
        String str4 = z[33];
        StringBuilder localStringBuilder2 = localStringBuilder1.append(str4);
        String str5 = paramWPSAuthentication.getUsername();
        String str6 = str5;
        String str7 = local_sdkpb._sdkb(str6);
        if (str7 == null)
        {
          _sdkhb local_sdkhb3 = this._sdka;
          String str8 = z[40];
          local_sdkhb3._sdkb(str8);
          localWPSAuthentication1 = null;
        }
        else
        {
          _sdkhb local_sdkhb4 = this._sdka;
          String str9 = z[41];
          local_sdkhb4._sdkb(str9);
          String str10 = paramWPSAuthentication.getRealm();
          WPSAuthentication localWPSAuthentication2 = new WPSAuthentication(str7, str10);
          _sdktd local_sdktd2 = _sdktd._sdka(paramWPSAuthentication, localWPSAuthentication2);
          this._sdkh = local_sdktd2;
          localWPSAuthentication1 = (WPSAuthentication)local_sdktd2.second;
        }
      }
    }
  }

  static String _sdke(_sdkt param_sdkt)
  {
    return _sdkd(param_sdkt);
  }

  /** @deprecated */
  private void _sdke()
  {
    try
    {
      _sdkhb local_sdkhb = this._sdka;
      String str = z[31];
      local_sdkhb._sdkb(str);
      this._sdkj = null;
      _sdkec local_sdkec = _sdkec._sdkd();
      this._sdkk = local_sdkec;
      return;
    }
    finally
    {
      localObject = finally;
      throw localObject;
    }
  }

  public static String getVersion()
  {
    return _sdksc._sdkb();
  }

  public static void setServerUrl(String paramString)
  {
    _sdktb._sdkc(paramString);
  }

  protected boolean _sdka()
  {
    return false;
  }

  public void abort()
  {
    _sdkhb local_sdkhb = this._sdka;
    String str = z[30];
    local_sdkhb._sdkb(str);
    _sdka(true, true);
  }

  public void getIPLocation(WPSAuthentication paramWPSAuthentication, WPSStreetAddressLookup paramWPSStreetAddressLookup, IPLocationCallback paramIPLocationCallback)
  {
    if (paramIPLocationCallback == null)
    {
      String str = z[15];
      throw new NullPointerException(str);
    }
    _sdkb();
    if (!_sdka(paramWPSAuthentication, paramIPLocationCallback))
      return;
    _sdkm local_sdkm = this._sdkb;
    WPSAuthentication localWPSAuthentication = _sdkb(paramWPSAuthentication);
    _sdkj local_sdkj = new _sdkj(localWPSAuthentication, paramWPSStreetAddressLookup, paramIPLocationCallback, null);
    boolean bool = _sdka(local_sdkm, paramIPLocationCallback, local_sdkj);
  }

  public void getLocation(WPSAuthentication paramWPSAuthentication, WPSStreetAddressLookup paramWPSStreetAddressLookup, WPSLocationCallback paramWPSLocationCallback)
  {
    if (paramWPSLocationCallback == null)
    {
      String str = z[15];
      throw new NullPointerException(str);
    }
    _sdkb();
    WPSAuthentication localWPSAuthentication1 = paramWPSAuthentication;
    WPSLocationCallback localWPSLocationCallback1 = paramWPSLocationCallback;
    if (!_sdka(localWPSAuthentication1, localWPSLocationCallback1))
      return;
    WPSAuthentication localWPSAuthentication2 = _sdkb(paramWPSAuthentication);
    boolean bool1 = _sdka(localWPSAuthentication2);
    _sdkm local_sdkm = this._sdkb;
    _sdkq local_sdkq1 = new com/skyhookwireless/wps/_sdkq;
    _sdkt local_sdkt1 = this._sdkd;
    boolean bool2 = _sdka();
    _sdkf local_sdkf1 = this;
    WPSStreetAddressLookup localWPSStreetAddressLookup = paramWPSStreetAddressLookup;
    WPSLocationCallback localWPSLocationCallback2 = paramWPSLocationCallback;
    _sdkn local_sdkn1 = new _sdkn(local_sdkf1, localWPSAuthentication2, localWPSStreetAddressLookup, 500L, localWPSLocationCallback2, null);
    _sdkq local_sdkq2 = local_sdkq1;
    _sdkt local_sdkt2 = local_sdkt1;
    boolean bool3 = bool2;
    long l = 500L;
    int i = 40;
    _sdkn local_sdkn2 = local_sdkn1;
    local_sdkq2.<init>(local_sdkt2, bool3, l, i, local_sdkn2);
    _sdkf local_sdkf2 = this;
    WPSLocationCallback localWPSLocationCallback3 = paramWPSLocationCallback;
    boolean bool4 = local_sdkf2._sdka(local_sdkm, localWPSLocationCallback3, local_sdkq1);
  }

  public void getPeriodicLocation(WPSAuthentication paramWPSAuthentication, WPSStreetAddressLookup paramWPSStreetAddressLookup, long paramLong, int paramInt, WPSPeriodicLocationCallback paramWPSPeriodicLocationCallback)
  {
    if (paramWPSPeriodicLocationCallback == null)
    {
      String str1 = z[15];
      throw new NullPointerException(str1);
    }
    while (true)
    {
      try
      {
        _sdkb();
        WPSPeriodicLocationCallback localWPSPeriodicLocationCallback1 = paramWPSPeriodicLocationCallback;
        if (!_sdka(paramWPSAuthentication, localWPSPeriodicLocationCallback1))
          return;
        WPSAuthentication localWPSAuthentication = _sdkb(paramWPSAuthentication);
        boolean bool1 = _sdka(localWPSAuthentication);
        if (paramLong < 500L)
        {
          _sdkhb local_sdkhb1 = this._sdka;
          StringBuilder localStringBuilder1 = new StringBuilder();
          String str2 = z[47];
          StringBuilder localStringBuilder2 = localStringBuilder1.append(str2);
          long l1 = paramLong;
          StringBuilder localStringBuilder3 = localStringBuilder2.append(l1);
          String str3 = z[48];
          String str4 = str3;
          local_sdkhb1._sdkd(str4);
          l2 = 500L;
          _sdkm local_sdkm = this._sdkb;
          _sdkq local_sdkq1 = new com/skyhookwireless/wps/_sdkq;
          _sdkt local_sdkt1 = this._sdkd;
          boolean bool2 = _sdka();
          _sdkt local_sdkt2 = this._sdkd;
          _sdkf local_sdkf = this;
          WPSStreetAddressLookup localWPSStreetAddressLookup = paramWPSStreetAddressLookup;
          WPSPeriodicLocationCallback localWPSPeriodicLocationCallback2 = paramWPSPeriodicLocationCallback;
          _sdko local_sdko1 = new _sdko(local_sdkf, local_sdkt2, localWPSAuthentication, localWPSStreetAddressLookup, l2, localWPSPeriodicLocationCallback2);
          _sdkq local_sdkq2 = local_sdkq1;
          _sdkt local_sdkt3 = local_sdkt1;
          boolean bool3 = bool2;
          int i = paramInt;
          _sdko local_sdko2 = local_sdko1;
          local_sdkq2.<init>(local_sdkt3, bool3, l2, i, local_sdko2);
          WPSPeriodicLocationCallback localWPSPeriodicLocationCallback3 = paramWPSPeriodicLocationCallback;
          boolean bool4 = _sdka(local_sdkm, localWPSPeriodicLocationCallback3, local_sdkq1);
          return;
        }
      }
      catch (Throwable localThrowable)
      {
        _sdkhb local_sdkhb2 = this._sdka;
        String str5 = z[46];
        local_sdkhb2._sdke(str5, localThrowable);
        WPSReturnCode localWPSReturnCode = WPSReturnCode.WPS_ERROR;
        _sdkb(paramWPSPeriodicLocationCallback, localWPSReturnCode);
        return;
      }
      long l2 = paramLong;
    }
  }

  public void registerUser(WPSAuthentication paramWPSAuthentication1, WPSAuthentication paramWPSAuthentication2, RegistrationCallback paramRegistrationCallback)
  {
    if (this._sdka._sdkb())
    {
      _sdkhb local_sdkhb1 = this._sdka;
      String str1 = z[19];
      local_sdkhb1._sdkb(str1);
      _sdkhb local_sdkhb2 = this._sdka;
      StringBuilder localStringBuilder1 = new StringBuilder();
      String str2 = z[16];
      String str3 = str2 + paramWPSAuthentication1;
      local_sdkhb2._sdkb(str3);
      _sdkhb local_sdkhb3 = this._sdka;
      StringBuilder localStringBuilder2 = new StringBuilder();
      String str4 = z[18];
      String str5 = str4 + paramWPSAuthentication2;
      local_sdkhb3._sdkb(str5);
    }
    if (paramRegistrationCallback == null)
    {
      String str6 = z[15];
      throw new NullPointerException(str6);
    }
    _sdkc();
    if (!_sdka(paramWPSAuthentication1, paramRegistrationCallback))
      return;
    WPSAuthentication localWPSAuthentication1;
    RegistrationCallback localRegistrationCallback;
    if (paramWPSAuthentication2 == null)
    {
      _sdktd local_sdktd = _sdka(paramWPSAuthentication1, paramRegistrationCallback);
      if (local_sdktd == null)
        return;
      localWPSAuthentication1 = (WPSAuthentication)local_sdktd.first;
      localRegistrationCallback = (RegistrationCallback)local_sdktd.second;
    }
    for (WPSAuthentication localWPSAuthentication2 = localWPSAuthentication1; ; localWPSAuthentication2 = paramWPSAuthentication2)
    {
      WPSReturnCode localWPSReturnCode = WPSReturnCode.WPS_ERROR;
      if (!_sdka(localWPSAuthentication2, localRegistrationCallback, localWPSReturnCode))
        return;
      _sdkhb local_sdkhb4 = this._sdka;
      String str7 = z[17];
      local_sdkhb4._sdkb(str7);
      _sdkm local_sdkm = this._sdkc;
      _sdkt local_sdkt = this._sdkd;
      _sdkf local_sdkf = this;
      WPSAuthentication localWPSAuthentication3 = paramWPSAuthentication1;
      _sdkk local_sdkk = new _sdkk(local_sdkf, localWPSAuthentication3, localWPSAuthentication2, local_sdkt, localRegistrationCallback, null);
      boolean bool = _sdka(local_sdkm, localRegistrationCallback, local_sdkk);
      return;
      localRegistrationCallback = paramRegistrationCallback;
    }
  }

  public void setLocalFilePaths(List<String> paramList)
  {
    try
    {
      _sdkb();
      this._sdke._sdka(paramList);
      return;
    }
    catch (Throwable localThrowable)
    {
      _sdkhb local_sdkhb = this._sdka;
      String str = z[56];
      local_sdkhb._sdke(str, localThrowable);
    }
  }

  public void setTiling(String paramString, long paramLong1, long paramLong2, TilingListener paramTilingListener)
  {
    try
    {
      _sdkb();
      _sdknb local_sdknb = this._sdke;
      String str1 = paramString;
      long l1 = paramLong1;
      long l2 = paramLong2;
      TilingListener localTilingListener = paramTilingListener;
      _sdkrc local_sdkrc = new _sdkrc(str1, l1, l2, localTilingListener);
      local_sdknb._sdka(local_sdkrc);
      return;
    }
    catch (Throwable localThrowable)
    {
      _sdkhb local_sdkhb = this._sdka;
      String str2 = z[20];
      local_sdkhb._sdke(str2, localThrowable);
    }
  }

  public void tuneLocation(WPSAuthentication paramWPSAuthentication, WPSLocation paramWPSLocation, TuneLocationCallback paramTuneLocationCallback)
  {
    if (paramTuneLocationCallback == null)
    {
      String str = z[15];
      throw new NullPointerException(str);
    }
    _sdkb();
    if (!_sdka(paramWPSAuthentication, paramTuneLocationCallback))
      return;
    _sdkm local_sdkm = this._sdkb;
    WPSAuthentication localWPSAuthentication = _sdkb(paramWPSAuthentication);
    _sdkl local_sdkl = new _sdkl(localWPSAuthentication, paramWPSLocation, paramTuneLocationCallback, null);
    boolean bool = _sdka(local_sdkm, paramTuneLocationCallback, local_sdkl);
  }
}

/* Location:           D:\Tools\extractapktools\extractapktools\dex2jar-0.0.7.11-SNAPSHOT\classes_dex2jar.jar
 * Qualified Name:     com.skyhookwireless.wps._sdkf
 * JD-Core Version:    0.6.2
 */