package com.skyhookwireless.wps;

import com.skyhookwireless._sdkec;
import com.skyhookwireless._sdkhd;
import java.io.File;
import java.io.FileOutputStream;
import java.io.IOException;
import java.io.InputStream;
import java.util.ArrayList;
import java.util.Collections;
import java.util.Comparator;
import java.util.Iterator;
import java.util.LinkedList;
import java.util.List;
import java.util.Map;
import java.util.regex.Matcher;
import java.util.regex.Pattern;

public final class _sdkkc
{
  static final boolean _sdkq;
  public static boolean _sdkr;
  private static final String[] z;
  private final _sdkqc _sdka;
  private final com.skyhookwireless._sdkhb _sdkb;
  private final _sdknc _sdkc;
  private final _sdkgc _sdkd;
  private final Cache<_sdkzb, Boolean> _sdke;
  private final _sdkfc _sdkf;
  private String _sdkg;
  private final TilingListener _sdkh;
  private boolean _sdki;
  private boolean _sdkj;
  private boolean _sdkk;
  private final LinkedList<_sdkic> _sdkl;
  private int _sdkm;
  private _sdkec _sdkn;
  private final boolean _sdko;
  private final Map<String, Boolean> _sdkp;

  static
  {
    // Byte code:
    //   0: iconst_1
    //   1: istore_0
    //   2: bipush 50
    //   4: anewarray 44	java/lang/String
    //   7: astore_1
    //   8: ldc 46
    //   10: invokevirtual 50	java/lang/String:toCharArray	()[C
    //   13: astore_2
    //   14: aload_2
    //   15: arraylength
    //   16: istore_3
    //   17: iload_3
    //   18: iload_0
    //   19: if_icmpgt +12375 -> 12394
    //   22: iconst_0
    //   23: istore 4
    //   25: aload_2
    //   26: astore 5
    //   28: iload 4
    //   30: istore 6
    //   32: iload_3
    //   33: istore 7
    //   35: aload_2
    //   36: astore 8
    //   38: iload 7
    //   40: istore 9
    //   42: aload 8
    //   44: iload 4
    //   46: caload
    //   47: istore 10
    //   49: iload 6
    //   51: iconst_5
    //   52: irem
    //   53: tableswitch	default:+31 -> 84, 0:+10377->10430, 1:+10384->10437, 2:+10391->10444, 3:+10398->10451
    //   85: isub
    //   86: istore 11
    //   88: iload 11
    //   90: iload 10
    //   92: ixor
    //   93: i2c
    //   94: istore 12
    //   96: aload 8
    //   98: iload 4
    //   100: iload 12
    //   102: castore
    //   103: iload 6
    //   105: iconst_1
    //   106: iadd
    //   107: istore 4
    //   109: iload 9
    //   111: ifne +18 -> 129
    //   114: aload 5
    //   116: astore 8
    //   118: iload 4
    //   120: istore 6
    //   122: iload 9
    //   124: istore 4
    //   126: goto -84 -> 42
    //   129: iload 9
    //   131: istore_3
    //   132: aload 5
    //   134: astore_2
    //   135: iload_3
    //   136: iload 4
    //   138: if_icmpgt -113 -> 25
    //   141: new 44	java/lang/String
    //   144: dup
    //   145: aload_2
    //   146: invokespecial 54	java/lang/String:<init>	([C)V
    //   149: invokevirtual 58	java/lang/String:intern	()Ljava/lang/String;
    //   152: astore 13
    //   154: aload_1
    //   155: iconst_0
    //   156: aload 13
    //   158: aastore
    //   159: ldc 60
    //   161: invokevirtual 50	java/lang/String:toCharArray	()[C
    //   164: astore 14
    //   166: aload 14
    //   168: arraylength
    //   169: istore 15
    //   171: iload 15
    //   173: iconst_1
    //   174: if_icmpgt +12214 -> 12388
    //   177: iconst_0
    //   178: istore 16
    //   180: aload 14
    //   182: astore 5
    //   184: iload 16
    //   186: istore 6
    //   188: iload 15
    //   190: istore 17
    //   192: aload 14
    //   194: astore 18
    //   196: iload 17
    //   198: istore 19
    //   200: aload 18
    //   202: iload 16
    //   204: caload
    //   205: istore 10
    //   207: iload 6
    //   209: iconst_5
    //   210: irem
    //   211: tableswitch	default:+29 -> 240, 0:+10247->10458, 1:+10254->10465, 2:+10261->10472, 3:+10268->10479
    //   241: isub
    //   242: istore 20
    //   244: iload 20
    //   246: iload 10
    //   248: ixor
    //   249: i2c
    //   250: istore 21
    //   252: aload 18
    //   254: iload 16
    //   256: iload 21
    //   258: castore
    //   259: iload 6
    //   261: iconst_1
    //   262: iadd
    //   263: istore 16
    //   265: iload 19
    //   267: ifne +18 -> 285
    //   270: aload 5
    //   272: astore 18
    //   274: iload 16
    //   276: istore 22
    //   278: iload 19
    //   280: istore 16
    //   282: goto -82 -> 200
    //   285: iload 19
    //   287: istore 15
    //   289: aload 5
    //   291: astore 14
    //   293: iload 15
    //   295: iload 16
    //   297: if_icmpgt -117 -> 180
    //   300: new 44	java/lang/String
    //   303: dup
    //   304: aload 14
    //   306: invokespecial 54	java/lang/String:<init>	([C)V
    //   309: invokevirtual 58	java/lang/String:intern	()Ljava/lang/String;
    //   312: astore 23
    //   314: aload_1
    //   315: iconst_1
    //   316: aload 23
    //   318: aastore
    //   319: iconst_2
    //   320: istore 24
    //   322: ldc 62
    //   324: invokevirtual 50	java/lang/String:toCharArray	()[C
    //   327: astore 25
    //   329: aload 25
    //   331: arraylength
    //   332: istore 26
    //   334: iload 26
    //   336: iconst_1
    //   337: if_icmpgt +12045 -> 12382
    //   340: iconst_0
    //   341: istore 27
    //   343: aload 25
    //   345: astore 5
    //   347: iload 27
    //   349: istore 6
    //   351: iload 26
    //   353: istore 28
    //   355: aload 25
    //   357: astore 29
    //   359: iload 28
    //   361: istore 30
    //   363: aload 29
    //   365: iload 27
    //   367: caload
    //   368: istore 31
    //   370: iload 6
    //   372: iconst_5
    //   373: irem
    //   374: tableswitch	default:+30 -> 404, 0:+10112->10486, 1:+10119->10493, 2:+10126->10500, 3:+10133->10507
    //   405: isub
    //   406: istore 32
    //   408: iload 32
    //   410: iload 31
    //   412: ixor
    //   413: i2c
    //   414: istore 33
    //   416: aload 29
    //   418: iload 27
    //   420: iload 33
    //   422: castore
    //   423: iload 6
    //   425: iconst_1
    //   426: iadd
    //   427: istore 27
    //   429: iload 30
    //   431: ifne +18 -> 449
    //   434: aload 5
    //   436: astore 29
    //   438: iload 27
    //   440: istore 34
    //   442: iload 30
    //   444: istore 27
    //   446: goto -83 -> 363
    //   449: iload 30
    //   451: istore 26
    //   453: aload 5
    //   455: astore 25
    //   457: iload 26
    //   459: iload 27
    //   461: if_icmpgt -118 -> 343
    //   464: new 44	java/lang/String
    //   467: dup
    //   468: aload 25
    //   470: invokespecial 54	java/lang/String:<init>	([C)V
    //   473: invokevirtual 58	java/lang/String:intern	()Ljava/lang/String;
    //   476: astore 35
    //   478: aload_1
    //   479: iload 24
    //   481: aload 35
    //   483: aastore
    //   484: iconst_3
    //   485: istore 36
    //   487: ldc 64
    //   489: invokevirtual 50	java/lang/String:toCharArray	()[C
    //   492: astore 37
    //   494: aload 37
    //   496: arraylength
    //   497: istore 38
    //   499: iload 38
    //   501: iconst_1
    //   502: if_icmpgt +11874 -> 12376
    //   505: iconst_0
    //   506: istore 39
    //   508: aload 37
    //   510: astore 5
    //   512: iload 39
    //   514: istore 6
    //   516: iload 38
    //   518: istore 40
    //   520: aload 37
    //   522: astore 41
    //   524: iload 40
    //   526: istore 42
    //   528: aload 41
    //   530: iload 39
    //   532: caload
    //   533: istore 31
    //   535: iload 6
    //   537: iconst_5
    //   538: irem
    //   539: tableswitch	default:+29 -> 568, 0:+9975->10514, 1:+9982->10521, 2:+9989->10528, 3:+9996->10535
    //   569: isub
    //   570: istore 43
    //   572: iload 43
    //   574: iload 31
    //   576: ixor
    //   577: i2c
    //   578: istore 44
    //   580: aload 41
    //   582: iload 39
    //   584: iload 44
    //   586: castore
    //   587: iload 6
    //   589: iconst_1
    //   590: iadd
    //   591: istore 39
    //   593: iload 42
    //   595: ifne +18 -> 613
    //   598: aload 5
    //   600: astore 41
    //   602: iload 39
    //   604: istore 45
    //   606: iload 42
    //   608: istore 39
    //   610: goto -82 -> 528
    //   613: iload 42
    //   615: istore 38
    //   617: aload 5
    //   619: astore 37
    //   621: iload 38
    //   623: iload 39
    //   625: if_icmpgt -117 -> 508
    //   628: new 44	java/lang/String
    //   631: dup
    //   632: aload 37
    //   634: invokespecial 54	java/lang/String:<init>	([C)V
    //   637: invokevirtual 58	java/lang/String:intern	()Ljava/lang/String;
    //   640: astore 46
    //   642: aload_1
    //   643: iload 36
    //   645: aload 46
    //   647: aastore
    //   648: iconst_4
    //   649: istore 47
    //   651: ldc 66
    //   653: invokevirtual 50	java/lang/String:toCharArray	()[C
    //   656: astore 48
    //   658: aload 48
    //   660: arraylength
    //   661: istore 49
    //   663: iload 49
    //   665: iconst_1
    //   666: if_icmpgt +11704 -> 12370
    //   669: iconst_0
    //   670: istore 50
    //   672: aload 48
    //   674: astore 5
    //   676: iload 50
    //   678: istore 6
    //   680: iload 49
    //   682: istore 51
    //   684: aload 48
    //   686: astore 52
    //   688: iload 51
    //   690: istore 53
    //   692: aload 52
    //   694: iload 50
    //   696: caload
    //   697: istore 31
    //   699: iload 6
    //   701: iconst_5
    //   702: irem
    //   703: tableswitch	default:+29 -> 732, 0:+9839->10542, 1:+9846->10549, 2:+9853->10556, 3:+9860->10563
    //   733: isub
    //   734: istore 54
    //   736: iload 54
    //   738: iload 31
    //   740: ixor
    //   741: i2c
    //   742: istore 55
    //   744: aload 52
    //   746: iload 50
    //   748: iload 55
    //   750: castore
    //   751: iload 6
    //   753: iconst_1
    //   754: iadd
    //   755: istore 50
    //   757: iload 53
    //   759: ifne +18 -> 777
    //   762: aload 5
    //   764: astore 52
    //   766: iload 50
    //   768: istore 56
    //   770: iload 53
    //   772: istore 50
    //   774: goto -82 -> 692
    //   777: iload 53
    //   779: istore 49
    //   781: aload 5
    //   783: astore 48
    //   785: iload 49
    //   787: iload 50
    //   789: if_icmpgt -117 -> 672
    //   792: new 44	java/lang/String
    //   795: dup
    //   796: aload 48
    //   798: invokespecial 54	java/lang/String:<init>	([C)V
    //   801: invokevirtual 58	java/lang/String:intern	()Ljava/lang/String;
    //   804: astore 57
    //   806: aload_1
    //   807: iload 47
    //   809: aload 57
    //   811: aastore
    //   812: iconst_5
    //   813: istore 58
    //   815: ldc 68
    //   817: invokevirtual 50	java/lang/String:toCharArray	()[C
    //   820: astore 59
    //   822: aload 59
    //   824: arraylength
    //   825: istore 60
    //   827: iload 60
    //   829: iconst_1
    //   830: if_icmpgt +11534 -> 12364
    //   833: iconst_0
    //   834: istore 61
    //   836: aload 59
    //   838: astore 5
    //   840: iload 61
    //   842: istore 6
    //   844: iload 60
    //   846: istore 62
    //   848: aload 59
    //   850: astore 63
    //   852: iload 62
    //   854: istore 64
    //   856: aload 63
    //   858: iload 61
    //   860: caload
    //   861: istore 31
    //   863: iload 6
    //   865: iconst_5
    //   866: irem
    //   867: tableswitch	default:+29 -> 896, 0:+9703->10570, 1:+9710->10577, 2:+9717->10584, 3:+9724->10591
    //   897: isub
    //   898: istore 65
    //   900: iload 65
    //   902: iload 31
    //   904: ixor
    //   905: i2c
    //   906: istore 66
    //   908: aload 63
    //   910: iload 61
    //   912: iload 66
    //   914: castore
    //   915: iload 6
    //   917: iconst_1
    //   918: iadd
    //   919: istore 61
    //   921: iload 64
    //   923: ifne +18 -> 941
    //   926: aload 5
    //   928: astore 63
    //   930: iload 61
    //   932: istore 67
    //   934: iload 64
    //   936: istore 61
    //   938: goto -82 -> 856
    //   941: iload 64
    //   943: istore 60
    //   945: aload 5
    //   947: astore 59
    //   949: iload 60
    //   951: iload 61
    //   953: if_icmpgt -117 -> 836
    //   956: new 44	java/lang/String
    //   959: dup
    //   960: aload 59
    //   962: invokespecial 54	java/lang/String:<init>	([C)V
    //   965: invokevirtual 58	java/lang/String:intern	()Ljava/lang/String;
    //   968: astore 68
    //   970: aload_1
    //   971: iload 58
    //   973: aload 68
    //   975: aastore
    //   976: bipush 6
    //   978: istore 69
    //   980: ldc 70
    //   982: invokevirtual 50	java/lang/String:toCharArray	()[C
    //   985: astore 70
    //   987: aload 70
    //   989: arraylength
    //   990: istore 71
    //   992: iload 71
    //   994: iconst_1
    //   995: if_icmpgt +11363 -> 12358
    //   998: iconst_0
    //   999: istore 72
    //   1001: aload 70
    //   1003: astore 5
    //   1005: iload 72
    //   1007: istore 6
    //   1009: iload 71
    //   1011: istore 73
    //   1013: aload 70
    //   1015: astore 74
    //   1017: iload 73
    //   1019: istore 75
    //   1021: aload 74
    //   1023: iload 72
    //   1025: caload
    //   1026: istore 31
    //   1028: iload 6
    //   1030: iconst_5
    //   1031: irem
    //   1032: tableswitch	default:+32 -> 1064, 0:+9566->10598, 1:+9573->10605, 2:+9580->10612, 3:+9587->10619
    //   1065: isub
    //   1066: istore 76
    //   1068: iload 76
    //   1070: iload 31
    //   1072: ixor
    //   1073: i2c
    //   1074: istore 77
    //   1076: aload 74
    //   1078: iload 72
    //   1080: iload 77
    //   1082: castore
    //   1083: iload 6
    //   1085: iconst_1
    //   1086: iadd
    //   1087: istore 72
    //   1089: iload 75
    //   1091: ifne +18 -> 1109
    //   1094: aload 5
    //   1096: astore 74
    //   1098: iload 72
    //   1100: istore 78
    //   1102: iload 75
    //   1104: istore 72
    //   1106: goto -85 -> 1021
    //   1109: iload 75
    //   1111: istore 71
    //   1113: aload 5
    //   1115: astore 70
    //   1117: iload 71
    //   1119: iload 72
    //   1121: if_icmpgt -120 -> 1001
    //   1124: new 44	java/lang/String
    //   1127: dup
    //   1128: aload 70
    //   1130: invokespecial 54	java/lang/String:<init>	([C)V
    //   1133: invokevirtual 58	java/lang/String:intern	()Ljava/lang/String;
    //   1136: astore 79
    //   1138: aload_1
    //   1139: iload 69
    //   1141: aload 79
    //   1143: aastore
    //   1144: bipush 7
    //   1146: istore 80
    //   1148: ldc 72
    //   1150: invokevirtual 50	java/lang/String:toCharArray	()[C
    //   1153: astore 81
    //   1155: aload 81
    //   1157: arraylength
    //   1158: istore 82
    //   1160: iload 82
    //   1162: iconst_1
    //   1163: if_icmpgt +11189 -> 12352
    //   1166: iconst_0
    //   1167: istore 83
    //   1169: aload 81
    //   1171: astore 5
    //   1173: iload 83
    //   1175: istore 6
    //   1177: iload 82
    //   1179: istore 84
    //   1181: aload 81
    //   1183: astore 85
    //   1185: iload 84
    //   1187: istore 86
    //   1189: aload 85
    //   1191: iload 83
    //   1193: caload
    //   1194: istore 31
    //   1196: iload 6
    //   1198: iconst_5
    //   1199: irem
    //   1200: tableswitch	default:+32 -> 1232, 0:+9426->10626, 1:+9433->10633, 2:+9440->10640, 3:+9447->10647
    //   1233: isub
    //   1234: istore 87
    //   1236: iload 87
    //   1238: iload 31
    //   1240: ixor
    //   1241: i2c
    //   1242: istore 88
    //   1244: aload 85
    //   1246: iload 83
    //   1248: iload 88
    //   1250: castore
    //   1251: iload 6
    //   1253: iconst_1
    //   1254: iadd
    //   1255: istore 83
    //   1257: iload 86
    //   1259: ifne +18 -> 1277
    //   1262: aload 5
    //   1264: astore 85
    //   1266: iload 83
    //   1268: istore 89
    //   1270: iload 86
    //   1272: istore 83
    //   1274: goto -85 -> 1189
    //   1277: iload 86
    //   1279: istore 82
    //   1281: aload 5
    //   1283: astore 81
    //   1285: iload 82
    //   1287: iload 83
    //   1289: if_icmpgt -120 -> 1169
    //   1292: new 44	java/lang/String
    //   1295: dup
    //   1296: aload 81
    //   1298: invokespecial 54	java/lang/String:<init>	([C)V
    //   1301: invokevirtual 58	java/lang/String:intern	()Ljava/lang/String;
    //   1304: astore 90
    //   1306: aload_1
    //   1307: iload 80
    //   1309: aload 90
    //   1311: aastore
    //   1312: bipush 8
    //   1314: istore 91
    //   1316: ldc 74
    //   1318: invokevirtual 50	java/lang/String:toCharArray	()[C
    //   1321: astore 92
    //   1323: aload 92
    //   1325: arraylength
    //   1326: istore 93
    //   1328: iload 93
    //   1330: iconst_1
    //   1331: if_icmpgt +11015 -> 12346
    //   1334: iconst_0
    //   1335: istore 94
    //   1337: aload 92
    //   1339: astore 5
    //   1341: iload 94
    //   1343: istore 6
    //   1345: iload 93
    //   1347: istore 95
    //   1349: aload 92
    //   1351: astore 96
    //   1353: iload 95
    //   1355: istore 97
    //   1357: aload 96
    //   1359: iload 94
    //   1361: caload
    //   1362: istore 31
    //   1364: iload 6
    //   1366: iconst_5
    //   1367: irem
    //   1368: tableswitch	default:+32 -> 1400, 0:+9286->10654, 1:+9293->10661, 2:+9300->10668, 3:+9307->10675
    //   1401: isub
    //   1402: istore 98
    //   1404: iload 98
    //   1406: iload 31
    //   1408: ixor
    //   1409: i2c
    //   1410: istore 99
    //   1412: aload 96
    //   1414: iload 94
    //   1416: iload 99
    //   1418: castore
    //   1419: iload 6
    //   1421: iconst_1
    //   1422: iadd
    //   1423: istore 94
    //   1425: iload 97
    //   1427: ifne +18 -> 1445
    //   1430: aload 5
    //   1432: astore 96
    //   1434: iload 94
    //   1436: istore 100
    //   1438: iload 97
    //   1440: istore 94
    //   1442: goto -85 -> 1357
    //   1445: iload 97
    //   1447: istore 93
    //   1449: aload 5
    //   1451: astore 92
    //   1453: iload 93
    //   1455: iload 94
    //   1457: if_icmpgt -120 -> 1337
    //   1460: new 44	java/lang/String
    //   1463: dup
    //   1464: aload 92
    //   1466: invokespecial 54	java/lang/String:<init>	([C)V
    //   1469: invokevirtual 58	java/lang/String:intern	()Ljava/lang/String;
    //   1472: astore 101
    //   1474: aload_1
    //   1475: iload 91
    //   1477: aload 101
    //   1479: aastore
    //   1480: bipush 9
    //   1482: istore 102
    //   1484: ldc 76
    //   1486: invokevirtual 50	java/lang/String:toCharArray	()[C
    //   1489: astore 103
    //   1491: aload 103
    //   1493: arraylength
    //   1494: istore 104
    //   1496: iload 104
    //   1498: iconst_1
    //   1499: if_icmpgt +10841 -> 12340
    //   1502: iconst_0
    //   1503: istore 105
    //   1505: aload 103
    //   1507: astore 5
    //   1509: iload 105
    //   1511: istore 6
    //   1513: iload 104
    //   1515: istore 106
    //   1517: aload 103
    //   1519: astore 107
    //   1521: iload 106
    //   1523: istore 108
    //   1525: aload 107
    //   1527: iload 105
    //   1529: caload
    //   1530: istore 31
    //   1532: iload 6
    //   1534: iconst_5
    //   1535: irem
    //   1536: tableswitch	default:+32 -> 1568, 0:+9146->10682, 1:+9153->10689, 2:+9160->10696, 3:+9167->10703
    //   1569: isub
    //   1570: istore 109
    //   1572: iload 109
    //   1574: iload 31
    //   1576: ixor
    //   1577: i2c
    //   1578: istore 110
    //   1580: aload 107
    //   1582: iload 105
    //   1584: iload 110
    //   1586: castore
    //   1587: iload 6
    //   1589: iconst_1
    //   1590: iadd
    //   1591: istore 105
    //   1593: iload 108
    //   1595: ifne +18 -> 1613
    //   1598: aload 5
    //   1600: astore 107
    //   1602: iload 105
    //   1604: istore 111
    //   1606: iload 108
    //   1608: istore 105
    //   1610: goto -85 -> 1525
    //   1613: iload 108
    //   1615: istore 104
    //   1617: aload 5
    //   1619: astore 103
    //   1621: iload 104
    //   1623: iload 105
    //   1625: if_icmpgt -120 -> 1505
    //   1628: new 44	java/lang/String
    //   1631: dup
    //   1632: aload 103
    //   1634: invokespecial 54	java/lang/String:<init>	([C)V
    //   1637: invokevirtual 58	java/lang/String:intern	()Ljava/lang/String;
    //   1640: astore 112
    //   1642: aload_1
    //   1643: iload 102
    //   1645: aload 112
    //   1647: aastore
    //   1648: bipush 10
    //   1650: istore 113
    //   1652: ldc 78
    //   1654: invokevirtual 50	java/lang/String:toCharArray	()[C
    //   1657: astore 114
    //   1659: aload 114
    //   1661: arraylength
    //   1662: istore 115
    //   1664: iload 115
    //   1666: iconst_1
    //   1667: if_icmpgt +10667 -> 12334
    //   1670: iconst_0
    //   1671: istore 116
    //   1673: aload 114
    //   1675: astore 5
    //   1677: iload 116
    //   1679: istore 6
    //   1681: iload 115
    //   1683: istore 117
    //   1685: aload 114
    //   1687: astore 118
    //   1689: iload 117
    //   1691: istore 119
    //   1693: aload 118
    //   1695: iload 116
    //   1697: caload
    //   1698: istore 31
    //   1700: iload 6
    //   1702: iconst_5
    //   1703: irem
    //   1704: tableswitch	default:+32 -> 1736, 0:+9006->10710, 1:+9013->10717, 2:+9020->10724, 3:+9027->10731
    //   1737: isub
    //   1738: istore 120
    //   1740: iload 120
    //   1742: iload 31
    //   1744: ixor
    //   1745: i2c
    //   1746: istore 121
    //   1748: aload 118
    //   1750: iload 116
    //   1752: iload 121
    //   1754: castore
    //   1755: iload 6
    //   1757: iconst_1
    //   1758: iadd
    //   1759: istore 116
    //   1761: iload 119
    //   1763: ifne +18 -> 1781
    //   1766: aload 5
    //   1768: astore 118
    //   1770: iload 116
    //   1772: istore 122
    //   1774: iload 119
    //   1776: istore 116
    //   1778: goto -85 -> 1693
    //   1781: iload 119
    //   1783: istore 115
    //   1785: aload 5
    //   1787: astore 114
    //   1789: iload 115
    //   1791: iload 116
    //   1793: if_icmpgt -120 -> 1673
    //   1796: new 44	java/lang/String
    //   1799: dup
    //   1800: aload 114
    //   1802: invokespecial 54	java/lang/String:<init>	([C)V
    //   1805: invokevirtual 58	java/lang/String:intern	()Ljava/lang/String;
    //   1808: astore 123
    //   1810: aload_1
    //   1811: iload 113
    //   1813: aload 123
    //   1815: aastore
    //   1816: bipush 11
    //   1818: istore 124
    //   1820: ldc 80
    //   1822: invokevirtual 50	java/lang/String:toCharArray	()[C
    //   1825: astore 125
    //   1827: aload 125
    //   1829: arraylength
    //   1830: istore 126
    //   1832: iload 126
    //   1834: iconst_1
    //   1835: if_icmpgt +10493 -> 12328
    //   1838: iconst_0
    //   1839: istore 127
    //   1841: aload 125
    //   1843: astore 5
    //   1845: iload 127
    //   1847: istore 6
    //   1849: iload 126
    //   1851: istore 128
    //   1853: aload 125
    //   1855: astore 129
    //   1857: iload 128
    //   1859: istore 130
    //   1861: aload 129
    //   1863: iload 127
    //   1865: caload
    //   1866: istore 31
    //   1868: iload 6
    //   1870: iconst_5
    //   1871: irem
    //   1872: tableswitch	default:+32 -> 1904, 0:+8866->10738, 1:+8873->10745, 2:+8880->10752, 3:+8887->10759
    //   1905: isub
    //   1906: istore 131
    //   1908: iload 131
    //   1910: iload 31
    //   1912: ixor
    //   1913: i2c
    //   1914: istore 132
    //   1916: aload 129
    //   1918: iload 127
    //   1920: iload 132
    //   1922: castore
    //   1923: iload 6
    //   1925: iconst_1
    //   1926: iadd
    //   1927: istore 127
    //   1929: iload 130
    //   1931: ifne +18 -> 1949
    //   1934: aload 5
    //   1936: astore 129
    //   1938: iload 127
    //   1940: istore 133
    //   1942: iload 130
    //   1944: istore 127
    //   1946: goto -85 -> 1861
    //   1949: iload 130
    //   1951: istore 126
    //   1953: aload 5
    //   1955: astore 125
    //   1957: iload 126
    //   1959: iload 127
    //   1961: if_icmpgt -120 -> 1841
    //   1964: new 44	java/lang/String
    //   1967: dup
    //   1968: aload 125
    //   1970: invokespecial 54	java/lang/String:<init>	([C)V
    //   1973: invokevirtual 58	java/lang/String:intern	()Ljava/lang/String;
    //   1976: astore 134
    //   1978: aload_1
    //   1979: iload 124
    //   1981: aload 134
    //   1983: aastore
    //   1984: bipush 12
    //   1986: istore 135
    //   1988: ldc 82
    //   1990: invokevirtual 50	java/lang/String:toCharArray	()[C
    //   1993: astore 136
    //   1995: aload 136
    //   1997: arraylength
    //   1998: istore 137
    //   2000: iload 137
    //   2002: iconst_1
    //   2003: if_icmpgt +10319 -> 12322
    //   2006: iconst_0
    //   2007: istore 138
    //   2009: aload 136
    //   2011: astore 5
    //   2013: iload 138
    //   2015: istore 6
    //   2017: iload 137
    //   2019: istore 139
    //   2021: aload 136
    //   2023: astore 140
    //   2025: iload 139
    //   2027: istore 141
    //   2029: aload 140
    //   2031: iload 138
    //   2033: caload
    //   2034: istore 31
    //   2036: iload 6
    //   2038: iconst_5
    //   2039: irem
    //   2040: tableswitch	default:+32 -> 2072, 0:+8726->10766, 1:+8733->10773, 2:+8740->10780, 3:+8747->10787
    //   2073: isub
    //   2074: istore 142
    //   2076: iload 142
    //   2078: iload 31
    //   2080: ixor
    //   2081: i2c
    //   2082: istore 143
    //   2084: aload 140
    //   2086: iload 138
    //   2088: iload 143
    //   2090: castore
    //   2091: iload 6
    //   2093: iconst_1
    //   2094: iadd
    //   2095: istore 138
    //   2097: iload 141
    //   2099: ifne +18 -> 2117
    //   2102: aload 5
    //   2104: astore 140
    //   2106: iload 138
    //   2108: istore 144
    //   2110: iload 141
    //   2112: istore 138
    //   2114: goto -85 -> 2029
    //   2117: iload 141
    //   2119: istore 137
    //   2121: aload 5
    //   2123: astore 136
    //   2125: iload 137
    //   2127: iload 138
    //   2129: if_icmpgt -120 -> 2009
    //   2132: new 44	java/lang/String
    //   2135: dup
    //   2136: aload 136
    //   2138: invokespecial 54	java/lang/String:<init>	([C)V
    //   2141: invokevirtual 58	java/lang/String:intern	()Ljava/lang/String;
    //   2144: astore 145
    //   2146: aload_1
    //   2147: iload 135
    //   2149: aload 145
    //   2151: aastore
    //   2152: bipush 13
    //   2154: istore 146
    //   2156: ldc 84
    //   2158: invokevirtual 50	java/lang/String:toCharArray	()[C
    //   2161: astore 147
    //   2163: aload 147
    //   2165: arraylength
    //   2166: istore 148
    //   2168: iload 148
    //   2170: iconst_1
    //   2171: if_icmpgt +10145 -> 12316
    //   2174: iconst_0
    //   2175: istore 149
    //   2177: aload 147
    //   2179: astore 5
    //   2181: iload 149
    //   2183: istore 6
    //   2185: iload 148
    //   2187: istore 150
    //   2189: aload 147
    //   2191: astore 151
    //   2193: iload 150
    //   2195: istore 152
    //   2197: aload 151
    //   2199: iload 149
    //   2201: caload
    //   2202: istore 31
    //   2204: iload 6
    //   2206: iconst_5
    //   2207: irem
    //   2208: tableswitch	default:+32 -> 2240, 0:+8586->10794, 1:+8593->10801, 2:+8600->10808, 3:+8607->10815
    //   2241: isub
    //   2242: istore 153
    //   2244: iload 153
    //   2246: iload 31
    //   2248: ixor
    //   2249: i2c
    //   2250: istore 154
    //   2252: aload 151
    //   2254: iload 149
    //   2256: iload 154
    //   2258: castore
    //   2259: iload 6
    //   2261: iconst_1
    //   2262: iadd
    //   2263: istore 149
    //   2265: iload 152
    //   2267: ifne +18 -> 2285
    //   2270: aload 5
    //   2272: astore 151
    //   2274: iload 149
    //   2276: istore 155
    //   2278: iload 152
    //   2280: istore 149
    //   2282: goto -85 -> 2197
    //   2285: iload 152
    //   2287: istore 148
    //   2289: aload 5
    //   2291: astore 147
    //   2293: iload 148
    //   2295: iload 149
    //   2297: if_icmpgt -120 -> 2177
    //   2300: new 44	java/lang/String
    //   2303: dup
    //   2304: aload 147
    //   2306: invokespecial 54	java/lang/String:<init>	([C)V
    //   2309: invokevirtual 58	java/lang/String:intern	()Ljava/lang/String;
    //   2312: astore 156
    //   2314: aload_1
    //   2315: iload 146
    //   2317: aload 156
    //   2319: aastore
    //   2320: bipush 14
    //   2322: istore 157
    //   2324: ldc 86
    //   2326: invokevirtual 50	java/lang/String:toCharArray	()[C
    //   2329: astore 158
    //   2331: aload 158
    //   2333: arraylength
    //   2334: istore 159
    //   2336: iload 159
    //   2338: iconst_1
    //   2339: if_icmpgt +9971 -> 12310
    //   2342: iconst_0
    //   2343: istore 160
    //   2345: aload 158
    //   2347: astore 5
    //   2349: iload 160
    //   2351: istore 6
    //   2353: iload 159
    //   2355: istore 161
    //   2357: aload 158
    //   2359: astore 162
    //   2361: iload 161
    //   2363: istore 163
    //   2365: aload 162
    //   2367: iload 160
    //   2369: caload
    //   2370: istore 31
    //   2372: iload 6
    //   2374: iconst_5
    //   2375: irem
    //   2376: tableswitch	default:+32 -> 2408, 0:+8446->10822, 1:+8453->10829, 2:+8460->10836, 3:+8467->10843
    //   2409: isub
    //   2410: istore 164
    //   2412: iload 164
    //   2414: iload 31
    //   2416: ixor
    //   2417: i2c
    //   2418: istore 165
    //   2420: aload 162
    //   2422: iload 160
    //   2424: iload 165
    //   2426: castore
    //   2427: iload 6
    //   2429: iconst_1
    //   2430: iadd
    //   2431: istore 160
    //   2433: iload 163
    //   2435: ifne +18 -> 2453
    //   2438: aload 5
    //   2440: astore 162
    //   2442: iload 160
    //   2444: istore 166
    //   2446: iload 163
    //   2448: istore 160
    //   2450: goto -85 -> 2365
    //   2453: iload 163
    //   2455: istore 159
    //   2457: aload 5
    //   2459: astore 158
    //   2461: iload 159
    //   2463: iload 160
    //   2465: if_icmpgt -120 -> 2345
    //   2468: new 44	java/lang/String
    //   2471: dup
    //   2472: aload 158
    //   2474: invokespecial 54	java/lang/String:<init>	([C)V
    //   2477: invokevirtual 58	java/lang/String:intern	()Ljava/lang/String;
    //   2480: astore 167
    //   2482: aload_1
    //   2483: iload 157
    //   2485: aload 167
    //   2487: aastore
    //   2488: bipush 15
    //   2490: istore 168
    //   2492: ldc 88
    //   2494: invokevirtual 50	java/lang/String:toCharArray	()[C
    //   2497: astore 169
    //   2499: aload 169
    //   2501: arraylength
    //   2502: istore 170
    //   2504: iload 170
    //   2506: iconst_1
    //   2507: if_icmpgt +9797 -> 12304
    //   2510: iconst_0
    //   2511: istore 171
    //   2513: aload 169
    //   2515: astore 5
    //   2517: iload 171
    //   2519: istore 6
    //   2521: iload 170
    //   2523: istore 172
    //   2525: aload 169
    //   2527: astore 173
    //   2529: iload 172
    //   2531: istore 174
    //   2533: aload 173
    //   2535: iload 171
    //   2537: caload
    //   2538: istore 31
    //   2540: iload 6
    //   2542: iconst_5
    //   2543: irem
    //   2544: tableswitch	default:+32 -> 2576, 0:+8306->10850, 1:+8313->10857, 2:+8320->10864, 3:+8327->10871
    //   2577: isub
    //   2578: istore 175
    //   2580: iload 175
    //   2582: iload 31
    //   2584: ixor
    //   2585: i2c
    //   2586: istore 176
    //   2588: aload 173
    //   2590: iload 171
    //   2592: iload 176
    //   2594: castore
    //   2595: iload 6
    //   2597: iconst_1
    //   2598: iadd
    //   2599: istore 171
    //   2601: iload 174
    //   2603: ifne +18 -> 2621
    //   2606: aload 5
    //   2608: astore 173
    //   2610: iload 171
    //   2612: istore 177
    //   2614: iload 174
    //   2616: istore 171
    //   2618: goto -85 -> 2533
    //   2621: iload 174
    //   2623: istore 170
    //   2625: aload 5
    //   2627: astore 169
    //   2629: iload 170
    //   2631: iload 171
    //   2633: if_icmpgt -120 -> 2513
    //   2636: new 44	java/lang/String
    //   2639: dup
    //   2640: aload 169
    //   2642: invokespecial 54	java/lang/String:<init>	([C)V
    //   2645: invokevirtual 58	java/lang/String:intern	()Ljava/lang/String;
    //   2648: astore 178
    //   2650: aload_1
    //   2651: iload 168
    //   2653: aload 178
    //   2655: aastore
    //   2656: bipush 16
    //   2658: istore 179
    //   2660: ldc 90
    //   2662: invokevirtual 50	java/lang/String:toCharArray	()[C
    //   2665: astore 180
    //   2667: aload 180
    //   2669: arraylength
    //   2670: istore 181
    //   2672: iload 181
    //   2674: iconst_1
    //   2675: if_icmpgt +9623 -> 12298
    //   2678: iconst_0
    //   2679: istore 182
    //   2681: aload 180
    //   2683: astore 5
    //   2685: iload 182
    //   2687: istore 6
    //   2689: iload 181
    //   2691: istore 183
    //   2693: aload 180
    //   2695: astore 184
    //   2697: iload 183
    //   2699: istore 185
    //   2701: aload 184
    //   2703: iload 182
    //   2705: caload
    //   2706: istore 31
    //   2708: iload 6
    //   2710: iconst_5
    //   2711: irem
    //   2712: tableswitch	default:+32 -> 2744, 0:+8166->10878, 1:+8173->10885, 2:+8180->10892, 3:+8187->10899
    //   2745: isub
    //   2746: istore 186
    //   2748: iload 186
    //   2750: iload 31
    //   2752: ixor
    //   2753: i2c
    //   2754: istore 187
    //   2756: aload 184
    //   2758: iload 182
    //   2760: iload 187
    //   2762: castore
    //   2763: iload 6
    //   2765: iconst_1
    //   2766: iadd
    //   2767: istore 182
    //   2769: iload 185
    //   2771: ifne +18 -> 2789
    //   2774: aload 5
    //   2776: astore 184
    //   2778: iload 182
    //   2780: istore 188
    //   2782: iload 185
    //   2784: istore 182
    //   2786: goto -85 -> 2701
    //   2789: iload 185
    //   2791: istore 181
    //   2793: aload 5
    //   2795: astore 180
    //   2797: iload 181
    //   2799: iload 182
    //   2801: if_icmpgt -120 -> 2681
    //   2804: new 44	java/lang/String
    //   2807: dup
    //   2808: aload 180
    //   2810: invokespecial 54	java/lang/String:<init>	([C)V
    //   2813: invokevirtual 58	java/lang/String:intern	()Ljava/lang/String;
    //   2816: astore 189
    //   2818: aload_1
    //   2819: iload 179
    //   2821: aload 189
    //   2823: aastore
    //   2824: bipush 17
    //   2826: istore 190
    //   2828: ldc 92
    //   2830: invokevirtual 50	java/lang/String:toCharArray	()[C
    //   2833: astore 191
    //   2835: aload 191
    //   2837: arraylength
    //   2838: istore 192
    //   2840: iload 192
    //   2842: iconst_1
    //   2843: if_icmpgt +9449 -> 12292
    //   2846: iconst_0
    //   2847: istore 193
    //   2849: aload 191
    //   2851: astore 5
    //   2853: iload 193
    //   2855: istore 6
    //   2857: iload 192
    //   2859: istore 194
    //   2861: aload 191
    //   2863: astore 195
    //   2865: iload 194
    //   2867: istore 196
    //   2869: aload 195
    //   2871: iload 193
    //   2873: caload
    //   2874: istore 31
    //   2876: iload 6
    //   2878: iconst_5
    //   2879: irem
    //   2880: tableswitch	default:+32 -> 2912, 0:+8026->10906, 1:+8033->10913, 2:+8040->10920, 3:+8047->10927
    //   2913: isub
    //   2914: istore 197
    //   2916: iload 197
    //   2918: iload 31
    //   2920: ixor
    //   2921: i2c
    //   2922: istore 198
    //   2924: aload 195
    //   2926: iload 193
    //   2928: iload 198
    //   2930: castore
    //   2931: iload 6
    //   2933: iconst_1
    //   2934: iadd
    //   2935: istore 193
    //   2937: iload 196
    //   2939: ifne +18 -> 2957
    //   2942: aload 5
    //   2944: astore 195
    //   2946: iload 193
    //   2948: istore 199
    //   2950: iload 196
    //   2952: istore 193
    //   2954: goto -85 -> 2869
    //   2957: iload 196
    //   2959: istore 192
    //   2961: aload 5
    //   2963: astore 191
    //   2965: iload 192
    //   2967: iload 193
    //   2969: if_icmpgt -120 -> 2849
    //   2972: new 44	java/lang/String
    //   2975: dup
    //   2976: aload 191
    //   2978: invokespecial 54	java/lang/String:<init>	([C)V
    //   2981: invokevirtual 58	java/lang/String:intern	()Ljava/lang/String;
    //   2984: astore 200
    //   2986: aload_1
    //   2987: iload 190
    //   2989: aload 200
    //   2991: aastore
    //   2992: bipush 18
    //   2994: istore 201
    //   2996: ldc 94
    //   2998: invokevirtual 50	java/lang/String:toCharArray	()[C
    //   3001: astore 202
    //   3003: aload 202
    //   3005: arraylength
    //   3006: istore 203
    //   3008: iload 203
    //   3010: iconst_1
    //   3011: if_icmpgt +9275 -> 12286
    //   3014: iconst_0
    //   3015: istore 204
    //   3017: aload 202
    //   3019: astore 5
    //   3021: iload 204
    //   3023: istore 6
    //   3025: iload 203
    //   3027: istore 205
    //   3029: aload 202
    //   3031: astore 206
    //   3033: iload 205
    //   3035: istore 207
    //   3037: aload 206
    //   3039: iload 204
    //   3041: caload
    //   3042: istore 31
    //   3044: iload 6
    //   3046: iconst_5
    //   3047: irem
    //   3048: tableswitch	default:+32 -> 3080, 0:+7886->10934, 1:+7893->10941, 2:+7900->10948, 3:+7907->10955
    //   3081: isub
    //   3082: istore 208
    //   3084: iload 208
    //   3086: iload 31
    //   3088: ixor
    //   3089: i2c
    //   3090: istore 209
    //   3092: aload 206
    //   3094: iload 204
    //   3096: iload 209
    //   3098: castore
    //   3099: iload 6
    //   3101: iconst_1
    //   3102: iadd
    //   3103: istore 204
    //   3105: iload 207
    //   3107: ifne +18 -> 3125
    //   3110: aload 5
    //   3112: astore 206
    //   3114: iload 204
    //   3116: istore 210
    //   3118: iload 207
    //   3120: istore 204
    //   3122: goto -85 -> 3037
    //   3125: iload 207
    //   3127: istore 203
    //   3129: aload 5
    //   3131: astore 202
    //   3133: iload 203
    //   3135: iload 204
    //   3137: if_icmpgt -120 -> 3017
    //   3140: new 44	java/lang/String
    //   3143: dup
    //   3144: aload 202
    //   3146: invokespecial 54	java/lang/String:<init>	([C)V
    //   3149: invokevirtual 58	java/lang/String:intern	()Ljava/lang/String;
    //   3152: astore 211
    //   3154: aload_1
    //   3155: iload 201
    //   3157: aload 211
    //   3159: aastore
    //   3160: bipush 19
    //   3162: istore 212
    //   3164: ldc 96
    //   3166: invokevirtual 50	java/lang/String:toCharArray	()[C
    //   3169: astore 213
    //   3171: aload 213
    //   3173: arraylength
    //   3174: istore 214
    //   3176: iload 214
    //   3178: iconst_1
    //   3179: if_icmpgt +9101 -> 12280
    //   3182: iconst_0
    //   3183: istore 215
    //   3185: aload 213
    //   3187: astore 5
    //   3189: iload 215
    //   3191: istore 6
    //   3193: iload 214
    //   3195: istore 216
    //   3197: aload 213
    //   3199: astore 217
    //   3201: iload 216
    //   3203: istore 218
    //   3205: aload 217
    //   3207: iload 215
    //   3209: caload
    //   3210: istore 31
    //   3212: iload 6
    //   3214: iconst_5
    //   3215: irem
    //   3216: tableswitch	default:+32 -> 3248, 0:+7746->10962, 1:+7753->10969, 2:+7760->10976, 3:+7767->10983
    //   3249: isub
    //   3250: istore 219
    //   3252: iload 219
    //   3254: iload 31
    //   3256: ixor
    //   3257: i2c
    //   3258: istore 220
    //   3260: aload 217
    //   3262: iload 215
    //   3264: iload 220
    //   3266: castore
    //   3267: iload 6
    //   3269: iconst_1
    //   3270: iadd
    //   3271: istore 215
    //   3273: iload 218
    //   3275: ifne +18 -> 3293
    //   3278: aload 5
    //   3280: astore 217
    //   3282: iload 215
    //   3284: istore 221
    //   3286: iload 218
    //   3288: istore 215
    //   3290: goto -85 -> 3205
    //   3293: iload 218
    //   3295: istore 214
    //   3297: aload 5
    //   3299: astore 213
    //   3301: iload 214
    //   3303: iload 215
    //   3305: if_icmpgt -120 -> 3185
    //   3308: new 44	java/lang/String
    //   3311: dup
    //   3312: aload 213
    //   3314: invokespecial 54	java/lang/String:<init>	([C)V
    //   3317: invokevirtual 58	java/lang/String:intern	()Ljava/lang/String;
    //   3320: astore 222
    //   3322: aload_1
    //   3323: iload 212
    //   3325: aload 222
    //   3327: aastore
    //   3328: bipush 20
    //   3330: istore 223
    //   3332: ldc 98
    //   3334: invokevirtual 50	java/lang/String:toCharArray	()[C
    //   3337: astore 224
    //   3339: aload 224
    //   3341: arraylength
    //   3342: istore 225
    //   3344: iload 225
    //   3346: iconst_1
    //   3347: if_icmpgt +8927 -> 12274
    //   3350: iconst_0
    //   3351: istore 226
    //   3353: aload 224
    //   3355: astore 5
    //   3357: iload 226
    //   3359: istore 6
    //   3361: iload 225
    //   3363: istore 227
    //   3365: aload 224
    //   3367: astore 228
    //   3369: iload 227
    //   3371: istore 229
    //   3373: aload 228
    //   3375: iload 226
    //   3377: caload
    //   3378: istore 31
    //   3380: iload 6
    //   3382: iconst_5
    //   3383: irem
    //   3384: tableswitch	default:+32 -> 3416, 0:+7606->10990, 1:+7613->10997, 2:+7620->11004, 3:+7627->11011
    //   3417: isub
    //   3418: istore 230
    //   3420: iload 230
    //   3422: iload 31
    //   3424: ixor
    //   3425: i2c
    //   3426: istore 231
    //   3428: aload 228
    //   3430: iload 226
    //   3432: iload 231
    //   3434: castore
    //   3435: iload 6
    //   3437: iconst_1
    //   3438: iadd
    //   3439: istore 226
    //   3441: iload 229
    //   3443: ifne +18 -> 3461
    //   3446: aload 5
    //   3448: astore 228
    //   3450: iload 226
    //   3452: istore 232
    //   3454: iload 229
    //   3456: istore 226
    //   3458: goto -85 -> 3373
    //   3461: iload 229
    //   3463: istore 225
    //   3465: aload 5
    //   3467: astore 224
    //   3469: iload 225
    //   3471: iload 226
    //   3473: if_icmpgt -120 -> 3353
    //   3476: new 44	java/lang/String
    //   3479: dup
    //   3480: aload 224
    //   3482: invokespecial 54	java/lang/String:<init>	([C)V
    //   3485: invokevirtual 58	java/lang/String:intern	()Ljava/lang/String;
    //   3488: astore 233
    //   3490: aload_1
    //   3491: iload 223
    //   3493: aload 233
    //   3495: aastore
    //   3496: bipush 21
    //   3498: istore 234
    //   3500: ldc 100
    //   3502: invokevirtual 50	java/lang/String:toCharArray	()[C
    //   3505: astore 235
    //   3507: aload 235
    //   3509: arraylength
    //   3510: istore 236
    //   3512: iload 236
    //   3514: iconst_1
    //   3515: if_icmpgt +8753 -> 12268
    //   3518: iconst_0
    //   3519: istore 237
    //   3521: aload 235
    //   3523: astore 5
    //   3525: iload 237
    //   3527: istore 6
    //   3529: iload 236
    //   3531: istore 238
    //   3533: aload 235
    //   3535: astore 239
    //   3537: iload 238
    //   3539: istore 240
    //   3541: aload 239
    //   3543: iload 237
    //   3545: caload
    //   3546: istore 31
    //   3548: iload 6
    //   3550: iconst_5
    //   3551: irem
    //   3552: tableswitch	default:+32 -> 3584, 0:+7466->11018, 1:+7473->11025, 2:+7480->11032, 3:+7487->11039
    //   3585: isub
    //   3586: istore 241
    //   3588: iload 241
    //   3590: iload 31
    //   3592: ixor
    //   3593: i2c
    //   3594: istore 242
    //   3596: aload 239
    //   3598: iload 237
    //   3600: iload 242
    //   3602: castore
    //   3603: iload 6
    //   3605: iconst_1
    //   3606: iadd
    //   3607: istore 237
    //   3609: iload 240
    //   3611: ifne +18 -> 3629
    //   3614: aload 5
    //   3616: astore 239
    //   3618: iload 237
    //   3620: istore 243
    //   3622: iload 240
    //   3624: istore 237
    //   3626: goto -85 -> 3541
    //   3629: iload 240
    //   3631: istore 236
    //   3633: aload 5
    //   3635: astore 235
    //   3637: iload 236
    //   3639: iload 237
    //   3641: if_icmpgt -120 -> 3521
    //   3644: new 44	java/lang/String
    //   3647: dup
    //   3648: aload 235
    //   3650: invokespecial 54	java/lang/String:<init>	([C)V
    //   3653: invokevirtual 58	java/lang/String:intern	()Ljava/lang/String;
    //   3656: astore 244
    //   3658: aload_1
    //   3659: iload 234
    //   3661: aload 244
    //   3663: aastore
    //   3664: bipush 22
    //   3666: istore 245
    //   3668: ldc 102
    //   3670: invokevirtual 50	java/lang/String:toCharArray	()[C
    //   3673: astore 246
    //   3675: aload 246
    //   3677: arraylength
    //   3678: istore 247
    //   3680: iload 247
    //   3682: iconst_1
    //   3683: if_icmpgt +8579 -> 12262
    //   3686: iconst_0
    //   3687: istore 248
    //   3689: aload 246
    //   3691: astore 5
    //   3693: iload 248
    //   3695: istore 6
    //   3697: iload 247
    //   3699: istore 249
    //   3701: aload 246
    //   3703: astore 250
    //   3705: iload 249
    //   3707: istore 251
    //   3709: aload 250
    //   3711: iload 248
    //   3713: caload
    //   3714: istore 31
    //   3716: iload 6
    //   3718: iconst_5
    //   3719: irem
    //   3720: tableswitch	default:+32 -> 3752, 0:+7326->11046, 1:+7333->11053, 2:+7340->11060, 3:+7347->11067
    //   3753: isub
    //   3754: istore 252
    //   3756: iload 252
    //   3758: iload 31
    //   3760: ixor
    //   3761: i2c
    //   3762: istore 253
    //   3764: aload 250
    //   3766: iload 248
    //   3768: iload 253
    //   3770: castore
    //   3771: iload 6
    //   3773: iconst_1
    //   3774: iadd
    //   3775: istore 248
    //   3777: iload 251
    //   3779: ifne +18 -> 3797
    //   3782: aload 5
    //   3784: astore 250
    //   3786: iload 248
    //   3788: istore 254
    //   3790: iload 251
    //   3792: istore 248
    //   3794: goto -85 -> 3709
    //   3797: iload 251
    //   3799: istore 247
    //   3801: aload 5
    //   3803: astore 246
    //   3805: iload 247
    //   3807: iload 248
    //   3809: if_icmpgt -120 -> 3689
    //   3812: new 44	java/lang/String
    //   3815: dup
    //   3816: aload 246
    //   3818: invokespecial 54	java/lang/String:<init>	([C)V
    //   3821: invokevirtual 58	java/lang/String:intern	()Ljava/lang/String;
    //   3824: astore 255
    //   3826: aload_1
    //   3827: iload 245
    //   3829: aload 255
    //   3831: aastore
    //   3832: bipush 23
    //   3834: wide
    //   3838: ldc 104
    //   3840: invokevirtual 50	java/lang/String:toCharArray	()[C
    //   3843: wide
    //   3847: wide
    //   3851: arraylength
    //   3852: wide
    //   3856: wide
    //   3860: iconst_1
    //   3861: if_icmpgt +8393 -> 12254
    //   3864: iconst_0
    //   3865: wide
    //   3869: wide
    //   3873: astore 5
    //   3875: wide
    //   3879: istore 6
    //   3881: wide
    //   3885: wide
    //   3889: wide
    //   3893: wide
    //   3897: wide
    //   3901: wide
    //   3905: wide
    //   3909: wide
    //   3913: caload
    //   3914: istore 31
    //   3916: iload 6
    //   3918: iconst_5
    //   3919: irem
    //   3920: tableswitch	default:+32 -> 3952, 0:+7154->11074, 1:+7163->11083, 2:+7172->11092, 3:+7181->11101
    //   3953: isub
    //   3954: wide
    //   3958: wide
    //   3962: iload 31
    //   3964: ixor
    //   3965: i2c
    //   3966: wide
    //   3970: wide
    //   3974: wide
    //   3978: wide
    //   3982: castore
    //   3983: iload 6
    //   3985: iconst_1
    //   3986: iadd
    //   3987: wide
    //   3991: wide
    //   3995: ifne +28 -> 4023
    //   3998: aload 5
    //   4000: wide
    //   4004: wide
    //   4008: wide
    //   4012: wide
    //   4016: wide
    //   4020: goto -115 -> 3905
    //   4023: wide
    //   4027: wide
    //   4031: aload 5
    //   4033: wide
    //   4037: wide
    //   4041: wide
    //   4045: if_icmpgt -176 -> 3869
    //   4048: new 44	java/lang/String
    //   4051: dup
    //   4052: wide
    //   4056: invokespecial 54	java/lang/String:<init>	([C)V
    //   4059: invokevirtual 58	java/lang/String:intern	()Ljava/lang/String;
    //   4062: wide
    //   4066: aload_1
    //   4067: wide
    //   4071: wide
    //   4075: aastore
    //   4076: bipush 24
    //   4078: wide
    //   4082: ldc 106
    //   4084: invokevirtual 50	java/lang/String:toCharArray	()[C
    //   4087: wide
    //   4091: wide
    //   4095: arraylength
    //   4096: wide
    //   4100: wide
    //   4104: iconst_1
    //   4105: if_icmpgt +8141 -> 12246
    //   4108: iconst_0
    //   4109: wide
    //   4113: wide
    //   4117: astore 5
    //   4119: wide
    //   4123: istore 6
    //   4125: wide
    //   4129: wide
    //   4133: wide
    //   4137: wide
    //   4141: wide
    //   4145: wide
    //   4149: wide
    //   4153: wide
    //   4157: caload
    //   4158: istore 31
    //   4160: iload 6
    //   4162: iconst_5
    //   4163: irem
    //   4164: tableswitch	default:+32 -> 4196, 0:+6946->11110, 1:+6955->11119, 2:+6964->11128, 3:+6973->11137
    //   4197: isub
    //   4198: wide
    //   4202: wide
    //   4206: iload 31
    //   4208: ixor
    //   4209: i2c
    //   4210: wide
    //   4214: wide
    //   4218: wide
    //   4222: wide
    //   4226: castore
    //   4227: iload 6
    //   4229: iconst_1
    //   4230: iadd
    //   4231: wide
    //   4235: wide
    //   4239: ifne +28 -> 4267
    //   4242: aload 5
    //   4244: wide
    //   4248: wide
    //   4252: wide
    //   4256: wide
    //   4260: wide
    //   4264: goto -115 -> 4149
    //   4267: wide
    //   4271: wide
    //   4275: aload 5
    //   4277: wide
    //   4281: wide
    //   4285: wide
    //   4289: if_icmpgt -176 -> 4113
    //   4292: new 44	java/lang/String
    //   4295: dup
    //   4296: wide
    //   4300: invokespecial 54	java/lang/String:<init>	([C)V
    //   4303: invokevirtual 58	java/lang/String:intern	()Ljava/lang/String;
    //   4306: wide
    //   4310: aload_1
    //   4311: wide
    //   4315: wide
    //   4319: aastore
    //   4320: ldc 108
    //   4322: invokevirtual 50	java/lang/String:toCharArray	()[C
    //   4325: wide
    //   4329: wide
    //   4333: arraylength
    //   4334: wide
    //   4338: wide
    //   4342: iconst_1
    //   4343: if_icmpgt +7895 -> 12238
    //   4346: iconst_0
    //   4347: wide
    //   4351: wide
    //   4355: astore 5
    //   4357: wide
    //   4361: istore 6
    //   4363: wide
    //   4367: wide
    //   4371: wide
    //   4375: wide
    //   4379: wide
    //   4383: wide
    //   4387: wide
    //   4391: wide
    //   4395: caload
    //   4396: wide
    //   4400: iload 6
    //   4402: iconst_5
    //   4403: irem
    //   4404: tableswitch	default:+32 -> 4436, 0:+6742->11146, 1:+6751->11155, 2:+6760->11164, 3:+6769->11173
    //   4437: isub
    //   4438: wide
    //   4442: wide
    //   4446: wide
    //   4450: ixor
    //   4451: i2c
    //   4452: wide
    //   4456: wide
    //   4460: wide
    //   4464: wide
    //   4468: castore
    //   4469: iload 6
    //   4471: iconst_1
    //   4472: iadd
    //   4473: wide
    //   4477: wide
    //   4481: ifne +28 -> 4509
    //   4484: aload 5
    //   4486: wide
    //   4490: wide
    //   4494: wide
    //   4498: wide
    //   4502: wide
    //   4506: goto -119 -> 4387
    //   4509: wide
    //   4513: wide
    //   4517: aload 5
    //   4519: wide
    //   4523: wide
    //   4527: wide
    //   4531: if_icmpgt -180 -> 4351
    //   4534: new 44	java/lang/String
    //   4537: dup
    //   4538: wide
    //   4542: invokespecial 54	java/lang/String:<init>	([C)V
    //   4545: invokevirtual 58	java/lang/String:intern	()Ljava/lang/String;
    //   4548: wide
    //   4552: aload_1
    //   4553: bipush 25
    //   4555: wide
    //   4559: aastore
    //   4560: bipush 26
    //   4562: wide
    //   4566: ldc 110
    //   4568: invokevirtual 50	java/lang/String:toCharArray	()[C
    //   4571: wide
    //   4575: wide
    //   4579: arraylength
    //   4580: wide
    //   4584: wide
    //   4588: iconst_1
    //   4589: if_icmpgt +7641 -> 12230
    //   4592: iconst_0
    //   4593: wide
    //   4597: wide
    //   4601: astore 5
    //   4603: wide
    //   4607: istore 6
    //   4609: wide
    //   4613: wide
    //   4617: wide
    //   4621: wide
    //   4625: wide
    //   4629: wide
    //   4633: wide
    //   4637: wide
    //   4641: caload
    //   4642: istore 31
    //   4644: iload 6
    //   4646: iconst_5
    //   4647: irem
    //   4648: tableswitch	default:+32 -> 4680, 0:+6534->11182, 1:+6543->11191, 2:+6552->11200, 3:+6561->11209
    //   4681: isub
    //   4682: wide
    //   4686: wide
    //   4690: iload 31
    //   4692: ixor
    //   4693: i2c
    //   4694: wide
    //   4698: wide
    //   4702: wide
    //   4706: wide
    //   4710: castore
    //   4711: iload 6
    //   4713: iconst_1
    //   4714: iadd
    //   4715: wide
    //   4719: wide
    //   4723: ifne +28 -> 4751
    //   4726: aload 5
    //   4728: wide
    //   4732: wide
    //   4736: wide
    //   4740: wide
    //   4744: wide
    //   4748: goto -115 -> 4633
    //   4751: wide
    //   4755: wide
    //   4759: aload 5
    //   4761: wide
    //   4765: wide
    //   4769: wide
    //   4773: if_icmpgt -176 -> 4597
    //   4776: new 44	java/lang/String
    //   4779: dup
    //   4780: wide
    //   4784: invokespecial 54	java/lang/String:<init>	([C)V
    //   4787: invokevirtual 58	java/lang/String:intern	()Ljava/lang/String;
    //   4790: wide
    //   4794: aload_1
    //   4795: wide
    //   4799: wide
    //   4803: aastore
    //   4804: bipush 27
    //   4806: wide
    //   4810: ldc 112
    //   4812: invokevirtual 50	java/lang/String:toCharArray	()[C
    //   4815: wide
    //   4819: wide
    //   4823: arraylength
    //   4824: wide
    //   4828: wide
    //   4832: iconst_1
    //   4833: if_icmpgt +7389 -> 12222
    //   4836: iconst_0
    //   4837: wide
    //   4841: wide
    //   4845: astore 5
    //   4847: wide
    //   4851: istore 6
    //   4853: wide
    //   4857: wide
    //   4861: wide
    //   4865: wide
    //   4869: wide
    //   4873: wide
    //   4877: wide
    //   4881: wide
    //   4885: caload
    //   4886: istore 31
    //   4888: iload 6
    //   4890: iconst_5
    //   4891: irem
    //   4892: tableswitch	default:+32 -> 4924, 0:+6326->11218, 1:+6335->11227, 2:+6344->11236, 3:+6353->11245
    //   4925: isub
    //   4926: wide
    //   4930: wide
    //   4934: iload 31
    //   4936: ixor
    //   4937: i2c
    //   4938: wide
    //   4942: wide
    //   4946: wide
    //   4950: wide
    //   4954: castore
    //   4955: iload 6
    //   4957: iconst_1
    //   4958: iadd
    //   4959: wide
    //   4963: wide
    //   4967: ifne +28 -> 4995
    //   4970: aload 5
    //   4972: wide
    //   4976: wide
    //   4980: wide
    //   4984: wide
    //   4988: wide
    //   4992: goto -115 -> 4877
    //   4995: wide
    //   4999: wide
    //   5003: aload 5
    //   5005: wide
    //   5009: wide
    //   5013: wide
    //   5017: if_icmpgt -176 -> 4841
    //   5020: new 44	java/lang/String
    //   5023: dup
    //   5024: wide
    //   5028: invokespecial 54	java/lang/String:<init>	([C)V
    //   5031: invokevirtual 58	java/lang/String:intern	()Ljava/lang/String;
    //   5034: wide
    //   5038: aload_1
    //   5039: wide
    //   5043: wide
    //   5047: aastore
    //   5048: bipush 28
    //   5050: wide
    //   5054: ldc 114
    //   5056: invokevirtual 50	java/lang/String:toCharArray	()[C
    //   5059: wide
    //   5063: wide
    //   5067: arraylength
    //   5068: wide
    //   5072: wide
    //   5076: iconst_1
    //   5077: if_icmpgt +7137 -> 12214
    //   5080: iconst_0
    //   5081: wide
    //   5085: wide
    //   5089: astore 5
    //   5091: wide
    //   5095: istore 6
    //   5097: wide
    //   5101: wide
    //   5105: wide
    //   5109: wide
    //   5113: wide
    //   5117: wide
    //   5121: wide
    //   5125: wide
    //   5129: caload
    //   5130: istore 31
    //   5132: iload 6
    //   5134: iconst_5
    //   5135: irem
    //   5136: tableswitch	default:+32 -> 5168, 0:+6118->11254, 1:+6127->11263, 2:+6136->11272, 3:+6145->11281
    //   5169: isub
    //   5170: wide
    //   5174: wide
    //   5178: iload 31
    //   5180: ixor
    //   5181: i2c
    //   5182: wide
    //   5186: wide
    //   5190: wide
    //   5194: wide
    //   5198: castore
    //   5199: iload 6
    //   5201: iconst_1
    //   5202: iadd
    //   5203: wide
    //   5207: wide
    //   5211: ifne +28 -> 5239
    //   5214: aload 5
    //   5216: wide
    //   5220: wide
    //   5224: wide
    //   5228: wide
    //   5232: wide
    //   5236: goto -115 -> 5121
    //   5239: wide
    //   5243: wide
    //   5247: aload 5
    //   5249: wide
    //   5253: wide
    //   5257: wide
    //   5261: if_icmpgt -176 -> 5085
    //   5264: new 44	java/lang/String
    //   5267: dup
    //   5268: wide
    //   5272: invokespecial 54	java/lang/String:<init>	([C)V
    //   5275: invokevirtual 58	java/lang/String:intern	()Ljava/lang/String;
    //   5278: wide
    //   5282: aload_1
    //   5283: wide
    //   5287: wide
    //   5291: aastore
    //   5292: bipush 29
    //   5294: wide
    //   5298: ldc 116
    //   5300: invokevirtual 50	java/lang/String:toCharArray	()[C
    //   5303: wide
    //   5307: wide
    //   5311: arraylength
    //   5312: wide
    //   5316: wide
    //   5320: iconst_1
    //   5321: if_icmpgt +6885 -> 12206
    //   5324: iconst_0
    //   5325: wide
    //   5329: wide
    //   5333: astore 5
    //   5335: wide
    //   5339: istore 6
    //   5341: wide
    //   5345: wide
    //   5349: wide
    //   5353: wide
    //   5357: wide
    //   5361: wide
    //   5365: wide
    //   5369: wide
    //   5373: caload
    //   5374: istore 31
    //   5376: iload 6
    //   5378: iconst_5
    //   5379: irem
    //   5380: tableswitch	default:+32 -> 5412, 0:+5910->11290, 1:+5919->11299, 2:+5928->11308, 3:+5937->11317
    //   5413: isub
    //   5414: wide
    //   5418: wide
    //   5422: iload 31
    //   5424: ixor
    //   5425: i2c
    //   5426: wide
    //   5430: wide
    //   5434: wide
    //   5438: wide
    //   5442: castore
    //   5443: iload 6
    //   5445: iconst_1
    //   5446: iadd
    //   5447: wide
    //   5451: wide
    //   5455: ifne +28 -> 5483
    //   5458: aload 5
    //   5460: wide
    //   5464: wide
    //   5468: wide
    //   5472: wide
    //   5476: wide
    //   5480: goto -115 -> 5365
    //   5483: wide
    //   5487: wide
    //   5491: aload 5
    //   5493: wide
    //   5497: wide
    //   5501: wide
    //   5505: if_icmpgt -176 -> 5329
    //   5508: new 44	java/lang/String
    //   5511: dup
    //   5512: wide
    //   5516: invokespecial 54	java/lang/String:<init>	([C)V
    //   5519: invokevirtual 58	java/lang/String:intern	()Ljava/lang/String;
    //   5522: wide
    //   5526: aload_1
    //   5527: wide
    //   5531: wide
    //   5535: aastore
    //   5536: bipush 30
    //   5538: wide
    //   5542: ldc 118
    //   5544: invokevirtual 50	java/lang/String:toCharArray	()[C
    //   5547: wide
    //   5551: wide
    //   5555: arraylength
    //   5556: wide
    //   5560: wide
    //   5564: iconst_1
    //   5565: if_icmpgt +6633 -> 12198
    //   5568: iconst_0
    //   5569: wide
    //   5573: wide
    //   5577: astore 5
    //   5579: wide
    //   5583: istore 6
    //   5585: wide
    //   5589: wide
    //   5593: wide
    //   5597: wide
    //   5601: wide
    //   5605: wide
    //   5609: wide
    //   5613: wide
    //   5617: caload
    //   5618: istore 31
    //   5620: iload 6
    //   5622: iconst_5
    //   5623: irem
    //   5624: tableswitch	default:+32 -> 5656, 0:+5702->11326, 1:+5711->11335, 2:+5720->11344, 3:+5729->11353
    //   5657: isub
    //   5658: wide
    //   5662: wide
    //   5666: iload 31
    //   5668: ixor
    //   5669: i2c
    //   5670: wide
    //   5674: wide
    //   5678: wide
    //   5682: wide
    //   5686: castore
    //   5687: iload 6
    //   5689: iconst_1
    //   5690: iadd
    //   5691: wide
    //   5695: wide
    //   5699: ifne +28 -> 5727
    //   5702: aload 5
    //   5704: wide
    //   5708: wide
    //   5712: wide
    //   5716: wide
    //   5720: wide
    //   5724: goto -115 -> 5609
    //   5727: wide
    //   5731: wide
    //   5735: aload 5
    //   5737: wide
    //   5741: wide
    //   5745: wide
    //   5749: if_icmpgt -176 -> 5573
    //   5752: new 44	java/lang/String
    //   5755: dup
    //   5756: wide
    //   5760: invokespecial 54	java/lang/String:<init>	([C)V
    //   5763: invokevirtual 58	java/lang/String:intern	()Ljava/lang/String;
    //   5766: wide
    //   5770: aload_1
    //   5771: wide
    //   5775: wide
    //   5779: aastore
    //   5780: bipush 31
    //   5782: wide
    //   5786: ldc 120
    //   5788: invokevirtual 50	java/lang/String:toCharArray	()[C
    //   5791: wide
    //   5795: wide
    //   5799: arraylength
    //   5800: wide
    //   5804: wide
    //   5808: iconst_1
    //   5809: if_icmpgt +6381 -> 12190
    //   5812: iconst_0
    //   5813: wide
    //   5817: wide
    //   5821: astore 5
    //   5823: wide
    //   5827: istore 6
    //   5829: wide
    //   5833: wide
    //   5837: wide
    //   5841: wide
    //   5845: wide
    //   5849: wide
    //   5853: wide
    //   5857: wide
    //   5861: caload
    //   5862: istore 31
    //   5864: iload 6
    //   5866: iconst_5
    //   5867: irem
    //   5868: tableswitch	default:+32 -> 5900, 0:+5494->11362, 1:+5503->11371, 2:+5512->11380, 3:+5521->11389
    //   5901: isub
    //   5902: wide
    //   5906: wide
    //   5910: iload 31
    //   5912: ixor
    //   5913: i2c
    //   5914: wide
    //   5918: wide
    //   5922: wide
    //   5926: wide
    //   5930: castore
    //   5931: iload 6
    //   5933: iconst_1
    //   5934: iadd
    //   5935: wide
    //   5939: wide
    //   5943: ifne +28 -> 5971
    //   5946: aload 5
    //   5948: wide
    //   5952: wide
    //   5956: wide
    //   5960: wide
    //   5964: wide
    //   5968: goto -115 -> 5853
    //   5971: wide
    //   5975: wide
    //   5979: aload 5
    //   5981: wide
    //   5985: wide
    //   5989: wide
    //   5993: if_icmpgt -176 -> 5817
    //   5996: new 44	java/lang/String
    //   5999: dup
    //   6000: wide
    //   6004: invokespecial 54	java/lang/String:<init>	([C)V
    //   6007: invokevirtual 58	java/lang/String:intern	()Ljava/lang/String;
    //   6010: wide
    //   6014: aload_1
    //   6015: wide
    //   6019: wide
    //   6023: aastore
    //   6024: ldc 122
    //   6026: invokevirtual 50	java/lang/String:toCharArray	()[C
    //   6029: wide
    //   6033: wide
    //   6037: arraylength
    //   6038: wide
    //   6042: wide
    //   6046: iconst_1
    //   6047: if_icmpgt +6135 -> 12182
    //   6050: iconst_0
    //   6051: wide
    //   6055: wide
    //   6059: astore 5
    //   6061: wide
    //   6065: istore 6
    //   6067: wide
    //   6071: wide
    //   6075: wide
    //   6079: wide
    //   6083: wide
    //   6087: wide
    //   6091: wide
    //   6095: wide
    //   6099: caload
    //   6100: wide
    //   6104: iload 6
    //   6106: iconst_5
    //   6107: irem
    //   6108: tableswitch	default:+32 -> 6140, 0:+5290->11398, 1:+5299->11407, 2:+5308->11416, 3:+5317->11425
    //   6141: isub
    //   6142: wide
    //   6146: wide
    //   6150: wide
    //   6154: ixor
    //   6155: i2c
    //   6156: wide
    //   6160: wide
    //   6164: wide
    //   6168: wide
    //   6172: castore
    //   6173: iload 6
    //   6175: iconst_1
    //   6176: iadd
    //   6177: wide
    //   6181: wide
    //   6185: ifne +28 -> 6213
    //   6188: aload 5
    //   6190: wide
    //   6194: wide
    //   6198: wide
    //   6202: wide
    //   6206: wide
    //   6210: goto -119 -> 6091
    //   6213: wide
    //   6217: wide
    //   6221: aload 5
    //   6223: wide
    //   6227: wide
    //   6231: wide
    //   6235: if_icmpgt -180 -> 6055
    //   6238: new 44	java/lang/String
    //   6241: dup
    //   6242: wide
    //   6246: invokespecial 54	java/lang/String:<init>	([C)V
    //   6249: invokevirtual 58	java/lang/String:intern	()Ljava/lang/String;
    //   6252: wide
    //   6256: aload_1
    //   6257: bipush 32
    //   6259: wide
    //   6263: aastore
    //   6264: bipush 33
    //   6266: wide
    //   6270: ldc 124
    //   6272: invokevirtual 50	java/lang/String:toCharArray	()[C
    //   6275: wide
    //   6279: wide
    //   6283: arraylength
    //   6284: wide
    //   6288: wide
    //   6292: iconst_1
    //   6293: if_icmpgt +5881 -> 12174
    //   6296: iconst_0
    //   6297: wide
    //   6301: wide
    //   6305: astore 5
    //   6307: wide
    //   6311: istore 6
    //   6313: wide
    //   6317: wide
    //   6321: wide
    //   6325: wide
    //   6329: wide
    //   6333: wide
    //   6337: wide
    //   6341: wide
    //   6345: caload
    //   6346: istore 31
    //   6348: iload 6
    //   6350: iconst_5
    //   6351: irem
    //   6352: tableswitch	default:+32 -> 6384, 0:+5082->11434, 1:+5091->11443, 2:+5100->11452, 3:+5109->11461
    //   6385: isub
    //   6386: wide
    //   6390: wide
    //   6394: iload 31
    //   6396: ixor
    //   6397: i2c
    //   6398: wide
    //   6402: wide
    //   6406: wide
    //   6410: wide
    //   6414: castore
    //   6415: iload 6
    //   6417: iconst_1
    //   6418: iadd
    //   6419: wide
    //   6423: wide
    //   6427: ifne +28 -> 6455
    //   6430: aload 5
    //   6432: wide
    //   6436: wide
    //   6440: wide
    //   6444: wide
    //   6448: wide
    //   6452: goto -115 -> 6337
    //   6455: wide
    //   6459: wide
    //   6463: aload 5
    //   6465: wide
    //   6469: wide
    //   6473: wide
    //   6477: if_icmpgt -176 -> 6301
    //   6480: new 44	java/lang/String
    //   6483: dup
    //   6484: wide
    //   6488: invokespecial 54	java/lang/String:<init>	([C)V
    //   6491: invokevirtual 58	java/lang/String:intern	()Ljava/lang/String;
    //   6494: wide
    //   6498: aload_1
    //   6499: wide
    //   6503: wide
    //   6507: aastore
    //   6508: bipush 34
    //   6510: wide
    //   6514: ldc 126
    //   6516: invokevirtual 50	java/lang/String:toCharArray	()[C
    //   6519: wide
    //   6523: wide
    //   6527: arraylength
    //   6528: wide
    //   6532: wide
    //   6536: iconst_1
    //   6537: if_icmpgt +5629 -> 12166
    //   6540: iconst_0
    //   6541: wide
    //   6545: wide
    //   6549: astore 5
    //   6551: wide
    //   6555: istore 6
    //   6557: wide
    //   6561: wide
    //   6565: wide
    //   6569: wide
    //   6573: wide
    //   6577: wide
    //   6581: wide
    //   6585: wide
    //   6589: caload
    //   6590: istore 31
    //   6592: iload 6
    //   6594: iconst_5
    //   6595: irem
    //   6596: tableswitch	default:+32 -> 6628, 0:+4874->11470, 1:+4883->11479, 2:+4892->11488, 3:+4901->11497
    //   6629: isub
    //   6630: wide
    //   6634: wide
    //   6638: iload 31
    //   6640: ixor
    //   6641: i2c
    //   6642: wide
    //   6646: wide
    //   6650: wide
    //   6654: wide
    //   6658: castore
    //   6659: iload 6
    //   6661: iconst_1
    //   6662: iadd
    //   6663: wide
    //   6667: wide
    //   6671: ifne +28 -> 6699
    //   6674: aload 5
    //   6676: wide
    //   6680: wide
    //   6684: wide
    //   6688: wide
    //   6692: wide
    //   6696: goto -115 -> 6581
    //   6699: wide
    //   6703: wide
    //   6707: aload 5
    //   6709: wide
    //   6713: wide
    //   6717: wide
    //   6721: if_icmpgt -176 -> 6545
    //   6724: new 44	java/lang/String
    //   6727: dup
    //   6728: wide
    //   6732: invokespecial 54	java/lang/String:<init>	([C)V
    //   6735: invokevirtual 58	java/lang/String:intern	()Ljava/lang/String;
    //   6738: wide
    //   6742: aload_1
    //   6743: wide
    //   6747: wide
    //   6751: aastore
    //   6752: bipush 35
    //   6754: wide
    //   6758: ldc 128
    //   6760: invokevirtual 50	java/lang/String:toCharArray	()[C
    //   6763: wide
    //   6767: wide
    //   6771: arraylength
    //   6772: wide
    //   6776: wide
    //   6780: iconst_1
    //   6781: if_icmpgt +5377 -> 12158
    //   6784: iconst_0
    //   6785: wide
    //   6789: wide
    //   6793: astore 5
    //   6795: wide
    //   6799: istore 6
    //   6801: wide
    //   6805: wide
    //   6809: wide
    //   6813: wide
    //   6817: wide
    //   6821: wide
    //   6825: wide
    //   6829: wide
    //   6833: caload
    //   6834: istore 31
    //   6836: iload 6
    //   6838: iconst_5
    //   6839: irem
    //   6840: tableswitch	default:+32 -> 6872, 0:+4666->11506, 1:+4675->11515, 2:+4684->11524, 3:+4693->11533
    //   6873: isub
    //   6874: wide
    //   6878: wide
    //   6882: iload 31
    //   6884: ixor
    //   6885: i2c
    //   6886: wide
    //   6890: wide
    //   6894: wide
    //   6898: wide
    //   6902: castore
    //   6903: iload 6
    //   6905: iconst_1
    //   6906: iadd
    //   6907: wide
    //   6911: wide
    //   6915: ifne +28 -> 6943
    //   6918: aload 5
    //   6920: wide
    //   6924: wide
    //   6928: wide
    //   6932: wide
    //   6936: wide
    //   6940: goto -115 -> 6825
    //   6943: wide
    //   6947: wide
    //   6951: aload 5
    //   6953: wide
    //   6957: wide
    //   6961: wide
    //   6965: if_icmpgt -176 -> 6789
    //   6968: new 44	java/lang/String
    //   6971: dup
    //   6972: wide
    //   6976: invokespecial 54	java/lang/String:<init>	([C)V
    //   6979: invokevirtual 58	java/lang/String:intern	()Ljava/lang/String;
    //   6982: wide
    //   6986: aload_1
    //   6987: wide
    //   6991: wide
    //   6995: aastore
    //   6996: ldc 130
    //   6998: invokevirtual 50	java/lang/String:toCharArray	()[C
    //   7001: wide
    //   7005: wide
    //   7009: arraylength
    //   7010: wide
    //   7014: wide
    //   7018: iconst_1
    //   7019: if_icmpgt +5131 -> 12150
    //   7022: iconst_0
    //   7023: wide
    //   7027: wide
    //   7031: astore 5
    //   7033: wide
    //   7037: istore 6
    //   7039: wide
    //   7043: wide
    //   7047: wide
    //   7051: wide
    //   7055: wide
    //   7059: wide
    //   7063: wide
    //   7067: wide
    //   7071: caload
    //   7072: wide
    //   7076: iload 6
    //   7078: iconst_5
    //   7079: irem
    //   7080: tableswitch	default:+32 -> 7112, 0:+4462->11542, 1:+4471->11551, 2:+4480->11560, 3:+4489->11569
    //   7113: isub
    //   7114: wide
    //   7118: wide
    //   7122: wide
    //   7126: ixor
    //   7127: i2c
    //   7128: wide
    //   7132: wide
    //   7136: wide
    //   7140: wide
    //   7144: castore
    //   7145: iload 6
    //   7147: iconst_1
    //   7148: iadd
    //   7149: wide
    //   7153: wide
    //   7157: ifne +28 -> 7185
    //   7160: aload 5
    //   7162: wide
    //   7166: wide
    //   7170: wide
    //   7174: wide
    //   7178: wide
    //   7182: goto -119 -> 7063
    //   7185: wide
    //   7189: wide
    //   7193: aload 5
    //   7195: wide
    //   7199: wide
    //   7203: wide
    //   7207: if_icmpgt -180 -> 7027
    //   7210: new 44	java/lang/String
    //   7213: dup
    //   7214: wide
    //   7218: invokespecial 54	java/lang/String:<init>	([C)V
    //   7221: invokevirtual 58	java/lang/String:intern	()Ljava/lang/String;
    //   7224: wide
    //   7228: aload_1
    //   7229: bipush 36
    //   7231: wide
    //   7235: aastore
    //   7236: bipush 37
    //   7238: wide
    //   7242: ldc 132
    //   7244: invokevirtual 50	java/lang/String:toCharArray	()[C
    //   7247: wide
    //   7251: wide
    //   7255: arraylength
    //   7256: wide
    //   7260: wide
    //   7264: iconst_1
    //   7265: if_icmpgt +4877 -> 12142
    //   7268: iconst_0
    //   7269: wide
    //   7273: wide
    //   7277: astore 5
    //   7279: wide
    //   7283: istore 6
    //   7285: wide
    //   7289: wide
    //   7293: wide
    //   7297: wide
    //   7301: wide
    //   7305: wide
    //   7309: wide
    //   7313: wide
    //   7317: caload
    //   7318: istore 31
    //   7320: iload 6
    //   7322: iconst_5
    //   7323: irem
    //   7324: tableswitch	default:+32 -> 7356, 0:+4254->11578, 1:+4263->11587, 2:+4272->11596, 3:+4281->11605
    //   7357: isub
    //   7358: wide
    //   7362: wide
    //   7366: iload 31
    //   7368: ixor
    //   7369: i2c
    //   7370: wide
    //   7374: wide
    //   7378: wide
    //   7382: wide
    //   7386: castore
    //   7387: iload 6
    //   7389: iconst_1
    //   7390: iadd
    //   7391: wide
    //   7395: wide
    //   7399: ifne +28 -> 7427
    //   7402: aload 5
    //   7404: wide
    //   7408: wide
    //   7412: wide
    //   7416: wide
    //   7420: wide
    //   7424: goto -115 -> 7309
    //   7427: wide
    //   7431: wide
    //   7435: aload 5
    //   7437: wide
    //   7441: wide
    //   7445: wide
    //   7449: if_icmpgt -176 -> 7273
    //   7452: new 44	java/lang/String
    //   7455: dup
    //   7456: wide
    //   7460: invokespecial 54	java/lang/String:<init>	([C)V
    //   7463: invokevirtual 58	java/lang/String:intern	()Ljava/lang/String;
    //   7466: wide
    //   7470: aload_1
    //   7471: wide
    //   7475: wide
    //   7479: aastore
    //   7480: bipush 38
    //   7482: wide
    //   7486: ldc 134
    //   7488: invokevirtual 50	java/lang/String:toCharArray	()[C
    //   7491: wide
    //   7495: wide
    //   7499: arraylength
    //   7500: wide
    //   7504: wide
    //   7508: iconst_1
    //   7509: if_icmpgt +4625 -> 12134
    //   7512: iconst_0
    //   7513: wide
    //   7517: wide
    //   7521: astore 5
    //   7523: wide
    //   7527: istore 6
    //   7529: wide
    //   7533: wide
    //   7537: wide
    //   7541: wide
    //   7545: wide
    //   7549: wide
    //   7553: wide
    //   7557: wide
    //   7561: caload
    //   7562: istore 31
    //   7564: iload 6
    //   7566: iconst_5
    //   7567: irem
    //   7568: tableswitch	default:+32 -> 7600, 0:+4046->11614, 1:+4055->11623, 2:+4064->11632, 3:+4073->11641
    //   7601: isub
    //   7602: wide
    //   7606: wide
    //   7610: iload 31
    //   7612: ixor
    //   7613: i2c
    //   7614: wide
    //   7618: wide
    //   7622: wide
    //   7626: wide
    //   7630: castore
    //   7631: iload 6
    //   7633: iconst_1
    //   7634: iadd
    //   7635: wide
    //   7639: wide
    //   7643: ifne +28 -> 7671
    //   7646: aload 5
    //   7648: wide
    //   7652: wide
    //   7656: wide
    //   7660: wide
    //   7664: wide
    //   7668: goto -115 -> 7553
    //   7671: wide
    //   7675: wide
    //   7679: aload 5
    //   7681: wide
    //   7685: wide
    //   7689: wide
    //   7693: if_icmpgt -176 -> 7517
    //   7696: new 44	java/lang/String
    //   7699: dup
    //   7700: wide
    //   7704: invokespecial 54	java/lang/String:<init>	([C)V
    //   7707: invokevirtual 58	java/lang/String:intern	()Ljava/lang/String;
    //   7710: wide
    //   7714: aload_1
    //   7715: wide
    //   7719: wide
    //   7723: aastore
    //   7724: bipush 39
    //   7726: wide
    //   7730: ldc 136
    //   7732: invokevirtual 50	java/lang/String:toCharArray	()[C
    //   7735: wide
    //   7739: wide
    //   7743: arraylength
    //   7744: wide
    //   7748: wide
    //   7752: iconst_1
    //   7753: if_icmpgt +4373 -> 12126
    //   7756: iconst_0
    //   7757: wide
    //   7761: wide
    //   7765: astore 5
    //   7767: wide
    //   7771: istore 6
    //   7773: wide
    //   7777: wide
    //   7781: wide
    //   7785: wide
    //   7789: wide
    //   7793: wide
    //   7797: wide
    //   7801: wide
    //   7805: caload
    //   7806: istore 31
    //   7808: iload 6
    //   7810: iconst_5
    //   7811: irem
    //   7812: tableswitch	default:+32 -> 7844, 0:+3838->11650, 1:+3847->11659, 2:+3856->11668, 3:+3865->11677
    //   7845: isub
    //   7846: wide
    //   7850: wide
    //   7854: iload 31
    //   7856: ixor
    //   7857: i2c
    //   7858: wide
    //   7862: wide
    //   7866: wide
    //   7870: wide
    //   7874: castore
    //   7875: iload 6
    //   7877: iconst_1
    //   7878: iadd
    //   7879: wide
    //   7883: wide
    //   7887: ifne +28 -> 7915
    //   7890: aload 5
    //   7892: wide
    //   7896: wide
    //   7900: wide
    //   7904: wide
    //   7908: wide
    //   7912: goto -115 -> 7797
    //   7915: wide
    //   7919: wide
    //   7923: aload 5
    //   7925: wide
    //   7929: wide
    //   7933: wide
    //   7937: if_icmpgt -176 -> 7761
    //   7940: new 44	java/lang/String
    //   7943: dup
    //   7944: wide
    //   7948: invokespecial 54	java/lang/String:<init>	([C)V
    //   7951: invokevirtual 58	java/lang/String:intern	()Ljava/lang/String;
    //   7954: wide
    //   7958: aload_1
    //   7959: wide
    //   7963: wide
    //   7967: aastore
    //   7968: bipush 40
    //   7970: wide
    //   7974: ldc 138
    //   7976: invokevirtual 50	java/lang/String:toCharArray	()[C
    //   7979: wide
    //   7983: wide
    //   7987: arraylength
    //   7988: wide
    //   7992: wide
    //   7996: iconst_1
    //   7997: if_icmpgt +4121 -> 12118
    //   8000: iconst_0
    //   8001: wide
    //   8005: wide
    //   8009: astore 5
    //   8011: wide
    //   8015: istore 6
    //   8017: wide
    //   8021: wide
    //   8025: wide
    //   8029: wide
    //   8033: wide
    //   8037: wide
    //   8041: wide
    //   8045: wide
    //   8049: caload
    //   8050: istore 31
    //   8052: iload 6
    //   8054: iconst_5
    //   8055: irem
    //   8056: tableswitch	default:+32 -> 8088, 0:+3630->11686, 1:+3639->11695, 2:+3648->11704, 3:+3657->11713
    //   8089: isub
    //   8090: wide
    //   8094: wide
    //   8098: iload 31
    //   8100: ixor
    //   8101: i2c
    //   8102: wide
    //   8106: wide
    //   8110: wide
    //   8114: wide
    //   8118: castore
    //   8119: iload 6
    //   8121: iconst_1
    //   8122: iadd
    //   8123: wide
    //   8127: wide
    //   8131: ifne +28 -> 8159
    //   8134: aload 5
    //   8136: wide
    //   8140: wide
    //   8144: wide
    //   8148: wide
    //   8152: wide
    //   8156: goto -115 -> 8041
    //   8159: wide
    //   8163: wide
    //   8167: aload 5
    //   8169: wide
    //   8173: wide
    //   8177: wide
    //   8181: if_icmpgt -176 -> 8005
    //   8184: new 44	java/lang/String
    //   8187: dup
    //   8188: wide
    //   8192: invokespecial 54	java/lang/String:<init>	([C)V
    //   8195: invokevirtual 58	java/lang/String:intern	()Ljava/lang/String;
    //   8198: wide
    //   8202: aload_1
    //   8203: wide
    //   8207: wide
    //   8211: aastore
    //   8212: bipush 41
    //   8214: wide
    //   8218: ldc 140
    //   8220: invokevirtual 50	java/lang/String:toCharArray	()[C
    //   8223: wide
    //   8227: wide
    //   8231: arraylength
    //   8232: wide
    //   8236: wide
    //   8240: iconst_1
    //   8241: if_icmpgt +3869 -> 12110
    //   8244: iconst_0
    //   8245: wide
    //   8249: wide
    //   8253: astore 5
    //   8255: wide
    //   8259: istore 6
    //   8261: wide
    //   8265: wide
    //   8269: wide
    //   8273: wide
    //   8277: wide
    //   8281: wide
    //   8285: wide
    //   8289: wide
    //   8293: caload
    //   8294: istore 31
    //   8296: iload 6
    //   8298: iconst_5
    //   8299: irem
    //   8300: tableswitch	default:+32 -> 8332, 0:+3422->11722, 1:+3431->11731, 2:+3440->11740, 3:+3449->11749
    //   8333: isub
    //   8334: wide
    //   8338: wide
    //   8342: iload 31
    //   8344: ixor
    //   8345: i2c
    //   8346: wide
    //   8350: wide
    //   8354: wide
    //   8358: wide
    //   8362: castore
    //   8363: iload 6
    //   8365: iconst_1
    //   8366: iadd
    //   8367: wide
    //   8371: wide
    //   8375: ifne +28 -> 8403
    //   8378: aload 5
    //   8380: wide
    //   8384: wide
    //   8388: wide
    //   8392: wide
    //   8396: wide
    //   8400: goto -115 -> 8285
    //   8403: wide
    //   8407: wide
    //   8411: aload 5
    //   8413: wide
    //   8417: wide
    //   8421: wide
    //   8425: if_icmpgt -176 -> 8249
    //   8428: new 44	java/lang/String
    //   8431: dup
    //   8432: wide
    //   8436: invokespecial 54	java/lang/String:<init>	([C)V
    //   8439: invokevirtual 58	java/lang/String:intern	()Ljava/lang/String;
    //   8442: wide
    //   8446: aload_1
    //   8447: wide
    //   8451: wide
    //   8455: aastore
    //   8456: bipush 42
    //   8458: wide
    //   8462: ldc 142
    //   8464: invokevirtual 50	java/lang/String:toCharArray	()[C
    //   8467: wide
    //   8471: wide
    //   8475: arraylength
    //   8476: wide
    //   8480: wide
    //   8484: iconst_1
    //   8485: if_icmpgt +3617 -> 12102
    //   8488: iconst_0
    //   8489: wide
    //   8493: wide
    //   8497: astore 5
    //   8499: wide
    //   8503: istore 6
    //   8505: wide
    //   8509: wide
    //   8513: wide
    //   8517: wide
    //   8521: wide
    //   8525: wide
    //   8529: wide
    //   8533: wide
    //   8537: caload
    //   8538: istore 31
    //   8540: iload 6
    //   8542: iconst_5
    //   8543: irem
    //   8544: tableswitch	default:+32 -> 8576, 0:+3214->11758, 1:+3223->11767, 2:+3232->11776, 3:+3241->11785
    //   8577: isub
    //   8578: wide
    //   8582: wide
    //   8586: iload 31
    //   8588: ixor
    //   8589: i2c
    //   8590: wide
    //   8594: wide
    //   8598: wide
    //   8602: wide
    //   8606: castore
    //   8607: iload 6
    //   8609: iconst_1
    //   8610: iadd
    //   8611: wide
    //   8615: wide
    //   8619: ifne +28 -> 8647
    //   8622: aload 5
    //   8624: wide
    //   8628: wide
    //   8632: wide
    //   8636: wide
    //   8640: wide
    //   8644: goto -115 -> 8529
    //   8647: wide
    //   8651: wide
    //   8655: aload 5
    //   8657: wide
    //   8661: wide
    //   8665: wide
    //   8669: if_icmpgt -176 -> 8493
    //   8672: new 44	java/lang/String
    //   8675: dup
    //   8676: wide
    //   8680: invokespecial 54	java/lang/String:<init>	([C)V
    //   8683: invokevirtual 58	java/lang/String:intern	()Ljava/lang/String;
    //   8686: wide
    //   8690: aload_1
    //   8691: wide
    //   8695: wide
    //   8699: aastore
    //   8700: bipush 43
    //   8702: wide
    //   8706: ldc 144
    //   8708: invokevirtual 50	java/lang/String:toCharArray	()[C
    //   8711: wide
    //   8715: wide
    //   8719: arraylength
    //   8720: wide
    //   8724: wide
    //   8728: iconst_1
    //   8729: if_icmpgt +3365 -> 12094
    //   8732: iconst_0
    //   8733: wide
    //   8737: wide
    //   8741: astore 5
    //   8743: wide
    //   8747: istore 6
    //   8749: wide
    //   8753: wide
    //   8757: wide
    //   8761: wide
    //   8765: wide
    //   8769: wide
    //   8773: wide
    //   8777: wide
    //   8781: caload
    //   8782: istore 31
    //   8784: iload 6
    //   8786: iconst_5
    //   8787: irem
    //   8788: tableswitch	default:+32 -> 8820, 0:+3006->11794, 1:+3015->11803, 2:+3024->11812, 3:+3033->11821
    //   8821: isub
    //   8822: wide
    //   8826: wide
    //   8830: iload 31
    //   8832: ixor
    //   8833: i2c
    //   8834: wide
    //   8838: wide
    //   8842: wide
    //   8846: wide
    //   8850: castore
    //   8851: iload 6
    //   8853: iconst_1
    //   8854: iadd
    //   8855: wide
    //   8859: wide
    //   8863: ifne +28 -> 8891
    //   8866: aload 5
    //   8868: wide
    //   8872: wide
    //   8876: wide
    //   8880: wide
    //   8884: wide
    //   8888: goto -115 -> 8773
    //   8891: wide
    //   8895: wide
    //   8899: aload 5
    //   8901: wide
    //   8905: wide
    //   8909: wide
    //   8913: if_icmpgt -176 -> 8737
    //   8916: new 44	java/lang/String
    //   8919: dup
    //   8920: wide
    //   8924: invokespecial 54	java/lang/String:<init>	([C)V
    //   8927: invokevirtual 58	java/lang/String:intern	()Ljava/lang/String;
    //   8930: wide
    //   8934: aload_1
    //   8935: wide
    //   8939: wide
    //   8943: aastore
    //   8944: bipush 44
    //   8946: wide
    //   8950: ldc 146
    //   8952: invokevirtual 50	java/lang/String:toCharArray	()[C
    //   8955: wide
    //   8959: wide
    //   8963: arraylength
    //   8964: wide
    //   8968: wide
    //   8972: iconst_1
    //   8973: if_icmpgt +3113 -> 12086
    //   8976: iconst_0
    //   8977: wide
    //   8981: wide
    //   8985: astore 5
    //   8987: wide
    //   8991: istore 6
    //   8993: wide
    //   8997: wide
    //   9001: wide
    //   9005: wide
    //   9009: wide
    //   9013: wide
    //   9017: wide
    //   9021: wide
    //   9025: caload
    //   9026: istore 31
    //   9028: iload 6
    //   9030: iconst_5
    //   9031: irem
    //   9032: tableswitch	default:+32 -> 9064, 0:+2798->11830, 1:+2807->11839, 2:+2816->11848, 3:+2825->11857
    //   9065: isub
    //   9066: wide
    //   9070: wide
    //   9074: iload 31
    //   9076: ixor
    //   9077: i2c
    //   9078: wide
    //   9082: wide
    //   9086: wide
    //   9090: wide
    //   9094: castore
    //   9095: iload 6
    //   9097: iconst_1
    //   9098: iadd
    //   9099: wide
    //   9103: wide
    //   9107: ifne +28 -> 9135
    //   9110: aload 5
    //   9112: wide
    //   9116: wide
    //   9120: wide
    //   9124: wide
    //   9128: wide
    //   9132: goto -115 -> 9017
    //   9135: wide
    //   9139: wide
    //   9143: aload 5
    //   9145: wide
    //   9149: wide
    //   9153: wide
    //   9157: if_icmpgt -176 -> 8981
    //   9160: new 44	java/lang/String
    //   9163: dup
    //   9164: wide
    //   9168: invokespecial 54	java/lang/String:<init>	([C)V
    //   9171: invokevirtual 58	java/lang/String:intern	()Ljava/lang/String;
    //   9174: wide
    //   9178: aload_1
    //   9179: wide
    //   9183: wide
    //   9187: aastore
    //   9188: bipush 45
    //   9190: wide
    //   9194: ldc 148
    //   9196: invokevirtual 50	java/lang/String:toCharArray	()[C
    //   9199: wide
    //   9203: wide
    //   9207: arraylength
    //   9208: wide
    //   9212: wide
    //   9216: iconst_1
    //   9217: if_icmpgt +2861 -> 12078
    //   9220: iconst_0
    //   9221: wide
    //   9225: wide
    //   9229: astore 5
    //   9231: wide
    //   9235: istore 6
    //   9237: wide
    //   9241: wide
    //   9245: wide
    //   9249: wide
    //   9253: wide
    //   9257: wide
    //   9261: wide
    //   9265: wide
    //   9269: caload
    //   9270: istore 31
    //   9272: iload 6
    //   9274: iconst_5
    //   9275: irem
    //   9276: tableswitch	default:+32 -> 9308, 0:+2590->11866, 1:+2599->11875, 2:+2608->11884, 3:+2617->11893
    //   9309: isub
    //   9310: wide
    //   9314: wide
    //   9318: iload 31
    //   9320: ixor
    //   9321: i2c
    //   9322: wide
    //   9326: wide
    //   9330: wide
    //   9334: wide
    //   9338: castore
    //   9339: iload 6
    //   9341: iconst_1
    //   9342: iadd
    //   9343: wide
    //   9347: wide
    //   9351: ifne +28 -> 9379
    //   9354: aload 5
    //   9356: wide
    //   9360: wide
    //   9364: wide
    //   9368: wide
    //   9372: wide
    //   9376: goto -115 -> 9261
    //   9379: wide
    //   9383: wide
    //   9387: aload 5
    //   9389: wide
    //   9393: wide
    //   9397: wide
    //   9401: if_icmpgt -176 -> 9225
    //   9404: new 44	java/lang/String
    //   9407: dup
    //   9408: wide
    //   9412: invokespecial 54	java/lang/String:<init>	([C)V
    //   9415: invokevirtual 58	java/lang/String:intern	()Ljava/lang/String;
    //   9418: wide
    //   9422: aload_1
    //   9423: wide
    //   9427: wide
    //   9431: aastore
    //   9432: bipush 46
    //   9434: wide
    //   9438: ldc 150
    //   9440: invokevirtual 50	java/lang/String:toCharArray	()[C
    //   9443: wide
    //   9447: wide
    //   9451: arraylength
    //   9452: wide
    //   9456: wide
    //   9460: iconst_1
    //   9461: if_icmpgt +2609 -> 12070
    //   9464: iconst_0
    //   9465: wide
    //   9469: wide
    //   9473: astore 5
    //   9475: wide
    //   9479: istore 6
    //   9481: wide
    //   9485: wide
    //   9489: wide
    //   9493: wide
    //   9497: wide
    //   9501: wide
    //   9505: wide
    //   9509: wide
    //   9513: caload
    //   9514: istore 31
    //   9516: iload 6
    //   9518: iconst_5
    //   9519: irem
    //   9520: tableswitch	default:+32 -> 9552, 0:+2382->11902, 1:+2391->11911, 2:+2400->11920, 3:+2409->11929
    //   9553: isub
    //   9554: wide
    //   9558: wide
    //   9562: iload 31
    //   9564: ixor
    //   9565: i2c
    //   9566: wide
    //   9570: wide
    //   9574: wide
    //   9578: wide
    //   9582: castore
    //   9583: iload 6
    //   9585: iconst_1
    //   9586: iadd
    //   9587: wide
    //   9591: wide
    //   9595: ifne +28 -> 9623
    //   9598: aload 5
    //   9600: wide
    //   9604: wide
    //   9608: wide
    //   9612: wide
    //   9616: wide
    //   9620: goto -115 -> 9505
    //   9623: wide
    //   9627: wide
    //   9631: aload 5
    //   9633: wide
    //   9637: wide
    //   9641: wide
    //   9645: if_icmpgt -176 -> 9469
    //   9648: new 44	java/lang/String
    //   9651: dup
    //   9652: wide
    //   9656: invokespecial 54	java/lang/String:<init>	([C)V
    //   9659: invokevirtual 58	java/lang/String:intern	()Ljava/lang/String;
    //   9662: wide
    //   9666: aload_1
    //   9667: wide
    //   9671: wide
    //   9675: aastore
    //   9676: bipush 47
    //   9678: wide
    //   9682: ldc 152
    //   9684: invokevirtual 50	java/lang/String:toCharArray	()[C
    //   9687: wide
    //   9691: wide
    //   9695: arraylength
    //   9696: wide
    //   9700: wide
    //   9704: iconst_1
    //   9705: if_icmpgt +2357 -> 12062
    //   9708: iconst_0
    //   9709: wide
    //   9713: wide
    //   9717: astore 5
    //   9719: wide
    //   9723: istore 6
    //   9725: wide
    //   9729: wide
    //   9733: wide
    //   9737: wide
    //   9741: wide
    //   9745: wide
    //   9749: wide
    //   9753: wide
    //   9757: caload
    //   9758: istore 31
    //   9760: iload 6
    //   9762: iconst_5
    //   9763: irem
    //   9764: tableswitch	default:+32 -> 9796, 0:+2174->11938, 1:+2183->11947, 2:+2192->11956, 3:+2201->11965
    //   9797: isub
    //   9798: wide
    //   9802: wide
    //   9806: iload 31
    //   9808: ixor
    //   9809: i2c
    //   9810: wide
    //   9814: wide
    //   9818: wide
    //   9822: wide
    //   9826: castore
    //   9827: iload 6
    //   9829: iconst_1
    //   9830: iadd
    //   9831: wide
    //   9835: wide
    //   9839: ifne +28 -> 9867
    //   9842: aload 5
    //   9844: wide
    //   9848: wide
    //   9852: wide
    //   9856: wide
    //   9860: wide
    //   9864: goto -115 -> 9749
    //   9867: wide
    //   9871: wide
    //   9875: aload 5
    //   9877: wide
    //   9881: wide
    //   9885: wide
    //   9889: if_icmpgt -176 -> 9713
    //   9892: new 44	java/lang/String
    //   9895: dup
    //   9896: wide
    //   9900: invokespecial 54	java/lang/String:<init>	([C)V
    //   9903: invokevirtual 58	java/lang/String:intern	()Ljava/lang/String;
    //   9906: wide
    //   9910: aload_1
    //   9911: wide
    //   9915: wide
    //   9919: aastore
    //   9920: bipush 48
    //   9922: wide
    //   9926: ldc 154
    //   9928: invokevirtual 50	java/lang/String:toCharArray	()[C
    //   9931: wide
    //   9935: wide
    //   9939: arraylength
    //   9940: wide
    //   9944: wide
    //   9948: iconst_1
    //   9949: if_icmpgt +2105 -> 12054
    //   9952: iconst_0
    //   9953: wide
    //   9957: wide
    //   9961: astore 5
    //   9963: wide
    //   9967: istore 6
    //   9969: wide
    //   9973: wide
    //   9977: wide
    //   9981: wide
    //   9985: wide
    //   9989: wide
    //   9993: wide
    //   9997: wide
    //   10001: caload
    //   10002: istore 31
    //   10004: iload 6
    //   10006: iconst_5
    //   10007: irem
    //   10008: tableswitch	default:+32 -> 10040, 0:+1966->11974, 1:+1975->11983, 2:+1984->11992, 3:+1993->12001
    //   10041: isub
    //   10042: wide
    //   10046: wide
    //   10050: iload 31
    //   10052: ixor
    //   10053: i2c
    //   10054: wide
    //   10058: wide
    //   10062: wide
    //   10066: wide
    //   10070: castore
    //   10071: iload 6
    //   10073: iconst_1
    //   10074: iadd
    //   10075: wide
    //   10079: wide
    //   10083: ifne +28 -> 10111
    //   10086: aload 5
    //   10088: wide
    //   10092: wide
    //   10096: wide
    //   10100: wide
    //   10104: wide
    //   10108: goto -115 -> 9993
    //   10111: wide
    //   10115: wide
    //   10119: aload 5
    //   10121: wide
    //   10125: wide
    //   10129: wide
    //   10133: if_icmpgt -176 -> 9957
    //   10136: new 44	java/lang/String
    //   10139: dup
    //   10140: wide
    //   10144: invokespecial 54	java/lang/String:<init>	([C)V
    //   10147: invokevirtual 58	java/lang/String:intern	()Ljava/lang/String;
    //   10150: wide
    //   10154: aload_1
    //   10155: wide
    //   10159: wide
    //   10163: aastore
    //   10164: bipush 49
    //   10166: wide
    //   10170: ldc 156
    //   10172: invokevirtual 50	java/lang/String:toCharArray	()[C
    //   10175: wide
    //   10179: wide
    //   10183: arraylength
    //   10184: wide
    //   10188: wide
    //   10192: iconst_1
    //   10193: if_icmpgt +1853 -> 12046
    //   10196: iconst_0
    //   10197: wide
    //   10201: wide
    //   10205: astore 5
    //   10207: wide
    //   10211: istore 6
    //   10213: wide
    //   10217: wide
    //   10221: wide
    //   10225: wide
    //   10229: wide
    //   10233: wide
    //   10237: wide
    //   10241: wide
    //   10245: caload
    //   10246: istore 31
    //   10248: iload 6
    //   10250: iconst_5
    //   10251: irem
    //   10252: tableswitch	default:+32 -> 10284, 0:+1758->12010, 1:+1767->12019, 2:+1776->12028, 3:+1785->12037
    //   10285: isub
    //   10286: wide
    //   10290: wide
    //   10294: iload 31
    //   10296: ixor
    //   10297: i2c
    //   10298: wide
    //   10302: wide
    //   10306: wide
    //   10310: wide
    //   10314: castore
    //   10315: iload 6
    //   10317: iconst_1
    //   10318: iadd
    //   10319: wide
    //   10323: wide
    //   10327: ifne +28 -> 10355
    //   10330: aload 5
    //   10332: wide
    //   10336: wide
    //   10340: wide
    //   10344: wide
    //   10348: wide
    //   10352: goto -115 -> 10237
    //   10355: wide
    //   10359: wide
    //   10363: aload 5
    //   10365: wide
    //   10369: wide
    //   10373: wide
    //   10377: if_icmpgt -176 -> 10201
    //   10380: new 44	java/lang/String
    //   10383: dup
    //   10384: wide
    //   10388: invokespecial 54	java/lang/String:<init>	([C)V
    //   10391: invokevirtual 58	java/lang/String:intern	()Ljava/lang/String;
    //   10394: wide
    //   10398: aload_1
    //   10399: wide
    //   10403: wide
    //   10407: aastore
    //   10408: aload_1
    //   10409: putstatic 158	com/skyhookwireless/wps/_sdkkc:z	[Ljava/lang/String;
    //   10412: ldc 2
    //   10414: invokevirtual 164	java/lang/Class:desiredAssertionStatus	()Z
    //   10417: ifne +8 -> 10425
    //   10420: iload_0
    //   10421: putstatic 166	com/skyhookwireless/wps/_sdkkc:_sdkq	Z
    //   10424: return
    //   10425: iconst_0
    //   10426: istore_0
    //   10427: goto -7 -> 10420
    //   10430: bipush 106
    //   10432: istore 11
    //   10434: goto -10346 -> 88
    //   10437: bipush 36
    //   10439: istore 11
    //   10441: goto -10353 -> 88
    //   10444: bipush 25
    //   10446: istore 11
    //   10448: goto -10360 -> 88
    //   10451: bipush 32
    //   10453: istore 11
    //   10455: goto -10367 -> 88
    //   10458: bipush 106
    //   10460: istore 20
    //   10462: goto -10218 -> 244
    //   10465: bipush 36
    //   10467: istore 20
    //   10469: goto -10225 -> 244
    //   10472: bipush 25
    //   10474: istore 20
    //   10476: goto -10232 -> 244
    //   10479: bipush 32
    //   10481: istore 20
    //   10483: goto -10239 -> 244
    //   10486: bipush 106
    //   10488: istore 32
    //   10490: goto -10082 -> 408
    //   10493: bipush 36
    //   10495: istore 32
    //   10497: goto -10089 -> 408
    //   10500: bipush 25
    //   10502: istore 32
    //   10504: goto -10096 -> 408
    //   10507: bipush 32
    //   10509: istore 32
    //   10511: goto -10103 -> 408
    //   10514: bipush 106
    //   10516: istore 43
    //   10518: goto -9946 -> 572
    //   10521: bipush 36
    //   10523: istore 43
    //   10525: goto -9953 -> 572
    //   10528: bipush 25
    //   10530: istore 43
    //   10532: goto -9960 -> 572
    //   10535: bipush 32
    //   10537: istore 43
    //   10539: goto -9967 -> 572
    //   10542: bipush 106
    //   10544: istore 54
    //   10546: goto -9810 -> 736
    //   10549: bipush 36
    //   10551: istore 54
    //   10553: goto -9817 -> 736
    //   10556: bipush 25
    //   10558: istore 54
    //   10560: goto -9824 -> 736
    //   10563: bipush 32
    //   10565: istore 54
    //   10567: goto -9831 -> 736
    //   10570: bipush 106
    //   10572: istore 65
    //   10574: goto -9674 -> 900
    //   10577: bipush 36
    //   10579: istore 65
    //   10581: goto -9681 -> 900
    //   10584: bipush 25
    //   10586: istore 65
    //   10588: goto -9688 -> 900
    //   10591: bipush 32
    //   10593: istore 65
    //   10595: goto -9695 -> 900
    //   10598: bipush 106
    //   10600: istore 76
    //   10602: goto -9534 -> 1068
    //   10605: bipush 36
    //   10607: istore 76
    //   10609: goto -9541 -> 1068
    //   10612: bipush 25
    //   10614: istore 76
    //   10616: goto -9548 -> 1068
    //   10619: bipush 32
    //   10621: istore 76
    //   10623: goto -9555 -> 1068
    //   10626: bipush 106
    //   10628: istore 87
    //   10630: goto -9394 -> 1236
    //   10633: bipush 36
    //   10635: istore 87
    //   10637: goto -9401 -> 1236
    //   10640: bipush 25
    //   10642: istore 87
    //   10644: goto -9408 -> 1236
    //   10647: bipush 32
    //   10649: istore 87
    //   10651: goto -9415 -> 1236
    //   10654: bipush 106
    //   10656: istore 98
    //   10658: goto -9254 -> 1404
    //   10661: bipush 36
    //   10663: istore 98
    //   10665: goto -9261 -> 1404
    //   10668: bipush 25
    //   10670: istore 98
    //   10672: goto -9268 -> 1404
    //   10675: bipush 32
    //   10677: istore 98
    //   10679: goto -9275 -> 1404
    //   10682: bipush 106
    //   10684: istore 109
    //   10686: goto -9114 -> 1572
    //   10689: bipush 36
    //   10691: istore 109
    //   10693: goto -9121 -> 1572
    //   10696: bipush 25
    //   10698: istore 109
    //   10700: goto -9128 -> 1572
    //   10703: bipush 32
    //   10705: istore 109
    //   10707: goto -9135 -> 1572
    //   10710: bipush 106
    //   10712: istore 120
    //   10714: goto -8974 -> 1740
    //   10717: bipush 36
    //   10719: istore 120
    //   10721: goto -8981 -> 1740
    //   10724: bipush 25
    //   10726: istore 120
    //   10728: goto -8988 -> 1740
    //   10731: bipush 32
    //   10733: istore 120
    //   10735: goto -8995 -> 1740
    //   10738: bipush 106
    //   10740: istore 131
    //   10742: goto -8834 -> 1908
    //   10745: bipush 36
    //   10747: istore 131
    //   10749: goto -8841 -> 1908
    //   10752: bipush 25
    //   10754: istore 131
    //   10756: goto -8848 -> 1908
    //   10759: bipush 32
    //   10761: istore 131
    //   10763: goto -8855 -> 1908
    //   10766: bipush 106
    //   10768: istore 142
    //   10770: goto -8694 -> 2076
    //   10773: bipush 36
    //   10775: istore 142
    //   10777: goto -8701 -> 2076
    //   10780: bipush 25
    //   10782: istore 142
    //   10784: goto -8708 -> 2076
    //   10787: bipush 32
    //   10789: istore 142
    //   10791: goto -8715 -> 2076
    //   10794: bipush 106
    //   10796: istore 153
    //   10798: goto -8554 -> 2244
    //   10801: bipush 36
    //   10803: istore 153
    //   10805: goto -8561 -> 2244
    //   10808: bipush 25
    //   10810: istore 153
    //   10812: goto -8568 -> 2244
    //   10815: bipush 32
    //   10817: istore 153
    //   10819: goto -8575 -> 2244
    //   10822: bipush 106
    //   10824: istore 164
    //   10826: goto -8414 -> 2412
    //   10829: bipush 36
    //   10831: istore 164
    //   10833: goto -8421 -> 2412
    //   10836: bipush 25
    //   10838: istore 164
    //   10840: goto -8428 -> 2412
    //   10843: bipush 32
    //   10845: istore 164
    //   10847: goto -8435 -> 2412
    //   10850: bipush 106
    //   10852: istore 175
    //   10854: goto -8274 -> 2580
    //   10857: bipush 36
    //   10859: istore 175
    //   10861: goto -8281 -> 2580
    //   10864: bipush 25
    //   10866: istore 175
    //   10868: goto -8288 -> 2580
    //   10871: bipush 32
    //   10873: istore 175
    //   10875: goto -8295 -> 2580
    //   10878: bipush 106
    //   10880: istore 186
    //   10882: goto -8134 -> 2748
    //   10885: bipush 36
    //   10887: istore 186
    //   10889: goto -8141 -> 2748
    //   10892: bipush 25
    //   10894: istore 186
    //   10896: goto -8148 -> 2748
    //   10899: bipush 32
    //   10901: istore 186
    //   10903: goto -8155 -> 2748
    //   10906: bipush 106
    //   10908: istore 197
    //   10910: goto -7994 -> 2916
    //   10913: bipush 36
    //   10915: istore 197
    //   10917: goto -8001 -> 2916
    //   10920: bipush 25
    //   10922: istore 197
    //   10924: goto -8008 -> 2916
    //   10927: bipush 32
    //   10929: istore 197
    //   10931: goto -8015 -> 2916
    //   10934: bipush 106
    //   10936: istore 208
    //   10938: goto -7854 -> 3084
    //   10941: bipush 36
    //   10943: istore 208
    //   10945: goto -7861 -> 3084
    //   10948: bipush 25
    //   10950: istore 208
    //   10952: goto -7868 -> 3084
    //   10955: bipush 32
    //   10957: istore 208
    //   10959: goto -7875 -> 3084
    //   10962: bipush 106
    //   10964: istore 219
    //   10966: goto -7714 -> 3252
    //   10969: bipush 36
    //   10971: istore 219
    //   10973: goto -7721 -> 3252
    //   10976: bipush 25
    //   10978: istore 219
    //   10980: goto -7728 -> 3252
    //   10983: bipush 32
    //   10985: istore 219
    //   10987: goto -7735 -> 3252
    //   10990: bipush 106
    //   10992: istore 230
    //   10994: goto -7574 -> 3420
    //   10997: bipush 36
    //   10999: istore 230
    //   11001: goto -7581 -> 3420
    //   11004: bipush 25
    //   11006: istore 230
    //   11008: goto -7588 -> 3420
    //   11011: bipush 32
    //   11013: istore 230
    //   11015: goto -7595 -> 3420
    //   11018: bipush 106
    //   11020: istore 241
    //   11022: goto -7434 -> 3588
    //   11025: bipush 36
    //   11027: istore 241
    //   11029: goto -7441 -> 3588
    //   11032: bipush 25
    //   11034: istore 241
    //   11036: goto -7448 -> 3588
    //   11039: bipush 32
    //   11041: istore 241
    //   11043: goto -7455 -> 3588
    //   11046: bipush 106
    //   11048: istore 252
    //   11050: goto -7294 -> 3756
    //   11053: bipush 36
    //   11055: istore 252
    //   11057: goto -7301 -> 3756
    //   11060: bipush 25
    //   11062: istore 252
    //   11064: goto -7308 -> 3756
    //   11067: bipush 32
    //   11069: istore 252
    //   11071: goto -7315 -> 3756
    //   11074: bipush 106
    //   11076: wide
    //   11080: goto -7122 -> 3958
    //   11083: bipush 36
    //   11085: wide
    //   11089: goto -7131 -> 3958
    //   11092: bipush 25
    //   11094: wide
    //   11098: goto -7140 -> 3958
    //   11101: bipush 32
    //   11103: wide
    //   11107: goto -7149 -> 3958
    //   11110: bipush 106
    //   11112: wide
    //   11116: goto -6914 -> 4202
    //   11119: bipush 36
    //   11121: wide
    //   11125: goto -6923 -> 4202
    //   11128: bipush 25
    //   11130: wide
    //   11134: goto -6932 -> 4202
    //   11137: bipush 32
    //   11139: wide
    //   11143: goto -6941 -> 4202
    //   11146: bipush 106
    //   11148: wide
    //   11152: goto -6710 -> 4442
    //   11155: bipush 36
    //   11157: wide
    //   11161: goto -6719 -> 4442
    //   11164: bipush 25
    //   11166: wide
    //   11170: goto -6728 -> 4442
    //   11173: bipush 32
    //   11175: wide
    //   11179: goto -6737 -> 4442
    //   11182: bipush 106
    //   11184: wide
    //   11188: goto -6502 -> 4686
    //   11191: bipush 36
    //   11193: wide
    //   11197: goto -6511 -> 4686
    //   11200: bipush 25
    //   11202: wide
    //   11206: goto -6520 -> 4686
    //   11209: bipush 32
    //   11211: wide
    //   11215: goto -6529 -> 4686
    //   11218: bipush 106
    //   11220: wide
    //   11224: goto -6294 -> 4930
    //   11227: bipush 36
    //   11229: wide
    //   11233: goto -6303 -> 4930
    //   11236: bipush 25
    //   11238: wide
    //   11242: goto -6312 -> 4930
    //   11245: bipush 32
    //   11247: wide
    //   11251: goto -6321 -> 4930
    //   11254: bipush 106
    //   11256: wide
    //   11260: goto -6086 -> 5174
    //   11263: bipush 36
    //   11265: wide
    //   11269: goto -6095 -> 5174
    //   11272: bipush 25
    //   11274: wide
    //   11278: goto -6104 -> 5174
    //   11281: bipush 32
    //   11283: wide
    //   11287: goto -6113 -> 5174
    //   11290: bipush 106
    //   11292: wide
    //   11296: goto -5878 -> 5418
    //   11299: bipush 36
    //   11301: wide
    //   11305: goto -5887 -> 5418
    //   11308: bipush 25
    //   11310: wide
    //   11314: goto -5896 -> 5418
    //   11317: bipush 32
    //   11319: wide
    //   11323: goto -5905 -> 5418
    //   11326: bipush 106
    //   11328: wide
    //   11332: goto -5670 -> 5662
    //   11335: bipush 36
    //   11337: wide
    //   11341: goto -5679 -> 5662
    //   11344: bipush 25
    //   11346: wide
    //   11350: goto -5688 -> 5662
    //   11353: bipush 32
    //   11355: wide
    //   11359: goto -5697 -> 5662
    //   11362: bipush 106
    //   11364: wide
    //   11368: goto -5462 -> 5906
    //   11371: bipush 36
    //   11373: wide
    //   11377: goto -5471 -> 5906
    //   11380: bipush 25
    //   11382: wide
    //   11386: goto -5480 -> 5906
    //   11389: bipush 32
    //   11391: wide
    //   11395: goto -5489 -> 5906
    //   11398: bipush 106
    //   11400: wide
    //   11404: goto -5258 -> 6146
    //   11407: bipush 36
    //   11409: wide
    //   11413: goto -5267 -> 6146
    //   11416: bipush 25
    //   11418: wide
    //   11422: goto -5276 -> 6146
    //   11425: bipush 32
    //   11427: wide
    //   11431: goto -5285 -> 6146
    //   11434: bipush 106
    //   11436: wide
    //   11440: goto -5050 -> 6390
    //   11443: bipush 36
    //   11445: wide
    //   11449: goto -5059 -> 6390
    //   11452: bipush 25
    //   11454: wide
    //   11458: goto -5068 -> 6390
    //   11461: bipush 32
    //   11463: wide
    //   11467: goto -5077 -> 6390
    //   11470: bipush 106
    //   11472: wide
    //   11476: goto -4842 -> 6634
    //   11479: bipush 36
    //   11481: wide
    //   11485: goto -4851 -> 6634
    //   11488: bipush 25
    //   11490: wide
    //   11494: goto -4860 -> 6634
    //   11497: bipush 32
    //   11499: wide
    //   11503: goto -4869 -> 6634
    //   11506: bipush 106
    //   11508: wide
    //   11512: goto -4634 -> 6878
    //   11515: bipush 36
    //   11517: wide
    //   11521: goto -4643 -> 6878
    //   11524: bipush 25
    //   11526: wide
    //   11530: goto -4652 -> 6878
    //   11533: bipush 32
    //   11535: wide
    //   11539: goto -4661 -> 6878
    //   11542: bipush 106
    //   11544: wide
    //   11548: goto -4430 -> 7118
    //   11551: bipush 36
    //   11553: wide
    //   11557: goto -4439 -> 7118
    //   11560: bipush 25
    //   11562: wide
    //   11566: goto -4448 -> 7118
    //   11569: bipush 32
    //   11571: wide
    //   11575: goto -4457 -> 7118
    //   11578: bipush 106
    //   11580: wide
    //   11584: goto -4222 -> 7362
    //   11587: bipush 36
    //   11589: wide
    //   11593: goto -4231 -> 7362
    //   11596: bipush 25
    //   11598: wide
    //   11602: goto -4240 -> 7362
    //   11605: bipush 32
    //   11607: wide
    //   11611: goto -4249 -> 7362
    //   11614: bipush 106
    //   11616: wide
    //   11620: goto -4014 -> 7606
    //   11623: bipush 36
    //   11625: wide
    //   11629: goto -4023 -> 7606
    //   11632: bipush 25
    //   11634: wide
    //   11638: goto -4032 -> 7606
    //   11641: bipush 32
    //   11643: wide
    //   11647: goto -4041 -> 7606
    //   11650: bipush 106
    //   11652: wide
    //   11656: goto -3806 -> 7850
    //   11659: bipush 36
    //   11661: wide
    //   11665: goto -3815 -> 7850
    //   11668: bipush 25
    //   11670: wide
    //   11674: goto -3824 -> 7850
    //   11677: bipush 32
    //   11679: wide
    //   11683: goto -3833 -> 7850
    //   11686: bipush 106
    //   11688: wide
    //   11692: goto -3598 -> 8094
    //   11695: bipush 36
    //   11697: wide
    //   11701: goto -3607 -> 8094
    //   11704: bipush 25
    //   11706: wide
    //   11710: goto -3616 -> 8094
    //   11713: bipush 32
    //   11715: wide
    //   11719: goto -3625 -> 8094
    //   11722: bipush 106
    //   11724: wide
    //   11728: goto -3390 -> 8338
    //   11731: bipush 36
    //   11733: wide
    //   11737: goto -3399 -> 8338
    //   11740: bipush 25
    //   11742: wide
    //   11746: goto -3408 -> 8338
    //   11749: bipush 32
    //   11751: wide
    //   11755: goto -3417 -> 8338
    //   11758: bipush 106
    //   11760: wide
    //   11764: goto -3182 -> 8582
    //   11767: bipush 36
    //   11769: wide
    //   11773: goto -3191 -> 8582
    //   11776: bipush 25
    //   11778: wide
    //   11782: goto -3200 -> 8582
    //   11785: bipush 32
    //   11787: wide
    //   11791: goto -3209 -> 8582
    //   11794: bipush 106
    //   11796: wide
    //   11800: goto -2974 -> 8826
    //   11803: bipush 36
    //   11805: wide
    //   11809: goto -2983 -> 8826
    //   11812: bipush 25
    //   11814: wide
    //   11818: goto -2992 -> 8826
    //   11821: bipush 32
    //   11823: wide
    //   11827: goto -3001 -> 8826
    //   11830: bipush 106
    //   11832: wide
    //   11836: goto -2766 -> 9070
    //   11839: bipush 36
    //   11841: wide
    //   11845: goto -2775 -> 9070
    //   11848: bipush 25
    //   11850: wide
    //   11854: goto -2784 -> 9070
    //   11857: bipush 32
    //   11859: wide
    //   11863: goto -2793 -> 9070
    //   11866: bipush 106
    //   11868: wide
    //   11872: goto -2558 -> 9314
    //   11875: bipush 36
    //   11877: wide
    //   11881: goto -2567 -> 9314
    //   11884: bipush 25
    //   11886: wide
    //   11890: goto -2576 -> 9314
    //   11893: bipush 32
    //   11895: wide
    //   11899: goto -2585 -> 9314
    //   11902: bipush 106
    //   11904: wide
    //   11908: goto -2350 -> 9558
    //   11911: bipush 36
    //   11913: wide
    //   11917: goto -2359 -> 9558
    //   11920: bipush 25
    //   11922: wide
    //   11926: goto -2368 -> 9558
    //   11929: bipush 32
    //   11931: wide
    //   11935: goto -2377 -> 9558
    //   11938: bipush 106
    //   11940: wide
    //   11944: goto -2142 -> 9802
    //   11947: bipush 36
    //   11949: wide
    //   11953: goto -2151 -> 9802
    //   11956: bipush 25
    //   11958: wide
    //   11962: goto -2160 -> 9802
    //   11965: bipush 32
    //   11967: wide
    //   11971: goto -2169 -> 9802
    //   11974: bipush 106
    //   11976: wide
    //   11980: goto -1934 -> 10046
    //   11983: bipush 36
    //   11985: wide
    //   11989: goto -1943 -> 10046
    //   11992: bipush 25
    //   11994: wide
    //   11998: goto -1952 -> 10046
    //   12001: bipush 32
    //   12003: wide
    //   12007: goto -1961 -> 10046
    //   12010: bipush 106
    //   12012: wide
    //   12016: goto -1726 -> 10290
    //   12019: bipush 36
    //   12021: wide
    //   12025: goto -1735 -> 10290
    //   12028: bipush 25
    //   12030: wide
    //   12034: goto -1744 -> 10290
    //   12037: bipush 32
    //   12039: wide
    //   12043: goto -1753 -> 10290
    //   12046: iconst_0
    //   12047: wide
    //   12051: goto -1682 -> 10369
    //   12054: iconst_0
    //   12055: wide
    //   12059: goto -1934 -> 10125
    //   12062: iconst_0
    //   12063: wide
    //   12067: goto -2186 -> 9881
    //   12070: iconst_0
    //   12071: wide
    //   12075: goto -2438 -> 9637
    //   12078: iconst_0
    //   12079: wide
    //   12083: goto -2690 -> 9393
    //   12086: iconst_0
    //   12087: wide
    //   12091: goto -2942 -> 9149
    //   12094: iconst_0
    //   12095: wide
    //   12099: goto -3194 -> 8905
    //   12102: iconst_0
    //   12103: wide
    //   12107: goto -3446 -> 8661
    //   12110: iconst_0
    //   12111: wide
    //   12115: goto -3698 -> 8417
    //   12118: iconst_0
    //   12119: wide
    //   12123: goto -3950 -> 8173
    //   12126: iconst_0
    //   12127: wide
    //   12131: goto -4202 -> 7929
    //   12134: iconst_0
    //   12135: wide
    //   12139: goto -4454 -> 7685
    //   12142: iconst_0
    //   12143: wide
    //   12147: goto -4706 -> 7441
    //   12150: iconst_0
    //   12151: wide
    //   12155: goto -4956 -> 7199
    //   12158: iconst_0
    //   12159: wide
    //   12163: goto -5206 -> 6957
    //   12166: iconst_0
    //   12167: wide
    //   12171: goto -5458 -> 6713
    //   12174: iconst_0
    //   12175: wide
    //   12179: goto -5710 -> 6469
    //   12182: iconst_0
    //   12183: wide
    //   12187: goto -5960 -> 6227
    //   12190: iconst_0
    //   12191: wide
    //   12195: goto -6210 -> 5985
    //   12198: iconst_0
    //   12199: wide
    //   12203: goto -6462 -> 5741
    //   12206: iconst_0
    //   12207: wide
    //   12211: goto -6714 -> 5497
    //   12214: iconst_0
    //   12215: wide
    //   12219: goto -6966 -> 5253
    //   12222: iconst_0
    //   12223: wide
    //   12227: goto -7218 -> 5009
    //   12230: iconst_0
    //   12231: wide
    //   12235: goto -7470 -> 4765
    //   12238: iconst_0
    //   12239: wide
    //   12243: goto -7720 -> 4523
    //   12246: iconst_0
    //   12247: wide
    //   12251: goto -7970 -> 4281
    //   12254: iconst_0
    //   12255: wide
    //   12259: goto -8222 -> 4037
    //   12262: iconst_0
    //   12263: istore 248
    //   12265: goto -8460 -> 3805
    //   12268: iconst_0
    //   12269: istore 237
    //   12271: goto -8634 -> 3637
    //   12274: iconst_0
    //   12275: istore 226
    //   12277: goto -8808 -> 3469
    //   12280: iconst_0
    //   12281: istore 215
    //   12283: goto -8982 -> 3301
    //   12286: iconst_0
    //   12287: istore 204
    //   12289: goto -9156 -> 3133
    //   12292: iconst_0
    //   12293: istore 193
    //   12295: goto -9330 -> 2965
    //   12298: iconst_0
    //   12299: istore 182
    //   12301: goto -9504 -> 2797
    //   12304: iconst_0
    //   12305: istore 171
    //   12307: goto -9678 -> 2629
    //   12310: iconst_0
    //   12311: istore 160
    //   12313: goto -9852 -> 2461
    //   12316: iconst_0
    //   12317: istore 149
    //   12319: goto -10026 -> 2293
    //   12322: iconst_0
    //   12323: istore 138
    //   12325: goto -10200 -> 2125
    //   12328: iconst_0
    //   12329: istore 127
    //   12331: goto -10374 -> 1957
    //   12334: iconst_0
    //   12335: istore 116
    //   12337: goto -10548 -> 1789
    //   12340: iconst_0
    //   12341: istore 105
    //   12343: goto -10722 -> 1621
    //   12346: iconst_0
    //   12347: istore 94
    //   12349: goto -10896 -> 1453
    //   12352: iconst_0
    //   12353: istore 83
    //   12355: goto -11070 -> 1285
    //   12358: iconst_0
    //   12359: istore 72
    //   12361: goto -11244 -> 1117
    //   12364: iconst_0
    //   12365: istore 61
    //   12367: goto -11418 -> 949
    //   12370: iconst_0
    //   12371: istore 50
    //   12373: goto -11588 -> 785
    //   12376: iconst_0
    //   12377: istore 39
    //   12379: goto -11758 -> 621
    //   12382: iconst_0
    //   12383: istore 27
    //   12385: goto -11928 -> 457
    //   12388: iconst_0
    //   12389: istore 16
    //   12391: goto -12098 -> 293
    //   12394: iconst_0
    //   12395: istore 4
    //   12397: goto -12262 -> 135
  }

  public _sdkkc(WPSAuthentication paramWPSAuthentication, _sdkrc param_sdkrc)
  {
    _sdklc local_sdklc = new _sdklc(this);
    this._sdka = local_sdklc;
    Cache localCache = new Cache();
    this._sdke = localCache;
    _sdkfc local_sdkfc = new _sdkfc();
    this._sdkf = local_sdkfc;
    this._sdkg = null;
    this._sdki = local_sdkhb1;
    this._sdkj = local_sdkhb1;
    this._sdkk = local_sdkhb1;
    LinkedList localLinkedList = new LinkedList();
    this._sdkl = localLinkedList;
    this._sdkm = local_sdkhb1;
    _sdkad local_sdkad = new _sdkad(this, 4, 0.75F, bool1);
    this._sdkp = local_sdkad;
    com.skyhookwireless._sdkhb local_sdkhb2 = com.skyhookwireless._sdkhb._sdkb(_sdkkc.class);
    this._sdkb = local_sdkhb2;
    if ((paramWPSAuthentication == null) || (param_sdkrc == null))
    {
      StringBuilder localStringBuilder2 = new StringBuilder();
      String str1 = z[26];
      String str2 = str1 + paramWPSAuthentication + "," + param_sdkrc + ")";
      throw new IllegalArgumentException(str2);
    }
    long l1 = param_sdkrc._sdkc();
    _sdkgc local_sdkgc1 = new _sdkgc(paramWPSAuthentication, l1);
    this._sdkd = local_sdkgc1;
    TilingListener localTilingListener = param_sdkrc._sdkd();
    this._sdkh = localTilingListener;
    String str3 = param_sdkrc._sdka();
    _sdkgc local_sdkgc2 = this._sdkd;
    String str4 = _sdka(str3, local_sdkgc2);
    this._sdkg = str4;
    long l2 = param_sdkrc._sdkb();
    com.skyhookwireless._sdkhb local_sdkhb3;
    boolean bool3;
    if (this._sdkg.length() == 0)
    {
      local_sdkhb3 = this._sdkb;
      String str5 = z[24];
      local_sdkhb3._sdkb(str5);
      if (!bool2)
        break label576;
      if (com.skyhookwireless._sdkhb._sdkd)
      {
        bool3 = false;
        com.skyhookwireless._sdkhb._sdkd = bool3;
        long l3 = 0L;
      }
    }
    else
    {
      if (local_sdkhb3 <= l1)
        break label569;
      com.skyhookwireless._sdkhb local_sdkhb4 = this._sdkb;
      StringBuilder localStringBuilder3 = new StringBuilder();
      String str6 = z[27];
      StringBuilder localStringBuilder4 = localStringBuilder3.append(str6).append(local_sdkhb3);
      String str7 = z[29];
      StringBuilder localStringBuilder5 = localStringBuilder4.append(str7).append(l1);
      String str8 = z[23];
      String str9 = str8;
      local_sdkhb4._sdkd(str9);
    }
    while (true)
    {
      label430: StringBuilder localStringBuilder1;
      if (l1 == 0L)
      {
        this._sdko = bool1;
        if (this._sdkb._sdkb())
        {
          local_sdkhb1 = this._sdkb;
          StringBuilder localStringBuilder6 = new StringBuilder();
          String str10 = z[22];
          localStringBuilder1 = localStringBuilder6.append(str10);
          if (!this._sdko)
            break label558;
        }
      }
      label558: for (String str11 = z[25]; ; str11 = z[28])
      {
        String str12 = str11;
        local_sdkhb1._sdkb(str12);
        _sdkqc local_sdkqc = this._sdka;
        _sdknc local_sdknc = new _sdknc(paramWPSAuthentication, l1, local_sdkqc);
        this._sdkc = local_sdknc;
        _sdkec local_sdkec = _sdkec._sdkd();
        this._sdkn = local_sdkec;
        return;
        bool3 = true;
        break;
        localStringBuilder1 = null;
        break label430;
      }
      label569: Object localObject = local_sdkhb3;
      continue;
      label576: localObject = null;
    }
  }

  static int _sdka(_sdkkc param_sdkkc, int paramInt)
  {
    param_sdkkc._sdkm = paramInt;
    return paramInt;
  }

  static com.skyhookwireless._sdkhb _sdka(_sdkkc param_sdkkc)
  {
    return param_sdkkc._sdkb;
  }

  private String _sdka(String paramString, _sdkgc param_sdkgc)
  {
    boolean bool1 = _sdkr;
    label12: ArrayList localArrayList;
    int j;
    label293: String str10;
    Matcher localMatcher;
    if (paramString == null)
    {
      paramString = "";
    }
    else
    {
      String[] arrayOfString;
      while (true)
      {
        return paramString;
        if (paramString.length() != 0)
        {
          String str1 = File.separator;
          if (!paramString.endsWith(str1))
          {
            StringBuilder localStringBuilder1 = new StringBuilder().append(paramString);
            String str2 = File.separator;
            paramString = str2;
          }
          File localFile = new File(paramString);
          if (!localFile.isDirectory())
          {
            com.skyhookwireless._sdkhb local_sdkhb1 = this._sdkb;
            StringBuilder localStringBuilder2 = new StringBuilder().append(paramString);
            String str3 = z[3];
            String str4 = str3;
            local_sdkhb1._sdke(str4);
          }
          else
          {
            if (this._sdkb._sdkb())
            {
              com.skyhookwireless._sdkhb local_sdkhb2 = this._sdkb;
              StringBuilder localStringBuilder3 = new StringBuilder();
              String str5 = z[6];
              StringBuilder localStringBuilder4 = localStringBuilder3.append(str5).append(paramString);
              String str6 = z[2];
              String str7 = str6;
              local_sdkhb2._sdkb(str7);
            }
            arrayOfString = localFile.list();
            if (arrayOfString != null)
              break;
            com.skyhookwireless._sdkhb local_sdkhb3 = this._sdkb;
            StringBuilder localStringBuilder5 = new StringBuilder();
            String str8 = z[7];
            String str9 = str8 + paramString;
            local_sdkhb3._sdke(str9);
          }
        }
      }
      Pattern localPattern = Pattern.compile(z[1]);
      localArrayList = new ArrayList();
      int i = arrayOfString.length;
      j = 0;
      if (j < i)
      {
        str10 = arrayOfString[j];
        localMatcher = localPattern.matcher(str10);
        if (localMatcher.matches())
          break label391;
      }
    }
    while (true)
    {
      j += 1;
      if (!bool1)
        break label293;
      Comparator localComparator = _sdkic._sdka;
      Collections.sort(localArrayList, localComparator);
      Iterator localIterator = localArrayList.iterator();
      if (!localIterator.hasNext())
        break label12;
      _sdkic local_sdkic1 = (_sdkic)localIterator.next();
      param_sdkgc._sdka(0, local_sdkic1);
      if (!bool1)
        break;
      break label12;
      label391: String str11 = paramString + str10;
      if (!new File(str11).isFile())
      {
        com.skyhookwireless._sdkhb local_sdkhb4 = this._sdkb;
        StringBuilder localStringBuilder6 = new StringBuilder();
        String str12 = z[4];
        StringBuilder localStringBuilder7 = localStringBuilder6.append(str12).append(str11);
        String str13 = z[0];
        String str14 = str13;
        local_sdkhb4._sdkd(str14);
        if (!bool1);
      }
      else
      {
        com.skyhookwireless._sdkhb local_sdkhb5 = this._sdkb;
        StringBuilder localStringBuilder8 = new StringBuilder();
        String str15 = z[5];
        String str16 = str15 + str10;
        local_sdkhb5._sdkb(str16);
        String str17 = localMatcher.group(1);
        int k = Integer.valueOf(localMatcher.group(2)).intValue();
        _sdkic local_sdkic2 = _sdkic._sdka(str17, k, str11);
        boolean bool2 = localArrayList.add(local_sdkic2);
      }
    }
  }

  private void _sdka(_sdkic param_sdkic, InputStream paramInputStream, int paramInt)
    throws IOException
  {
    boolean bool = _sdkr;
    StringBuilder localStringBuilder1 = new StringBuilder();
    String str1 = this._sdkg;
    StringBuilder localStringBuilder2 = localStringBuilder1.append(str1).append(param_sdkic);
    String str2 = z[44];
    String str3 = str2;
    FileOutputStream localFileOutputStream = new FileOutputStream(str3);
    byte[] arrayOfByte = new byte[1024];
    long l1 = 0L;
    do
    {
      int i = paramInputStream.read(arrayOfByte);
      if (i == -1)
        break;
      localFileOutputStream.write(arrayOfByte, 0, i);
      long l2 = i;
      l1 += l2;
    }
    while (!bool);
    localFileOutputStream.close();
    long l3 = new File(str3).length();
    if (l3 != l1)
    {
      StringBuilder localStringBuilder3 = new StringBuilder();
      String str4 = z[45];
      StringBuilder localStringBuilder4 = localStringBuilder3.append(str4).append(param_sdkic);
      String str5 = z[42];
      StringBuilder localStringBuilder5 = localStringBuilder4.append(str5).append(l3);
      String str6 = z[41];
      String str7 = str6 + l1;
      throw new IOException(str7);
    }
    if (this._sdkb._sdkb())
    {
      com.skyhookwireless._sdkhb local_sdkhb = this._sdkb;
      StringBuilder localStringBuilder6 = new StringBuilder();
      String str8 = z[4];
      StringBuilder localStringBuilder7 = localStringBuilder6.append(str8).append(param_sdkic);
      String str9 = z[43];
      String str10 = str9 + str3;
      local_sdkhb._sdkb(str10);
    }
    try
    {
      _sdkgc local_sdkgc = this._sdkd;
      String str11 = param_sdkic._sdka();
      int j = param_sdkic._sdkb();
      _sdkic local_sdkic = _sdkic._sdka(str11, j, str3);
      local_sdkgc._sdka(paramInt, local_sdkic);
      return;
    }
    finally
    {
      localObject = finally;
      throw localObject;
    }
  }

  static void _sdka(_sdkkc param_sdkkc, _sdkic param_sdkic, InputStream paramInputStream, int paramInt)
    throws IOException
  {
    param_sdkkc._sdka(param_sdkic, paramInputStream, paramInt);
  }

  static boolean _sdka(_sdkkc param_sdkkc, boolean paramBoolean)
  {
    param_sdkkc._sdki = paramBoolean;
    return paramBoolean;
  }

  static boolean _sdkb(_sdkkc param_sdkkc)
  {
    return param_sdkkc._sdki;
  }

  static boolean _sdkb(_sdkkc param_sdkkc, boolean paramBoolean)
  {
    param_sdkkc._sdkj = paramBoolean;
    return paramBoolean;
  }

  static _sdkfc _sdkc(_sdkkc param_sdkkc)
  {
    return param_sdkkc._sdkf;
  }

  private void _sdkc()
  {
    if ((!_sdkq) && (this._sdki))
      throw new AssertionError();
    this._sdkk = true;
  }

  /** @deprecated */
  private void _sdkd()
  {
    boolean bool;
    _sdkic local_sdkic1;
    int i;
    int j;
    try
    {
      bool = _sdkr;
      do
      {
        do
        {
          if (this._sdkl.isEmpty())
            break label729;
          local_sdkic1 = (_sdkic)this._sdkl.getFirst();
          _sdkic local_sdkic2 = this._sdkd._sdka(local_sdkic1);
          i = this._sdkm;
          j = _sdke();
          Object localObject1 = this._sdkl.removeFirst();
          if (local_sdkic2 == null)
            break;
          if (this._sdkb._sdkb())
          {
            com.skyhookwireless._sdkhb local_sdkhb1 = this._sdkb;
            StringBuilder localStringBuilder1 = new StringBuilder();
            String str1 = z[40];
            StringBuilder localStringBuilder2 = localStringBuilder1.append(str1).append(j).append("(").append(local_sdkic1);
            String str2 = z[36];
            String str3 = str2 + local_sdkic2;
            local_sdkhb1._sdkb(str3);
          }
          if (local_sdkic1._sdkb(local_sdkic2))
          {
            int k = local_sdkic1._sdkb();
            int m = local_sdkic2._sdkb();
            if (k >= m)
            {
              com.skyhookwireless._sdkhb local_sdkhb2 = this._sdkb;
              String str4 = z[33];
              local_sdkhb2._sdkb(str4);
              if (!bool)
                break;
            }
          }
          int n = local_sdkic1._sdkb();
          int i1 = local_sdkic2._sdkb();
          if (n - i1 > 1209600L)
          {
            com.skyhookwireless._sdkhb local_sdkhb3 = this._sdkb;
            String str5 = z[38];
            local_sdkhb3._sdkb(str5);
            if (!bool)
              break;
          }
        }
        while (!this._sdkb._sdkb());
        com.skyhookwireless._sdkhb local_sdkhb4 = this._sdkb;
        StringBuilder localStringBuilder3 = new StringBuilder();
        String str6 = z[34];
        String str7 = str6 + local_sdkic1;
        local_sdkhb4._sdkb(str7);
      }
      while (!bool);
      if (this._sdkh == null)
        break label400;
      if ((!_sdkq) && (j >= i))
        throw new AssertionError();
    }
    finally
    {
    }
    WPSContinuation localWPSContinuation = this._sdkh.tilingCallback(j, i);
    int[] arrayOfInt = _sdkmc._sdka;
    int i2 = localWPSContinuation.ordinal();
    switch (arrayOfInt[i2])
    {
    default:
      label400: if (this._sdkb._sdkb())
      {
        com.skyhookwireless._sdkhb local_sdkhb5 = this._sdkb;
        StringBuilder localStringBuilder4 = new StringBuilder();
        String str8 = z[32];
        StringBuilder localStringBuilder5 = localStringBuilder4.append(str8).append(j).append("/").append(i);
        String str9 = z[20];
        StringBuilder localStringBuilder6 = localStringBuilder5.append(str9).append(local_sdkic1);
        String str10 = z[39];
        String str11 = str10;
        local_sdkhb5._sdkb(str11);
      }
      if (!this._sdkc._sdka(local_sdkic1, j))
      {
        com.skyhookwireless._sdkhb local_sdkhb6 = this._sdkb;
        StringBuilder localStringBuilder7 = new StringBuilder();
        String str12 = z[31];
        StringBuilder localStringBuilder8 = localStringBuilder7.append(str12).append(j).append("/").append(i);
        String str13 = z[20];
        StringBuilder localStringBuilder9 = localStringBuilder8.append(str13).append(local_sdkic1);
        String str14 = z[39];
        String str15 = str14;
        local_sdkhb6._sdke(str15);
        this._sdkj = false;
      }
      break;
    case 1:
    case 2:
    }
    while (true)
    {
      return;
      com.skyhookwireless._sdkhb local_sdkhb7 = this._sdkb;
      StringBuilder localStringBuilder10 = new StringBuilder();
      String str16 = z[35];
      StringBuilder localStringBuilder11 = localStringBuilder10.append(str16).append(j);
      String str17 = z[20];
      String str18 = str17 + local_sdkic1 + ")";
      local_sdkhb7._sdkb(str18);
      if (!bool)
        break;
      com.skyhookwireless._sdkhb local_sdkhb8 = this._sdkb;
      String str19 = z[37];
      local_sdkhb8._sdkb(str19);
      this._sdkj = false;
      continue;
      label729: this._sdkj = false;
      com.skyhookwireless._sdkhb local_sdkhb9 = this._sdkb;
      String str20 = z[30];
      local_sdkhb9._sdkb(str20);
    }
  }

  static boolean _sdkd(_sdkkc param_sdkkc)
  {
    return param_sdkkc._sdko;
  }

  private int _sdke()
  {
    int i = this._sdkm;
    int j = this._sdkl.size();
    return i - j;
  }

  static Cache _sdke(_sdkkc param_sdkkc)
  {
    return param_sdkkc._sdke;
  }

  static Map _sdkf(_sdkkc param_sdkkc)
  {
    return param_sdkkc._sdkp;
  }

  private void _sdkf()
  {
    com.skyhookwireless._sdkhb local_sdkhb = this._sdkb;
    String str = z[49];
    local_sdkhb._sdkb(str);
    if ((!_sdkq) && (!this._sdki))
      throw new AssertionError();
    this._sdki = false;
    this._sdkf._sdkf();
  }

  static LinkedList _sdkg(_sdkkc param_sdkkc)
  {
    return param_sdkkc._sdkl;
  }

  private boolean _sdkg()
  {
    int i = Protocol.rqSize(this._sdkf._sdkb());
    if (this._sdkb._sdkb())
    {
      com.skyhookwireless._sdkhb local_sdkhb1 = this._sdkb;
      StringBuilder localStringBuilder1 = new StringBuilder();
      String str1 = z[46];
      StringBuilder localStringBuilder2 = localStringBuilder1.append(str1);
      int j = i / 1024;
      StringBuilder localStringBuilder3 = localStringBuilder2.append(j);
      String str2 = z[48];
      String str3 = str2;
      local_sdkhb1._sdkb(str3);
    }
    if (i >= 30720)
    {
      com.skyhookwireless._sdkhb local_sdkhb2 = this._sdkb;
      String str4 = z[47];
      local_sdkhb2._sdkb(str4);
    }
    for (boolean bool = true; ; bool = false)
      return bool;
  }

  static _sdkgc _sdkh(_sdkkc param_sdkkc)
  {
    return param_sdkkc._sdkd;
  }

  static int _sdki(_sdkkc param_sdkkc)
  {
    return param_sdkkc._sdkm;
  }

  static boolean _sdkj(_sdkkc param_sdkkc)
  {
    return param_sdkkc._sdkj;
  }

  static void _sdkk(_sdkkc param_sdkkc)
  {
    param_sdkkc._sdkd();
  }

  static void _sdkl(_sdkkc param_sdkkc)
  {
    param_sdkkc._sdkf();
  }

  public void _sdka()
    throws InterruptedException
  {
    this._sdkc._sdka();
  }

  /** @deprecated */
  public void _sdka(_sdkzb param_sdkzb, ArrayList<_sdkhb> paramArrayList)
  {
    int i = 0;
    int m = 0;
    while (true)
    {
      int n;
      try
      {
        this._sdkk = false;
        if (!param_sdkzb.hasBeacons())
        {
          com.skyhookwireless._sdkhb local_sdkhb1 = this._sdkb;
          String str1 = z[15];
          local_sdkhb1._sdkb(str1);
          return;
        }
        ArrayList localArrayList = param_sdkzb.getAPs();
        if (!localArrayList.isEmpty())
        {
          d1 = 4.9E-324D;
          n = this._sdkd._sdka(localArrayList, paramArrayList);
          this._sdkf._sdka(param_sdkzb);
          if ((d1 != null) && (this._sdkb._sdkb()))
          {
            com.skyhookwireless._sdkhb local_sdkhb2 = this._sdkb;
            StringBuilder localStringBuilder1 = new StringBuilder();
            String str2 = z[17];
            StringBuilder localStringBuilder2 = localStringBuilder1.append(str2);
            if (n.length() != 0)
              break label208;
            j = z[21];
            String str3 = j;
            local_sdkhb2._sdkb(str3);
          }
          if (!this._sdki)
            break label214;
          com.skyhookwireless._sdkhb local_sdkhb3 = this._sdkb;
          String str4 = z[16];
          local_sdkhb3._sdkb(str4);
          continue;
        }
      }
      finally
      {
      }
      double d1 = 0.0D;
      continue;
      label208: int j = n;
      continue;
      label214: if ((this._sdkj) && (_sdke() < 2))
      {
        com.skyhookwireless._sdkhb local_sdkhb4 = this._sdkb;
        String str5 = z[18];
        local_sdkhb4._sdkb(str5);
      }
      else if ((d1 != null) && (n.length() == 0))
      {
        com.skyhookwireless._sdkhb local_sdkhb5 = this._sdkb;
        String str6 = z[14];
        local_sdkhb5._sdkb(str6);
        _sdkc();
      }
      else if ((d1 != null) && (this._sdkp.get(n) == null))
      {
        com.skyhookwireless._sdkhb local_sdkhb6 = this._sdkb;
        String str7 = z[19];
        local_sdkhb6._sdkb(str7);
        _sdkc();
      }
      else if ((paramArrayList.size() != 0) && (this._sdkn._sdka() > 40000L))
      {
        int k = param_sdkzb.getAPs().size();
        int i1 = paramArrayList.size();
        double d2 = i1;
        double d3 = k;
        d1 = d2 / d3;
        if (d1 < 0.2D)
        {
          com.skyhookwireless._sdkhb local_sdkhb7 = this._sdkb;
          StringBuilder localStringBuilder3 = new StringBuilder();
          String str8 = z[13];
          StringBuilder localStringBuilder4 = localStringBuilder3.append(str8).append(d1);
          String str9 = z[20];
          StringBuilder localStringBuilder5 = localStringBuilder4.append(str9).append(i1).append("/").append(k);
          String str10 = z[12];
          String str11 = str10 + 0.2D;
          local_sdkhb7._sdkb(str11);
          _sdkc();
        }
      }
      else if (_sdkg())
      {
        _sdkc();
      }
    }
  }

  /** @deprecated */
  public void _sdkb()
  {
    while (true)
    {
      try
      {
        if (!this._sdkk)
        {
          com.skyhookwireless._sdkhb local_sdkhb1 = this._sdkb;
          String str1 = z[11];
          local_sdkhb1._sdkb(str1);
          return;
        }
        boolean bool = false;
        this._sdkk = bool;
        if ((!_sdkq) && (this._sdki))
          throw new AssertionError();
      }
      finally
      {
      }
      if (this._sdkf._sdkb().numAPs() == 0)
      {
        com.skyhookwireless._sdkhb local_sdkhb2 = this._sdkb;
        String str2 = z[10];
        local_sdkhb2._sdkb(str2);
      }
      else
      {
        if (!_sdkq)
        {
          ArrayList localArrayList1 = this._sdkf._sdkb().getLastScan().getAPs();
          Comparator localComparator1 = com.skyhookwireless._sdkgc.COMPARATOR;
          if (!_sdkhd._sdka(localArrayList1, localComparator1))
            throw new AssertionError();
        }
        if (!_sdkq)
        {
          ArrayList localArrayList2 = this._sdkf._sdkb().getLastScan().getAPs();
          Comparator localComparator2 = com.skyhookwireless._sdkgc.COMPARATOR;
          if (!_sdkhd._sdkb(localArrayList2, localComparator2))
            throw new AssertionError();
        }
        if (!_sdkg())
        {
          if (!this._sdko)
          {
            Cache localCache = this._sdke;
            ArrayList localArrayList3 = this._sdkf._sdkb().getLastScan().getAPs();
            _sdkzb local_sdkzb = new _sdkzb(localArrayList3, null, null);
            if (localCache.get(local_sdkzb) != null)
            {
              com.skyhookwireless._sdkhb local_sdkhb3 = this._sdkb;
              String str3 = z[8];
              local_sdkhb3._sdkb(str3);
            }
          }
        }
        else
        {
          this._sdki = true;
          _sdknc local_sdknc = this._sdkc;
          ScanHistory localScanHistory = this._sdkf._sdkd();
          if (!local_sdknc._sdka(localScanHistory))
          {
            com.skyhookwireless._sdkhb local_sdkhb4 = this._sdkb;
            String str4 = z[9];
            local_sdkhb4._sdkb(str4);
            _sdkf();
          }
          _sdkec local_sdkec = _sdkec._sdkd();
          this._sdkn = local_sdkec;
        }
      }
    }
  }
}

/* Location:           D:\Tools\extractapktools\extractapktools\dex2jar-0.0.7.11-SNAPSHOT\classes_dex2jar.jar
 * Qualified Name:     com.skyhookwireless.wps._sdkkc
 * JD-Core Version:    0.6.2
 */