package com.skyhookwireless.wps;

import com.skyhookwireless._sdkjc;
import com.skyhookwireless._sdktd;
import java.io.File;
import java.util.ArrayList;
import java.util.Collections;
import java.util.HashMap;
import java.util.Iterator;
import java.util.LinkedList;
import java.util.List;
import java.util.ListIterator;
import java.util.Map;

final class _sdkgc
{
  static final boolean _sdke;
  private static final String[] z;
  private final com.skyhookwireless._sdkhb _sdka;
  private final long _sdkb;
  private final _sdkcb _sdkc;
  private final List<_sdkhc> _sdkd;

  // ERROR //
  static
  {
    // Byte code:
    //   0: iconst_1
    //   1: istore_0
    //   2: bipush 39
    //   4: anewarray 21	java/lang/String
    //   7: astore_1
    //   8: ldc 23
    //   10: invokevirtual 27	java/lang/String:toCharArray	()[C
    //   13: astore_2
    //   14: aload_2
    //   15: arraylength
    //   16: istore_3
    //   17: iload_3
    //   18: iload_0
    //   19: if_icmpgt +9219 -> 9238
    //   22: iconst_0
    //   23: istore 4
    //   25: aload_2
    //   26: astore 5
    //   28: iload 4
    //   30: istore 6
    //   32: iload_3
    //   33: istore 7
    //   35: aload_2
    //   36: astore 8
    //   38: iload 7
    //   40: istore 9
    //   42: aload 8
    //   44: iload 4
    //   46: caload
    //   47: istore 10
    //   49: iload 6
    //   51: iconst_5
    //   52: irem
    //   53: tableswitch	default:+31 -> 84, 0:+7705->7758, 1:+7712->7765, 2:+7719->7772, 3:+7726->7779
    //   85: lstore_2
    //   86: istore 11
    //   88: iload 11
    //   90: iload 10
    //   92: ixor
    //   93: i2c
    //   94: istore 12
    //   96: aload 8
    //   98: iload 4
    //   100: iload 12
    //   102: castore
    //   103: iload 6
    //   105: iconst_1
    //   106: iadd
    //   107: istore 4
    //   109: iload 9
    //   111: ifne +18 -> 129
    //   114: aload 5
    //   116: astore 8
    //   118: iload 4
    //   120: istore 6
    //   122: iload 9
    //   124: istore 4
    //   126: goto -84 -> 42
    //   129: iload 9
    //   131: istore_3
    //   132: aload 5
    //   134: astore_2
    //   135: iload_3
    //   136: iload 4
    //   138: if_icmpgt -113 -> 25
    //   141: new 21	java/lang/String
    //   144: dup
    //   145: aload_2
    //   146: invokespecial 31	java/lang/String:<init>	([C)V
    //   149: invokevirtual 35	java/lang/String:intern	()Ljava/lang/String;
    //   152: astore 13
    //   154: aload_1
    //   155: iconst_0
    //   156: aload 13
    //   158: aastore
    //   159: ldc 37
    //   161: invokevirtual 27	java/lang/String:toCharArray	()[C
    //   164: astore 14
    //   166: aload 14
    //   168: arraylength
    //   169: istore 15
    //   171: iload 15
    //   173: iconst_1
    //   174: if_icmpgt +9058 -> 9232
    //   177: iconst_0
    //   178: istore 16
    //   180: aload 14
    //   182: astore 5
    //   184: iload 16
    //   186: istore 6
    //   188: iload 15
    //   190: istore 17
    //   192: aload 14
    //   194: astore 18
    //   196: iload 17
    //   198: istore 19
    //   200: aload 18
    //   202: iload 16
    //   204: caload
    //   205: istore 10
    //   207: iload 6
    //   209: iconst_5
    //   210: irem
    //   211: tableswitch	default:+29 -> 240, 0:+7575->7786, 1:+7582->7793, 2:+7589->7800, 3:+7596->7807
    //   241: lstore_2
    //   242: istore 20
    //   244: iload 20
    //   246: iload 10
    //   248: ixor
    //   249: i2c
    //   250: istore 21
    //   252: aload 18
    //   254: iload 16
    //   256: iload 21
    //   258: castore
    //   259: iload 6
    //   261: iconst_1
    //   262: iadd
    //   263: istore 16
    //   265: iload 19
    //   267: ifne +18 -> 285
    //   270: aload 5
    //   272: astore 18
    //   274: iload 16
    //   276: istore 22
    //   278: iload 19
    //   280: istore 16
    //   282: goto -82 -> 200
    //   285: iload 19
    //   287: istore 15
    //   289: aload 5
    //   291: astore 14
    //   293: iload 15
    //   295: iload 16
    //   297: if_icmpgt -117 -> 180
    //   300: new 21	java/lang/String
    //   303: dup
    //   304: aload 14
    //   306: invokespecial 31	java/lang/String:<init>	([C)V
    //   309: invokevirtual 35	java/lang/String:intern	()Ljava/lang/String;
    //   312: astore 23
    //   314: aload_1
    //   315: iconst_1
    //   316: aload 23
    //   318: aastore
    //   319: iconst_2
    //   320: istore 24
    //   322: ldc 39
    //   324: invokevirtual 27	java/lang/String:toCharArray	()[C
    //   327: astore 25
    //   329: aload 25
    //   331: arraylength
    //   332: istore 26
    //   334: iload 26
    //   336: iconst_1
    //   337: if_icmpgt +8889 -> 9226
    //   340: iconst_0
    //   341: istore 27
    //   343: aload 25
    //   345: astore 5
    //   347: iload 27
    //   349: istore 6
    //   351: iload 26
    //   353: istore 28
    //   355: aload 25
    //   357: astore 29
    //   359: iload 28
    //   361: istore 30
    //   363: aload 29
    //   365: iload 27
    //   367: caload
    //   368: istore 31
    //   370: iload 6
    //   372: iconst_5
    //   373: irem
    //   374: tableswitch	default:+30 -> 404, 0:+7440->7814, 1:+7447->7821, 2:+7454->7828, 3:+7461->7835
    //   405: lstore_2
    //   406: istore 32
    //   408: iload 32
    //   410: iload 31
    //   412: ixor
    //   413: i2c
    //   414: istore 33
    //   416: aload 29
    //   418: iload 27
    //   420: iload 33
    //   422: castore
    //   423: iload 6
    //   425: iconst_1
    //   426: iadd
    //   427: istore 27
    //   429: iload 30
    //   431: ifne +18 -> 449
    //   434: aload 5
    //   436: astore 29
    //   438: iload 27
    //   440: istore 34
    //   442: iload 30
    //   444: istore 27
    //   446: goto -83 -> 363
    //   449: iload 30
    //   451: istore 26
    //   453: aload 5
    //   455: astore 25
    //   457: iload 26
    //   459: iload 27
    //   461: if_icmpgt -118 -> 343
    //   464: new 21	java/lang/String
    //   467: dup
    //   468: aload 25
    //   470: invokespecial 31	java/lang/String:<init>	([C)V
    //   473: invokevirtual 35	java/lang/String:intern	()Ljava/lang/String;
    //   476: astore 35
    //   478: aload_1
    //   479: iload 24
    //   481: aload 35
    //   483: aastore
    //   484: iconst_3
    //   485: istore 36
    //   487: ldc 41
    //   489: invokevirtual 27	java/lang/String:toCharArray	()[C
    //   492: astore 37
    //   494: aload 37
    //   496: arraylength
    //   497: istore 38
    //   499: iload 38
    //   501: iconst_1
    //   502: if_icmpgt +8718 -> 9220
    //   505: iconst_0
    //   506: istore 39
    //   508: aload 37
    //   510: astore 5
    //   512: iload 39
    //   514: istore 6
    //   516: iload 38
    //   518: istore 40
    //   520: aload 37
    //   522: astore 41
    //   524: iload 40
    //   526: istore 42
    //   528: aload 41
    //   530: iload 39
    //   532: caload
    //   533: istore 31
    //   535: iload 6
    //   537: iconst_5
    //   538: irem
    //   539: tableswitch	default:+29 -> 568, 0:+7303->7842, 1:+7310->7849, 2:+7317->7856, 3:+7324->7863
    //   569: lstore_2
    //   570: istore 43
    //   572: iload 43
    //   574: iload 31
    //   576: ixor
    //   577: i2c
    //   578: istore 44
    //   580: aload 41
    //   582: iload 39
    //   584: iload 44
    //   586: castore
    //   587: iload 6
    //   589: iconst_1
    //   590: iadd
    //   591: istore 39
    //   593: iload 42
    //   595: ifne +18 -> 613
    //   598: aload 5
    //   600: astore 41
    //   602: iload 39
    //   604: istore 45
    //   606: iload 42
    //   608: istore 39
    //   610: goto -82 -> 528
    //   613: iload 42
    //   615: istore 38
    //   617: aload 5
    //   619: astore 37
    //   621: iload 38
    //   623: iload 39
    //   625: if_icmpgt -117 -> 508
    //   628: new 21	java/lang/String
    //   631: dup
    //   632: aload 37
    //   634: invokespecial 31	java/lang/String:<init>	([C)V
    //   637: invokevirtual 35	java/lang/String:intern	()Ljava/lang/String;
    //   640: astore 46
    //   642: aload_1
    //   643: iload 36
    //   645: aload 46
    //   647: aastore
    //   648: iconst_4
    //   649: istore 47
    //   651: ldc 43
    //   653: invokevirtual 27	java/lang/String:toCharArray	()[C
    //   656: astore 48
    //   658: aload 48
    //   660: arraylength
    //   661: istore 49
    //   663: iload 49
    //   665: iconst_1
    //   666: if_icmpgt +8548 -> 9214
    //   669: iconst_0
    //   670: istore 50
    //   672: aload 48
    //   674: astore 5
    //   676: iload 50
    //   678: istore 6
    //   680: iload 49
    //   682: istore 51
    //   684: aload 48
    //   686: astore 52
    //   688: iload 51
    //   690: istore 53
    //   692: aload 52
    //   694: iload 50
    //   696: caload
    //   697: istore 31
    //   699: iload 6
    //   701: iconst_5
    //   702: irem
    //   703: tableswitch	default:+29 -> 732, 0:+7167->7870, 1:+7174->7877, 2:+7181->7884, 3:+7188->7891
    //   733: lstore_2
    //   734: istore 54
    //   736: iload 54
    //   738: iload 31
    //   740: ixor
    //   741: i2c
    //   742: istore 55
    //   744: aload 52
    //   746: iload 50
    //   748: iload 55
    //   750: castore
    //   751: iload 6
    //   753: iconst_1
    //   754: iadd
    //   755: istore 50
    //   757: iload 53
    //   759: ifne +18 -> 777
    //   762: aload 5
    //   764: astore 52
    //   766: iload 50
    //   768: istore 56
    //   770: iload 53
    //   772: istore 50
    //   774: goto -82 -> 692
    //   777: iload 53
    //   779: istore 49
    //   781: aload 5
    //   783: astore 48
    //   785: iload 49
    //   787: iload 50
    //   789: if_icmpgt -117 -> 672
    //   792: new 21	java/lang/String
    //   795: dup
    //   796: aload 48
    //   798: invokespecial 31	java/lang/String:<init>	([C)V
    //   801: invokevirtual 35	java/lang/String:intern	()Ljava/lang/String;
    //   804: astore 57
    //   806: aload_1
    //   807: iload 47
    //   809: aload 57
    //   811: aastore
    //   812: iconst_5
    //   813: istore 58
    //   815: ldc 45
    //   817: invokevirtual 27	java/lang/String:toCharArray	()[C
    //   820: astore 59
    //   822: aload 59
    //   824: arraylength
    //   825: istore 60
    //   827: iload 60
    //   829: iconst_1
    //   830: if_icmpgt +8378 -> 9208
    //   833: iconst_0
    //   834: istore 61
    //   836: aload 59
    //   838: astore 5
    //   840: iload 61
    //   842: istore 6
    //   844: iload 60
    //   846: istore 62
    //   848: aload 59
    //   850: astore 63
    //   852: iload 62
    //   854: istore 64
    //   856: aload 63
    //   858: iload 61
    //   860: caload
    //   861: istore 31
    //   863: iload 6
    //   865: iconst_5
    //   866: irem
    //   867: tableswitch	default:+29 -> 896, 0:+7031->7898, 1:+7038->7905, 2:+7045->7912, 3:+7052->7919
    //   897: lstore_2
    //   898: istore 65
    //   900: iload 65
    //   902: iload 31
    //   904: ixor
    //   905: i2c
    //   906: istore 66
    //   908: aload 63
    //   910: iload 61
    //   912: iload 66
    //   914: castore
    //   915: iload 6
    //   917: iconst_1
    //   918: iadd
    //   919: istore 61
    //   921: iload 64
    //   923: ifne +18 -> 941
    //   926: aload 5
    //   928: astore 63
    //   930: iload 61
    //   932: istore 67
    //   934: iload 64
    //   936: istore 61
    //   938: goto -82 -> 856
    //   941: iload 64
    //   943: istore 60
    //   945: aload 5
    //   947: astore 59
    //   949: iload 60
    //   951: iload 61
    //   953: if_icmpgt -117 -> 836
    //   956: new 21	java/lang/String
    //   959: dup
    //   960: aload 59
    //   962: invokespecial 31	java/lang/String:<init>	([C)V
    //   965: invokevirtual 35	java/lang/String:intern	()Ljava/lang/String;
    //   968: astore 68
    //   970: aload_1
    //   971: iload 58
    //   973: aload 68
    //   975: aastore
    //   976: bipush 6
    //   978: istore 69
    //   980: ldc 47
    //   982: invokevirtual 27	java/lang/String:toCharArray	()[C
    //   985: astore 70
    //   987: aload 70
    //   989: arraylength
    //   990: istore 71
    //   992: iload 71
    //   994: iconst_1
    //   995: if_icmpgt +8207 -> 9202
    //   998: iconst_0
    //   999: istore 72
    //   1001: aload 70
    //   1003: astore 5
    //   1005: iload 72
    //   1007: istore 6
    //   1009: iload 71
    //   1011: istore 73
    //   1013: aload 70
    //   1015: astore 74
    //   1017: iload 73
    //   1019: istore 75
    //   1021: aload 74
    //   1023: iload 72
    //   1025: caload
    //   1026: istore 31
    //   1028: iload 6
    //   1030: iconst_5
    //   1031: irem
    //   1032: tableswitch	default:+32 -> 1064, 0:+6894->7926, 1:+6901->7933, 2:+6908->7940, 3:+6915->7947
    //   1065: lstore_2
    //   1066: istore 76
    //   1068: iload 76
    //   1070: iload 31
    //   1072: ixor
    //   1073: i2c
    //   1074: istore 77
    //   1076: aload 74
    //   1078: iload 72
    //   1080: iload 77
    //   1082: castore
    //   1083: iload 6
    //   1085: iconst_1
    //   1086: iadd
    //   1087: istore 72
    //   1089: iload 75
    //   1091: ifne +18 -> 1109
    //   1094: aload 5
    //   1096: astore 74
    //   1098: iload 72
    //   1100: istore 78
    //   1102: iload 75
    //   1104: istore 72
    //   1106: goto -85 -> 1021
    //   1109: iload 75
    //   1111: istore 71
    //   1113: aload 5
    //   1115: astore 70
    //   1117: iload 71
    //   1119: iload 72
    //   1121: if_icmpgt -120 -> 1001
    //   1124: new 21	java/lang/String
    //   1127: dup
    //   1128: aload 70
    //   1130: invokespecial 31	java/lang/String:<init>	([C)V
    //   1133: invokevirtual 35	java/lang/String:intern	()Ljava/lang/String;
    //   1136: astore 79
    //   1138: aload_1
    //   1139: iload 69
    //   1141: aload 79
    //   1143: aastore
    //   1144: bipush 7
    //   1146: istore 80
    //   1148: ldc 49
    //   1150: invokevirtual 27	java/lang/String:toCharArray	()[C
    //   1153: astore 81
    //   1155: aload 81
    //   1157: arraylength
    //   1158: istore 82
    //   1160: iload 82
    //   1162: iconst_1
    //   1163: if_icmpgt +8033 -> 9196
    //   1166: iconst_0
    //   1167: istore 83
    //   1169: aload 81
    //   1171: astore 5
    //   1173: iload 83
    //   1175: istore 6
    //   1177: iload 82
    //   1179: istore 84
    //   1181: aload 81
    //   1183: astore 85
    //   1185: iload 84
    //   1187: istore 86
    //   1189: aload 85
    //   1191: iload 83
    //   1193: caload
    //   1194: istore 31
    //   1196: iload 6
    //   1198: iconst_5
    //   1199: irem
    //   1200: tableswitch	default:+32 -> 1232, 0:+6754->7954, 1:+6761->7961, 2:+6768->7968, 3:+6775->7975
    //   1233: lstore_2
    //   1234: istore 87
    //   1236: iload 87
    //   1238: iload 31
    //   1240: ixor
    //   1241: i2c
    //   1242: istore 88
    //   1244: aload 85
    //   1246: iload 83
    //   1248: iload 88
    //   1250: castore
    //   1251: iload 6
    //   1253: iconst_1
    //   1254: iadd
    //   1255: istore 83
    //   1257: iload 86
    //   1259: ifne +18 -> 1277
    //   1262: aload 5
    //   1264: astore 85
    //   1266: iload 83
    //   1268: istore 89
    //   1270: iload 86
    //   1272: istore 83
    //   1274: goto -85 -> 1189
    //   1277: iload 86
    //   1279: istore 82
    //   1281: aload 5
    //   1283: astore 81
    //   1285: iload 82
    //   1287: iload 83
    //   1289: if_icmpgt -120 -> 1169
    //   1292: new 21	java/lang/String
    //   1295: dup
    //   1296: aload 81
    //   1298: invokespecial 31	java/lang/String:<init>	([C)V
    //   1301: invokevirtual 35	java/lang/String:intern	()Ljava/lang/String;
    //   1304: astore 90
    //   1306: aload_1
    //   1307: iload 80
    //   1309: aload 90
    //   1311: aastore
    //   1312: bipush 8
    //   1314: istore 91
    //   1316: ldc 51
    //   1318: invokevirtual 27	java/lang/String:toCharArray	()[C
    //   1321: astore 92
    //   1323: aload 92
    //   1325: arraylength
    //   1326: istore 93
    //   1328: iload 93
    //   1330: iconst_1
    //   1331: if_icmpgt +7859 -> 9190
    //   1334: iconst_0
    //   1335: istore 94
    //   1337: aload 92
    //   1339: astore 5
    //   1341: iload 94
    //   1343: istore 6
    //   1345: iload 93
    //   1347: istore 95
    //   1349: aload 92
    //   1351: astore 96
    //   1353: iload 95
    //   1355: istore 97
    //   1357: aload 96
    //   1359: iload 94
    //   1361: caload
    //   1362: istore 31
    //   1364: iload 6
    //   1366: iconst_5
    //   1367: irem
    //   1368: tableswitch	default:+32 -> 1400, 0:+6614->7982, 1:+6621->7989, 2:+6628->7996, 3:+6635->8003
    //   1401: lstore_2
    //   1402: istore 98
    //   1404: iload 98
    //   1406: iload 31
    //   1408: ixor
    //   1409: i2c
    //   1410: istore 99
    //   1412: aload 96
    //   1414: iload 94
    //   1416: iload 99
    //   1418: castore
    //   1419: iload 6
    //   1421: iconst_1
    //   1422: iadd
    //   1423: istore 94
    //   1425: iload 97
    //   1427: ifne +18 -> 1445
    //   1430: aload 5
    //   1432: astore 96
    //   1434: iload 94
    //   1436: istore 100
    //   1438: iload 97
    //   1440: istore 94
    //   1442: goto -85 -> 1357
    //   1445: iload 97
    //   1447: istore 93
    //   1449: aload 5
    //   1451: astore 92
    //   1453: iload 93
    //   1455: iload 94
    //   1457: if_icmpgt -120 -> 1337
    //   1460: new 21	java/lang/String
    //   1463: dup
    //   1464: aload 92
    //   1466: invokespecial 31	java/lang/String:<init>	([C)V
    //   1469: invokevirtual 35	java/lang/String:intern	()Ljava/lang/String;
    //   1472: astore 101
    //   1474: aload_1
    //   1475: iload 91
    //   1477: aload 101
    //   1479: aastore
    //   1480: bipush 9
    //   1482: istore 102
    //   1484: ldc 53
    //   1486: invokevirtual 27	java/lang/String:toCharArray	()[C
    //   1489: astore 103
    //   1491: aload 103
    //   1493: arraylength
    //   1494: istore 104
    //   1496: iload 104
    //   1498: iconst_1
    //   1499: if_icmpgt +7685 -> 9184
    //   1502: iconst_0
    //   1503: istore 105
    //   1505: aload 103
    //   1507: astore 5
    //   1509: iload 105
    //   1511: istore 6
    //   1513: iload 104
    //   1515: istore 106
    //   1517: aload 103
    //   1519: astore 107
    //   1521: iload 106
    //   1523: istore 108
    //   1525: aload 107
    //   1527: iload 105
    //   1529: caload
    //   1530: istore 31
    //   1532: iload 6
    //   1534: iconst_5
    //   1535: irem
    //   1536: tableswitch	default:+32 -> 1568, 0:+6474->8010, 1:+6481->8017, 2:+6488->8024, 3:+6495->8031
    //   1569: lstore_2
    //   1570: istore 109
    //   1572: iload 109
    //   1574: iload 31
    //   1576: ixor
    //   1577: i2c
    //   1578: istore 110
    //   1580: aload 107
    //   1582: iload 105
    //   1584: iload 110
    //   1586: castore
    //   1587: iload 6
    //   1589: iconst_1
    //   1590: iadd
    //   1591: istore 105
    //   1593: iload 108
    //   1595: ifne +18 -> 1613
    //   1598: aload 5
    //   1600: astore 107
    //   1602: iload 105
    //   1604: istore 111
    //   1606: iload 108
    //   1608: istore 105
    //   1610: goto -85 -> 1525
    //   1613: iload 108
    //   1615: istore 104
    //   1617: aload 5
    //   1619: astore 103
    //   1621: iload 104
    //   1623: iload 105
    //   1625: if_icmpgt -120 -> 1505
    //   1628: new 21	java/lang/String
    //   1631: dup
    //   1632: aload 103
    //   1634: invokespecial 31	java/lang/String:<init>	([C)V
    //   1637: invokevirtual 35	java/lang/String:intern	()Ljava/lang/String;
    //   1640: astore 112
    //   1642: aload_1
    //   1643: iload 102
    //   1645: aload 112
    //   1647: aastore
    //   1648: bipush 10
    //   1650: istore 113
    //   1652: ldc 55
    //   1654: invokevirtual 27	java/lang/String:toCharArray	()[C
    //   1657: astore 114
    //   1659: aload 114
    //   1661: arraylength
    //   1662: istore 115
    //   1664: iload 115
    //   1666: iconst_1
    //   1667: if_icmpgt +7511 -> 9178
    //   1670: iconst_0
    //   1671: istore 116
    //   1673: aload 114
    //   1675: astore 5
    //   1677: iload 116
    //   1679: istore 6
    //   1681: iload 115
    //   1683: istore 117
    //   1685: aload 114
    //   1687: astore 118
    //   1689: iload 117
    //   1691: istore 119
    //   1693: aload 118
    //   1695: iload 116
    //   1697: caload
    //   1698: istore 31
    //   1700: iload 6
    //   1702: iconst_5
    //   1703: irem
    //   1704: tableswitch	default:+32 -> 1736, 0:+6334->8038, 1:+6341->8045, 2:+6348->8052, 3:+6355->8059
    //   1737: lstore_2
    //   1738: istore 120
    //   1740: iload 120
    //   1742: iload 31
    //   1744: ixor
    //   1745: i2c
    //   1746: istore 121
    //   1748: aload 118
    //   1750: iload 116
    //   1752: iload 121
    //   1754: castore
    //   1755: iload 6
    //   1757: iconst_1
    //   1758: iadd
    //   1759: istore 116
    //   1761: iload 119
    //   1763: ifne +18 -> 1781
    //   1766: aload 5
    //   1768: astore 118
    //   1770: iload 116
    //   1772: istore 122
    //   1774: iload 119
    //   1776: istore 116
    //   1778: goto -85 -> 1693
    //   1781: iload 119
    //   1783: istore 115
    //   1785: aload 5
    //   1787: astore 114
    //   1789: iload 115
    //   1791: iload 116
    //   1793: if_icmpgt -120 -> 1673
    //   1796: new 21	java/lang/String
    //   1799: dup
    //   1800: aload 114
    //   1802: invokespecial 31	java/lang/String:<init>	([C)V
    //   1805: invokevirtual 35	java/lang/String:intern	()Ljava/lang/String;
    //   1808: astore 123
    //   1810: aload_1
    //   1811: iload 113
    //   1813: aload 123
    //   1815: aastore
    //   1816: bipush 11
    //   1818: istore 124
    //   1820: ldc 57
    //   1822: invokevirtual 27	java/lang/String:toCharArray	()[C
    //   1825: astore 125
    //   1827: aload 125
    //   1829: arraylength
    //   1830: istore 126
    //   1832: iload 126
    //   1834: iconst_1
    //   1835: if_icmpgt +7337 -> 9172
    //   1838: iconst_0
    //   1839: istore 127
    //   1841: aload 125
    //   1843: astore 5
    //   1845: iload 127
    //   1847: istore 6
    //   1849: iload 126
    //   1851: istore 128
    //   1853: aload 125
    //   1855: astore 129
    //   1857: iload 128
    //   1859: istore 130
    //   1861: aload 129
    //   1863: iload 127
    //   1865: caload
    //   1866: istore 31
    //   1868: iload 6
    //   1870: iconst_5
    //   1871: irem
    //   1872: tableswitch	default:+32 -> 1904, 0:+6194->8066, 1:+6201->8073, 2:+6208->8080, 3:+6215->8087
    //   1905: lstore_2
    //   1906: istore 131
    //   1908: iload 131
    //   1910: iload 31
    //   1912: ixor
    //   1913: i2c
    //   1914: istore 132
    //   1916: aload 129
    //   1918: iload 127
    //   1920: iload 132
    //   1922: castore
    //   1923: iload 6
    //   1925: iconst_1
    //   1926: iadd
    //   1927: istore 127
    //   1929: iload 130
    //   1931: ifne +18 -> 1949
    //   1934: aload 5
    //   1936: astore 129
    //   1938: iload 127
    //   1940: istore 133
    //   1942: iload 130
    //   1944: istore 127
    //   1946: goto -85 -> 1861
    //   1949: iload 130
    //   1951: istore 126
    //   1953: aload 5
    //   1955: astore 125
    //   1957: iload 126
    //   1959: iload 127
    //   1961: if_icmpgt -120 -> 1841
    //   1964: new 21	java/lang/String
    //   1967: dup
    //   1968: aload 125
    //   1970: invokespecial 31	java/lang/String:<init>	([C)V
    //   1973: invokevirtual 35	java/lang/String:intern	()Ljava/lang/String;
    //   1976: astore 134
    //   1978: aload_1
    //   1979: iload 124
    //   1981: aload 134
    //   1983: aastore
    //   1984: bipush 12
    //   1986: istore 135
    //   1988: ldc 59
    //   1990: invokevirtual 27	java/lang/String:toCharArray	()[C
    //   1993: astore 136
    //   1995: aload 136
    //   1997: arraylength
    //   1998: istore 137
    //   2000: iload 137
    //   2002: iconst_1
    //   2003: if_icmpgt +7163 -> 9166
    //   2006: iconst_0
    //   2007: istore 138
    //   2009: aload 136
    //   2011: astore 5
    //   2013: iload 138
    //   2015: istore 6
    //   2017: iload 137
    //   2019: istore 139
    //   2021: aload 136
    //   2023: astore 140
    //   2025: iload 139
    //   2027: istore 141
    //   2029: aload 140
    //   2031: iload 138
    //   2033: caload
    //   2034: istore 31
    //   2036: iload 6
    //   2038: iconst_5
    //   2039: irem
    //   2040: tableswitch	default:+32 -> 2072, 0:+6054->8094, 1:+6061->8101, 2:+6068->8108, 3:+6075->8115
    //   2073: lstore_2
    //   2074: istore 142
    //   2076: iload 142
    //   2078: iload 31
    //   2080: ixor
    //   2081: i2c
    //   2082: istore 143
    //   2084: aload 140
    //   2086: iload 138
    //   2088: iload 143
    //   2090: castore
    //   2091: iload 6
    //   2093: iconst_1
    //   2094: iadd
    //   2095: istore 138
    //   2097: iload 141
    //   2099: ifne +18 -> 2117
    //   2102: aload 5
    //   2104: astore 140
    //   2106: iload 138
    //   2108: istore 144
    //   2110: iload 141
    //   2112: istore 138
    //   2114: goto -85 -> 2029
    //   2117: iload 141
    //   2119: istore 137
    //   2121: aload 5
    //   2123: astore 136
    //   2125: iload 137
    //   2127: iload 138
    //   2129: if_icmpgt -120 -> 2009
    //   2132: new 21	java/lang/String
    //   2135: dup
    //   2136: aload 136
    //   2138: invokespecial 31	java/lang/String:<init>	([C)V
    //   2141: invokevirtual 35	java/lang/String:intern	()Ljava/lang/String;
    //   2144: astore 145
    //   2146: aload_1
    //   2147: iload 135
    //   2149: aload 145
    //   2151: aastore
    //   2152: bipush 13
    //   2154: istore 146
    //   2156: ldc 61
    //   2158: invokevirtual 27	java/lang/String:toCharArray	()[C
    //   2161: astore 147
    //   2163: aload 147
    //   2165: arraylength
    //   2166: istore 148
    //   2168: iload 148
    //   2170: iconst_1
    //   2171: if_icmpgt +6989 -> 9160
    //   2174: iconst_0
    //   2175: istore 149
    //   2177: aload 147
    //   2179: astore 5
    //   2181: iload 149
    //   2183: istore 6
    //   2185: iload 148
    //   2187: istore 150
    //   2189: aload 147
    //   2191: astore 151
    //   2193: iload 150
    //   2195: istore 152
    //   2197: aload 151
    //   2199: iload 149
    //   2201: caload
    //   2202: istore 31
    //   2204: iload 6
    //   2206: iconst_5
    //   2207: irem
    //   2208: tableswitch	default:+32 -> 2240, 0:+5914->8122, 1:+5921->8129, 2:+5928->8136, 3:+5935->8143
    //   2241: lstore_2
    //   2242: istore 153
    //   2244: iload 153
    //   2246: iload 31
    //   2248: ixor
    //   2249: i2c
    //   2250: istore 154
    //   2252: aload 151
    //   2254: iload 149
    //   2256: iload 154
    //   2258: castore
    //   2259: iload 6
    //   2261: iconst_1
    //   2262: iadd
    //   2263: istore 149
    //   2265: iload 152
    //   2267: ifne +18 -> 2285
    //   2270: aload 5
    //   2272: astore 151
    //   2274: iload 149
    //   2276: istore 155
    //   2278: iload 152
    //   2280: istore 149
    //   2282: goto -85 -> 2197
    //   2285: iload 152
    //   2287: istore 148
    //   2289: aload 5
    //   2291: astore 147
    //   2293: iload 148
    //   2295: iload 149
    //   2297: if_icmpgt -120 -> 2177
    //   2300: new 21	java/lang/String
    //   2303: dup
    //   2304: aload 147
    //   2306: invokespecial 31	java/lang/String:<init>	([C)V
    //   2309: invokevirtual 35	java/lang/String:intern	()Ljava/lang/String;
    //   2312: astore 156
    //   2314: aload_1
    //   2315: iload 146
    //   2317: aload 156
    //   2319: aastore
    //   2320: bipush 14
    //   2322: istore 157
    //   2324: ldc 63
    //   2326: invokevirtual 27	java/lang/String:toCharArray	()[C
    //   2329: astore 158
    //   2331: aload 158
    //   2333: arraylength
    //   2334: istore 159
    //   2336: iload 159
    //   2338: iconst_1
    //   2339: if_icmpgt +6815 -> 9154
    //   2342: iconst_0
    //   2343: istore 160
    //   2345: aload 158
    //   2347: astore 5
    //   2349: iload 160
    //   2351: istore 6
    //   2353: iload 159
    //   2355: istore 161
    //   2357: aload 158
    //   2359: astore 162
    //   2361: iload 161
    //   2363: istore 163
    //   2365: aload 162
    //   2367: iload 160
    //   2369: caload
    //   2370: istore 31
    //   2372: iload 6
    //   2374: iconst_5
    //   2375: irem
    //   2376: tableswitch	default:+32 -> 2408, 0:+5774->8150, 1:+5781->8157, 2:+5788->8164, 3:+5795->8171
    //   2409: lstore_2
    //   2410: istore 164
    //   2412: iload 164
    //   2414: iload 31
    //   2416: ixor
    //   2417: i2c
    //   2418: istore 165
    //   2420: aload 162
    //   2422: iload 160
    //   2424: iload 165
    //   2426: castore
    //   2427: iload 6
    //   2429: iconst_1
    //   2430: iadd
    //   2431: istore 160
    //   2433: iload 163
    //   2435: ifne +18 -> 2453
    //   2438: aload 5
    //   2440: astore 162
    //   2442: iload 160
    //   2444: istore 166
    //   2446: iload 163
    //   2448: istore 160
    //   2450: goto -85 -> 2365
    //   2453: iload 163
    //   2455: istore 159
    //   2457: aload 5
    //   2459: astore 158
    //   2461: iload 159
    //   2463: iload 160
    //   2465: if_icmpgt -120 -> 2345
    //   2468: new 21	java/lang/String
    //   2471: dup
    //   2472: aload 158
    //   2474: invokespecial 31	java/lang/String:<init>	([C)V
    //   2477: invokevirtual 35	java/lang/String:intern	()Ljava/lang/String;
    //   2480: astore 167
    //   2482: aload_1
    //   2483: iload 157
    //   2485: aload 167
    //   2487: aastore
    //   2488: bipush 15
    //   2490: istore 168
    //   2492: ldc 65
    //   2494: invokevirtual 27	java/lang/String:toCharArray	()[C
    //   2497: astore 169
    //   2499: aload 169
    //   2501: arraylength
    //   2502: istore 170
    //   2504: iload 170
    //   2506: iconst_1
    //   2507: if_icmpgt +6641 -> 9148
    //   2510: iconst_0
    //   2511: istore 171
    //   2513: aload 169
    //   2515: astore 5
    //   2517: iload 171
    //   2519: istore 6
    //   2521: iload 170
    //   2523: istore 172
    //   2525: aload 169
    //   2527: astore 173
    //   2529: iload 172
    //   2531: istore 174
    //   2533: aload 173
    //   2535: iload 171
    //   2537: caload
    //   2538: istore 31
    //   2540: iload 6
    //   2542: iconst_5
    //   2543: irem
    //   2544: tableswitch	default:+32 -> 2576, 0:+5634->8178, 1:+5641->8185, 2:+5648->8192, 3:+5655->8199
    //   2577: lstore_2
    //   2578: istore 175
    //   2580: iload 175
    //   2582: iload 31
    //   2584: ixor
    //   2585: i2c
    //   2586: istore 176
    //   2588: aload 173
    //   2590: iload 171
    //   2592: iload 176
    //   2594: castore
    //   2595: iload 6
    //   2597: iconst_1
    //   2598: iadd
    //   2599: istore 171
    //   2601: iload 174
    //   2603: ifne +18 -> 2621
    //   2606: aload 5
    //   2608: astore 173
    //   2610: iload 171
    //   2612: istore 177
    //   2614: iload 174
    //   2616: istore 171
    //   2618: goto -85 -> 2533
    //   2621: iload 174
    //   2623: istore 170
    //   2625: aload 5
    //   2627: astore 169
    //   2629: iload 170
    //   2631: iload 171
    //   2633: if_icmpgt -120 -> 2513
    //   2636: new 21	java/lang/String
    //   2639: dup
    //   2640: aload 169
    //   2642: invokespecial 31	java/lang/String:<init>	([C)V
    //   2645: invokevirtual 35	java/lang/String:intern	()Ljava/lang/String;
    //   2648: astore 178
    //   2650: aload_1
    //   2651: iload 168
    //   2653: aload 178
    //   2655: aastore
    //   2656: bipush 16
    //   2658: istore 179
    //   2660: ldc 67
    //   2662: invokevirtual 27	java/lang/String:toCharArray	()[C
    //   2665: astore 180
    //   2667: aload 180
    //   2669: arraylength
    //   2670: istore 181
    //   2672: iload 181
    //   2674: iconst_1
    //   2675: if_icmpgt +6467 -> 9142
    //   2678: iconst_0
    //   2679: istore 182
    //   2681: aload 180
    //   2683: astore 5
    //   2685: iload 182
    //   2687: istore 6
    //   2689: iload 181
    //   2691: istore 183
    //   2693: aload 180
    //   2695: astore 184
    //   2697: iload 183
    //   2699: istore 185
    //   2701: aload 184
    //   2703: iload 182
    //   2705: caload
    //   2706: istore 31
    //   2708: iload 6
    //   2710: iconst_5
    //   2711: irem
    //   2712: tableswitch	default:+32 -> 2744, 0:+5494->8206, 1:+5501->8213, 2:+5508->8220, 3:+5515->8227
    //   2745: lstore_2
    //   2746: istore 186
    //   2748: iload 186
    //   2750: iload 31
    //   2752: ixor
    //   2753: i2c
    //   2754: istore 187
    //   2756: aload 184
    //   2758: iload 182
    //   2760: iload 187
    //   2762: castore
    //   2763: iload 6
    //   2765: iconst_1
    //   2766: iadd
    //   2767: istore 182
    //   2769: iload 185
    //   2771: ifne +18 -> 2789
    //   2774: aload 5
    //   2776: astore 184
    //   2778: iload 182
    //   2780: istore 188
    //   2782: iload 185
    //   2784: istore 182
    //   2786: goto -85 -> 2701
    //   2789: iload 185
    //   2791: istore 181
    //   2793: aload 5
    //   2795: astore 180
    //   2797: iload 181
    //   2799: iload 182
    //   2801: if_icmpgt -120 -> 2681
    //   2804: new 21	java/lang/String
    //   2807: dup
    //   2808: aload 180
    //   2810: invokespecial 31	java/lang/String:<init>	([C)V
    //   2813: invokevirtual 35	java/lang/String:intern	()Ljava/lang/String;
    //   2816: astore 189
    //   2818: aload_1
    //   2819: iload 179
    //   2821: aload 189
    //   2823: aastore
    //   2824: bipush 17
    //   2826: istore 190
    //   2828: ldc 69
    //   2830: invokevirtual 27	java/lang/String:toCharArray	()[C
    //   2833: astore 191
    //   2835: aload 191
    //   2837: arraylength
    //   2838: istore 192
    //   2840: iload 192
    //   2842: iconst_1
    //   2843: if_icmpgt +6293 -> 9136
    //   2846: iconst_0
    //   2847: istore 193
    //   2849: aload 191
    //   2851: astore 5
    //   2853: iload 193
    //   2855: istore 6
    //   2857: iload 192
    //   2859: istore 194
    //   2861: aload 191
    //   2863: astore 195
    //   2865: iload 194
    //   2867: istore 196
    //   2869: aload 195
    //   2871: iload 193
    //   2873: caload
    //   2874: istore 31
    //   2876: iload 6
    //   2878: iconst_5
    //   2879: irem
    //   2880: tableswitch	default:+32 -> 2912, 0:+5354->8234, 1:+5361->8241, 2:+5368->8248, 3:+5375->8255
    //   2913: lstore_2
    //   2914: istore 197
    //   2916: iload 197
    //   2918: iload 31
    //   2920: ixor
    //   2921: i2c
    //   2922: istore 198
    //   2924: aload 195
    //   2926: iload 193
    //   2928: iload 198
    //   2930: castore
    //   2931: iload 6
    //   2933: iconst_1
    //   2934: iadd
    //   2935: istore 193
    //   2937: iload 196
    //   2939: ifne +18 -> 2957
    //   2942: aload 5
    //   2944: astore 195
    //   2946: iload 193
    //   2948: istore 199
    //   2950: iload 196
    //   2952: istore 193
    //   2954: goto -85 -> 2869
    //   2957: iload 196
    //   2959: istore 192
    //   2961: aload 5
    //   2963: astore 191
    //   2965: iload 192
    //   2967: iload 193
    //   2969: if_icmpgt -120 -> 2849
    //   2972: new 21	java/lang/String
    //   2975: dup
    //   2976: aload 191
    //   2978: invokespecial 31	java/lang/String:<init>	([C)V
    //   2981: invokevirtual 35	java/lang/String:intern	()Ljava/lang/String;
    //   2984: astore 200
    //   2986: aload_1
    //   2987: iload 190
    //   2989: aload 200
    //   2991: aastore
    //   2992: bipush 18
    //   2994: istore 201
    //   2996: ldc 71
    //   2998: invokevirtual 27	java/lang/String:toCharArray	()[C
    //   3001: astore 202
    //   3003: aload 202
    //   3005: arraylength
    //   3006: istore 203
    //   3008: iload 203
    //   3010: iconst_1
    //   3011: if_icmpgt +6119 -> 9130
    //   3014: iconst_0
    //   3015: istore 204
    //   3017: aload 202
    //   3019: astore 5
    //   3021: iload 204
    //   3023: istore 6
    //   3025: iload 203
    //   3027: istore 205
    //   3029: aload 202
    //   3031: astore 206
    //   3033: iload 205
    //   3035: istore 207
    //   3037: aload 206
    //   3039: iload 204
    //   3041: caload
    //   3042: istore 31
    //   3044: iload 6
    //   3046: iconst_5
    //   3047: irem
    //   3048: tableswitch	default:+32 -> 3080, 0:+5214->8262, 1:+5221->8269, 2:+5228->8276, 3:+5235->8283
    //   3081: lstore_2
    //   3082: istore 208
    //   3084: iload 208
    //   3086: iload 31
    //   3088: ixor
    //   3089: i2c
    //   3090: istore 209
    //   3092: aload 206
    //   3094: iload 204
    //   3096: iload 209
    //   3098: castore
    //   3099: iload 6
    //   3101: iconst_1
    //   3102: iadd
    //   3103: istore 204
    //   3105: iload 207
    //   3107: ifne +18 -> 3125
    //   3110: aload 5
    //   3112: astore 206
    //   3114: iload 204
    //   3116: istore 210
    //   3118: iload 207
    //   3120: istore 204
    //   3122: goto -85 -> 3037
    //   3125: iload 207
    //   3127: istore 203
    //   3129: aload 5
    //   3131: astore 202
    //   3133: iload 203
    //   3135: iload 204
    //   3137: if_icmpgt -120 -> 3017
    //   3140: new 21	java/lang/String
    //   3143: dup
    //   3144: aload 202
    //   3146: invokespecial 31	java/lang/String:<init>	([C)V
    //   3149: invokevirtual 35	java/lang/String:intern	()Ljava/lang/String;
    //   3152: astore 211
    //   3154: aload_1
    //   3155: iload 201
    //   3157: aload 211
    //   3159: aastore
    //   3160: bipush 19
    //   3162: istore 212
    //   3164: ldc 73
    //   3166: invokevirtual 27	java/lang/String:toCharArray	()[C
    //   3169: astore 213
    //   3171: aload 213
    //   3173: arraylength
    //   3174: istore 214
    //   3176: iload 214
    //   3178: iconst_1
    //   3179: if_icmpgt +5945 -> 9124
    //   3182: iconst_0
    //   3183: istore 215
    //   3185: aload 213
    //   3187: astore 5
    //   3189: iload 215
    //   3191: istore 6
    //   3193: iload 214
    //   3195: istore 216
    //   3197: aload 213
    //   3199: astore 217
    //   3201: iload 216
    //   3203: istore 218
    //   3205: aload 217
    //   3207: iload 215
    //   3209: caload
    //   3210: istore 31
    //   3212: iload 6
    //   3214: iconst_5
    //   3215: irem
    //   3216: tableswitch	default:+32 -> 3248, 0:+5074->8290, 1:+5081->8297, 2:+5088->8304, 3:+5095->8311
    //   3249: lstore_2
    //   3250: istore 219
    //   3252: iload 219
    //   3254: iload 31
    //   3256: ixor
    //   3257: i2c
    //   3258: istore 220
    //   3260: aload 217
    //   3262: iload 215
    //   3264: iload 220
    //   3266: castore
    //   3267: iload 6
    //   3269: iconst_1
    //   3270: iadd
    //   3271: istore 215
    //   3273: iload 218
    //   3275: ifne +18 -> 3293
    //   3278: aload 5
    //   3280: astore 217
    //   3282: iload 215
    //   3284: istore 221
    //   3286: iload 218
    //   3288: istore 215
    //   3290: goto -85 -> 3205
    //   3293: iload 218
    //   3295: istore 214
    //   3297: aload 5
    //   3299: astore 213
    //   3301: iload 214
    //   3303: iload 215
    //   3305: if_icmpgt -120 -> 3185
    //   3308: new 21	java/lang/String
    //   3311: dup
    //   3312: aload 213
    //   3314: invokespecial 31	java/lang/String:<init>	([C)V
    //   3317: invokevirtual 35	java/lang/String:intern	()Ljava/lang/String;
    //   3320: astore 222
    //   3322: aload_1
    //   3323: iload 212
    //   3325: aload 222
    //   3327: aastore
    //   3328: bipush 20
    //   3330: istore 223
    //   3332: ldc 75
    //   3334: invokevirtual 27	java/lang/String:toCharArray	()[C
    //   3337: astore 224
    //   3339: aload 224
    //   3341: arraylength
    //   3342: istore 225
    //   3344: iload 225
    //   3346: iconst_1
    //   3347: if_icmpgt +5771 -> 9118
    //   3350: iconst_0
    //   3351: istore 226
    //   3353: aload 224
    //   3355: astore 5
    //   3357: iload 226
    //   3359: istore 6
    //   3361: iload 225
    //   3363: istore 227
    //   3365: aload 224
    //   3367: astore 228
    //   3369: iload 227
    //   3371: istore 229
    //   3373: aload 228
    //   3375: iload 226
    //   3377: caload
    //   3378: istore 31
    //   3380: iload 6
    //   3382: iconst_5
    //   3383: irem
    //   3384: tableswitch	default:+32 -> 3416, 0:+4934->8318, 1:+4941->8325, 2:+4948->8332, 3:+4955->8339
    //   3417: lstore_2
    //   3418: istore 230
    //   3420: iload 230
    //   3422: iload 31
    //   3424: ixor
    //   3425: i2c
    //   3426: istore 231
    //   3428: aload 228
    //   3430: iload 226
    //   3432: iload 231
    //   3434: castore
    //   3435: iload 6
    //   3437: iconst_1
    //   3438: iadd
    //   3439: istore 226
    //   3441: iload 229
    //   3443: ifne +18 -> 3461
    //   3446: aload 5
    //   3448: astore 228
    //   3450: iload 226
    //   3452: istore 232
    //   3454: iload 229
    //   3456: istore 226
    //   3458: goto -85 -> 3373
    //   3461: iload 229
    //   3463: istore 225
    //   3465: aload 5
    //   3467: astore 224
    //   3469: iload 225
    //   3471: iload 226
    //   3473: if_icmpgt -120 -> 3353
    //   3476: new 21	java/lang/String
    //   3479: dup
    //   3480: aload 224
    //   3482: invokespecial 31	java/lang/String:<init>	([C)V
    //   3485: invokevirtual 35	java/lang/String:intern	()Ljava/lang/String;
    //   3488: astore 233
    //   3490: aload_1
    //   3491: iload 223
    //   3493: aload 233
    //   3495: aastore
    //   3496: bipush 21
    //   3498: istore 234
    //   3500: ldc 77
    //   3502: invokevirtual 27	java/lang/String:toCharArray	()[C
    //   3505: astore 235
    //   3507: aload 235
    //   3509: arraylength
    //   3510: istore 236
    //   3512: iload 236
    //   3514: iconst_1
    //   3515: if_icmpgt +5597 -> 9112
    //   3518: iconst_0
    //   3519: istore 237
    //   3521: aload 235
    //   3523: astore 5
    //   3525: iload 237
    //   3527: istore 6
    //   3529: iload 236
    //   3531: istore 238
    //   3533: aload 235
    //   3535: astore 239
    //   3537: iload 238
    //   3539: istore 240
    //   3541: aload 239
    //   3543: iload 237
    //   3545: caload
    //   3546: istore 31
    //   3548: iload 6
    //   3550: iconst_5
    //   3551: irem
    //   3552: tableswitch	default:+32 -> 3584, 0:+4794->8346, 1:+4801->8353, 2:+4808->8360, 3:+4815->8367
    //   3585: lstore_2
    //   3586: istore 241
    //   3588: iload 241
    //   3590: iload 31
    //   3592: ixor
    //   3593: i2c
    //   3594: istore 242
    //   3596: aload 239
    //   3598: iload 237
    //   3600: iload 242
    //   3602: castore
    //   3603: iload 6
    //   3605: iconst_1
    //   3606: iadd
    //   3607: istore 237
    //   3609: iload 240
    //   3611: ifne +18 -> 3629
    //   3614: aload 5
    //   3616: astore 239
    //   3618: iload 237
    //   3620: istore 243
    //   3622: iload 240
    //   3624: istore 237
    //   3626: goto -85 -> 3541
    //   3629: iload 240
    //   3631: istore 236
    //   3633: aload 5
    //   3635: astore 235
    //   3637: iload 236
    //   3639: iload 237
    //   3641: if_icmpgt -120 -> 3521
    //   3644: new 21	java/lang/String
    //   3647: dup
    //   3648: aload 235
    //   3650: invokespecial 31	java/lang/String:<init>	([C)V
    //   3653: invokevirtual 35	java/lang/String:intern	()Ljava/lang/String;
    //   3656: astore 244
    //   3658: aload_1
    //   3659: iload 234
    //   3661: aload 244
    //   3663: aastore
    //   3664: bipush 22
    //   3666: istore 245
    //   3668: ldc 79
    //   3670: invokevirtual 27	java/lang/String:toCharArray	()[C
    //   3673: astore 246
    //   3675: aload 246
    //   3677: arraylength
    //   3678: istore 247
    //   3680: iload 247
    //   3682: iconst_1
    //   3683: if_icmpgt +5423 -> 9106
    //   3686: iconst_0
    //   3687: istore 248
    //   3689: aload 246
    //   3691: astore 5
    //   3693: iload 248
    //   3695: istore 6
    //   3697: iload 247
    //   3699: istore 249
    //   3701: aload 246
    //   3703: astore 250
    //   3705: iload 249
    //   3707: istore 251
    //   3709: aload 250
    //   3711: iload 248
    //   3713: caload
    //   3714: istore 31
    //   3716: iload 6
    //   3718: iconst_5
    //   3719: irem
    //   3720: tableswitch	default:+32 -> 3752, 0:+4654->8374, 1:+4661->8381, 2:+4668->8388, 3:+4675->8395
    //   3753: lstore_2
    //   3754: istore 252
    //   3756: iload 252
    //   3758: iload 31
    //   3760: ixor
    //   3761: i2c
    //   3762: istore 253
    //   3764: aload 250
    //   3766: iload 248
    //   3768: iload 253
    //   3770: castore
    //   3771: iload 6
    //   3773: iconst_1
    //   3774: iadd
    //   3775: istore 248
    //   3777: iload 251
    //   3779: ifne +18 -> 3797
    //   3782: aload 5
    //   3784: astore 250
    //   3786: iload 248
    //   3788: istore 254
    //   3790: iload 251
    //   3792: istore 248
    //   3794: goto -85 -> 3709
    //   3797: iload 251
    //   3799: istore 247
    //   3801: aload 5
    //   3803: astore 246
    //   3805: iload 247
    //   3807: iload 248
    //   3809: if_icmpgt -120 -> 3689
    //   3812: new 21	java/lang/String
    //   3815: dup
    //   3816: aload 246
    //   3818: invokespecial 31	java/lang/String:<init>	([C)V
    //   3821: invokevirtual 35	java/lang/String:intern	()Ljava/lang/String;
    //   3824: astore 255
    //   3826: aload_1
    //   3827: iload 245
    //   3829: aload 255
    //   3831: aastore
    //   3832: bipush 23
    //   3834: wide
    //   3838: ldc 81
    //   3840: invokevirtual 27	java/lang/String:toCharArray	()[C
    //   3843: wide
    //   3847: wide
    //   3851: arraylength
    //   3852: wide
    //   3856: wide
    //   3860: iconst_1
    //   3861: if_icmpgt +5237 -> 9098
    //   3864: iconst_0
    //   3865: wide
    //   3869: wide
    //   3873: astore 5
    //   3875: wide
    //   3879: istore 6
    //   3881: wide
    //   3885: wide
    //   3889: wide
    //   3893: wide
    //   3897: wide
    //   3901: wide
    //   3905: wide
    //   3909: wide
    //   3913: caload
    //   3914: istore 31
    //   3916: iload 6
    //   3918: iconst_5
    //   3919: irem
    //   3920: tableswitch	default:+32 -> 3952, 0:+4482->8402, 1:+4491->8411, 2:+4500->8420, 3:+4509->8429
    //   3953: lstore_2
    //   3954: wide
    //   3958: wide
    //   3962: iload 31
    //   3964: ixor
    //   3965: i2c
    //   3966: wide
    //   3970: wide
    //   3974: wide
    //   3978: wide
    //   3982: castore
    //   3983: iload 6
    //   3985: iconst_1
    //   3986: iadd
    //   3987: wide
    //   3991: wide
    //   3995: ifne +28 -> 4023
    //   3998: aload 5
    //   4000: wide
    //   4004: wide
    //   4008: wide
    //   4012: wide
    //   4016: wide
    //   4020: goto -115 -> 3905
    //   4023: wide
    //   4027: wide
    //   4031: aload 5
    //   4033: wide
    //   4037: wide
    //   4041: wide
    //   4045: if_icmpgt -176 -> 3869
    //   4048: new 21	java/lang/String
    //   4051: dup
    //   4052: wide
    //   4056: invokespecial 31	java/lang/String:<init>	([C)V
    //   4059: invokevirtual 35	java/lang/String:intern	()Ljava/lang/String;
    //   4062: wide
    //   4066: aload_1
    //   4067: wide
    //   4071: wide
    //   4075: aastore
    //   4076: bipush 24
    //   4078: wide
    //   4082: ldc 83
    //   4084: invokevirtual 27	java/lang/String:toCharArray	()[C
    //   4087: wide
    //   4091: wide
    //   4095: arraylength
    //   4096: wide
    //   4100: wide
    //   4104: iconst_1
    //   4105: if_icmpgt +4985 -> 9090
    //   4108: iconst_0
    //   4109: wide
    //   4113: wide
    //   4117: astore 5
    //   4119: wide
    //   4123: istore 6
    //   4125: wide
    //   4129: wide
    //   4133: wide
    //   4137: wide
    //   4141: wide
    //   4145: wide
    //   4149: wide
    //   4153: wide
    //   4157: caload
    //   4158: istore 31
    //   4160: iload 6
    //   4162: iconst_5
    //   4163: irem
    //   4164: tableswitch	default:+32 -> 4196, 0:+4274->8438, 1:+4283->8447, 2:+4292->8456, 3:+4301->8465
    //   4197: lstore_2
    //   4198: wide
    //   4202: wide
    //   4206: iload 31
    //   4208: ixor
    //   4209: i2c
    //   4210: wide
    //   4214: wide
    //   4218: wide
    //   4222: wide
    //   4226: castore
    //   4227: iload 6
    //   4229: iconst_1
    //   4230: iadd
    //   4231: wide
    //   4235: wide
    //   4239: ifne +28 -> 4267
    //   4242: aload 5
    //   4244: wide
    //   4248: wide
    //   4252: wide
    //   4256: wide
    //   4260: wide
    //   4264: goto -115 -> 4149
    //   4267: wide
    //   4271: wide
    //   4275: aload 5
    //   4277: wide
    //   4281: wide
    //   4285: wide
    //   4289: if_icmpgt -176 -> 4113
    //   4292: new 21	java/lang/String
    //   4295: dup
    //   4296: wide
    //   4300: invokespecial 31	java/lang/String:<init>	([C)V
    //   4303: invokevirtual 35	java/lang/String:intern	()Ljava/lang/String;
    //   4306: wide
    //   4310: aload_1
    //   4311: wide
    //   4315: wide
    //   4319: aastore
    //   4320: bipush 25
    //   4322: wide
    //   4326: ldc 85
    //   4328: invokevirtual 27	java/lang/String:toCharArray	()[C
    //   4331: wide
    //   4335: wide
    //   4339: arraylength
    //   4340: wide
    //   4344: wide
    //   4348: iconst_1
    //   4349: if_icmpgt +4733 -> 9082
    //   4352: iconst_0
    //   4353: wide
    //   4357: wide
    //   4361: astore 5
    //   4363: wide
    //   4367: istore 6
    //   4369: wide
    //   4373: wide
    //   4377: wide
    //   4381: wide
    //   4385: wide
    //   4389: wide
    //   4393: wide
    //   4397: wide
    //   4401: caload
    //   4402: istore 31
    //   4404: iload 6
    //   4406: iconst_5
    //   4407: irem
    //   4408: tableswitch	default:+32 -> 4440, 0:+4066->8474, 1:+4075->8483, 2:+4084->8492, 3:+4093->8501
    //   4441: lstore_2
    //   4442: wide
    //   4446: wide
    //   4450: iload 31
    //   4452: ixor
    //   4453: i2c
    //   4454: wide
    //   4458: wide
    //   4462: wide
    //   4466: wide
    //   4470: castore
    //   4471: iload 6
    //   4473: iconst_1
    //   4474: iadd
    //   4475: wide
    //   4479: wide
    //   4483: ifne +28 -> 4511
    //   4486: aload 5
    //   4488: wide
    //   4492: wide
    //   4496: wide
    //   4500: wide
    //   4504: wide
    //   4508: goto -115 -> 4393
    //   4511: wide
    //   4515: wide
    //   4519: aload 5
    //   4521: wide
    //   4525: wide
    //   4529: wide
    //   4533: if_icmpgt -176 -> 4357
    //   4536: new 21	java/lang/String
    //   4539: dup
    //   4540: wide
    //   4544: invokespecial 31	java/lang/String:<init>	([C)V
    //   4547: invokevirtual 35	java/lang/String:intern	()Ljava/lang/String;
    //   4550: wide
    //   4554: aload_1
    //   4555: wide
    //   4559: wide
    //   4563: aastore
    //   4564: bipush 26
    //   4566: wide
    //   4570: ldc 87
    //   4572: invokevirtual 27	java/lang/String:toCharArray	()[C
    //   4575: wide
    //   4579: wide
    //   4583: arraylength
    //   4584: wide
    //   4588: wide
    //   4592: iconst_1
    //   4593: if_icmpgt +4481 -> 9074
    //   4596: iconst_0
    //   4597: wide
    //   4601: wide
    //   4605: astore 5
    //   4607: wide
    //   4611: istore 6
    //   4613: wide
    //   4617: wide
    //   4621: wide
    //   4625: wide
    //   4629: wide
    //   4633: wide
    //   4637: wide
    //   4641: wide
    //   4645: caload
    //   4646: istore 31
    //   4648: iload 6
    //   4650: iconst_5
    //   4651: irem
    //   4652: tableswitch	default:+32 -> 4684, 0:+3858->8510, 1:+3867->8519, 2:+3876->8528, 3:+3885->8537
    //   4685: lstore_2
    //   4686: wide
    //   4690: wide
    //   4694: iload 31
    //   4696: ixor
    //   4697: i2c
    //   4698: wide
    //   4702: wide
    //   4706: wide
    //   4710: wide
    //   4714: castore
    //   4715: iload 6
    //   4717: iconst_1
    //   4718: iadd
    //   4719: wide
    //   4723: wide
    //   4727: ifne +28 -> 4755
    //   4730: aload 5
    //   4732: wide
    //   4736: wide
    //   4740: wide
    //   4744: wide
    //   4748: wide
    //   4752: goto -115 -> 4637
    //   4755: wide
    //   4759: wide
    //   4763: aload 5
    //   4765: wide
    //   4769: wide
    //   4773: wide
    //   4777: if_icmpgt -176 -> 4601
    //   4780: new 21	java/lang/String
    //   4783: dup
    //   4784: wide
    //   4788: invokespecial 31	java/lang/String:<init>	([C)V
    //   4791: invokevirtual 35	java/lang/String:intern	()Ljava/lang/String;
    //   4794: wide
    //   4798: aload_1
    //   4799: wide
    //   4803: wide
    //   4807: aastore
    //   4808: bipush 27
    //   4810: wide
    //   4814: ldc 89
    //   4816: invokevirtual 27	java/lang/String:toCharArray	()[C
    //   4819: wide
    //   4823: wide
    //   4827: arraylength
    //   4828: wide
    //   4832: wide
    //   4836: iconst_1
    //   4837: if_icmpgt +4229 -> 9066
    //   4840: iconst_0
    //   4841: wide
    //   4845: wide
    //   4849: astore 5
    //   4851: wide
    //   4855: istore 6
    //   4857: wide
    //   4861: wide
    //   4865: wide
    //   4869: wide
    //   4873: wide
    //   4877: wide
    //   4881: wide
    //   4885: wide
    //   4889: caload
    //   4890: istore 31
    //   4892: iload 6
    //   4894: iconst_5
    //   4895: irem
    //   4896: tableswitch	default:+32 -> 4928, 0:+3650->8546, 1:+3659->8555, 2:+3668->8564, 3:+3677->8573
    //   4929: lstore_2
    //   4930: wide
    //   4934: wide
    //   4938: iload 31
    //   4940: ixor
    //   4941: i2c
    //   4942: wide
    //   4946: wide
    //   4950: wide
    //   4954: wide
    //   4958: castore
    //   4959: iload 6
    //   4961: iconst_1
    //   4962: iadd
    //   4963: wide
    //   4967: wide
    //   4971: ifne +28 -> 4999
    //   4974: aload 5
    //   4976: wide
    //   4980: wide
    //   4984: wide
    //   4988: wide
    //   4992: wide
    //   4996: goto -115 -> 4881
    //   4999: wide
    //   5003: wide
    //   5007: aload 5
    //   5009: wide
    //   5013: wide
    //   5017: wide
    //   5021: if_icmpgt -176 -> 4845
    //   5024: new 21	java/lang/String
    //   5027: dup
    //   5028: wide
    //   5032: invokespecial 31	java/lang/String:<init>	([C)V
    //   5035: invokevirtual 35	java/lang/String:intern	()Ljava/lang/String;
    //   5038: wide
    //   5042: aload_1
    //   5043: wide
    //   5047: wide
    //   5051: aastore
    //   5052: bipush 28
    //   5054: wide
    //   5058: ldc 91
    //   5060: invokevirtual 27	java/lang/String:toCharArray	()[C
    //   5063: wide
    //   5067: wide
    //   5071: arraylength
    //   5072: wide
    //   5076: wide
    //   5080: iconst_1
    //   5081: if_icmpgt +3977 -> 9058
    //   5084: iconst_0
    //   5085: wide
    //   5089: wide
    //   5093: astore 5
    //   5095: wide
    //   5099: istore 6
    //   5101: wide
    //   5105: wide
    //   5109: wide
    //   5113: wide
    //   5117: wide
    //   5121: wide
    //   5125: wide
    //   5129: wide
    //   5133: caload
    //   5134: istore 31
    //   5136: iload 6
    //   5138: iconst_5
    //   5139: irem
    //   5140: tableswitch	default:+32 -> 5172, 0:+3442->8582, 1:+3451->8591, 2:+3460->8600, 3:+3469->8609
    //   5173: lstore_2
    //   5174: wide
    //   5178: wide
    //   5182: iload 31
    //   5184: ixor
    //   5185: i2c
    //   5186: wide
    //   5190: wide
    //   5194: wide
    //   5198: wide
    //   5202: castore
    //   5203: iload 6
    //   5205: iconst_1
    //   5206: iadd
    //   5207: wide
    //   5211: wide
    //   5215: ifne +28 -> 5243
    //   5218: aload 5
    //   5220: wide
    //   5224: wide
    //   5228: wide
    //   5232: wide
    //   5236: wide
    //   5240: goto -115 -> 5125
    //   5243: wide
    //   5247: wide
    //   5251: aload 5
    //   5253: wide
    //   5257: wide
    //   5261: wide
    //   5265: if_icmpgt -176 -> 5089
    //   5268: new 21	java/lang/String
    //   5271: dup
    //   5272: wide
    //   5276: invokespecial 31	java/lang/String:<init>	([C)V
    //   5279: invokevirtual 35	java/lang/String:intern	()Ljava/lang/String;
    //   5282: wide
    //   5286: aload_1
    //   5287: wide
    //   5291: wide
    //   5295: aastore
    //   5296: bipush 29
    //   5298: wide
    //   5302: ldc 93
    //   5304: invokevirtual 27	java/lang/String:toCharArray	()[C
    //   5307: wide
    //   5311: wide
    //   5315: arraylength
    //   5316: wide
    //   5320: wide
    //   5324: iconst_1
    //   5325: if_icmpgt +3725 -> 9050
    //   5328: iconst_0
    //   5329: wide
    //   5333: wide
    //   5337: astore 5
    //   5339: wide
    //   5343: istore 6
    //   5345: wide
    //   5349: wide
    //   5353: wide
    //   5357: wide
    //   5361: wide
    //   5365: wide
    //   5369: wide
    //   5373: wide
    //   5377: caload
    //   5378: istore 31
    //   5380: iload 6
    //   5382: iconst_5
    //   5383: irem
    //   5384: tableswitch	default:+32 -> 5416, 0:+3234->8618, 1:+3243->8627, 2:+3252->8636, 3:+3261->8645
    //   5417: lstore_2
    //   5418: wide
    //   5422: wide
    //   5426: iload 31
    //   5428: ixor
    //   5429: i2c
    //   5430: wide
    //   5434: wide
    //   5438: wide
    //   5442: wide
    //   5446: castore
    //   5447: iload 6
    //   5449: iconst_1
    //   5450: iadd
    //   5451: wide
    //   5455: wide
    //   5459: ifne +28 -> 5487
    //   5462: aload 5
    //   5464: wide
    //   5468: wide
    //   5472: wide
    //   5476: wide
    //   5480: wide
    //   5484: goto -115 -> 5369
    //   5487: wide
    //   5491: wide
    //   5495: aload 5
    //   5497: wide
    //   5501: wide
    //   5505: wide
    //   5509: if_icmpgt -176 -> 5333
    //   5512: new 21	java/lang/String
    //   5515: dup
    //   5516: wide
    //   5520: invokespecial 31	java/lang/String:<init>	([C)V
    //   5523: invokevirtual 35	java/lang/String:intern	()Ljava/lang/String;
    //   5526: wide
    //   5530: aload_1
    //   5531: wide
    //   5535: wide
    //   5539: aastore
    //   5540: bipush 30
    //   5542: wide
    //   5546: ldc 95
    //   5548: invokevirtual 27	java/lang/String:toCharArray	()[C
    //   5551: wide
    //   5555: wide
    //   5559: arraylength
    //   5560: wide
    //   5564: wide
    //   5568: iconst_1
    //   5569: if_icmpgt +3473 -> 9042
    //   5572: iconst_0
    //   5573: wide
    //   5577: wide
    //   5581: astore 5
    //   5583: wide
    //   5587: istore 6
    //   5589: wide
    //   5593: wide
    //   5597: wide
    //   5601: wide
    //   5605: wide
    //   5609: wide
    //   5613: wide
    //   5617: wide
    //   5621: caload
    //   5622: istore 31
    //   5624: iload 6
    //   5626: iconst_5
    //   5627: irem
    //   5628: tableswitch	default:+32 -> 5660, 0:+3026->8654, 1:+3035->8663, 2:+3044->8672, 3:+3053->8681
    //   5661: lstore_2
    //   5662: wide
    //   5666: wide
    //   5670: iload 31
    //   5672: ixor
    //   5673: i2c
    //   5674: wide
    //   5678: wide
    //   5682: wide
    //   5686: wide
    //   5690: castore
    //   5691: iload 6
    //   5693: iconst_1
    //   5694: iadd
    //   5695: wide
    //   5699: wide
    //   5703: ifne +28 -> 5731
    //   5706: aload 5
    //   5708: wide
    //   5712: wide
    //   5716: wide
    //   5720: wide
    //   5724: wide
    //   5728: goto -115 -> 5613
    //   5731: wide
    //   5735: wide
    //   5739: aload 5
    //   5741: wide
    //   5745: wide
    //   5749: wide
    //   5753: if_icmpgt -176 -> 5577
    //   5756: new 21	java/lang/String
    //   5759: dup
    //   5760: wide
    //   5764: invokespecial 31	java/lang/String:<init>	([C)V
    //   5767: invokevirtual 35	java/lang/String:intern	()Ljava/lang/String;
    //   5770: wide
    //   5774: aload_1
    //   5775: wide
    //   5779: wide
    //   5783: aastore
    //   5784: bipush 31
    //   5786: wide
    //   5790: ldc 97
    //   5792: invokevirtual 27	java/lang/String:toCharArray	()[C
    //   5795: wide
    //   5799: wide
    //   5803: arraylength
    //   5804: wide
    //   5808: wide
    //   5812: iconst_1
    //   5813: if_icmpgt +3221 -> 9034
    //   5816: iconst_0
    //   5817: wide
    //   5821: wide
    //   5825: astore 5
    //   5827: wide
    //   5831: istore 6
    //   5833: wide
    //   5837: wide
    //   5841: wide
    //   5845: wide
    //   5849: wide
    //   5853: wide
    //   5857: wide
    //   5861: wide
    //   5865: caload
    //   5866: istore 31
    //   5868: iload 6
    //   5870: iconst_5
    //   5871: irem
    //   5872: tableswitch	default:+32 -> 5904, 0:+2818->8690, 1:+2827->8699, 2:+2836->8708, 3:+2845->8717
    //   5905: lstore_2
    //   5906: wide
    //   5910: wide
    //   5914: iload 31
    //   5916: ixor
    //   5917: i2c
    //   5918: wide
    //   5922: wide
    //   5926: wide
    //   5930: wide
    //   5934: castore
    //   5935: iload 6
    //   5937: iconst_1
    //   5938: iadd
    //   5939: wide
    //   5943: wide
    //   5947: ifne +28 -> 5975
    //   5950: aload 5
    //   5952: wide
    //   5956: wide
    //   5960: wide
    //   5964: wide
    //   5968: wide
    //   5972: goto -115 -> 5857
    //   5975: wide
    //   5979: wide
    //   5983: aload 5
    //   5985: wide
    //   5989: wide
    //   5993: wide
    //   5997: if_icmpgt -176 -> 5821
    //   6000: new 21	java/lang/String
    //   6003: dup
    //   6004: wide
    //   6008: invokespecial 31	java/lang/String:<init>	([C)V
    //   6011: invokevirtual 35	java/lang/String:intern	()Ljava/lang/String;
    //   6014: wide
    //   6018: aload_1
    //   6019: wide
    //   6023: wide
    //   6027: aastore
    //   6028: bipush 32
    //   6030: wide
    //   6034: ldc 99
    //   6036: invokevirtual 27	java/lang/String:toCharArray	()[C
    //   6039: wide
    //   6043: wide
    //   6047: arraylength
    //   6048: wide
    //   6052: wide
    //   6056: iconst_1
    //   6057: if_icmpgt +2969 -> 9026
    //   6060: iconst_0
    //   6061: wide
    //   6065: wide
    //   6069: astore 5
    //   6071: wide
    //   6075: istore 6
    //   6077: wide
    //   6081: wide
    //   6085: wide
    //   6089: wide
    //   6093: wide
    //   6097: wide
    //   6101: wide
    //   6105: wide
    //   6109: caload
    //   6110: istore 31
    //   6112: iload 6
    //   6114: iconst_5
    //   6115: irem
    //   6116: tableswitch	default:+32 -> 6148, 0:+2610->8726, 1:+2619->8735, 2:+2628->8744, 3:+2637->8753
    //   6149: lstore_2
    //   6150: wide
    //   6154: wide
    //   6158: iload 31
    //   6160: ixor
    //   6161: i2c
    //   6162: wide
    //   6166: wide
    //   6170: wide
    //   6174: wide
    //   6178: castore
    //   6179: iload 6
    //   6181: iconst_1
    //   6182: iadd
    //   6183: wide
    //   6187: wide
    //   6191: ifne +28 -> 6219
    //   6194: aload 5
    //   6196: wide
    //   6200: wide
    //   6204: wide
    //   6208: wide
    //   6212: wide
    //   6216: goto -115 -> 6101
    //   6219: wide
    //   6223: wide
    //   6227: aload 5
    //   6229: wide
    //   6233: wide
    //   6237: wide
    //   6241: if_icmpgt -176 -> 6065
    //   6244: new 21	java/lang/String
    //   6247: dup
    //   6248: wide
    //   6252: invokespecial 31	java/lang/String:<init>	([C)V
    //   6255: invokevirtual 35	java/lang/String:intern	()Ljava/lang/String;
    //   6258: wide
    //   6262: aload_1
    //   6263: wide
    //   6267: wide
    //   6271: aastore
    //   6272: bipush 33
    //   6274: wide
    //   6278: ldc 101
    //   6280: invokevirtual 27	java/lang/String:toCharArray	()[C
    //   6283: wide
    //   6287: wide
    //   6291: arraylength
    //   6292: wide
    //   6296: wide
    //   6300: iconst_1
    //   6301: if_icmpgt +2717 -> 9018
    //   6304: iconst_0
    //   6305: wide
    //   6309: wide
    //   6313: astore 5
    //   6315: wide
    //   6319: istore 6
    //   6321: wide
    //   6325: wide
    //   6329: wide
    //   6333: wide
    //   6337: wide
    //   6341: wide
    //   6345: wide
    //   6349: wide
    //   6353: caload
    //   6354: istore 31
    //   6356: iload 6
    //   6358: iconst_5
    //   6359: irem
    //   6360: tableswitch	default:+32 -> 6392, 0:+2402->8762, 1:+2411->8771, 2:+2420->8780, 3:+2429->8789
    //   6393: lstore_2
    //   6394: wide
    //   6398: wide
    //   6402: iload 31
    //   6404: ixor
    //   6405: i2c
    //   6406: wide
    //   6410: wide
    //   6414: wide
    //   6418: wide
    //   6422: castore
    //   6423: iload 6
    //   6425: iconst_1
    //   6426: iadd
    //   6427: wide
    //   6431: wide
    //   6435: ifne +28 -> 6463
    //   6438: aload 5
    //   6440: wide
    //   6444: wide
    //   6448: wide
    //   6452: wide
    //   6456: wide
    //   6460: goto -115 -> 6345
    //   6463: wide
    //   6467: wide
    //   6471: aload 5
    //   6473: wide
    //   6477: wide
    //   6481: wide
    //   6485: if_icmpgt -176 -> 6309
    //   6488: new 21	java/lang/String
    //   6491: dup
    //   6492: wide
    //   6496: invokespecial 31	java/lang/String:<init>	([C)V
    //   6499: invokevirtual 35	java/lang/String:intern	()Ljava/lang/String;
    //   6502: wide
    //   6506: aload_1
    //   6507: wide
    //   6511: wide
    //   6515: aastore
    //   6516: bipush 34
    //   6518: wide
    //   6522: ldc 103
    //   6524: invokevirtual 27	java/lang/String:toCharArray	()[C
    //   6527: wide
    //   6531: wide
    //   6535: arraylength
    //   6536: wide
    //   6540: wide
    //   6544: iconst_1
    //   6545: if_icmpgt +2465 -> 9010
    //   6548: iconst_0
    //   6549: wide
    //   6553: wide
    //   6557: astore 5
    //   6559: wide
    //   6563: istore 6
    //   6565: wide
    //   6569: wide
    //   6573: wide
    //   6577: wide
    //   6581: wide
    //   6585: wide
    //   6589: wide
    //   6593: wide
    //   6597: caload
    //   6598: istore 31
    //   6600: iload 6
    //   6602: iconst_5
    //   6603: irem
    //   6604: tableswitch	default:+32 -> 6636, 0:+2194->8798, 1:+2203->8807, 2:+2212->8816, 3:+2221->8825
    //   6637: lstore_2
    //   6638: wide
    //   6642: wide
    //   6646: iload 31
    //   6648: ixor
    //   6649: i2c
    //   6650: wide
    //   6654: wide
    //   6658: wide
    //   6662: wide
    //   6666: castore
    //   6667: iload 6
    //   6669: iconst_1
    //   6670: iadd
    //   6671: wide
    //   6675: wide
    //   6679: ifne +28 -> 6707
    //   6682: aload 5
    //   6684: wide
    //   6688: wide
    //   6692: wide
    //   6696: wide
    //   6700: wide
    //   6704: goto -115 -> 6589
    //   6707: wide
    //   6711: wide
    //   6715: aload 5
    //   6717: wide
    //   6721: wide
    //   6725: wide
    //   6729: if_icmpgt -176 -> 6553
    //   6732: new 21	java/lang/String
    //   6735: dup
    //   6736: wide
    //   6740: invokespecial 31	java/lang/String:<init>	([C)V
    //   6743: invokevirtual 35	java/lang/String:intern	()Ljava/lang/String;
    //   6746: wide
    //   6750: aload_1
    //   6751: wide
    //   6755: wide
    //   6759: aastore
    //   6760: bipush 35
    //   6762: wide
    //   6766: ldc 105
    //   6768: invokevirtual 27	java/lang/String:toCharArray	()[C
    //   6771: wide
    //   6775: wide
    //   6779: arraylength
    //   6780: wide
    //   6784: wide
    //   6788: iconst_1
    //   6789: if_icmpgt +2213 -> 9002
    //   6792: iconst_0
    //   6793: wide
    //   6797: wide
    //   6801: astore 5
    //   6803: wide
    //   6807: istore 6
    //   6809: wide
    //   6813: wide
    //   6817: wide
    //   6821: wide
    //   6825: wide
    //   6829: wide
    //   6833: wide
    //   6837: wide
    //   6841: caload
    //   6842: istore 31
    //   6844: iload 6
    //   6846: iconst_5
    //   6847: irem
    //   6848: tableswitch	default:+32 -> 6880, 0:+1986->8834, 1:+1995->8843, 2:+2004->8852, 3:+2013->8861
    //   6881: lstore_2
    //   6882: wide
    //   6886: wide
    //   6890: iload 31
    //   6892: ixor
    //   6893: i2c
    //   6894: wide
    //   6898: wide
    //   6902: wide
    //   6906: wide
    //   6910: castore
    //   6911: iload 6
    //   6913: iconst_1
    //   6914: iadd
    //   6915: wide
    //   6919: wide
    //   6923: ifne +28 -> 6951
    //   6926: aload 5
    //   6928: wide
    //   6932: wide
    //   6936: wide
    //   6940: wide
    //   6944: wide
    //   6948: goto -115 -> 6833
    //   6951: wide
    //   6955: wide
    //   6959: aload 5
    //   6961: wide
    //   6965: wide
    //   6969: wide
    //   6973: if_icmpgt -176 -> 6797
    //   6976: new 21	java/lang/String
    //   6979: dup
    //   6980: wide
    //   6984: invokespecial 31	java/lang/String:<init>	([C)V
    //   6987: invokevirtual 35	java/lang/String:intern	()Ljava/lang/String;
    //   6990: wide
    //   6994: aload_1
    //   6995: wide
    //   6999: wide
    //   7003: aastore
    //   7004: bipush 36
    //   7006: wide
    //   7010: ldc 107
    //   7012: invokevirtual 27	java/lang/String:toCharArray	()[C
    //   7015: wide
    //   7019: wide
    //   7023: arraylength
    //   7024: wide
    //   7028: wide
    //   7032: iconst_1
    //   7033: if_icmpgt +1961 -> 8994
    //   7036: iconst_0
    //   7037: wide
    //   7041: wide
    //   7045: astore 5
    //   7047: wide
    //   7051: istore 6
    //   7053: wide
    //   7057: wide
    //   7061: wide
    //   7065: wide
    //   7069: wide
    //   7073: wide
    //   7077: wide
    //   7081: wide
    //   7085: caload
    //   7086: istore 31
    //   7088: iload 6
    //   7090: iconst_5
    //   7091: irem
    //   7092: tableswitch	default:+32 -> 7124, 0:+1778->8870, 1:+1787->8879, 2:+1796->8888, 3:+1805->8897
    //   7125: lstore_2
    //   7126: wide
    //   7130: wide
    //   7134: iload 31
    //   7136: ixor
    //   7137: i2c
    //   7138: wide
    //   7142: wide
    //   7146: wide
    //   7150: wide
    //   7154: castore
    //   7155: iload 6
    //   7157: iconst_1
    //   7158: iadd
    //   7159: wide
    //   7163: wide
    //   7167: ifne +28 -> 7195
    //   7170: aload 5
    //   7172: wide
    //   7176: wide
    //   7180: wide
    //   7184: wide
    //   7188: wide
    //   7192: goto -115 -> 7077
    //   7195: wide
    //   7199: wide
    //   7203: aload 5
    //   7205: wide
    //   7209: wide
    //   7213: wide
    //   7217: if_icmpgt -176 -> 7041
    //   7220: new 21	java/lang/String
    //   7223: dup
    //   7224: wide
    //   7228: invokespecial 31	java/lang/String:<init>	([C)V
    //   7231: invokevirtual 35	java/lang/String:intern	()Ljava/lang/String;
    //   7234: wide
    //   7238: aload_1
    //   7239: wide
    //   7243: wide
    //   7247: aastore
    //   7248: bipush 37
    //   7250: wide
    //   7254: ldc 109
    //   7256: invokevirtual 27	java/lang/String:toCharArray	()[C
    //   7259: wide
    //   7263: wide
    //   7267: arraylength
    //   7268: wide
    //   7272: wide
    //   7276: iconst_1
    //   7277: if_icmpgt +1709 -> 8986
    //   7280: iconst_0
    //   7281: wide
    //   7285: wide
    //   7289: astore 5
    //   7291: wide
    //   7295: istore 6
    //   7297: wide
    //   7301: wide
    //   7305: wide
    //   7309: wide
    //   7313: wide
    //   7317: wide
    //   7321: wide
    //   7325: wide
    //   7329: caload
    //   7330: istore 31
    //   7332: iload 6
    //   7334: iconst_5
    //   7335: irem
    //   7336: tableswitch	default:+32 -> 7368, 0:+1570->8906, 1:+1579->8915, 2:+1588->8924, 3:+1597->8933
    //   7369: lstore_2
    //   7370: wide
    //   7374: wide
    //   7378: iload 31
    //   7380: ixor
    //   7381: i2c
    //   7382: wide
    //   7386: wide
    //   7390: wide
    //   7394: wide
    //   7398: castore
    //   7399: iload 6
    //   7401: iconst_1
    //   7402: iadd
    //   7403: wide
    //   7407: wide
    //   7411: ifne +28 -> 7439
    //   7414: aload 5
    //   7416: wide
    //   7420: wide
    //   7424: wide
    //   7428: wide
    //   7432: wide
    //   7436: goto -115 -> 7321
    //   7439: wide
    //   7443: wide
    //   7447: aload 5
    //   7449: wide
    //   7453: wide
    //   7457: wide
    //   7461: if_icmpgt -176 -> 7285
    //   7464: new 21	java/lang/String
    //   7467: dup
    //   7468: wide
    //   7472: invokespecial 31	java/lang/String:<init>	([C)V
    //   7475: invokevirtual 35	java/lang/String:intern	()Ljava/lang/String;
    //   7478: wide
    //   7482: aload_1
    //   7483: wide
    //   7487: wide
    //   7491: aastore
    //   7492: bipush 38
    //   7494: wide
    //   7498: ldc 111
    //   7500: invokevirtual 27	java/lang/String:toCharArray	()[C
    //   7503: wide
    //   7507: wide
    //   7511: arraylength
    //   7512: wide
    //   7516: wide
    //   7520: iconst_1
    //   7521: if_icmpgt +1457 -> 8978
    //   7524: iconst_0
    //   7525: wide
    //   7529: wide
    //   7533: astore 5
    //   7535: wide
    //   7539: istore 6
    //   7541: wide
    //   7545: wide
    //   7549: wide
    //   7553: wide
    //   7557: wide
    //   7561: wide
    //   7565: wide
    //   7569: wide
    //   7573: caload
    //   7574: istore 31
    //   7576: iload 6
    //   7578: iconst_5
    //   7579: irem
    //   7580: tableswitch	default:+32 -> 7612, 0:+1362->8942, 1:+1371->8951, 2:+1380->8960, 3:+1389->8969
    //   7613: lstore_2
    //   7614: wide
    //   7618: wide
    //   7622: iload 31
    //   7624: ixor
    //   7625: i2c
    //   7626: wide
    //   7630: wide
    //   7634: wide
    //   7638: wide
    //   7642: castore
    //   7643: iload 6
    //   7645: iconst_1
    //   7646: iadd
    //   7647: wide
    //   7651: wide
    //   7655: ifne +28 -> 7683
    //   7658: aload 5
    //   7660: wide
    //   7664: wide
    //   7668: wide
    //   7672: wide
    //   7676: wide
    //   7680: goto -115 -> 7565
    //   7683: wide
    //   7687: wide
    //   7691: aload 5
    //   7693: wide
    //   7697: wide
    //   7701: wide
    //   7705: if_icmpgt -176 -> 7529
    //   7708: new 21	java/lang/String
    //   7711: dup
    //   7712: wide
    //   7716: invokespecial 31	java/lang/String:<init>	([C)V
    //   7719: invokevirtual 35	java/lang/String:intern	()Ljava/lang/String;
    //   7722: wide
    //   7726: aload_1
    //   7727: wide
    //   7731: wide
    //   7735: aastore
    //   7736: aload_1
    //   7737: putstatic 113	com/skyhookwireless/wps/_sdkgc:z	[Ljava/lang/String;
    //   7740: ldc 2
    //   7742: invokevirtual 119	java/lang/Class:desiredAssertionStatus	()Z
    //   7745: ifne +8 -> 7753
    //   7748: iload_0
    //   7749: putstatic 121	com/skyhookwireless/wps/_sdkgc:_sdke	Z
    //   7752: return
    //   7753: iconst_0
    //   7754: istore_0
    //   7755: goto -7 -> 7748
    //   7758: bipush 115
    //   7760: istore 11
    //   7762: goto -7674 -> 88
    //   7765: bipush 52
    //   7767: istore 11
    //   7769: goto -7681 -> 88
    //   7772: bipush 123
    //   7774: istore 11
    //   7776: goto -7688 -> 88
    //   7779: bipush 64
    //   7781: istore 11
    //   7783: goto -7695 -> 88
    //   7786: bipush 115
    //   7788: istore 20
    //   7790: goto -7546 -> 244
    //   7793: bipush 52
    //   7795: istore 20
    //   7797: goto -7553 -> 244
    //   7800: bipush 123
    //   7802: istore 20
    //   7804: goto -7560 -> 244
    //   7807: bipush 64
    //   7809: istore 20
    //   7811: goto -7567 -> 244
    //   7814: bipush 115
    //   7816: istore 32
    //   7818: goto -7410 -> 408
    //   7821: bipush 52
    //   7823: istore 32
    //   7825: goto -7417 -> 408
    //   7828: bipush 123
    //   7830: istore 32
    //   7832: goto -7424 -> 408
    //   7835: bipush 64
    //   7837: istore 32
    //   7839: goto -7431 -> 408
    //   7842: bipush 115
    //   7844: istore 43
    //   7846: goto -7274 -> 572
    //   7849: bipush 52
    //   7851: istore 43
    //   7853: goto -7281 -> 572
    //   7856: bipush 123
    //   7858: istore 43
    //   7860: goto -7288 -> 572
    //   7863: bipush 64
    //   7865: istore 43
    //   7867: goto -7295 -> 572
    //   7870: bipush 115
    //   7872: istore 54
    //   7874: goto -7138 -> 736
    //   7877: bipush 52
    //   7879: istore 54
    //   7881: goto -7145 -> 736
    //   7884: bipush 123
    //   7886: istore 54
    //   7888: goto -7152 -> 736
    //   7891: bipush 64
    //   7893: istore 54
    //   7895: goto -7159 -> 736
    //   7898: bipush 115
    //   7900: istore 65
    //   7902: goto -7002 -> 900
    //   7905: bipush 52
    //   7907: istore 65
    //   7909: goto -7009 -> 900
    //   7912: bipush 123
    //   7914: istore 65
    //   7916: goto -7016 -> 900
    //   7919: bipush 64
    //   7921: istore 65
    //   7923: goto -7023 -> 900
    //   7926: bipush 115
    //   7928: istore 76
    //   7930: goto -6862 -> 1068
    //   7933: bipush 52
    //   7935: istore 76
    //   7937: goto -6869 -> 1068
    //   7940: bipush 123
    //   7942: istore 76
    //   7944: goto -6876 -> 1068
    //   7947: bipush 64
    //   7949: istore 76
    //   7951: goto -6883 -> 1068
    //   7954: bipush 115
    //   7956: istore 87
    //   7958: goto -6722 -> 1236
    //   7961: bipush 52
    //   7963: istore 87
    //   7965: goto -6729 -> 1236
    //   7968: bipush 123
    //   7970: istore 87
    //   7972: goto -6736 -> 1236
    //   7975: bipush 64
    //   7977: istore 87
    //   7979: goto -6743 -> 1236
    //   7982: bipush 115
    //   7984: istore 98
    //   7986: goto -6582 -> 1404
    //   7989: bipush 52
    //   7991: istore 98
    //   7993: goto -6589 -> 1404
    //   7996: bipush 123
    //   7998: istore 98
    //   8000: goto -6596 -> 1404
    //   8003: bipush 64
    //   8005: istore 98
    //   8007: goto -6603 -> 1404
    //   8010: bipush 115
    //   8012: istore 109
    //   8014: goto -6442 -> 1572
    //   8017: bipush 52
    //   8019: istore 109
    //   8021: goto -6449 -> 1572
    //   8024: bipush 123
    //   8026: istore 109
    //   8028: goto -6456 -> 1572
    //   8031: bipush 64
    //   8033: istore 109
    //   8035: goto -6463 -> 1572
    //   8038: bipush 115
    //   8040: istore 120
    //   8042: goto -6302 -> 1740
    //   8045: bipush 52
    //   8047: istore 120
    //   8049: goto -6309 -> 1740
    //   8052: bipush 123
    //   8054: istore 120
    //   8056: goto -6316 -> 1740
    //   8059: bipush 64
    //   8061: istore 120
    //   8063: goto -6323 -> 1740
    //   8066: bipush 115
    //   8068: istore 131
    //   8070: goto -6162 -> 1908
    //   8073: bipush 52
    //   8075: istore 131
    //   8077: goto -6169 -> 1908
    //   8080: bipush 123
    //   8082: istore 131
    //   8084: goto -6176 -> 1908
    //   8087: bipush 64
    //   8089: istore 131
    //   8091: goto -6183 -> 1908
    //   8094: bipush 115
    //   8096: istore 142
    //   8098: goto -6022 -> 2076
    //   8101: bipush 52
    //   8103: istore 142
    //   8105: goto -6029 -> 2076
    //   8108: bipush 123
    //   8110: istore 142
    //   8112: goto -6036 -> 2076
    //   8115: bipush 64
    //   8117: istore 142
    //   8119: goto -6043 -> 2076
    //   8122: bipush 115
    //   8124: istore 153
    //   8126: goto -5882 -> 2244
    //   8129: bipush 52
    //   8131: istore 153
    //   8133: goto -5889 -> 2244
    //   8136: bipush 123
    //   8138: istore 153
    //   8140: goto -5896 -> 2244
    //   8143: bipush 64
    //   8145: istore 153
    //   8147: goto -5903 -> 2244
    //   8150: bipush 115
    //   8152: istore 164
    //   8154: goto -5742 -> 2412
    //   8157: bipush 52
    //   8159: istore 164
    //   8161: goto -5749 -> 2412
    //   8164: bipush 123
    //   8166: istore 164
    //   8168: goto -5756 -> 2412
    //   8171: bipush 64
    //   8173: istore 164
    //   8175: goto -5763 -> 2412
    //   8178: bipush 115
    //   8180: istore 175
    //   8182: goto -5602 -> 2580
    //   8185: bipush 52
    //   8187: istore 175
    //   8189: goto -5609 -> 2580
    //   8192: bipush 123
    //   8194: istore 175
    //   8196: goto -5616 -> 2580
    //   8199: bipush 64
    //   8201: istore 175
    //   8203: goto -5623 -> 2580
    //   8206: bipush 115
    //   8208: istore 186
    //   8210: goto -5462 -> 2748
    //   8213: bipush 52
    //   8215: istore 186
    //   8217: goto -5469 -> 2748
    //   8220: bipush 123
    //   8222: istore 186
    //   8224: goto -5476 -> 2748
    //   8227: bipush 64
    //   8229: istore 186
    //   8231: goto -5483 -> 2748
    //   8234: bipush 115
    //   8236: istore 197
    //   8238: goto -5322 -> 2916
    //   8241: bipush 52
    //   8243: istore 197
    //   8245: goto -5329 -> 2916
    //   8248: bipush 123
    //   8250: istore 197
    //   8252: goto -5336 -> 2916
    //   8255: bipush 64
    //   8257: istore 197
    //   8259: goto -5343 -> 2916
    //   8262: bipush 115
    //   8264: istore 208
    //   8266: goto -5182 -> 3084
    //   8269: bipush 52
    //   8271: istore 208
    //   8273: goto -5189 -> 3084
    //   8276: bipush 123
    //   8278: istore 208
    //   8280: goto -5196 -> 3084
    //   8283: bipush 64
    //   8285: istore 208
    //   8287: goto -5203 -> 3084
    //   8290: bipush 115
    //   8292: istore 219
    //   8294: goto -5042 -> 3252
    //   8297: bipush 52
    //   8299: istore 219
    //   8301: goto -5049 -> 3252
    //   8304: bipush 123
    //   8306: istore 219
    //   8308: goto -5056 -> 3252
    //   8311: bipush 64
    //   8313: istore 219
    //   8315: goto -5063 -> 3252
    //   8318: bipush 115
    //   8320: istore 230
    //   8322: goto -4902 -> 3420
    //   8325: bipush 52
    //   8327: istore 230
    //   8329: goto -4909 -> 3420
    //   8332: bipush 123
    //   8334: istore 230
    //   8336: goto -4916 -> 3420
    //   8339: bipush 64
    //   8341: istore 230
    //   8343: goto -4923 -> 3420
    //   8346: bipush 115
    //   8348: istore 241
    //   8350: goto -4762 -> 3588
    //   8353: bipush 52
    //   8355: istore 241
    //   8357: goto -4769 -> 3588
    //   8360: bipush 123
    //   8362: istore 241
    //   8364: goto -4776 -> 3588
    //   8367: bipush 64
    //   8369: istore 241
    //   8371: goto -4783 -> 3588
    //   8374: bipush 115
    //   8376: istore 252
    //   8378: goto -4622 -> 3756
    //   8381: bipush 52
    //   8383: istore 252
    //   8385: goto -4629 -> 3756
    //   8388: bipush 123
    //   8390: istore 252
    //   8392: goto -4636 -> 3756
    //   8395: bipush 64
    //   8397: istore 252
    //   8399: goto -4643 -> 3756
    //   8402: bipush 115
    //   8404: wide
    //   8408: goto -4450 -> 3958
    //   8411: bipush 52
    //   8413: wide
    //   8417: goto -4459 -> 3958
    //   8420: bipush 123
    //   8422: wide
    //   8426: goto -4468 -> 3958
    //   8429: bipush 64
    //   8431: wide
    //   8435: goto -4477 -> 3958
    //   8438: bipush 115
    //   8440: wide
    //   8444: goto -4242 -> 4202
    //   8447: bipush 52
    //   8449: wide
    //   8453: goto -4251 -> 4202
    //   8456: bipush 123
    //   8458: wide
    //   8462: goto -4260 -> 4202
    //   8465: bipush 64
    //   8467: wide
    //   8471: goto -4269 -> 4202
    //   8474: bipush 115
    //   8476: wide
    //   8480: goto -4034 -> 4446
    //   8483: bipush 52
    //   8485: wide
    //   8489: goto -4043 -> 4446
    //   8492: bipush 123
    //   8494: wide
    //   8498: goto -4052 -> 4446
    //   8501: bipush 64
    //   8503: wide
    //   8507: goto -4061 -> 4446
    //   8510: bipush 115
    //   8512: wide
    //   8516: goto -3826 -> 4690
    //   8519: bipush 52
    //   8521: wide
    //   8525: goto -3835 -> 4690
    //   8528: bipush 123
    //   8530: wide
    //   8534: goto -3844 -> 4690
    //   8537: bipush 64
    //   8539: wide
    //   8543: goto -3853 -> 4690
    //   8546: bipush 115
    //   8548: wide
    //   8552: goto -3618 -> 4934
    //   8555: bipush 52
    //   8557: wide
    //   8561: goto -3627 -> 4934
    //   8564: bipush 123
    //   8566: wide
    //   8570: goto -3636 -> 4934
    //   8573: bipush 64
    //   8575: wide
    //   8579: goto -3645 -> 4934
    //   8582: bipush 115
    //   8584: wide
    //   8588: goto -3410 -> 5178
    //   8591: bipush 52
    //   8593: wide
    //   8597: goto -3419 -> 5178
    //   8600: bipush 123
    //   8602: wide
    //   8606: goto -3428 -> 5178
    //   8609: bipush 64
    //   8611: wide
    //   8615: goto -3437 -> 5178
    //   8618: bipush 115
    //   8620: wide
    //   8624: goto -3202 -> 5422
    //   8627: bipush 52
    //   8629: wide
    //   8633: goto -3211 -> 5422
    //   8636: bipush 123
    //   8638: wide
    //   8642: goto -3220 -> 5422
    //   8645: bipush 64
    //   8647: wide
    //   8651: goto -3229 -> 5422
    //   8654: bipush 115
    //   8656: wide
    //   8660: goto -2994 -> 5666
    //   8663: bipush 52
    //   8665: wide
    //   8669: goto -3003 -> 5666
    //   8672: bipush 123
    //   8674: wide
    //   8678: goto -3012 -> 5666
    //   8681: bipush 64
    //   8683: wide
    //   8687: goto -3021 -> 5666
    //   8690: bipush 115
    //   8692: wide
    //   8696: goto -2786 -> 5910
    //   8699: bipush 52
    //   8701: wide
    //   8705: goto -2795 -> 5910
    //   8708: bipush 123
    //   8710: wide
    //   8714: goto -2804 -> 5910
    //   8717: bipush 64
    //   8719: wide
    //   8723: goto -2813 -> 5910
    //   8726: bipush 115
    //   8728: wide
    //   8732: goto -2578 -> 6154
    //   8735: bipush 52
    //   8737: wide
    //   8741: goto -2587 -> 6154
    //   8744: bipush 123
    //   8746: wide
    //   8750: goto -2596 -> 6154
    //   8753: bipush 64
    //   8755: wide
    //   8759: goto -2605 -> 6154
    //   8762: bipush 115
    //   8764: wide
    //   8768: goto -2370 -> 6398
    //   8771: bipush 52
    //   8773: wide
    //   8777: goto -2379 -> 6398
    //   8780: bipush 123
    //   8782: wide
    //   8786: goto -2388 -> 6398
    //   8789: bipush 64
    //   8791: wide
    //   8795: goto -2397 -> 6398
    //   8798: bipush 115
    //   8800: wide
    //   8804: goto -2162 -> 6642
    //   8807: bipush 52
    //   8809: wide
    //   8813: goto -2171 -> 6642
    //   8816: bipush 123
    //   8818: wide
    //   8822: goto -2180 -> 6642
    //   8825: bipush 64
    //   8827: wide
    //   8831: goto -2189 -> 6642
    //   8834: bipush 115
    //   8836: wide
    //   8840: goto -1954 -> 6886
    //   8843: bipush 52
    //   8845: wide
    //   8849: goto -1963 -> 6886
    //   8852: bipush 123
    //   8854: wide
    //   8858: goto -1972 -> 6886
    //   8861: bipush 64
    //   8863: wide
    //   8867: goto -1981 -> 6886
    //   8870: bipush 115
    //   8872: wide
    //   8876: goto -1746 -> 7130
    //   8879: bipush 52
    //   8881: wide
    //   8885: goto -1755 -> 7130
    //   8888: bipush 123
    //   8890: wide
    //   8894: goto -1764 -> 7130
    //   8897: bipush 64
    //   8899: wide
    //   8903: goto -1773 -> 7130
    //   8906: bipush 115
    //   8908: wide
    //   8912: goto -1538 -> 7374
    //   8915: bipush 52
    //   8917: wide
    //   8921: goto -1547 -> 7374
    //   8924: bipush 123
    //   8926: wide
    //   8930: goto -1556 -> 7374
    //   8933: bipush 64
    //   8935: wide
    //   8939: goto -1565 -> 7374
    //   8942: bipush 115
    //   8944: wide
    //   8948: goto -1330 -> 7618
    //   8951: bipush 52
    //   8953: wide
    //   8957: goto -1339 -> 7618
    //   8960: bipush 123
    //   8962: wide
    //   8966: goto -1348 -> 7618
    //   8969: bipush 64
    //   8971: wide
    //   8975: goto -1357 -> 7618
    //   8978: iconst_0
    //   8979: wide
    //   8983: goto -1286 -> 7697
    //   8986: iconst_0
    //   8987: wide
    //   8991: goto -1538 -> 7453
    //   8994: iconst_0
    //   8995: wide
    //   8999: goto -1790 -> 7209
    //   9002: iconst_0
    //   9003: wide
    //   9007: goto -2042 -> 6965
    //   9010: iconst_0
    //   9011: wide
    //   9015: goto -2294 -> 6721
    //   9018: iconst_0
    //   9019: wide
    //   9023: goto -2546 -> 6477
    //   9026: iconst_0
    //   9027: wide
    //   9031: goto -2798 -> 6233
    //   9034: iconst_0
    //   9035: wide
    //   9039: goto -3050 -> 5989
    //   9042: iconst_0
    //   9043: wide
    //   9047: goto -3302 -> 5745
    //   9050: iconst_0
    //   9051: wide
    //   9055: goto -3554 -> 5501
    //   9058: iconst_0
    //   9059: wide
    //   9063: goto -3806 -> 5257
    //   9066: iconst_0
    //   9067: wide
    //   9071: goto -4058 -> 5013
    //   9074: iconst_0
    //   9075: wide
    //   9079: goto -4310 -> 4769
    //   9082: iconst_0
    //   9083: wide
    //   9087: goto -4562 -> 4525
    //   9090: iconst_0
    //   9091: wide
    //   9095: goto -4814 -> 4281
    //   9098: iconst_0
    //   9099: wide
    //   9103: goto -5066 -> 4037
    //   9106: iconst_0
    //   9107: istore 248
    //   9109: goto -5304 -> 3805
    //   9112: iconst_0
    //   9113: istore 237
    //   9115: goto -5478 -> 3637
    //   9118: iconst_0
    //   9119: istore 226
    //   9121: goto -5652 -> 3469
    //   9124: iconst_0
    //   9125: istore 215
    //   9127: goto -5826 -> 3301
    //   9130: iconst_0
    //   9131: istore 204
    //   9133: goto -6000 -> 3133
    //   9136: iconst_0
    //   9137: istore 193
    //   9139: goto -6174 -> 2965
    //   9142: iconst_0
    //   9143: istore 182
    //   9145: goto -6348 -> 2797
    //   9148: iconst_0
    //   9149: istore 171
    //   9151: goto -6522 -> 2629
    //   9154: iconst_0
    //   9155: istore 160
    //   9157: goto -6696 -> 2461
    //   9160: iconst_0
    //   9161: istore 149
    //   9163: goto -6870 -> 2293
    //   9166: iconst_0
    //   9167: istore 138
    //   9169: goto -7044 -> 2125
    //   9172: iconst_0
    //   9173: istore 127
    //   9175: goto -7218 -> 1957
    //   9178: iconst_0
    //   9179: istore 116
    //   9181: goto -7392 -> 1789
    //   9184: iconst_0
    //   9185: istore 105
    //   9187: goto -7566 -> 1621
    //   9190: iconst_0
    //   9191: istore 94
    //   9193: goto -7740 -> 1453
    //   9196: iconst_0
    //   9197: istore 83
    //   9199: goto -7914 -> 1285
    //   9202: iconst_0
    //   9203: istore 72
    //   9205: goto -8088 -> 1117
    //   9208: iconst_0
    //   9209: istore 61
    //   9211: goto -8262 -> 949
    //   9214: iconst_0
    //   9215: istore 50
    //   9217: goto -8432 -> 785
    //   9220: iconst_0
    //   9221: istore 39
    //   9223: goto -8602 -> 621
    //   9226: iconst_0
    //   9227: istore 27
    //   9229: goto -8772 -> 457
    //   9232: iconst_0
    //   9233: istore 16
    //   9235: goto -8942 -> 293
    //   9238: iconst_0
    //   9239: istore 4
    //   9241: goto -9106 -> 135
  }

  _sdkgc(WPSAuthentication paramWPSAuthentication, long paramLong)
  {
    com.skyhookwireless._sdkhb local_sdkhb = com.skyhookwireless._sdkhb._sdkb(_sdkgc.class);
    this._sdka = local_sdkhb;
    this._sdkb = paramLong;
    _sdkcb local_sdkcb = new _sdkcb(paramWPSAuthentication);
    this._sdkc = local_sdkcb;
    LinkedList localLinkedList = new LinkedList();
    this._sdkd = localLinkedList;
  }

  private int _sdka()
  {
    boolean bool = _sdkkc._sdkr;
    int i = 0;
    do
    {
      if (this._sdkc._sdkc())
        break;
      i = this._sdkc._sdkb();
      if (i < 81)
        break;
      if (this._sdka._sdkb())
      {
        com.skyhookwireless._sdkhb local_sdkhb = this._sdka;
        StringBuilder localStringBuilder1 = new StringBuilder();
        String str1 = z[25];
        StringBuilder localStringBuilder2 = localStringBuilder1.append(str1).append(i).append("/").append(81);
        String str2 = z[24];
        String str3 = str2;
        local_sdkhb._sdkb(str3);
      }
      _sdkhc local_sdkhc = _sdke();
    }
    while (!bool);
    return i;
  }

  private void _sdka(_sdkeb param_sdkeb)
  {
    if ((!_sdke) && (param_sdkeb == null))
      throw new AssertionError();
    if (param_sdkeb == null)
      return;
    _sdkhc local_sdkhc = _sdkb(param_sdkeb);
    if (local_sdkhc == null)
      return;
    _sdka(local_sdkhc);
  }

  private void _sdka(_sdkhc param_sdkhc)
  {
    int i = this._sdkd.indexOf(param_sdkhc);
    if ((!_sdke) && (i < 0))
      throw new AssertionError();
    if (i < 0)
    {
      com.skyhookwireless._sdkhb local_sdkhb = this._sdka;
      String str = z[38];
      local_sdkhb._sdke(str);
      return;
    }
    ListIterator localListIterator = this._sdkd.listIterator(i);
    Object localObject = localListIterator.next();
    _sdka(param_sdkhc, localListIterator);
  }

  private void _sdka(_sdkhc param_sdkhc, Iterator<_sdkhc> paramIterator)
  {
    if (this._sdka._sdkb())
    {
      com.skyhookwireless._sdkhb local_sdkhb1 = this._sdka;
      StringBuilder localStringBuilder1 = new StringBuilder();
      String str1 = z[23];
      StringBuilder localStringBuilder2 = localStringBuilder1.append(str1).append(param_sdkhc);
      String str2 = z[22];
      String str3 = str2;
      local_sdkhb1._sdkb(str3);
    }
    if (param_sdkhc._sdkb != null)
    {
      if (this._sdka._sdkb())
      {
        com.skyhookwireless._sdkhb local_sdkhb2 = this._sdka;
        StringBuilder localStringBuilder3 = new StringBuilder();
        String str4 = z[21];
        String str5 = str4 + param_sdkhc;
        local_sdkhb2._sdkb(str5);
      }
      _sdkcb local_sdkcb = this._sdkc;
      _sdkeb local_sdkeb = param_sdkhc._sdkb;
      local_sdkcb._sdka(local_sdkeb);
    }
    String str6 = param_sdkhc._sdka._sdkf();
    _sdka(str6);
    paramIterator.remove();
  }

  private void _sdka(String paramString)
  {
    if (this._sdka._sdkb())
    {
      com.skyhookwireless._sdkhb local_sdkhb1 = this._sdka;
      StringBuilder localStringBuilder1 = new StringBuilder();
      String str1 = z[36];
      String str2 = str1 + paramString;
      local_sdkhb1._sdkb(str2);
    }
    File localFile = new File(paramString);
    if (!localFile.exists())
      return;
    if (localFile.isDirectory())
      return;
    if (localFile.delete())
      return;
    com.skyhookwireless._sdkhb local_sdkhb2 = this._sdka;
    StringBuilder localStringBuilder2 = new StringBuilder();
    String str3 = z[37];
    String str4 = str3 + localFile;
    local_sdkhb2._sdkd(str4);
  }

  private boolean _sdka(long paramLong)
  {
    boolean bool = false;
    if (this._sdkd.isEmpty());
    while (true)
    {
      return bool;
      long l1 = this._sdkb;
      if (paramLong > l1)
        if ((this._sdkd.size() == 1) && (this._sdkb > 0L))
        {
          com.skyhookwireless._sdkhb local_sdkhb = this._sdka;
          StringBuilder localStringBuilder1 = new StringBuilder();
          String str1 = z[31];
          StringBuilder localStringBuilder2 = localStringBuilder1.append(str1);
          long l2 = paramLong / 1024L;
          StringBuilder localStringBuilder3 = localStringBuilder2.append(l2).append("/");
          long l3 = this._sdkb / 1024L;
          StringBuilder localStringBuilder4 = localStringBuilder3.append(l3);
          String str2 = z[30];
          String str3 = str2;
          local_sdkhb._sdkb(str3);
        }
        else
        {
          bool = true;
        }
    }
  }

  private long _sdkb()
  {
    boolean bool = _sdkkc._sdkr;
    long l1 = _sdkc();
    long l2 = this._sdkb;
    if (l1 <= l2);
    while (true)
    {
      return l1;
      List localList = _sdkd();
      for (long l3 = l1; ; l3 = l1)
      {
        if (!_sdka(l3))
          break label373;
        if (this._sdka._sdkb())
        {
          com.skyhookwireless._sdkhb local_sdkhb1 = this._sdka;
          StringBuilder localStringBuilder1 = new StringBuilder();
          String str1 = z[35];
          StringBuilder localStringBuilder2 = localStringBuilder1.append(str1);
          long l4 = l3 / 1024L;
          StringBuilder localStringBuilder3 = localStringBuilder2.append(l4).append("/");
          long l5 = this._sdkb / 1024L;
          StringBuilder localStringBuilder4 = localStringBuilder3.append(l5);
          String str2 = z[30];
          String str3 = str2;
          local_sdkhb1._sdkb(str3);
        }
        _sdkhc local_sdkhc1;
        if (!localList.isEmpty())
        {
          local_sdkhc1 = (_sdkhc)localList.get(0);
          Object localObject1 = localList.remove(0);
          com.skyhookwireless._sdkhb local_sdkhb2 = this._sdka;
          StringBuilder localStringBuilder5 = new StringBuilder();
          String str4 = z[34];
          String str5 = str4 + local_sdkhc1;
          local_sdkhb2._sdkb(str5);
        }
        _sdkhc local_sdkhc2;
        for (Object localObject2 = local_sdkhc1; !_sdke; localObject2 = local_sdkhc2)
        {
          long l6 = ((_sdkhc)localObject2)._sdkc;
          if (l3 >= l6)
            break;
          throw new AssertionError();
          local_sdkhc2 = _sdke();
          if ((!_sdke) && (local_sdkhc2 == null))
            throw new AssertionError();
          com.skyhookwireless._sdkhb local_sdkhb3 = this._sdka;
          StringBuilder localStringBuilder6 = new StringBuilder();
          String str6 = z[33];
          String str7 = str6 + local_sdkhc2;
          local_sdkhb3._sdkb(str7);
        }
        long l7 = ((_sdkhc)localObject2)._sdkc;
        l1 = l3 - l7;
        _sdka((_sdkhc)localObject2);
        if (bool)
          break;
      }
      label373: l1 = l3;
    }
  }

  private _sdkhc _sdkb(_sdkeb param_sdkeb)
  {
    boolean bool = _sdkkc._sdkr;
    if ((!_sdke) && (param_sdkeb == null))
      throw new AssertionError();
    _sdkhc local_sdkhc;
    if (param_sdkeb == null)
      local_sdkhc = null;
    while (true)
    {
      return local_sdkhc;
      Iterator localIterator = this._sdkd.iterator();
      do
      {
        if (!localIterator.hasNext())
          break label79;
        _sdkeb local_sdkeb = ((_sdkhc)localIterator.next())._sdkb;
        if (param_sdkeb.equals(local_sdkeb))
          break;
      }
      while (!bool);
      label79: local_sdkhc = null;
    }
  }

  private long _sdkc()
  {
    boolean bool = _sdkkc._sdkr;
    Iterator localIterator = this._sdkd.iterator();
    long l1 = 0L;
    long l3;
    if (localIterator.hasNext())
    {
      long l2 = ((_sdkhc)localIterator.next())._sdkc;
      l3 = l1 + l2;
      if (!bool);
    }
    while (true)
    {
      return l3;
      l1 = l3;
      break;
      l3 = l1;
    }
  }

  private List<_sdkhc> _sdkd()
  {
    boolean bool1 = _sdkkc._sdkr;
    ArrayList localArrayList = new ArrayList();
    Iterator localIterator = this._sdkd.iterator();
    do
    {
      if (!localIterator.hasNext())
        break;
      _sdkhc local_sdkhc = (_sdkhc)localIterator.next();
      if (local_sdkhc._sdkb == null)
        boolean bool2 = localArrayList.add(local_sdkhc);
    }
    while (!bool1);
    Collections.sort(localArrayList);
    return localArrayList;
  }

  private _sdkhc _sdke()
  {
    Object localObject = null;
    _sdkeb local_sdkeb = this._sdkc._sdka();
    if ((!_sdke) && (local_sdkeb == null))
      throw new AssertionError();
    if (local_sdkeb == null)
    {
      com.skyhookwireless._sdkhb local_sdkhb1 = this._sdka;
      String str1 = z[27];
      local_sdkhb1._sdke(str1);
    }
    while (true)
    {
      return localObject;
      _sdkhc local_sdkhc = _sdkb(local_sdkeb);
      if (local_sdkhc != null)
      {
        if (this._sdka._sdkb())
        {
          com.skyhookwireless._sdkhb local_sdkhb2 = this._sdka;
          StringBuilder localStringBuilder1 = new StringBuilder();
          String str2 = z[28];
          String str3 = str2 + local_sdkhc;
          local_sdkhb2._sdkb(str3);
        }
        local_sdkhc._sdkb = null;
        localObject = local_sdkhc;
      }
      else
      {
        com.skyhookwireless._sdkhb local_sdkhb3 = this._sdka;
        StringBuilder localStringBuilder2 = new StringBuilder();
        String str4 = z[29];
        StringBuilder localStringBuilder3 = localStringBuilder2.append(str4).append(local_sdkeb);
        String str5 = z[26];
        String str6 = str5;
        local_sdkhb3._sdke(str6);
      }
    }
  }

  /** @deprecated */
  _sdkic _sdka(_sdkic param_sdkic)
  {
    try
    {
      boolean bool = _sdkkc._sdkr;
      Iterator localIterator = this._sdkd.iterator();
      do
      {
        if (!localIterator.hasNext())
          break;
        localObject1 = (_sdkhc)localIterator.next();
        _sdkic local_sdkic = ((_sdkhc)localObject1)._sdka;
        if (param_sdkic._sdka(local_sdkic))
        {
          localObject1 = ((_sdkhc)localObject1)._sdka;
          return localObject1;
        }
      }
      while (!bool);
      Object localObject1 = null;
    }
    finally
    {
    }
  }

  /** @deprecated */
  String _sdka(ArrayList<_sdkjc> paramArrayList, ArrayList<_sdkhb> paramArrayList1)
  {
    Object localObject1 = null;
    while (true)
    {
      int i;
      try
      {
        boolean bool1 = _sdkkc._sdkr;
        HashMap localHashMap = new HashMap();
        Iterator localIterator = paramArrayList.iterator();
        i = 0;
        j = null;
        if (!localIterator.hasNext())
          break label291;
        localObject1 = (_sdkjc)localIterator.next();
        try
        {
          _sdkcb local_sdkcb = this._sdkc;
          com.skyhookwireless._sdkic local_sdkic = ((_sdkjc)localObject1)._sdka();
          Object localObject5 = local_sdkcb._sdka(local_sdkic);
          localObject6 = localObject5;
          if (localObject6 != null)
          {
            Object localObject7 = localObject6.second;
            boolean bool2 = paramArrayList1.add(localObject7);
            Object localObject8 = localObject6.first;
            localObject1 = (Integer)localHashMap.get(localObject8);
            if (localObject1 == null)
              localObject1 = Integer.valueOf(0);
            Object localObject9 = localObject6.first;
            Integer localInteger = Integer.valueOf(((Integer)localObject1).intValue() + 1);
            Object localObject10 = localHashMap.put(localObject9, localInteger);
            if (localInteger.intValue() > i)
            {
              localObject1 = (_sdkeb)localObject6.first;
              j = localInteger.intValue();
              if (!bool1)
                break label297;
              if (localObject1 != null)
              {
                localObject1 = _sdkb((_sdkeb)localObject1);
                if ((localObject1 != null) && (((_sdkhc)localObject1)._sdka != null))
                {
                  localObject5 = ((_sdkhc)localObject1)._sdka._sdka();
                  localObject11 = localObject5;
                  return localObject11;
                }
              }
            }
          }
        }
        catch (_sdkc local_sdkc)
        {
          com.skyhookwireless._sdkhb local_sdkhb = this._sdka;
          String str = z[32];
          local_sdkhb._sdkd(str);
          _sdkeb local_sdkeb = local_sdkc._sdka();
          _sdka(local_sdkeb);
          Object localObject6 = null;
          continue;
          Object localObject11 = "";
          continue;
        }
      }
      finally
      {
      }
      Object localObject2 = j;
      int j = i;
      continue;
      label291: localObject2 = j;
      continue;
      label297: Object localObject3 = j;
      Object localObject4 = localObject2;
    }
  }

  /** @deprecated */
  void _sdka(int paramInt, _sdkic param_sdkic)
  {
    long l1 = 1;
    Object localObject1 = null;
    while (true)
    {
      _sdkhc local_sdkhc1;
      _sdkic local_sdkic1;
      try
      {
        boolean bool = _sdkkc._sdkr;
        Iterator localIterator = this._sdkd.iterator();
        int j = 0;
        int i;
        if (localIterator.hasNext())
        {
          int k = (_sdkhc)localIterator.next();
          _sdkic local_sdkic2 = k._sdka;
          if (local_sdkic2.equals(param_sdkic))
          {
            if (this._sdka._sdkb())
            {
              com.skyhookwireless._sdkhb local_sdkhb1 = this._sdka;
              StringBuilder localStringBuilder1 = new StringBuilder();
              String str2 = z[12];
              StringBuilder localStringBuilder2 = localStringBuilder1.append(str2).append(param_sdkic);
              String str3 = z[14];
              String str4 = str3;
              local_sdkhb1._sdkb(str4);
            }
            if (!bool)
              continue;
            i = 0;
          }
          if (param_sdkic._sdka(local_sdkic2))
          {
            int n = param_sdkic._sdkb();
            int i1 = local_sdkic2._sdkb();
            if (n <= i1)
            {
              int i2 = param_sdkic._sdkb();
              int i3 = local_sdkic2._sdkb();
              if ((i2 == i3) || (!param_sdkic._sdkb(local_sdkic2)));
            }
            else
            {
              if (this._sdka._sdkb())
              {
                com.skyhookwireless._sdkhb local_sdkhb2 = this._sdka;
                StringBuilder localStringBuilder3 = new StringBuilder();
                String str5 = z[12];
                StringBuilder localStringBuilder4 = localStringBuilder3.append(str5);
                String str6 = local_sdkic2._sdka();
                StringBuilder localStringBuilder5 = localStringBuilder4.append(str6).append("_");
                int i4 = local_sdkic2._sdkb();
                StringBuilder localStringBuilder6 = localStringBuilder5.append(i4);
                String str7 = z[13];
                StringBuilder localStringBuilder7 = localStringBuilder6.append(str7);
                String str8 = param_sdkic._sdka();
                StringBuilder localStringBuilder8 = localStringBuilder7.append(str8).append("_");
                int i5 = param_sdkic._sdkb();
                String str9 = i5;
                local_sdkhb2._sdkb(str9);
              }
              _sdka(k, localIterator);
              if (!bool)
                continue;
            }
            if (this._sdka._sdkb())
            {
              com.skyhookwireless._sdkhb local_sdkhb3 = this._sdka;
              StringBuilder localStringBuilder9 = new StringBuilder();
              String str10 = z[12];
              StringBuilder localStringBuilder10 = localStringBuilder9.append(str10);
              String str11 = param_sdkic._sdka();
              StringBuilder localStringBuilder11 = localStringBuilder10.append(str11).append("_");
              int i6 = param_sdkic._sdkb();
              StringBuilder localStringBuilder12 = localStringBuilder11.append(i6);
              String str12 = z[6];
              StringBuilder localStringBuilder13 = localStringBuilder12.append(str12);
              String str13 = local_sdkic2._sdka();
              StringBuilder localStringBuilder14 = localStringBuilder13.append(str13).append("_");
              int i7 = local_sdkic2._sdkb();
              String str14 = i7;
              local_sdkhb3._sdkb(str14);
            }
            String str15 = param_sdkic._sdkf();
            _sdka(str15);
            if (!bool)
              continue;
            i = 0;
          }
          if (!bool)
            continue;
        }
        long l3 = i;
        if (l3 != null)
        {
          if (this._sdka._sdkb())
          {
            com.skyhookwireless._sdkhb local_sdkhb4 = this._sdka;
            StringBuilder localStringBuilder15 = new StringBuilder();
            String str16 = z[4];
            StringBuilder localStringBuilder16 = localStringBuilder15.append(str16);
            String str17 = param_sdkic._sdka();
            StringBuilder localStringBuilder17 = localStringBuilder16.append(str17).append("_");
            int i8 = param_sdkic._sdkb();
            StringBuilder localStringBuilder18 = localStringBuilder17.append(i8);
            String str18 = z[8];
            StringBuilder localStringBuilder19 = localStringBuilder18.append(str18);
            String str19 = z[1];
            StringBuilder localStringBuilder20 = localStringBuilder19.append(str19);
            int i9 = this._sdkd.size() + 1;
            String str20 = i9 + ")";
            local_sdkhb4._sdkb(str20);
          }
          List localList = this._sdkd;
          _sdkhc local_sdkhc2 = new _sdkhc(this, param_sdkic);
          localList.add(0, local_sdkhc2);
          local_sdkhc1 = (_sdkhc)this._sdkd.get(0);
          if (!bool);
        }
        else if (local_sdkhc1._sdkb != null)
        {
          if (this._sdka._sdkb())
          {
            com.skyhookwireless._sdkhb local_sdkhb5 = this._sdka;
            StringBuilder localStringBuilder21 = new StringBuilder();
            String str21 = z[12];
            StringBuilder localStringBuilder22 = localStringBuilder21.append(str21).append(local_sdkhc1);
            String str22 = z[0];
            String str23 = str22;
            local_sdkhb5._sdkb(str23);
          }
          return;
        }
        local_sdkic1 = local_sdkhc1._sdka;
        if (paramInt >= 81)
        {
          if (!this._sdka._sdkb())
            continue;
          com.skyhookwireless._sdkhb local_sdkhb6 = this._sdka;
          StringBuilder localStringBuilder23 = new StringBuilder();
          String str24 = z[12];
          StringBuilder localStringBuilder24 = localStringBuilder23.append(str24).append(local_sdkic1);
          String str25 = z[3];
          StringBuilder localStringBuilder25 = localStringBuilder24.append(str25).append(paramInt);
          String str26 = z[19];
          String str27 = str26 + 81 + ")";
          local_sdkhb6._sdkb(str27);
          continue;
        }
      }
      finally
      {
      }
      int i10 = _sdka();
      String str1 = local_sdkic1._sdkf();
      _sdkeb local_sdkeb = this._sdkc._sdka(paramInt, str1);
      local_sdkhc1._sdkb = local_sdkeb;
      if (local_sdkhc1._sdkb == null)
      {
        com.skyhookwireless._sdkhb local_sdkhb7 = this._sdka;
        StringBuilder localStringBuilder26 = new StringBuilder();
        String str28 = z[17];
        StringBuilder localStringBuilder27 = localStringBuilder26.append(str28).append(str1);
        String str29 = z[2];
        String str30 = str29;
        local_sdkhb7._sdkd(str30);
        _sdka(local_sdkhc1);
      }
      else
      {
        long l2 = _sdkb();
        if (l2 == 0L)
        {
          com.skyhookwireless._sdkhb local_sdkhb8 = this._sdka;
          StringBuilder localStringBuilder28 = new StringBuilder();
          String str31 = z[11];
          StringBuilder localStringBuilder29 = localStringBuilder28.append(str31);
          long l4 = this._sdkb / 1024L;
          StringBuilder localStringBuilder30 = localStringBuilder29.append(l4);
          String str32 = z[7];
          String str33 = str32 + local_sdkic1;
          local_sdkhb8._sdkb(str33);
        }
        else
        {
          int m = this._sdkc._sdkb();
          if (!_sdke)
          {
            int i11 = this._sdkd.size();
            if (m > i11)
              throw new AssertionError();
          }
          if (this._sdka._sdkb())
          {
            com.skyhookwireless._sdkhb local_sdkhb9 = this._sdka;
            StringBuilder localStringBuilder31 = new StringBuilder();
            String str34 = z[5];
            StringBuilder localStringBuilder32 = localStringBuilder31.append(str34).append(local_sdkic1);
            String str35 = z[18];
            StringBuilder localStringBuilder33 = localStringBuilder32.append(str35);
            int i12 = this._sdkd.size();
            StringBuilder localStringBuilder34 = localStringBuilder33.append(i12);
            String str36 = z[16];
            StringBuilder localStringBuilder35 = localStringBuilder34.append(str36).append(m);
            String str37 = z[20];
            StringBuilder localStringBuilder36 = localStringBuilder35.append(str37).append(81);
            String str38 = z[15];
            StringBuilder localStringBuilder37 = localStringBuilder36.append(str38);
            long l5 = l2 / 1024L;
            StringBuilder localStringBuilder38 = localStringBuilder37.append(l5);
            String str39 = z[10];
            StringBuilder localStringBuilder39 = localStringBuilder38.append(str39);
            long l6 = this._sdkb / 1024L;
            StringBuilder localStringBuilder40 = localStringBuilder39.append(l6);
            String str40 = z[9];
            String str41 = str40;
            local_sdkhb9._sdkb(str41);
          }
        }
      }
    }
  }
}

/* Location:           D:\Tools\extractapktools\extractapktools\dex2jar-0.0.7.11-SNAPSHOT\classes_dex2jar.jar
 * Qualified Name:     com.skyhookwireless.wps._sdkgc
 * JD-Core Version:    0.6.2
 */