package com.skyhookwireless.wps;

import com.skyhookwireless._sdkec;
import com.skyhookwireless._sdkgc;
import com.skyhookwireless._sdkhb;
import com.skyhookwireless._sdkhd;
import com.skyhookwireless._sdkk;
import com.skyhookwireless._sdknd;
import com.skyhookwireless._sdkpd;
import com.skyhookwireless._sdkt;
import com.skyhookwireless._sdktd;
import com.skyhookwireless._sdkuc;
import com.skyhookwireless._sdkw;
import com.skyhookwireless._sdkwb;
import java.util.ArrayList;
import java.util.Collection;
import java.util.Comparator;
import java.util.HashMap;
import java.util.Iterator;
import java.util.List;
import java.util.Map;
import java.util.Map.Entry;
import java.util.Set;
import java.util.concurrent.CancellationException;
import java.util.concurrent.ExecutionException;
import java.util.concurrent.Future;
import java.util.concurrent.TimeUnit;
import java.util.concurrent.TimeoutException;

final class _sdko
  implements _sdkvc
{
  static final boolean _sdko;
  private static final String[] z;
  private final _sdkhb _sdka;
  private final _sdkxb _sdkb;
  private int _sdkc;
  private int _sdkd;
  private final _sdkec _sdke;
  private _sdkib _sdkf;
  private final WPSAuthentication _sdkg;
  private final WPSStreetAddressLookup _sdkh;
  private final long _sdki;
  private final _sdktb _sdkj;
  private final _sdkuc _sdkk;
  private final _sdkuc _sdkl;
  private final _sdkzb _sdkm;
  private final Map<_sdkzb, _sdkp> _sdkn;
  final _sdkf _sdkp;

  static
  {
    // Byte code:
    //   0: iconst_1
    //   1: istore_0
    //   2: bipush 47
    //   4: anewarray 43	java/lang/String
    //   7: astore_1
    //   8: ldc 45
    //   10: invokevirtual 49	java/lang/String:toCharArray	()[C
    //   13: astore_2
    //   14: aload_2
    //   15: arraylength
    //   16: istore_3
    //   17: iload_3
    //   18: iload_0
    //   19: if_icmpgt +11507 -> 11526
    //   22: iconst_0
    //   23: istore 4
    //   25: aload_2
    //   26: astore 5
    //   28: iload 4
    //   30: istore 6
    //   32: iload_3
    //   33: istore 7
    //   35: aload_2
    //   36: astore 8
    //   38: iload 7
    //   40: istore 9
    //   42: aload 8
    //   44: iload 4
    //   46: caload
    //   47: istore 10
    //   49: iload 6
    //   51: iconst_5
    //   52: irem
    //   53: tableswitch	default:+31 -> 84, 0:+9641->9694, 1:+9648->9701, 2:+9655->9708, 3:+9662->9715
    //   85: frem
    //   86: istore 11
    //   88: iload 11
    //   90: iload 10
    //   92: ixor
    //   93: i2c
    //   94: istore 12
    //   96: aload 8
    //   98: iload 4
    //   100: iload 12
    //   102: castore
    //   103: iload 6
    //   105: iconst_1
    //   106: iadd
    //   107: istore 4
    //   109: iload 9
    //   111: ifne +18 -> 129
    //   114: aload 5
    //   116: astore 8
    //   118: iload 4
    //   120: istore 6
    //   122: iload 9
    //   124: istore 4
    //   126: goto -84 -> 42
    //   129: iload 9
    //   131: istore_3
    //   132: aload 5
    //   134: astore_2
    //   135: iload_3
    //   136: iload 4
    //   138: if_icmpgt -113 -> 25
    //   141: new 43	java/lang/String
    //   144: dup
    //   145: aload_2
    //   146: invokespecial 53	java/lang/String:<init>	([C)V
    //   149: invokevirtual 57	java/lang/String:intern	()Ljava/lang/String;
    //   152: astore 13
    //   154: aload_1
    //   155: iconst_0
    //   156: aload 13
    //   158: aastore
    //   159: ldc 59
    //   161: invokevirtual 49	java/lang/String:toCharArray	()[C
    //   164: astore 14
    //   166: aload 14
    //   168: arraylength
    //   169: istore 15
    //   171: iload 15
    //   173: iconst_1
    //   174: if_icmpgt +11346 -> 11520
    //   177: iconst_0
    //   178: istore 16
    //   180: aload 14
    //   182: astore 5
    //   184: iload 16
    //   186: istore 6
    //   188: iload 15
    //   190: istore 17
    //   192: aload 14
    //   194: astore 18
    //   196: iload 17
    //   198: istore 19
    //   200: aload 18
    //   202: iload 16
    //   204: caload
    //   205: istore 10
    //   207: iload 6
    //   209: iconst_5
    //   210: irem
    //   211: tableswitch	default:+29 -> 240, 0:+9511->9722, 1:+9518->9729, 2:+9525->9736, 3:+9532->9743
    //   241: frem
    //   242: istore 20
    //   244: iload 20
    //   246: iload 10
    //   248: ixor
    //   249: i2c
    //   250: istore 21
    //   252: aload 18
    //   254: iload 16
    //   256: iload 21
    //   258: castore
    //   259: iload 6
    //   261: iconst_1
    //   262: iadd
    //   263: istore 16
    //   265: iload 19
    //   267: ifne +18 -> 285
    //   270: aload 5
    //   272: astore 18
    //   274: iload 16
    //   276: istore 22
    //   278: iload 19
    //   280: istore 16
    //   282: goto -82 -> 200
    //   285: iload 19
    //   287: istore 15
    //   289: aload 5
    //   291: astore 14
    //   293: iload 15
    //   295: iload 16
    //   297: if_icmpgt -117 -> 180
    //   300: new 43	java/lang/String
    //   303: dup
    //   304: aload 14
    //   306: invokespecial 53	java/lang/String:<init>	([C)V
    //   309: invokevirtual 57	java/lang/String:intern	()Ljava/lang/String;
    //   312: astore 23
    //   314: aload_1
    //   315: iconst_1
    //   316: aload 23
    //   318: aastore
    //   319: iconst_2
    //   320: istore 24
    //   322: ldc 61
    //   324: invokevirtual 49	java/lang/String:toCharArray	()[C
    //   327: astore 25
    //   329: aload 25
    //   331: arraylength
    //   332: istore 26
    //   334: iload 26
    //   336: iconst_1
    //   337: if_icmpgt +11177 -> 11514
    //   340: iconst_0
    //   341: istore 27
    //   343: aload 25
    //   345: astore 5
    //   347: iload 27
    //   349: istore 6
    //   351: iload 26
    //   353: istore 28
    //   355: aload 25
    //   357: astore 29
    //   359: iload 28
    //   361: istore 30
    //   363: aload 29
    //   365: iload 27
    //   367: caload
    //   368: istore 31
    //   370: iload 6
    //   372: iconst_5
    //   373: irem
    //   374: tableswitch	default:+30 -> 404, 0:+9376->9750, 1:+9383->9757, 2:+9390->9764, 3:+9397->9771
    //   405: frem
    //   406: istore 32
    //   408: iload 32
    //   410: iload 31
    //   412: ixor
    //   413: i2c
    //   414: istore 33
    //   416: aload 29
    //   418: iload 27
    //   420: iload 33
    //   422: castore
    //   423: iload 6
    //   425: iconst_1
    //   426: iadd
    //   427: istore 27
    //   429: iload 30
    //   431: ifne +18 -> 449
    //   434: aload 5
    //   436: astore 29
    //   438: iload 27
    //   440: istore 34
    //   442: iload 30
    //   444: istore 27
    //   446: goto -83 -> 363
    //   449: iload 30
    //   451: istore 26
    //   453: aload 5
    //   455: astore 25
    //   457: iload 26
    //   459: iload 27
    //   461: if_icmpgt -118 -> 343
    //   464: new 43	java/lang/String
    //   467: dup
    //   468: aload 25
    //   470: invokespecial 53	java/lang/String:<init>	([C)V
    //   473: invokevirtual 57	java/lang/String:intern	()Ljava/lang/String;
    //   476: astore 35
    //   478: aload_1
    //   479: iload 24
    //   481: aload 35
    //   483: aastore
    //   484: iconst_3
    //   485: istore 36
    //   487: ldc 63
    //   489: invokevirtual 49	java/lang/String:toCharArray	()[C
    //   492: astore 37
    //   494: aload 37
    //   496: arraylength
    //   497: istore 38
    //   499: iload 38
    //   501: iconst_1
    //   502: if_icmpgt +11006 -> 11508
    //   505: iconst_0
    //   506: istore 39
    //   508: aload 37
    //   510: astore 5
    //   512: iload 39
    //   514: istore 6
    //   516: iload 38
    //   518: istore 40
    //   520: aload 37
    //   522: astore 41
    //   524: iload 40
    //   526: istore 42
    //   528: aload 41
    //   530: iload 39
    //   532: caload
    //   533: istore 31
    //   535: iload 6
    //   537: iconst_5
    //   538: irem
    //   539: tableswitch	default:+29 -> 568, 0:+9239->9778, 1:+9246->9785, 2:+9253->9792, 3:+9260->9799
    //   569: frem
    //   570: istore 43
    //   572: iload 43
    //   574: iload 31
    //   576: ixor
    //   577: i2c
    //   578: istore 44
    //   580: aload 41
    //   582: iload 39
    //   584: iload 44
    //   586: castore
    //   587: iload 6
    //   589: iconst_1
    //   590: iadd
    //   591: istore 39
    //   593: iload 42
    //   595: ifne +18 -> 613
    //   598: aload 5
    //   600: astore 41
    //   602: iload 39
    //   604: istore 45
    //   606: iload 42
    //   608: istore 39
    //   610: goto -82 -> 528
    //   613: iload 42
    //   615: istore 38
    //   617: aload 5
    //   619: astore 37
    //   621: iload 38
    //   623: iload 39
    //   625: if_icmpgt -117 -> 508
    //   628: new 43	java/lang/String
    //   631: dup
    //   632: aload 37
    //   634: invokespecial 53	java/lang/String:<init>	([C)V
    //   637: invokevirtual 57	java/lang/String:intern	()Ljava/lang/String;
    //   640: astore 46
    //   642: aload_1
    //   643: iload 36
    //   645: aload 46
    //   647: aastore
    //   648: iconst_4
    //   649: istore 47
    //   651: ldc 65
    //   653: invokevirtual 49	java/lang/String:toCharArray	()[C
    //   656: astore 48
    //   658: aload 48
    //   660: arraylength
    //   661: istore 49
    //   663: iload 49
    //   665: iconst_1
    //   666: if_icmpgt +10836 -> 11502
    //   669: iconst_0
    //   670: istore 50
    //   672: aload 48
    //   674: astore 5
    //   676: iload 50
    //   678: istore 6
    //   680: iload 49
    //   682: istore 51
    //   684: aload 48
    //   686: astore 52
    //   688: iload 51
    //   690: istore 53
    //   692: aload 52
    //   694: iload 50
    //   696: caload
    //   697: istore 31
    //   699: iload 6
    //   701: iconst_5
    //   702: irem
    //   703: tableswitch	default:+29 -> 732, 0:+9103->9806, 1:+9110->9813, 2:+9117->9820, 3:+9124->9827
    //   733: frem
    //   734: istore 54
    //   736: iload 54
    //   738: iload 31
    //   740: ixor
    //   741: i2c
    //   742: istore 55
    //   744: aload 52
    //   746: iload 50
    //   748: iload 55
    //   750: castore
    //   751: iload 6
    //   753: iconst_1
    //   754: iadd
    //   755: istore 50
    //   757: iload 53
    //   759: ifne +18 -> 777
    //   762: aload 5
    //   764: astore 52
    //   766: iload 50
    //   768: istore 56
    //   770: iload 53
    //   772: istore 50
    //   774: goto -82 -> 692
    //   777: iload 53
    //   779: istore 49
    //   781: aload 5
    //   783: astore 48
    //   785: iload 49
    //   787: iload 50
    //   789: if_icmpgt -117 -> 672
    //   792: new 43	java/lang/String
    //   795: dup
    //   796: aload 48
    //   798: invokespecial 53	java/lang/String:<init>	([C)V
    //   801: invokevirtual 57	java/lang/String:intern	()Ljava/lang/String;
    //   804: astore 57
    //   806: aload_1
    //   807: iload 47
    //   809: aload 57
    //   811: aastore
    //   812: iconst_5
    //   813: istore 58
    //   815: ldc 67
    //   817: invokevirtual 49	java/lang/String:toCharArray	()[C
    //   820: astore 59
    //   822: aload 59
    //   824: arraylength
    //   825: istore 60
    //   827: iload 60
    //   829: iconst_1
    //   830: if_icmpgt +10666 -> 11496
    //   833: iconst_0
    //   834: istore 61
    //   836: aload 59
    //   838: astore 5
    //   840: iload 61
    //   842: istore 6
    //   844: iload 60
    //   846: istore 62
    //   848: aload 59
    //   850: astore 63
    //   852: iload 62
    //   854: istore 64
    //   856: aload 63
    //   858: iload 61
    //   860: caload
    //   861: istore 31
    //   863: iload 6
    //   865: iconst_5
    //   866: irem
    //   867: tableswitch	default:+29 -> 896, 0:+8967->9834, 1:+8974->9841, 2:+8981->9848, 3:+8988->9855
    //   897: frem
    //   898: istore 65
    //   900: iload 65
    //   902: iload 31
    //   904: ixor
    //   905: i2c
    //   906: istore 66
    //   908: aload 63
    //   910: iload 61
    //   912: iload 66
    //   914: castore
    //   915: iload 6
    //   917: iconst_1
    //   918: iadd
    //   919: istore 61
    //   921: iload 64
    //   923: ifne +18 -> 941
    //   926: aload 5
    //   928: astore 63
    //   930: iload 61
    //   932: istore 67
    //   934: iload 64
    //   936: istore 61
    //   938: goto -82 -> 856
    //   941: iload 64
    //   943: istore 60
    //   945: aload 5
    //   947: astore 59
    //   949: iload 60
    //   951: iload 61
    //   953: if_icmpgt -117 -> 836
    //   956: new 43	java/lang/String
    //   959: dup
    //   960: aload 59
    //   962: invokespecial 53	java/lang/String:<init>	([C)V
    //   965: invokevirtual 57	java/lang/String:intern	()Ljava/lang/String;
    //   968: astore 68
    //   970: aload_1
    //   971: iload 58
    //   973: aload 68
    //   975: aastore
    //   976: bipush 6
    //   978: istore 69
    //   980: ldc 69
    //   982: invokevirtual 49	java/lang/String:toCharArray	()[C
    //   985: astore 70
    //   987: aload 70
    //   989: arraylength
    //   990: istore 71
    //   992: iload 71
    //   994: iconst_1
    //   995: if_icmpgt +10495 -> 11490
    //   998: iconst_0
    //   999: istore 72
    //   1001: aload 70
    //   1003: astore 5
    //   1005: iload 72
    //   1007: istore 6
    //   1009: iload 71
    //   1011: istore 73
    //   1013: aload 70
    //   1015: astore 74
    //   1017: iload 73
    //   1019: istore 75
    //   1021: aload 74
    //   1023: iload 72
    //   1025: caload
    //   1026: istore 31
    //   1028: iload 6
    //   1030: iconst_5
    //   1031: irem
    //   1032: tableswitch	default:+32 -> 1064, 0:+8830->9862, 1:+8837->9869, 2:+8844->9876, 3:+8851->9883
    //   1065: frem
    //   1066: istore 76
    //   1068: iload 76
    //   1070: iload 31
    //   1072: ixor
    //   1073: i2c
    //   1074: istore 77
    //   1076: aload 74
    //   1078: iload 72
    //   1080: iload 77
    //   1082: castore
    //   1083: iload 6
    //   1085: iconst_1
    //   1086: iadd
    //   1087: istore 72
    //   1089: iload 75
    //   1091: ifne +18 -> 1109
    //   1094: aload 5
    //   1096: astore 74
    //   1098: iload 72
    //   1100: istore 78
    //   1102: iload 75
    //   1104: istore 72
    //   1106: goto -85 -> 1021
    //   1109: iload 75
    //   1111: istore 71
    //   1113: aload 5
    //   1115: astore 70
    //   1117: iload 71
    //   1119: iload 72
    //   1121: if_icmpgt -120 -> 1001
    //   1124: new 43	java/lang/String
    //   1127: dup
    //   1128: aload 70
    //   1130: invokespecial 53	java/lang/String:<init>	([C)V
    //   1133: invokevirtual 57	java/lang/String:intern	()Ljava/lang/String;
    //   1136: astore 79
    //   1138: aload_1
    //   1139: iload 69
    //   1141: aload 79
    //   1143: aastore
    //   1144: bipush 7
    //   1146: istore 80
    //   1148: ldc 71
    //   1150: invokevirtual 49	java/lang/String:toCharArray	()[C
    //   1153: astore 81
    //   1155: aload 81
    //   1157: arraylength
    //   1158: istore 82
    //   1160: iload 82
    //   1162: iconst_1
    //   1163: if_icmpgt +10321 -> 11484
    //   1166: iconst_0
    //   1167: istore 83
    //   1169: aload 81
    //   1171: astore 5
    //   1173: iload 83
    //   1175: istore 6
    //   1177: iload 82
    //   1179: istore 84
    //   1181: aload 81
    //   1183: astore 85
    //   1185: iload 84
    //   1187: istore 86
    //   1189: aload 85
    //   1191: iload 83
    //   1193: caload
    //   1194: istore 31
    //   1196: iload 6
    //   1198: iconst_5
    //   1199: irem
    //   1200: tableswitch	default:+32 -> 1232, 0:+8690->9890, 1:+8697->9897, 2:+8704->9904, 3:+8711->9911
    //   1233: frem
    //   1234: istore 87
    //   1236: iload 87
    //   1238: iload 31
    //   1240: ixor
    //   1241: i2c
    //   1242: istore 88
    //   1244: aload 85
    //   1246: iload 83
    //   1248: iload 88
    //   1250: castore
    //   1251: iload 6
    //   1253: iconst_1
    //   1254: iadd
    //   1255: istore 83
    //   1257: iload 86
    //   1259: ifne +18 -> 1277
    //   1262: aload 5
    //   1264: astore 85
    //   1266: iload 83
    //   1268: istore 89
    //   1270: iload 86
    //   1272: istore 83
    //   1274: goto -85 -> 1189
    //   1277: iload 86
    //   1279: istore 82
    //   1281: aload 5
    //   1283: astore 81
    //   1285: iload 82
    //   1287: iload 83
    //   1289: if_icmpgt -120 -> 1169
    //   1292: new 43	java/lang/String
    //   1295: dup
    //   1296: aload 81
    //   1298: invokespecial 53	java/lang/String:<init>	([C)V
    //   1301: invokevirtual 57	java/lang/String:intern	()Ljava/lang/String;
    //   1304: astore 90
    //   1306: aload_1
    //   1307: iload 80
    //   1309: aload 90
    //   1311: aastore
    //   1312: bipush 8
    //   1314: istore 91
    //   1316: ldc 73
    //   1318: invokevirtual 49	java/lang/String:toCharArray	()[C
    //   1321: astore 92
    //   1323: aload 92
    //   1325: arraylength
    //   1326: istore 93
    //   1328: iload 93
    //   1330: iconst_1
    //   1331: if_icmpgt +10147 -> 11478
    //   1334: iconst_0
    //   1335: istore 94
    //   1337: aload 92
    //   1339: astore 5
    //   1341: iload 94
    //   1343: istore 6
    //   1345: iload 93
    //   1347: istore 95
    //   1349: aload 92
    //   1351: astore 96
    //   1353: iload 95
    //   1355: istore 97
    //   1357: aload 96
    //   1359: iload 94
    //   1361: caload
    //   1362: istore 31
    //   1364: iload 6
    //   1366: iconst_5
    //   1367: irem
    //   1368: tableswitch	default:+32 -> 1400, 0:+8550->9918, 1:+8557->9925, 2:+8564->9932, 3:+8571->9939
    //   1401: frem
    //   1402: istore 98
    //   1404: iload 98
    //   1406: iload 31
    //   1408: ixor
    //   1409: i2c
    //   1410: istore 99
    //   1412: aload 96
    //   1414: iload 94
    //   1416: iload 99
    //   1418: castore
    //   1419: iload 6
    //   1421: iconst_1
    //   1422: iadd
    //   1423: istore 94
    //   1425: iload 97
    //   1427: ifne +18 -> 1445
    //   1430: aload 5
    //   1432: astore 96
    //   1434: iload 94
    //   1436: istore 100
    //   1438: iload 97
    //   1440: istore 94
    //   1442: goto -85 -> 1357
    //   1445: iload 97
    //   1447: istore 93
    //   1449: aload 5
    //   1451: astore 92
    //   1453: iload 93
    //   1455: iload 94
    //   1457: if_icmpgt -120 -> 1337
    //   1460: new 43	java/lang/String
    //   1463: dup
    //   1464: aload 92
    //   1466: invokespecial 53	java/lang/String:<init>	([C)V
    //   1469: invokevirtual 57	java/lang/String:intern	()Ljava/lang/String;
    //   1472: astore 101
    //   1474: aload_1
    //   1475: iload 91
    //   1477: aload 101
    //   1479: aastore
    //   1480: ldc 75
    //   1482: invokevirtual 49	java/lang/String:toCharArray	()[C
    //   1485: astore 102
    //   1487: aload 102
    //   1489: arraylength
    //   1490: istore 103
    //   1492: iload 103
    //   1494: iconst_1
    //   1495: if_icmpgt +9977 -> 11472
    //   1498: iconst_0
    //   1499: istore 104
    //   1501: aload 102
    //   1503: astore 5
    //   1505: iload 104
    //   1507: istore 6
    //   1509: iload 103
    //   1511: istore 105
    //   1513: aload 102
    //   1515: astore 106
    //   1517: iload 105
    //   1519: istore 107
    //   1521: aload 106
    //   1523: iload 104
    //   1525: caload
    //   1526: istore 91
    //   1528: iload 6
    //   1530: iconst_5
    //   1531: irem
    //   1532: tableswitch	default:+32 -> 1564, 0:+8414->9946, 1:+8421->9953, 2:+8428->9960, 3:+8435->9967
    //   1565: frem
    //   1566: istore 108
    //   1568: iload 108
    //   1570: iload 91
    //   1572: ixor
    //   1573: i2c
    //   1574: istore 109
    //   1576: aload 106
    //   1578: iload 104
    //   1580: iload 109
    //   1582: castore
    //   1583: iload 6
    //   1585: iconst_1
    //   1586: iadd
    //   1587: istore 104
    //   1589: iload 107
    //   1591: ifne +18 -> 1609
    //   1594: aload 5
    //   1596: astore 106
    //   1598: iload 104
    //   1600: istore 110
    //   1602: iload 107
    //   1604: istore 104
    //   1606: goto -85 -> 1521
    //   1609: iload 107
    //   1611: istore 103
    //   1613: aload 5
    //   1615: astore 102
    //   1617: iload 103
    //   1619: iload 104
    //   1621: if_icmpgt -120 -> 1501
    //   1624: new 43	java/lang/String
    //   1627: dup
    //   1628: aload 102
    //   1630: invokespecial 53	java/lang/String:<init>	([C)V
    //   1633: invokevirtual 57	java/lang/String:intern	()Ljava/lang/String;
    //   1636: astore 111
    //   1638: aload_1
    //   1639: bipush 9
    //   1641: aload 111
    //   1643: aastore
    //   1644: bipush 10
    //   1646: istore 112
    //   1648: ldc 77
    //   1650: invokevirtual 49	java/lang/String:toCharArray	()[C
    //   1653: astore 113
    //   1655: aload 113
    //   1657: arraylength
    //   1658: istore 114
    //   1660: iload 114
    //   1662: iconst_1
    //   1663: if_icmpgt +9803 -> 11466
    //   1666: iconst_0
    //   1667: istore 115
    //   1669: aload 113
    //   1671: astore 5
    //   1673: iload 115
    //   1675: istore 6
    //   1677: iload 114
    //   1679: istore 116
    //   1681: aload 113
    //   1683: astore 117
    //   1685: iload 116
    //   1687: istore 118
    //   1689: aload 117
    //   1691: iload 115
    //   1693: caload
    //   1694: istore 31
    //   1696: iload 6
    //   1698: iconst_5
    //   1699: irem
    //   1700: tableswitch	default:+32 -> 1732, 0:+8274->9974, 1:+8281->9981, 2:+8288->9988, 3:+8295->9995
    //   1733: frem
    //   1734: istore 119
    //   1736: iload 119
    //   1738: iload 31
    //   1740: ixor
    //   1741: i2c
    //   1742: istore 120
    //   1744: aload 117
    //   1746: iload 115
    //   1748: iload 120
    //   1750: castore
    //   1751: iload 6
    //   1753: iconst_1
    //   1754: iadd
    //   1755: istore 115
    //   1757: iload 118
    //   1759: ifne +18 -> 1777
    //   1762: aload 5
    //   1764: astore 117
    //   1766: iload 115
    //   1768: istore 121
    //   1770: iload 118
    //   1772: istore 115
    //   1774: goto -85 -> 1689
    //   1777: iload 118
    //   1779: istore 114
    //   1781: aload 5
    //   1783: astore 113
    //   1785: iload 114
    //   1787: iload 115
    //   1789: if_icmpgt -120 -> 1669
    //   1792: new 43	java/lang/String
    //   1795: dup
    //   1796: aload 113
    //   1798: invokespecial 53	java/lang/String:<init>	([C)V
    //   1801: invokevirtual 57	java/lang/String:intern	()Ljava/lang/String;
    //   1804: astore 122
    //   1806: aload_1
    //   1807: iload 112
    //   1809: aload 122
    //   1811: aastore
    //   1812: bipush 11
    //   1814: istore 123
    //   1816: ldc 79
    //   1818: invokevirtual 49	java/lang/String:toCharArray	()[C
    //   1821: astore 124
    //   1823: aload 124
    //   1825: arraylength
    //   1826: istore 125
    //   1828: iload 125
    //   1830: iconst_1
    //   1831: if_icmpgt +9629 -> 11460
    //   1834: iconst_0
    //   1835: istore 126
    //   1837: aload 124
    //   1839: astore 5
    //   1841: iload 126
    //   1843: istore 6
    //   1845: iload 125
    //   1847: istore 127
    //   1849: aload 124
    //   1851: astore 128
    //   1853: iload 127
    //   1855: istore 129
    //   1857: aload 128
    //   1859: iload 126
    //   1861: caload
    //   1862: istore 31
    //   1864: iload 6
    //   1866: iconst_5
    //   1867: irem
    //   1868: tableswitch	default:+32 -> 1900, 0:+8134->10002, 1:+8141->10009, 2:+8148->10016, 3:+8155->10023
    //   1901: frem
    //   1902: istore 130
    //   1904: iload 130
    //   1906: iload 31
    //   1908: ixor
    //   1909: i2c
    //   1910: istore 131
    //   1912: aload 128
    //   1914: iload 126
    //   1916: iload 131
    //   1918: castore
    //   1919: iload 6
    //   1921: iconst_1
    //   1922: iadd
    //   1923: istore 126
    //   1925: iload 129
    //   1927: ifne +18 -> 1945
    //   1930: aload 5
    //   1932: astore 128
    //   1934: iload 126
    //   1936: istore 132
    //   1938: iload 129
    //   1940: istore 126
    //   1942: goto -85 -> 1857
    //   1945: iload 129
    //   1947: istore 125
    //   1949: aload 5
    //   1951: astore 124
    //   1953: iload 125
    //   1955: iload 126
    //   1957: if_icmpgt -120 -> 1837
    //   1960: new 43	java/lang/String
    //   1963: dup
    //   1964: aload 124
    //   1966: invokespecial 53	java/lang/String:<init>	([C)V
    //   1969: invokevirtual 57	java/lang/String:intern	()Ljava/lang/String;
    //   1972: astore 133
    //   1974: aload_1
    //   1975: iload 123
    //   1977: aload 133
    //   1979: aastore
    //   1980: bipush 12
    //   1982: istore 134
    //   1984: ldc 81
    //   1986: invokevirtual 49	java/lang/String:toCharArray	()[C
    //   1989: astore 135
    //   1991: aload 135
    //   1993: arraylength
    //   1994: istore 136
    //   1996: iload 136
    //   1998: iconst_1
    //   1999: if_icmpgt +9455 -> 11454
    //   2002: iconst_0
    //   2003: istore 137
    //   2005: aload 135
    //   2007: astore 5
    //   2009: iload 137
    //   2011: istore 6
    //   2013: iload 136
    //   2015: istore 138
    //   2017: aload 135
    //   2019: astore 139
    //   2021: iload 138
    //   2023: istore 140
    //   2025: aload 139
    //   2027: iload 137
    //   2029: caload
    //   2030: istore 31
    //   2032: iload 6
    //   2034: iconst_5
    //   2035: irem
    //   2036: tableswitch	default:+32 -> 2068, 0:+7994->10030, 1:+8001->10037, 2:+8008->10044, 3:+8015->10051
    //   2069: frem
    //   2070: istore 141
    //   2072: iload 141
    //   2074: iload 31
    //   2076: ixor
    //   2077: i2c
    //   2078: istore 142
    //   2080: aload 139
    //   2082: iload 137
    //   2084: iload 142
    //   2086: castore
    //   2087: iload 6
    //   2089: iconst_1
    //   2090: iadd
    //   2091: istore 137
    //   2093: iload 140
    //   2095: ifne +18 -> 2113
    //   2098: aload 5
    //   2100: astore 139
    //   2102: iload 137
    //   2104: istore 143
    //   2106: iload 140
    //   2108: istore 137
    //   2110: goto -85 -> 2025
    //   2113: iload 140
    //   2115: istore 136
    //   2117: aload 5
    //   2119: astore 135
    //   2121: iload 136
    //   2123: iload 137
    //   2125: if_icmpgt -120 -> 2005
    //   2128: new 43	java/lang/String
    //   2131: dup
    //   2132: aload 135
    //   2134: invokespecial 53	java/lang/String:<init>	([C)V
    //   2137: invokevirtual 57	java/lang/String:intern	()Ljava/lang/String;
    //   2140: astore 144
    //   2142: aload_1
    //   2143: iload 134
    //   2145: aload 144
    //   2147: aastore
    //   2148: bipush 13
    //   2150: istore 145
    //   2152: ldc 83
    //   2154: invokevirtual 49	java/lang/String:toCharArray	()[C
    //   2157: astore 146
    //   2159: aload 146
    //   2161: arraylength
    //   2162: istore 147
    //   2164: iload 147
    //   2166: iconst_1
    //   2167: if_icmpgt +9281 -> 11448
    //   2170: iconst_0
    //   2171: istore 148
    //   2173: aload 146
    //   2175: astore 5
    //   2177: iload 148
    //   2179: istore 6
    //   2181: iload 147
    //   2183: istore 149
    //   2185: aload 146
    //   2187: astore 150
    //   2189: iload 149
    //   2191: istore 151
    //   2193: aload 150
    //   2195: iload 148
    //   2197: caload
    //   2198: istore 31
    //   2200: iload 6
    //   2202: iconst_5
    //   2203: irem
    //   2204: tableswitch	default:+32 -> 2236, 0:+7854->10058, 1:+7861->10065, 2:+7868->10072, 3:+7875->10079
    //   2237: frem
    //   2238: istore 152
    //   2240: iload 152
    //   2242: iload 31
    //   2244: ixor
    //   2245: i2c
    //   2246: istore 153
    //   2248: aload 150
    //   2250: iload 148
    //   2252: iload 153
    //   2254: castore
    //   2255: iload 6
    //   2257: iconst_1
    //   2258: iadd
    //   2259: istore 148
    //   2261: iload 151
    //   2263: ifne +18 -> 2281
    //   2266: aload 5
    //   2268: astore 150
    //   2270: iload 148
    //   2272: istore 154
    //   2274: iload 151
    //   2276: istore 148
    //   2278: goto -85 -> 2193
    //   2281: iload 151
    //   2283: istore 147
    //   2285: aload 5
    //   2287: astore 146
    //   2289: iload 147
    //   2291: iload 148
    //   2293: if_icmpgt -120 -> 2173
    //   2296: new 43	java/lang/String
    //   2299: dup
    //   2300: aload 146
    //   2302: invokespecial 53	java/lang/String:<init>	([C)V
    //   2305: invokevirtual 57	java/lang/String:intern	()Ljava/lang/String;
    //   2308: astore 155
    //   2310: aload_1
    //   2311: iload 145
    //   2313: aload 155
    //   2315: aastore
    //   2316: bipush 14
    //   2318: istore 156
    //   2320: ldc 85
    //   2322: invokevirtual 49	java/lang/String:toCharArray	()[C
    //   2325: astore 157
    //   2327: aload 157
    //   2329: arraylength
    //   2330: istore 158
    //   2332: iload 158
    //   2334: iconst_1
    //   2335: if_icmpgt +9107 -> 11442
    //   2338: iconst_0
    //   2339: istore 159
    //   2341: aload 157
    //   2343: astore 5
    //   2345: iload 159
    //   2347: istore 6
    //   2349: iload 158
    //   2351: istore 160
    //   2353: aload 157
    //   2355: astore 161
    //   2357: iload 160
    //   2359: istore 162
    //   2361: aload 161
    //   2363: iload 159
    //   2365: caload
    //   2366: istore 31
    //   2368: iload 6
    //   2370: iconst_5
    //   2371: irem
    //   2372: tableswitch	default:+32 -> 2404, 0:+7714->10086, 1:+7721->10093, 2:+7728->10100, 3:+7735->10107
    //   2405: frem
    //   2406: istore 163
    //   2408: iload 163
    //   2410: iload 31
    //   2412: ixor
    //   2413: i2c
    //   2414: istore 164
    //   2416: aload 161
    //   2418: iload 159
    //   2420: iload 164
    //   2422: castore
    //   2423: iload 6
    //   2425: iconst_1
    //   2426: iadd
    //   2427: istore 159
    //   2429: iload 162
    //   2431: ifne +18 -> 2449
    //   2434: aload 5
    //   2436: astore 161
    //   2438: iload 159
    //   2440: istore 165
    //   2442: iload 162
    //   2444: istore 159
    //   2446: goto -85 -> 2361
    //   2449: iload 162
    //   2451: istore 158
    //   2453: aload 5
    //   2455: astore 157
    //   2457: iload 158
    //   2459: iload 159
    //   2461: if_icmpgt -120 -> 2341
    //   2464: new 43	java/lang/String
    //   2467: dup
    //   2468: aload 157
    //   2470: invokespecial 53	java/lang/String:<init>	([C)V
    //   2473: invokevirtual 57	java/lang/String:intern	()Ljava/lang/String;
    //   2476: astore 166
    //   2478: aload_1
    //   2479: iload 156
    //   2481: aload 166
    //   2483: aastore
    //   2484: bipush 15
    //   2486: istore 167
    //   2488: ldc 87
    //   2490: invokevirtual 49	java/lang/String:toCharArray	()[C
    //   2493: astore 168
    //   2495: aload 168
    //   2497: arraylength
    //   2498: istore 169
    //   2500: iload 169
    //   2502: iconst_1
    //   2503: if_icmpgt +8933 -> 11436
    //   2506: iconst_0
    //   2507: istore 170
    //   2509: aload 168
    //   2511: astore 5
    //   2513: iload 170
    //   2515: istore 6
    //   2517: iload 169
    //   2519: istore 171
    //   2521: aload 168
    //   2523: astore 172
    //   2525: iload 171
    //   2527: istore 173
    //   2529: aload 172
    //   2531: iload 170
    //   2533: caload
    //   2534: istore 31
    //   2536: iload 6
    //   2538: iconst_5
    //   2539: irem
    //   2540: tableswitch	default:+32 -> 2572, 0:+7574->10114, 1:+7581->10121, 2:+7588->10128, 3:+7595->10135
    //   2573: frem
    //   2574: istore 174
    //   2576: iload 174
    //   2578: iload 31
    //   2580: ixor
    //   2581: i2c
    //   2582: istore 175
    //   2584: aload 172
    //   2586: iload 170
    //   2588: iload 175
    //   2590: castore
    //   2591: iload 6
    //   2593: iconst_1
    //   2594: iadd
    //   2595: istore 170
    //   2597: iload 173
    //   2599: ifne +18 -> 2617
    //   2602: aload 5
    //   2604: astore 172
    //   2606: iload 170
    //   2608: istore 176
    //   2610: iload 173
    //   2612: istore 170
    //   2614: goto -85 -> 2529
    //   2617: iload 173
    //   2619: istore 169
    //   2621: aload 5
    //   2623: astore 168
    //   2625: iload 169
    //   2627: iload 170
    //   2629: if_icmpgt -120 -> 2509
    //   2632: new 43	java/lang/String
    //   2635: dup
    //   2636: aload 168
    //   2638: invokespecial 53	java/lang/String:<init>	([C)V
    //   2641: invokevirtual 57	java/lang/String:intern	()Ljava/lang/String;
    //   2644: astore 177
    //   2646: aload_1
    //   2647: iload 167
    //   2649: aload 177
    //   2651: aastore
    //   2652: bipush 16
    //   2654: istore 178
    //   2656: ldc 89
    //   2658: invokevirtual 49	java/lang/String:toCharArray	()[C
    //   2661: astore 179
    //   2663: aload 179
    //   2665: arraylength
    //   2666: istore 180
    //   2668: iload 180
    //   2670: iconst_1
    //   2671: if_icmpgt +8759 -> 11430
    //   2674: iconst_0
    //   2675: istore 181
    //   2677: aload 179
    //   2679: astore 5
    //   2681: iload 181
    //   2683: istore 6
    //   2685: iload 180
    //   2687: istore 182
    //   2689: aload 179
    //   2691: astore 183
    //   2693: iload 182
    //   2695: istore 184
    //   2697: aload 183
    //   2699: iload 181
    //   2701: caload
    //   2702: istore 31
    //   2704: iload 6
    //   2706: iconst_5
    //   2707: irem
    //   2708: tableswitch	default:+32 -> 2740, 0:+7434->10142, 1:+7441->10149, 2:+7448->10156, 3:+7455->10163
    //   2741: frem
    //   2742: istore 185
    //   2744: iload 185
    //   2746: iload 31
    //   2748: ixor
    //   2749: i2c
    //   2750: istore 186
    //   2752: aload 183
    //   2754: iload 181
    //   2756: iload 186
    //   2758: castore
    //   2759: iload 6
    //   2761: iconst_1
    //   2762: iadd
    //   2763: istore 181
    //   2765: iload 184
    //   2767: ifne +18 -> 2785
    //   2770: aload 5
    //   2772: astore 183
    //   2774: iload 181
    //   2776: istore 187
    //   2778: iload 184
    //   2780: istore 181
    //   2782: goto -85 -> 2697
    //   2785: iload 184
    //   2787: istore 180
    //   2789: aload 5
    //   2791: astore 179
    //   2793: iload 180
    //   2795: iload 181
    //   2797: if_icmpgt -120 -> 2677
    //   2800: new 43	java/lang/String
    //   2803: dup
    //   2804: aload 179
    //   2806: invokespecial 53	java/lang/String:<init>	([C)V
    //   2809: invokevirtual 57	java/lang/String:intern	()Ljava/lang/String;
    //   2812: astore 188
    //   2814: aload_1
    //   2815: iload 178
    //   2817: aload 188
    //   2819: aastore
    //   2820: bipush 17
    //   2822: istore 189
    //   2824: ldc 91
    //   2826: invokevirtual 49	java/lang/String:toCharArray	()[C
    //   2829: astore 190
    //   2831: aload 190
    //   2833: arraylength
    //   2834: istore 191
    //   2836: iload 191
    //   2838: iconst_1
    //   2839: if_icmpgt +8585 -> 11424
    //   2842: iconst_0
    //   2843: istore 192
    //   2845: aload 190
    //   2847: astore 5
    //   2849: iload 192
    //   2851: istore 6
    //   2853: iload 191
    //   2855: istore 193
    //   2857: aload 190
    //   2859: astore 194
    //   2861: iload 193
    //   2863: istore 195
    //   2865: aload 194
    //   2867: iload 192
    //   2869: caload
    //   2870: istore 31
    //   2872: iload 6
    //   2874: iconst_5
    //   2875: irem
    //   2876: tableswitch	default:+32 -> 2908, 0:+7294->10170, 1:+7301->10177, 2:+7308->10184, 3:+7315->10191
    //   2909: frem
    //   2910: istore 196
    //   2912: iload 196
    //   2914: iload 31
    //   2916: ixor
    //   2917: i2c
    //   2918: istore 197
    //   2920: aload 194
    //   2922: iload 192
    //   2924: iload 197
    //   2926: castore
    //   2927: iload 6
    //   2929: iconst_1
    //   2930: iadd
    //   2931: istore 192
    //   2933: iload 195
    //   2935: ifne +18 -> 2953
    //   2938: aload 5
    //   2940: astore 194
    //   2942: iload 192
    //   2944: istore 198
    //   2946: iload 195
    //   2948: istore 192
    //   2950: goto -85 -> 2865
    //   2953: iload 195
    //   2955: istore 191
    //   2957: aload 5
    //   2959: astore 190
    //   2961: iload 191
    //   2963: iload 192
    //   2965: if_icmpgt -120 -> 2845
    //   2968: new 43	java/lang/String
    //   2971: dup
    //   2972: aload 190
    //   2974: invokespecial 53	java/lang/String:<init>	([C)V
    //   2977: invokevirtual 57	java/lang/String:intern	()Ljava/lang/String;
    //   2980: astore 199
    //   2982: aload_1
    //   2983: iload 189
    //   2985: aload 199
    //   2987: aastore
    //   2988: bipush 18
    //   2990: istore 200
    //   2992: ldc 93
    //   2994: invokevirtual 49	java/lang/String:toCharArray	()[C
    //   2997: astore 201
    //   2999: aload 201
    //   3001: arraylength
    //   3002: istore 202
    //   3004: iload 202
    //   3006: iconst_1
    //   3007: if_icmpgt +8411 -> 11418
    //   3010: iconst_0
    //   3011: istore 203
    //   3013: aload 201
    //   3015: astore 5
    //   3017: iload 203
    //   3019: istore 6
    //   3021: iload 202
    //   3023: istore 204
    //   3025: aload 201
    //   3027: astore 205
    //   3029: iload 204
    //   3031: istore 206
    //   3033: aload 205
    //   3035: iload 203
    //   3037: caload
    //   3038: istore 31
    //   3040: iload 6
    //   3042: iconst_5
    //   3043: irem
    //   3044: tableswitch	default:+32 -> 3076, 0:+7154->10198, 1:+7161->10205, 2:+7168->10212, 3:+7175->10219
    //   3077: frem
    //   3078: istore 207
    //   3080: iload 207
    //   3082: iload 31
    //   3084: ixor
    //   3085: i2c
    //   3086: istore 208
    //   3088: aload 205
    //   3090: iload 203
    //   3092: iload 208
    //   3094: castore
    //   3095: iload 6
    //   3097: iconst_1
    //   3098: iadd
    //   3099: istore 203
    //   3101: iload 206
    //   3103: ifne +18 -> 3121
    //   3106: aload 5
    //   3108: astore 205
    //   3110: iload 203
    //   3112: istore 209
    //   3114: iload 206
    //   3116: istore 203
    //   3118: goto -85 -> 3033
    //   3121: iload 206
    //   3123: istore 202
    //   3125: aload 5
    //   3127: astore 201
    //   3129: iload 202
    //   3131: iload 203
    //   3133: if_icmpgt -120 -> 3013
    //   3136: new 43	java/lang/String
    //   3139: dup
    //   3140: aload 201
    //   3142: invokespecial 53	java/lang/String:<init>	([C)V
    //   3145: invokevirtual 57	java/lang/String:intern	()Ljava/lang/String;
    //   3148: astore 210
    //   3150: aload_1
    //   3151: iload 200
    //   3153: aload 210
    //   3155: aastore
    //   3156: bipush 19
    //   3158: istore 211
    //   3160: ldc 95
    //   3162: invokevirtual 49	java/lang/String:toCharArray	()[C
    //   3165: astore 212
    //   3167: aload 212
    //   3169: arraylength
    //   3170: istore 213
    //   3172: iload 213
    //   3174: iconst_1
    //   3175: if_icmpgt +8237 -> 11412
    //   3178: iconst_0
    //   3179: istore 214
    //   3181: aload 212
    //   3183: astore 5
    //   3185: iload 214
    //   3187: istore 6
    //   3189: iload 213
    //   3191: istore 215
    //   3193: aload 212
    //   3195: astore 216
    //   3197: iload 215
    //   3199: istore 217
    //   3201: aload 216
    //   3203: iload 214
    //   3205: caload
    //   3206: istore 31
    //   3208: iload 6
    //   3210: iconst_5
    //   3211: irem
    //   3212: tableswitch	default:+32 -> 3244, 0:+7014->10226, 1:+7021->10233, 2:+7028->10240, 3:+7035->10247
    //   3245: frem
    //   3246: istore 218
    //   3248: iload 218
    //   3250: iload 31
    //   3252: ixor
    //   3253: i2c
    //   3254: istore 219
    //   3256: aload 216
    //   3258: iload 214
    //   3260: iload 219
    //   3262: castore
    //   3263: iload 6
    //   3265: iconst_1
    //   3266: iadd
    //   3267: istore 214
    //   3269: iload 217
    //   3271: ifne +18 -> 3289
    //   3274: aload 5
    //   3276: astore 216
    //   3278: iload 214
    //   3280: istore 220
    //   3282: iload 217
    //   3284: istore 214
    //   3286: goto -85 -> 3201
    //   3289: iload 217
    //   3291: istore 213
    //   3293: aload 5
    //   3295: astore 212
    //   3297: iload 213
    //   3299: iload 214
    //   3301: if_icmpgt -120 -> 3181
    //   3304: new 43	java/lang/String
    //   3307: dup
    //   3308: aload 212
    //   3310: invokespecial 53	java/lang/String:<init>	([C)V
    //   3313: invokevirtual 57	java/lang/String:intern	()Ljava/lang/String;
    //   3316: astore 221
    //   3318: aload_1
    //   3319: iload 211
    //   3321: aload 221
    //   3323: aastore
    //   3324: bipush 20
    //   3326: istore 222
    //   3328: ldc 97
    //   3330: invokevirtual 49	java/lang/String:toCharArray	()[C
    //   3333: astore 223
    //   3335: aload 223
    //   3337: arraylength
    //   3338: istore 224
    //   3340: iload 224
    //   3342: iconst_1
    //   3343: if_icmpgt +8063 -> 11406
    //   3346: iconst_0
    //   3347: istore 225
    //   3349: aload 223
    //   3351: astore 5
    //   3353: iload 225
    //   3355: istore 6
    //   3357: iload 224
    //   3359: istore 226
    //   3361: aload 223
    //   3363: astore 227
    //   3365: iload 226
    //   3367: istore 228
    //   3369: aload 227
    //   3371: iload 225
    //   3373: caload
    //   3374: istore 31
    //   3376: iload 6
    //   3378: iconst_5
    //   3379: irem
    //   3380: tableswitch	default:+32 -> 3412, 0:+6874->10254, 1:+6881->10261, 2:+6888->10268, 3:+6895->10275
    //   3413: frem
    //   3414: istore 229
    //   3416: iload 229
    //   3418: iload 31
    //   3420: ixor
    //   3421: i2c
    //   3422: istore 230
    //   3424: aload 227
    //   3426: iload 225
    //   3428: iload 230
    //   3430: castore
    //   3431: iload 6
    //   3433: iconst_1
    //   3434: iadd
    //   3435: istore 225
    //   3437: iload 228
    //   3439: ifne +18 -> 3457
    //   3442: aload 5
    //   3444: astore 227
    //   3446: iload 225
    //   3448: istore 231
    //   3450: iload 228
    //   3452: istore 225
    //   3454: goto -85 -> 3369
    //   3457: iload 228
    //   3459: istore 224
    //   3461: aload 5
    //   3463: astore 223
    //   3465: iload 224
    //   3467: iload 225
    //   3469: if_icmpgt -120 -> 3349
    //   3472: new 43	java/lang/String
    //   3475: dup
    //   3476: aload 223
    //   3478: invokespecial 53	java/lang/String:<init>	([C)V
    //   3481: invokevirtual 57	java/lang/String:intern	()Ljava/lang/String;
    //   3484: astore 232
    //   3486: aload_1
    //   3487: iload 222
    //   3489: aload 232
    //   3491: aastore
    //   3492: bipush 21
    //   3494: istore 233
    //   3496: ldc 99
    //   3498: invokevirtual 49	java/lang/String:toCharArray	()[C
    //   3501: astore 234
    //   3503: aload 234
    //   3505: arraylength
    //   3506: istore 235
    //   3508: iload 235
    //   3510: iconst_1
    //   3511: if_icmpgt +7889 -> 11400
    //   3514: iconst_0
    //   3515: istore 236
    //   3517: aload 234
    //   3519: astore 5
    //   3521: iload 236
    //   3523: istore 6
    //   3525: iload 235
    //   3527: istore 237
    //   3529: aload 234
    //   3531: astore 238
    //   3533: iload 237
    //   3535: istore 239
    //   3537: aload 238
    //   3539: iload 236
    //   3541: caload
    //   3542: istore 31
    //   3544: iload 6
    //   3546: iconst_5
    //   3547: irem
    //   3548: tableswitch	default:+32 -> 3580, 0:+6734->10282, 1:+6741->10289, 2:+6748->10296, 3:+6755->10303
    //   3581: frem
    //   3582: istore 240
    //   3584: iload 240
    //   3586: iload 31
    //   3588: ixor
    //   3589: i2c
    //   3590: istore 241
    //   3592: aload 238
    //   3594: iload 236
    //   3596: iload 241
    //   3598: castore
    //   3599: iload 6
    //   3601: iconst_1
    //   3602: iadd
    //   3603: istore 236
    //   3605: iload 239
    //   3607: ifne +18 -> 3625
    //   3610: aload 5
    //   3612: astore 238
    //   3614: iload 236
    //   3616: istore 242
    //   3618: iload 239
    //   3620: istore 236
    //   3622: goto -85 -> 3537
    //   3625: iload 239
    //   3627: istore 235
    //   3629: aload 5
    //   3631: astore 234
    //   3633: iload 235
    //   3635: iload 236
    //   3637: if_icmpgt -120 -> 3517
    //   3640: new 43	java/lang/String
    //   3643: dup
    //   3644: aload 234
    //   3646: invokespecial 53	java/lang/String:<init>	([C)V
    //   3649: invokevirtual 57	java/lang/String:intern	()Ljava/lang/String;
    //   3652: astore 243
    //   3654: aload_1
    //   3655: iload 233
    //   3657: aload 243
    //   3659: aastore
    //   3660: bipush 22
    //   3662: istore 244
    //   3664: ldc 101
    //   3666: invokevirtual 49	java/lang/String:toCharArray	()[C
    //   3669: astore 245
    //   3671: aload 245
    //   3673: arraylength
    //   3674: istore 246
    //   3676: iload 246
    //   3678: iconst_1
    //   3679: if_icmpgt +7715 -> 11394
    //   3682: iconst_0
    //   3683: istore 247
    //   3685: aload 245
    //   3687: astore 5
    //   3689: iload 247
    //   3691: istore 6
    //   3693: iload 246
    //   3695: istore 248
    //   3697: aload 245
    //   3699: astore 249
    //   3701: iload 248
    //   3703: istore 250
    //   3705: aload 249
    //   3707: iload 247
    //   3709: caload
    //   3710: istore 31
    //   3712: iload 6
    //   3714: iconst_5
    //   3715: irem
    //   3716: tableswitch	default:+32 -> 3748, 0:+6594->10310, 1:+6601->10317, 2:+6608->10324, 3:+6615->10331
    //   3749: frem
    //   3750: istore 251
    //   3752: iload 251
    //   3754: iload 31
    //   3756: ixor
    //   3757: i2c
    //   3758: istore 252
    //   3760: aload 249
    //   3762: iload 247
    //   3764: iload 252
    //   3766: castore
    //   3767: iload 6
    //   3769: iconst_1
    //   3770: iadd
    //   3771: istore 247
    //   3773: iload 250
    //   3775: ifne +18 -> 3793
    //   3778: aload 5
    //   3780: astore 249
    //   3782: iload 247
    //   3784: istore 253
    //   3786: iload 250
    //   3788: istore 247
    //   3790: goto -85 -> 3705
    //   3793: iload 250
    //   3795: istore 246
    //   3797: aload 5
    //   3799: astore 245
    //   3801: iload 246
    //   3803: iload 247
    //   3805: if_icmpgt -120 -> 3685
    //   3808: new 43	java/lang/String
    //   3811: dup
    //   3812: aload 245
    //   3814: invokespecial 53	java/lang/String:<init>	([C)V
    //   3817: invokevirtual 57	java/lang/String:intern	()Ljava/lang/String;
    //   3820: astore 254
    //   3822: aload_1
    //   3823: iload 244
    //   3825: aload 254
    //   3827: aastore
    //   3828: bipush 23
    //   3830: istore 255
    //   3832: ldc 103
    //   3834: invokevirtual 49	java/lang/String:toCharArray	()[C
    //   3837: wide
    //   3841: wide
    //   3845: arraylength
    //   3846: wide
    //   3850: wide
    //   3854: iconst_1
    //   3855: if_icmpgt +7531 -> 11386
    //   3858: iconst_0
    //   3859: wide
    //   3863: wide
    //   3867: astore 5
    //   3869: wide
    //   3873: istore 6
    //   3875: wide
    //   3879: wide
    //   3883: wide
    //   3887: wide
    //   3891: wide
    //   3895: wide
    //   3899: wide
    //   3903: wide
    //   3907: caload
    //   3908: istore 31
    //   3910: iload 6
    //   3912: iconst_5
    //   3913: irem
    //   3914: tableswitch	default:+30 -> 3944, 0:+6424->10338, 1:+6433->10347, 2:+6442->10356, 3:+6451->10365
    //   3945: frem
    //   3946: wide
    //   3950: wide
    //   3954: iload 31
    //   3956: ixor
    //   3957: i2c
    //   3958: wide
    //   3962: wide
    //   3966: wide
    //   3970: wide
    //   3974: castore
    //   3975: iload 6
    //   3977: iconst_1
    //   3978: iadd
    //   3979: wide
    //   3983: wide
    //   3987: ifne +28 -> 4015
    //   3990: aload 5
    //   3992: wide
    //   3996: wide
    //   4000: wide
    //   4004: wide
    //   4008: wide
    //   4012: goto -113 -> 3899
    //   4015: wide
    //   4019: wide
    //   4023: aload 5
    //   4025: wide
    //   4029: wide
    //   4033: wide
    //   4037: if_icmpgt -174 -> 3863
    //   4040: new 43	java/lang/String
    //   4043: dup
    //   4044: wide
    //   4048: invokespecial 53	java/lang/String:<init>	([C)V
    //   4051: invokevirtual 57	java/lang/String:intern	()Ljava/lang/String;
    //   4054: wide
    //   4058: aload_1
    //   4059: iload 255
    //   4061: wide
    //   4065: aastore
    //   4066: bipush 24
    //   4068: wide
    //   4072: ldc 105
    //   4074: invokevirtual 49	java/lang/String:toCharArray	()[C
    //   4077: wide
    //   4081: wide
    //   4085: arraylength
    //   4086: wide
    //   4090: wide
    //   4094: iconst_1
    //   4095: if_icmpgt +7283 -> 11378
    //   4098: iconst_0
    //   4099: wide
    //   4103: wide
    //   4107: astore 5
    //   4109: wide
    //   4113: istore 6
    //   4115: wide
    //   4119: wide
    //   4123: wide
    //   4127: wide
    //   4131: wide
    //   4135: wide
    //   4139: wide
    //   4143: wide
    //   4147: caload
    //   4148: istore 31
    //   4150: iload 6
    //   4152: iconst_5
    //   4153: irem
    //   4154: tableswitch	default:+30 -> 4184, 0:+6220->10374, 1:+6229->10383, 2:+6238->10392, 3:+6247->10401
    //   4185: frem
    //   4186: wide
    //   4190: wide
    //   4194: iload 31
    //   4196: ixor
    //   4197: i2c
    //   4198: wide
    //   4202: wide
    //   4206: wide
    //   4210: wide
    //   4214: castore
    //   4215: iload 6
    //   4217: iconst_1
    //   4218: iadd
    //   4219: wide
    //   4223: wide
    //   4227: ifne +28 -> 4255
    //   4230: aload 5
    //   4232: wide
    //   4236: wide
    //   4240: wide
    //   4244: wide
    //   4248: wide
    //   4252: goto -113 -> 4139
    //   4255: wide
    //   4259: wide
    //   4263: aload 5
    //   4265: wide
    //   4269: wide
    //   4273: wide
    //   4277: if_icmpgt -174 -> 4103
    //   4280: new 43	java/lang/String
    //   4283: dup
    //   4284: wide
    //   4288: invokespecial 53	java/lang/String:<init>	([C)V
    //   4291: invokevirtual 57	java/lang/String:intern	()Ljava/lang/String;
    //   4294: wide
    //   4298: aload_1
    //   4299: wide
    //   4303: wide
    //   4307: aastore
    //   4308: ldc 107
    //   4310: invokevirtual 49	java/lang/String:toCharArray	()[C
    //   4313: wide
    //   4317: wide
    //   4321: arraylength
    //   4322: wide
    //   4326: wide
    //   4330: iconst_1
    //   4331: if_icmpgt +7039 -> 11370
    //   4334: iconst_0
    //   4335: wide
    //   4339: wide
    //   4343: astore 5
    //   4345: wide
    //   4349: istore 6
    //   4351: wide
    //   4355: wide
    //   4359: wide
    //   4363: wide
    //   4367: wide
    //   4371: wide
    //   4375: wide
    //   4379: wide
    //   4383: caload
    //   4384: wide
    //   4388: iload 6
    //   4390: iconst_5
    //   4391: irem
    //   4392: tableswitch	default:+32 -> 4424, 0:+6018->10410, 1:+6027->10419, 2:+6036->10428, 3:+6045->10437
    //   4425: frem
    //   4426: wide
    //   4430: wide
    //   4434: wide
    //   4438: ixor
    //   4439: i2c
    //   4440: wide
    //   4444: wide
    //   4448: wide
    //   4452: wide
    //   4456: castore
    //   4457: iload 6
    //   4459: iconst_1
    //   4460: iadd
    //   4461: wide
    //   4465: wide
    //   4469: ifne +28 -> 4497
    //   4472: aload 5
    //   4474: wide
    //   4478: wide
    //   4482: wide
    //   4486: wide
    //   4490: wide
    //   4494: goto -119 -> 4375
    //   4497: wide
    //   4501: wide
    //   4505: aload 5
    //   4507: wide
    //   4511: wide
    //   4515: wide
    //   4519: if_icmpgt -180 -> 4339
    //   4522: new 43	java/lang/String
    //   4525: dup
    //   4526: wide
    //   4530: invokespecial 53	java/lang/String:<init>	([C)V
    //   4533: invokevirtual 57	java/lang/String:intern	()Ljava/lang/String;
    //   4536: wide
    //   4540: aload_1
    //   4541: bipush 25
    //   4543: wide
    //   4547: aastore
    //   4548: bipush 26
    //   4550: wide
    //   4554: ldc 109
    //   4556: invokevirtual 49	java/lang/String:toCharArray	()[C
    //   4559: wide
    //   4563: wide
    //   4567: arraylength
    //   4568: wide
    //   4572: wide
    //   4576: iconst_1
    //   4577: if_icmpgt +6785 -> 11362
    //   4580: iconst_0
    //   4581: wide
    //   4585: wide
    //   4589: astore 5
    //   4591: wide
    //   4595: istore 6
    //   4597: wide
    //   4601: wide
    //   4605: wide
    //   4609: wide
    //   4613: wide
    //   4617: wide
    //   4621: wide
    //   4625: wide
    //   4629: caload
    //   4630: istore 31
    //   4632: iload 6
    //   4634: iconst_5
    //   4635: irem
    //   4636: tableswitch	default:+32 -> 4668, 0:+5810->10446, 1:+5819->10455, 2:+5828->10464, 3:+5837->10473
    //   4669: frem
    //   4670: wide
    //   4674: wide
    //   4678: iload 31
    //   4680: ixor
    //   4681: i2c
    //   4682: wide
    //   4686: wide
    //   4690: wide
    //   4694: wide
    //   4698: castore
    //   4699: iload 6
    //   4701: iconst_1
    //   4702: iadd
    //   4703: wide
    //   4707: wide
    //   4711: ifne +28 -> 4739
    //   4714: aload 5
    //   4716: wide
    //   4720: wide
    //   4724: wide
    //   4728: wide
    //   4732: wide
    //   4736: goto -115 -> 4621
    //   4739: wide
    //   4743: wide
    //   4747: aload 5
    //   4749: wide
    //   4753: wide
    //   4757: wide
    //   4761: if_icmpgt -176 -> 4585
    //   4764: new 43	java/lang/String
    //   4767: dup
    //   4768: wide
    //   4772: invokespecial 53	java/lang/String:<init>	([C)V
    //   4775: invokevirtual 57	java/lang/String:intern	()Ljava/lang/String;
    //   4778: wide
    //   4782: aload_1
    //   4783: wide
    //   4787: wide
    //   4791: aastore
    //   4792: bipush 27
    //   4794: wide
    //   4798: ldc 111
    //   4800: invokevirtual 49	java/lang/String:toCharArray	()[C
    //   4803: wide
    //   4807: wide
    //   4811: arraylength
    //   4812: wide
    //   4816: wide
    //   4820: iconst_1
    //   4821: if_icmpgt +6533 -> 11354
    //   4824: iconst_0
    //   4825: wide
    //   4829: wide
    //   4833: astore 5
    //   4835: wide
    //   4839: istore 6
    //   4841: wide
    //   4845: wide
    //   4849: wide
    //   4853: wide
    //   4857: wide
    //   4861: wide
    //   4865: wide
    //   4869: wide
    //   4873: caload
    //   4874: istore 31
    //   4876: iload 6
    //   4878: iconst_5
    //   4879: irem
    //   4880: tableswitch	default:+32 -> 4912, 0:+5602->10482, 1:+5611->10491, 2:+5620->10500, 3:+5629->10509
    //   4913: frem
    //   4914: wide
    //   4918: wide
    //   4922: iload 31
    //   4924: ixor
    //   4925: i2c
    //   4926: wide
    //   4930: wide
    //   4934: wide
    //   4938: wide
    //   4942: castore
    //   4943: iload 6
    //   4945: iconst_1
    //   4946: iadd
    //   4947: wide
    //   4951: wide
    //   4955: ifne +28 -> 4983
    //   4958: aload 5
    //   4960: wide
    //   4964: wide
    //   4968: wide
    //   4972: wide
    //   4976: wide
    //   4980: goto -115 -> 4865
    //   4983: wide
    //   4987: wide
    //   4991: aload 5
    //   4993: wide
    //   4997: wide
    //   5001: wide
    //   5005: if_icmpgt -176 -> 4829
    //   5008: new 43	java/lang/String
    //   5011: dup
    //   5012: wide
    //   5016: invokespecial 53	java/lang/String:<init>	([C)V
    //   5019: invokevirtual 57	java/lang/String:intern	()Ljava/lang/String;
    //   5022: wide
    //   5026: aload_1
    //   5027: wide
    //   5031: wide
    //   5035: aastore
    //   5036: bipush 28
    //   5038: wide
    //   5042: ldc 113
    //   5044: invokevirtual 49	java/lang/String:toCharArray	()[C
    //   5047: wide
    //   5051: wide
    //   5055: arraylength
    //   5056: wide
    //   5060: wide
    //   5064: iconst_1
    //   5065: if_icmpgt +6281 -> 11346
    //   5068: iconst_0
    //   5069: wide
    //   5073: wide
    //   5077: astore 5
    //   5079: wide
    //   5083: istore 6
    //   5085: wide
    //   5089: wide
    //   5093: wide
    //   5097: wide
    //   5101: wide
    //   5105: wide
    //   5109: wide
    //   5113: wide
    //   5117: caload
    //   5118: istore 31
    //   5120: iload 6
    //   5122: iconst_5
    //   5123: irem
    //   5124: tableswitch	default:+32 -> 5156, 0:+5394->10518, 1:+5403->10527, 2:+5412->10536, 3:+5421->10545
    //   5157: frem
    //   5158: wide
    //   5162: wide
    //   5166: iload 31
    //   5168: ixor
    //   5169: i2c
    //   5170: wide
    //   5174: wide
    //   5178: wide
    //   5182: wide
    //   5186: castore
    //   5187: iload 6
    //   5189: iconst_1
    //   5190: iadd
    //   5191: wide
    //   5195: wide
    //   5199: ifne +28 -> 5227
    //   5202: aload 5
    //   5204: wide
    //   5208: wide
    //   5212: wide
    //   5216: wide
    //   5220: wide
    //   5224: goto -115 -> 5109
    //   5227: wide
    //   5231: wide
    //   5235: aload 5
    //   5237: wide
    //   5241: wide
    //   5245: wide
    //   5249: if_icmpgt -176 -> 5073
    //   5252: new 43	java/lang/String
    //   5255: dup
    //   5256: wide
    //   5260: invokespecial 53	java/lang/String:<init>	([C)V
    //   5263: invokevirtual 57	java/lang/String:intern	()Ljava/lang/String;
    //   5266: wide
    //   5270: aload_1
    //   5271: wide
    //   5275: wide
    //   5279: aastore
    //   5280: bipush 29
    //   5282: wide
    //   5286: ldc 115
    //   5288: invokevirtual 49	java/lang/String:toCharArray	()[C
    //   5291: wide
    //   5295: wide
    //   5299: arraylength
    //   5300: wide
    //   5304: wide
    //   5308: iconst_1
    //   5309: if_icmpgt +6029 -> 11338
    //   5312: iconst_0
    //   5313: wide
    //   5317: wide
    //   5321: astore 5
    //   5323: wide
    //   5327: istore 6
    //   5329: wide
    //   5333: wide
    //   5337: wide
    //   5341: wide
    //   5345: wide
    //   5349: wide
    //   5353: wide
    //   5357: wide
    //   5361: caload
    //   5362: istore 31
    //   5364: iload 6
    //   5366: iconst_5
    //   5367: irem
    //   5368: tableswitch	default:+32 -> 5400, 0:+5186->10554, 1:+5195->10563, 2:+5204->10572, 3:+5213->10581
    //   5401: frem
    //   5402: wide
    //   5406: wide
    //   5410: iload 31
    //   5412: ixor
    //   5413: i2c
    //   5414: wide
    //   5418: wide
    //   5422: wide
    //   5426: wide
    //   5430: castore
    //   5431: iload 6
    //   5433: iconst_1
    //   5434: iadd
    //   5435: wide
    //   5439: wide
    //   5443: ifne +28 -> 5471
    //   5446: aload 5
    //   5448: wide
    //   5452: wide
    //   5456: wide
    //   5460: wide
    //   5464: wide
    //   5468: goto -115 -> 5353
    //   5471: wide
    //   5475: wide
    //   5479: aload 5
    //   5481: wide
    //   5485: wide
    //   5489: wide
    //   5493: if_icmpgt -176 -> 5317
    //   5496: new 43	java/lang/String
    //   5499: dup
    //   5500: wide
    //   5504: invokespecial 53	java/lang/String:<init>	([C)V
    //   5507: invokevirtual 57	java/lang/String:intern	()Ljava/lang/String;
    //   5510: wide
    //   5514: aload_1
    //   5515: wide
    //   5519: wide
    //   5523: aastore
    //   5524: bipush 30
    //   5526: wide
    //   5530: ldc 117
    //   5532: invokevirtual 49	java/lang/String:toCharArray	()[C
    //   5535: wide
    //   5539: wide
    //   5543: arraylength
    //   5544: wide
    //   5548: wide
    //   5552: iconst_1
    //   5553: if_icmpgt +5777 -> 11330
    //   5556: iconst_0
    //   5557: wide
    //   5561: wide
    //   5565: astore 5
    //   5567: wide
    //   5571: istore 6
    //   5573: wide
    //   5577: wide
    //   5581: wide
    //   5585: wide
    //   5589: wide
    //   5593: wide
    //   5597: wide
    //   5601: wide
    //   5605: caload
    //   5606: istore 31
    //   5608: iload 6
    //   5610: iconst_5
    //   5611: irem
    //   5612: tableswitch	default:+32 -> 5644, 0:+4978->10590, 1:+4987->10599, 2:+4996->10608, 3:+5005->10617
    //   5645: frem
    //   5646: wide
    //   5650: wide
    //   5654: iload 31
    //   5656: ixor
    //   5657: i2c
    //   5658: wide
    //   5662: wide
    //   5666: wide
    //   5670: wide
    //   5674: castore
    //   5675: iload 6
    //   5677: iconst_1
    //   5678: iadd
    //   5679: wide
    //   5683: wide
    //   5687: ifne +28 -> 5715
    //   5690: aload 5
    //   5692: wide
    //   5696: wide
    //   5700: wide
    //   5704: wide
    //   5708: wide
    //   5712: goto -115 -> 5597
    //   5715: wide
    //   5719: wide
    //   5723: aload 5
    //   5725: wide
    //   5729: wide
    //   5733: wide
    //   5737: if_icmpgt -176 -> 5561
    //   5740: new 43	java/lang/String
    //   5743: dup
    //   5744: wide
    //   5748: invokespecial 53	java/lang/String:<init>	([C)V
    //   5751: invokevirtual 57	java/lang/String:intern	()Ljava/lang/String;
    //   5754: wide
    //   5758: aload_1
    //   5759: wide
    //   5763: wide
    //   5767: aastore
    //   5768: bipush 31
    //   5770: wide
    //   5774: ldc 119
    //   5776: invokevirtual 49	java/lang/String:toCharArray	()[C
    //   5779: wide
    //   5783: wide
    //   5787: arraylength
    //   5788: wide
    //   5792: wide
    //   5796: iconst_1
    //   5797: if_icmpgt +5525 -> 11322
    //   5800: iconst_0
    //   5801: wide
    //   5805: wide
    //   5809: astore 5
    //   5811: wide
    //   5815: istore 6
    //   5817: wide
    //   5821: wide
    //   5825: wide
    //   5829: wide
    //   5833: wide
    //   5837: wide
    //   5841: wide
    //   5845: wide
    //   5849: caload
    //   5850: istore 31
    //   5852: iload 6
    //   5854: iconst_5
    //   5855: irem
    //   5856: tableswitch	default:+32 -> 5888, 0:+4770->10626, 1:+4779->10635, 2:+4788->10644, 3:+4797->10653
    //   5889: frem
    //   5890: wide
    //   5894: wide
    //   5898: iload 31
    //   5900: ixor
    //   5901: i2c
    //   5902: wide
    //   5906: wide
    //   5910: wide
    //   5914: wide
    //   5918: castore
    //   5919: iload 6
    //   5921: iconst_1
    //   5922: iadd
    //   5923: wide
    //   5927: wide
    //   5931: ifne +28 -> 5959
    //   5934: aload 5
    //   5936: wide
    //   5940: wide
    //   5944: wide
    //   5948: wide
    //   5952: wide
    //   5956: goto -115 -> 5841
    //   5959: wide
    //   5963: wide
    //   5967: aload 5
    //   5969: wide
    //   5973: wide
    //   5977: wide
    //   5981: if_icmpgt -176 -> 5805
    //   5984: new 43	java/lang/String
    //   5987: dup
    //   5988: wide
    //   5992: invokespecial 53	java/lang/String:<init>	([C)V
    //   5995: invokevirtual 57	java/lang/String:intern	()Ljava/lang/String;
    //   5998: wide
    //   6002: aload_1
    //   6003: wide
    //   6007: wide
    //   6011: aastore
    //   6012: bipush 32
    //   6014: wide
    //   6018: ldc 121
    //   6020: invokevirtual 49	java/lang/String:toCharArray	()[C
    //   6023: wide
    //   6027: wide
    //   6031: arraylength
    //   6032: wide
    //   6036: wide
    //   6040: iconst_1
    //   6041: if_icmpgt +5273 -> 11314
    //   6044: iconst_0
    //   6045: wide
    //   6049: wide
    //   6053: astore 5
    //   6055: wide
    //   6059: istore 6
    //   6061: wide
    //   6065: wide
    //   6069: wide
    //   6073: wide
    //   6077: wide
    //   6081: wide
    //   6085: wide
    //   6089: wide
    //   6093: caload
    //   6094: istore 31
    //   6096: iload 6
    //   6098: iconst_5
    //   6099: irem
    //   6100: tableswitch	default:+32 -> 6132, 0:+4562->10662, 1:+4571->10671, 2:+4580->10680, 3:+4589->10689
    //   6133: frem
    //   6134: wide
    //   6138: wide
    //   6142: iload 31
    //   6144: ixor
    //   6145: i2c
    //   6146: wide
    //   6150: wide
    //   6154: wide
    //   6158: wide
    //   6162: castore
    //   6163: iload 6
    //   6165: iconst_1
    //   6166: iadd
    //   6167: wide
    //   6171: wide
    //   6175: ifne +28 -> 6203
    //   6178: aload 5
    //   6180: wide
    //   6184: wide
    //   6188: wide
    //   6192: wide
    //   6196: wide
    //   6200: goto -115 -> 6085
    //   6203: wide
    //   6207: wide
    //   6211: aload 5
    //   6213: wide
    //   6217: wide
    //   6221: wide
    //   6225: if_icmpgt -176 -> 6049
    //   6228: new 43	java/lang/String
    //   6231: dup
    //   6232: wide
    //   6236: invokespecial 53	java/lang/String:<init>	([C)V
    //   6239: invokevirtual 57	java/lang/String:intern	()Ljava/lang/String;
    //   6242: wide
    //   6246: aload_1
    //   6247: wide
    //   6251: wide
    //   6255: aastore
    //   6256: bipush 33
    //   6258: wide
    //   6262: ldc 123
    //   6264: invokevirtual 49	java/lang/String:toCharArray	()[C
    //   6267: wide
    //   6271: wide
    //   6275: arraylength
    //   6276: wide
    //   6280: wide
    //   6284: iconst_1
    //   6285: if_icmpgt +5021 -> 11306
    //   6288: iconst_0
    //   6289: wide
    //   6293: wide
    //   6297: astore 5
    //   6299: wide
    //   6303: istore 6
    //   6305: wide
    //   6309: wide
    //   6313: wide
    //   6317: wide
    //   6321: wide
    //   6325: wide
    //   6329: wide
    //   6333: wide
    //   6337: caload
    //   6338: istore 31
    //   6340: iload 6
    //   6342: iconst_5
    //   6343: irem
    //   6344: tableswitch	default:+32 -> 6376, 0:+4354->10698, 1:+4363->10707, 2:+4372->10716, 3:+4381->10725
    //   6377: frem
    //   6378: wide
    //   6382: wide
    //   6386: iload 31
    //   6388: ixor
    //   6389: i2c
    //   6390: wide
    //   6394: wide
    //   6398: wide
    //   6402: wide
    //   6406: castore
    //   6407: iload 6
    //   6409: iconst_1
    //   6410: iadd
    //   6411: wide
    //   6415: wide
    //   6419: ifne +28 -> 6447
    //   6422: aload 5
    //   6424: wide
    //   6428: wide
    //   6432: wide
    //   6436: wide
    //   6440: wide
    //   6444: goto -115 -> 6329
    //   6447: wide
    //   6451: wide
    //   6455: aload 5
    //   6457: wide
    //   6461: wide
    //   6465: wide
    //   6469: if_icmpgt -176 -> 6293
    //   6472: new 43	java/lang/String
    //   6475: dup
    //   6476: wide
    //   6480: invokespecial 53	java/lang/String:<init>	([C)V
    //   6483: invokevirtual 57	java/lang/String:intern	()Ljava/lang/String;
    //   6486: wide
    //   6490: aload_1
    //   6491: wide
    //   6495: wide
    //   6499: aastore
    //   6500: bipush 34
    //   6502: wide
    //   6506: ldc 125
    //   6508: invokevirtual 49	java/lang/String:toCharArray	()[C
    //   6511: wide
    //   6515: wide
    //   6519: arraylength
    //   6520: wide
    //   6524: wide
    //   6528: iconst_1
    //   6529: if_icmpgt +4769 -> 11298
    //   6532: iconst_0
    //   6533: wide
    //   6537: wide
    //   6541: astore 5
    //   6543: wide
    //   6547: istore 6
    //   6549: wide
    //   6553: wide
    //   6557: wide
    //   6561: wide
    //   6565: wide
    //   6569: wide
    //   6573: wide
    //   6577: wide
    //   6581: caload
    //   6582: istore 31
    //   6584: iload 6
    //   6586: iconst_5
    //   6587: irem
    //   6588: tableswitch	default:+32 -> 6620, 0:+4146->10734, 1:+4155->10743, 2:+4164->10752, 3:+4173->10761
    //   6621: frem
    //   6622: wide
    //   6626: wide
    //   6630: iload 31
    //   6632: ixor
    //   6633: i2c
    //   6634: wide
    //   6638: wide
    //   6642: wide
    //   6646: wide
    //   6650: castore
    //   6651: iload 6
    //   6653: iconst_1
    //   6654: iadd
    //   6655: wide
    //   6659: wide
    //   6663: ifne +28 -> 6691
    //   6666: aload 5
    //   6668: wide
    //   6672: wide
    //   6676: wide
    //   6680: wide
    //   6684: wide
    //   6688: goto -115 -> 6573
    //   6691: wide
    //   6695: wide
    //   6699: aload 5
    //   6701: wide
    //   6705: wide
    //   6709: wide
    //   6713: if_icmpgt -176 -> 6537
    //   6716: new 43	java/lang/String
    //   6719: dup
    //   6720: wide
    //   6724: invokespecial 53	java/lang/String:<init>	([C)V
    //   6727: invokevirtual 57	java/lang/String:intern	()Ljava/lang/String;
    //   6730: wide
    //   6734: aload_1
    //   6735: wide
    //   6739: wide
    //   6743: aastore
    //   6744: bipush 35
    //   6746: wide
    //   6750: ldc 127
    //   6752: invokevirtual 49	java/lang/String:toCharArray	()[C
    //   6755: wide
    //   6759: wide
    //   6763: arraylength
    //   6764: wide
    //   6768: wide
    //   6772: iconst_1
    //   6773: if_icmpgt +4517 -> 11290
    //   6776: iconst_0
    //   6777: wide
    //   6781: wide
    //   6785: astore 5
    //   6787: wide
    //   6791: istore 6
    //   6793: wide
    //   6797: wide
    //   6801: wide
    //   6805: wide
    //   6809: wide
    //   6813: wide
    //   6817: wide
    //   6821: wide
    //   6825: caload
    //   6826: istore 31
    //   6828: iload 6
    //   6830: iconst_5
    //   6831: irem
    //   6832: tableswitch	default:+32 -> 6864, 0:+3938->10770, 1:+3947->10779, 2:+3956->10788, 3:+3965->10797
    //   6865: frem
    //   6866: wide
    //   6870: wide
    //   6874: iload 31
    //   6876: ixor
    //   6877: i2c
    //   6878: wide
    //   6882: wide
    //   6886: wide
    //   6890: wide
    //   6894: castore
    //   6895: iload 6
    //   6897: iconst_1
    //   6898: iadd
    //   6899: wide
    //   6903: wide
    //   6907: ifne +28 -> 6935
    //   6910: aload 5
    //   6912: wide
    //   6916: wide
    //   6920: wide
    //   6924: wide
    //   6928: wide
    //   6932: goto -115 -> 6817
    //   6935: wide
    //   6939: wide
    //   6943: aload 5
    //   6945: wide
    //   6949: wide
    //   6953: wide
    //   6957: if_icmpgt -176 -> 6781
    //   6960: new 43	java/lang/String
    //   6963: dup
    //   6964: wide
    //   6968: invokespecial 53	java/lang/String:<init>	([C)V
    //   6971: invokevirtual 57	java/lang/String:intern	()Ljava/lang/String;
    //   6974: wide
    //   6978: aload_1
    //   6979: wide
    //   6983: wide
    //   6987: aastore
    //   6988: bipush 36
    //   6990: wide
    //   6994: ldc 129
    //   6996: invokevirtual 49	java/lang/String:toCharArray	()[C
    //   6999: wide
    //   7003: wide
    //   7007: arraylength
    //   7008: wide
    //   7012: wide
    //   7016: iconst_1
    //   7017: if_icmpgt +4265 -> 11282
    //   7020: iconst_0
    //   7021: wide
    //   7025: wide
    //   7029: astore 5
    //   7031: wide
    //   7035: istore 6
    //   7037: wide
    //   7041: wide
    //   7045: wide
    //   7049: wide
    //   7053: wide
    //   7057: wide
    //   7061: wide
    //   7065: wide
    //   7069: caload
    //   7070: istore 31
    //   7072: iload 6
    //   7074: iconst_5
    //   7075: irem
    //   7076: tableswitch	default:+32 -> 7108, 0:+3730->10806, 1:+3739->10815, 2:+3748->10824, 3:+3757->10833
    //   7109: frem
    //   7110: wide
    //   7114: wide
    //   7118: iload 31
    //   7120: ixor
    //   7121: i2c
    //   7122: wide
    //   7126: wide
    //   7130: wide
    //   7134: wide
    //   7138: castore
    //   7139: iload 6
    //   7141: iconst_1
    //   7142: iadd
    //   7143: wide
    //   7147: wide
    //   7151: ifne +28 -> 7179
    //   7154: aload 5
    //   7156: wide
    //   7160: wide
    //   7164: wide
    //   7168: wide
    //   7172: wide
    //   7176: goto -115 -> 7061
    //   7179: wide
    //   7183: wide
    //   7187: aload 5
    //   7189: wide
    //   7193: wide
    //   7197: wide
    //   7201: if_icmpgt -176 -> 7025
    //   7204: new 43	java/lang/String
    //   7207: dup
    //   7208: wide
    //   7212: invokespecial 53	java/lang/String:<init>	([C)V
    //   7215: invokevirtual 57	java/lang/String:intern	()Ljava/lang/String;
    //   7218: wide
    //   7222: aload_1
    //   7223: wide
    //   7227: wide
    //   7231: aastore
    //   7232: bipush 37
    //   7234: wide
    //   7238: ldc 131
    //   7240: invokevirtual 49	java/lang/String:toCharArray	()[C
    //   7243: wide
    //   7247: wide
    //   7251: arraylength
    //   7252: wide
    //   7256: wide
    //   7260: iconst_1
    //   7261: if_icmpgt +4013 -> 11274
    //   7264: iconst_0
    //   7265: wide
    //   7269: wide
    //   7273: astore 5
    //   7275: wide
    //   7279: istore 6
    //   7281: wide
    //   7285: wide
    //   7289: wide
    //   7293: wide
    //   7297: wide
    //   7301: wide
    //   7305: wide
    //   7309: wide
    //   7313: caload
    //   7314: istore 31
    //   7316: iload 6
    //   7318: iconst_5
    //   7319: irem
    //   7320: tableswitch	default:+32 -> 7352, 0:+3522->10842, 1:+3531->10851, 2:+3540->10860, 3:+3549->10869
    //   7353: frem
    //   7354: wide
    //   7358: wide
    //   7362: iload 31
    //   7364: ixor
    //   7365: i2c
    //   7366: wide
    //   7370: wide
    //   7374: wide
    //   7378: wide
    //   7382: castore
    //   7383: iload 6
    //   7385: iconst_1
    //   7386: iadd
    //   7387: wide
    //   7391: wide
    //   7395: ifne +28 -> 7423
    //   7398: aload 5
    //   7400: wide
    //   7404: wide
    //   7408: wide
    //   7412: wide
    //   7416: wide
    //   7420: goto -115 -> 7305
    //   7423: wide
    //   7427: wide
    //   7431: aload 5
    //   7433: wide
    //   7437: wide
    //   7441: wide
    //   7445: if_icmpgt -176 -> 7269
    //   7448: new 43	java/lang/String
    //   7451: dup
    //   7452: wide
    //   7456: invokespecial 53	java/lang/String:<init>	([C)V
    //   7459: invokevirtual 57	java/lang/String:intern	()Ljava/lang/String;
    //   7462: wide
    //   7466: aload_1
    //   7467: wide
    //   7471: wide
    //   7475: aastore
    //   7476: bipush 38
    //   7478: wide
    //   7482: ldc 133
    //   7484: invokevirtual 49	java/lang/String:toCharArray	()[C
    //   7487: wide
    //   7491: wide
    //   7495: arraylength
    //   7496: wide
    //   7500: wide
    //   7504: iconst_1
    //   7505: if_icmpgt +3761 -> 11266
    //   7508: iconst_0
    //   7509: wide
    //   7513: wide
    //   7517: astore 5
    //   7519: wide
    //   7523: istore 6
    //   7525: wide
    //   7529: wide
    //   7533: wide
    //   7537: wide
    //   7541: wide
    //   7545: wide
    //   7549: wide
    //   7553: wide
    //   7557: caload
    //   7558: istore 31
    //   7560: iload 6
    //   7562: iconst_5
    //   7563: irem
    //   7564: tableswitch	default:+32 -> 7596, 0:+3314->10878, 1:+3323->10887, 2:+3332->10896, 3:+3341->10905
    //   7597: frem
    //   7598: wide
    //   7602: wide
    //   7606: iload 31
    //   7608: ixor
    //   7609: i2c
    //   7610: wide
    //   7614: wide
    //   7618: wide
    //   7622: wide
    //   7626: castore
    //   7627: iload 6
    //   7629: iconst_1
    //   7630: iadd
    //   7631: wide
    //   7635: wide
    //   7639: ifne +28 -> 7667
    //   7642: aload 5
    //   7644: wide
    //   7648: wide
    //   7652: wide
    //   7656: wide
    //   7660: wide
    //   7664: goto -115 -> 7549
    //   7667: wide
    //   7671: wide
    //   7675: aload 5
    //   7677: wide
    //   7681: wide
    //   7685: wide
    //   7689: if_icmpgt -176 -> 7513
    //   7692: new 43	java/lang/String
    //   7695: dup
    //   7696: wide
    //   7700: invokespecial 53	java/lang/String:<init>	([C)V
    //   7703: invokevirtual 57	java/lang/String:intern	()Ljava/lang/String;
    //   7706: wide
    //   7710: aload_1
    //   7711: wide
    //   7715: wide
    //   7719: aastore
    //   7720: bipush 39
    //   7722: wide
    //   7726: ldc 135
    //   7728: invokevirtual 49	java/lang/String:toCharArray	()[C
    //   7731: wide
    //   7735: wide
    //   7739: arraylength
    //   7740: wide
    //   7744: wide
    //   7748: iconst_1
    //   7749: if_icmpgt +3509 -> 11258
    //   7752: iconst_0
    //   7753: wide
    //   7757: wide
    //   7761: astore 5
    //   7763: wide
    //   7767: istore 6
    //   7769: wide
    //   7773: wide
    //   7777: wide
    //   7781: wide
    //   7785: wide
    //   7789: wide
    //   7793: wide
    //   7797: wide
    //   7801: caload
    //   7802: istore 31
    //   7804: iload 6
    //   7806: iconst_5
    //   7807: irem
    //   7808: tableswitch	default:+32 -> 7840, 0:+3106->10914, 1:+3115->10923, 2:+3124->10932, 3:+3133->10941
    //   7841: frem
    //   7842: wide
    //   7846: wide
    //   7850: iload 31
    //   7852: ixor
    //   7853: i2c
    //   7854: wide
    //   7858: wide
    //   7862: wide
    //   7866: wide
    //   7870: castore
    //   7871: iload 6
    //   7873: iconst_1
    //   7874: iadd
    //   7875: wide
    //   7879: wide
    //   7883: ifne +28 -> 7911
    //   7886: aload 5
    //   7888: wide
    //   7892: wide
    //   7896: wide
    //   7900: wide
    //   7904: wide
    //   7908: goto -115 -> 7793
    //   7911: wide
    //   7915: wide
    //   7919: aload 5
    //   7921: wide
    //   7925: wide
    //   7929: wide
    //   7933: if_icmpgt -176 -> 7757
    //   7936: new 43	java/lang/String
    //   7939: dup
    //   7940: wide
    //   7944: invokespecial 53	java/lang/String:<init>	([C)V
    //   7947: invokevirtual 57	java/lang/String:intern	()Ljava/lang/String;
    //   7950: wide
    //   7954: aload_1
    //   7955: wide
    //   7959: wide
    //   7963: aastore
    //   7964: bipush 40
    //   7966: wide
    //   7970: ldc 137
    //   7972: invokevirtual 49	java/lang/String:toCharArray	()[C
    //   7975: wide
    //   7979: wide
    //   7983: arraylength
    //   7984: wide
    //   7988: wide
    //   7992: iconst_1
    //   7993: if_icmpgt +3257 -> 11250
    //   7996: iconst_0
    //   7997: wide
    //   8001: wide
    //   8005: astore 5
    //   8007: wide
    //   8011: istore 6
    //   8013: wide
    //   8017: wide
    //   8021: wide
    //   8025: wide
    //   8029: wide
    //   8033: wide
    //   8037: wide
    //   8041: wide
    //   8045: caload
    //   8046: istore 31
    //   8048: iload 6
    //   8050: iconst_5
    //   8051: irem
    //   8052: tableswitch	default:+32 -> 8084, 0:+2898->10950, 1:+2907->10959, 2:+2916->10968, 3:+2925->10977
    //   8085: frem
    //   8086: wide
    //   8090: wide
    //   8094: iload 31
    //   8096: ixor
    //   8097: i2c
    //   8098: wide
    //   8102: wide
    //   8106: wide
    //   8110: wide
    //   8114: castore
    //   8115: iload 6
    //   8117: iconst_1
    //   8118: iadd
    //   8119: wide
    //   8123: wide
    //   8127: ifne +28 -> 8155
    //   8130: aload 5
    //   8132: wide
    //   8136: wide
    //   8140: wide
    //   8144: wide
    //   8148: wide
    //   8152: goto -115 -> 8037
    //   8155: wide
    //   8159: wide
    //   8163: aload 5
    //   8165: wide
    //   8169: wide
    //   8173: wide
    //   8177: if_icmpgt -176 -> 8001
    //   8180: new 43	java/lang/String
    //   8183: dup
    //   8184: wide
    //   8188: invokespecial 53	java/lang/String:<init>	([C)V
    //   8191: invokevirtual 57	java/lang/String:intern	()Ljava/lang/String;
    //   8194: wide
    //   8198: aload_1
    //   8199: wide
    //   8203: wide
    //   8207: aastore
    //   8208: bipush 41
    //   8210: wide
    //   8214: ldc 139
    //   8216: invokevirtual 49	java/lang/String:toCharArray	()[C
    //   8219: wide
    //   8223: wide
    //   8227: arraylength
    //   8228: wide
    //   8232: wide
    //   8236: iconst_1
    //   8237: if_icmpgt +3005 -> 11242
    //   8240: iconst_0
    //   8241: wide
    //   8245: wide
    //   8249: astore 5
    //   8251: wide
    //   8255: istore 6
    //   8257: wide
    //   8261: wide
    //   8265: wide
    //   8269: wide
    //   8273: wide
    //   8277: wide
    //   8281: wide
    //   8285: wide
    //   8289: caload
    //   8290: istore 31
    //   8292: iload 6
    //   8294: iconst_5
    //   8295: irem
    //   8296: tableswitch	default:+32 -> 8328, 0:+2690->10986, 1:+2699->10995, 2:+2708->11004, 3:+2717->11013
    //   8329: frem
    //   8330: wide
    //   8334: wide
    //   8338: iload 31
    //   8340: ixor
    //   8341: i2c
    //   8342: wide
    //   8346: wide
    //   8350: wide
    //   8354: wide
    //   8358: castore
    //   8359: iload 6
    //   8361: iconst_1
    //   8362: iadd
    //   8363: wide
    //   8367: wide
    //   8371: ifne +28 -> 8399
    //   8374: aload 5
    //   8376: wide
    //   8380: wide
    //   8384: wide
    //   8388: wide
    //   8392: wide
    //   8396: goto -115 -> 8281
    //   8399: wide
    //   8403: wide
    //   8407: aload 5
    //   8409: wide
    //   8413: wide
    //   8417: wide
    //   8421: if_icmpgt -176 -> 8245
    //   8424: new 43	java/lang/String
    //   8427: dup
    //   8428: wide
    //   8432: invokespecial 53	java/lang/String:<init>	([C)V
    //   8435: invokevirtual 57	java/lang/String:intern	()Ljava/lang/String;
    //   8438: wide
    //   8442: aload_1
    //   8443: wide
    //   8447: wide
    //   8451: aastore
    //   8452: bipush 42
    //   8454: wide
    //   8458: ldc 141
    //   8460: invokevirtual 49	java/lang/String:toCharArray	()[C
    //   8463: wide
    //   8467: wide
    //   8471: arraylength
    //   8472: wide
    //   8476: wide
    //   8480: iconst_1
    //   8481: if_icmpgt +2753 -> 11234
    //   8484: iconst_0
    //   8485: wide
    //   8489: wide
    //   8493: astore 5
    //   8495: wide
    //   8499: istore 6
    //   8501: wide
    //   8505: wide
    //   8509: wide
    //   8513: wide
    //   8517: wide
    //   8521: wide
    //   8525: wide
    //   8529: wide
    //   8533: caload
    //   8534: istore 31
    //   8536: iload 6
    //   8538: iconst_5
    //   8539: irem
    //   8540: tableswitch	default:+32 -> 8572, 0:+2482->11022, 1:+2491->11031, 2:+2500->11040, 3:+2509->11049
    //   8573: frem
    //   8574: wide
    //   8578: wide
    //   8582: iload 31
    //   8584: ixor
    //   8585: i2c
    //   8586: wide
    //   8590: wide
    //   8594: wide
    //   8598: wide
    //   8602: castore
    //   8603: iload 6
    //   8605: iconst_1
    //   8606: iadd
    //   8607: wide
    //   8611: wide
    //   8615: ifne +28 -> 8643
    //   8618: aload 5
    //   8620: wide
    //   8624: wide
    //   8628: wide
    //   8632: wide
    //   8636: wide
    //   8640: goto -115 -> 8525
    //   8643: wide
    //   8647: wide
    //   8651: aload 5
    //   8653: wide
    //   8657: wide
    //   8661: wide
    //   8665: if_icmpgt -176 -> 8489
    //   8668: new 43	java/lang/String
    //   8671: dup
    //   8672: wide
    //   8676: invokespecial 53	java/lang/String:<init>	([C)V
    //   8679: invokevirtual 57	java/lang/String:intern	()Ljava/lang/String;
    //   8682: wide
    //   8686: aload_1
    //   8687: wide
    //   8691: wide
    //   8695: aastore
    //   8696: bipush 43
    //   8698: wide
    //   8702: ldc 143
    //   8704: invokevirtual 49	java/lang/String:toCharArray	()[C
    //   8707: wide
    //   8711: wide
    //   8715: arraylength
    //   8716: wide
    //   8720: wide
    //   8724: iconst_1
    //   8725: if_icmpgt +2501 -> 11226
    //   8728: iconst_0
    //   8729: wide
    //   8733: wide
    //   8737: astore 5
    //   8739: wide
    //   8743: istore 6
    //   8745: wide
    //   8749: wide
    //   8753: wide
    //   8757: wide
    //   8761: wide
    //   8765: wide
    //   8769: wide
    //   8773: wide
    //   8777: caload
    //   8778: istore 31
    //   8780: iload 6
    //   8782: iconst_5
    //   8783: irem
    //   8784: tableswitch	default:+32 -> 8816, 0:+2274->11058, 1:+2283->11067, 2:+2292->11076, 3:+2301->11085
    //   8817: frem
    //   8818: wide
    //   8822: wide
    //   8826: iload 31
    //   8828: ixor
    //   8829: i2c
    //   8830: wide
    //   8834: wide
    //   8838: wide
    //   8842: wide
    //   8846: castore
    //   8847: iload 6
    //   8849: iconst_1
    //   8850: iadd
    //   8851: wide
    //   8855: wide
    //   8859: ifne +28 -> 8887
    //   8862: aload 5
    //   8864: wide
    //   8868: wide
    //   8872: wide
    //   8876: wide
    //   8880: wide
    //   8884: goto -115 -> 8769
    //   8887: wide
    //   8891: wide
    //   8895: aload 5
    //   8897: wide
    //   8901: wide
    //   8905: wide
    //   8909: if_icmpgt -176 -> 8733
    //   8912: new 43	java/lang/String
    //   8915: dup
    //   8916: wide
    //   8920: invokespecial 53	java/lang/String:<init>	([C)V
    //   8923: invokevirtual 57	java/lang/String:intern	()Ljava/lang/String;
    //   8926: wide
    //   8930: aload_1
    //   8931: wide
    //   8935: wide
    //   8939: aastore
    //   8940: bipush 44
    //   8942: wide
    //   8946: ldc 145
    //   8948: invokevirtual 49	java/lang/String:toCharArray	()[C
    //   8951: wide
    //   8955: wide
    //   8959: arraylength
    //   8960: wide
    //   8964: wide
    //   8968: iconst_1
    //   8969: if_icmpgt +2249 -> 11218
    //   8972: iconst_0
    //   8973: wide
    //   8977: wide
    //   8981: astore 5
    //   8983: wide
    //   8987: istore 6
    //   8989: wide
    //   8993: wide
    //   8997: wide
    //   9001: wide
    //   9005: wide
    //   9009: wide
    //   9013: wide
    //   9017: wide
    //   9021: caload
    //   9022: istore 31
    //   9024: iload 6
    //   9026: iconst_5
    //   9027: irem
    //   9028: tableswitch	default:+32 -> 9060, 0:+2066->11094, 1:+2075->11103, 2:+2084->11112, 3:+2093->11121
    //   9061: frem
    //   9062: wide
    //   9066: wide
    //   9070: iload 31
    //   9072: ixor
    //   9073: i2c
    //   9074: wide
    //   9078: wide
    //   9082: wide
    //   9086: wide
    //   9090: castore
    //   9091: iload 6
    //   9093: iconst_1
    //   9094: iadd
    //   9095: wide
    //   9099: wide
    //   9103: ifne +28 -> 9131
    //   9106: aload 5
    //   9108: wide
    //   9112: wide
    //   9116: wide
    //   9120: wide
    //   9124: wide
    //   9128: goto -115 -> 9013
    //   9131: wide
    //   9135: wide
    //   9139: aload 5
    //   9141: wide
    //   9145: wide
    //   9149: wide
    //   9153: if_icmpgt -176 -> 8977
    //   9156: new 43	java/lang/String
    //   9159: dup
    //   9160: wide
    //   9164: invokespecial 53	java/lang/String:<init>	([C)V
    //   9167: invokevirtual 57	java/lang/String:intern	()Ljava/lang/String;
    //   9170: wide
    //   9174: aload_1
    //   9175: wide
    //   9179: wide
    //   9183: aastore
    //   9184: bipush 45
    //   9186: wide
    //   9190: ldc 147
    //   9192: invokevirtual 49	java/lang/String:toCharArray	()[C
    //   9195: wide
    //   9199: wide
    //   9203: arraylength
    //   9204: wide
    //   9208: wide
    //   9212: iconst_1
    //   9213: if_icmpgt +1997 -> 11210
    //   9216: iconst_0
    //   9217: wide
    //   9221: wide
    //   9225: astore 5
    //   9227: wide
    //   9231: istore 6
    //   9233: wide
    //   9237: wide
    //   9241: wide
    //   9245: wide
    //   9249: wide
    //   9253: wide
    //   9257: wide
    //   9261: wide
    //   9265: caload
    //   9266: istore 31
    //   9268: iload 6
    //   9270: iconst_5
    //   9271: irem
    //   9272: tableswitch	default:+32 -> 9304, 0:+1858->11130, 1:+1867->11139, 2:+1876->11148, 3:+1885->11157
    //   9305: frem
    //   9306: wide
    //   9310: wide
    //   9314: iload 31
    //   9316: ixor
    //   9317: i2c
    //   9318: wide
    //   9322: wide
    //   9326: wide
    //   9330: wide
    //   9334: castore
    //   9335: iload 6
    //   9337: iconst_1
    //   9338: iadd
    //   9339: wide
    //   9343: wide
    //   9347: ifne +28 -> 9375
    //   9350: aload 5
    //   9352: wide
    //   9356: wide
    //   9360: wide
    //   9364: wide
    //   9368: wide
    //   9372: goto -115 -> 9257
    //   9375: wide
    //   9379: wide
    //   9383: aload 5
    //   9385: wide
    //   9389: wide
    //   9393: wide
    //   9397: if_icmpgt -176 -> 9221
    //   9400: new 43	java/lang/String
    //   9403: dup
    //   9404: wide
    //   9408: invokespecial 53	java/lang/String:<init>	([C)V
    //   9411: invokevirtual 57	java/lang/String:intern	()Ljava/lang/String;
    //   9414: wide
    //   9418: aload_1
    //   9419: wide
    //   9423: wide
    //   9427: aastore
    //   9428: bipush 46
    //   9430: wide
    //   9434: ldc 149
    //   9436: invokevirtual 49	java/lang/String:toCharArray	()[C
    //   9439: wide
    //   9443: wide
    //   9447: arraylength
    //   9448: wide
    //   9452: wide
    //   9456: iconst_1
    //   9457: if_icmpgt +1745 -> 11202
    //   9460: iconst_0
    //   9461: wide
    //   9465: wide
    //   9469: astore 5
    //   9471: wide
    //   9475: istore 6
    //   9477: wide
    //   9481: wide
    //   9485: wide
    //   9489: wide
    //   9493: wide
    //   9497: wide
    //   9501: wide
    //   9505: wide
    //   9509: caload
    //   9510: istore 31
    //   9512: iload 6
    //   9514: iconst_5
    //   9515: irem
    //   9516: tableswitch	default:+32 -> 9548, 0:+1650->11166, 1:+1659->11175, 2:+1668->11184, 3:+1677->11193
    //   9549: frem
    //   9550: wide
    //   9554: wide
    //   9558: iload 31
    //   9560: ixor
    //   9561: i2c
    //   9562: wide
    //   9566: wide
    //   9570: wide
    //   9574: wide
    //   9578: castore
    //   9579: iload 6
    //   9581: iconst_1
    //   9582: iadd
    //   9583: wide
    //   9587: wide
    //   9591: ifne +28 -> 9619
    //   9594: aload 5
    //   9596: wide
    //   9600: wide
    //   9604: wide
    //   9608: wide
    //   9612: wide
    //   9616: goto -115 -> 9501
    //   9619: wide
    //   9623: wide
    //   9627: aload 5
    //   9629: wide
    //   9633: wide
    //   9637: wide
    //   9641: if_icmpgt -176 -> 9465
    //   9644: new 43	java/lang/String
    //   9647: dup
    //   9648: wide
    //   9652: invokespecial 53	java/lang/String:<init>	([C)V
    //   9655: invokevirtual 57	java/lang/String:intern	()Ljava/lang/String;
    //   9658: wide
    //   9662: aload_1
    //   9663: wide
    //   9667: wide
    //   9671: aastore
    //   9672: aload_1
    //   9673: putstatic 151	com/skyhookwireless/wps/_sdko:z	[Ljava/lang/String;
    //   9676: ldc 153
    //   9678: invokevirtual 159	java/lang/Class:desiredAssertionStatus	()Z
    //   9681: ifne +8 -> 9689
    //   9684: iload_0
    //   9685: putstatic 161	com/skyhookwireless/wps/_sdko:_sdko	Z
    //   9688: return
    //   9689: iconst_0
    //   9690: istore_0
    //   9691: goto -7 -> 9684
    //   9694: bipush 25
    //   9696: istore 11
    //   9698: goto -9610 -> 88
    //   9701: bipush 103
    //   9703: istore 11
    //   9705: goto -9617 -> 88
    //   9708: bipush 9
    //   9710: istore 11
    //   9712: goto -9624 -> 88
    //   9715: bipush 98
    //   9717: istore 11
    //   9719: goto -9631 -> 88
    //   9722: bipush 25
    //   9724: istore 20
    //   9726: goto -9482 -> 244
    //   9729: bipush 103
    //   9731: istore 20
    //   9733: goto -9489 -> 244
    //   9736: bipush 9
    //   9738: istore 20
    //   9740: goto -9496 -> 244
    //   9743: bipush 98
    //   9745: istore 20
    //   9747: goto -9503 -> 244
    //   9750: bipush 25
    //   9752: istore 32
    //   9754: goto -9346 -> 408
    //   9757: bipush 103
    //   9759: istore 32
    //   9761: goto -9353 -> 408
    //   9764: bipush 9
    //   9766: istore 32
    //   9768: goto -9360 -> 408
    //   9771: bipush 98
    //   9773: istore 32
    //   9775: goto -9367 -> 408
    //   9778: bipush 25
    //   9780: istore 43
    //   9782: goto -9210 -> 572
    //   9785: bipush 103
    //   9787: istore 43
    //   9789: goto -9217 -> 572
    //   9792: bipush 9
    //   9794: istore 43
    //   9796: goto -9224 -> 572
    //   9799: bipush 98
    //   9801: istore 43
    //   9803: goto -9231 -> 572
    //   9806: bipush 25
    //   9808: istore 54
    //   9810: goto -9074 -> 736
    //   9813: bipush 103
    //   9815: istore 54
    //   9817: goto -9081 -> 736
    //   9820: bipush 9
    //   9822: istore 54
    //   9824: goto -9088 -> 736
    //   9827: bipush 98
    //   9829: istore 54
    //   9831: goto -9095 -> 736
    //   9834: bipush 25
    //   9836: istore 65
    //   9838: goto -8938 -> 900
    //   9841: bipush 103
    //   9843: istore 65
    //   9845: goto -8945 -> 900
    //   9848: bipush 9
    //   9850: istore 65
    //   9852: goto -8952 -> 900
    //   9855: bipush 98
    //   9857: istore 65
    //   9859: goto -8959 -> 900
    //   9862: bipush 25
    //   9864: istore 76
    //   9866: goto -8798 -> 1068
    //   9869: bipush 103
    //   9871: istore 76
    //   9873: goto -8805 -> 1068
    //   9876: bipush 9
    //   9878: istore 76
    //   9880: goto -8812 -> 1068
    //   9883: bipush 98
    //   9885: istore 76
    //   9887: goto -8819 -> 1068
    //   9890: bipush 25
    //   9892: istore 87
    //   9894: goto -8658 -> 1236
    //   9897: bipush 103
    //   9899: istore 87
    //   9901: goto -8665 -> 1236
    //   9904: bipush 9
    //   9906: istore 87
    //   9908: goto -8672 -> 1236
    //   9911: bipush 98
    //   9913: istore 87
    //   9915: goto -8679 -> 1236
    //   9918: bipush 25
    //   9920: istore 98
    //   9922: goto -8518 -> 1404
    //   9925: bipush 103
    //   9927: istore 98
    //   9929: goto -8525 -> 1404
    //   9932: bipush 9
    //   9934: istore 98
    //   9936: goto -8532 -> 1404
    //   9939: bipush 98
    //   9941: istore 98
    //   9943: goto -8539 -> 1404
    //   9946: bipush 25
    //   9948: istore 108
    //   9950: goto -8382 -> 1568
    //   9953: bipush 103
    //   9955: istore 108
    //   9957: goto -8389 -> 1568
    //   9960: bipush 9
    //   9962: istore 108
    //   9964: goto -8396 -> 1568
    //   9967: bipush 98
    //   9969: istore 108
    //   9971: goto -8403 -> 1568
    //   9974: bipush 25
    //   9976: istore 119
    //   9978: goto -8242 -> 1736
    //   9981: bipush 103
    //   9983: istore 119
    //   9985: goto -8249 -> 1736
    //   9988: bipush 9
    //   9990: istore 119
    //   9992: goto -8256 -> 1736
    //   9995: bipush 98
    //   9997: istore 119
    //   9999: goto -8263 -> 1736
    //   10002: bipush 25
    //   10004: istore 130
    //   10006: goto -8102 -> 1904
    //   10009: bipush 103
    //   10011: istore 130
    //   10013: goto -8109 -> 1904
    //   10016: bipush 9
    //   10018: istore 130
    //   10020: goto -8116 -> 1904
    //   10023: bipush 98
    //   10025: istore 130
    //   10027: goto -8123 -> 1904
    //   10030: bipush 25
    //   10032: istore 141
    //   10034: goto -7962 -> 2072
    //   10037: bipush 103
    //   10039: istore 141
    //   10041: goto -7969 -> 2072
    //   10044: bipush 9
    //   10046: istore 141
    //   10048: goto -7976 -> 2072
    //   10051: bipush 98
    //   10053: istore 141
    //   10055: goto -7983 -> 2072
    //   10058: bipush 25
    //   10060: istore 152
    //   10062: goto -7822 -> 2240
    //   10065: bipush 103
    //   10067: istore 152
    //   10069: goto -7829 -> 2240
    //   10072: bipush 9
    //   10074: istore 152
    //   10076: goto -7836 -> 2240
    //   10079: bipush 98
    //   10081: istore 152
    //   10083: goto -7843 -> 2240
    //   10086: bipush 25
    //   10088: istore 163
    //   10090: goto -7682 -> 2408
    //   10093: bipush 103
    //   10095: istore 163
    //   10097: goto -7689 -> 2408
    //   10100: bipush 9
    //   10102: istore 163
    //   10104: goto -7696 -> 2408
    //   10107: bipush 98
    //   10109: istore 163
    //   10111: goto -7703 -> 2408
    //   10114: bipush 25
    //   10116: istore 174
    //   10118: goto -7542 -> 2576
    //   10121: bipush 103
    //   10123: istore 174
    //   10125: goto -7549 -> 2576
    //   10128: bipush 9
    //   10130: istore 174
    //   10132: goto -7556 -> 2576
    //   10135: bipush 98
    //   10137: istore 174
    //   10139: goto -7563 -> 2576
    //   10142: bipush 25
    //   10144: istore 185
    //   10146: goto -7402 -> 2744
    //   10149: bipush 103
    //   10151: istore 185
    //   10153: goto -7409 -> 2744
    //   10156: bipush 9
    //   10158: istore 185
    //   10160: goto -7416 -> 2744
    //   10163: bipush 98
    //   10165: istore 185
    //   10167: goto -7423 -> 2744
    //   10170: bipush 25
    //   10172: istore 196
    //   10174: goto -7262 -> 2912
    //   10177: bipush 103
    //   10179: istore 196
    //   10181: goto -7269 -> 2912
    //   10184: bipush 9
    //   10186: istore 196
    //   10188: goto -7276 -> 2912
    //   10191: bipush 98
    //   10193: istore 196
    //   10195: goto -7283 -> 2912
    //   10198: bipush 25
    //   10200: istore 207
    //   10202: goto -7122 -> 3080
    //   10205: bipush 103
    //   10207: istore 207
    //   10209: goto -7129 -> 3080
    //   10212: bipush 9
    //   10214: istore 207
    //   10216: goto -7136 -> 3080
    //   10219: bipush 98
    //   10221: istore 207
    //   10223: goto -7143 -> 3080
    //   10226: bipush 25
    //   10228: istore 218
    //   10230: goto -6982 -> 3248
    //   10233: bipush 103
    //   10235: istore 218
    //   10237: goto -6989 -> 3248
    //   10240: bipush 9
    //   10242: istore 218
    //   10244: goto -6996 -> 3248
    //   10247: bipush 98
    //   10249: istore 218
    //   10251: goto -7003 -> 3248
    //   10254: bipush 25
    //   10256: istore 229
    //   10258: goto -6842 -> 3416
    //   10261: bipush 103
    //   10263: istore 229
    //   10265: goto -6849 -> 3416
    //   10268: bipush 9
    //   10270: istore 229
    //   10272: goto -6856 -> 3416
    //   10275: bipush 98
    //   10277: istore 229
    //   10279: goto -6863 -> 3416
    //   10282: bipush 25
    //   10284: istore 240
    //   10286: goto -6702 -> 3584
    //   10289: bipush 103
    //   10291: istore 240
    //   10293: goto -6709 -> 3584
    //   10296: bipush 9
    //   10298: istore 240
    //   10300: goto -6716 -> 3584
    //   10303: bipush 98
    //   10305: istore 240
    //   10307: goto -6723 -> 3584
    //   10310: bipush 25
    //   10312: istore 251
    //   10314: goto -6562 -> 3752
    //   10317: bipush 103
    //   10319: istore 251
    //   10321: goto -6569 -> 3752
    //   10324: bipush 9
    //   10326: istore 251
    //   10328: goto -6576 -> 3752
    //   10331: bipush 98
    //   10333: istore 251
    //   10335: goto -6583 -> 3752
    //   10338: bipush 25
    //   10340: wide
    //   10344: goto -6394 -> 3950
    //   10347: bipush 103
    //   10349: wide
    //   10353: goto -6403 -> 3950
    //   10356: bipush 9
    //   10358: wide
    //   10362: goto -6412 -> 3950
    //   10365: bipush 98
    //   10367: wide
    //   10371: goto -6421 -> 3950
    //   10374: bipush 25
    //   10376: wide
    //   10380: goto -6190 -> 4190
    //   10383: bipush 103
    //   10385: wide
    //   10389: goto -6199 -> 4190
    //   10392: bipush 9
    //   10394: wide
    //   10398: goto -6208 -> 4190
    //   10401: bipush 98
    //   10403: wide
    //   10407: goto -6217 -> 4190
    //   10410: bipush 25
    //   10412: wide
    //   10416: goto -5986 -> 4430
    //   10419: bipush 103
    //   10421: wide
    //   10425: goto -5995 -> 4430
    //   10428: bipush 9
    //   10430: wide
    //   10434: goto -6004 -> 4430
    //   10437: bipush 98
    //   10439: wide
    //   10443: goto -6013 -> 4430
    //   10446: bipush 25
    //   10448: wide
    //   10452: goto -5778 -> 4674
    //   10455: bipush 103
    //   10457: wide
    //   10461: goto -5787 -> 4674
    //   10464: bipush 9
    //   10466: wide
    //   10470: goto -5796 -> 4674
    //   10473: bipush 98
    //   10475: wide
    //   10479: goto -5805 -> 4674
    //   10482: bipush 25
    //   10484: wide
    //   10488: goto -5570 -> 4918
    //   10491: bipush 103
    //   10493: wide
    //   10497: goto -5579 -> 4918
    //   10500: bipush 9
    //   10502: wide
    //   10506: goto -5588 -> 4918
    //   10509: bipush 98
    //   10511: wide
    //   10515: goto -5597 -> 4918
    //   10518: bipush 25
    //   10520: wide
    //   10524: goto -5362 -> 5162
    //   10527: bipush 103
    //   10529: wide
    //   10533: goto -5371 -> 5162
    //   10536: bipush 9
    //   10538: wide
    //   10542: goto -5380 -> 5162
    //   10545: bipush 98
    //   10547: wide
    //   10551: goto -5389 -> 5162
    //   10554: bipush 25
    //   10556: wide
    //   10560: goto -5154 -> 5406
    //   10563: bipush 103
    //   10565: wide
    //   10569: goto -5163 -> 5406
    //   10572: bipush 9
    //   10574: wide
    //   10578: goto -5172 -> 5406
    //   10581: bipush 98
    //   10583: wide
    //   10587: goto -5181 -> 5406
    //   10590: bipush 25
    //   10592: wide
    //   10596: goto -4946 -> 5650
    //   10599: bipush 103
    //   10601: wide
    //   10605: goto -4955 -> 5650
    //   10608: bipush 9
    //   10610: wide
    //   10614: goto -4964 -> 5650
    //   10617: bipush 98
    //   10619: wide
    //   10623: goto -4973 -> 5650
    //   10626: bipush 25
    //   10628: wide
    //   10632: goto -4738 -> 5894
    //   10635: bipush 103
    //   10637: wide
    //   10641: goto -4747 -> 5894
    //   10644: bipush 9
    //   10646: wide
    //   10650: goto -4756 -> 5894
    //   10653: bipush 98
    //   10655: wide
    //   10659: goto -4765 -> 5894
    //   10662: bipush 25
    //   10664: wide
    //   10668: goto -4530 -> 6138
    //   10671: bipush 103
    //   10673: wide
    //   10677: goto -4539 -> 6138
    //   10680: bipush 9
    //   10682: wide
    //   10686: goto -4548 -> 6138
    //   10689: bipush 98
    //   10691: wide
    //   10695: goto -4557 -> 6138
    //   10698: bipush 25
    //   10700: wide
    //   10704: goto -4322 -> 6382
    //   10707: bipush 103
    //   10709: wide
    //   10713: goto -4331 -> 6382
    //   10716: bipush 9
    //   10718: wide
    //   10722: goto -4340 -> 6382
    //   10725: bipush 98
    //   10727: wide
    //   10731: goto -4349 -> 6382
    //   10734: bipush 25
    //   10736: wide
    //   10740: goto -4114 -> 6626
    //   10743: bipush 103
    //   10745: wide
    //   10749: goto -4123 -> 6626
    //   10752: bipush 9
    //   10754: wide
    //   10758: goto -4132 -> 6626
    //   10761: bipush 98
    //   10763: wide
    //   10767: goto -4141 -> 6626
    //   10770: bipush 25
    //   10772: wide
    //   10776: goto -3906 -> 6870
    //   10779: bipush 103
    //   10781: wide
    //   10785: goto -3915 -> 6870
    //   10788: bipush 9
    //   10790: wide
    //   10794: goto -3924 -> 6870
    //   10797: bipush 98
    //   10799: wide
    //   10803: goto -3933 -> 6870
    //   10806: bipush 25
    //   10808: wide
    //   10812: goto -3698 -> 7114
    //   10815: bipush 103
    //   10817: wide
    //   10821: goto -3707 -> 7114
    //   10824: bipush 9
    //   10826: wide
    //   10830: goto -3716 -> 7114
    //   10833: bipush 98
    //   10835: wide
    //   10839: goto -3725 -> 7114
    //   10842: bipush 25
    //   10844: wide
    //   10848: goto -3490 -> 7358
    //   10851: bipush 103
    //   10853: wide
    //   10857: goto -3499 -> 7358
    //   10860: bipush 9
    //   10862: wide
    //   10866: goto -3508 -> 7358
    //   10869: bipush 98
    //   10871: wide
    //   10875: goto -3517 -> 7358
    //   10878: bipush 25
    //   10880: wide
    //   10884: goto -3282 -> 7602
    //   10887: bipush 103
    //   10889: wide
    //   10893: goto -3291 -> 7602
    //   10896: bipush 9
    //   10898: wide
    //   10902: goto -3300 -> 7602
    //   10905: bipush 98
    //   10907: wide
    //   10911: goto -3309 -> 7602
    //   10914: bipush 25
    //   10916: wide
    //   10920: goto -3074 -> 7846
    //   10923: bipush 103
    //   10925: wide
    //   10929: goto -3083 -> 7846
    //   10932: bipush 9
    //   10934: wide
    //   10938: goto -3092 -> 7846
    //   10941: bipush 98
    //   10943: wide
    //   10947: goto -3101 -> 7846
    //   10950: bipush 25
    //   10952: wide
    //   10956: goto -2866 -> 8090
    //   10959: bipush 103
    //   10961: wide
    //   10965: goto -2875 -> 8090
    //   10968: bipush 9
    //   10970: wide
    //   10974: goto -2884 -> 8090
    //   10977: bipush 98
    //   10979: wide
    //   10983: goto -2893 -> 8090
    //   10986: bipush 25
    //   10988: wide
    //   10992: goto -2658 -> 8334
    //   10995: bipush 103
    //   10997: wide
    //   11001: goto -2667 -> 8334
    //   11004: bipush 9
    //   11006: wide
    //   11010: goto -2676 -> 8334
    //   11013: bipush 98
    //   11015: wide
    //   11019: goto -2685 -> 8334
    //   11022: bipush 25
    //   11024: wide
    //   11028: goto -2450 -> 8578
    //   11031: bipush 103
    //   11033: wide
    //   11037: goto -2459 -> 8578
    //   11040: bipush 9
    //   11042: wide
    //   11046: goto -2468 -> 8578
    //   11049: bipush 98
    //   11051: wide
    //   11055: goto -2477 -> 8578
    //   11058: bipush 25
    //   11060: wide
    //   11064: goto -2242 -> 8822
    //   11067: bipush 103
    //   11069: wide
    //   11073: goto -2251 -> 8822
    //   11076: bipush 9
    //   11078: wide
    //   11082: goto -2260 -> 8822
    //   11085: bipush 98
    //   11087: wide
    //   11091: goto -2269 -> 8822
    //   11094: bipush 25
    //   11096: wide
    //   11100: goto -2034 -> 9066
    //   11103: bipush 103
    //   11105: wide
    //   11109: goto -2043 -> 9066
    //   11112: bipush 9
    //   11114: wide
    //   11118: goto -2052 -> 9066
    //   11121: bipush 98
    //   11123: wide
    //   11127: goto -2061 -> 9066
    //   11130: bipush 25
    //   11132: wide
    //   11136: goto -1826 -> 9310
    //   11139: bipush 103
    //   11141: wide
    //   11145: goto -1835 -> 9310
    //   11148: bipush 9
    //   11150: wide
    //   11154: goto -1844 -> 9310
    //   11157: bipush 98
    //   11159: wide
    //   11163: goto -1853 -> 9310
    //   11166: bipush 25
    //   11168: wide
    //   11172: goto -1618 -> 9554
    //   11175: bipush 103
    //   11177: wide
    //   11181: goto -1627 -> 9554
    //   11184: bipush 9
    //   11186: wide
    //   11190: goto -1636 -> 9554
    //   11193: bipush 98
    //   11195: wide
    //   11199: goto -1645 -> 9554
    //   11202: iconst_0
    //   11203: wide
    //   11207: goto -1574 -> 9633
    //   11210: iconst_0
    //   11211: wide
    //   11215: goto -1826 -> 9389
    //   11218: iconst_0
    //   11219: wide
    //   11223: goto -2078 -> 9145
    //   11226: iconst_0
    //   11227: wide
    //   11231: goto -2330 -> 8901
    //   11234: iconst_0
    //   11235: wide
    //   11239: goto -2582 -> 8657
    //   11242: iconst_0
    //   11243: wide
    //   11247: goto -2834 -> 8413
    //   11250: iconst_0
    //   11251: wide
    //   11255: goto -3086 -> 8169
    //   11258: iconst_0
    //   11259: wide
    //   11263: goto -3338 -> 7925
    //   11266: iconst_0
    //   11267: wide
    //   11271: goto -3590 -> 7681
    //   11274: iconst_0
    //   11275: wide
    //   11279: goto -3842 -> 7437
    //   11282: iconst_0
    //   11283: wide
    //   11287: goto -4094 -> 7193
    //   11290: iconst_0
    //   11291: wide
    //   11295: goto -4346 -> 6949
    //   11298: iconst_0
    //   11299: wide
    //   11303: goto -4598 -> 6705
    //   11306: iconst_0
    //   11307: wide
    //   11311: goto -4850 -> 6461
    //   11314: iconst_0
    //   11315: wide
    //   11319: goto -5102 -> 6217
    //   11322: iconst_0
    //   11323: wide
    //   11327: goto -5354 -> 5973
    //   11330: iconst_0
    //   11331: wide
    //   11335: goto -5606 -> 5729
    //   11338: iconst_0
    //   11339: wide
    //   11343: goto -5858 -> 5485
    //   11346: iconst_0
    //   11347: wide
    //   11351: goto -6110 -> 5241
    //   11354: iconst_0
    //   11355: wide
    //   11359: goto -6362 -> 4997
    //   11362: iconst_0
    //   11363: wide
    //   11367: goto -6614 -> 4753
    //   11370: iconst_0
    //   11371: wide
    //   11375: goto -6864 -> 4511
    //   11378: iconst_0
    //   11379: wide
    //   11383: goto -7114 -> 4269
    //   11386: iconst_0
    //   11387: wide
    //   11391: goto -7362 -> 4029
    //   11394: iconst_0
    //   11395: istore 247
    //   11397: goto -7596 -> 3801
    //   11400: iconst_0
    //   11401: istore 236
    //   11403: goto -7770 -> 3633
    //   11406: iconst_0
    //   11407: istore 225
    //   11409: goto -7944 -> 3465
    //   11412: iconst_0
    //   11413: istore 214
    //   11415: goto -8118 -> 3297
    //   11418: iconst_0
    //   11419: istore 203
    //   11421: goto -8292 -> 3129
    //   11424: iconst_0
    //   11425: istore 192
    //   11427: goto -8466 -> 2961
    //   11430: iconst_0
    //   11431: istore 181
    //   11433: goto -8640 -> 2793
    //   11436: iconst_0
    //   11437: istore 170
    //   11439: goto -8814 -> 2625
    //   11442: iconst_0
    //   11443: istore 159
    //   11445: goto -8988 -> 2457
    //   11448: iconst_0
    //   11449: istore 148
    //   11451: goto -9162 -> 2289
    //   11454: iconst_0
    //   11455: istore 137
    //   11457: goto -9336 -> 2121
    //   11460: iconst_0
    //   11461: istore 126
    //   11463: goto -9510 -> 1953
    //   11466: iconst_0
    //   11467: istore 115
    //   11469: goto -9684 -> 1785
    //   11472: iconst_0
    //   11473: istore 104
    //   11475: goto -9858 -> 1617
    //   11478: iconst_0
    //   11479: istore 94
    //   11481: goto -10028 -> 1453
    //   11484: iconst_0
    //   11485: istore 83
    //   11487: goto -10202 -> 1285
    //   11490: iconst_0
    //   11491: istore 72
    //   11493: goto -10376 -> 1117
    //   11496: iconst_0
    //   11497: istore 61
    //   11499: goto -10550 -> 949
    //   11502: iconst_0
    //   11503: istore 50
    //   11505: goto -10720 -> 785
    //   11508: iconst_0
    //   11509: istore 39
    //   11511: goto -10890 -> 621
    //   11514: iconst_0
    //   11515: istore 27
    //   11517: goto -11060 -> 457
    //   11520: iconst_0
    //   11521: istore 16
    //   11523: goto -11230 -> 293
    //   11526: iconst_0
    //   11527: istore 4
    //   11529: goto -11394 -> 135
  }

  _sdko(_sdkf param_sdkf, _sdkt param_sdkt, WPSAuthentication paramWPSAuthentication, WPSStreetAddressLookup paramWPSStreetAddressLookup, long paramLong, WPSPeriodicLocationCallback paramWPSPeriodicLocationCallback)
  {
    _sdkhb local_sdkhb1 = _sdkhb._sdkb(_sdko.class);
    this._sdka = local_sdkhb1;
    _sdkxb local_sdkxb = new _sdkxb();
    this._sdkb = local_sdkxb;
    this._sdkc = 0;
    this._sdkg = paramWPSAuthentication;
    this._sdkh = paramWPSStreetAddressLookup;
    this._sdki = paramLong;
    WPSContinuation localWPSContinuation = WPSContinuation.WPS_CONTINUE;
    _sdktb local_sdktb = new _sdktb(paramWPSPeriodicLocationCallback, localWPSContinuation);
    this._sdkj = local_sdktb;
    _sdkzb local_sdkzb = new _sdkzb();
    this._sdkm = local_sdkzb;
    _sdkec local_sdkec = _sdkec._sdkd();
    this._sdke = local_sdkec;
    this._sdkd = 0;
    this._sdkf = null;
    _sdkf._sdka(param_sdkf);
    HashMap localHashMap = new HashMap(3);
    this._sdkn = localHashMap;
    try
    {
      String str1 = z[42];
      local_sdkuc1 = _sdkuc._sdkb(param_sdkt, str1);
      long l = this._sdki;
      local_sdkuc1._sdka(l);
      this._sdkk = local_sdkuc1;
    }
    catch (_sdkk local_sdkk1)
    {
      try
      {
        String str2 = z[40];
        _sdkuc local_sdkuc2 = _sdkuc._sdkb(param_sdkt, str2);
        local_sdkuc3 = local_sdkuc2;
        this._sdkl = local_sdkuc3;
        return;
        local_sdkk1 = local_sdkk1;
        _sdkhb local_sdkhb2 = this._sdka;
        String str3 = z[41];
        local_sdkhb2._sdkb(str3, local_sdkk1);
        _sdkuc local_sdkuc1 = _sdkuc.NULL_LOCATION_PROVIDER;
      }
      catch (_sdkk local_sdkk2)
      {
        while (true)
        {
          _sdkhb local_sdkhb3 = this._sdka;
          String str4 = z[39];
          local_sdkhb3._sdkb(str4, local_sdkk2);
          _sdkuc local_sdkuc3 = _sdkuc.NULL_LOCATION_PROVIDER;
        }
      }
    }
  }

  private _sdktd<WPSReturnCode, _sdkib> _sdka(_sdkzb param_sdkzb, _sdknd param_sdknd, boolean paramBoolean, _sdktd<WPSReturnCode, _sdkib> param_sdktd, _sdkec param_sdkec)
  {
    _sdkhb local_sdkhb1 = this._sdka;
    String str1 = z[17];
    local_sdkhb1._sdkb(str1);
    Object localObject1 = param_sdktd.first;
    WPSReturnCode localWPSReturnCode1 = WPSReturnCode.WPS_ERROR;
    if ((localObject1 == localWPSReturnCode1) && (paramBoolean))
      _sdka(param_sdkzb, param_sdknd, param_sdkec);
    Object localObject2 = param_sdktd.first;
    WPSReturnCode localWPSReturnCode2 = WPSReturnCode.WPS_OK;
    if (localObject2 == localWPSReturnCode2)
    {
      _sdkib local_sdkib1 = (_sdkib)param_sdktd.second;
      int i = this._sdkd;
      if (_sdka(local_sdkib1, i, param_sdkec))
      {
        _sdkhb local_sdkhb2 = this._sdka;
        String str2 = z[19];
        local_sdkhb2._sdkb(str2);
      }
    }
    while (true)
    {
      return param_sdktd;
      _sdkib local_sdkib2 = _sdkf._sdkb(param_sdktd);
      _sdka(local_sdkib2);
      if ((this._sdkf != null) && (this._sdke._sdka(param_sdkec) >= 10000L))
      {
        _sdkhb local_sdkhb3 = this._sdka;
        String str3 = z[18];
        local_sdkhb3._sdkb(str3);
        if ((!_sdko) && (this._sdkj._sdkb() != null))
          throw new AssertionError();
        WPSReturnCode localWPSReturnCode3 = WPSReturnCode.WPS_OK;
        _sdkib local_sdkib3 = this._sdkf.clone();
        param_sdktd = _sdktd._sdka(localWPSReturnCode3, local_sdkib3);
      }
      else
      {
        _sdkhb local_sdkhb4 = this._sdka;
        String str4 = z[16];
        local_sdkhb4._sdkb(str4);
        param_sdktd = _sdktd._sdka(WPSReturnCode.WPS_ERROR_LOCATION_CANNOT_BE_DETERMINED, null);
      }
    }
  }

  private _sdktd<WPSReturnCode, _sdkib> _sdka(_sdkzb param_sdkzb, boolean paramBoolean1, boolean paramBoolean2, List<_sdkwb> paramList)
  {
    _sdkhb local_sdkhb1 = this._sdka;
    String str1 = z[32];
    local_sdkhb1._sdkb(str1);
    _sdknb local_sdknb = this._sdkp._sdke;
    long l = this._sdki;
    _sdkzb local_sdkzb = param_sdkzb;
    boolean bool1 = paramBoolean1;
    boolean bool2 = paramBoolean2;
    List<_sdkwb> localList = paramList;
    _sdktd local_sdktd = local_sdknb._sdka(local_sdkzb, bool1, bool2, l, localList);
    if (this._sdka._sdkb())
    {
      Object localObject1 = local_sdktd.first;
      WPSReturnCode localWPSReturnCode = WPSReturnCode.WPS_OK;
      if (localObject1 == localWPSReturnCode)
      {
        _sdkhb local_sdkhb2 = this._sdka;
        StringBuilder localStringBuilder1 = new StringBuilder();
        String str2 = z[31];
        StringBuilder localStringBuilder2 = localStringBuilder1.append(str2);
        boolean bool3 = ((_sdkib)local_sdktd.second).isExtrapolated();
        String str3 = bool3;
        local_sdkhb2._sdkb(str3);
        if (Location._sdki == 0);
      }
      else
      {
        _sdkhb local_sdkhb3 = this._sdka;
        StringBuilder localStringBuilder3 = new StringBuilder();
        String str4 = z[30];
        StringBuilder localStringBuilder4 = localStringBuilder3.append(str4);
        Object localObject2 = local_sdktd.first;
        String str5 = localObject2;
        local_sdkhb3._sdkb(str5);
      }
    }
    return local_sdktd;
  }

  private _sdktd<_sdkib, _sdkp> _sdka(List<_sdkpd> paramList)
  {
    Object localObject1 = null;
    int i = Location._sdki;
    Iterator localIterator = paramList.iterator();
    Object localObject2 = localObject1;
    Object localObject3 = localObject1;
    while (true)
    {
      Object localObject4;
      Map.Entry localEntry;
      long l;
      if (localIterator.hasNext())
      {
        localObject4 = (Future)localIterator.next();
        localEntry = _sdka((Future)localObject4);
        if ((!_sdko) && (localEntry == null))
          throw new AssertionError();
        if (!_sdko)
        {
          Map localMap = this._sdkn;
          Object localObject5 = localEntry.getKey();
          if (localMap.containsKey(localObject5))
            throw new AssertionError();
        }
        if ((!_sdko) && (!((Future)localObject4).isDone()))
          throw new AssertionError();
        l = 0L;
      }
      Object localObject8;
      Object localObject9;
      while (true)
      {
        try
        {
          TimeUnit localTimeUnit = TimeUnit.NANOSECONDS;
          localObject4 = (_sdktd)((Future)localObject4).get(l, localTimeUnit);
          _sdkf local_sdkf1 = this._sdkp;
          _sdkzb local_sdkzb1 = (_sdkzb)localEntry.getKey();
          _sdkf._sdka(local_sdkf1, (_sdktd)localObject4, local_sdkzb1);
          _sdkib local_sdkib = _sdkf._sdkb((_sdktd)localObject4);
          _sdka(local_sdkib);
          Object localObject6 = ((_sdktd)localObject4).first;
          WPSReturnCode localWPSReturnCode1 = WPSReturnCode.WPS_ERROR_UNAUTHORIZED;
          if (localObject6 == localWPSReturnCode1)
          {
            _sdkhb local_sdkhb1 = this._sdka;
            String str1 = z[15];
            local_sdkhb1._sdkb(str1);
            _sdkf local_sdkf2 = this._sdkp;
            _sdkec local_sdkec1 = ((_sdkp)localEntry.getValue())._sdkd;
            _sdkf._sdka(local_sdkf2, local_sdkec1);
          }
          Object localObject7 = ((_sdktd)localObject4).first;
          WPSReturnCode localWPSReturnCode2 = WPSReturnCode.WPS_OK;
          if (localObject7 != localWPSReturnCode2)
            break label468;
          if (localObject3 != null)
          {
            _sdkec local_sdkec2 = ((_sdkib)((_sdktd)localObject4).second).getAge();
            _sdkec local_sdkec3 = localObject2.getAge();
            if (local_sdkec2._sdkc(local_sdkec3) > 0)
              break label468;
          }
          localObject8 = (_sdkib)((_sdktd)localObject4).second;
          localObject9 = localEntry;
          if (i == 0)
            break label486;
          localObject2 = localObject8;
          if (localObject9 == null)
            return localObject1;
        }
        catch (TimeoutException localTimeoutException)
        {
          _sdkhb local_sdkhb2 = this._sdka;
          String str2 = z[14];
          local_sdkhb2._sdkd(str2);
        }
        catch (ExecutionException localExecutionException)
        {
          _sdkhb local_sdkhb3 = this._sdka;
          String str3 = z[13];
          local_sdkhb3._sdkb(str3, localExecutionException);
          if (_sdko)
            break;
          throw new AssertionError();
          _sdkzb local_sdkzb2 = (_sdkzb)((Map.Entry)localObject9).getKey();
          localObject2._sdkp = local_sdkzb2;
          Object localObject10 = ((Map.Entry)localObject9).getValue();
          localObject1 = _sdktd._sdka(localObject2, localObject10);
          continue;
        }
        catch (InterruptedException localInterruptedException)
        {
        }
        catch (CancellationException localCancellationException)
        {
        }
        break;
        label468: localObject8 = localObject2;
        localObject9 = localObject3;
        continue;
        localObject9 = localObject3;
      }
      label486: Object localObject11 = localObject8;
      localObject3 = localObject9;
    }
  }

  private WPSContinuation _sdka(_sdktd<WPSReturnCode, _sdkib> param_sdktd, int paramInt)
  {
    Object localObject = param_sdktd.first;
    _sdkib local_sdkib = _sdkf._sdkb(param_sdktd);
    _sdktd local_sdktd = _sdktd._sdka(localObject, local_sdkib);
    WPSContinuation localWPSContinuation = _sdkb(local_sdktd, paramInt);
    _sdka();
    return localWPSContinuation;
  }

  private WPSContinuation _sdka(_sdkib param_sdkib, _sdkp param_sdkp)
  {
    if (this._sdka._sdkb())
    {
      _sdkhb local_sdkhb1 = this._sdka;
      StringBuilder localStringBuilder1 = new StringBuilder();
      String str1 = z[38];
      StringBuilder localStringBuilder2 = localStringBuilder1.append(str1);
      int i = param_sdkp._sdkb;
      StringBuilder localStringBuilder3 = localStringBuilder2.append(i);
      String str2 = z[36];
      StringBuilder localStringBuilder4 = localStringBuilder3.append(str2);
      int j = param_sdkp._sdkc;
      StringBuilder localStringBuilder5 = localStringBuilder4.append(j);
      String str3 = z[37];
      String str4 = str3 + param_sdkib;
      local_sdkhb1._sdkb(str4);
    }
    int k = param_sdkp._sdkc;
    _sdkec local_sdkec = _sdkec._sdkd();
    _sdktd local_sdktd;
    int m;
    if (_sdka(param_sdkib, k, local_sdkec))
    {
      _sdkhb local_sdkhb2 = this._sdka;
      String str5 = z[34];
      local_sdkhb2._sdkb(str5);
      WPSReturnCode localWPSReturnCode = WPSReturnCode.WPS_OK;
      _sdkib local_sdkib = param_sdkib.clone();
      local_sdktd = _sdktd._sdka(localWPSReturnCode, local_sdkib);
      m = param_sdkp._sdkb;
    }
    for (WPSContinuation localWPSContinuation = _sdka(local_sdktd, m); ; localWPSContinuation = WPSContinuation.WPS_CONTINUE)
    {
      return localWPSContinuation;
      _sdkhb local_sdkhb3 = this._sdka;
      String str6 = z[35];
      local_sdkhb3._sdkb(str6);
    }
  }

  private Map.Entry<_sdkzb, _sdkp> _sdka(Future<_sdktd<WPSReturnCode, _sdkib>> paramFuture)
  {
    int i = Location._sdki;
    Iterator localIterator = this._sdkn.entrySet().iterator();
    Map.Entry localEntry;
    if (localIterator.hasNext())
    {
      localEntry = (Map.Entry)localIterator.next();
      if (((_sdkp)localEntry.getValue())._sdka == paramFuture)
        localIterator.remove();
    }
    while (true)
    {
      return localEntry;
      if (i == 0)
        break;
      localEntry = null;
    }
  }

  private void _sdka()
  {
    WPSContinuation localWPSContinuation1 = this._sdkj._sdkc();
    WPSContinuation localWPSContinuation2 = WPSContinuation.WPS_STOP;
    if (localWPSContinuation1 == localWPSContinuation2)
    {
      this._sdkp._sdke._sdkb();
      _sdkhb local_sdkhb = this._sdka;
      String str = z[33];
      local_sdkhb._sdkb(str);
      return;
    }
    if (this._sdkj._sdkb() == null)
      return;
    this._sdkp._sdke._sdkb();
  }

  private void _sdka(_sdkib param_sdkib)
  {
    if (param_sdkib == null)
      return;
    if (this._sdkf != null)
    {
      _sdkec local_sdkec1 = param_sdkib.getAge();
      _sdkec local_sdkec2 = this._sdkf.getAge();
      if (local_sdkec1._sdkc(local_sdkec2) > 0)
        return;
    }
    _sdkhb local_sdkhb = this._sdka;
    String str = z[0];
    local_sdkhb._sdkb(str);
    this._sdkf = param_sdkib;
  }

  private void _sdka(_sdkzb param_sdkzb, _sdknd param_sdknd, _sdkec param_sdkec)
  {
    _sdkhb local_sdkhb1 = this._sdka;
    String str1 = z[26];
    local_sdkhb1._sdkb(str1);
    if (_sdkf._sdkb(this._sdkp, param_sdkec))
    {
      _sdkhb local_sdkhb2 = this._sdka;
      String str2 = z[25];
      local_sdkhb2._sdkb(str2);
      return;
    }
    if (!com.skyhookwireless._sdktb._sdkf())
    {
      _sdkhb local_sdkhb3 = this._sdka;
      String str3 = z[22];
      local_sdkhb3._sdkb(str3);
      return;
    }
    if (!param_sdkzb.hasBeacons())
    {
      _sdkhb local_sdkhb4 = this._sdka;
      String str4 = z[24];
      local_sdkhb4._sdkb(str4);
      return;
    }
    if (this._sdkn.size() >= 2)
    {
      _sdkhb local_sdkhb5 = this._sdka;
      StringBuilder localStringBuilder1 = new StringBuilder();
      String str5 = z[23];
      StringBuilder localStringBuilder2 = localStringBuilder1.append(str5);
      int i = this._sdkn.size();
      String str6 = i;
      local_sdkhb5._sdkb(str6);
      return;
    }
    if (!_sdko)
    {
      ArrayList localArrayList1 = param_sdkzb.getAPs();
      Comparator localComparator1 = _sdkgc.COMPARATOR;
      if (!_sdkhd._sdka(localArrayList1, localComparator1))
        throw new AssertionError();
    }
    if (!_sdko)
    {
      ArrayList localArrayList2 = param_sdkzb.getCells();
      Comparator localComparator2 = _sdkw.CELL_COMPARATOR;
      if (!_sdkhd._sdka(localArrayList2, localComparator2))
        throw new AssertionError();
    }
    if (!_sdko)
    {
      ArrayList localArrayList3 = param_sdkzb.getAPs();
      Comparator localComparator3 = _sdkgc.COMPARATOR;
      if (!_sdkhd._sdkb(localArrayList3, localComparator3))
        throw new AssertionError();
    }
    if (!_sdko)
    {
      ArrayList localArrayList4 = param_sdkzb.getCells();
      Comparator localComparator4 = _sdkw.CELL_COMPARATOR;
      if (!_sdkhd._sdkb(localArrayList4, localComparator4))
        throw new AssertionError();
    }
    if (this._sdkn.containsKey(param_sdkzb))
    {
      _sdkhb local_sdkhb6 = this._sdka;
      String str7 = z[20];
      local_sdkhb6._sdkb(str7);
      return;
    }
    _sdkzb local_sdkzb = param_sdkzb.clone();
    Map localMap = this._sdkn;
    _sdkxb local_sdkxb = this._sdkb;
    WPSAuthentication localWPSAuthentication = this._sdkg;
    WPSStreetAddressLookup localWPSStreetAddressLookup = this._sdkh;
    Future localFuture = local_sdkxb._sdka(localWPSAuthentication, localWPSStreetAddressLookup, local_sdkzb, param_sdknd);
    int j = this._sdkc;
    int k = this._sdkd;
    _sdko local_sdko = this;
    _sdkec local_sdkec = param_sdkec;
    _sdkp local_sdkp = new _sdkp(local_sdko, localFuture, j, k, local_sdkec);
    Object localObject = localMap.put(local_sdkzb, local_sdkp);
    if (!this._sdka._sdkb())
      return;
    _sdkhb local_sdkhb7 = this._sdka;
    StringBuilder localStringBuilder3 = new StringBuilder();
    String str8 = z[21];
    StringBuilder localStringBuilder4 = localStringBuilder3.append(str8);
    int m = this._sdkc;
    StringBuilder localStringBuilder5 = localStringBuilder4.append(m);
    String str9 = z[27];
    StringBuilder localStringBuilder6 = localStringBuilder5.append(str9);
    int n = this._sdkd;
    StringBuilder localStringBuilder7 = localStringBuilder6.append(n);
    String str10 = z[29];
    StringBuilder localStringBuilder8 = localStringBuilder7.append(str10);
    int i1 = this._sdkn.size();
    StringBuilder localStringBuilder9 = localStringBuilder8.append(i1);
    String str11 = z[28];
    String str12 = str11;
    local_sdkhb7._sdkb(str12);
  }

  private boolean _sdka(_sdkib param_sdkib, int paramInt, _sdkec param_sdkec)
  {
    if ((this._sdkj._sdkb() != null) || (param_sdkib._sdkd()) || (this._sdke._sdka(param_sdkec) >= 10000L) || (paramInt >= 3));
    for (boolean bool = true; ; bool = false)
      return bool;
  }

  private WPSContinuation _sdkb(_sdktd<WPSReturnCode, _sdkib> param_sdktd, int paramInt)
  {
    int i = this._sdkj._sdkd();
    WPSContinuation localWPSContinuation1;
    if (paramInt <= i)
    {
      _sdkhb local_sdkhb1 = this._sdka;
      String str1 = z[12];
      local_sdkhb1._sdkb(str1);
      localWPSContinuation1 = WPSContinuation.WPS_CONTINUE;
    }
    while (true)
    {
      return localWPSContinuation1;
      Object localObject1 = param_sdktd.first;
      WPSReturnCode localWPSReturnCode1 = WPSReturnCode.WPS_OK;
      if (localObject1 != localWPSReturnCode1)
      {
        if (this._sdka._sdkb())
        {
          _sdkhb local_sdkhb2 = this._sdka;
          StringBuilder localStringBuilder1 = new StringBuilder();
          String str2 = z[10];
          StringBuilder localStringBuilder2 = localStringBuilder1.append(str2);
          Object localObject2 = param_sdktd.first;
          String str3 = localObject2;
          local_sdkhb2._sdkb(str3);
        }
        _sdkib local_sdkib = this._sdkk._sdkd();
        if (local_sdkib != null)
        {
          Object localObject3 = param_sdktd.first;
          WPSReturnCode localWPSReturnCode2 = WPSReturnCode.WPS_ERROR_UNAUTHORIZED;
          if (localObject3 != localWPSReturnCode2)
          {
            _sdkhb local_sdkhb3 = this._sdka;
            String str4 = z[8];
            local_sdkhb3._sdkb(str4);
            localWPSContinuation1 = this._sdkj.handleWPSPeriodicLocation(local_sdkib);
          }
        }
        else if (this._sdkj._sdke() == null)
        {
          long l1 = this._sdkj._sdka();
          long l2 = this._sdki - 200L;
          if (l1 < l2)
          {
            _sdkhb local_sdkhb4 = this._sdka;
            String str5 = z[11];
            local_sdkhb4._sdkb(str5);
            localWPSContinuation1 = WPSContinuation.WPS_CONTINUE;
          }
        }
        else
        {
          _sdktb local_sdktb1 = this._sdkj;
          WPSReturnCode localWPSReturnCode3 = (WPSReturnCode)param_sdktd.first;
          localWPSContinuation1 = local_sdktb1.handleError(localWPSReturnCode3);
        }
      }
      else
      {
        if (this._sdka._sdkc())
        {
          _sdkhb local_sdkhb5 = this._sdka;
          StringBuilder localStringBuilder3 = new StringBuilder();
          String str6 = z[9];
          StringBuilder localStringBuilder4 = localStringBuilder3.append(str6);
          Object localObject4 = param_sdktd.second;
          String str7 = localObject4;
          local_sdkhb5._sdkc(str7);
        }
        if (this._sdkl._sdkb())
        {
          _sdkhb local_sdkhb6 = this._sdka;
          String str8 = z[7];
          local_sdkhb6._sdkb(str8);
          this._sdkl._sdkc();
        }
        this._sdkf = null;
        _sdktb local_sdktb2 = this._sdkj;
        WPSLocation localWPSLocation = (WPSLocation)param_sdktd.second;
        WPSContinuation localWPSContinuation2 = local_sdktb2.handleWPSPeriodicLocationTrack(localWPSLocation, paramInt);
        localWPSContinuation1 = this._sdkj._sdkc();
      }
    }
  }

  private void _sdkb()
  {
    int i = Location._sdki;
    Iterator localIterator = this._sdkn.values().iterator();
    do
    {
      if (!localIterator.hasNext())
        break;
      boolean bool = ((_sdkp)localIterator.next())._sdka.cancel(true);
    }
    while (i == 0);
    this._sdkn.clear();
  }

  public void abort()
  {
  }

  public void done()
  {
    if (this._sdkf != null)
    {
      _sdkhb local_sdkhb1 = this._sdka;
      String str1 = z[46];
      local_sdkhb1._sdkb(str1);
      if ((!_sdko) && (this._sdkj._sdkb() != null))
        throw new AssertionError();
      WPSReturnCode localWPSReturnCode = WPSReturnCode.WPS_OK;
      _sdkib local_sdkib = this._sdkf.clone();
      _sdktd local_sdktd = _sdktd._sdka(localWPSReturnCode, local_sdkib);
      int i = this._sdkc;
      WPSContinuation localWPSContinuation = _sdka(local_sdktd, i);
    }
    try
    {
      this._sdkk._sdkc();
    }
    catch (Throwable localThrowable2)
    {
      try
      {
        this._sdkl._sdkc();
      }
      catch (Throwable localThrowable2)
      {
        try
        {
          while (true)
          {
            _sdkb();
            this._sdkp._sdke._sdkb();
            this._sdkj.done();
            _sdkhb local_sdkhb2 = this._sdka;
            String str2;
            return;
            localThrowable1 = localThrowable1;
            _sdkhb local_sdkhb3 = this._sdka;
            String str3 = z[45];
            local_sdkhb3._sdke(str3, localThrowable1);
          }
          localThrowable2 = localThrowable2;
          _sdkhb local_sdkhb4 = this._sdka;
          String str4 = z[44];
          local_sdkhb4._sdke(str4, localThrowable2);
        }
        finally
        {
          this._sdkp._sdke._sdkb();
          this._sdkj.done();
        }
      }
    }
  }

  public long getGpsPeriod()
  {
    return this._sdkp._sdke._sdkd();
  }

  public long getWifiPeriod()
  {
    return this._sdkp._sdke._sdkc();
  }

  public WPSContinuation handleError(WPSReturnCode paramWPSReturnCode)
  {
    return this._sdkj.handleError(paramWPSReturnCode);
  }

  public WPSContinuation handleEvents(List<_sdkpd> paramList, _sdknd param_sdknd)
  {
    _sdktd local_sdktd = _sdka(paramList);
    if (local_sdktd == null);
    _sdkib local_sdkib;
    _sdkp local_sdkp;
    for (WPSContinuation localWPSContinuation = WPSContinuation.WPS_CONTINUE; ; localWPSContinuation = _sdka(local_sdkib, local_sdkp))
    {
      return localWPSContinuation;
      local_sdkib = (_sdkib)local_sdktd.first;
      local_sdkp = (_sdkp)local_sdktd.second;
    }
  }

  public WPSContinuation handleScan(_sdkzb param_sdkzb, _sdknd param_sdknd, boolean paramBoolean1, boolean paramBoolean2, List<_sdkwb> paramList)
  {
    _sdkec local_sdkec = _sdkec._sdkd();
    if (param_sdkzb.getAPs().size() > 0)
    {
      int i = this._sdkd + 1;
      this._sdkd = i;
    }
    if (this._sdka._sdkb())
    {
      _sdkhb local_sdkhb1 = this._sdka;
      StringBuilder localStringBuilder1 = new StringBuilder();
      String str1 = z[2];
      StringBuilder localStringBuilder2 = localStringBuilder1.append(str1);
      int j = this._sdkd;
      String str2 = j;
      local_sdkhb1._sdkb(str2);
    }
    this._sdkm.merge(param_sdkzb);
    this._sdkm.filterOld(local_sdkec);
    _sdkzb local_sdkzb = this._sdkm.clone();
    if (this._sdka._sdkb())
    {
      _sdkhb local_sdkhb2 = this._sdka;
      StringBuilder localStringBuilder3 = new StringBuilder();
      String str3 = z[3];
      StringBuilder localStringBuilder4 = localStringBuilder3.append(str3);
      int k = local_sdkzb.getAPs().size();
      StringBuilder localStringBuilder5 = localStringBuilder4.append(k);
      String str4 = z[4];
      StringBuilder localStringBuilder6 = localStringBuilder5.append(str4);
      ArrayList localArrayList1 = local_sdkzb.getAPs();
      String str5 = localArrayList1;
      local_sdkhb2._sdkb(str5);
      _sdkhb local_sdkhb3 = this._sdka;
      StringBuilder localStringBuilder7 = new StringBuilder();
      String str6 = z[6];
      StringBuilder localStringBuilder8 = localStringBuilder7.append(str6);
      int m = local_sdkzb.getCells().size();
      StringBuilder localStringBuilder9 = localStringBuilder8.append(m);
      String str7 = z[4];
      StringBuilder localStringBuilder10 = localStringBuilder9.append(str7);
      ArrayList localArrayList2 = local_sdkzb.getCells();
      String str8 = localArrayList2;
      local_sdkhb3._sdkb(str8);
    }
    int n = this._sdkc + 1;
    this._sdkc = n;
    _sdktd local_sdktd1 = _sdkf._sdka(this._sdkp, local_sdkzb);
    _sdktd local_sdktd2 = _sdka(local_sdkzb, paramBoolean1, paramBoolean2, paramList);
    Object localObject = local_sdktd2.first;
    WPSReturnCode localWPSReturnCode = WPSReturnCode.WPS_OK;
    int i1;
    if (localObject == localWPSReturnCode)
    {
      _sdkhb local_sdkhb4 = this._sdka;
      String str9 = z[1];
      local_sdkhb4._sdkb(str9);
      i1 = this._sdkc;
    }
    _sdktd local_sdktd3;
    int i2;
    for (WPSContinuation localWPSContinuation = _sdka(local_sdktd2, i1); ; localWPSContinuation = _sdka(local_sdktd3, i2))
    {
      return localWPSContinuation;
      _sdko local_sdko = this;
      _sdknd local_sdknd = param_sdknd;
      boolean bool = paramBoolean2;
      local_sdktd3 = local_sdko._sdka(local_sdkzb, local_sdknd, bool, local_sdktd1, local_sdkec);
      _sdkhb local_sdkhb5 = this._sdka;
      String str10 = z[5];
      local_sdkhb5._sdkb(str10);
      i2 = this._sdkc;
    }
  }

  public void init()
  {
    this._sdkp._sdke._sdka();
  }

  public _sdkib lastLocation()
  {
    return this._sdkj._sdke();
  }

  public boolean reportedFirstFix()
  {
    if (this._sdkj._sdkb() != null)
    {
      long l1 = this._sdkj._sdkb().longValue();
      long l2 = this._sdki;
      long l3 = 2L * l2;
      if (l1 >= l3);
    }
    for (boolean bool = true; ; bool = false)
      return bool;
  }
}

/* Location:           D:\Tools\extractapktools\extractapktools\dex2jar-0.0.7.11-SNAPSHOT\classes_dex2jar.jar
 * Qualified Name:     com.skyhookwireless.wps._sdko
 * JD-Core Version:    0.6.2
 */