package com.skyhookwireless.wps;

import com.skyhookwireless._sdkab;
import com.skyhookwireless._sdkec;
import com.skyhookwireless._sdkhd;
import com.skyhookwireless._sdkic;
import com.skyhookwireless._sdkjc;
import com.skyhookwireless._sdkv;
import java.util.ArrayList;
import java.util.Collection;
import java.util.Collections;
import java.util.Comparator;
import java.util.HashSet;
import java.util.Iterator;

public abstract class Protocol
{
  private static final Comparator<_sdkib> _sdka;
  static final boolean _sdkb;
  private static final String[] z;

  // ERROR //
  static
  {
    // Byte code:
    //   0: iconst_1
    //   1: istore_0
    //   2: bipush 79
    //   4: anewarray 15	java/lang/String
    //   7: astore_1
    //   8: ldc 17
    //   10: invokevirtual 21	java/lang/String:toCharArray	()[C
    //   13: astore_2
    //   14: aload_2
    //   15: arraylength
    //   16: istore_3
    //   17: iload_3
    //   18: iload_0
    //   19: if_icmpgt +20733 -> 20752
    //   22: iconst_0
    //   23: istore 4
    //   25: aload_2
    //   26: astore 5
    //   28: iload 4
    //   30: istore 6
    //   32: iload_3
    //   33: istore 7
    //   35: aload_2
    //   36: astore 8
    //   38: iload 7
    //   40: istore 9
    //   42: aload 8
    //   44: iload 4
    //   46: caload
    //   47: istore 10
    //   49: iload 6
    //   51: iconst_5
    //   52: irem
    //   53: tableswitch	default:+31 -> 84, 0:+17459->17512, 1:+17466->17519, 2:+17473->17526, 3:+17480->17533
    //   85: pop
    //   86: istore 11
    //   88: iload 11
    //   90: iload 10
    //   92: ixor
    //   93: i2c
    //   94: istore 12
    //   96: aload 8
    //   98: iload 4
    //   100: iload 12
    //   102: castore
    //   103: iload 6
    //   105: iconst_1
    //   106: iadd
    //   107: istore 4
    //   109: iload 9
    //   111: ifne +18 -> 129
    //   114: aload 5
    //   116: astore 8
    //   118: iload 4
    //   120: istore 6
    //   122: iload 9
    //   124: istore 4
    //   126: goto -84 -> 42
    //   129: iload 9
    //   131: istore_3
    //   132: aload 5
    //   134: astore_2
    //   135: iload_3
    //   136: iload 4
    //   138: if_icmpgt -113 -> 25
    //   141: new 15	java/lang/String
    //   144: dup
    //   145: aload_2
    //   146: invokespecial 25	java/lang/String:<init>	([C)V
    //   149: invokevirtual 29	java/lang/String:intern	()Ljava/lang/String;
    //   152: astore 13
    //   154: aload_1
    //   155: iconst_0
    //   156: aload 13
    //   158: aastore
    //   159: ldc 31
    //   161: invokevirtual 21	java/lang/String:toCharArray	()[C
    //   164: astore 14
    //   166: aload 14
    //   168: arraylength
    //   169: istore 15
    //   171: iload 15
    //   173: iconst_1
    //   174: if_icmpgt +20572 -> 20746
    //   177: iconst_0
    //   178: istore 16
    //   180: aload 14
    //   182: astore 5
    //   184: iload 16
    //   186: istore 6
    //   188: iload 15
    //   190: istore 17
    //   192: aload 14
    //   194: astore 18
    //   196: iload 17
    //   198: istore 19
    //   200: aload 18
    //   202: iload 16
    //   204: caload
    //   205: istore 10
    //   207: iload 6
    //   209: iconst_5
    //   210: irem
    //   211: tableswitch	default:+29 -> 240, 0:+17329->17540, 1:+17336->17547, 2:+17343->17554, 3:+17350->17561
    //   241: pop
    //   242: istore 20
    //   244: iload 20
    //   246: iload 10
    //   248: ixor
    //   249: i2c
    //   250: istore 21
    //   252: aload 18
    //   254: iload 16
    //   256: iload 21
    //   258: castore
    //   259: iload 6
    //   261: iconst_1
    //   262: iadd
    //   263: istore 16
    //   265: iload 19
    //   267: ifne +18 -> 285
    //   270: aload 5
    //   272: astore 18
    //   274: iload 16
    //   276: istore 22
    //   278: iload 19
    //   280: istore 16
    //   282: goto -82 -> 200
    //   285: iload 19
    //   287: istore 15
    //   289: aload 5
    //   291: astore 14
    //   293: iload 15
    //   295: iload 16
    //   297: if_icmpgt -117 -> 180
    //   300: new 15	java/lang/String
    //   303: dup
    //   304: aload 14
    //   306: invokespecial 25	java/lang/String:<init>	([C)V
    //   309: invokevirtual 29	java/lang/String:intern	()Ljava/lang/String;
    //   312: astore 23
    //   314: aload_1
    //   315: iconst_1
    //   316: aload 23
    //   318: aastore
    //   319: iconst_2
    //   320: istore 24
    //   322: ldc 33
    //   324: invokevirtual 21	java/lang/String:toCharArray	()[C
    //   327: astore 25
    //   329: aload 25
    //   331: arraylength
    //   332: istore 26
    //   334: iload 26
    //   336: iconst_1
    //   337: if_icmpgt +20403 -> 20740
    //   340: iconst_0
    //   341: istore 27
    //   343: aload 25
    //   345: astore 5
    //   347: iload 27
    //   349: istore 6
    //   351: iload 26
    //   353: istore 28
    //   355: aload 25
    //   357: astore 29
    //   359: iload 28
    //   361: istore 30
    //   363: aload 29
    //   365: iload 27
    //   367: caload
    //   368: istore 31
    //   370: iload 6
    //   372: iconst_5
    //   373: irem
    //   374: tableswitch	default:+30 -> 404, 0:+17194->17568, 1:+17201->17575, 2:+17208->17582, 3:+17215->17589
    //   405: pop
    //   406: istore 32
    //   408: iload 32
    //   410: iload 31
    //   412: ixor
    //   413: i2c
    //   414: istore 33
    //   416: aload 29
    //   418: iload 27
    //   420: iload 33
    //   422: castore
    //   423: iload 6
    //   425: iconst_1
    //   426: iadd
    //   427: istore 27
    //   429: iload 30
    //   431: ifne +18 -> 449
    //   434: aload 5
    //   436: astore 29
    //   438: iload 27
    //   440: istore 34
    //   442: iload 30
    //   444: istore 27
    //   446: goto -83 -> 363
    //   449: iload 30
    //   451: istore 26
    //   453: aload 5
    //   455: astore 25
    //   457: iload 26
    //   459: iload 27
    //   461: if_icmpgt -118 -> 343
    //   464: new 15	java/lang/String
    //   467: dup
    //   468: aload 25
    //   470: invokespecial 25	java/lang/String:<init>	([C)V
    //   473: invokevirtual 29	java/lang/String:intern	()Ljava/lang/String;
    //   476: astore 35
    //   478: aload_1
    //   479: iload 24
    //   481: aload 35
    //   483: aastore
    //   484: iconst_3
    //   485: istore 36
    //   487: ldc 35
    //   489: invokevirtual 21	java/lang/String:toCharArray	()[C
    //   492: astore 37
    //   494: aload 37
    //   496: arraylength
    //   497: istore 38
    //   499: iload 38
    //   501: iconst_1
    //   502: if_icmpgt +20232 -> 20734
    //   505: iconst_0
    //   506: istore 39
    //   508: aload 37
    //   510: astore 5
    //   512: iload 39
    //   514: istore 6
    //   516: iload 38
    //   518: istore 40
    //   520: aload 37
    //   522: astore 41
    //   524: iload 40
    //   526: istore 42
    //   528: aload 41
    //   530: iload 39
    //   532: caload
    //   533: istore 31
    //   535: iload 6
    //   537: iconst_5
    //   538: irem
    //   539: tableswitch	default:+29 -> 568, 0:+17057->17596, 1:+17064->17603, 2:+17071->17610, 3:+17078->17617
    //   569: pop
    //   570: istore 43
    //   572: iload 43
    //   574: iload 31
    //   576: ixor
    //   577: i2c
    //   578: istore 44
    //   580: aload 41
    //   582: iload 39
    //   584: iload 44
    //   586: castore
    //   587: iload 6
    //   589: iconst_1
    //   590: iadd
    //   591: istore 39
    //   593: iload 42
    //   595: ifne +18 -> 613
    //   598: aload 5
    //   600: astore 41
    //   602: iload 39
    //   604: istore 45
    //   606: iload 42
    //   608: istore 39
    //   610: goto -82 -> 528
    //   613: iload 42
    //   615: istore 38
    //   617: aload 5
    //   619: astore 37
    //   621: iload 38
    //   623: iload 39
    //   625: if_icmpgt -117 -> 508
    //   628: new 15	java/lang/String
    //   631: dup
    //   632: aload 37
    //   634: invokespecial 25	java/lang/String:<init>	([C)V
    //   637: invokevirtual 29	java/lang/String:intern	()Ljava/lang/String;
    //   640: astore 46
    //   642: aload_1
    //   643: iload 36
    //   645: aload 46
    //   647: aastore
    //   648: iconst_4
    //   649: istore 47
    //   651: ldc 37
    //   653: invokevirtual 21	java/lang/String:toCharArray	()[C
    //   656: astore 48
    //   658: aload 48
    //   660: arraylength
    //   661: istore 49
    //   663: iload 49
    //   665: iconst_1
    //   666: if_icmpgt +20062 -> 20728
    //   669: iconst_0
    //   670: istore 50
    //   672: aload 48
    //   674: astore 5
    //   676: iload 50
    //   678: istore 6
    //   680: iload 49
    //   682: istore 51
    //   684: aload 48
    //   686: astore 52
    //   688: iload 51
    //   690: istore 53
    //   692: aload 52
    //   694: iload 50
    //   696: caload
    //   697: istore 31
    //   699: iload 6
    //   701: iconst_5
    //   702: irem
    //   703: tableswitch	default:+29 -> 732, 0:+16921->17624, 1:+16928->17631, 2:+16935->17638, 3:+16942->17645
    //   733: pop
    //   734: istore 54
    //   736: iload 54
    //   738: iload 31
    //   740: ixor
    //   741: i2c
    //   742: istore 55
    //   744: aload 52
    //   746: iload 50
    //   748: iload 55
    //   750: castore
    //   751: iload 6
    //   753: iconst_1
    //   754: iadd
    //   755: istore 50
    //   757: iload 53
    //   759: ifne +18 -> 777
    //   762: aload 5
    //   764: astore 52
    //   766: iload 50
    //   768: istore 56
    //   770: iload 53
    //   772: istore 50
    //   774: goto -82 -> 692
    //   777: iload 53
    //   779: istore 49
    //   781: aload 5
    //   783: astore 48
    //   785: iload 49
    //   787: iload 50
    //   789: if_icmpgt -117 -> 672
    //   792: new 15	java/lang/String
    //   795: dup
    //   796: aload 48
    //   798: invokespecial 25	java/lang/String:<init>	([C)V
    //   801: invokevirtual 29	java/lang/String:intern	()Ljava/lang/String;
    //   804: astore 57
    //   806: aload_1
    //   807: iload 47
    //   809: aload 57
    //   811: aastore
    //   812: iconst_5
    //   813: istore 58
    //   815: ldc 39
    //   817: invokevirtual 21	java/lang/String:toCharArray	()[C
    //   820: astore 59
    //   822: aload 59
    //   824: arraylength
    //   825: istore 60
    //   827: iload 60
    //   829: iconst_1
    //   830: if_icmpgt +19892 -> 20722
    //   833: iconst_0
    //   834: istore 61
    //   836: aload 59
    //   838: astore 5
    //   840: iload 61
    //   842: istore 6
    //   844: iload 60
    //   846: istore 62
    //   848: aload 59
    //   850: astore 63
    //   852: iload 62
    //   854: istore 64
    //   856: aload 63
    //   858: iload 61
    //   860: caload
    //   861: istore 31
    //   863: iload 6
    //   865: iconst_5
    //   866: irem
    //   867: tableswitch	default:+29 -> 896, 0:+16785->17652, 1:+16792->17659, 2:+16799->17666, 3:+16806->17673
    //   897: pop
    //   898: istore 65
    //   900: iload 65
    //   902: iload 31
    //   904: ixor
    //   905: i2c
    //   906: istore 66
    //   908: aload 63
    //   910: iload 61
    //   912: iload 66
    //   914: castore
    //   915: iload 6
    //   917: iconst_1
    //   918: iadd
    //   919: istore 61
    //   921: iload 64
    //   923: ifne +18 -> 941
    //   926: aload 5
    //   928: astore 63
    //   930: iload 61
    //   932: istore 67
    //   934: iload 64
    //   936: istore 61
    //   938: goto -82 -> 856
    //   941: iload 64
    //   943: istore 60
    //   945: aload 5
    //   947: astore 59
    //   949: iload 60
    //   951: iload 61
    //   953: if_icmpgt -117 -> 836
    //   956: new 15	java/lang/String
    //   959: dup
    //   960: aload 59
    //   962: invokespecial 25	java/lang/String:<init>	([C)V
    //   965: invokevirtual 29	java/lang/String:intern	()Ljava/lang/String;
    //   968: astore 68
    //   970: aload_1
    //   971: iload 58
    //   973: aload 68
    //   975: aastore
    //   976: bipush 6
    //   978: istore 69
    //   980: ldc 41
    //   982: invokevirtual 21	java/lang/String:toCharArray	()[C
    //   985: astore 70
    //   987: aload 70
    //   989: arraylength
    //   990: istore 71
    //   992: iload 71
    //   994: iconst_1
    //   995: if_icmpgt +19721 -> 20716
    //   998: iconst_0
    //   999: istore 72
    //   1001: aload 70
    //   1003: astore 5
    //   1005: iload 72
    //   1007: istore 6
    //   1009: iload 71
    //   1011: istore 73
    //   1013: aload 70
    //   1015: astore 74
    //   1017: iload 73
    //   1019: istore 75
    //   1021: aload 74
    //   1023: iload 72
    //   1025: caload
    //   1026: istore 31
    //   1028: iload 6
    //   1030: iconst_5
    //   1031: irem
    //   1032: tableswitch	default:+32 -> 1064, 0:+16648->17680, 1:+16655->17687, 2:+16662->17694, 3:+16669->17701
    //   1065: pop
    //   1066: istore 76
    //   1068: iload 76
    //   1070: iload 31
    //   1072: ixor
    //   1073: i2c
    //   1074: istore 77
    //   1076: aload 74
    //   1078: iload 72
    //   1080: iload 77
    //   1082: castore
    //   1083: iload 6
    //   1085: iconst_1
    //   1086: iadd
    //   1087: istore 72
    //   1089: iload 75
    //   1091: ifne +18 -> 1109
    //   1094: aload 5
    //   1096: astore 74
    //   1098: iload 72
    //   1100: istore 78
    //   1102: iload 75
    //   1104: istore 72
    //   1106: goto -85 -> 1021
    //   1109: iload 75
    //   1111: istore 71
    //   1113: aload 5
    //   1115: astore 70
    //   1117: iload 71
    //   1119: iload 72
    //   1121: if_icmpgt -120 -> 1001
    //   1124: new 15	java/lang/String
    //   1127: dup
    //   1128: aload 70
    //   1130: invokespecial 25	java/lang/String:<init>	([C)V
    //   1133: invokevirtual 29	java/lang/String:intern	()Ljava/lang/String;
    //   1136: astore 79
    //   1138: aload_1
    //   1139: iload 69
    //   1141: aload 79
    //   1143: aastore
    //   1144: bipush 7
    //   1146: istore 80
    //   1148: ldc 43
    //   1150: invokevirtual 21	java/lang/String:toCharArray	()[C
    //   1153: astore 81
    //   1155: aload 81
    //   1157: arraylength
    //   1158: istore 82
    //   1160: iload 82
    //   1162: iconst_1
    //   1163: if_icmpgt +19547 -> 20710
    //   1166: iconst_0
    //   1167: istore 83
    //   1169: aload 81
    //   1171: astore 5
    //   1173: iload 83
    //   1175: istore 6
    //   1177: iload 82
    //   1179: istore 84
    //   1181: aload 81
    //   1183: astore 85
    //   1185: iload 84
    //   1187: istore 86
    //   1189: aload 85
    //   1191: iload 83
    //   1193: caload
    //   1194: istore 31
    //   1196: iload 6
    //   1198: iconst_5
    //   1199: irem
    //   1200: tableswitch	default:+32 -> 1232, 0:+16508->17708, 1:+16515->17715, 2:+16522->17722, 3:+16529->17729
    //   1233: pop
    //   1234: istore 87
    //   1236: iload 87
    //   1238: iload 31
    //   1240: ixor
    //   1241: i2c
    //   1242: istore 88
    //   1244: aload 85
    //   1246: iload 83
    //   1248: iload 88
    //   1250: castore
    //   1251: iload 6
    //   1253: iconst_1
    //   1254: iadd
    //   1255: istore 83
    //   1257: iload 86
    //   1259: ifne +18 -> 1277
    //   1262: aload 5
    //   1264: astore 85
    //   1266: iload 83
    //   1268: istore 89
    //   1270: iload 86
    //   1272: istore 83
    //   1274: goto -85 -> 1189
    //   1277: iload 86
    //   1279: istore 82
    //   1281: aload 5
    //   1283: astore 81
    //   1285: iload 82
    //   1287: iload 83
    //   1289: if_icmpgt -120 -> 1169
    //   1292: new 15	java/lang/String
    //   1295: dup
    //   1296: aload 81
    //   1298: invokespecial 25	java/lang/String:<init>	([C)V
    //   1301: invokevirtual 29	java/lang/String:intern	()Ljava/lang/String;
    //   1304: astore 90
    //   1306: aload_1
    //   1307: iload 80
    //   1309: aload 90
    //   1311: aastore
    //   1312: bipush 8
    //   1314: istore 91
    //   1316: ldc 45
    //   1318: invokevirtual 21	java/lang/String:toCharArray	()[C
    //   1321: astore 92
    //   1323: aload 92
    //   1325: arraylength
    //   1326: istore 93
    //   1328: iload 93
    //   1330: iconst_1
    //   1331: if_icmpgt +19373 -> 20704
    //   1334: iconst_0
    //   1335: istore 94
    //   1337: aload 92
    //   1339: astore 5
    //   1341: iload 94
    //   1343: istore 6
    //   1345: iload 93
    //   1347: istore 95
    //   1349: aload 92
    //   1351: astore 96
    //   1353: iload 95
    //   1355: istore 97
    //   1357: aload 96
    //   1359: iload 94
    //   1361: caload
    //   1362: istore 31
    //   1364: iload 6
    //   1366: iconst_5
    //   1367: irem
    //   1368: tableswitch	default:+32 -> 1400, 0:+16368->17736, 1:+16375->17743, 2:+16382->17750, 3:+16389->17757
    //   1401: pop
    //   1402: istore 98
    //   1404: iload 98
    //   1406: iload 31
    //   1408: ixor
    //   1409: i2c
    //   1410: istore 99
    //   1412: aload 96
    //   1414: iload 94
    //   1416: iload 99
    //   1418: castore
    //   1419: iload 6
    //   1421: iconst_1
    //   1422: iadd
    //   1423: istore 94
    //   1425: iload 97
    //   1427: ifne +18 -> 1445
    //   1430: aload 5
    //   1432: astore 96
    //   1434: iload 94
    //   1436: istore 100
    //   1438: iload 97
    //   1440: istore 94
    //   1442: goto -85 -> 1357
    //   1445: iload 97
    //   1447: istore 93
    //   1449: aload 5
    //   1451: astore 92
    //   1453: iload 93
    //   1455: iload 94
    //   1457: if_icmpgt -120 -> 1337
    //   1460: new 15	java/lang/String
    //   1463: dup
    //   1464: aload 92
    //   1466: invokespecial 25	java/lang/String:<init>	([C)V
    //   1469: invokevirtual 29	java/lang/String:intern	()Ljava/lang/String;
    //   1472: astore 101
    //   1474: aload_1
    //   1475: iload 91
    //   1477: aload 101
    //   1479: aastore
    //   1480: bipush 9
    //   1482: istore 102
    //   1484: ldc 47
    //   1486: invokevirtual 21	java/lang/String:toCharArray	()[C
    //   1489: astore 103
    //   1491: aload 103
    //   1493: arraylength
    //   1494: istore 104
    //   1496: iload 104
    //   1498: iconst_1
    //   1499: if_icmpgt +19199 -> 20698
    //   1502: iconst_0
    //   1503: istore 105
    //   1505: aload 103
    //   1507: astore 5
    //   1509: iload 105
    //   1511: istore 6
    //   1513: iload 104
    //   1515: istore 106
    //   1517: aload 103
    //   1519: astore 107
    //   1521: iload 106
    //   1523: istore 108
    //   1525: aload 107
    //   1527: iload 105
    //   1529: caload
    //   1530: istore 31
    //   1532: iload 6
    //   1534: iconst_5
    //   1535: irem
    //   1536: tableswitch	default:+32 -> 1568, 0:+16228->17764, 1:+16235->17771, 2:+16242->17778, 3:+16249->17785
    //   1569: pop
    //   1570: istore 109
    //   1572: iload 109
    //   1574: iload 31
    //   1576: ixor
    //   1577: i2c
    //   1578: istore 110
    //   1580: aload 107
    //   1582: iload 105
    //   1584: iload 110
    //   1586: castore
    //   1587: iload 6
    //   1589: iconst_1
    //   1590: iadd
    //   1591: istore 105
    //   1593: iload 108
    //   1595: ifne +18 -> 1613
    //   1598: aload 5
    //   1600: astore 107
    //   1602: iload 105
    //   1604: istore 111
    //   1606: iload 108
    //   1608: istore 105
    //   1610: goto -85 -> 1525
    //   1613: iload 108
    //   1615: istore 104
    //   1617: aload 5
    //   1619: astore 103
    //   1621: iload 104
    //   1623: iload 105
    //   1625: if_icmpgt -120 -> 1505
    //   1628: new 15	java/lang/String
    //   1631: dup
    //   1632: aload 103
    //   1634: invokespecial 25	java/lang/String:<init>	([C)V
    //   1637: invokevirtual 29	java/lang/String:intern	()Ljava/lang/String;
    //   1640: astore 112
    //   1642: aload_1
    //   1643: iload 102
    //   1645: aload 112
    //   1647: aastore
    //   1648: bipush 10
    //   1650: istore 113
    //   1652: ldc 49
    //   1654: invokevirtual 21	java/lang/String:toCharArray	()[C
    //   1657: astore 114
    //   1659: aload 114
    //   1661: arraylength
    //   1662: istore 115
    //   1664: iload 115
    //   1666: iconst_1
    //   1667: if_icmpgt +19025 -> 20692
    //   1670: iconst_0
    //   1671: istore 116
    //   1673: aload 114
    //   1675: astore 5
    //   1677: iload 116
    //   1679: istore 6
    //   1681: iload 115
    //   1683: istore 117
    //   1685: aload 114
    //   1687: astore 118
    //   1689: iload 117
    //   1691: istore 119
    //   1693: aload 118
    //   1695: iload 116
    //   1697: caload
    //   1698: istore 31
    //   1700: iload 6
    //   1702: iconst_5
    //   1703: irem
    //   1704: tableswitch	default:+32 -> 1736, 0:+16088->17792, 1:+16095->17799, 2:+16102->17806, 3:+16109->17813
    //   1737: pop
    //   1738: istore 120
    //   1740: iload 120
    //   1742: iload 31
    //   1744: ixor
    //   1745: i2c
    //   1746: istore 121
    //   1748: aload 118
    //   1750: iload 116
    //   1752: iload 121
    //   1754: castore
    //   1755: iload 6
    //   1757: iconst_1
    //   1758: iadd
    //   1759: istore 116
    //   1761: iload 119
    //   1763: ifne +18 -> 1781
    //   1766: aload 5
    //   1768: astore 118
    //   1770: iload 116
    //   1772: istore 122
    //   1774: iload 119
    //   1776: istore 116
    //   1778: goto -85 -> 1693
    //   1781: iload 119
    //   1783: istore 115
    //   1785: aload 5
    //   1787: astore 114
    //   1789: iload 115
    //   1791: iload 116
    //   1793: if_icmpgt -120 -> 1673
    //   1796: new 15	java/lang/String
    //   1799: dup
    //   1800: aload 114
    //   1802: invokespecial 25	java/lang/String:<init>	([C)V
    //   1805: invokevirtual 29	java/lang/String:intern	()Ljava/lang/String;
    //   1808: astore 123
    //   1810: aload_1
    //   1811: iload 113
    //   1813: aload 123
    //   1815: aastore
    //   1816: bipush 11
    //   1818: istore 124
    //   1820: ldc 51
    //   1822: invokevirtual 21	java/lang/String:toCharArray	()[C
    //   1825: astore 125
    //   1827: aload 125
    //   1829: arraylength
    //   1830: istore 126
    //   1832: iload 126
    //   1834: iconst_1
    //   1835: if_icmpgt +18851 -> 20686
    //   1838: iconst_0
    //   1839: istore 127
    //   1841: aload 125
    //   1843: astore 5
    //   1845: iload 127
    //   1847: istore 6
    //   1849: iload 126
    //   1851: istore 128
    //   1853: aload 125
    //   1855: astore 129
    //   1857: iload 128
    //   1859: istore 130
    //   1861: aload 129
    //   1863: iload 127
    //   1865: caload
    //   1866: istore 31
    //   1868: iload 6
    //   1870: iconst_5
    //   1871: irem
    //   1872: tableswitch	default:+32 -> 1904, 0:+15948->17820, 1:+15955->17827, 2:+15962->17834, 3:+15969->17841
    //   1905: pop
    //   1906: istore 131
    //   1908: iload 131
    //   1910: iload 31
    //   1912: ixor
    //   1913: i2c
    //   1914: istore 132
    //   1916: aload 129
    //   1918: iload 127
    //   1920: iload 132
    //   1922: castore
    //   1923: iload 6
    //   1925: iconst_1
    //   1926: iadd
    //   1927: istore 127
    //   1929: iload 130
    //   1931: ifne +18 -> 1949
    //   1934: aload 5
    //   1936: astore 129
    //   1938: iload 127
    //   1940: istore 133
    //   1942: iload 130
    //   1944: istore 127
    //   1946: goto -85 -> 1861
    //   1949: iload 130
    //   1951: istore 126
    //   1953: aload 5
    //   1955: astore 125
    //   1957: iload 126
    //   1959: iload 127
    //   1961: if_icmpgt -120 -> 1841
    //   1964: new 15	java/lang/String
    //   1967: dup
    //   1968: aload 125
    //   1970: invokespecial 25	java/lang/String:<init>	([C)V
    //   1973: invokevirtual 29	java/lang/String:intern	()Ljava/lang/String;
    //   1976: astore 134
    //   1978: aload_1
    //   1979: iload 124
    //   1981: aload 134
    //   1983: aastore
    //   1984: ldc 53
    //   1986: invokevirtual 21	java/lang/String:toCharArray	()[C
    //   1989: astore 135
    //   1991: aload 135
    //   1993: arraylength
    //   1994: istore 136
    //   1996: iload 136
    //   1998: iconst_1
    //   1999: if_icmpgt +18681 -> 20680
    //   2002: iconst_0
    //   2003: istore 137
    //   2005: aload 135
    //   2007: astore 5
    //   2009: iload 137
    //   2011: istore 6
    //   2013: iload 136
    //   2015: istore 138
    //   2017: aload 135
    //   2019: astore 139
    //   2021: iload 138
    //   2023: istore 140
    //   2025: aload 139
    //   2027: iload 137
    //   2029: caload
    //   2030: istore 124
    //   2032: iload 6
    //   2034: iconst_5
    //   2035: irem
    //   2036: tableswitch	default:+32 -> 2068, 0:+15812->17848, 1:+15819->17855, 2:+15826->17862, 3:+15833->17869
    //   2069: pop
    //   2070: istore 141
    //   2072: iload 141
    //   2074: iload 124
    //   2076: ixor
    //   2077: i2c
    //   2078: istore 142
    //   2080: aload 139
    //   2082: iload 137
    //   2084: iload 142
    //   2086: castore
    //   2087: iload 6
    //   2089: iconst_1
    //   2090: iadd
    //   2091: istore 137
    //   2093: iload 140
    //   2095: ifne +18 -> 2113
    //   2098: aload 5
    //   2100: astore 139
    //   2102: iload 137
    //   2104: istore 143
    //   2106: iload 140
    //   2108: istore 137
    //   2110: goto -85 -> 2025
    //   2113: iload 140
    //   2115: istore 136
    //   2117: aload 5
    //   2119: astore 135
    //   2121: iload 136
    //   2123: iload 137
    //   2125: if_icmpgt -120 -> 2005
    //   2128: new 15	java/lang/String
    //   2131: dup
    //   2132: aload 135
    //   2134: invokespecial 25	java/lang/String:<init>	([C)V
    //   2137: invokevirtual 29	java/lang/String:intern	()Ljava/lang/String;
    //   2140: astore 144
    //   2142: aload_1
    //   2143: bipush 12
    //   2145: aload 144
    //   2147: aastore
    //   2148: bipush 13
    //   2150: istore 145
    //   2152: ldc 55
    //   2154: invokevirtual 21	java/lang/String:toCharArray	()[C
    //   2157: astore 146
    //   2159: aload 146
    //   2161: arraylength
    //   2162: istore 147
    //   2164: iload 147
    //   2166: iconst_1
    //   2167: if_icmpgt +18507 -> 20674
    //   2170: iconst_0
    //   2171: istore 148
    //   2173: aload 146
    //   2175: astore 5
    //   2177: iload 148
    //   2179: istore 6
    //   2181: iload 147
    //   2183: istore 149
    //   2185: aload 146
    //   2187: astore 150
    //   2189: iload 149
    //   2191: istore 151
    //   2193: aload 150
    //   2195: iload 148
    //   2197: caload
    //   2198: istore 31
    //   2200: iload 6
    //   2202: iconst_5
    //   2203: irem
    //   2204: tableswitch	default:+32 -> 2236, 0:+15672->17876, 1:+15679->17883, 2:+15686->17890, 3:+15693->17897
    //   2237: pop
    //   2238: istore 152
    //   2240: iload 152
    //   2242: iload 31
    //   2244: ixor
    //   2245: i2c
    //   2246: istore 153
    //   2248: aload 150
    //   2250: iload 148
    //   2252: iload 153
    //   2254: castore
    //   2255: iload 6
    //   2257: iconst_1
    //   2258: iadd
    //   2259: istore 148
    //   2261: iload 151
    //   2263: ifne +18 -> 2281
    //   2266: aload 5
    //   2268: astore 150
    //   2270: iload 148
    //   2272: istore 154
    //   2274: iload 151
    //   2276: istore 148
    //   2278: goto -85 -> 2193
    //   2281: iload 151
    //   2283: istore 147
    //   2285: aload 5
    //   2287: astore 146
    //   2289: iload 147
    //   2291: iload 148
    //   2293: if_icmpgt -120 -> 2173
    //   2296: new 15	java/lang/String
    //   2299: dup
    //   2300: aload 146
    //   2302: invokespecial 25	java/lang/String:<init>	([C)V
    //   2305: invokevirtual 29	java/lang/String:intern	()Ljava/lang/String;
    //   2308: astore 155
    //   2310: aload_1
    //   2311: iload 145
    //   2313: aload 155
    //   2315: aastore
    //   2316: bipush 14
    //   2318: istore 156
    //   2320: ldc 57
    //   2322: invokevirtual 21	java/lang/String:toCharArray	()[C
    //   2325: astore 157
    //   2327: aload 157
    //   2329: arraylength
    //   2330: istore 158
    //   2332: iload 158
    //   2334: iconst_1
    //   2335: if_icmpgt +18333 -> 20668
    //   2338: iconst_0
    //   2339: istore 159
    //   2341: aload 157
    //   2343: astore 5
    //   2345: iload 159
    //   2347: istore 6
    //   2349: iload 158
    //   2351: istore 160
    //   2353: aload 157
    //   2355: astore 161
    //   2357: iload 160
    //   2359: istore 162
    //   2361: aload 161
    //   2363: iload 159
    //   2365: caload
    //   2366: istore 31
    //   2368: iload 6
    //   2370: iconst_5
    //   2371: irem
    //   2372: tableswitch	default:+32 -> 2404, 0:+15532->17904, 1:+15539->17911, 2:+15546->17918, 3:+15553->17925
    //   2405: pop
    //   2406: istore 163
    //   2408: iload 163
    //   2410: iload 31
    //   2412: ixor
    //   2413: i2c
    //   2414: istore 164
    //   2416: aload 161
    //   2418: iload 159
    //   2420: iload 164
    //   2422: castore
    //   2423: iload 6
    //   2425: iconst_1
    //   2426: iadd
    //   2427: istore 159
    //   2429: iload 162
    //   2431: ifne +18 -> 2449
    //   2434: aload 5
    //   2436: astore 161
    //   2438: iload 159
    //   2440: istore 165
    //   2442: iload 162
    //   2444: istore 159
    //   2446: goto -85 -> 2361
    //   2449: iload 162
    //   2451: istore 158
    //   2453: aload 5
    //   2455: astore 157
    //   2457: iload 158
    //   2459: iload 159
    //   2461: if_icmpgt -120 -> 2341
    //   2464: new 15	java/lang/String
    //   2467: dup
    //   2468: aload 157
    //   2470: invokespecial 25	java/lang/String:<init>	([C)V
    //   2473: invokevirtual 29	java/lang/String:intern	()Ljava/lang/String;
    //   2476: astore 166
    //   2478: aload_1
    //   2479: iload 156
    //   2481: aload 166
    //   2483: aastore
    //   2484: bipush 15
    //   2486: istore 167
    //   2488: ldc 59
    //   2490: invokevirtual 21	java/lang/String:toCharArray	()[C
    //   2493: astore 168
    //   2495: aload 168
    //   2497: arraylength
    //   2498: istore 169
    //   2500: iload 169
    //   2502: iconst_1
    //   2503: if_icmpgt +18159 -> 20662
    //   2506: iconst_0
    //   2507: istore 170
    //   2509: aload 168
    //   2511: astore 5
    //   2513: iload 170
    //   2515: istore 6
    //   2517: iload 169
    //   2519: istore 171
    //   2521: aload 168
    //   2523: astore 172
    //   2525: iload 171
    //   2527: istore 173
    //   2529: aload 172
    //   2531: iload 170
    //   2533: caload
    //   2534: istore 31
    //   2536: iload 6
    //   2538: iconst_5
    //   2539: irem
    //   2540: tableswitch	default:+32 -> 2572, 0:+15392->17932, 1:+15399->17939, 2:+15406->17946, 3:+15413->17953
    //   2573: pop
    //   2574: istore 174
    //   2576: iload 174
    //   2578: iload 31
    //   2580: ixor
    //   2581: i2c
    //   2582: istore 175
    //   2584: aload 172
    //   2586: iload 170
    //   2588: iload 175
    //   2590: castore
    //   2591: iload 6
    //   2593: iconst_1
    //   2594: iadd
    //   2595: istore 170
    //   2597: iload 173
    //   2599: ifne +18 -> 2617
    //   2602: aload 5
    //   2604: astore 172
    //   2606: iload 170
    //   2608: istore 176
    //   2610: iload 173
    //   2612: istore 170
    //   2614: goto -85 -> 2529
    //   2617: iload 173
    //   2619: istore 169
    //   2621: aload 5
    //   2623: astore 168
    //   2625: iload 169
    //   2627: iload 170
    //   2629: if_icmpgt -120 -> 2509
    //   2632: new 15	java/lang/String
    //   2635: dup
    //   2636: aload 168
    //   2638: invokespecial 25	java/lang/String:<init>	([C)V
    //   2641: invokevirtual 29	java/lang/String:intern	()Ljava/lang/String;
    //   2644: astore 177
    //   2646: aload_1
    //   2647: iload 167
    //   2649: aload 177
    //   2651: aastore
    //   2652: bipush 16
    //   2654: istore 178
    //   2656: ldc 61
    //   2658: invokevirtual 21	java/lang/String:toCharArray	()[C
    //   2661: astore 179
    //   2663: aload 179
    //   2665: arraylength
    //   2666: istore 180
    //   2668: iload 180
    //   2670: iconst_1
    //   2671: if_icmpgt +17985 -> 20656
    //   2674: iconst_0
    //   2675: istore 181
    //   2677: aload 179
    //   2679: astore 5
    //   2681: iload 181
    //   2683: istore 6
    //   2685: iload 180
    //   2687: istore 182
    //   2689: aload 179
    //   2691: astore 183
    //   2693: iload 182
    //   2695: istore 184
    //   2697: aload 183
    //   2699: iload 181
    //   2701: caload
    //   2702: istore 31
    //   2704: iload 6
    //   2706: iconst_5
    //   2707: irem
    //   2708: tableswitch	default:+32 -> 2740, 0:+15252->17960, 1:+15259->17967, 2:+15266->17974, 3:+15273->17981
    //   2741: pop
    //   2742: istore 185
    //   2744: iload 185
    //   2746: iload 31
    //   2748: ixor
    //   2749: i2c
    //   2750: istore 186
    //   2752: aload 183
    //   2754: iload 181
    //   2756: iload 186
    //   2758: castore
    //   2759: iload 6
    //   2761: iconst_1
    //   2762: iadd
    //   2763: istore 181
    //   2765: iload 184
    //   2767: ifne +18 -> 2785
    //   2770: aload 5
    //   2772: astore 183
    //   2774: iload 181
    //   2776: istore 187
    //   2778: iload 184
    //   2780: istore 181
    //   2782: goto -85 -> 2697
    //   2785: iload 184
    //   2787: istore 180
    //   2789: aload 5
    //   2791: astore 179
    //   2793: iload 180
    //   2795: iload 181
    //   2797: if_icmpgt -120 -> 2677
    //   2800: new 15	java/lang/String
    //   2803: dup
    //   2804: aload 179
    //   2806: invokespecial 25	java/lang/String:<init>	([C)V
    //   2809: invokevirtual 29	java/lang/String:intern	()Ljava/lang/String;
    //   2812: astore 188
    //   2814: aload_1
    //   2815: iload 178
    //   2817: aload 188
    //   2819: aastore
    //   2820: bipush 17
    //   2822: istore 189
    //   2824: ldc 63
    //   2826: invokevirtual 21	java/lang/String:toCharArray	()[C
    //   2829: astore 190
    //   2831: aload 190
    //   2833: arraylength
    //   2834: istore 191
    //   2836: iload 191
    //   2838: iconst_1
    //   2839: if_icmpgt +17811 -> 20650
    //   2842: iconst_0
    //   2843: istore 192
    //   2845: aload 190
    //   2847: astore 5
    //   2849: iload 192
    //   2851: istore 6
    //   2853: iload 191
    //   2855: istore 193
    //   2857: aload 190
    //   2859: astore 194
    //   2861: iload 193
    //   2863: istore 195
    //   2865: aload 194
    //   2867: iload 192
    //   2869: caload
    //   2870: istore 31
    //   2872: iload 6
    //   2874: iconst_5
    //   2875: irem
    //   2876: tableswitch	default:+32 -> 2908, 0:+15112->17988, 1:+15119->17995, 2:+15126->18002, 3:+15133->18009
    //   2909: pop
    //   2910: istore 196
    //   2912: iload 196
    //   2914: iload 31
    //   2916: ixor
    //   2917: i2c
    //   2918: istore 197
    //   2920: aload 194
    //   2922: iload 192
    //   2924: iload 197
    //   2926: castore
    //   2927: iload 6
    //   2929: iconst_1
    //   2930: iadd
    //   2931: istore 192
    //   2933: iload 195
    //   2935: ifne +18 -> 2953
    //   2938: aload 5
    //   2940: astore 194
    //   2942: iload 192
    //   2944: istore 198
    //   2946: iload 195
    //   2948: istore 192
    //   2950: goto -85 -> 2865
    //   2953: iload 195
    //   2955: istore 191
    //   2957: aload 5
    //   2959: astore 190
    //   2961: iload 191
    //   2963: iload 192
    //   2965: if_icmpgt -120 -> 2845
    //   2968: new 15	java/lang/String
    //   2971: dup
    //   2972: aload 190
    //   2974: invokespecial 25	java/lang/String:<init>	([C)V
    //   2977: invokevirtual 29	java/lang/String:intern	()Ljava/lang/String;
    //   2980: astore 199
    //   2982: aload_1
    //   2983: iload 189
    //   2985: aload 199
    //   2987: aastore
    //   2988: bipush 18
    //   2990: istore 200
    //   2992: ldc 65
    //   2994: invokevirtual 21	java/lang/String:toCharArray	()[C
    //   2997: astore 201
    //   2999: aload 201
    //   3001: arraylength
    //   3002: istore 202
    //   3004: iload 202
    //   3006: iconst_1
    //   3007: if_icmpgt +17637 -> 20644
    //   3010: iconst_0
    //   3011: istore 203
    //   3013: aload 201
    //   3015: astore 5
    //   3017: iload 203
    //   3019: istore 6
    //   3021: iload 202
    //   3023: istore 204
    //   3025: aload 201
    //   3027: astore 205
    //   3029: iload 204
    //   3031: istore 206
    //   3033: aload 205
    //   3035: iload 203
    //   3037: caload
    //   3038: istore 31
    //   3040: iload 6
    //   3042: iconst_5
    //   3043: irem
    //   3044: tableswitch	default:+32 -> 3076, 0:+14972->18016, 1:+14979->18023, 2:+14986->18030, 3:+14993->18037
    //   3077: pop
    //   3078: istore 207
    //   3080: iload 207
    //   3082: iload 31
    //   3084: ixor
    //   3085: i2c
    //   3086: istore 208
    //   3088: aload 205
    //   3090: iload 203
    //   3092: iload 208
    //   3094: castore
    //   3095: iload 6
    //   3097: iconst_1
    //   3098: iadd
    //   3099: istore 203
    //   3101: iload 206
    //   3103: ifne +18 -> 3121
    //   3106: aload 5
    //   3108: astore 205
    //   3110: iload 203
    //   3112: istore 209
    //   3114: iload 206
    //   3116: istore 203
    //   3118: goto -85 -> 3033
    //   3121: iload 206
    //   3123: istore 202
    //   3125: aload 5
    //   3127: astore 201
    //   3129: iload 202
    //   3131: iload 203
    //   3133: if_icmpgt -120 -> 3013
    //   3136: new 15	java/lang/String
    //   3139: dup
    //   3140: aload 201
    //   3142: invokespecial 25	java/lang/String:<init>	([C)V
    //   3145: invokevirtual 29	java/lang/String:intern	()Ljava/lang/String;
    //   3148: astore 210
    //   3150: aload_1
    //   3151: iload 200
    //   3153: aload 210
    //   3155: aastore
    //   3156: bipush 19
    //   3158: istore 211
    //   3160: ldc 67
    //   3162: invokevirtual 21	java/lang/String:toCharArray	()[C
    //   3165: astore 212
    //   3167: aload 212
    //   3169: arraylength
    //   3170: istore 213
    //   3172: iload 213
    //   3174: iconst_1
    //   3175: if_icmpgt +17463 -> 20638
    //   3178: iconst_0
    //   3179: istore 214
    //   3181: aload 212
    //   3183: astore 5
    //   3185: iload 214
    //   3187: istore 6
    //   3189: iload 213
    //   3191: istore 215
    //   3193: aload 212
    //   3195: astore 216
    //   3197: iload 215
    //   3199: istore 217
    //   3201: aload 216
    //   3203: iload 214
    //   3205: caload
    //   3206: istore 31
    //   3208: iload 6
    //   3210: iconst_5
    //   3211: irem
    //   3212: tableswitch	default:+32 -> 3244, 0:+14832->18044, 1:+14839->18051, 2:+14846->18058, 3:+14853->18065
    //   3245: pop
    //   3246: istore 218
    //   3248: iload 218
    //   3250: iload 31
    //   3252: ixor
    //   3253: i2c
    //   3254: istore 219
    //   3256: aload 216
    //   3258: iload 214
    //   3260: iload 219
    //   3262: castore
    //   3263: iload 6
    //   3265: iconst_1
    //   3266: iadd
    //   3267: istore 214
    //   3269: iload 217
    //   3271: ifne +18 -> 3289
    //   3274: aload 5
    //   3276: astore 216
    //   3278: iload 214
    //   3280: istore 220
    //   3282: iload 217
    //   3284: istore 214
    //   3286: goto -85 -> 3201
    //   3289: iload 217
    //   3291: istore 213
    //   3293: aload 5
    //   3295: astore 212
    //   3297: iload 213
    //   3299: iload 214
    //   3301: if_icmpgt -120 -> 3181
    //   3304: new 15	java/lang/String
    //   3307: dup
    //   3308: aload 212
    //   3310: invokespecial 25	java/lang/String:<init>	([C)V
    //   3313: invokevirtual 29	java/lang/String:intern	()Ljava/lang/String;
    //   3316: astore 221
    //   3318: aload_1
    //   3319: iload 211
    //   3321: aload 221
    //   3323: aastore
    //   3324: bipush 20
    //   3326: istore 222
    //   3328: ldc 69
    //   3330: invokevirtual 21	java/lang/String:toCharArray	()[C
    //   3333: astore 223
    //   3335: aload 223
    //   3337: arraylength
    //   3338: istore 224
    //   3340: iload 224
    //   3342: iconst_1
    //   3343: if_icmpgt +17289 -> 20632
    //   3346: iconst_0
    //   3347: istore 225
    //   3349: aload 223
    //   3351: astore 5
    //   3353: iload 225
    //   3355: istore 6
    //   3357: iload 224
    //   3359: istore 226
    //   3361: aload 223
    //   3363: astore 227
    //   3365: iload 226
    //   3367: istore 228
    //   3369: aload 227
    //   3371: iload 225
    //   3373: caload
    //   3374: istore 31
    //   3376: iload 6
    //   3378: iconst_5
    //   3379: irem
    //   3380: tableswitch	default:+32 -> 3412, 0:+14692->18072, 1:+14699->18079, 2:+14706->18086, 3:+14713->18093
    //   3413: pop
    //   3414: istore 229
    //   3416: iload 229
    //   3418: iload 31
    //   3420: ixor
    //   3421: i2c
    //   3422: istore 230
    //   3424: aload 227
    //   3426: iload 225
    //   3428: iload 230
    //   3430: castore
    //   3431: iload 6
    //   3433: iconst_1
    //   3434: iadd
    //   3435: istore 225
    //   3437: iload 228
    //   3439: ifne +18 -> 3457
    //   3442: aload 5
    //   3444: astore 227
    //   3446: iload 225
    //   3448: istore 231
    //   3450: iload 228
    //   3452: istore 225
    //   3454: goto -85 -> 3369
    //   3457: iload 228
    //   3459: istore 224
    //   3461: aload 5
    //   3463: astore 223
    //   3465: iload 224
    //   3467: iload 225
    //   3469: if_icmpgt -120 -> 3349
    //   3472: new 15	java/lang/String
    //   3475: dup
    //   3476: aload 223
    //   3478: invokespecial 25	java/lang/String:<init>	([C)V
    //   3481: invokevirtual 29	java/lang/String:intern	()Ljava/lang/String;
    //   3484: astore 232
    //   3486: aload_1
    //   3487: iload 222
    //   3489: aload 232
    //   3491: aastore
    //   3492: bipush 21
    //   3494: istore 233
    //   3496: ldc 71
    //   3498: invokevirtual 21	java/lang/String:toCharArray	()[C
    //   3501: astore 234
    //   3503: aload 234
    //   3505: arraylength
    //   3506: istore 235
    //   3508: iload 235
    //   3510: iconst_1
    //   3511: if_icmpgt +17115 -> 20626
    //   3514: iconst_0
    //   3515: istore 236
    //   3517: aload 234
    //   3519: astore 5
    //   3521: iload 236
    //   3523: istore 6
    //   3525: iload 235
    //   3527: istore 237
    //   3529: aload 234
    //   3531: astore 238
    //   3533: iload 237
    //   3535: istore 239
    //   3537: aload 238
    //   3539: iload 236
    //   3541: caload
    //   3542: istore 31
    //   3544: iload 6
    //   3546: iconst_5
    //   3547: irem
    //   3548: tableswitch	default:+32 -> 3580, 0:+14552->18100, 1:+14559->18107, 2:+14566->18114, 3:+14573->18121
    //   3581: pop
    //   3582: istore 240
    //   3584: iload 240
    //   3586: iload 31
    //   3588: ixor
    //   3589: i2c
    //   3590: istore 241
    //   3592: aload 238
    //   3594: iload 236
    //   3596: iload 241
    //   3598: castore
    //   3599: iload 6
    //   3601: iconst_1
    //   3602: iadd
    //   3603: istore 236
    //   3605: iload 239
    //   3607: ifne +18 -> 3625
    //   3610: aload 5
    //   3612: astore 238
    //   3614: iload 236
    //   3616: istore 242
    //   3618: iload 239
    //   3620: istore 236
    //   3622: goto -85 -> 3537
    //   3625: iload 239
    //   3627: istore 235
    //   3629: aload 5
    //   3631: astore 234
    //   3633: iload 235
    //   3635: iload 236
    //   3637: if_icmpgt -120 -> 3517
    //   3640: new 15	java/lang/String
    //   3643: dup
    //   3644: aload 234
    //   3646: invokespecial 25	java/lang/String:<init>	([C)V
    //   3649: invokevirtual 29	java/lang/String:intern	()Ljava/lang/String;
    //   3652: astore 243
    //   3654: aload_1
    //   3655: iload 233
    //   3657: aload 243
    //   3659: aastore
    //   3660: bipush 22
    //   3662: istore 244
    //   3664: ldc 73
    //   3666: invokevirtual 21	java/lang/String:toCharArray	()[C
    //   3669: astore 245
    //   3671: aload 245
    //   3673: arraylength
    //   3674: istore 246
    //   3676: iload 246
    //   3678: iconst_1
    //   3679: if_icmpgt +16941 -> 20620
    //   3682: iconst_0
    //   3683: istore 247
    //   3685: aload 245
    //   3687: astore 5
    //   3689: iload 247
    //   3691: istore 6
    //   3693: iload 246
    //   3695: istore 248
    //   3697: aload 245
    //   3699: astore 249
    //   3701: iload 248
    //   3703: istore 250
    //   3705: aload 249
    //   3707: iload 247
    //   3709: caload
    //   3710: istore 31
    //   3712: iload 6
    //   3714: iconst_5
    //   3715: irem
    //   3716: tableswitch	default:+32 -> 3748, 0:+14412->18128, 1:+14419->18135, 2:+14426->18142, 3:+14433->18149
    //   3749: pop
    //   3750: istore 251
    //   3752: iload 251
    //   3754: iload 31
    //   3756: ixor
    //   3757: i2c
    //   3758: istore 252
    //   3760: aload 249
    //   3762: iload 247
    //   3764: iload 252
    //   3766: castore
    //   3767: iload 6
    //   3769: iconst_1
    //   3770: iadd
    //   3771: istore 247
    //   3773: iload 250
    //   3775: ifne +18 -> 3793
    //   3778: aload 5
    //   3780: astore 249
    //   3782: iload 247
    //   3784: istore 253
    //   3786: iload 250
    //   3788: istore 247
    //   3790: goto -85 -> 3705
    //   3793: iload 250
    //   3795: istore 246
    //   3797: aload 5
    //   3799: astore 245
    //   3801: iload 246
    //   3803: iload 247
    //   3805: if_icmpgt -120 -> 3685
    //   3808: new 15	java/lang/String
    //   3811: dup
    //   3812: aload 245
    //   3814: invokespecial 25	java/lang/String:<init>	([C)V
    //   3817: invokevirtual 29	java/lang/String:intern	()Ljava/lang/String;
    //   3820: astore 254
    //   3822: aload_1
    //   3823: iload 244
    //   3825: aload 254
    //   3827: aastore
    //   3828: bipush 23
    //   3830: istore 255
    //   3832: ldc 75
    //   3834: invokevirtual 21	java/lang/String:toCharArray	()[C
    //   3837: wide
    //   3841: wide
    //   3845: arraylength
    //   3846: wide
    //   3850: wide
    //   3854: iconst_1
    //   3855: if_icmpgt +16757 -> 20612
    //   3858: iconst_0
    //   3859: wide
    //   3863: wide
    //   3867: astore 5
    //   3869: wide
    //   3873: istore 6
    //   3875: wide
    //   3879: wide
    //   3883: wide
    //   3887: wide
    //   3891: wide
    //   3895: wide
    //   3899: wide
    //   3903: wide
    //   3907: caload
    //   3908: istore 31
    //   3910: iload 6
    //   3912: iconst_5
    //   3913: irem
    //   3914: tableswitch	default:+30 -> 3944, 0:+14242->18156, 1:+14251->18165, 2:+14260->18174, 3:+14269->18183
    //   3945: pop
    //   3946: wide
    //   3950: wide
    //   3954: iload 31
    //   3956: ixor
    //   3957: i2c
    //   3958: wide
    //   3962: wide
    //   3966: wide
    //   3970: wide
    //   3974: castore
    //   3975: iload 6
    //   3977: iconst_1
    //   3978: iadd
    //   3979: wide
    //   3983: wide
    //   3987: ifne +28 -> 4015
    //   3990: aload 5
    //   3992: wide
    //   3996: wide
    //   4000: wide
    //   4004: wide
    //   4008: wide
    //   4012: goto -113 -> 3899
    //   4015: wide
    //   4019: wide
    //   4023: aload 5
    //   4025: wide
    //   4029: wide
    //   4033: wide
    //   4037: if_icmpgt -174 -> 3863
    //   4040: new 15	java/lang/String
    //   4043: dup
    //   4044: wide
    //   4048: invokespecial 25	java/lang/String:<init>	([C)V
    //   4051: invokevirtual 29	java/lang/String:intern	()Ljava/lang/String;
    //   4054: wide
    //   4058: aload_1
    //   4059: iload 255
    //   4061: wide
    //   4065: aastore
    //   4066: bipush 24
    //   4068: wide
    //   4072: ldc 77
    //   4074: invokevirtual 21	java/lang/String:toCharArray	()[C
    //   4077: wide
    //   4081: wide
    //   4085: arraylength
    //   4086: wide
    //   4090: wide
    //   4094: iconst_1
    //   4095: if_icmpgt +16509 -> 20604
    //   4098: iconst_0
    //   4099: wide
    //   4103: wide
    //   4107: astore 5
    //   4109: wide
    //   4113: istore 6
    //   4115: wide
    //   4119: wide
    //   4123: wide
    //   4127: wide
    //   4131: wide
    //   4135: wide
    //   4139: wide
    //   4143: wide
    //   4147: caload
    //   4148: istore 31
    //   4150: iload 6
    //   4152: iconst_5
    //   4153: irem
    //   4154: tableswitch	default:+30 -> 4184, 0:+14038->18192, 1:+14047->18201, 2:+14056->18210, 3:+14065->18219
    //   4185: pop
    //   4186: wide
    //   4190: wide
    //   4194: iload 31
    //   4196: ixor
    //   4197: i2c
    //   4198: wide
    //   4202: wide
    //   4206: wide
    //   4210: wide
    //   4214: castore
    //   4215: iload 6
    //   4217: iconst_1
    //   4218: iadd
    //   4219: wide
    //   4223: wide
    //   4227: ifne +28 -> 4255
    //   4230: aload 5
    //   4232: wide
    //   4236: wide
    //   4240: wide
    //   4244: wide
    //   4248: wide
    //   4252: goto -113 -> 4139
    //   4255: wide
    //   4259: wide
    //   4263: aload 5
    //   4265: wide
    //   4269: wide
    //   4273: wide
    //   4277: if_icmpgt -174 -> 4103
    //   4280: new 15	java/lang/String
    //   4283: dup
    //   4284: wide
    //   4288: invokespecial 25	java/lang/String:<init>	([C)V
    //   4291: invokevirtual 29	java/lang/String:intern	()Ljava/lang/String;
    //   4294: wide
    //   4298: aload_1
    //   4299: wide
    //   4303: wide
    //   4307: aastore
    //   4308: bipush 25
    //   4310: wide
    //   4314: ldc 79
    //   4316: invokevirtual 21	java/lang/String:toCharArray	()[C
    //   4319: wide
    //   4323: wide
    //   4327: arraylength
    //   4328: wide
    //   4332: wide
    //   4336: iconst_1
    //   4337: if_icmpgt +16259 -> 20596
    //   4340: iconst_0
    //   4341: wide
    //   4345: wide
    //   4349: astore 5
    //   4351: wide
    //   4355: istore 6
    //   4357: wide
    //   4361: wide
    //   4365: wide
    //   4369: wide
    //   4373: wide
    //   4377: wide
    //   4381: wide
    //   4385: wide
    //   4389: caload
    //   4390: istore 31
    //   4392: iload 6
    //   4394: iconst_5
    //   4395: irem
    //   4396: tableswitch	default:+32 -> 4428, 0:+13832->18228, 1:+13841->18237, 2:+13850->18246, 3:+13859->18255
    //   4429: pop
    //   4430: wide
    //   4434: wide
    //   4438: iload 31
    //   4440: ixor
    //   4441: i2c
    //   4442: wide
    //   4446: wide
    //   4450: wide
    //   4454: wide
    //   4458: castore
    //   4459: iload 6
    //   4461: iconst_1
    //   4462: iadd
    //   4463: wide
    //   4467: wide
    //   4471: ifne +28 -> 4499
    //   4474: aload 5
    //   4476: wide
    //   4480: wide
    //   4484: wide
    //   4488: wide
    //   4492: wide
    //   4496: goto -115 -> 4381
    //   4499: wide
    //   4503: wide
    //   4507: aload 5
    //   4509: wide
    //   4513: wide
    //   4517: wide
    //   4521: if_icmpgt -176 -> 4345
    //   4524: new 15	java/lang/String
    //   4527: dup
    //   4528: wide
    //   4532: invokespecial 25	java/lang/String:<init>	([C)V
    //   4535: invokevirtual 29	java/lang/String:intern	()Ljava/lang/String;
    //   4538: wide
    //   4542: aload_1
    //   4543: wide
    //   4547: wide
    //   4551: aastore
    //   4552: bipush 26
    //   4554: wide
    //   4558: ldc 81
    //   4560: invokevirtual 21	java/lang/String:toCharArray	()[C
    //   4563: wide
    //   4567: wide
    //   4571: arraylength
    //   4572: wide
    //   4576: wide
    //   4580: iconst_1
    //   4581: if_icmpgt +16007 -> 20588
    //   4584: iconst_0
    //   4585: wide
    //   4589: wide
    //   4593: astore 5
    //   4595: wide
    //   4599: istore 6
    //   4601: wide
    //   4605: wide
    //   4609: wide
    //   4613: wide
    //   4617: wide
    //   4621: wide
    //   4625: wide
    //   4629: wide
    //   4633: caload
    //   4634: istore 31
    //   4636: iload 6
    //   4638: iconst_5
    //   4639: irem
    //   4640: tableswitch	default:+32 -> 4672, 0:+13624->18264, 1:+13633->18273, 2:+13642->18282, 3:+13651->18291
    //   4673: pop
    //   4674: wide
    //   4678: wide
    //   4682: iload 31
    //   4684: ixor
    //   4685: i2c
    //   4686: wide
    //   4690: wide
    //   4694: wide
    //   4698: wide
    //   4702: castore
    //   4703: iload 6
    //   4705: iconst_1
    //   4706: iadd
    //   4707: wide
    //   4711: wide
    //   4715: ifne +28 -> 4743
    //   4718: aload 5
    //   4720: wide
    //   4724: wide
    //   4728: wide
    //   4732: wide
    //   4736: wide
    //   4740: goto -115 -> 4625
    //   4743: wide
    //   4747: wide
    //   4751: aload 5
    //   4753: wide
    //   4757: wide
    //   4761: wide
    //   4765: if_icmpgt -176 -> 4589
    //   4768: new 15	java/lang/String
    //   4771: dup
    //   4772: wide
    //   4776: invokespecial 25	java/lang/String:<init>	([C)V
    //   4779: invokevirtual 29	java/lang/String:intern	()Ljava/lang/String;
    //   4782: wide
    //   4786: aload_1
    //   4787: wide
    //   4791: wide
    //   4795: aastore
    //   4796: bipush 27
    //   4798: wide
    //   4802: ldc 83
    //   4804: invokevirtual 21	java/lang/String:toCharArray	()[C
    //   4807: wide
    //   4811: wide
    //   4815: arraylength
    //   4816: wide
    //   4820: wide
    //   4824: iconst_1
    //   4825: if_icmpgt +15755 -> 20580
    //   4828: iconst_0
    //   4829: wide
    //   4833: wide
    //   4837: astore 5
    //   4839: wide
    //   4843: istore 6
    //   4845: wide
    //   4849: wide
    //   4853: wide
    //   4857: wide
    //   4861: wide
    //   4865: wide
    //   4869: wide
    //   4873: wide
    //   4877: caload
    //   4878: istore 31
    //   4880: iload 6
    //   4882: iconst_5
    //   4883: irem
    //   4884: tableswitch	default:+32 -> 4916, 0:+13416->18300, 1:+13425->18309, 2:+13434->18318, 3:+13443->18327
    //   4917: pop
    //   4918: wide
    //   4922: wide
    //   4926: iload 31
    //   4928: ixor
    //   4929: i2c
    //   4930: wide
    //   4934: wide
    //   4938: wide
    //   4942: wide
    //   4946: castore
    //   4947: iload 6
    //   4949: iconst_1
    //   4950: iadd
    //   4951: wide
    //   4955: wide
    //   4959: ifne +28 -> 4987
    //   4962: aload 5
    //   4964: wide
    //   4968: wide
    //   4972: wide
    //   4976: wide
    //   4980: wide
    //   4984: goto -115 -> 4869
    //   4987: wide
    //   4991: wide
    //   4995: aload 5
    //   4997: wide
    //   5001: wide
    //   5005: wide
    //   5009: if_icmpgt -176 -> 4833
    //   5012: new 15	java/lang/String
    //   5015: dup
    //   5016: wide
    //   5020: invokespecial 25	java/lang/String:<init>	([C)V
    //   5023: invokevirtual 29	java/lang/String:intern	()Ljava/lang/String;
    //   5026: wide
    //   5030: aload_1
    //   5031: wide
    //   5035: wide
    //   5039: aastore
    //   5040: bipush 28
    //   5042: wide
    //   5046: ldc 85
    //   5048: invokevirtual 21	java/lang/String:toCharArray	()[C
    //   5051: wide
    //   5055: wide
    //   5059: arraylength
    //   5060: wide
    //   5064: wide
    //   5068: iconst_1
    //   5069: if_icmpgt +15503 -> 20572
    //   5072: iconst_0
    //   5073: wide
    //   5077: wide
    //   5081: astore 5
    //   5083: wide
    //   5087: istore 6
    //   5089: wide
    //   5093: wide
    //   5097: wide
    //   5101: wide
    //   5105: wide
    //   5109: wide
    //   5113: wide
    //   5117: wide
    //   5121: caload
    //   5122: istore 31
    //   5124: iload 6
    //   5126: iconst_5
    //   5127: irem
    //   5128: tableswitch	default:+32 -> 5160, 0:+13208->18336, 1:+13217->18345, 2:+13226->18354, 3:+13235->18363
    //   5161: pop
    //   5162: wide
    //   5166: wide
    //   5170: iload 31
    //   5172: ixor
    //   5173: i2c
    //   5174: wide
    //   5178: wide
    //   5182: wide
    //   5186: wide
    //   5190: castore
    //   5191: iload 6
    //   5193: iconst_1
    //   5194: iadd
    //   5195: wide
    //   5199: wide
    //   5203: ifne +28 -> 5231
    //   5206: aload 5
    //   5208: wide
    //   5212: wide
    //   5216: wide
    //   5220: wide
    //   5224: wide
    //   5228: goto -115 -> 5113
    //   5231: wide
    //   5235: wide
    //   5239: aload 5
    //   5241: wide
    //   5245: wide
    //   5249: wide
    //   5253: if_icmpgt -176 -> 5077
    //   5256: new 15	java/lang/String
    //   5259: dup
    //   5260: wide
    //   5264: invokespecial 25	java/lang/String:<init>	([C)V
    //   5267: invokevirtual 29	java/lang/String:intern	()Ljava/lang/String;
    //   5270: wide
    //   5274: aload_1
    //   5275: wide
    //   5279: wide
    //   5283: aastore
    //   5284: bipush 29
    //   5286: wide
    //   5290: ldc 87
    //   5292: invokevirtual 21	java/lang/String:toCharArray	()[C
    //   5295: wide
    //   5299: wide
    //   5303: arraylength
    //   5304: wide
    //   5308: wide
    //   5312: iconst_1
    //   5313: if_icmpgt +15251 -> 20564
    //   5316: iconst_0
    //   5317: wide
    //   5321: wide
    //   5325: astore 5
    //   5327: wide
    //   5331: istore 6
    //   5333: wide
    //   5337: wide
    //   5341: wide
    //   5345: wide
    //   5349: wide
    //   5353: wide
    //   5357: wide
    //   5361: wide
    //   5365: caload
    //   5366: istore 31
    //   5368: iload 6
    //   5370: iconst_5
    //   5371: irem
    //   5372: tableswitch	default:+32 -> 5404, 0:+13000->18372, 1:+13009->18381, 2:+13018->18390, 3:+13027->18399
    //   5405: pop
    //   5406: wide
    //   5410: wide
    //   5414: iload 31
    //   5416: ixor
    //   5417: i2c
    //   5418: wide
    //   5422: wide
    //   5426: wide
    //   5430: wide
    //   5434: castore
    //   5435: iload 6
    //   5437: iconst_1
    //   5438: iadd
    //   5439: wide
    //   5443: wide
    //   5447: ifne +28 -> 5475
    //   5450: aload 5
    //   5452: wide
    //   5456: wide
    //   5460: wide
    //   5464: wide
    //   5468: wide
    //   5472: goto -115 -> 5357
    //   5475: wide
    //   5479: wide
    //   5483: aload 5
    //   5485: wide
    //   5489: wide
    //   5493: wide
    //   5497: if_icmpgt -176 -> 5321
    //   5500: new 15	java/lang/String
    //   5503: dup
    //   5504: wide
    //   5508: invokespecial 25	java/lang/String:<init>	([C)V
    //   5511: invokevirtual 29	java/lang/String:intern	()Ljava/lang/String;
    //   5514: wide
    //   5518: aload_1
    //   5519: wide
    //   5523: wide
    //   5527: aastore
    //   5528: bipush 30
    //   5530: wide
    //   5534: ldc 89
    //   5536: invokevirtual 21	java/lang/String:toCharArray	()[C
    //   5539: wide
    //   5543: wide
    //   5547: arraylength
    //   5548: wide
    //   5552: wide
    //   5556: iconst_1
    //   5557: if_icmpgt +14999 -> 20556
    //   5560: iconst_0
    //   5561: wide
    //   5565: wide
    //   5569: astore 5
    //   5571: wide
    //   5575: istore 6
    //   5577: wide
    //   5581: wide
    //   5585: wide
    //   5589: wide
    //   5593: wide
    //   5597: wide
    //   5601: wide
    //   5605: wide
    //   5609: caload
    //   5610: istore 31
    //   5612: iload 6
    //   5614: iconst_5
    //   5615: irem
    //   5616: tableswitch	default:+32 -> 5648, 0:+12792->18408, 1:+12801->18417, 2:+12810->18426, 3:+12819->18435
    //   5649: pop
    //   5650: wide
    //   5654: wide
    //   5658: iload 31
    //   5660: ixor
    //   5661: i2c
    //   5662: wide
    //   5666: wide
    //   5670: wide
    //   5674: wide
    //   5678: castore
    //   5679: iload 6
    //   5681: iconst_1
    //   5682: iadd
    //   5683: wide
    //   5687: wide
    //   5691: ifne +28 -> 5719
    //   5694: aload 5
    //   5696: wide
    //   5700: wide
    //   5704: wide
    //   5708: wide
    //   5712: wide
    //   5716: goto -115 -> 5601
    //   5719: wide
    //   5723: wide
    //   5727: aload 5
    //   5729: wide
    //   5733: wide
    //   5737: wide
    //   5741: if_icmpgt -176 -> 5565
    //   5744: new 15	java/lang/String
    //   5747: dup
    //   5748: wide
    //   5752: invokespecial 25	java/lang/String:<init>	([C)V
    //   5755: invokevirtual 29	java/lang/String:intern	()Ljava/lang/String;
    //   5758: wide
    //   5762: aload_1
    //   5763: wide
    //   5767: wide
    //   5771: aastore
    //   5772: bipush 31
    //   5774: wide
    //   5778: ldc 91
    //   5780: invokevirtual 21	java/lang/String:toCharArray	()[C
    //   5783: wide
    //   5787: wide
    //   5791: arraylength
    //   5792: wide
    //   5796: wide
    //   5800: iconst_1
    //   5801: if_icmpgt +14747 -> 20548
    //   5804: iconst_0
    //   5805: wide
    //   5809: wide
    //   5813: astore 5
    //   5815: wide
    //   5819: istore 6
    //   5821: wide
    //   5825: wide
    //   5829: wide
    //   5833: wide
    //   5837: wide
    //   5841: wide
    //   5845: wide
    //   5849: wide
    //   5853: caload
    //   5854: istore 31
    //   5856: iload 6
    //   5858: iconst_5
    //   5859: irem
    //   5860: tableswitch	default:+32 -> 5892, 0:+12584->18444, 1:+12593->18453, 2:+12602->18462, 3:+12611->18471
    //   5893: pop
    //   5894: wide
    //   5898: wide
    //   5902: iload 31
    //   5904: ixor
    //   5905: i2c
    //   5906: wide
    //   5910: wide
    //   5914: wide
    //   5918: wide
    //   5922: castore
    //   5923: iload 6
    //   5925: iconst_1
    //   5926: iadd
    //   5927: wide
    //   5931: wide
    //   5935: ifne +28 -> 5963
    //   5938: aload 5
    //   5940: wide
    //   5944: wide
    //   5948: wide
    //   5952: wide
    //   5956: wide
    //   5960: goto -115 -> 5845
    //   5963: wide
    //   5967: wide
    //   5971: aload 5
    //   5973: wide
    //   5977: wide
    //   5981: wide
    //   5985: if_icmpgt -176 -> 5809
    //   5988: new 15	java/lang/String
    //   5991: dup
    //   5992: wide
    //   5996: invokespecial 25	java/lang/String:<init>	([C)V
    //   5999: invokevirtual 29	java/lang/String:intern	()Ljava/lang/String;
    //   6002: wide
    //   6006: aload_1
    //   6007: wide
    //   6011: wide
    //   6015: aastore
    //   6016: bipush 32
    //   6018: wide
    //   6022: ldc 93
    //   6024: invokevirtual 21	java/lang/String:toCharArray	()[C
    //   6027: wide
    //   6031: wide
    //   6035: arraylength
    //   6036: wide
    //   6040: wide
    //   6044: iconst_1
    //   6045: if_icmpgt +14495 -> 20540
    //   6048: iconst_0
    //   6049: wide
    //   6053: wide
    //   6057: astore 5
    //   6059: wide
    //   6063: istore 6
    //   6065: wide
    //   6069: wide
    //   6073: wide
    //   6077: wide
    //   6081: wide
    //   6085: wide
    //   6089: wide
    //   6093: wide
    //   6097: caload
    //   6098: istore 31
    //   6100: iload 6
    //   6102: iconst_5
    //   6103: irem
    //   6104: tableswitch	default:+32 -> 6136, 0:+12376->18480, 1:+12385->18489, 2:+12394->18498, 3:+12403->18507
    //   6137: pop
    //   6138: wide
    //   6142: wide
    //   6146: iload 31
    //   6148: ixor
    //   6149: i2c
    //   6150: wide
    //   6154: wide
    //   6158: wide
    //   6162: wide
    //   6166: castore
    //   6167: iload 6
    //   6169: iconst_1
    //   6170: iadd
    //   6171: wide
    //   6175: wide
    //   6179: ifne +28 -> 6207
    //   6182: aload 5
    //   6184: wide
    //   6188: wide
    //   6192: wide
    //   6196: wide
    //   6200: wide
    //   6204: goto -115 -> 6089
    //   6207: wide
    //   6211: wide
    //   6215: aload 5
    //   6217: wide
    //   6221: wide
    //   6225: wide
    //   6229: if_icmpgt -176 -> 6053
    //   6232: new 15	java/lang/String
    //   6235: dup
    //   6236: wide
    //   6240: invokespecial 25	java/lang/String:<init>	([C)V
    //   6243: invokevirtual 29	java/lang/String:intern	()Ljava/lang/String;
    //   6246: wide
    //   6250: aload_1
    //   6251: wide
    //   6255: wide
    //   6259: aastore
    //   6260: bipush 33
    //   6262: wide
    //   6266: ldc 95
    //   6268: invokevirtual 21	java/lang/String:toCharArray	()[C
    //   6271: wide
    //   6275: wide
    //   6279: arraylength
    //   6280: wide
    //   6284: wide
    //   6288: iconst_1
    //   6289: if_icmpgt +14243 -> 20532
    //   6292: iconst_0
    //   6293: wide
    //   6297: wide
    //   6301: astore 5
    //   6303: wide
    //   6307: istore 6
    //   6309: wide
    //   6313: wide
    //   6317: wide
    //   6321: wide
    //   6325: wide
    //   6329: wide
    //   6333: wide
    //   6337: wide
    //   6341: caload
    //   6342: istore 31
    //   6344: iload 6
    //   6346: iconst_5
    //   6347: irem
    //   6348: tableswitch	default:+32 -> 6380, 0:+12168->18516, 1:+12177->18525, 2:+12186->18534, 3:+12195->18543
    //   6381: pop
    //   6382: wide
    //   6386: wide
    //   6390: iload 31
    //   6392: ixor
    //   6393: i2c
    //   6394: wide
    //   6398: wide
    //   6402: wide
    //   6406: wide
    //   6410: castore
    //   6411: iload 6
    //   6413: iconst_1
    //   6414: iadd
    //   6415: wide
    //   6419: wide
    //   6423: ifne +28 -> 6451
    //   6426: aload 5
    //   6428: wide
    //   6432: wide
    //   6436: wide
    //   6440: wide
    //   6444: wide
    //   6448: goto -115 -> 6333
    //   6451: wide
    //   6455: wide
    //   6459: aload 5
    //   6461: wide
    //   6465: wide
    //   6469: wide
    //   6473: if_icmpgt -176 -> 6297
    //   6476: new 15	java/lang/String
    //   6479: dup
    //   6480: wide
    //   6484: invokespecial 25	java/lang/String:<init>	([C)V
    //   6487: invokevirtual 29	java/lang/String:intern	()Ljava/lang/String;
    //   6490: wide
    //   6494: aload_1
    //   6495: wide
    //   6499: wide
    //   6503: aastore
    //   6504: bipush 34
    //   6506: wide
    //   6510: ldc 97
    //   6512: invokevirtual 21	java/lang/String:toCharArray	()[C
    //   6515: wide
    //   6519: wide
    //   6523: arraylength
    //   6524: wide
    //   6528: wide
    //   6532: iconst_1
    //   6533: if_icmpgt +13991 -> 20524
    //   6536: iconst_0
    //   6537: wide
    //   6541: wide
    //   6545: astore 5
    //   6547: wide
    //   6551: istore 6
    //   6553: wide
    //   6557: wide
    //   6561: wide
    //   6565: wide
    //   6569: wide
    //   6573: wide
    //   6577: wide
    //   6581: wide
    //   6585: caload
    //   6586: istore 31
    //   6588: iload 6
    //   6590: iconst_5
    //   6591: irem
    //   6592: tableswitch	default:+32 -> 6624, 0:+11960->18552, 1:+11969->18561, 2:+11978->18570, 3:+11987->18579
    //   6625: pop
    //   6626: wide
    //   6630: wide
    //   6634: iload 31
    //   6636: ixor
    //   6637: i2c
    //   6638: wide
    //   6642: wide
    //   6646: wide
    //   6650: wide
    //   6654: castore
    //   6655: iload 6
    //   6657: iconst_1
    //   6658: iadd
    //   6659: wide
    //   6663: wide
    //   6667: ifne +28 -> 6695
    //   6670: aload 5
    //   6672: wide
    //   6676: wide
    //   6680: wide
    //   6684: wide
    //   6688: wide
    //   6692: goto -115 -> 6577
    //   6695: wide
    //   6699: wide
    //   6703: aload 5
    //   6705: wide
    //   6709: wide
    //   6713: wide
    //   6717: if_icmpgt -176 -> 6541
    //   6720: new 15	java/lang/String
    //   6723: dup
    //   6724: wide
    //   6728: invokespecial 25	java/lang/String:<init>	([C)V
    //   6731: invokevirtual 29	java/lang/String:intern	()Ljava/lang/String;
    //   6734: wide
    //   6738: aload_1
    //   6739: wide
    //   6743: wide
    //   6747: aastore
    //   6748: bipush 35
    //   6750: wide
    //   6754: ldc 99
    //   6756: invokevirtual 21	java/lang/String:toCharArray	()[C
    //   6759: wide
    //   6763: wide
    //   6767: arraylength
    //   6768: wide
    //   6772: wide
    //   6776: iconst_1
    //   6777: if_icmpgt +13739 -> 20516
    //   6780: iconst_0
    //   6781: wide
    //   6785: wide
    //   6789: astore 5
    //   6791: wide
    //   6795: istore 6
    //   6797: wide
    //   6801: wide
    //   6805: wide
    //   6809: wide
    //   6813: wide
    //   6817: wide
    //   6821: wide
    //   6825: wide
    //   6829: caload
    //   6830: istore 31
    //   6832: iload 6
    //   6834: iconst_5
    //   6835: irem
    //   6836: tableswitch	default:+32 -> 6868, 0:+11752->18588, 1:+11761->18597, 2:+11770->18606, 3:+11779->18615
    //   6869: pop
    //   6870: wide
    //   6874: wide
    //   6878: iload 31
    //   6880: ixor
    //   6881: i2c
    //   6882: wide
    //   6886: wide
    //   6890: wide
    //   6894: wide
    //   6898: castore
    //   6899: iload 6
    //   6901: iconst_1
    //   6902: iadd
    //   6903: wide
    //   6907: wide
    //   6911: ifne +28 -> 6939
    //   6914: aload 5
    //   6916: wide
    //   6920: wide
    //   6924: wide
    //   6928: wide
    //   6932: wide
    //   6936: goto -115 -> 6821
    //   6939: wide
    //   6943: wide
    //   6947: aload 5
    //   6949: wide
    //   6953: wide
    //   6957: wide
    //   6961: if_icmpgt -176 -> 6785
    //   6964: new 15	java/lang/String
    //   6967: dup
    //   6968: wide
    //   6972: invokespecial 25	java/lang/String:<init>	([C)V
    //   6975: invokevirtual 29	java/lang/String:intern	()Ljava/lang/String;
    //   6978: wide
    //   6982: aload_1
    //   6983: wide
    //   6987: wide
    //   6991: aastore
    //   6992: bipush 36
    //   6994: wide
    //   6998: ldc 101
    //   7000: invokevirtual 21	java/lang/String:toCharArray	()[C
    //   7003: wide
    //   7007: wide
    //   7011: arraylength
    //   7012: wide
    //   7016: wide
    //   7020: iconst_1
    //   7021: if_icmpgt +13487 -> 20508
    //   7024: iconst_0
    //   7025: wide
    //   7029: wide
    //   7033: astore 5
    //   7035: wide
    //   7039: istore 6
    //   7041: wide
    //   7045: wide
    //   7049: wide
    //   7053: wide
    //   7057: wide
    //   7061: wide
    //   7065: wide
    //   7069: wide
    //   7073: caload
    //   7074: istore 31
    //   7076: iload 6
    //   7078: iconst_5
    //   7079: irem
    //   7080: tableswitch	default:+32 -> 7112, 0:+11544->18624, 1:+11553->18633, 2:+11562->18642, 3:+11571->18651
    //   7113: pop
    //   7114: wide
    //   7118: wide
    //   7122: iload 31
    //   7124: ixor
    //   7125: i2c
    //   7126: wide
    //   7130: wide
    //   7134: wide
    //   7138: wide
    //   7142: castore
    //   7143: iload 6
    //   7145: iconst_1
    //   7146: iadd
    //   7147: wide
    //   7151: wide
    //   7155: ifne +28 -> 7183
    //   7158: aload 5
    //   7160: wide
    //   7164: wide
    //   7168: wide
    //   7172: wide
    //   7176: wide
    //   7180: goto -115 -> 7065
    //   7183: wide
    //   7187: wide
    //   7191: aload 5
    //   7193: wide
    //   7197: wide
    //   7201: wide
    //   7205: if_icmpgt -176 -> 7029
    //   7208: new 15	java/lang/String
    //   7211: dup
    //   7212: wide
    //   7216: invokespecial 25	java/lang/String:<init>	([C)V
    //   7219: invokevirtual 29	java/lang/String:intern	()Ljava/lang/String;
    //   7222: wide
    //   7226: aload_1
    //   7227: wide
    //   7231: wide
    //   7235: aastore
    //   7236: bipush 37
    //   7238: wide
    //   7242: ldc 103
    //   7244: invokevirtual 21	java/lang/String:toCharArray	()[C
    //   7247: wide
    //   7251: wide
    //   7255: arraylength
    //   7256: wide
    //   7260: wide
    //   7264: iconst_1
    //   7265: if_icmpgt +13235 -> 20500
    //   7268: iconst_0
    //   7269: wide
    //   7273: wide
    //   7277: astore 5
    //   7279: wide
    //   7283: istore 6
    //   7285: wide
    //   7289: wide
    //   7293: wide
    //   7297: wide
    //   7301: wide
    //   7305: wide
    //   7309: wide
    //   7313: wide
    //   7317: caload
    //   7318: istore 31
    //   7320: iload 6
    //   7322: iconst_5
    //   7323: irem
    //   7324: tableswitch	default:+32 -> 7356, 0:+11336->18660, 1:+11345->18669, 2:+11354->18678, 3:+11363->18687
    //   7357: pop
    //   7358: wide
    //   7362: wide
    //   7366: iload 31
    //   7368: ixor
    //   7369: i2c
    //   7370: wide
    //   7374: wide
    //   7378: wide
    //   7382: wide
    //   7386: castore
    //   7387: iload 6
    //   7389: iconst_1
    //   7390: iadd
    //   7391: wide
    //   7395: wide
    //   7399: ifne +28 -> 7427
    //   7402: aload 5
    //   7404: wide
    //   7408: wide
    //   7412: wide
    //   7416: wide
    //   7420: wide
    //   7424: goto -115 -> 7309
    //   7427: wide
    //   7431: wide
    //   7435: aload 5
    //   7437: wide
    //   7441: wide
    //   7445: wide
    //   7449: if_icmpgt -176 -> 7273
    //   7452: new 15	java/lang/String
    //   7455: dup
    //   7456: wide
    //   7460: invokespecial 25	java/lang/String:<init>	([C)V
    //   7463: invokevirtual 29	java/lang/String:intern	()Ljava/lang/String;
    //   7466: wide
    //   7470: aload_1
    //   7471: wide
    //   7475: wide
    //   7479: aastore
    //   7480: bipush 38
    //   7482: wide
    //   7486: ldc 105
    //   7488: invokevirtual 21	java/lang/String:toCharArray	()[C
    //   7491: wide
    //   7495: wide
    //   7499: arraylength
    //   7500: wide
    //   7504: wide
    //   7508: iconst_1
    //   7509: if_icmpgt +12983 -> 20492
    //   7512: iconst_0
    //   7513: wide
    //   7517: wide
    //   7521: astore 5
    //   7523: wide
    //   7527: istore 6
    //   7529: wide
    //   7533: wide
    //   7537: wide
    //   7541: wide
    //   7545: wide
    //   7549: wide
    //   7553: wide
    //   7557: wide
    //   7561: caload
    //   7562: istore 31
    //   7564: iload 6
    //   7566: iconst_5
    //   7567: irem
    //   7568: tableswitch	default:+32 -> 7600, 0:+11128->18696, 1:+11137->18705, 2:+11146->18714, 3:+11155->18723
    //   7601: pop
    //   7602: wide
    //   7606: wide
    //   7610: iload 31
    //   7612: ixor
    //   7613: i2c
    //   7614: wide
    //   7618: wide
    //   7622: wide
    //   7626: wide
    //   7630: castore
    //   7631: iload 6
    //   7633: iconst_1
    //   7634: iadd
    //   7635: wide
    //   7639: wide
    //   7643: ifne +28 -> 7671
    //   7646: aload 5
    //   7648: wide
    //   7652: wide
    //   7656: wide
    //   7660: wide
    //   7664: wide
    //   7668: goto -115 -> 7553
    //   7671: wide
    //   7675: wide
    //   7679: aload 5
    //   7681: wide
    //   7685: wide
    //   7689: wide
    //   7693: if_icmpgt -176 -> 7517
    //   7696: new 15	java/lang/String
    //   7699: dup
    //   7700: wide
    //   7704: invokespecial 25	java/lang/String:<init>	([C)V
    //   7707: invokevirtual 29	java/lang/String:intern	()Ljava/lang/String;
    //   7710: wide
    //   7714: aload_1
    //   7715: wide
    //   7719: wide
    //   7723: aastore
    //   7724: bipush 39
    //   7726: wide
    //   7730: ldc 107
    //   7732: invokevirtual 21	java/lang/String:toCharArray	()[C
    //   7735: wide
    //   7739: wide
    //   7743: arraylength
    //   7744: wide
    //   7748: wide
    //   7752: iconst_1
    //   7753: if_icmpgt +12731 -> 20484
    //   7756: iconst_0
    //   7757: wide
    //   7761: wide
    //   7765: astore 5
    //   7767: wide
    //   7771: istore 6
    //   7773: wide
    //   7777: wide
    //   7781: wide
    //   7785: wide
    //   7789: wide
    //   7793: wide
    //   7797: wide
    //   7801: wide
    //   7805: caload
    //   7806: istore 31
    //   7808: iload 6
    //   7810: iconst_5
    //   7811: irem
    //   7812: tableswitch	default:+32 -> 7844, 0:+10920->18732, 1:+10929->18741, 2:+10938->18750, 3:+10947->18759
    //   7845: pop
    //   7846: wide
    //   7850: wide
    //   7854: iload 31
    //   7856: ixor
    //   7857: i2c
    //   7858: wide
    //   7862: wide
    //   7866: wide
    //   7870: wide
    //   7874: castore
    //   7875: iload 6
    //   7877: iconst_1
    //   7878: iadd
    //   7879: wide
    //   7883: wide
    //   7887: ifne +28 -> 7915
    //   7890: aload 5
    //   7892: wide
    //   7896: wide
    //   7900: wide
    //   7904: wide
    //   7908: wide
    //   7912: goto -115 -> 7797
    //   7915: wide
    //   7919: wide
    //   7923: aload 5
    //   7925: wide
    //   7929: wide
    //   7933: wide
    //   7937: if_icmpgt -176 -> 7761
    //   7940: new 15	java/lang/String
    //   7943: dup
    //   7944: wide
    //   7948: invokespecial 25	java/lang/String:<init>	([C)V
    //   7951: invokevirtual 29	java/lang/String:intern	()Ljava/lang/String;
    //   7954: wide
    //   7958: aload_1
    //   7959: wide
    //   7963: wide
    //   7967: aastore
    //   7968: bipush 40
    //   7970: wide
    //   7974: ldc 109
    //   7976: invokevirtual 21	java/lang/String:toCharArray	()[C
    //   7979: wide
    //   7983: wide
    //   7987: arraylength
    //   7988: wide
    //   7992: wide
    //   7996: iconst_1
    //   7997: if_icmpgt +12479 -> 20476
    //   8000: iconst_0
    //   8001: wide
    //   8005: wide
    //   8009: astore 5
    //   8011: wide
    //   8015: istore 6
    //   8017: wide
    //   8021: wide
    //   8025: wide
    //   8029: wide
    //   8033: wide
    //   8037: wide
    //   8041: wide
    //   8045: wide
    //   8049: caload
    //   8050: istore 31
    //   8052: iload 6
    //   8054: iconst_5
    //   8055: irem
    //   8056: tableswitch	default:+32 -> 8088, 0:+10712->18768, 1:+10721->18777, 2:+10730->18786, 3:+10739->18795
    //   8089: pop
    //   8090: wide
    //   8094: wide
    //   8098: iload 31
    //   8100: ixor
    //   8101: i2c
    //   8102: wide
    //   8106: wide
    //   8110: wide
    //   8114: wide
    //   8118: castore
    //   8119: iload 6
    //   8121: iconst_1
    //   8122: iadd
    //   8123: wide
    //   8127: wide
    //   8131: ifne +28 -> 8159
    //   8134: aload 5
    //   8136: wide
    //   8140: wide
    //   8144: wide
    //   8148: wide
    //   8152: wide
    //   8156: goto -115 -> 8041
    //   8159: wide
    //   8163: wide
    //   8167: aload 5
    //   8169: wide
    //   8173: wide
    //   8177: wide
    //   8181: if_icmpgt -176 -> 8005
    //   8184: new 15	java/lang/String
    //   8187: dup
    //   8188: wide
    //   8192: invokespecial 25	java/lang/String:<init>	([C)V
    //   8195: invokevirtual 29	java/lang/String:intern	()Ljava/lang/String;
    //   8198: wide
    //   8202: aload_1
    //   8203: wide
    //   8207: wide
    //   8211: aastore
    //   8212: bipush 41
    //   8214: wide
    //   8218: ldc 111
    //   8220: invokevirtual 21	java/lang/String:toCharArray	()[C
    //   8223: wide
    //   8227: wide
    //   8231: arraylength
    //   8232: wide
    //   8236: wide
    //   8240: iconst_1
    //   8241: if_icmpgt +12227 -> 20468
    //   8244: iconst_0
    //   8245: wide
    //   8249: wide
    //   8253: astore 5
    //   8255: wide
    //   8259: istore 6
    //   8261: wide
    //   8265: wide
    //   8269: wide
    //   8273: wide
    //   8277: wide
    //   8281: wide
    //   8285: wide
    //   8289: wide
    //   8293: caload
    //   8294: istore 31
    //   8296: iload 6
    //   8298: iconst_5
    //   8299: irem
    //   8300: tableswitch	default:+32 -> 8332, 0:+10504->18804, 1:+10513->18813, 2:+10522->18822, 3:+10531->18831
    //   8333: pop
    //   8334: wide
    //   8338: wide
    //   8342: iload 31
    //   8344: ixor
    //   8345: i2c
    //   8346: wide
    //   8350: wide
    //   8354: wide
    //   8358: wide
    //   8362: castore
    //   8363: iload 6
    //   8365: iconst_1
    //   8366: iadd
    //   8367: wide
    //   8371: wide
    //   8375: ifne +28 -> 8403
    //   8378: aload 5
    //   8380: wide
    //   8384: wide
    //   8388: wide
    //   8392: wide
    //   8396: wide
    //   8400: goto -115 -> 8285
    //   8403: wide
    //   8407: wide
    //   8411: aload 5
    //   8413: wide
    //   8417: wide
    //   8421: wide
    //   8425: if_icmpgt -176 -> 8249
    //   8428: new 15	java/lang/String
    //   8431: dup
    //   8432: wide
    //   8436: invokespecial 25	java/lang/String:<init>	([C)V
    //   8439: invokevirtual 29	java/lang/String:intern	()Ljava/lang/String;
    //   8442: wide
    //   8446: aload_1
    //   8447: wide
    //   8451: wide
    //   8455: aastore
    //   8456: bipush 42
    //   8458: wide
    //   8462: ldc 113
    //   8464: invokevirtual 21	java/lang/String:toCharArray	()[C
    //   8467: wide
    //   8471: wide
    //   8475: arraylength
    //   8476: wide
    //   8480: wide
    //   8484: iconst_1
    //   8485: if_icmpgt +11975 -> 20460
    //   8488: iconst_0
    //   8489: wide
    //   8493: wide
    //   8497: astore 5
    //   8499: wide
    //   8503: istore 6
    //   8505: wide
    //   8509: wide
    //   8513: wide
    //   8517: wide
    //   8521: wide
    //   8525: wide
    //   8529: wide
    //   8533: wide
    //   8537: caload
    //   8538: istore 31
    //   8540: iload 6
    //   8542: iconst_5
    //   8543: irem
    //   8544: tableswitch	default:+32 -> 8576, 0:+10296->18840, 1:+10305->18849, 2:+10314->18858, 3:+10323->18867
    //   8577: pop
    //   8578: wide
    //   8582: wide
    //   8586: iload 31
    //   8588: ixor
    //   8589: i2c
    //   8590: wide
    //   8594: wide
    //   8598: wide
    //   8602: wide
    //   8606: castore
    //   8607: iload 6
    //   8609: iconst_1
    //   8610: iadd
    //   8611: wide
    //   8615: wide
    //   8619: ifne +28 -> 8647
    //   8622: aload 5
    //   8624: wide
    //   8628: wide
    //   8632: wide
    //   8636: wide
    //   8640: wide
    //   8644: goto -115 -> 8529
    //   8647: wide
    //   8651: wide
    //   8655: aload 5
    //   8657: wide
    //   8661: wide
    //   8665: wide
    //   8669: if_icmpgt -176 -> 8493
    //   8672: new 15	java/lang/String
    //   8675: dup
    //   8676: wide
    //   8680: invokespecial 25	java/lang/String:<init>	([C)V
    //   8683: invokevirtual 29	java/lang/String:intern	()Ljava/lang/String;
    //   8686: wide
    //   8690: aload_1
    //   8691: wide
    //   8695: wide
    //   8699: aastore
    //   8700: bipush 43
    //   8702: wide
    //   8706: ldc 115
    //   8708: invokevirtual 21	java/lang/String:toCharArray	()[C
    //   8711: wide
    //   8715: wide
    //   8719: arraylength
    //   8720: wide
    //   8724: wide
    //   8728: iconst_1
    //   8729: if_icmpgt +11723 -> 20452
    //   8732: iconst_0
    //   8733: wide
    //   8737: wide
    //   8741: astore 5
    //   8743: wide
    //   8747: istore 6
    //   8749: wide
    //   8753: wide
    //   8757: wide
    //   8761: wide
    //   8765: wide
    //   8769: wide
    //   8773: wide
    //   8777: wide
    //   8781: caload
    //   8782: istore 31
    //   8784: iload 6
    //   8786: iconst_5
    //   8787: irem
    //   8788: tableswitch	default:+32 -> 8820, 0:+10088->18876, 1:+10097->18885, 2:+10106->18894, 3:+10115->18903
    //   8821: pop
    //   8822: wide
    //   8826: wide
    //   8830: iload 31
    //   8832: ixor
    //   8833: i2c
    //   8834: wide
    //   8838: wide
    //   8842: wide
    //   8846: wide
    //   8850: castore
    //   8851: iload 6
    //   8853: iconst_1
    //   8854: iadd
    //   8855: wide
    //   8859: wide
    //   8863: ifne +28 -> 8891
    //   8866: aload 5
    //   8868: wide
    //   8872: wide
    //   8876: wide
    //   8880: wide
    //   8884: wide
    //   8888: goto -115 -> 8773
    //   8891: wide
    //   8895: wide
    //   8899: aload 5
    //   8901: wide
    //   8905: wide
    //   8909: wide
    //   8913: if_icmpgt -176 -> 8737
    //   8916: new 15	java/lang/String
    //   8919: dup
    //   8920: wide
    //   8924: invokespecial 25	java/lang/String:<init>	([C)V
    //   8927: invokevirtual 29	java/lang/String:intern	()Ljava/lang/String;
    //   8930: wide
    //   8934: aload_1
    //   8935: wide
    //   8939: wide
    //   8943: aastore
    //   8944: bipush 44
    //   8946: wide
    //   8950: ldc 117
    //   8952: invokevirtual 21	java/lang/String:toCharArray	()[C
    //   8955: wide
    //   8959: wide
    //   8963: arraylength
    //   8964: wide
    //   8968: wide
    //   8972: iconst_1
    //   8973: if_icmpgt +11471 -> 20444
    //   8976: iconst_0
    //   8977: wide
    //   8981: wide
    //   8985: astore 5
    //   8987: wide
    //   8991: istore 6
    //   8993: wide
    //   8997: wide
    //   9001: wide
    //   9005: wide
    //   9009: wide
    //   9013: wide
    //   9017: wide
    //   9021: wide
    //   9025: caload
    //   9026: istore 31
    //   9028: iload 6
    //   9030: iconst_5
    //   9031: irem
    //   9032: tableswitch	default:+32 -> 9064, 0:+9880->18912, 1:+9889->18921, 2:+9898->18930, 3:+9907->18939
    //   9065: pop
    //   9066: wide
    //   9070: wide
    //   9074: iload 31
    //   9076: ixor
    //   9077: i2c
    //   9078: wide
    //   9082: wide
    //   9086: wide
    //   9090: wide
    //   9094: castore
    //   9095: iload 6
    //   9097: iconst_1
    //   9098: iadd
    //   9099: wide
    //   9103: wide
    //   9107: ifne +28 -> 9135
    //   9110: aload 5
    //   9112: wide
    //   9116: wide
    //   9120: wide
    //   9124: wide
    //   9128: wide
    //   9132: goto -115 -> 9017
    //   9135: wide
    //   9139: wide
    //   9143: aload 5
    //   9145: wide
    //   9149: wide
    //   9153: wide
    //   9157: if_icmpgt -176 -> 8981
    //   9160: new 15	java/lang/String
    //   9163: dup
    //   9164: wide
    //   9168: invokespecial 25	java/lang/String:<init>	([C)V
    //   9171: invokevirtual 29	java/lang/String:intern	()Ljava/lang/String;
    //   9174: wide
    //   9178: aload_1
    //   9179: wide
    //   9183: wide
    //   9187: aastore
    //   9188: ldc 119
    //   9190: invokevirtual 21	java/lang/String:toCharArray	()[C
    //   9193: wide
    //   9197: wide
    //   9201: arraylength
    //   9202: wide
    //   9206: wide
    //   9210: iconst_1
    //   9211: if_icmpgt +11225 -> 20436
    //   9214: iconst_0
    //   9215: wide
    //   9219: wide
    //   9223: astore 5
    //   9225: wide
    //   9229: istore 6
    //   9231: wide
    //   9235: wide
    //   9239: wide
    //   9243: wide
    //   9247: wide
    //   9251: wide
    //   9255: wide
    //   9259: wide
    //   9263: caload
    //   9264: wide
    //   9268: iload 6
    //   9270: iconst_5
    //   9271: irem
    //   9272: tableswitch	default:+32 -> 9304, 0:+9676->18948, 1:+9685->18957, 2:+9694->18966, 3:+9703->18975
    //   9305: pop
    //   9306: wide
    //   9310: wide
    //   9314: wide
    //   9318: ixor
    //   9319: i2c
    //   9320: wide
    //   9324: wide
    //   9328: wide
    //   9332: wide
    //   9336: castore
    //   9337: iload 6
    //   9339: iconst_1
    //   9340: iadd
    //   9341: wide
    //   9345: wide
    //   9349: ifne +28 -> 9377
    //   9352: aload 5
    //   9354: wide
    //   9358: wide
    //   9362: wide
    //   9366: wide
    //   9370: wide
    //   9374: goto -119 -> 9255
    //   9377: wide
    //   9381: wide
    //   9385: aload 5
    //   9387: wide
    //   9391: wide
    //   9395: wide
    //   9399: if_icmpgt -180 -> 9219
    //   9402: new 15	java/lang/String
    //   9405: dup
    //   9406: wide
    //   9410: invokespecial 25	java/lang/String:<init>	([C)V
    //   9413: invokevirtual 29	java/lang/String:intern	()Ljava/lang/String;
    //   9416: wide
    //   9420: aload_1
    //   9421: bipush 45
    //   9423: wide
    //   9427: aastore
    //   9428: bipush 46
    //   9430: wide
    //   9434: ldc 121
    //   9436: invokevirtual 21	java/lang/String:toCharArray	()[C
    //   9439: wide
    //   9443: wide
    //   9447: arraylength
    //   9448: wide
    //   9452: wide
    //   9456: iconst_1
    //   9457: if_icmpgt +10971 -> 20428
    //   9460: iconst_0
    //   9461: wide
    //   9465: wide
    //   9469: astore 5
    //   9471: wide
    //   9475: istore 6
    //   9477: wide
    //   9481: wide
    //   9485: wide
    //   9489: wide
    //   9493: wide
    //   9497: wide
    //   9501: wide
    //   9505: wide
    //   9509: caload
    //   9510: istore 31
    //   9512: iload 6
    //   9514: iconst_5
    //   9515: irem
    //   9516: tableswitch	default:+32 -> 9548, 0:+9468->18984, 1:+9477->18993, 2:+9486->19002, 3:+9495->19011
    //   9549: pop
    //   9550: wide
    //   9554: wide
    //   9558: iload 31
    //   9560: ixor
    //   9561: i2c
    //   9562: wide
    //   9566: wide
    //   9570: wide
    //   9574: wide
    //   9578: castore
    //   9579: iload 6
    //   9581: iconst_1
    //   9582: iadd
    //   9583: wide
    //   9587: wide
    //   9591: ifne +28 -> 9619
    //   9594: aload 5
    //   9596: wide
    //   9600: wide
    //   9604: wide
    //   9608: wide
    //   9612: wide
    //   9616: goto -115 -> 9501
    //   9619: wide
    //   9623: wide
    //   9627: aload 5
    //   9629: wide
    //   9633: wide
    //   9637: wide
    //   9641: if_icmpgt -176 -> 9465
    //   9644: new 15	java/lang/String
    //   9647: dup
    //   9648: wide
    //   9652: invokespecial 25	java/lang/String:<init>	([C)V
    //   9655: invokevirtual 29	java/lang/String:intern	()Ljava/lang/String;
    //   9658: wide
    //   9662: aload_1
    //   9663: wide
    //   9667: wide
    //   9671: aastore
    //   9672: bipush 47
    //   9674: wide
    //   9678: ldc 123
    //   9680: invokevirtual 21	java/lang/String:toCharArray	()[C
    //   9683: wide
    //   9687: wide
    //   9691: arraylength
    //   9692: wide
    //   9696: wide
    //   9700: iconst_1
    //   9701: if_icmpgt +10719 -> 20420
    //   9704: iconst_0
    //   9705: wide
    //   9709: wide
    //   9713: astore 5
    //   9715: wide
    //   9719: istore 6
    //   9721: wide
    //   9725: wide
    //   9729: wide
    //   9733: wide
    //   9737: wide
    //   9741: wide
    //   9745: wide
    //   9749: wide
    //   9753: caload
    //   9754: istore 31
    //   9756: iload 6
    //   9758: iconst_5
    //   9759: irem
    //   9760: tableswitch	default:+32 -> 9792, 0:+9260->19020, 1:+9269->19029, 2:+9278->19038, 3:+9287->19047
    //   9793: pop
    //   9794: wide
    //   9798: wide
    //   9802: iload 31
    //   9804: ixor
    //   9805: i2c
    //   9806: wide
    //   9810: wide
    //   9814: wide
    //   9818: wide
    //   9822: castore
    //   9823: iload 6
    //   9825: iconst_1
    //   9826: iadd
    //   9827: wide
    //   9831: wide
    //   9835: ifne +28 -> 9863
    //   9838: aload 5
    //   9840: wide
    //   9844: wide
    //   9848: wide
    //   9852: wide
    //   9856: wide
    //   9860: goto -115 -> 9745
    //   9863: wide
    //   9867: wide
    //   9871: aload 5
    //   9873: wide
    //   9877: wide
    //   9881: wide
    //   9885: if_icmpgt -176 -> 9709
    //   9888: new 15	java/lang/String
    //   9891: dup
    //   9892: wide
    //   9896: invokespecial 25	java/lang/String:<init>	([C)V
    //   9899: invokevirtual 29	java/lang/String:intern	()Ljava/lang/String;
    //   9902: wide
    //   9906: aload_1
    //   9907: wide
    //   9911: wide
    //   9915: aastore
    //   9916: bipush 48
    //   9918: wide
    //   9922: ldc 125
    //   9924: invokevirtual 21	java/lang/String:toCharArray	()[C
    //   9927: wide
    //   9931: wide
    //   9935: arraylength
    //   9936: wide
    //   9940: wide
    //   9944: iconst_1
    //   9945: if_icmpgt +10467 -> 20412
    //   9948: iconst_0
    //   9949: wide
    //   9953: wide
    //   9957: astore 5
    //   9959: wide
    //   9963: istore 6
    //   9965: wide
    //   9969: wide
    //   9973: wide
    //   9977: wide
    //   9981: wide
    //   9985: wide
    //   9989: wide
    //   9993: wide
    //   9997: caload
    //   9998: istore 31
    //   10000: iload 6
    //   10002: iconst_5
    //   10003: irem
    //   10004: tableswitch	default:+32 -> 10036, 0:+9052->19056, 1:+9061->19065, 2:+9070->19074, 3:+9079->19083
    //   10037: pop
    //   10038: wide
    //   10042: wide
    //   10046: iload 31
    //   10048: ixor
    //   10049: i2c
    //   10050: wide
    //   10054: wide
    //   10058: wide
    //   10062: wide
    //   10066: castore
    //   10067: iload 6
    //   10069: iconst_1
    //   10070: iadd
    //   10071: wide
    //   10075: wide
    //   10079: ifne +28 -> 10107
    //   10082: aload 5
    //   10084: wide
    //   10088: wide
    //   10092: wide
    //   10096: wide
    //   10100: wide
    //   10104: goto -115 -> 9989
    //   10107: wide
    //   10111: wide
    //   10115: aload 5
    //   10117: wide
    //   10121: wide
    //   10125: wide
    //   10129: if_icmpgt -176 -> 9953
    //   10132: new 15	java/lang/String
    //   10135: dup
    //   10136: wide
    //   10140: invokespecial 25	java/lang/String:<init>	([C)V
    //   10143: invokevirtual 29	java/lang/String:intern	()Ljava/lang/String;
    //   10146: wide
    //   10150: aload_1
    //   10151: wide
    //   10155: wide
    //   10159: aastore
    //   10160: bipush 49
    //   10162: wide
    //   10166: ldc 127
    //   10168: invokevirtual 21	java/lang/String:toCharArray	()[C
    //   10171: wide
    //   10175: wide
    //   10179: arraylength
    //   10180: wide
    //   10184: wide
    //   10188: iconst_1
    //   10189: if_icmpgt +10215 -> 20404
    //   10192: iconst_0
    //   10193: wide
    //   10197: wide
    //   10201: astore 5
    //   10203: wide
    //   10207: istore 6
    //   10209: wide
    //   10213: wide
    //   10217: wide
    //   10221: wide
    //   10225: wide
    //   10229: wide
    //   10233: wide
    //   10237: wide
    //   10241: caload
    //   10242: istore 31
    //   10244: iload 6
    //   10246: iconst_5
    //   10247: irem
    //   10248: tableswitch	default:+32 -> 10280, 0:+8844->19092, 1:+8853->19101, 2:+8862->19110, 3:+8871->19119
    //   10281: pop
    //   10282: wide
    //   10286: wide
    //   10290: iload 31
    //   10292: ixor
    //   10293: i2c
    //   10294: wide
    //   10298: wide
    //   10302: wide
    //   10306: wide
    //   10310: castore
    //   10311: iload 6
    //   10313: iconst_1
    //   10314: iadd
    //   10315: wide
    //   10319: wide
    //   10323: ifne +28 -> 10351
    //   10326: aload 5
    //   10328: wide
    //   10332: wide
    //   10336: wide
    //   10340: wide
    //   10344: wide
    //   10348: goto -115 -> 10233
    //   10351: wide
    //   10355: wide
    //   10359: aload 5
    //   10361: wide
    //   10365: wide
    //   10369: wide
    //   10373: if_icmpgt -176 -> 10197
    //   10376: new 15	java/lang/String
    //   10379: dup
    //   10380: wide
    //   10384: invokespecial 25	java/lang/String:<init>	([C)V
    //   10387: invokevirtual 29	java/lang/String:intern	()Ljava/lang/String;
    //   10390: wide
    //   10394: aload_1
    //   10395: wide
    //   10399: wide
    //   10403: aastore
    //   10404: bipush 50
    //   10406: wide
    //   10410: ldc 129
    //   10412: invokevirtual 21	java/lang/String:toCharArray	()[C
    //   10415: wide
    //   10419: wide
    //   10423: arraylength
    //   10424: wide
    //   10428: wide
    //   10432: iconst_1
    //   10433: if_icmpgt +9963 -> 20396
    //   10436: iconst_0
    //   10437: wide
    //   10441: wide
    //   10445: astore 5
    //   10447: wide
    //   10451: istore 6
    //   10453: wide
    //   10457: wide
    //   10461: wide
    //   10465: wide
    //   10469: wide
    //   10473: wide
    //   10477: wide
    //   10481: wide
    //   10485: caload
    //   10486: istore 31
    //   10488: iload 6
    //   10490: iconst_5
    //   10491: irem
    //   10492: tableswitch	default:+32 -> 10524, 0:+8636->19128, 1:+8645->19137, 2:+8654->19146, 3:+8663->19155
    //   10525: pop
    //   10526: wide
    //   10530: wide
    //   10534: iload 31
    //   10536: ixor
    //   10537: i2c
    //   10538: wide
    //   10542: wide
    //   10546: wide
    //   10550: wide
    //   10554: castore
    //   10555: iload 6
    //   10557: iconst_1
    //   10558: iadd
    //   10559: wide
    //   10563: wide
    //   10567: ifne +28 -> 10595
    //   10570: aload 5
    //   10572: wide
    //   10576: wide
    //   10580: wide
    //   10584: wide
    //   10588: wide
    //   10592: goto -115 -> 10477
    //   10595: wide
    //   10599: wide
    //   10603: aload 5
    //   10605: wide
    //   10609: wide
    //   10613: wide
    //   10617: if_icmpgt -176 -> 10441
    //   10620: new 15	java/lang/String
    //   10623: dup
    //   10624: wide
    //   10628: invokespecial 25	java/lang/String:<init>	([C)V
    //   10631: invokevirtual 29	java/lang/String:intern	()Ljava/lang/String;
    //   10634: wide
    //   10638: aload_1
    //   10639: wide
    //   10643: wide
    //   10647: aastore
    //   10648: bipush 51
    //   10650: wide
    //   10654: ldc 131
    //   10656: invokevirtual 21	java/lang/String:toCharArray	()[C
    //   10659: wide
    //   10663: wide
    //   10667: arraylength
    //   10668: wide
    //   10672: wide
    //   10676: iconst_1
    //   10677: if_icmpgt +9711 -> 20388
    //   10680: iconst_0
    //   10681: wide
    //   10685: wide
    //   10689: astore 5
    //   10691: wide
    //   10695: istore 6
    //   10697: wide
    //   10701: wide
    //   10705: wide
    //   10709: wide
    //   10713: wide
    //   10717: wide
    //   10721: wide
    //   10725: wide
    //   10729: caload
    //   10730: istore 31
    //   10732: iload 6
    //   10734: iconst_5
    //   10735: irem
    //   10736: tableswitch	default:+32 -> 10768, 0:+8428->19164, 1:+8437->19173, 2:+8446->19182, 3:+8455->19191
    //   10769: pop
    //   10770: wide
    //   10774: wide
    //   10778: iload 31
    //   10780: ixor
    //   10781: i2c
    //   10782: wide
    //   10786: wide
    //   10790: wide
    //   10794: wide
    //   10798: castore
    //   10799: iload 6
    //   10801: iconst_1
    //   10802: iadd
    //   10803: wide
    //   10807: wide
    //   10811: ifne +28 -> 10839
    //   10814: aload 5
    //   10816: wide
    //   10820: wide
    //   10824: wide
    //   10828: wide
    //   10832: wide
    //   10836: goto -115 -> 10721
    //   10839: wide
    //   10843: wide
    //   10847: aload 5
    //   10849: wide
    //   10853: wide
    //   10857: wide
    //   10861: if_icmpgt -176 -> 10685
    //   10864: new 15	java/lang/String
    //   10867: dup
    //   10868: wide
    //   10872: invokespecial 25	java/lang/String:<init>	([C)V
    //   10875: invokevirtual 29	java/lang/String:intern	()Ljava/lang/String;
    //   10878: wide
    //   10882: aload_1
    //   10883: wide
    //   10887: wide
    //   10891: aastore
    //   10892: bipush 52
    //   10894: wide
    //   10898: ldc 133
    //   10900: invokevirtual 21	java/lang/String:toCharArray	()[C
    //   10903: wide
    //   10907: wide
    //   10911: arraylength
    //   10912: wide
    //   10916: wide
    //   10920: iconst_1
    //   10921: if_icmpgt +9459 -> 20380
    //   10924: iconst_0
    //   10925: wide
    //   10929: wide
    //   10933: astore 5
    //   10935: wide
    //   10939: istore 6
    //   10941: wide
    //   10945: wide
    //   10949: wide
    //   10953: wide
    //   10957: wide
    //   10961: wide
    //   10965: wide
    //   10969: wide
    //   10973: caload
    //   10974: istore 31
    //   10976: iload 6
    //   10978: iconst_5
    //   10979: irem
    //   10980: tableswitch	default:+32 -> 11012, 0:+8220->19200, 1:+8229->19209, 2:+8238->19218, 3:+8247->19227
    //   11013: pop
    //   11014: wide
    //   11018: wide
    //   11022: iload 31
    //   11024: ixor
    //   11025: i2c
    //   11026: wide
    //   11030: wide
    //   11034: wide
    //   11038: wide
    //   11042: castore
    //   11043: iload 6
    //   11045: iconst_1
    //   11046: iadd
    //   11047: wide
    //   11051: wide
    //   11055: ifne +28 -> 11083
    //   11058: aload 5
    //   11060: wide
    //   11064: wide
    //   11068: wide
    //   11072: wide
    //   11076: wide
    //   11080: goto -115 -> 10965
    //   11083: wide
    //   11087: wide
    //   11091: aload 5
    //   11093: wide
    //   11097: wide
    //   11101: wide
    //   11105: if_icmpgt -176 -> 10929
    //   11108: new 15	java/lang/String
    //   11111: dup
    //   11112: wide
    //   11116: invokespecial 25	java/lang/String:<init>	([C)V
    //   11119: invokevirtual 29	java/lang/String:intern	()Ljava/lang/String;
    //   11122: wide
    //   11126: aload_1
    //   11127: wide
    //   11131: wide
    //   11135: aastore
    //   11136: bipush 53
    //   11138: wide
    //   11142: ldc 135
    //   11144: invokevirtual 21	java/lang/String:toCharArray	()[C
    //   11147: wide
    //   11151: wide
    //   11155: arraylength
    //   11156: wide
    //   11160: wide
    //   11164: iconst_1
    //   11165: if_icmpgt +9207 -> 20372
    //   11168: iconst_0
    //   11169: wide
    //   11173: wide
    //   11177: astore 5
    //   11179: wide
    //   11183: istore 6
    //   11185: wide
    //   11189: wide
    //   11193: wide
    //   11197: wide
    //   11201: wide
    //   11205: wide
    //   11209: wide
    //   11213: wide
    //   11217: caload
    //   11218: istore 31
    //   11220: iload 6
    //   11222: iconst_5
    //   11223: irem
    //   11224: tableswitch	default:+32 -> 11256, 0:+8012->19236, 1:+8021->19245, 2:+8030->19254, 3:+8039->19263
    //   11257: pop
    //   11258: wide
    //   11262: wide
    //   11266: iload 31
    //   11268: ixor
    //   11269: i2c
    //   11270: wide
    //   11274: wide
    //   11278: wide
    //   11282: wide
    //   11286: castore
    //   11287: iload 6
    //   11289: iconst_1
    //   11290: iadd
    //   11291: wide
    //   11295: wide
    //   11299: ifne +28 -> 11327
    //   11302: aload 5
    //   11304: wide
    //   11308: wide
    //   11312: wide
    //   11316: wide
    //   11320: wide
    //   11324: goto -115 -> 11209
    //   11327: wide
    //   11331: wide
    //   11335: aload 5
    //   11337: wide
    //   11341: wide
    //   11345: wide
    //   11349: if_icmpgt -176 -> 11173
    //   11352: new 15	java/lang/String
    //   11355: dup
    //   11356: wide
    //   11360: invokespecial 25	java/lang/String:<init>	([C)V
    //   11363: invokevirtual 29	java/lang/String:intern	()Ljava/lang/String;
    //   11366: wide
    //   11370: aload_1
    //   11371: wide
    //   11375: wide
    //   11379: aastore
    //   11380: bipush 54
    //   11382: wide
    //   11386: ldc 137
    //   11388: invokevirtual 21	java/lang/String:toCharArray	()[C
    //   11391: wide
    //   11395: wide
    //   11399: arraylength
    //   11400: wide
    //   11404: wide
    //   11408: iconst_1
    //   11409: if_icmpgt +8955 -> 20364
    //   11412: iconst_0
    //   11413: wide
    //   11417: wide
    //   11421: astore 5
    //   11423: wide
    //   11427: istore 6
    //   11429: wide
    //   11433: wide
    //   11437: wide
    //   11441: wide
    //   11445: wide
    //   11449: wide
    //   11453: wide
    //   11457: wide
    //   11461: caload
    //   11462: istore 31
    //   11464: iload 6
    //   11466: iconst_5
    //   11467: irem
    //   11468: tableswitch	default:+32 -> 11500, 0:+7804->19272, 1:+7813->19281, 2:+7822->19290, 3:+7831->19299
    //   11501: pop
    //   11502: wide
    //   11506: wide
    //   11510: iload 31
    //   11512: ixor
    //   11513: i2c
    //   11514: wide
    //   11518: wide
    //   11522: wide
    //   11526: wide
    //   11530: castore
    //   11531: iload 6
    //   11533: iconst_1
    //   11534: iadd
    //   11535: wide
    //   11539: wide
    //   11543: ifne +28 -> 11571
    //   11546: aload 5
    //   11548: wide
    //   11552: wide
    //   11556: wide
    //   11560: wide
    //   11564: wide
    //   11568: goto -115 -> 11453
    //   11571: wide
    //   11575: wide
    //   11579: aload 5
    //   11581: wide
    //   11585: wide
    //   11589: wide
    //   11593: if_icmpgt -176 -> 11417
    //   11596: new 15	java/lang/String
    //   11599: dup
    //   11600: wide
    //   11604: invokespecial 25	java/lang/String:<init>	([C)V
    //   11607: invokevirtual 29	java/lang/String:intern	()Ljava/lang/String;
    //   11610: wide
    //   11614: aload_1
    //   11615: wide
    //   11619: wide
    //   11623: aastore
    //   11624: bipush 55
    //   11626: wide
    //   11630: ldc 139
    //   11632: invokevirtual 21	java/lang/String:toCharArray	()[C
    //   11635: wide
    //   11639: wide
    //   11643: arraylength
    //   11644: wide
    //   11648: wide
    //   11652: iconst_1
    //   11653: if_icmpgt +8703 -> 20356
    //   11656: iconst_0
    //   11657: wide
    //   11661: wide
    //   11665: astore 5
    //   11667: wide
    //   11671: istore 6
    //   11673: wide
    //   11677: wide
    //   11681: wide
    //   11685: wide
    //   11689: wide
    //   11693: wide
    //   11697: wide
    //   11701: wide
    //   11705: caload
    //   11706: istore 31
    //   11708: iload 6
    //   11710: iconst_5
    //   11711: irem
    //   11712: tableswitch	default:+32 -> 11744, 0:+7596->19308, 1:+7605->19317, 2:+7614->19326, 3:+7623->19335
    //   11745: pop
    //   11746: wide
    //   11750: wide
    //   11754: iload 31
    //   11756: ixor
    //   11757: i2c
    //   11758: wide
    //   11762: wide
    //   11766: wide
    //   11770: wide
    //   11774: castore
    //   11775: iload 6
    //   11777: iconst_1
    //   11778: iadd
    //   11779: wide
    //   11783: wide
    //   11787: ifne +28 -> 11815
    //   11790: aload 5
    //   11792: wide
    //   11796: wide
    //   11800: wide
    //   11804: wide
    //   11808: wide
    //   11812: goto -115 -> 11697
    //   11815: wide
    //   11819: wide
    //   11823: aload 5
    //   11825: wide
    //   11829: wide
    //   11833: wide
    //   11837: if_icmpgt -176 -> 11661
    //   11840: new 15	java/lang/String
    //   11843: dup
    //   11844: wide
    //   11848: invokespecial 25	java/lang/String:<init>	([C)V
    //   11851: invokevirtual 29	java/lang/String:intern	()Ljava/lang/String;
    //   11854: wide
    //   11858: aload_1
    //   11859: wide
    //   11863: wide
    //   11867: aastore
    //   11868: bipush 56
    //   11870: wide
    //   11874: ldc 141
    //   11876: invokevirtual 21	java/lang/String:toCharArray	()[C
    //   11879: wide
    //   11883: wide
    //   11887: arraylength
    //   11888: wide
    //   11892: wide
    //   11896: iconst_1
    //   11897: if_icmpgt +8451 -> 20348
    //   11900: iconst_0
    //   11901: wide
    //   11905: wide
    //   11909: astore 5
    //   11911: wide
    //   11915: istore 6
    //   11917: wide
    //   11921: wide
    //   11925: wide
    //   11929: wide
    //   11933: wide
    //   11937: wide
    //   11941: wide
    //   11945: wide
    //   11949: caload
    //   11950: istore 31
    //   11952: iload 6
    //   11954: iconst_5
    //   11955: irem
    //   11956: tableswitch	default:+32 -> 11988, 0:+7388->19344, 1:+7397->19353, 2:+7406->19362, 3:+7415->19371
    //   11989: pop
    //   11990: wide
    //   11994: wide
    //   11998: iload 31
    //   12000: ixor
    //   12001: i2c
    //   12002: wide
    //   12006: wide
    //   12010: wide
    //   12014: wide
    //   12018: castore
    //   12019: iload 6
    //   12021: iconst_1
    //   12022: iadd
    //   12023: wide
    //   12027: wide
    //   12031: ifne +28 -> 12059
    //   12034: aload 5
    //   12036: wide
    //   12040: wide
    //   12044: wide
    //   12048: wide
    //   12052: wide
    //   12056: goto -115 -> 11941
    //   12059: wide
    //   12063: wide
    //   12067: aload 5
    //   12069: wide
    //   12073: wide
    //   12077: wide
    //   12081: if_icmpgt -176 -> 11905
    //   12084: new 15	java/lang/String
    //   12087: dup
    //   12088: wide
    //   12092: invokespecial 25	java/lang/String:<init>	([C)V
    //   12095: invokevirtual 29	java/lang/String:intern	()Ljava/lang/String;
    //   12098: wide
    //   12102: aload_1
    //   12103: wide
    //   12107: wide
    //   12111: aastore
    //   12112: bipush 57
    //   12114: wide
    //   12118: ldc 143
    //   12120: invokevirtual 21	java/lang/String:toCharArray	()[C
    //   12123: wide
    //   12127: wide
    //   12131: arraylength
    //   12132: wide
    //   12136: wide
    //   12140: iconst_1
    //   12141: if_icmpgt +8199 -> 20340
    //   12144: iconst_0
    //   12145: wide
    //   12149: wide
    //   12153: astore 5
    //   12155: wide
    //   12159: istore 6
    //   12161: wide
    //   12165: wide
    //   12169: wide
    //   12173: wide
    //   12177: wide
    //   12181: wide
    //   12185: wide
    //   12189: wide
    //   12193: caload
    //   12194: istore 31
    //   12196: iload 6
    //   12198: iconst_5
    //   12199: irem
    //   12200: tableswitch	default:+32 -> 12232, 0:+7180->19380, 1:+7189->19389, 2:+7198->19398, 3:+7207->19407
    //   12233: pop
    //   12234: wide
    //   12238: wide
    //   12242: iload 31
    //   12244: ixor
    //   12245: i2c
    //   12246: wide
    //   12250: wide
    //   12254: wide
    //   12258: wide
    //   12262: castore
    //   12263: iload 6
    //   12265: iconst_1
    //   12266: iadd
    //   12267: wide
    //   12271: wide
    //   12275: ifne +28 -> 12303
    //   12278: aload 5
    //   12280: wide
    //   12284: wide
    //   12288: wide
    //   12292: wide
    //   12296: wide
    //   12300: goto -115 -> 12185
    //   12303: wide
    //   12307: wide
    //   12311: aload 5
    //   12313: wide
    //   12317: wide
    //   12321: wide
    //   12325: if_icmpgt -176 -> 12149
    //   12328: new 15	java/lang/String
    //   12331: dup
    //   12332: wide
    //   12336: invokespecial 25	java/lang/String:<init>	([C)V
    //   12339: invokevirtual 29	java/lang/String:intern	()Ljava/lang/String;
    //   12342: wide
    //   12346: aload_1
    //   12347: wide
    //   12351: wide
    //   12355: aastore
    //   12356: bipush 58
    //   12358: wide
    //   12362: ldc 145
    //   12364: invokevirtual 21	java/lang/String:toCharArray	()[C
    //   12367: wide
    //   12371: wide
    //   12375: arraylength
    //   12376: wide
    //   12380: wide
    //   12384: iconst_1
    //   12385: if_icmpgt +7947 -> 20332
    //   12388: iconst_0
    //   12389: wide
    //   12393: wide
    //   12397: astore 5
    //   12399: wide
    //   12403: istore 6
    //   12405: wide
    //   12409: wide
    //   12413: wide
    //   12417: wide
    //   12421: wide
    //   12425: wide
    //   12429: wide
    //   12433: wide
    //   12437: caload
    //   12438: istore 31
    //   12440: iload 6
    //   12442: iconst_5
    //   12443: irem
    //   12444: tableswitch	default:+32 -> 12476, 0:+6972->19416, 1:+6981->19425, 2:+6990->19434, 3:+6999->19443
    //   12477: pop
    //   12478: wide
    //   12482: wide
    //   12486: iload 31
    //   12488: ixor
    //   12489: i2c
    //   12490: wide
    //   12494: wide
    //   12498: wide
    //   12502: wide
    //   12506: castore
    //   12507: iload 6
    //   12509: iconst_1
    //   12510: iadd
    //   12511: wide
    //   12515: wide
    //   12519: ifne +28 -> 12547
    //   12522: aload 5
    //   12524: wide
    //   12528: wide
    //   12532: wide
    //   12536: wide
    //   12540: wide
    //   12544: goto -115 -> 12429
    //   12547: wide
    //   12551: wide
    //   12555: aload 5
    //   12557: wide
    //   12561: wide
    //   12565: wide
    //   12569: if_icmpgt -176 -> 12393
    //   12572: new 15	java/lang/String
    //   12575: dup
    //   12576: wide
    //   12580: invokespecial 25	java/lang/String:<init>	([C)V
    //   12583: invokevirtual 29	java/lang/String:intern	()Ljava/lang/String;
    //   12586: wide
    //   12590: aload_1
    //   12591: wide
    //   12595: wide
    //   12599: aastore
    //   12600: bipush 59
    //   12602: wide
    //   12606: ldc 147
    //   12608: invokevirtual 21	java/lang/String:toCharArray	()[C
    //   12611: wide
    //   12615: wide
    //   12619: arraylength
    //   12620: wide
    //   12624: wide
    //   12628: iconst_1
    //   12629: if_icmpgt +7695 -> 20324
    //   12632: iconst_0
    //   12633: wide
    //   12637: wide
    //   12641: astore 5
    //   12643: wide
    //   12647: istore 6
    //   12649: wide
    //   12653: wide
    //   12657: wide
    //   12661: wide
    //   12665: wide
    //   12669: wide
    //   12673: wide
    //   12677: wide
    //   12681: caload
    //   12682: istore 31
    //   12684: iload 6
    //   12686: iconst_5
    //   12687: irem
    //   12688: tableswitch	default:+32 -> 12720, 0:+6764->19452, 1:+6773->19461, 2:+6782->19470, 3:+6791->19479
    //   12721: pop
    //   12722: wide
    //   12726: wide
    //   12730: iload 31
    //   12732: ixor
    //   12733: i2c
    //   12734: wide
    //   12738: wide
    //   12742: wide
    //   12746: wide
    //   12750: castore
    //   12751: iload 6
    //   12753: iconst_1
    //   12754: iadd
    //   12755: wide
    //   12759: wide
    //   12763: ifne +28 -> 12791
    //   12766: aload 5
    //   12768: wide
    //   12772: wide
    //   12776: wide
    //   12780: wide
    //   12784: wide
    //   12788: goto -115 -> 12673
    //   12791: wide
    //   12795: wide
    //   12799: aload 5
    //   12801: wide
    //   12805: wide
    //   12809: wide
    //   12813: if_icmpgt -176 -> 12637
    //   12816: new 15	java/lang/String
    //   12819: dup
    //   12820: wide
    //   12824: invokespecial 25	java/lang/String:<init>	([C)V
    //   12827: invokevirtual 29	java/lang/String:intern	()Ljava/lang/String;
    //   12830: wide
    //   12834: aload_1
    //   12835: wide
    //   12839: wide
    //   12843: aastore
    //   12844: bipush 60
    //   12846: wide
    //   12850: ldc 149
    //   12852: invokevirtual 21	java/lang/String:toCharArray	()[C
    //   12855: wide
    //   12859: wide
    //   12863: arraylength
    //   12864: wide
    //   12868: wide
    //   12872: iconst_1
    //   12873: if_icmpgt +7443 -> 20316
    //   12876: iconst_0
    //   12877: wide
    //   12881: wide
    //   12885: astore 5
    //   12887: wide
    //   12891: istore 6
    //   12893: wide
    //   12897: wide
    //   12901: wide
    //   12905: wide
    //   12909: wide
    //   12913: wide
    //   12917: wide
    //   12921: wide
    //   12925: caload
    //   12926: istore 31
    //   12928: iload 6
    //   12930: iconst_5
    //   12931: irem
    //   12932: tableswitch	default:+32 -> 12964, 0:+6556->19488, 1:+6565->19497, 2:+6574->19506, 3:+6583->19515
    //   12965: pop
    //   12966: wide
    //   12970: wide
    //   12974: iload 31
    //   12976: ixor
    //   12977: i2c
    //   12978: wide
    //   12982: wide
    //   12986: wide
    //   12990: wide
    //   12994: castore
    //   12995: iload 6
    //   12997: iconst_1
    //   12998: iadd
    //   12999: wide
    //   13003: wide
    //   13007: ifne +28 -> 13035
    //   13010: aload 5
    //   13012: wide
    //   13016: wide
    //   13020: wide
    //   13024: wide
    //   13028: wide
    //   13032: goto -115 -> 12917
    //   13035: wide
    //   13039: wide
    //   13043: aload 5
    //   13045: wide
    //   13049: wide
    //   13053: wide
    //   13057: if_icmpgt -176 -> 12881
    //   13060: new 15	java/lang/String
    //   13063: dup
    //   13064: wide
    //   13068: invokespecial 25	java/lang/String:<init>	([C)V
    //   13071: invokevirtual 29	java/lang/String:intern	()Ljava/lang/String;
    //   13074: wide
    //   13078: aload_1
    //   13079: wide
    //   13083: wide
    //   13087: aastore
    //   13088: bipush 61
    //   13090: wide
    //   13094: ldc 151
    //   13096: invokevirtual 21	java/lang/String:toCharArray	()[C
    //   13099: wide
    //   13103: wide
    //   13107: arraylength
    //   13108: wide
    //   13112: wide
    //   13116: iconst_1
    //   13117: if_icmpgt +7191 -> 20308
    //   13120: iconst_0
    //   13121: wide
    //   13125: wide
    //   13129: astore 5
    //   13131: wide
    //   13135: istore 6
    //   13137: wide
    //   13141: wide
    //   13145: wide
    //   13149: wide
    //   13153: wide
    //   13157: wide
    //   13161: wide
    //   13165: wide
    //   13169: caload
    //   13170: istore 31
    //   13172: iload 6
    //   13174: iconst_5
    //   13175: irem
    //   13176: tableswitch	default:+32 -> 13208, 0:+6348->19524, 1:+6357->19533, 2:+6366->19542, 3:+6375->19551
    //   13209: pop
    //   13210: wide
    //   13214: wide
    //   13218: iload 31
    //   13220: ixor
    //   13221: i2c
    //   13222: wide
    //   13226: wide
    //   13230: wide
    //   13234: wide
    //   13238: castore
    //   13239: iload 6
    //   13241: iconst_1
    //   13242: iadd
    //   13243: wide
    //   13247: wide
    //   13251: ifne +28 -> 13279
    //   13254: aload 5
    //   13256: wide
    //   13260: wide
    //   13264: wide
    //   13268: wide
    //   13272: wide
    //   13276: goto -115 -> 13161
    //   13279: wide
    //   13283: wide
    //   13287: aload 5
    //   13289: wide
    //   13293: wide
    //   13297: wide
    //   13301: if_icmpgt -176 -> 13125
    //   13304: new 15	java/lang/String
    //   13307: dup
    //   13308: wide
    //   13312: invokespecial 25	java/lang/String:<init>	([C)V
    //   13315: invokevirtual 29	java/lang/String:intern	()Ljava/lang/String;
    //   13318: wide
    //   13322: aload_1
    //   13323: wide
    //   13327: wide
    //   13331: aastore
    //   13332: bipush 62
    //   13334: wide
    //   13338: ldc 153
    //   13340: invokevirtual 21	java/lang/String:toCharArray	()[C
    //   13343: wide
    //   13347: wide
    //   13351: arraylength
    //   13352: wide
    //   13356: wide
    //   13360: iconst_1
    //   13361: if_icmpgt +6939 -> 20300
    //   13364: iconst_0
    //   13365: wide
    //   13369: wide
    //   13373: astore 5
    //   13375: wide
    //   13379: istore 6
    //   13381: wide
    //   13385: wide
    //   13389: wide
    //   13393: wide
    //   13397: wide
    //   13401: wide
    //   13405: wide
    //   13409: wide
    //   13413: caload
    //   13414: istore 31
    //   13416: iload 6
    //   13418: iconst_5
    //   13419: irem
    //   13420: tableswitch	default:+32 -> 13452, 0:+6140->19560, 1:+6149->19569, 2:+6158->19578, 3:+6167->19587
    //   13453: pop
    //   13454: wide
    //   13458: wide
    //   13462: iload 31
    //   13464: ixor
    //   13465: i2c
    //   13466: wide
    //   13470: wide
    //   13474: wide
    //   13478: wide
    //   13482: castore
    //   13483: iload 6
    //   13485: iconst_1
    //   13486: iadd
    //   13487: wide
    //   13491: wide
    //   13495: ifne +28 -> 13523
    //   13498: aload 5
    //   13500: wide
    //   13504: wide
    //   13508: wide
    //   13512: wide
    //   13516: wide
    //   13520: goto -115 -> 13405
    //   13523: wide
    //   13527: wide
    //   13531: aload 5
    //   13533: wide
    //   13537: wide
    //   13541: wide
    //   13545: if_icmpgt -176 -> 13369
    //   13548: new 15	java/lang/String
    //   13551: dup
    //   13552: wide
    //   13556: invokespecial 25	java/lang/String:<init>	([C)V
    //   13559: invokevirtual 29	java/lang/String:intern	()Ljava/lang/String;
    //   13562: wide
    //   13566: aload_1
    //   13567: wide
    //   13571: wide
    //   13575: aastore
    //   13576: bipush 63
    //   13578: wide
    //   13582: ldc 155
    //   13584: invokevirtual 21	java/lang/String:toCharArray	()[C
    //   13587: wide
    //   13591: wide
    //   13595: arraylength
    //   13596: wide
    //   13600: wide
    //   13604: iconst_1
    //   13605: if_icmpgt +6687 -> 20292
    //   13608: iconst_0
    //   13609: wide
    //   13613: wide
    //   13617: astore 5
    //   13619: wide
    //   13623: istore 6
    //   13625: wide
    //   13629: wide
    //   13633: wide
    //   13637: wide
    //   13641: wide
    //   13645: wide
    //   13649: wide
    //   13653: wide
    //   13657: caload
    //   13658: istore 31
    //   13660: iload 6
    //   13662: iconst_5
    //   13663: irem
    //   13664: tableswitch	default:+32 -> 13696, 0:+5932->19596, 1:+5941->19605, 2:+5950->19614, 3:+5959->19623
    //   13697: pop
    //   13698: wide
    //   13702: wide
    //   13706: iload 31
    //   13708: ixor
    //   13709: i2c
    //   13710: wide
    //   13714: wide
    //   13718: wide
    //   13722: wide
    //   13726: castore
    //   13727: iload 6
    //   13729: iconst_1
    //   13730: iadd
    //   13731: wide
    //   13735: wide
    //   13739: ifne +28 -> 13767
    //   13742: aload 5
    //   13744: wide
    //   13748: wide
    //   13752: wide
    //   13756: wide
    //   13760: wide
    //   13764: goto -115 -> 13649
    //   13767: wide
    //   13771: wide
    //   13775: aload 5
    //   13777: wide
    //   13781: wide
    //   13785: wide
    //   13789: if_icmpgt -176 -> 13613
    //   13792: new 15	java/lang/String
    //   13795: dup
    //   13796: wide
    //   13800: invokespecial 25	java/lang/String:<init>	([C)V
    //   13803: invokevirtual 29	java/lang/String:intern	()Ljava/lang/String;
    //   13806: wide
    //   13810: aload_1
    //   13811: wide
    //   13815: wide
    //   13819: aastore
    //   13820: bipush 64
    //   13822: wide
    //   13826: ldc 157
    //   13828: invokevirtual 21	java/lang/String:toCharArray	()[C
    //   13831: wide
    //   13835: wide
    //   13839: arraylength
    //   13840: wide
    //   13844: wide
    //   13848: iconst_1
    //   13849: if_icmpgt +6435 -> 20284
    //   13852: iconst_0
    //   13853: wide
    //   13857: wide
    //   13861: astore 5
    //   13863: wide
    //   13867: istore 6
    //   13869: wide
    //   13873: wide
    //   13877: wide
    //   13881: wide
    //   13885: wide
    //   13889: wide
    //   13893: wide
    //   13897: wide
    //   13901: caload
    //   13902: istore 31
    //   13904: iload 6
    //   13906: iconst_5
    //   13907: irem
    //   13908: tableswitch	default:+32 -> 13940, 0:+5724->19632, 1:+5733->19641, 2:+5742->19650, 3:+5751->19659
    //   13941: pop
    //   13942: wide
    //   13946: wide
    //   13950: iload 31
    //   13952: ixor
    //   13953: i2c
    //   13954: wide
    //   13958: wide
    //   13962: wide
    //   13966: wide
    //   13970: castore
    //   13971: iload 6
    //   13973: iconst_1
    //   13974: iadd
    //   13975: wide
    //   13979: wide
    //   13983: ifne +28 -> 14011
    //   13986: aload 5
    //   13988: wide
    //   13992: wide
    //   13996: wide
    //   14000: wide
    //   14004: wide
    //   14008: goto -115 -> 13893
    //   14011: wide
    //   14015: wide
    //   14019: aload 5
    //   14021: wide
    //   14025: wide
    //   14029: wide
    //   14033: if_icmpgt -176 -> 13857
    //   14036: new 15	java/lang/String
    //   14039: dup
    //   14040: wide
    //   14044: invokespecial 25	java/lang/String:<init>	([C)V
    //   14047: invokevirtual 29	java/lang/String:intern	()Ljava/lang/String;
    //   14050: wide
    //   14054: aload_1
    //   14055: wide
    //   14059: wide
    //   14063: aastore
    //   14064: bipush 65
    //   14066: wide
    //   14070: ldc 159
    //   14072: invokevirtual 21	java/lang/String:toCharArray	()[C
    //   14075: wide
    //   14079: wide
    //   14083: arraylength
    //   14084: wide
    //   14088: wide
    //   14092: iconst_1
    //   14093: if_icmpgt +6183 -> 20276
    //   14096: iconst_0
    //   14097: wide
    //   14101: wide
    //   14105: astore 5
    //   14107: wide
    //   14111: istore 6
    //   14113: wide
    //   14117: wide
    //   14121: wide
    //   14125: wide
    //   14129: wide
    //   14133: wide
    //   14137: wide
    //   14141: wide
    //   14145: caload
    //   14146: istore 31
    //   14148: iload 6
    //   14150: iconst_5
    //   14151: irem
    //   14152: tableswitch	default:+32 -> 14184, 0:+5516->19668, 1:+5525->19677, 2:+5534->19686, 3:+5543->19695
    //   14185: pop
    //   14186: wide
    //   14190: wide
    //   14194: iload 31
    //   14196: ixor
    //   14197: i2c
    //   14198: wide
    //   14202: wide
    //   14206: wide
    //   14210: wide
    //   14214: castore
    //   14215: iload 6
    //   14217: iconst_1
    //   14218: iadd
    //   14219: wide
    //   14223: wide
    //   14227: ifne +28 -> 14255
    //   14230: aload 5
    //   14232: wide
    //   14236: wide
    //   14240: wide
    //   14244: wide
    //   14248: wide
    //   14252: goto -115 -> 14137
    //   14255: wide
    //   14259: wide
    //   14263: aload 5
    //   14265: wide
    //   14269: wide
    //   14273: wide
    //   14277: if_icmpgt -176 -> 14101
    //   14280: new 15	java/lang/String
    //   14283: dup
    //   14284: wide
    //   14288: invokespecial 25	java/lang/String:<init>	([C)V
    //   14291: invokevirtual 29	java/lang/String:intern	()Ljava/lang/String;
    //   14294: wide
    //   14298: aload_1
    //   14299: wide
    //   14303: wide
    //   14307: aastore
    //   14308: bipush 66
    //   14310: wide
    //   14314: ldc 161
    //   14316: invokevirtual 21	java/lang/String:toCharArray	()[C
    //   14319: wide
    //   14323: wide
    //   14327: arraylength
    //   14328: wide
    //   14332: wide
    //   14336: iconst_1
    //   14337: if_icmpgt +5931 -> 20268
    //   14340: iconst_0
    //   14341: wide
    //   14345: wide
    //   14349: astore 5
    //   14351: wide
    //   14355: istore 6
    //   14357: wide
    //   14361: wide
    //   14365: wide
    //   14369: wide
    //   14373: wide
    //   14377: wide
    //   14381: wide
    //   14385: wide
    //   14389: caload
    //   14390: istore 31
    //   14392: iload 6
    //   14394: iconst_5
    //   14395: irem
    //   14396: tableswitch	default:+32 -> 14428, 0:+5308->19704, 1:+5317->19713, 2:+5326->19722, 3:+5335->19731
    //   14429: pop
    //   14430: wide
    //   14434: wide
    //   14438: iload 31
    //   14440: ixor
    //   14441: i2c
    //   14442: wide
    //   14446: wide
    //   14450: wide
    //   14454: wide
    //   14458: castore
    //   14459: iload 6
    //   14461: iconst_1
    //   14462: iadd
    //   14463: wide
    //   14467: wide
    //   14471: ifne +28 -> 14499
    //   14474: aload 5
    //   14476: wide
    //   14480: wide
    //   14484: wide
    //   14488: wide
    //   14492: wide
    //   14496: goto -115 -> 14381
    //   14499: wide
    //   14503: wide
    //   14507: aload 5
    //   14509: wide
    //   14513: wide
    //   14517: wide
    //   14521: if_icmpgt -176 -> 14345
    //   14524: new 15	java/lang/String
    //   14527: dup
    //   14528: wide
    //   14532: invokespecial 25	java/lang/String:<init>	([C)V
    //   14535: invokevirtual 29	java/lang/String:intern	()Ljava/lang/String;
    //   14538: wide
    //   14542: aload_1
    //   14543: wide
    //   14547: wide
    //   14551: aastore
    //   14552: bipush 67
    //   14554: wide
    //   14558: ldc 163
    //   14560: invokevirtual 21	java/lang/String:toCharArray	()[C
    //   14563: wide
    //   14567: wide
    //   14571: arraylength
    //   14572: wide
    //   14576: wide
    //   14580: iconst_1
    //   14581: if_icmpgt +5679 -> 20260
    //   14584: iconst_0
    //   14585: wide
    //   14589: wide
    //   14593: astore 5
    //   14595: wide
    //   14599: istore 6
    //   14601: wide
    //   14605: wide
    //   14609: wide
    //   14613: wide
    //   14617: wide
    //   14621: wide
    //   14625: wide
    //   14629: wide
    //   14633: caload
    //   14634: istore 31
    //   14636: iload 6
    //   14638: iconst_5
    //   14639: irem
    //   14640: tableswitch	default:+32 -> 14672, 0:+5100->19740, 1:+5109->19749, 2:+5118->19758, 3:+5127->19767
    //   14673: pop
    //   14674: wide
    //   14678: wide
    //   14682: iload 31
    //   14684: ixor
    //   14685: i2c
    //   14686: wide
    //   14690: wide
    //   14694: wide
    //   14698: wide
    //   14702: castore
    //   14703: iload 6
    //   14705: iconst_1
    //   14706: iadd
    //   14707: wide
    //   14711: wide
    //   14715: ifne +28 -> 14743
    //   14718: aload 5
    //   14720: wide
    //   14724: wide
    //   14728: wide
    //   14732: wide
    //   14736: wide
    //   14740: goto -115 -> 14625
    //   14743: wide
    //   14747: wide
    //   14751: aload 5
    //   14753: wide
    //   14757: wide
    //   14761: wide
    //   14765: if_icmpgt -176 -> 14589
    //   14768: new 15	java/lang/String
    //   14771: dup
    //   14772: wide
    //   14776: invokespecial 25	java/lang/String:<init>	([C)V
    //   14779: invokevirtual 29	java/lang/String:intern	()Ljava/lang/String;
    //   14782: wide
    //   14786: aload_1
    //   14787: wide
    //   14791: wide
    //   14795: aastore
    //   14796: bipush 68
    //   14798: wide
    //   14802: ldc 165
    //   14804: invokevirtual 21	java/lang/String:toCharArray	()[C
    //   14807: wide
    //   14811: wide
    //   14815: arraylength
    //   14816: wide
    //   14820: wide
    //   14824: iconst_1
    //   14825: if_icmpgt +5427 -> 20252
    //   14828: iconst_0
    //   14829: wide
    //   14833: wide
    //   14837: astore 5
    //   14839: wide
    //   14843: istore 6
    //   14845: wide
    //   14849: wide
    //   14853: wide
    //   14857: wide
    //   14861: wide
    //   14865: wide
    //   14869: wide
    //   14873: wide
    //   14877: caload
    //   14878: istore 31
    //   14880: iload 6
    //   14882: iconst_5
    //   14883: irem
    //   14884: tableswitch	default:+32 -> 14916, 0:+4892->19776, 1:+4901->19785, 2:+4910->19794, 3:+4919->19803
    //   14917: pop
    //   14918: wide
    //   14922: wide
    //   14926: iload 31
    //   14928: ixor
    //   14929: i2c
    //   14930: wide
    //   14934: wide
    //   14938: wide
    //   14942: wide
    //   14946: castore
    //   14947: iload 6
    //   14949: iconst_1
    //   14950: iadd
    //   14951: wide
    //   14955: wide
    //   14959: ifne +28 -> 14987
    //   14962: aload 5
    //   14964: wide
    //   14968: wide
    //   14972: wide
    //   14976: wide
    //   14980: wide
    //   14984: goto -115 -> 14869
    //   14987: wide
    //   14991: wide
    //   14995: aload 5
    //   14997: wide
    //   15001: wide
    //   15005: wide
    //   15009: if_icmpgt -176 -> 14833
    //   15012: new 15	java/lang/String
    //   15015: dup
    //   15016: wide
    //   15020: invokespecial 25	java/lang/String:<init>	([C)V
    //   15023: invokevirtual 29	java/lang/String:intern	()Ljava/lang/String;
    //   15026: wide
    //   15030: aload_1
    //   15031: wide
    //   15035: wide
    //   15039: aastore
    //   15040: bipush 69
    //   15042: wide
    //   15046: ldc 167
    //   15048: invokevirtual 21	java/lang/String:toCharArray	()[C
    //   15051: wide
    //   15055: wide
    //   15059: arraylength
    //   15060: wide
    //   15064: wide
    //   15068: iconst_1
    //   15069: if_icmpgt +5175 -> 20244
    //   15072: iconst_0
    //   15073: wide
    //   15077: wide
    //   15081: astore 5
    //   15083: wide
    //   15087: istore 6
    //   15089: wide
    //   15093: wide
    //   15097: wide
    //   15101: wide
    //   15105: wide
    //   15109: wide
    //   15113: wide
    //   15117: wide
    //   15121: caload
    //   15122: istore 31
    //   15124: iload 6
    //   15126: iconst_5
    //   15127: irem
    //   15128: tableswitch	default:+32 -> 15160, 0:+4684->19812, 1:+4693->19821, 2:+4702->19830, 3:+4711->19839
    //   15161: pop
    //   15162: wide
    //   15166: wide
    //   15170: iload 31
    //   15172: ixor
    //   15173: i2c
    //   15174: wide
    //   15178: wide
    //   15182: wide
    //   15186: wide
    //   15190: castore
    //   15191: iload 6
    //   15193: iconst_1
    //   15194: iadd
    //   15195: wide
    //   15199: wide
    //   15203: ifne +28 -> 15231
    //   15206: aload 5
    //   15208: wide
    //   15212: wide
    //   15216: wide
    //   15220: wide
    //   15224: wide
    //   15228: goto -115 -> 15113
    //   15231: wide
    //   15235: wide
    //   15239: aload 5
    //   15241: wide
    //   15245: wide
    //   15249: wide
    //   15253: if_icmpgt -176 -> 15077
    //   15256: new 15	java/lang/String
    //   15259: dup
    //   15260: wide
    //   15264: invokespecial 25	java/lang/String:<init>	([C)V
    //   15267: invokevirtual 29	java/lang/String:intern	()Ljava/lang/String;
    //   15270: wide
    //   15274: aload_1
    //   15275: wide
    //   15279: wide
    //   15283: aastore
    //   15284: bipush 70
    //   15286: wide
    //   15290: ldc 169
    //   15292: invokevirtual 21	java/lang/String:toCharArray	()[C
    //   15295: wide
    //   15299: wide
    //   15303: arraylength
    //   15304: wide
    //   15308: wide
    //   15312: iconst_1
    //   15313: if_icmpgt +4923 -> 20236
    //   15316: iconst_0
    //   15317: wide
    //   15321: wide
    //   15325: astore 5
    //   15327: wide
    //   15331: istore 6
    //   15333: wide
    //   15337: wide
    //   15341: wide
    //   15345: wide
    //   15349: wide
    //   15353: wide
    //   15357: wide
    //   15361: wide
    //   15365: caload
    //   15366: istore 31
    //   15368: iload 6
    //   15370: iconst_5
    //   15371: irem
    //   15372: tableswitch	default:+32 -> 15404, 0:+4476->19848, 1:+4485->19857, 2:+4494->19866, 3:+4503->19875
    //   15405: pop
    //   15406: wide
    //   15410: wide
    //   15414: iload 31
    //   15416: ixor
    //   15417: i2c
    //   15418: wide
    //   15422: wide
    //   15426: wide
    //   15430: wide
    //   15434: castore
    //   15435: iload 6
    //   15437: iconst_1
    //   15438: iadd
    //   15439: wide
    //   15443: wide
    //   15447: ifne +28 -> 15475
    //   15450: aload 5
    //   15452: wide
    //   15456: wide
    //   15460: wide
    //   15464: wide
    //   15468: wide
    //   15472: goto -115 -> 15357
    //   15475: wide
    //   15479: wide
    //   15483: aload 5
    //   15485: wide
    //   15489: wide
    //   15493: wide
    //   15497: if_icmpgt -176 -> 15321
    //   15500: new 15	java/lang/String
    //   15503: dup
    //   15504: wide
    //   15508: invokespecial 25	java/lang/String:<init>	([C)V
    //   15511: invokevirtual 29	java/lang/String:intern	()Ljava/lang/String;
    //   15514: wide
    //   15518: aload_1
    //   15519: wide
    //   15523: wide
    //   15527: aastore
    //   15528: bipush 71
    //   15530: wide
    //   15534: ldc 171
    //   15536: invokevirtual 21	java/lang/String:toCharArray	()[C
    //   15539: wide
    //   15543: wide
    //   15547: arraylength
    //   15548: wide
    //   15552: wide
    //   15556: iconst_1
    //   15557: if_icmpgt +4671 -> 20228
    //   15560: iconst_0
    //   15561: wide
    //   15565: wide
    //   15569: astore 5
    //   15571: wide
    //   15575: istore 6
    //   15577: wide
    //   15581: wide
    //   15585: wide
    //   15589: wide
    //   15593: wide
    //   15597: wide
    //   15601: wide
    //   15605: wide
    //   15609: caload
    //   15610: istore 31
    //   15612: iload 6
    //   15614: iconst_5
    //   15615: irem
    //   15616: tableswitch	default:+32 -> 15648, 0:+4268->19884, 1:+4277->19893, 2:+4286->19902, 3:+4295->19911
    //   15649: pop
    //   15650: wide
    //   15654: wide
    //   15658: iload 31
    //   15660: ixor
    //   15661: i2c
    //   15662: wide
    //   15666: wide
    //   15670: wide
    //   15674: wide
    //   15678: castore
    //   15679: iload 6
    //   15681: iconst_1
    //   15682: iadd
    //   15683: wide
    //   15687: wide
    //   15691: ifne +28 -> 15719
    //   15694: aload 5
    //   15696: wide
    //   15700: wide
    //   15704: wide
    //   15708: wide
    //   15712: wide
    //   15716: goto -115 -> 15601
    //   15719: wide
    //   15723: wide
    //   15727: aload 5
    //   15729: wide
    //   15733: wide
    //   15737: wide
    //   15741: if_icmpgt -176 -> 15565
    //   15744: new 15	java/lang/String
    //   15747: dup
    //   15748: wide
    //   15752: invokespecial 25	java/lang/String:<init>	([C)V
    //   15755: invokevirtual 29	java/lang/String:intern	()Ljava/lang/String;
    //   15758: wide
    //   15762: aload_1
    //   15763: wide
    //   15767: wide
    //   15771: aastore
    //   15772: bipush 72
    //   15774: wide
    //   15778: ldc 173
    //   15780: invokevirtual 21	java/lang/String:toCharArray	()[C
    //   15783: wide
    //   15787: wide
    //   15791: arraylength
    //   15792: wide
    //   15796: wide
    //   15800: iconst_1
    //   15801: if_icmpgt +4419 -> 20220
    //   15804: iconst_0
    //   15805: wide
    //   15809: wide
    //   15813: astore 5
    //   15815: wide
    //   15819: istore 6
    //   15821: wide
    //   15825: wide
    //   15829: wide
    //   15833: wide
    //   15837: wide
    //   15841: wide
    //   15845: wide
    //   15849: wide
    //   15853: caload
    //   15854: istore 31
    //   15856: iload 6
    //   15858: iconst_5
    //   15859: irem
    //   15860: tableswitch	default:+32 -> 15892, 0:+4060->19920, 1:+4069->19929, 2:+4078->19938, 3:+4087->19947
    //   15893: pop
    //   15894: wide
    //   15898: wide
    //   15902: iload 31
    //   15904: ixor
    //   15905: i2c
    //   15906: wide
    //   15910: wide
    //   15914: wide
    //   15918: wide
    //   15922: castore
    //   15923: iload 6
    //   15925: iconst_1
    //   15926: iadd
    //   15927: wide
    //   15931: wide
    //   15935: ifne +28 -> 15963
    //   15938: aload 5
    //   15940: wide
    //   15944: wide
    //   15948: wide
    //   15952: wide
    //   15956: wide
    //   15960: goto -115 -> 15845
    //   15963: wide
    //   15967: wide
    //   15971: aload 5
    //   15973: wide
    //   15977: wide
    //   15981: wide
    //   15985: if_icmpgt -176 -> 15809
    //   15988: new 15	java/lang/String
    //   15991: dup
    //   15992: wide
    //   15996: invokespecial 25	java/lang/String:<init>	([C)V
    //   15999: invokevirtual 29	java/lang/String:intern	()Ljava/lang/String;
    //   16002: wide
    //   16006: aload_1
    //   16007: wide
    //   16011: wide
    //   16015: aastore
    //   16016: bipush 73
    //   16018: wide
    //   16022: ldc 175
    //   16024: invokevirtual 21	java/lang/String:toCharArray	()[C
    //   16027: wide
    //   16031: wide
    //   16035: arraylength
    //   16036: wide
    //   16040: wide
    //   16044: iconst_1
    //   16045: if_icmpgt +4167 -> 20212
    //   16048: iconst_0
    //   16049: wide
    //   16053: wide
    //   16057: astore 5
    //   16059: wide
    //   16063: istore 6
    //   16065: wide
    //   16069: wide
    //   16073: wide
    //   16077: wide
    //   16081: wide
    //   16085: wide
    //   16089: wide
    //   16093: wide
    //   16097: caload
    //   16098: istore 31
    //   16100: iload 6
    //   16102: iconst_5
    //   16103: irem
    //   16104: tableswitch	default:+32 -> 16136, 0:+3852->19956, 1:+3861->19965, 2:+3870->19974, 3:+3879->19983
    //   16137: pop
    //   16138: wide
    //   16142: wide
    //   16146: iload 31
    //   16148: ixor
    //   16149: i2c
    //   16150: wide
    //   16154: wide
    //   16158: wide
    //   16162: wide
    //   16166: castore
    //   16167: iload 6
    //   16169: iconst_1
    //   16170: iadd
    //   16171: wide
    //   16175: wide
    //   16179: ifne +28 -> 16207
    //   16182: aload 5
    //   16184: wide
    //   16188: wide
    //   16192: wide
    //   16196: wide
    //   16200: wide
    //   16204: goto -115 -> 16089
    //   16207: wide
    //   16211: wide
    //   16215: aload 5
    //   16217: wide
    //   16221: wide
    //   16225: wide
    //   16229: if_icmpgt -176 -> 16053
    //   16232: new 15	java/lang/String
    //   16235: dup
    //   16236: wide
    //   16240: invokespecial 25	java/lang/String:<init>	([C)V
    //   16243: invokevirtual 29	java/lang/String:intern	()Ljava/lang/String;
    //   16246: wide
    //   16250: aload_1
    //   16251: wide
    //   16255: wide
    //   16259: aastore
    //   16260: bipush 74
    //   16262: wide
    //   16266: ldc 177
    //   16268: invokevirtual 21	java/lang/String:toCharArray	()[C
    //   16271: wide
    //   16275: wide
    //   16279: arraylength
    //   16280: wide
    //   16284: wide
    //   16288: iconst_1
    //   16289: if_icmpgt +3915 -> 20204
    //   16292: iconst_0
    //   16293: wide
    //   16297: wide
    //   16301: astore 5
    //   16303: wide
    //   16307: istore 6
    //   16309: wide
    //   16313: wide
    //   16317: wide
    //   16321: wide
    //   16325: wide
    //   16329: wide
    //   16333: wide
    //   16337: wide
    //   16341: caload
    //   16342: istore 31
    //   16344: iload 6
    //   16346: iconst_5
    //   16347: irem
    //   16348: tableswitch	default:+32 -> 16380, 0:+3644->19992, 1:+3653->20001, 2:+3662->20010, 3:+3671->20019
    //   16381: pop
    //   16382: wide
    //   16386: wide
    //   16390: iload 31
    //   16392: ixor
    //   16393: i2c
    //   16394: wide
    //   16398: wide
    //   16402: wide
    //   16406: wide
    //   16410: castore
    //   16411: iload 6
    //   16413: iconst_1
    //   16414: iadd
    //   16415: wide
    //   16419: wide
    //   16423: ifne +28 -> 16451
    //   16426: aload 5
    //   16428: wide
    //   16432: wide
    //   16436: wide
    //   16440: wide
    //   16444: wide
    //   16448: goto -115 -> 16333
    //   16451: wide
    //   16455: wide
    //   16459: aload 5
    //   16461: wide
    //   16465: wide
    //   16469: wide
    //   16473: if_icmpgt -176 -> 16297
    //   16476: new 15	java/lang/String
    //   16479: dup
    //   16480: wide
    //   16484: invokespecial 25	java/lang/String:<init>	([C)V
    //   16487: invokevirtual 29	java/lang/String:intern	()Ljava/lang/String;
    //   16490: wide
    //   16494: aload_1
    //   16495: wide
    //   16499: wide
    //   16503: aastore
    //   16504: bipush 75
    //   16506: wide
    //   16510: ldc 179
    //   16512: invokevirtual 21	java/lang/String:toCharArray	()[C
    //   16515: wide
    //   16519: wide
    //   16523: arraylength
    //   16524: wide
    //   16528: wide
    //   16532: iconst_1
    //   16533: if_icmpgt +3663 -> 20196
    //   16536: iconst_0
    //   16537: wide
    //   16541: wide
    //   16545: astore 5
    //   16547: wide
    //   16551: istore 6
    //   16553: wide
    //   16557: wide
    //   16561: wide
    //   16565: wide
    //   16569: wide
    //   16573: wide
    //   16577: wide
    //   16581: wide
    //   16585: caload
    //   16586: istore 31
    //   16588: iload 6
    //   16590: iconst_5
    //   16591: irem
    //   16592: tableswitch	default:+32 -> 16624, 0:+3436->20028, 1:+3445->20037, 2:+3454->20046, 3:+3463->20055
    //   16625: pop
    //   16626: wide
    //   16630: wide
    //   16634: iload 31
    //   16636: ixor
    //   16637: i2c
    //   16638: wide
    //   16642: wide
    //   16646: wide
    //   16650: wide
    //   16654: castore
    //   16655: iload 6
    //   16657: iconst_1
    //   16658: iadd
    //   16659: wide
    //   16663: wide
    //   16667: ifne +28 -> 16695
    //   16670: aload 5
    //   16672: wide
    //   16676: wide
    //   16680: wide
    //   16684: wide
    //   16688: wide
    //   16692: goto -115 -> 16577
    //   16695: wide
    //   16699: wide
    //   16703: aload 5
    //   16705: wide
    //   16709: wide
    //   16713: wide
    //   16717: if_icmpgt -176 -> 16541
    //   16720: new 15	java/lang/String
    //   16723: dup
    //   16724: wide
    //   16728: invokespecial 25	java/lang/String:<init>	([C)V
    //   16731: invokevirtual 29	java/lang/String:intern	()Ljava/lang/String;
    //   16734: wide
    //   16738: aload_1
    //   16739: wide
    //   16743: wide
    //   16747: aastore
    //   16748: bipush 76
    //   16750: wide
    //   16754: ldc 181
    //   16756: invokevirtual 21	java/lang/String:toCharArray	()[C
    //   16759: wide
    //   16763: wide
    //   16767: arraylength
    //   16768: wide
    //   16772: wide
    //   16776: iconst_1
    //   16777: if_icmpgt +3411 -> 20188
    //   16780: iconst_0
    //   16781: wide
    //   16785: wide
    //   16789: astore 5
    //   16791: wide
    //   16795: istore 6
    //   16797: wide
    //   16801: wide
    //   16805: wide
    //   16809: wide
    //   16813: wide
    //   16817: wide
    //   16821: wide
    //   16825: wide
    //   16829: caload
    //   16830: istore 31
    //   16832: iload 6
    //   16834: iconst_5
    //   16835: irem
    //   16836: tableswitch	default:+32 -> 16868, 0:+3228->20064, 1:+3237->20073, 2:+3246->20082, 3:+3255->20091
    //   16869: pop
    //   16870: wide
    //   16874: wide
    //   16878: iload 31
    //   16880: ixor
    //   16881: i2c
    //   16882: wide
    //   16886: wide
    //   16890: wide
    //   16894: wide
    //   16898: castore
    //   16899: iload 6
    //   16901: iconst_1
    //   16902: iadd
    //   16903: wide
    //   16907: wide
    //   16911: ifne +28 -> 16939
    //   16914: aload 5
    //   16916: wide
    //   16920: wide
    //   16924: wide
    //   16928: wide
    //   16932: wide
    //   16936: goto -115 -> 16821
    //   16939: wide
    //   16943: wide
    //   16947: aload 5
    //   16949: wide
    //   16953: wide
    //   16957: wide
    //   16961: if_icmpgt -176 -> 16785
    //   16964: new 15	java/lang/String
    //   16967: dup
    //   16968: wide
    //   16972: invokespecial 25	java/lang/String:<init>	([C)V
    //   16975: invokevirtual 29	java/lang/String:intern	()Ljava/lang/String;
    //   16978: wide
    //   16982: aload_1
    //   16983: wide
    //   16987: wide
    //   16991: aastore
    //   16992: bipush 77
    //   16994: wide
    //   16998: ldc 183
    //   17000: invokevirtual 21	java/lang/String:toCharArray	()[C
    //   17003: wide
    //   17007: wide
    //   17011: arraylength
    //   17012: wide
    //   17016: wide
    //   17020: iconst_1
    //   17021: if_icmpgt +3159 -> 20180
    //   17024: iconst_0
    //   17025: wide
    //   17029: wide
    //   17033: astore 5
    //   17035: wide
    //   17039: istore 6
    //   17041: wide
    //   17045: wide
    //   17049: wide
    //   17053: wide
    //   17057: wide
    //   17061: wide
    //   17065: wide
    //   17069: wide
    //   17073: caload
    //   17074: istore 31
    //   17076: iload 6
    //   17078: iconst_5
    //   17079: irem
    //   17080: tableswitch	default:+32 -> 17112, 0:+3020->20100, 1:+3029->20109, 2:+3038->20118, 3:+3047->20127
    //   17113: pop
    //   17114: wide
    //   17118: wide
    //   17122: iload 31
    //   17124: ixor
    //   17125: i2c
    //   17126: wide
    //   17130: wide
    //   17134: wide
    //   17138: wide
    //   17142: castore
    //   17143: iload 6
    //   17145: iconst_1
    //   17146: iadd
    //   17147: wide
    //   17151: wide
    //   17155: ifne +28 -> 17183
    //   17158: aload 5
    //   17160: wide
    //   17164: wide
    //   17168: wide
    //   17172: wide
    //   17176: wide
    //   17180: goto -115 -> 17065
    //   17183: wide
    //   17187: wide
    //   17191: aload 5
    //   17193: wide
    //   17197: wide
    //   17201: wide
    //   17205: if_icmpgt -176 -> 17029
    //   17208: new 15	java/lang/String
    //   17211: dup
    //   17212: wide
    //   17216: invokespecial 25	java/lang/String:<init>	([C)V
    //   17219: invokevirtual 29	java/lang/String:intern	()Ljava/lang/String;
    //   17222: wide
    //   17226: aload_1
    //   17227: wide
    //   17231: wide
    //   17235: aastore
    //   17236: bipush 78
    //   17238: wide
    //   17242: ldc 185
    //   17244: invokevirtual 21	java/lang/String:toCharArray	()[C
    //   17247: wide
    //   17251: wide
    //   17255: arraylength
    //   17256: wide
    //   17260: wide
    //   17264: iconst_1
    //   17265: if_icmpgt +2907 -> 20172
    //   17268: iconst_0
    //   17269: wide
    //   17273: wide
    //   17277: astore 5
    //   17279: wide
    //   17283: istore 6
    //   17285: wide
    //   17289: wide
    //   17293: wide
    //   17297: wide
    //   17301: wide
    //   17305: wide
    //   17309: wide
    //   17313: wide
    //   17317: caload
    //   17318: istore 31
    //   17320: iload 6
    //   17322: iconst_5
    //   17323: irem
    //   17324: tableswitch	default:+32 -> 17356, 0:+2812->20136, 1:+2821->20145, 2:+2830->20154, 3:+2839->20163
    //   17357: pop
    //   17358: wide
    //   17362: wide
    //   17366: iload 31
    //   17368: ixor
    //   17369: i2c
    //   17370: wide
    //   17374: wide
    //   17378: wide
    //   17382: wide
    //   17386: castore
    //   17387: iload 6
    //   17389: iconst_1
    //   17390: iadd
    //   17391: wide
    //   17395: wide
    //   17399: ifne +28 -> 17427
    //   17402: aload 5
    //   17404: wide
    //   17408: wide
    //   17412: wide
    //   17416: wide
    //   17420: wide
    //   17424: goto -115 -> 17309
    //   17427: wide
    //   17431: wide
    //   17435: aload 5
    //   17437: wide
    //   17441: wide
    //   17445: wide
    //   17449: if_icmpgt -176 -> 17273
    //   17452: new 15	java/lang/String
    //   17455: dup
    //   17456: wide
    //   17460: invokespecial 25	java/lang/String:<init>	([C)V
    //   17463: invokevirtual 29	java/lang/String:intern	()Ljava/lang/String;
    //   17466: wide
    //   17470: aload_1
    //   17471: wide
    //   17475: wide
    //   17479: aastore
    //   17480: aload_1
    //   17481: putstatic 187	com/skyhookwireless/wps/Protocol:z	[Ljava/lang/String;
    //   17484: ldc 2
    //   17486: invokevirtual 193	java/lang/Class:desiredAssertionStatus	()Z
    //   17489: ifne +18 -> 17507
    //   17492: iload_0
    //   17493: putstatic 195	com/skyhookwireless/wps/Protocol:_sdkb	Z
    //   17496: new 197	com/skyhookwireless/wps/_sdkyb
    //   17499: dup
    //   17500: invokespecial 199	com/skyhookwireless/wps/_sdkyb:<init>	()V
    //   17503: putstatic 201	com/skyhookwireless/wps/Protocol:_sdka	Ljava/util/Comparator;
    //   17506: return
    //   17507: iconst_0
    //   17508: istore_0
    //   17509: goto -17 -> 17492
    //   17512: bipush 123
    //   17514: istore 11
    //   17516: goto -17428 -> 88
    //   17519: bipush 12
    //   17521: istore 11
    //   17523: goto -17435 -> 88
    //   17526: bipush 45
    //   17528: istore 11
    //   17530: goto -17442 -> 88
    //   17533: bipush 126
    //   17535: istore 11
    //   17537: goto -17449 -> 88
    //   17540: bipush 123
    //   17542: istore 20
    //   17544: goto -17300 -> 244
    //   17547: bipush 12
    //   17549: istore 20
    //   17551: goto -17307 -> 244
    //   17554: bipush 45
    //   17556: istore 20
    //   17558: goto -17314 -> 244
    //   17561: bipush 126
    //   17563: istore 20
    //   17565: goto -17321 -> 244
    //   17568: bipush 123
    //   17570: istore 32
    //   17572: goto -17164 -> 408
    //   17575: bipush 12
    //   17577: istore 32
    //   17579: goto -17171 -> 408
    //   17582: bipush 45
    //   17584: istore 32
    //   17586: goto -17178 -> 408
    //   17589: bipush 126
    //   17591: istore 32
    //   17593: goto -17185 -> 408
    //   17596: bipush 123
    //   17598: istore 43
    //   17600: goto -17028 -> 572
    //   17603: bipush 12
    //   17605: istore 43
    //   17607: goto -17035 -> 572
    //   17610: bipush 45
    //   17612: istore 43
    //   17614: goto -17042 -> 572
    //   17617: bipush 126
    //   17619: istore 43
    //   17621: goto -17049 -> 572
    //   17624: bipush 123
    //   17626: istore 54
    //   17628: goto -16892 -> 736
    //   17631: bipush 12
    //   17633: istore 54
    //   17635: goto -16899 -> 736
    //   17638: bipush 45
    //   17640: istore 54
    //   17642: goto -16906 -> 736
    //   17645: bipush 126
    //   17647: istore 54
    //   17649: goto -16913 -> 736
    //   17652: bipush 123
    //   17654: istore 65
    //   17656: goto -16756 -> 900
    //   17659: bipush 12
    //   17661: istore 65
    //   17663: goto -16763 -> 900
    //   17666: bipush 45
    //   17668: istore 65
    //   17670: goto -16770 -> 900
    //   17673: bipush 126
    //   17675: istore 65
    //   17677: goto -16777 -> 900
    //   17680: bipush 123
    //   17682: istore 76
    //   17684: goto -16616 -> 1068
    //   17687: bipush 12
    //   17689: istore 76
    //   17691: goto -16623 -> 1068
    //   17694: bipush 45
    //   17696: istore 76
    //   17698: goto -16630 -> 1068
    //   17701: bipush 126
    //   17703: istore 76
    //   17705: goto -16637 -> 1068
    //   17708: bipush 123
    //   17710: istore 87
    //   17712: goto -16476 -> 1236
    //   17715: bipush 12
    //   17717: istore 87
    //   17719: goto -16483 -> 1236
    //   17722: bipush 45
    //   17724: istore 87
    //   17726: goto -16490 -> 1236
    //   17729: bipush 126
    //   17731: istore 87
    //   17733: goto -16497 -> 1236
    //   17736: bipush 123
    //   17738: istore 98
    //   17740: goto -16336 -> 1404
    //   17743: bipush 12
    //   17745: istore 98
    //   17747: goto -16343 -> 1404
    //   17750: bipush 45
    //   17752: istore 98
    //   17754: goto -16350 -> 1404
    //   17757: bipush 126
    //   17759: istore 98
    //   17761: goto -16357 -> 1404
    //   17764: bipush 123
    //   17766: istore 109
    //   17768: goto -16196 -> 1572
    //   17771: bipush 12
    //   17773: istore 109
    //   17775: goto -16203 -> 1572
    //   17778: bipush 45
    //   17780: istore 109
    //   17782: goto -16210 -> 1572
    //   17785: bipush 126
    //   17787: istore 109
    //   17789: goto -16217 -> 1572
    //   17792: bipush 123
    //   17794: istore 120
    //   17796: goto -16056 -> 1740
    //   17799: bipush 12
    //   17801: istore 120
    //   17803: goto -16063 -> 1740
    //   17806: bipush 45
    //   17808: istore 120
    //   17810: goto -16070 -> 1740
    //   17813: bipush 126
    //   17815: istore 120
    //   17817: goto -16077 -> 1740
    //   17820: bipush 123
    //   17822: istore 131
    //   17824: goto -15916 -> 1908
    //   17827: bipush 12
    //   17829: istore 131
    //   17831: goto -15923 -> 1908
    //   17834: bipush 45
    //   17836: istore 131
    //   17838: goto -15930 -> 1908
    //   17841: bipush 126
    //   17843: istore 131
    //   17845: goto -15937 -> 1908
    //   17848: bipush 123
    //   17850: istore 141
    //   17852: goto -15780 -> 2072
    //   17855: bipush 12
    //   17857: istore 141
    //   17859: goto -15787 -> 2072
    //   17862: bipush 45
    //   17864: istore 141
    //   17866: goto -15794 -> 2072
    //   17869: bipush 126
    //   17871: istore 141
    //   17873: goto -15801 -> 2072
    //   17876: bipush 123
    //   17878: istore 152
    //   17880: goto -15640 -> 2240
    //   17883: bipush 12
    //   17885: istore 152
    //   17887: goto -15647 -> 2240
    //   17890: bipush 45
    //   17892: istore 152
    //   17894: goto -15654 -> 2240
    //   17897: bipush 126
    //   17899: istore 152
    //   17901: goto -15661 -> 2240
    //   17904: bipush 123
    //   17906: istore 163
    //   17908: goto -15500 -> 2408
    //   17911: bipush 12
    //   17913: istore 163
    //   17915: goto -15507 -> 2408
    //   17918: bipush 45
    //   17920: istore 163
    //   17922: goto -15514 -> 2408
    //   17925: bipush 126
    //   17927: istore 163
    //   17929: goto -15521 -> 2408
    //   17932: bipush 123
    //   17934: istore 174
    //   17936: goto -15360 -> 2576
    //   17939: bipush 12
    //   17941: istore 174
    //   17943: goto -15367 -> 2576
    //   17946: bipush 45
    //   17948: istore 174
    //   17950: goto -15374 -> 2576
    //   17953: bipush 126
    //   17955: istore 174
    //   17957: goto -15381 -> 2576
    //   17960: bipush 123
    //   17962: istore 185
    //   17964: goto -15220 -> 2744
    //   17967: bipush 12
    //   17969: istore 185
    //   17971: goto -15227 -> 2744
    //   17974: bipush 45
    //   17976: istore 185
    //   17978: goto -15234 -> 2744
    //   17981: bipush 126
    //   17983: istore 185
    //   17985: goto -15241 -> 2744
    //   17988: bipush 123
    //   17990: istore 196
    //   17992: goto -15080 -> 2912
    //   17995: bipush 12
    //   17997: istore 196
    //   17999: goto -15087 -> 2912
    //   18002: bipush 45
    //   18004: istore 196
    //   18006: goto -15094 -> 2912
    //   18009: bipush 126
    //   18011: istore 196
    //   18013: goto -15101 -> 2912
    //   18016: bipush 123
    //   18018: istore 207
    //   18020: goto -14940 -> 3080
    //   18023: bipush 12
    //   18025: istore 207
    //   18027: goto -14947 -> 3080
    //   18030: bipush 45
    //   18032: istore 207
    //   18034: goto -14954 -> 3080
    //   18037: bipush 126
    //   18039: istore 207
    //   18041: goto -14961 -> 3080
    //   18044: bipush 123
    //   18046: istore 218
    //   18048: goto -14800 -> 3248
    //   18051: bipush 12
    //   18053: istore 218
    //   18055: goto -14807 -> 3248
    //   18058: bipush 45
    //   18060: istore 218
    //   18062: goto -14814 -> 3248
    //   18065: bipush 126
    //   18067: istore 218
    //   18069: goto -14821 -> 3248
    //   18072: bipush 123
    //   18074: istore 229
    //   18076: goto -14660 -> 3416
    //   18079: bipush 12
    //   18081: istore 229
    //   18083: goto -14667 -> 3416
    //   18086: bipush 45
    //   18088: istore 229
    //   18090: goto -14674 -> 3416
    //   18093: bipush 126
    //   18095: istore 229
    //   18097: goto -14681 -> 3416
    //   18100: bipush 123
    //   18102: istore 240
    //   18104: goto -14520 -> 3584
    //   18107: bipush 12
    //   18109: istore 240
    //   18111: goto -14527 -> 3584
    //   18114: bipush 45
    //   18116: istore 240
    //   18118: goto -14534 -> 3584
    //   18121: bipush 126
    //   18123: istore 240
    //   18125: goto -14541 -> 3584
    //   18128: bipush 123
    //   18130: istore 251
    //   18132: goto -14380 -> 3752
    //   18135: bipush 12
    //   18137: istore 251
    //   18139: goto -14387 -> 3752
    //   18142: bipush 45
    //   18144: istore 251
    //   18146: goto -14394 -> 3752
    //   18149: bipush 126
    //   18151: istore 251
    //   18153: goto -14401 -> 3752
    //   18156: bipush 123
    //   18158: wide
    //   18162: goto -14212 -> 3950
    //   18165: bipush 12
    //   18167: wide
    //   18171: goto -14221 -> 3950
    //   18174: bipush 45
    //   18176: wide
    //   18180: goto -14230 -> 3950
    //   18183: bipush 126
    //   18185: wide
    //   18189: goto -14239 -> 3950
    //   18192: bipush 123
    //   18194: wide
    //   18198: goto -14008 -> 4190
    //   18201: bipush 12
    //   18203: wide
    //   18207: goto -14017 -> 4190
    //   18210: bipush 45
    //   18212: wide
    //   18216: goto -14026 -> 4190
    //   18219: bipush 126
    //   18221: wide
    //   18225: goto -14035 -> 4190
    //   18228: bipush 123
    //   18230: wide
    //   18234: goto -13800 -> 4434
    //   18237: bipush 12
    //   18239: wide
    //   18243: goto -13809 -> 4434
    //   18246: bipush 45
    //   18248: wide
    //   18252: goto -13818 -> 4434
    //   18255: bipush 126
    //   18257: wide
    //   18261: goto -13827 -> 4434
    //   18264: bipush 123
    //   18266: wide
    //   18270: goto -13592 -> 4678
    //   18273: bipush 12
    //   18275: wide
    //   18279: goto -13601 -> 4678
    //   18282: bipush 45
    //   18284: wide
    //   18288: goto -13610 -> 4678
    //   18291: bipush 126
    //   18293: wide
    //   18297: goto -13619 -> 4678
    //   18300: bipush 123
    //   18302: wide
    //   18306: goto -13384 -> 4922
    //   18309: bipush 12
    //   18311: wide
    //   18315: goto -13393 -> 4922
    //   18318: bipush 45
    //   18320: wide
    //   18324: goto -13402 -> 4922
    //   18327: bipush 126
    //   18329: wide
    //   18333: goto -13411 -> 4922
    //   18336: bipush 123
    //   18338: wide
    //   18342: goto -13176 -> 5166
    //   18345: bipush 12
    //   18347: wide
    //   18351: goto -13185 -> 5166
    //   18354: bipush 45
    //   18356: wide
    //   18360: goto -13194 -> 5166
    //   18363: bipush 126
    //   18365: wide
    //   18369: goto -13203 -> 5166
    //   18372: bipush 123
    //   18374: wide
    //   18378: goto -12968 -> 5410
    //   18381: bipush 12
    //   18383: wide
    //   18387: goto -12977 -> 5410
    //   18390: bipush 45
    //   18392: wide
    //   18396: goto -12986 -> 5410
    //   18399: bipush 126
    //   18401: wide
    //   18405: goto -12995 -> 5410
    //   18408: bipush 123
    //   18410: wide
    //   18414: goto -12760 -> 5654
    //   18417: bipush 12
    //   18419: wide
    //   18423: goto -12769 -> 5654
    //   18426: bipush 45
    //   18428: wide
    //   18432: goto -12778 -> 5654
    //   18435: bipush 126
    //   18437: wide
    //   18441: goto -12787 -> 5654
    //   18444: bipush 123
    //   18446: wide
    //   18450: goto -12552 -> 5898
    //   18453: bipush 12
    //   18455: wide
    //   18459: goto -12561 -> 5898
    //   18462: bipush 45
    //   18464: wide
    //   18468: goto -12570 -> 5898
    //   18471: bipush 126
    //   18473: wide
    //   18477: goto -12579 -> 5898
    //   18480: bipush 123
    //   18482: wide
    //   18486: goto -12344 -> 6142
    //   18489: bipush 12
    //   18491: wide
    //   18495: goto -12353 -> 6142
    //   18498: bipush 45
    //   18500: wide
    //   18504: goto -12362 -> 6142
    //   18507: bipush 126
    //   18509: wide
    //   18513: goto -12371 -> 6142
    //   18516: bipush 123
    //   18518: wide
    //   18522: goto -12136 -> 6386
    //   18525: bipush 12
    //   18527: wide
    //   18531: goto -12145 -> 6386
    //   18534: bipush 45
    //   18536: wide
    //   18540: goto -12154 -> 6386
    //   18543: bipush 126
    //   18545: wide
    //   18549: goto -12163 -> 6386
    //   18552: bipush 123
    //   18554: wide
    //   18558: goto -11928 -> 6630
    //   18561: bipush 12
    //   18563: wide
    //   18567: goto -11937 -> 6630
    //   18570: bipush 45
    //   18572: wide
    //   18576: goto -11946 -> 6630
    //   18579: bipush 126
    //   18581: wide
    //   18585: goto -11955 -> 6630
    //   18588: bipush 123
    //   18590: wide
    //   18594: goto -11720 -> 6874
    //   18597: bipush 12
    //   18599: wide
    //   18603: goto -11729 -> 6874
    //   18606: bipush 45
    //   18608: wide
    //   18612: goto -11738 -> 6874
    //   18615: bipush 126
    //   18617: wide
    //   18621: goto -11747 -> 6874
    //   18624: bipush 123
    //   18626: wide
    //   18630: goto -11512 -> 7118
    //   18633: bipush 12
    //   18635: wide
    //   18639: goto -11521 -> 7118
    //   18642: bipush 45
    //   18644: wide
    //   18648: goto -11530 -> 7118
    //   18651: bipush 126
    //   18653: wide
    //   18657: goto -11539 -> 7118
    //   18660: bipush 123
    //   18662: wide
    //   18666: goto -11304 -> 7362
    //   18669: bipush 12
    //   18671: wide
    //   18675: goto -11313 -> 7362
    //   18678: bipush 45
    //   18680: wide
    //   18684: goto -11322 -> 7362
    //   18687: bipush 126
    //   18689: wide
    //   18693: goto -11331 -> 7362
    //   18696: bipush 123
    //   18698: wide
    //   18702: goto -11096 -> 7606
    //   18705: bipush 12
    //   18707: wide
    //   18711: goto -11105 -> 7606
    //   18714: bipush 45
    //   18716: wide
    //   18720: goto -11114 -> 7606
    //   18723: bipush 126
    //   18725: wide
    //   18729: goto -11123 -> 7606
    //   18732: bipush 123
    //   18734: wide
    //   18738: goto -10888 -> 7850
    //   18741: bipush 12
    //   18743: wide
    //   18747: goto -10897 -> 7850
    //   18750: bipush 45
    //   18752: wide
    //   18756: goto -10906 -> 7850
    //   18759: bipush 126
    //   18761: wide
    //   18765: goto -10915 -> 7850
    //   18768: bipush 123
    //   18770: wide
    //   18774: goto -10680 -> 8094
    //   18777: bipush 12
    //   18779: wide
    //   18783: goto -10689 -> 8094
    //   18786: bipush 45
    //   18788: wide
    //   18792: goto -10698 -> 8094
    //   18795: bipush 126
    //   18797: wide
    //   18801: goto -10707 -> 8094
    //   18804: bipush 123
    //   18806: wide
    //   18810: goto -10472 -> 8338
    //   18813: bipush 12
    //   18815: wide
    //   18819: goto -10481 -> 8338
    //   18822: bipush 45
    //   18824: wide
    //   18828: goto -10490 -> 8338
    //   18831: bipush 126
    //   18833: wide
    //   18837: goto -10499 -> 8338
    //   18840: bipush 123
    //   18842: wide
    //   18846: goto -10264 -> 8582
    //   18849: bipush 12
    //   18851: wide
    //   18855: goto -10273 -> 8582
    //   18858: bipush 45
    //   18860: wide
    //   18864: goto -10282 -> 8582
    //   18867: bipush 126
    //   18869: wide
    //   18873: goto -10291 -> 8582
    //   18876: bipush 123
    //   18878: wide
    //   18882: goto -10056 -> 8826
    //   18885: bipush 12
    //   18887: wide
    //   18891: goto -10065 -> 8826
    //   18894: bipush 45
    //   18896: wide
    //   18900: goto -10074 -> 8826
    //   18903: bipush 126
    //   18905: wide
    //   18909: goto -10083 -> 8826
    //   18912: bipush 123
    //   18914: wide
    //   18918: goto -9848 -> 9070
    //   18921: bipush 12
    //   18923: wide
    //   18927: goto -9857 -> 9070
    //   18930: bipush 45
    //   18932: wide
    //   18936: goto -9866 -> 9070
    //   18939: bipush 126
    //   18941: wide
    //   18945: goto -9875 -> 9070
    //   18948: bipush 123
    //   18950: wide
    //   18954: goto -9644 -> 9310
    //   18957: bipush 12
    //   18959: wide
    //   18963: goto -9653 -> 9310
    //   18966: bipush 45
    //   18968: wide
    //   18972: goto -9662 -> 9310
    //   18975: bipush 126
    //   18977: wide
    //   18981: goto -9671 -> 9310
    //   18984: bipush 123
    //   18986: wide
    //   18990: goto -9436 -> 9554
    //   18993: bipush 12
    //   18995: wide
    //   18999: goto -9445 -> 9554
    //   19002: bipush 45
    //   19004: wide
    //   19008: goto -9454 -> 9554
    //   19011: bipush 126
    //   19013: wide
    //   19017: goto -9463 -> 9554
    //   19020: bipush 123
    //   19022: wide
    //   19026: goto -9228 -> 9798
    //   19029: bipush 12
    //   19031: wide
    //   19035: goto -9237 -> 9798
    //   19038: bipush 45
    //   19040: wide
    //   19044: goto -9246 -> 9798
    //   19047: bipush 126
    //   19049: wide
    //   19053: goto -9255 -> 9798
    //   19056: bipush 123
    //   19058: wide
    //   19062: goto -9020 -> 10042
    //   19065: bipush 12
    //   19067: wide
    //   19071: goto -9029 -> 10042
    //   19074: bipush 45
    //   19076: wide
    //   19080: goto -9038 -> 10042
    //   19083: bipush 126
    //   19085: wide
    //   19089: goto -9047 -> 10042
    //   19092: bipush 123
    //   19094: wide
    //   19098: goto -8812 -> 10286
    //   19101: bipush 12
    //   19103: wide
    //   19107: goto -8821 -> 10286
    //   19110: bipush 45
    //   19112: wide
    //   19116: goto -8830 -> 10286
    //   19119: bipush 126
    //   19121: wide
    //   19125: goto -8839 -> 10286
    //   19128: bipush 123
    //   19130: wide
    //   19134: goto -8604 -> 10530
    //   19137: bipush 12
    //   19139: wide
    //   19143: goto -8613 -> 10530
    //   19146: bipush 45
    //   19148: wide
    //   19152: goto -8622 -> 10530
    //   19155: bipush 126
    //   19157: wide
    //   19161: goto -8631 -> 10530
    //   19164: bipush 123
    //   19166: wide
    //   19170: goto -8396 -> 10774
    //   19173: bipush 12
    //   19175: wide
    //   19179: goto -8405 -> 10774
    //   19182: bipush 45
    //   19184: wide
    //   19188: goto -8414 -> 10774
    //   19191: bipush 126
    //   19193: wide
    //   19197: goto -8423 -> 10774
    //   19200: bipush 123
    //   19202: wide
    //   19206: goto -8188 -> 11018
    //   19209: bipush 12
    //   19211: wide
    //   19215: goto -8197 -> 11018
    //   19218: bipush 45
    //   19220: wide
    //   19224: goto -8206 -> 11018
    //   19227: bipush 126
    //   19229: wide
    //   19233: goto -8215 -> 11018
    //   19236: bipush 123
    //   19238: wide
    //   19242: goto -7980 -> 11262
    //   19245: bipush 12
    //   19247: wide
    //   19251: goto -7989 -> 11262
    //   19254: bipush 45
    //   19256: wide
    //   19260: goto -7998 -> 11262
    //   19263: bipush 126
    //   19265: wide
    //   19269: goto -8007 -> 11262
    //   19272: bipush 123
    //   19274: wide
    //   19278: goto -7772 -> 11506
    //   19281: bipush 12
    //   19283: wide
    //   19287: goto -7781 -> 11506
    //   19290: bipush 45
    //   19292: wide
    //   19296: goto -7790 -> 11506
    //   19299: bipush 126
    //   19301: wide
    //   19305: goto -7799 -> 11506
    //   19308: bipush 123
    //   19310: wide
    //   19314: goto -7564 -> 11750
    //   19317: bipush 12
    //   19319: wide
    //   19323: goto -7573 -> 11750
    //   19326: bipush 45
    //   19328: wide
    //   19332: goto -7582 -> 11750
    //   19335: bipush 126
    //   19337: wide
    //   19341: goto -7591 -> 11750
    //   19344: bipush 123
    //   19346: wide
    //   19350: goto -7356 -> 11994
    //   19353: bipush 12
    //   19355: wide
    //   19359: goto -7365 -> 11994
    //   19362: bipush 45
    //   19364: wide
    //   19368: goto -7374 -> 11994
    //   19371: bipush 126
    //   19373: wide
    //   19377: goto -7383 -> 11994
    //   19380: bipush 123
    //   19382: wide
    //   19386: goto -7148 -> 12238
    //   19389: bipush 12
    //   19391: wide
    //   19395: goto -7157 -> 12238
    //   19398: bipush 45
    //   19400: wide
    //   19404: goto -7166 -> 12238
    //   19407: bipush 126
    //   19409: wide
    //   19413: goto -7175 -> 12238
    //   19416: bipush 123
    //   19418: wide
    //   19422: goto -6940 -> 12482
    //   19425: bipush 12
    //   19427: wide
    //   19431: goto -6949 -> 12482
    //   19434: bipush 45
    //   19436: wide
    //   19440: goto -6958 -> 12482
    //   19443: bipush 126
    //   19445: wide
    //   19449: goto -6967 -> 12482
    //   19452: bipush 123
    //   19454: wide
    //   19458: goto -6732 -> 12726
    //   19461: bipush 12
    //   19463: wide
    //   19467: goto -6741 -> 12726
    //   19470: bipush 45
    //   19472: wide
    //   19476: goto -6750 -> 12726
    //   19479: bipush 126
    //   19481: wide
    //   19485: goto -6759 -> 12726
    //   19488: bipush 123
    //   19490: wide
    //   19494: goto -6524 -> 12970
    //   19497: bipush 12
    //   19499: wide
    //   19503: goto -6533 -> 12970
    //   19506: bipush 45
    //   19508: wide
    //   19512: goto -6542 -> 12970
    //   19515: bipush 126
    //   19517: wide
    //   19521: goto -6551 -> 12970
    //   19524: bipush 123
    //   19526: wide
    //   19530: goto -6316 -> 13214
    //   19533: bipush 12
    //   19535: wide
    //   19539: goto -6325 -> 13214
    //   19542: bipush 45
    //   19544: wide
    //   19548: goto -6334 -> 13214
    //   19551: bipush 126
    //   19553: wide
    //   19557: goto -6343 -> 13214
    //   19560: bipush 123
    //   19562: wide
    //   19566: goto -6108 -> 13458
    //   19569: bipush 12
    //   19571: wide
    //   19575: goto -6117 -> 13458
    //   19578: bipush 45
    //   19580: wide
    //   19584: goto -6126 -> 13458
    //   19587: bipush 126
    //   19589: wide
    //   19593: goto -6135 -> 13458
    //   19596: bipush 123
    //   19598: wide
    //   19602: goto -5900 -> 13702
    //   19605: bipush 12
    //   19607: wide
    //   19611: goto -5909 -> 13702
    //   19614: bipush 45
    //   19616: wide
    //   19620: goto -5918 -> 13702
    //   19623: bipush 126
    //   19625: wide
    //   19629: goto -5927 -> 13702
    //   19632: bipush 123
    //   19634: wide
    //   19638: goto -5692 -> 13946
    //   19641: bipush 12
    //   19643: wide
    //   19647: goto -5701 -> 13946
    //   19650: bipush 45
    //   19652: wide
    //   19656: goto -5710 -> 13946
    //   19659: bipush 126
    //   19661: wide
    //   19665: goto -5719 -> 13946
    //   19668: bipush 123
    //   19670: wide
    //   19674: goto -5484 -> 14190
    //   19677: bipush 12
    //   19679: wide
    //   19683: goto -5493 -> 14190
    //   19686: bipush 45
    //   19688: wide
    //   19692: goto -5502 -> 14190
    //   19695: bipush 126
    //   19697: wide
    //   19701: goto -5511 -> 14190
    //   19704: bipush 123
    //   19706: wide
    //   19710: goto -5276 -> 14434
    //   19713: bipush 12
    //   19715: wide
    //   19719: goto -5285 -> 14434
    //   19722: bipush 45
    //   19724: wide
    //   19728: goto -5294 -> 14434
    //   19731: bipush 126
    //   19733: wide
    //   19737: goto -5303 -> 14434
    //   19740: bipush 123
    //   19742: wide
    //   19746: goto -5068 -> 14678
    //   19749: bipush 12
    //   19751: wide
    //   19755: goto -5077 -> 14678
    //   19758: bipush 45
    //   19760: wide
    //   19764: goto -5086 -> 14678
    //   19767: bipush 126
    //   19769: wide
    //   19773: goto -5095 -> 14678
    //   19776: bipush 123
    //   19778: wide
    //   19782: goto -4860 -> 14922
    //   19785: bipush 12
    //   19787: wide
    //   19791: goto -4869 -> 14922
    //   19794: bipush 45
    //   19796: wide
    //   19800: goto -4878 -> 14922
    //   19803: bipush 126
    //   19805: wide
    //   19809: goto -4887 -> 14922
    //   19812: bipush 123
    //   19814: wide
    //   19818: goto -4652 -> 15166
    //   19821: bipush 12
    //   19823: wide
    //   19827: goto -4661 -> 15166
    //   19830: bipush 45
    //   19832: wide
    //   19836: goto -4670 -> 15166
    //   19839: bipush 126
    //   19841: wide
    //   19845: goto -4679 -> 15166
    //   19848: bipush 123
    //   19850: wide
    //   19854: goto -4444 -> 15410
    //   19857: bipush 12
    //   19859: wide
    //   19863: goto -4453 -> 15410
    //   19866: bipush 45
    //   19868: wide
    //   19872: goto -4462 -> 15410
    //   19875: bipush 126
    //   19877: wide
    //   19881: goto -4471 -> 15410
    //   19884: bipush 123
    //   19886: wide
    //   19890: goto -4236 -> 15654
    //   19893: bipush 12
    //   19895: wide
    //   19899: goto -4245 -> 15654
    //   19902: bipush 45
    //   19904: wide
    //   19908: goto -4254 -> 15654
    //   19911: bipush 126
    //   19913: wide
    //   19917: goto -4263 -> 15654
    //   19920: bipush 123
    //   19922: wide
    //   19926: goto -4028 -> 15898
    //   19929: bipush 12
    //   19931: wide
    //   19935: goto -4037 -> 15898
    //   19938: bipush 45
    //   19940: wide
    //   19944: goto -4046 -> 15898
    //   19947: bipush 126
    //   19949: wide
    //   19953: goto -4055 -> 15898
    //   19956: bipush 123
    //   19958: wide
    //   19962: goto -3820 -> 16142
    //   19965: bipush 12
    //   19967: wide
    //   19971: goto -3829 -> 16142
    //   19974: bipush 45
    //   19976: wide
    //   19980: goto -3838 -> 16142
    //   19983: bipush 126
    //   19985: wide
    //   19989: goto -3847 -> 16142
    //   19992: bipush 123
    //   19994: wide
    //   19998: goto -3612 -> 16386
    //   20001: bipush 12
    //   20003: wide
    //   20007: goto -3621 -> 16386
    //   20010: bipush 45
    //   20012: wide
    //   20016: goto -3630 -> 16386
    //   20019: bipush 126
    //   20021: wide
    //   20025: goto -3639 -> 16386
    //   20028: bipush 123
    //   20030: wide
    //   20034: goto -3404 -> 16630
    //   20037: bipush 12
    //   20039: wide
    //   20043: goto -3413 -> 16630
    //   20046: bipush 45
    //   20048: wide
    //   20052: goto -3422 -> 16630
    //   20055: bipush 126
    //   20057: wide
    //   20061: goto -3431 -> 16630
    //   20064: bipush 123
    //   20066: wide
    //   20070: goto -3196 -> 16874
    //   20073: bipush 12
    //   20075: wide
    //   20079: goto -3205 -> 16874
    //   20082: bipush 45
    //   20084: wide
    //   20088: goto -3214 -> 16874
    //   20091: bipush 126
    //   20093: wide
    //   20097: goto -3223 -> 16874
    //   20100: bipush 123
    //   20102: wide
    //   20106: goto -2988 -> 17118
    //   20109: bipush 12
    //   20111: wide
    //   20115: goto -2997 -> 17118
    //   20118: bipush 45
    //   20120: wide
    //   20124: goto -3006 -> 17118
    //   20127: bipush 126
    //   20129: wide
    //   20133: goto -3015 -> 17118
    //   20136: bipush 123
    //   20138: wide
    //   20142: goto -2780 -> 17362
    //   20145: bipush 12
    //   20147: wide
    //   20151: goto -2789 -> 17362
    //   20154: bipush 45
    //   20156: wide
    //   20160: goto -2798 -> 17362
    //   20163: bipush 126
    //   20165: wide
    //   20169: goto -2807 -> 17362
    //   20172: iconst_0
    //   20173: wide
    //   20177: goto -2736 -> 17441
    //   20180: iconst_0
    //   20181: wide
    //   20185: goto -2988 -> 17197
    //   20188: iconst_0
    //   20189: wide
    //   20193: goto -3240 -> 16953
    //   20196: iconst_0
    //   20197: wide
    //   20201: goto -3492 -> 16709
    //   20204: iconst_0
    //   20205: wide
    //   20209: goto -3744 -> 16465
    //   20212: iconst_0
    //   20213: wide
    //   20217: goto -3996 -> 16221
    //   20220: iconst_0
    //   20221: wide
    //   20225: goto -4248 -> 15977
    //   20228: iconst_0
    //   20229: wide
    //   20233: goto -4500 -> 15733
    //   20236: iconst_0
    //   20237: wide
    //   20241: goto -4752 -> 15489
    //   20244: iconst_0
    //   20245: wide
    //   20249: goto -5004 -> 15245
    //   20252: iconst_0
    //   20253: wide
    //   20257: goto -5256 -> 15001
    //   20260: iconst_0
    //   20261: wide
    //   20265: goto -5508 -> 14757
    //   20268: iconst_0
    //   20269: wide
    //   20273: goto -5760 -> 14513
    //   20276: iconst_0
    //   20277: wide
    //   20281: goto -6012 -> 14269
    //   20284: iconst_0
    //   20285: wide
    //   20289: goto -6264 -> 14025
    //   20292: iconst_0
    //   20293: wide
    //   20297: goto -6516 -> 13781
    //   20300: iconst_0
    //   20301: wide
    //   20305: goto -6768 -> 13537
    //   20308: iconst_0
    //   20309: wide
    //   20313: goto -7020 -> 13293
    //   20316: iconst_0
    //   20317: wide
    //   20321: goto -7272 -> 13049
    //   20324: iconst_0
    //   20325: wide
    //   20329: goto -7524 -> 12805
    //   20332: iconst_0
    //   20333: wide
    //   20337: goto -7776 -> 12561
    //   20340: iconst_0
    //   20341: wide
    //   20345: goto -8028 -> 12317
    //   20348: iconst_0
    //   20349: wide
    //   20353: goto -8280 -> 12073
    //   20356: iconst_0
    //   20357: wide
    //   20361: goto -8532 -> 11829
    //   20364: iconst_0
    //   20365: wide
    //   20369: goto -8784 -> 11585
    //   20372: iconst_0
    //   20373: wide
    //   20377: goto -9036 -> 11341
    //   20380: iconst_0
    //   20381: wide
    //   20385: goto -9288 -> 11097
    //   20388: iconst_0
    //   20389: wide
    //   20393: goto -9540 -> 10853
    //   20396: iconst_0
    //   20397: wide
    //   20401: goto -9792 -> 10609
    //   20404: iconst_0
    //   20405: wide
    //   20409: goto -10044 -> 10365
    //   20412: iconst_0
    //   20413: wide
    //   20417: goto -10296 -> 10121
    //   20420: iconst_0
    //   20421: wide
    //   20425: goto -10548 -> 9877
    //   20428: iconst_0
    //   20429: wide
    //   20433: goto -10800 -> 9633
    //   20436: iconst_0
    //   20437: wide
    //   20441: goto -11050 -> 9391
    //   20444: iconst_0
    //   20445: wide
    //   20449: goto -11300 -> 9149
    //   20452: iconst_0
    //   20453: wide
    //   20457: goto -11552 -> 8905
    //   20460: iconst_0
    //   20461: wide
    //   20465: goto -11804 -> 8661
    //   20468: iconst_0
    //   20469: wide
    //   20473: goto -12056 -> 8417
    //   20476: iconst_0
    //   20477: wide
    //   20481: goto -12308 -> 8173
    //   20484: iconst_0
    //   20485: wide
    //   20489: goto -12560 -> 7929
    //   20492: iconst_0
    //   20493: wide
    //   20497: goto -12812 -> 7685
    //   20500: iconst_0
    //   20501: wide
    //   20505: goto -13064 -> 7441
    //   20508: iconst_0
    //   20509: wide
    //   20513: goto -13316 -> 7197
    //   20516: iconst_0
    //   20517: wide
    //   20521: goto -13568 -> 6953
    //   20524: iconst_0
    //   20525: wide
    //   20529: goto -13820 -> 6709
    //   20532: iconst_0
    //   20533: wide
    //   20537: goto -14072 -> 6465
    //   20540: iconst_0
    //   20541: wide
    //   20545: goto -14324 -> 6221
    //   20548: iconst_0
    //   20549: wide
    //   20553: goto -14576 -> 5977
    //   20556: iconst_0
    //   20557: wide
    //   20561: goto -14828 -> 5733
    //   20564: iconst_0
    //   20565: wide
    //   20569: goto -15080 -> 5489
    //   20572: iconst_0
    //   20573: wide
    //   20577: goto -15332 -> 5245
    //   20580: iconst_0
    //   20581: wide
    //   20585: goto -15584 -> 5001
    //   20588: iconst_0
    //   20589: wide
    //   20593: goto -15836 -> 4757
    //   20596: iconst_0
    //   20597: wide
    //   20601: goto -16088 -> 4513
    //   20604: iconst_0
    //   20605: wide
    //   20609: goto -16340 -> 4269
    //   20612: iconst_0
    //   20613: wide
    //   20617: goto -16588 -> 4029
    //   20620: iconst_0
    //   20621: istore 247
    //   20623: goto -16822 -> 3801
    //   20626: iconst_0
    //   20627: istore 236
    //   20629: goto -16996 -> 3633
    //   20632: iconst_0
    //   20633: istore 225
    //   20635: goto -17170 -> 3465
    //   20638: iconst_0
    //   20639: istore 214
    //   20641: goto -17344 -> 3297
    //   20644: iconst_0
    //   20645: istore 203
    //   20647: goto -17518 -> 3129
    //   20650: iconst_0
    //   20651: istore 192
    //   20653: goto -17692 -> 2961
    //   20656: iconst_0
    //   20657: istore 181
    //   20659: goto -17866 -> 2793
    //   20662: iconst_0
    //   20663: istore 170
    //   20665: goto -18040 -> 2625
    //   20668: iconst_0
    //   20669: istore 159
    //   20671: goto -18214 -> 2457
    //   20674: iconst_0
    //   20675: istore 148
    //   20677: goto -18388 -> 2289
    //   20680: iconst_0
    //   20681: istore 137
    //   20683: goto -18562 -> 2121
    //   20686: iconst_0
    //   20687: istore 127
    //   20689: goto -18732 -> 1957
    //   20692: iconst_0
    //   20693: istore 116
    //   20695: goto -18906 -> 1789
    //   20698: iconst_0
    //   20699: istore 105
    //   20701: goto -19080 -> 1621
    //   20704: iconst_0
    //   20705: istore 94
    //   20707: goto -19254 -> 1453
    //   20710: iconst_0
    //   20711: istore 83
    //   20713: goto -19428 -> 1285
    //   20716: iconst_0
    //   20717: istore 72
    //   20719: goto -19602 -> 1117
    //   20722: iconst_0
    //   20723: istore 61
    //   20725: goto -19776 -> 949
    //   20728: iconst_0
    //   20729: istore 50
    //   20731: goto -19946 -> 785
    //   20734: iconst_0
    //   20735: istore 39
    //   20737: goto -20116 -> 621
    //   20740: iconst_0
    //   20741: istore 27
    //   20743: goto -20286 -> 457
    //   20746: iconst_0
    //   20747: istore 16
    //   20749: goto -20456 -> 293
    //   20752: iconst_0
    //   20753: istore 4
    //   20755: goto -20620 -> 135
  }

  private static int _sdka(int paramInt)
  {
    return paramInt * 128;
  }

  private static int _sdka(_sdkzb param_sdkzb)
  {
    int i = _sdkb(param_sdkzb.getAPs());
    int j = _sdkc(param_sdkzb.getCells());
    int k = i + j;
    int m = _sdkd(param_sdkzb.getGpsLocations());
    return k + m;
  }

  private static String _sdka(_sdkab param_sdkab, _sdkec param_sdkec)
  {
    StringBuilder localStringBuilder1 = new StringBuilder(128);
    String str1 = z[51];
    StringBuilder localStringBuilder2 = localStringBuilder1.append(str1);
    String str2 = z[61];
    StringBuilder localStringBuilder3 = localStringBuilder2.append(str2);
    int i = param_sdkab._sdka()._sdkd();
    StringBuilder localStringBuilder4 = localStringBuilder3.append(i);
    String str3 = z[53];
    StringBuilder localStringBuilder5 = localStringBuilder4.append(str3);
    String str4 = z[52];
    StringBuilder localStringBuilder6 = localStringBuilder5.append(str4);
    int j = param_sdkab._sdka()._sdke();
    StringBuilder localStringBuilder7 = localStringBuilder6.append(j);
    String str5 = z[54];
    StringBuilder localStringBuilder8 = localStringBuilder7.append(str5);
    if ((param_sdkab._sdka()._sdkc() != -1) && (param_sdkab._sdka()._sdkb() != -1))
    {
      String str6 = z[55];
      StringBuilder localStringBuilder9 = localStringBuilder1.append(str6);
      int k = param_sdkab._sdka()._sdkc();
      StringBuilder localStringBuilder10 = localStringBuilder9.append(k);
      String str7 = z[66];
      StringBuilder localStringBuilder11 = localStringBuilder10.append(str7);
      String str8 = z[58];
      StringBuilder localStringBuilder12 = localStringBuilder11.append(str8);
      int m = param_sdkab._sdka()._sdkb();
      StringBuilder localStringBuilder13 = localStringBuilder12.append(m);
      String str9 = z[62];
      StringBuilder localStringBuilder14 = localStringBuilder13.append(str9);
      if (Location._sdki == 0);
    }
    else
    {
      if ((!_sdkb) && (param_sdkab._sdka()._sdka() == -1))
        throw new AssertionError();
      String str10 = z[59];
      StringBuilder localStringBuilder15 = localStringBuilder1.append(str10);
      int n = param_sdkab._sdka()._sdka();
      StringBuilder localStringBuilder16 = localStringBuilder15.append(n);
      String str11 = z[64];
      StringBuilder localStringBuilder17 = localStringBuilder16.append(str11);
    }
    String str12 = z[63];
    StringBuilder localStringBuilder18 = localStringBuilder1.append(str12);
    int i1 = param_sdkab._sdkb();
    StringBuilder localStringBuilder19 = localStringBuilder18.append(i1);
    String str13 = z[65];
    StringBuilder localStringBuilder20 = localStringBuilder19.append(str13);
    if (param_sdkab._sdka() != 0)
    {
      String str14 = z[60];
      StringBuilder localStringBuilder21 = localStringBuilder1.append(str14);
      int i2 = param_sdkab._sdkb();
      StringBuilder localStringBuilder22 = localStringBuilder21.append(i2);
      String str15 = z[57];
      StringBuilder localStringBuilder23 = localStringBuilder22.append(str15);
    }
    long l = param_sdkab.getAge()._sdka(param_sdkec);
    if (l > 0L)
    {
      String str16 = z[44];
      StringBuilder localStringBuilder24 = localStringBuilder1.append(str16).append(l);
      String str17 = z[47];
      StringBuilder localStringBuilder25 = localStringBuilder24.append(str17);
    }
    String str18 = z[56];
    StringBuilder localStringBuilder26 = localStringBuilder1.append(str18);
    return localStringBuilder1.toString();
  }

  private static String _sdka(_sdkjc param_sdkjc, long paramLong)
  {
    StringBuilder localStringBuilder1 = new StringBuilder(128);
    String str1 = z[43];
    StringBuilder localStringBuilder2 = localStringBuilder1.append(str1);
    String str2 = param_sdkjc._sdka().toString();
    StringBuilder localStringBuilder3 = localStringBuilder1.append(str2);
    String str3 = z[46];
    StringBuilder localStringBuilder4 = localStringBuilder1.append(str3);
    int i = param_sdkjc._sdka();
    StringBuilder localStringBuilder5 = localStringBuilder1.append(i);
    String str4 = z[48];
    StringBuilder localStringBuilder6 = localStringBuilder1.append(str4);
    if (paramLong >= 0L)
    {
      String str5 = z[44];
      StringBuilder localStringBuilder7 = localStringBuilder1.append(str5);
      long l1 = param_sdkjc._sdkb();
      long l2 = paramLong - l1;
      StringBuilder localStringBuilder8 = localStringBuilder1.append(l2);
      String str6 = z[47];
      StringBuilder localStringBuilder9 = localStringBuilder1.append(str6);
    }
    String str7 = z[45];
    StringBuilder localStringBuilder10 = localStringBuilder1.append(str7);
    return localStringBuilder1.toString();
  }

  private static String _sdka(ScanHistory paramScanHistory, long paramLong)
  {
    int i = Location._sdki;
    if (paramScanHistory.numAPs() <= 0);
    StringBuilder localStringBuilder1;
    for (String str1 = ""; ; str1 = localStringBuilder1.toString())
    {
      return str1;
      HashSet localHashSet = new HashSet();
      Iterator localIterator = paramScanHistory.iterator();
      do
      {
        if (!localIterator.hasNext())
          break;
        ArrayList localArrayList = ((_sdkzb)localIterator.next()).getAPs();
        boolean bool = localHashSet.addAll(localArrayList);
      }
      while (i == 0);
      int j = _sdkb(localHashSet);
      localStringBuilder1 = new StringBuilder(j);
      String str2 = z[0];
      StringBuilder localStringBuilder2 = localStringBuilder1.append(str2);
      String str3 = _sdka(localHashSet, paramLong);
      StringBuilder localStringBuilder3 = localStringBuilder1.append(str3);
      String str4 = z[1];
      StringBuilder localStringBuilder4 = localStringBuilder1.append(str4);
    }
  }

  private static String _sdka(ScanHistory paramScanHistory, _sdkec param_sdkec)
  {
    int i = Location._sdki;
    if (paramScanHistory.numCells() <= 0);
    StringBuilder localStringBuilder1;
    for (String str1 = ""; ; str1 = localStringBuilder1.toString())
    {
      return str1;
      HashSet localHashSet = new HashSet();
      Iterator localIterator = paramScanHistory.iterator();
      do
      {
        if (!localIterator.hasNext())
          break;
        ArrayList localArrayList = ((_sdkzb)localIterator.next()).getCells();
        boolean bool = localHashSet.addAll(localArrayList);
      }
      while (i == 0);
      int j = _sdkc(localHashSet);
      localStringBuilder1 = new StringBuilder(j);
      String str2 = z[11];
      StringBuilder localStringBuilder2 = localStringBuilder1.append(str2);
      String str3 = _sdka(localHashSet, param_sdkec);
      StringBuilder localStringBuilder3 = localStringBuilder1.append(str3);
      String str4 = z[10];
      StringBuilder localStringBuilder4 = localStringBuilder1.append(str4);
    }
  }

  private static String _sdka(WPSAuthentication paramWPSAuthentication)
  {
    String str1 = paramWPSAuthentication.getUsername();
    String str2 = paramWPSAuthentication.getRealm();
    int i = str1.length() + 128;
    int j = str2.length();
    int k = i + j;
    StringBuilder localStringBuilder1 = new StringBuilder(k);
    String str3 = z[42];
    StringBuilder localStringBuilder2 = localStringBuilder1.append(str3);
    StringBuilder localStringBuilder3 = localStringBuilder1.append(str1);
    String str4 = z[40];
    StringBuilder localStringBuilder4 = localStringBuilder1.append(str4);
    StringBuilder localStringBuilder5 = localStringBuilder1.append(str2);
    String str5 = z[41];
    StringBuilder localStringBuilder6 = localStringBuilder1.append(str5);
    return localStringBuilder1.toString();
  }

  private static String _sdka(_sdkib param_sdkib, _sdkec param_sdkec)
  {
    StringBuilder localStringBuilder1 = new StringBuilder(256);
    String str1 = z[76];
    StringBuilder localStringBuilder2 = localStringBuilder1.append(str1);
    int i = param_sdkib.getSatellites();
    StringBuilder localStringBuilder3 = localStringBuilder2.append(i);
    String str2 = z[74];
    StringBuilder localStringBuilder4 = localStringBuilder3.append(str2);
    String str3 = z[70];
    StringBuilder localStringBuilder5 = localStringBuilder4.append(str3);
    double d1 = param_sdkib.getLatitude();
    StringBuilder localStringBuilder6 = localStringBuilder5.append(d1);
    String str4 = z[68];
    StringBuilder localStringBuilder7 = localStringBuilder6.append(str4);
    String str5 = z[67];
    StringBuilder localStringBuilder8 = localStringBuilder7.append(str5);
    double d2 = param_sdkib.getLongitude();
    StringBuilder localStringBuilder9 = localStringBuilder8.append(d2);
    String str6 = z[13];
    StringBuilder localStringBuilder10 = localStringBuilder9.append(str6);
    String str7 = z[78];
    StringBuilder localStringBuilder11 = localStringBuilder10.append(str7);
    int j = param_sdkib.getHPE();
    StringBuilder localStringBuilder12 = localStringBuilder11.append(j);
    String str8 = z[72];
    StringBuilder localStringBuilder13 = localStringBuilder12.append(str8);
    if (param_sdkib.hasAltitude())
    {
      String str9 = z[77];
      StringBuilder localStringBuilder14 = localStringBuilder1.append(str9);
      double d3 = param_sdkib.getAltitude();
      StringBuilder localStringBuilder15 = localStringBuilder14.append(d3);
      String str10 = z[75];
      StringBuilder localStringBuilder16 = localStringBuilder15.append(str10);
    }
    if (param_sdkib.hasSpeed())
    {
      String str11 = z[69];
      StringBuilder localStringBuilder17 = localStringBuilder1.append(str11);
      double d4 = param_sdkib.getSpeed();
      StringBuilder localStringBuilder18 = localStringBuilder17.append(d4);
      String str12 = z[73];
      StringBuilder localStringBuilder19 = localStringBuilder18.append(str12);
    }
    long l = param_sdkib.getAge()._sdka(param_sdkec);
    String str13 = z[44];
    StringBuilder localStringBuilder20 = localStringBuilder1.append(str13).append(l);
    String str14 = z[47];
    StringBuilder localStringBuilder21 = localStringBuilder20.append(str14);
    String str15 = z[71];
    StringBuilder localStringBuilder22 = localStringBuilder1.append(str15);
    return localStringBuilder1.toString();
  }

  private static String _sdka(Collection<_sdkjc> paramCollection)
  {
    return _sdka(paramCollection, 65535L);
  }

  private static String _sdka(Collection<_sdkjc> paramCollection, long paramLong)
  {
    int i = Location._sdki;
    if ((!_sdkb) && (!_sdkhd._sdkb(paramCollection)))
      throw new AssertionError();
    int j = _sdkb(paramCollection);
    StringBuilder localStringBuilder1 = new StringBuilder(j);
    Iterator localIterator = paramCollection.iterator();
    do
    {
      if (!localIterator.hasNext())
        break;
      String str = _sdka((_sdkjc)localIterator.next(), paramLong);
      StringBuilder localStringBuilder2 = localStringBuilder1.append(str);
    }
    while (i == 0);
    return localStringBuilder1.toString();
  }

  private static String _sdka(Collection<_sdkab> paramCollection, _sdkec param_sdkec)
  {
    int i = Location._sdki;
    if ((!_sdkb) && (!_sdkhd._sdkb(paramCollection)))
      throw new AssertionError();
    int j = _sdkc(paramCollection);
    StringBuilder localStringBuilder1 = new StringBuilder(j);
    Iterator localIterator = paramCollection.iterator();
    do
    {
      if (!localIterator.hasNext())
        break;
      String str = _sdka((_sdkab)localIterator.next(), param_sdkec);
      StringBuilder localStringBuilder2 = localStringBuilder1.append(str);
    }
    while (i == 0);
    return localStringBuilder1.toString();
  }

  private static int _sdkb(int paramInt)
  {
    return paramInt * 128;
  }

  private static int _sdkb(Collection<_sdkjc> paramCollection)
  {
    return _sdka(paramCollection.size());
  }

  private static String _sdkb(ScanHistory paramScanHistory, _sdkec param_sdkec)
  {
    int i = Location._sdki;
    if (paramScanHistory.numGpsLocations() <= 0);
    StringBuilder localStringBuilder1;
    for (String str1 = ""; ; str1 = localStringBuilder1.toString())
    {
      return str1;
      int j = paramScanHistory.numGpsLocations();
      ArrayList localArrayList1 = new ArrayList(j);
      Iterator localIterator = paramScanHistory.iterator();
      do
      {
        if (!localIterator.hasNext())
          break;
        ArrayList localArrayList2 = ((_sdkzb)localIterator.next()).getGpsLocations();
        boolean bool = localArrayList1.addAll(localArrayList2);
      }
      while (i == 0);
      Comparator localComparator1 = _sdka;
      Collections.sort(localArrayList1, localComparator1);
      Comparator localComparator2 = _sdka;
      _sdkhd._sdkc(localArrayList1, localComparator2);
      int k = _sdkd(localArrayList1);
      localStringBuilder1 = new StringBuilder(k);
      String str2 = z[49];
      StringBuilder localStringBuilder2 = localStringBuilder1.append(str2);
      String str3 = _sdkb(localArrayList1, param_sdkec);
      StringBuilder localStringBuilder3 = localStringBuilder1.append(str3);
      String str4 = z[50];
      StringBuilder localStringBuilder4 = localStringBuilder1.append(str4);
    }
  }

  private static String _sdkb(Collection<_sdkib> paramCollection, _sdkec param_sdkec)
  {
    int i = Location._sdki;
    if (!_sdkb)
    {
      Comparator localComparator = _sdka;
      if (!_sdkhd._sdkb(paramCollection, localComparator))
        throw new AssertionError();
    }
    int j = _sdkd(paramCollection);
    StringBuilder localStringBuilder1 = new StringBuilder(j);
    Iterator localIterator = paramCollection.iterator();
    do
    {
      if (!localIterator.hasNext())
        break;
      String str = _sdka((_sdkib)localIterator.next(), param_sdkec);
      StringBuilder localStringBuilder2 = localStringBuilder1.append(str);
    }
    while (i == 0);
    return localStringBuilder1.toString();
  }

  private static int _sdkc(int paramInt)
  {
    return paramInt * 256;
  }

  private static int _sdkc(Collection<_sdkab> paramCollection)
  {
    return _sdkb(paramCollection.size());
  }

  private static int _sdkd(Collection<_sdkib> paramCollection)
  {
    return _sdkc(paramCollection.size());
  }

  public static String getIPLocationRQ(WPSAuthentication paramWPSAuthentication, WPSStreetAddressLookup paramWPSStreetAddressLookup)
  {
    String str1 = paramWPSStreetAddressLookup.toString();
    String str2 = _sdka(paramWPSAuthentication);
    int i = str1.length() + 256;
    int j = str2.length();
    int k = i + j;
    StringBuilder localStringBuilder1 = new StringBuilder(k);
    String str3 = z[2];
    StringBuilder localStringBuilder2 = localStringBuilder1.append(str3);
    String str4 = z[7];
    StringBuilder localStringBuilder3 = localStringBuilder1.append(str4);
    String str5 = z[6];
    StringBuilder localStringBuilder4 = localStringBuilder1.append(str5);
    StringBuilder localStringBuilder5 = localStringBuilder1.append(str1);
    String str6 = z[8];
    StringBuilder localStringBuilder6 = localStringBuilder1.append(str6);
    StringBuilder localStringBuilder7 = localStringBuilder1.append(str2);
    String str7 = z[9];
    StringBuilder localStringBuilder8 = localStringBuilder1.append(str7);
    return localStringBuilder1.toString();
  }

  public static String getLocationRQ(WPSAuthentication paramWPSAuthentication, WPSStreetAddressLookup paramWPSStreetAddressLookup, _sdkzb param_sdkzb)
  {
    String str1 = paramWPSStreetAddressLookup.toString();
    String str2 = _sdka(paramWPSAuthentication);
    int i = str1.length() + 256;
    int j = str2.length();
    int k = i + j;
    int m = _sdka(param_sdkzb);
    int n = k + m;
    StringBuilder localStringBuilder1 = new StringBuilder(n);
    String str3 = z[2];
    StringBuilder localStringBuilder2 = localStringBuilder1.append(str3);
    String str4 = z[39];
    StringBuilder localStringBuilder3 = localStringBuilder1.append(str4);
    String str5 = z[6];
    StringBuilder localStringBuilder4 = localStringBuilder1.append(str5);
    StringBuilder localStringBuilder5 = localStringBuilder1.append(str1);
    String str6 = z[8];
    StringBuilder localStringBuilder6 = localStringBuilder1.append(str6);
    StringBuilder localStringBuilder7 = localStringBuilder1.append(str2);
    _sdkec local_sdkec = _sdkec._sdkd();
    ArrayList localArrayList = param_sdkzb.getAPs();
    long l = System.currentTimeMillis();
    String str7 = _sdka(localArrayList, l);
    StringBuilder localStringBuilder8 = localStringBuilder1.append(str7);
    String str8 = _sdka(param_sdkzb.getCells(), local_sdkec);
    StringBuilder localStringBuilder9 = localStringBuilder1.append(str8);
    String str9 = _sdkb(param_sdkzb.getGpsLocations(), local_sdkec);
    StringBuilder localStringBuilder10 = localStringBuilder1.append(str9);
    String str10 = z[38];
    StringBuilder localStringBuilder11 = localStringBuilder1.append(str10);
    return localStringBuilder1.toString();
  }

  public static String getRegistrationRQ(WPSAuthentication paramWPSAuthentication1, WPSAuthentication paramWPSAuthentication2, String paramString)
  {
    String str1 = paramWPSAuthentication2.getUsername();
    String str2 = paramWPSAuthentication2.getRealm();
    String str3 = _sdka(paramWPSAuthentication1);
    int i = str1.length() + 256;
    int j = str2.length();
    int k = i + j;
    int m = str3.length() + k;
    StringBuilder localStringBuilder1;
    String str4;
    if (paramString != null)
    {
      localStringBuilder1 = new StringBuilder();
      str4 = z[31];
    }
    for (String str5 = str4 + paramString + "\""; ; str5 = "")
    {
      StringBuilder localStringBuilder2 = new StringBuilder(m);
      String str6 = z[2];
      StringBuilder localStringBuilder3 = localStringBuilder2.append(str6);
      StringBuilder localStringBuilder4 = new StringBuilder();
      String str7 = z[32];
      String str8 = str7 + str5 + ">";
      StringBuilder localStringBuilder5 = localStringBuilder2.append(str8);
      StringBuilder localStringBuilder6 = localStringBuilder2.append(str3);
      StringBuilder localStringBuilder7 = new StringBuilder();
      String str9 = z[35];
      StringBuilder localStringBuilder8 = localStringBuilder7.append(str9).append(str1);
      String str10 = z[33];
      String str11 = str10;
      StringBuilder localStringBuilder9 = localStringBuilder2.append(str11);
      StringBuilder localStringBuilder10 = new StringBuilder();
      String str12 = z[34];
      StringBuilder localStringBuilder11 = localStringBuilder10.append(str12).append(str2);
      String str13 = z[37];
      String str14 = str13;
      StringBuilder localStringBuilder12 = localStringBuilder2.append(str14);
      String str15 = z[36];
      StringBuilder localStringBuilder13 = localStringBuilder2.append(str15);
      return localStringBuilder2.toString();
    }
  }

  public static String getTilingRQ(WPSAuthentication paramWPSAuthentication, ScanHistory paramScanHistory, long paramLong)
  {
    String str1 = _sdka(paramWPSAuthentication);
    int i = str1.length() + 512;
    int j = rqSize(paramScanHistory);
    int k = i + j;
    StringBuilder localStringBuilder1 = new StringBuilder(k);
    String str2 = z[2];
    StringBuilder localStringBuilder2 = localStringBuilder1.append(str2);
    String str3 = z[5];
    StringBuilder localStringBuilder3 = localStringBuilder1.append(str3);
    StringBuilder localStringBuilder4 = new StringBuilder().append("").append(paramLong);
    String str4 = z[3];
    String str5 = str4;
    StringBuilder localStringBuilder5 = localStringBuilder1.append(str5);
    StringBuilder localStringBuilder6 = localStringBuilder1.append(str1);
    long l = System.currentTimeMillis();
    _sdkec local_sdkec = _sdkec._sdkd();
    String str6 = _sdka(paramScanHistory, l);
    StringBuilder localStringBuilder7 = localStringBuilder1.append(str6);
    String str7 = _sdka(paramScanHistory, local_sdkec);
    StringBuilder localStringBuilder8 = localStringBuilder1.append(str7);
    String str8 = _sdkb(paramScanHistory, local_sdkec);
    StringBuilder localStringBuilder9 = localStringBuilder1.append(str8);
    String str9 = z[4];
    StringBuilder localStringBuilder10 = localStringBuilder1.append(str9);
    return localStringBuilder1.toString();
  }

  public static String getUserLocationRQ(WPSAuthentication paramWPSAuthentication, WPSLocation paramWPSLocation)
  {
    int i = Location._sdki;
    String str1 = _sdka(paramWPSAuthentication);
    int j = str1.length() + 512;
    int k = _sdka(paramWPSLocation._sdkp);
    int m = j + k;
    StringBuilder localStringBuilder1 = new StringBuilder(m);
    String str2 = z[2];
    StringBuilder localStringBuilder2 = localStringBuilder1.append(str2);
    String str3 = z[24];
    StringBuilder localStringBuilder3 = localStringBuilder1.append(str3);
    StringBuilder localStringBuilder4 = localStringBuilder1.append(str1);
    String str4 = _sdka(paramWPSLocation._sdkp.getAPs());
    StringBuilder localStringBuilder5 = localStringBuilder1.append(str4);
    ArrayList localArrayList = paramWPSLocation._sdkp.getCells();
    _sdkec local_sdkec = _sdkec._sdkd();
    String str5 = _sdka(localArrayList, local_sdkec);
    StringBuilder localStringBuilder6 = localStringBuilder1.append(str5);
    String str6 = z[30];
    StringBuilder localStringBuilder7 = localStringBuilder1.append(str6);
    double d1 = paramWPSLocation.getLatitude();
    StringBuilder localStringBuilder8 = localStringBuilder1.append(d1);
    String str7 = z[19];
    StringBuilder localStringBuilder9 = localStringBuilder1.append(str7);
    double d2 = paramWPSLocation.getLongitude();
    StringBuilder localStringBuilder10 = localStringBuilder1.append(d2);
    String str8 = z[13];
    StringBuilder localStringBuilder11 = localStringBuilder1.append(str8);
    StreetAddress localStreetAddress = paramWPSLocation.getStreetAddress();
    if (localStreetAddress != null)
    {
      String str9 = z[12];
      StringBuilder localStringBuilder12 = localStringBuilder1.append(str9);
      if (localStreetAddress.getStreetNumber() != null)
      {
        String str10 = z[18];
        StringBuilder localStringBuilder13 = localStringBuilder1.append(str10);
        String str11 = localStreetAddress.getStreetNumber();
        StringBuilder localStringBuilder14 = localStringBuilder1.append(str11);
        String str12 = z[16];
        StringBuilder localStringBuilder15 = localStringBuilder1.append(str12);
      }
      if (localStreetAddress.getAddressLine() != null)
      {
        String[] arrayOfString = localStreetAddress.getAddressLine();
        int n = arrayOfString.length;
        int i1 = 0;
        do
        {
          if (i1 >= n)
            break;
          String str13 = arrayOfString[i1];
          String str14 = z[26];
          StringBuilder localStringBuilder16 = localStringBuilder1.append(str14);
          StringBuilder localStringBuilder17 = localStringBuilder1.append(str13);
          String str15 = z[22];
          StringBuilder localStringBuilder18 = localStringBuilder1.append(str15);
          i1 += 1;
        }
        while (i == 0);
      }
      if (localStreetAddress.getCity() != null)
      {
        String str16 = z[21];
        StringBuilder localStringBuilder19 = localStringBuilder1.append(str16);
        String str17 = localStreetAddress.getCity();
        StringBuilder localStringBuilder20 = localStringBuilder1.append(str17);
        String str18 = z[20];
        StringBuilder localStringBuilder21 = localStringBuilder1.append(str18);
      }
      if (localStreetAddress.getPostalCode() != null)
      {
        String str19 = z[23];
        StringBuilder localStringBuilder22 = localStringBuilder1.append(str19);
        String str20 = localStreetAddress.getPostalCode();
        StringBuilder localStringBuilder23 = localStringBuilder1.append(str20);
        String str21 = z[14];
        StringBuilder localStringBuilder24 = localStringBuilder1.append(str21);
      }
      if ((localStreetAddress.getStateCode() != null) && (localStreetAddress.getStateName() != null))
      {
        String str22 = z[27];
        StringBuilder localStringBuilder25 = localStringBuilder1.append(str22);
        String str23 = localStreetAddress.getStateCode();
        StringBuilder localStringBuilder26 = localStringBuilder1.append(str23);
        String str24 = z[8];
        StringBuilder localStringBuilder27 = localStringBuilder1.append(str24);
        String str25 = localStreetAddress.getStateName();
        StringBuilder localStringBuilder28 = localStringBuilder1.append(str25);
        String str26 = z[28];
        StringBuilder localStringBuilder29 = localStringBuilder1.append(str26);
      }
      if ((localStreetAddress.getCountryCode() != null) && (localStreetAddress.getCountryName() != null))
      {
        String str27 = z[29];
        StringBuilder localStringBuilder30 = localStringBuilder1.append(str27);
        String str28 = localStreetAddress.getCountryCode();
        StringBuilder localStringBuilder31 = localStringBuilder1.append(str28);
        String str29 = z[8];
        StringBuilder localStringBuilder32 = localStringBuilder1.append(str29);
        String str30 = localStreetAddress.getCountryName();
        StringBuilder localStringBuilder33 = localStringBuilder1.append(str30);
        String str31 = z[15];
        StringBuilder localStringBuilder34 = localStringBuilder1.append(str31);
      }
      String str32 = z[25];
      StringBuilder localStringBuilder35 = localStringBuilder1.append(str32);
    }
    String str33 = z[17];
    StringBuilder localStringBuilder36 = localStringBuilder1.append(str33);
    return localStringBuilder1.toString();
  }

  public static int rqSize(ScanHistory paramScanHistory)
  {
    int i = _sdka(paramScanHistory.numAPs());
    int j = _sdkb(paramScanHistory.numCells());
    int k = i + j;
    int m = _sdkc(paramScanHistory.numGpsLocations());
    return k + m;
  }
}

/* Location:           D:\Tools\extractapktools\extractapktools\dex2jar-0.0.7.11-SNAPSHOT\classes_dex2jar.jar
 * Qualified Name:     com.skyhookwireless.wps.Protocol
 * JD-Core Version:    0.6.2
 */