package com.skyhookwireless.wps;

import com.skyhookwireless._sdkbb;
import com.skyhookwireless._sdkhd;
import com.skyhookwireless._sdkjc;
import com.skyhookwireless._sdksd;
import com.skyhookwireless._sdktd;
import com.skyhookwireless._sdkud;
import com.skyhookwireless._sdkwb;
import java.util.ArrayList;
import java.util.Collection;
import java.util.Collections;
import java.util.Iterator;
import java.util.List;

public class XPSSwitchingAlgorithm extends _sdkmb
{
  static final boolean _sdkq;
  private static final String[] z;
  private final com.skyhookwireless._sdkhb _sdka;
  private final _sdkpb _sdkb;
  private final _sdks<_sdkib> _sdkc;
  private final ScanObservation _sdkd;
  private final _sdktc _sdke;
  private final _sdkub _sdkf;
  private final _sdkdc _sdkg;
  private final _sdkec _sdkh;
  private com.skyhookwireless._sdkec _sdki;
  private com.skyhookwireless._sdkec _sdkj;
  private _sdkib _sdkk;
  private boolean _sdkl;
  private boolean _sdkm;
  private boolean _sdkn;
  private boolean _sdko;
  private boolean _sdkp;

  // ERROR //
  static
  {
    // Byte code:
    //   0: iconst_1
    //   1: istore_0
    //   2: bipush 51
    //   4: anewarray 39	java/lang/String
    //   7: astore_1
    //   8: ldc 41
    //   10: invokevirtual 45	java/lang/String:toCharArray	()[C
    //   13: astore_2
    //   14: aload_2
    //   15: arraylength
    //   16: istore_3
    //   17: iload_3
    //   18: iload_0
    //   19: if_icmpgt +12675 -> 12694
    //   22: iconst_0
    //   23: istore 4
    //   25: aload_2
    //   26: astore 5
    //   28: iload 4
    //   30: istore 6
    //   32: iload_3
    //   33: istore 7
    //   35: aload_2
    //   36: astore 8
    //   38: iload 7
    //   40: istore 9
    //   42: aload 8
    //   44: iload 4
    //   46: caload
    //   47: istore 10
    //   49: iload 6
    //   51: iconst_5
    //   52: irem
    //   53: tableswitch	default:+31 -> 84, 0:+10633->10686, 1:+10640->10693, 2:+10647->10700, 3:+10654->10707
    //   85: irem
    //   86: istore 11
    //   88: iload 11
    //   90: iload 10
    //   92: ixor
    //   93: i2c
    //   94: istore 12
    //   96: aload 8
    //   98: iload 4
    //   100: iload 12
    //   102: castore
    //   103: iload 6
    //   105: iconst_1
    //   106: iadd
    //   107: istore 4
    //   109: iload 9
    //   111: ifne +18 -> 129
    //   114: aload 5
    //   116: astore 8
    //   118: iload 4
    //   120: istore 6
    //   122: iload 9
    //   124: istore 4
    //   126: goto -84 -> 42
    //   129: iload 9
    //   131: istore_3
    //   132: aload 5
    //   134: astore_2
    //   135: iload_3
    //   136: iload 4
    //   138: if_icmpgt -113 -> 25
    //   141: new 39	java/lang/String
    //   144: dup
    //   145: aload_2
    //   146: invokespecial 49	java/lang/String:<init>	([C)V
    //   149: invokevirtual 53	java/lang/String:intern	()Ljava/lang/String;
    //   152: astore 13
    //   154: aload_1
    //   155: iconst_0
    //   156: aload 13
    //   158: aastore
    //   159: ldc 55
    //   161: invokevirtual 45	java/lang/String:toCharArray	()[C
    //   164: astore 14
    //   166: aload 14
    //   168: arraylength
    //   169: istore 15
    //   171: iload 15
    //   173: iconst_1
    //   174: if_icmpgt +12514 -> 12688
    //   177: iconst_0
    //   178: istore 16
    //   180: aload 14
    //   182: astore 5
    //   184: iload 16
    //   186: istore 6
    //   188: iload 15
    //   190: istore 17
    //   192: aload 14
    //   194: astore 18
    //   196: iload 17
    //   198: istore 19
    //   200: aload 18
    //   202: iload 16
    //   204: caload
    //   205: istore 10
    //   207: iload 6
    //   209: iconst_5
    //   210: irem
    //   211: tableswitch	default:+29 -> 240, 0:+10503->10714, 1:+10510->10721, 2:+10517->10728, 3:+10524->10735
    //   241: irem
    //   242: istore 20
    //   244: iload 20
    //   246: iload 10
    //   248: ixor
    //   249: i2c
    //   250: istore 21
    //   252: aload 18
    //   254: iload 16
    //   256: iload 21
    //   258: castore
    //   259: iload 6
    //   261: iconst_1
    //   262: iadd
    //   263: istore 16
    //   265: iload 19
    //   267: ifne +18 -> 285
    //   270: aload 5
    //   272: astore 18
    //   274: iload 16
    //   276: istore 22
    //   278: iload 19
    //   280: istore 16
    //   282: goto -82 -> 200
    //   285: iload 19
    //   287: istore 15
    //   289: aload 5
    //   291: astore 14
    //   293: iload 15
    //   295: iload 16
    //   297: if_icmpgt -117 -> 180
    //   300: new 39	java/lang/String
    //   303: dup
    //   304: aload 14
    //   306: invokespecial 49	java/lang/String:<init>	([C)V
    //   309: invokevirtual 53	java/lang/String:intern	()Ljava/lang/String;
    //   312: astore 23
    //   314: aload_1
    //   315: iconst_1
    //   316: aload 23
    //   318: aastore
    //   319: iconst_2
    //   320: istore 24
    //   322: ldc 57
    //   324: invokevirtual 45	java/lang/String:toCharArray	()[C
    //   327: astore 25
    //   329: aload 25
    //   331: arraylength
    //   332: istore 26
    //   334: iload 26
    //   336: iconst_1
    //   337: if_icmpgt +12345 -> 12682
    //   340: iconst_0
    //   341: istore 27
    //   343: aload 25
    //   345: astore 5
    //   347: iload 27
    //   349: istore 6
    //   351: iload 26
    //   353: istore 28
    //   355: aload 25
    //   357: astore 29
    //   359: iload 28
    //   361: istore 30
    //   363: aload 29
    //   365: iload 27
    //   367: caload
    //   368: istore 31
    //   370: iload 6
    //   372: iconst_5
    //   373: irem
    //   374: tableswitch	default:+30 -> 404, 0:+10368->10742, 1:+10375->10749, 2:+10382->10756, 3:+10389->10763
    //   405: irem
    //   406: istore 32
    //   408: iload 32
    //   410: iload 31
    //   412: ixor
    //   413: i2c
    //   414: istore 33
    //   416: aload 29
    //   418: iload 27
    //   420: iload 33
    //   422: castore
    //   423: iload 6
    //   425: iconst_1
    //   426: iadd
    //   427: istore 27
    //   429: iload 30
    //   431: ifne +18 -> 449
    //   434: aload 5
    //   436: astore 29
    //   438: iload 27
    //   440: istore 34
    //   442: iload 30
    //   444: istore 27
    //   446: goto -83 -> 363
    //   449: iload 30
    //   451: istore 26
    //   453: aload 5
    //   455: astore 25
    //   457: iload 26
    //   459: iload 27
    //   461: if_icmpgt -118 -> 343
    //   464: new 39	java/lang/String
    //   467: dup
    //   468: aload 25
    //   470: invokespecial 49	java/lang/String:<init>	([C)V
    //   473: invokevirtual 53	java/lang/String:intern	()Ljava/lang/String;
    //   476: astore 35
    //   478: aload_1
    //   479: iload 24
    //   481: aload 35
    //   483: aastore
    //   484: iconst_3
    //   485: istore 36
    //   487: ldc 59
    //   489: invokevirtual 45	java/lang/String:toCharArray	()[C
    //   492: astore 37
    //   494: aload 37
    //   496: arraylength
    //   497: istore 38
    //   499: iload 38
    //   501: iconst_1
    //   502: if_icmpgt +12174 -> 12676
    //   505: iconst_0
    //   506: istore 39
    //   508: aload 37
    //   510: astore 5
    //   512: iload 39
    //   514: istore 6
    //   516: iload 38
    //   518: istore 40
    //   520: aload 37
    //   522: astore 41
    //   524: iload 40
    //   526: istore 42
    //   528: aload 41
    //   530: iload 39
    //   532: caload
    //   533: istore 31
    //   535: iload 6
    //   537: iconst_5
    //   538: irem
    //   539: tableswitch	default:+29 -> 568, 0:+10231->10770, 1:+10238->10777, 2:+10245->10784, 3:+10252->10791
    //   569: irem
    //   570: istore 43
    //   572: iload 43
    //   574: iload 31
    //   576: ixor
    //   577: i2c
    //   578: istore 44
    //   580: aload 41
    //   582: iload 39
    //   584: iload 44
    //   586: castore
    //   587: iload 6
    //   589: iconst_1
    //   590: iadd
    //   591: istore 39
    //   593: iload 42
    //   595: ifne +18 -> 613
    //   598: aload 5
    //   600: astore 41
    //   602: iload 39
    //   604: istore 45
    //   606: iload 42
    //   608: istore 39
    //   610: goto -82 -> 528
    //   613: iload 42
    //   615: istore 38
    //   617: aload 5
    //   619: astore 37
    //   621: iload 38
    //   623: iload 39
    //   625: if_icmpgt -117 -> 508
    //   628: new 39	java/lang/String
    //   631: dup
    //   632: aload 37
    //   634: invokespecial 49	java/lang/String:<init>	([C)V
    //   637: invokevirtual 53	java/lang/String:intern	()Ljava/lang/String;
    //   640: astore 46
    //   642: aload_1
    //   643: iload 36
    //   645: aload 46
    //   647: aastore
    //   648: iconst_4
    //   649: istore 47
    //   651: ldc 61
    //   653: invokevirtual 45	java/lang/String:toCharArray	()[C
    //   656: astore 48
    //   658: aload 48
    //   660: arraylength
    //   661: istore 49
    //   663: iload 49
    //   665: iconst_1
    //   666: if_icmpgt +12004 -> 12670
    //   669: iconst_0
    //   670: istore 50
    //   672: aload 48
    //   674: astore 5
    //   676: iload 50
    //   678: istore 6
    //   680: iload 49
    //   682: istore 51
    //   684: aload 48
    //   686: astore 52
    //   688: iload 51
    //   690: istore 53
    //   692: aload 52
    //   694: iload 50
    //   696: caload
    //   697: istore 31
    //   699: iload 6
    //   701: iconst_5
    //   702: irem
    //   703: tableswitch	default:+29 -> 732, 0:+10095->10798, 1:+10102->10805, 2:+10109->10812, 3:+10116->10819
    //   733: irem
    //   734: istore 54
    //   736: iload 54
    //   738: iload 31
    //   740: ixor
    //   741: i2c
    //   742: istore 55
    //   744: aload 52
    //   746: iload 50
    //   748: iload 55
    //   750: castore
    //   751: iload 6
    //   753: iconst_1
    //   754: iadd
    //   755: istore 50
    //   757: iload 53
    //   759: ifne +18 -> 777
    //   762: aload 5
    //   764: astore 52
    //   766: iload 50
    //   768: istore 56
    //   770: iload 53
    //   772: istore 50
    //   774: goto -82 -> 692
    //   777: iload 53
    //   779: istore 49
    //   781: aload 5
    //   783: astore 48
    //   785: iload 49
    //   787: iload 50
    //   789: if_icmpgt -117 -> 672
    //   792: new 39	java/lang/String
    //   795: dup
    //   796: aload 48
    //   798: invokespecial 49	java/lang/String:<init>	([C)V
    //   801: invokevirtual 53	java/lang/String:intern	()Ljava/lang/String;
    //   804: astore 57
    //   806: aload_1
    //   807: iload 47
    //   809: aload 57
    //   811: aastore
    //   812: iconst_5
    //   813: istore 58
    //   815: ldc 63
    //   817: invokevirtual 45	java/lang/String:toCharArray	()[C
    //   820: astore 59
    //   822: aload 59
    //   824: arraylength
    //   825: istore 60
    //   827: iload 60
    //   829: iconst_1
    //   830: if_icmpgt +11834 -> 12664
    //   833: iconst_0
    //   834: istore 61
    //   836: aload 59
    //   838: astore 5
    //   840: iload 61
    //   842: istore 6
    //   844: iload 60
    //   846: istore 62
    //   848: aload 59
    //   850: astore 63
    //   852: iload 62
    //   854: istore 64
    //   856: aload 63
    //   858: iload 61
    //   860: caload
    //   861: istore 31
    //   863: iload 6
    //   865: iconst_5
    //   866: irem
    //   867: tableswitch	default:+29 -> 896, 0:+9959->10826, 1:+9966->10833, 2:+9973->10840, 3:+9980->10847
    //   897: irem
    //   898: istore 65
    //   900: iload 65
    //   902: iload 31
    //   904: ixor
    //   905: i2c
    //   906: istore 66
    //   908: aload 63
    //   910: iload 61
    //   912: iload 66
    //   914: castore
    //   915: iload 6
    //   917: iconst_1
    //   918: iadd
    //   919: istore 61
    //   921: iload 64
    //   923: ifne +18 -> 941
    //   926: aload 5
    //   928: astore 63
    //   930: iload 61
    //   932: istore 67
    //   934: iload 64
    //   936: istore 61
    //   938: goto -82 -> 856
    //   941: iload 64
    //   943: istore 60
    //   945: aload 5
    //   947: astore 59
    //   949: iload 60
    //   951: iload 61
    //   953: if_icmpgt -117 -> 836
    //   956: new 39	java/lang/String
    //   959: dup
    //   960: aload 59
    //   962: invokespecial 49	java/lang/String:<init>	([C)V
    //   965: invokevirtual 53	java/lang/String:intern	()Ljava/lang/String;
    //   968: astore 68
    //   970: aload_1
    //   971: iload 58
    //   973: aload 68
    //   975: aastore
    //   976: bipush 6
    //   978: istore 69
    //   980: ldc 65
    //   982: invokevirtual 45	java/lang/String:toCharArray	()[C
    //   985: astore 70
    //   987: aload 70
    //   989: arraylength
    //   990: istore 71
    //   992: iload 71
    //   994: iconst_1
    //   995: if_icmpgt +11663 -> 12658
    //   998: iconst_0
    //   999: istore 72
    //   1001: aload 70
    //   1003: astore 5
    //   1005: iload 72
    //   1007: istore 6
    //   1009: iload 71
    //   1011: istore 73
    //   1013: aload 70
    //   1015: astore 74
    //   1017: iload 73
    //   1019: istore 75
    //   1021: aload 74
    //   1023: iload 72
    //   1025: caload
    //   1026: istore 31
    //   1028: iload 6
    //   1030: iconst_5
    //   1031: irem
    //   1032: tableswitch	default:+32 -> 1064, 0:+9822->10854, 1:+9829->10861, 2:+9836->10868, 3:+9843->10875
    //   1065: irem
    //   1066: istore 76
    //   1068: iload 76
    //   1070: iload 31
    //   1072: ixor
    //   1073: i2c
    //   1074: istore 77
    //   1076: aload 74
    //   1078: iload 72
    //   1080: iload 77
    //   1082: castore
    //   1083: iload 6
    //   1085: iconst_1
    //   1086: iadd
    //   1087: istore 72
    //   1089: iload 75
    //   1091: ifne +18 -> 1109
    //   1094: aload 5
    //   1096: astore 74
    //   1098: iload 72
    //   1100: istore 78
    //   1102: iload 75
    //   1104: istore 72
    //   1106: goto -85 -> 1021
    //   1109: iload 75
    //   1111: istore 71
    //   1113: aload 5
    //   1115: astore 70
    //   1117: iload 71
    //   1119: iload 72
    //   1121: if_icmpgt -120 -> 1001
    //   1124: new 39	java/lang/String
    //   1127: dup
    //   1128: aload 70
    //   1130: invokespecial 49	java/lang/String:<init>	([C)V
    //   1133: invokevirtual 53	java/lang/String:intern	()Ljava/lang/String;
    //   1136: astore 79
    //   1138: aload_1
    //   1139: iload 69
    //   1141: aload 79
    //   1143: aastore
    //   1144: bipush 7
    //   1146: istore 80
    //   1148: ldc 67
    //   1150: invokevirtual 45	java/lang/String:toCharArray	()[C
    //   1153: astore 81
    //   1155: aload 81
    //   1157: arraylength
    //   1158: istore 82
    //   1160: iload 82
    //   1162: iconst_1
    //   1163: if_icmpgt +11489 -> 12652
    //   1166: iconst_0
    //   1167: istore 83
    //   1169: aload 81
    //   1171: astore 5
    //   1173: iload 83
    //   1175: istore 6
    //   1177: iload 82
    //   1179: istore 84
    //   1181: aload 81
    //   1183: astore 85
    //   1185: iload 84
    //   1187: istore 86
    //   1189: aload 85
    //   1191: iload 83
    //   1193: caload
    //   1194: istore 31
    //   1196: iload 6
    //   1198: iconst_5
    //   1199: irem
    //   1200: tableswitch	default:+32 -> 1232, 0:+9682->10882, 1:+9689->10889, 2:+9696->10896, 3:+9703->10903
    //   1233: irem
    //   1234: istore 87
    //   1236: iload 87
    //   1238: iload 31
    //   1240: ixor
    //   1241: i2c
    //   1242: istore 88
    //   1244: aload 85
    //   1246: iload 83
    //   1248: iload 88
    //   1250: castore
    //   1251: iload 6
    //   1253: iconst_1
    //   1254: iadd
    //   1255: istore 83
    //   1257: iload 86
    //   1259: ifne +18 -> 1277
    //   1262: aload 5
    //   1264: astore 85
    //   1266: iload 83
    //   1268: istore 89
    //   1270: iload 86
    //   1272: istore 83
    //   1274: goto -85 -> 1189
    //   1277: iload 86
    //   1279: istore 82
    //   1281: aload 5
    //   1283: astore 81
    //   1285: iload 82
    //   1287: iload 83
    //   1289: if_icmpgt -120 -> 1169
    //   1292: new 39	java/lang/String
    //   1295: dup
    //   1296: aload 81
    //   1298: invokespecial 49	java/lang/String:<init>	([C)V
    //   1301: invokevirtual 53	java/lang/String:intern	()Ljava/lang/String;
    //   1304: astore 90
    //   1306: aload_1
    //   1307: iload 80
    //   1309: aload 90
    //   1311: aastore
    //   1312: bipush 8
    //   1314: istore 91
    //   1316: ldc 69
    //   1318: invokevirtual 45	java/lang/String:toCharArray	()[C
    //   1321: astore 92
    //   1323: aload 92
    //   1325: arraylength
    //   1326: istore 93
    //   1328: iload 93
    //   1330: iconst_1
    //   1331: if_icmpgt +11315 -> 12646
    //   1334: iconst_0
    //   1335: istore 94
    //   1337: aload 92
    //   1339: astore 5
    //   1341: iload 94
    //   1343: istore 6
    //   1345: iload 93
    //   1347: istore 95
    //   1349: aload 92
    //   1351: astore 96
    //   1353: iload 95
    //   1355: istore 97
    //   1357: aload 96
    //   1359: iload 94
    //   1361: caload
    //   1362: istore 31
    //   1364: iload 6
    //   1366: iconst_5
    //   1367: irem
    //   1368: tableswitch	default:+32 -> 1400, 0:+9542->10910, 1:+9549->10917, 2:+9556->10924, 3:+9563->10931
    //   1401: irem
    //   1402: istore 98
    //   1404: iload 98
    //   1406: iload 31
    //   1408: ixor
    //   1409: i2c
    //   1410: istore 99
    //   1412: aload 96
    //   1414: iload 94
    //   1416: iload 99
    //   1418: castore
    //   1419: iload 6
    //   1421: iconst_1
    //   1422: iadd
    //   1423: istore 94
    //   1425: iload 97
    //   1427: ifne +18 -> 1445
    //   1430: aload 5
    //   1432: astore 96
    //   1434: iload 94
    //   1436: istore 100
    //   1438: iload 97
    //   1440: istore 94
    //   1442: goto -85 -> 1357
    //   1445: iload 97
    //   1447: istore 93
    //   1449: aload 5
    //   1451: astore 92
    //   1453: iload 93
    //   1455: iload 94
    //   1457: if_icmpgt -120 -> 1337
    //   1460: new 39	java/lang/String
    //   1463: dup
    //   1464: aload 92
    //   1466: invokespecial 49	java/lang/String:<init>	([C)V
    //   1469: invokevirtual 53	java/lang/String:intern	()Ljava/lang/String;
    //   1472: astore 101
    //   1474: aload_1
    //   1475: iload 91
    //   1477: aload 101
    //   1479: aastore
    //   1480: bipush 9
    //   1482: istore 102
    //   1484: ldc 71
    //   1486: invokevirtual 45	java/lang/String:toCharArray	()[C
    //   1489: astore 103
    //   1491: aload 103
    //   1493: arraylength
    //   1494: istore 104
    //   1496: iload 104
    //   1498: iconst_1
    //   1499: if_icmpgt +11141 -> 12640
    //   1502: iconst_0
    //   1503: istore 105
    //   1505: aload 103
    //   1507: astore 5
    //   1509: iload 105
    //   1511: istore 6
    //   1513: iload 104
    //   1515: istore 106
    //   1517: aload 103
    //   1519: astore 107
    //   1521: iload 106
    //   1523: istore 108
    //   1525: aload 107
    //   1527: iload 105
    //   1529: caload
    //   1530: istore 31
    //   1532: iload 6
    //   1534: iconst_5
    //   1535: irem
    //   1536: tableswitch	default:+32 -> 1568, 0:+9402->10938, 1:+9409->10945, 2:+9416->10952, 3:+9423->10959
    //   1569: irem
    //   1570: istore 109
    //   1572: iload 109
    //   1574: iload 31
    //   1576: ixor
    //   1577: i2c
    //   1578: istore 110
    //   1580: aload 107
    //   1582: iload 105
    //   1584: iload 110
    //   1586: castore
    //   1587: iload 6
    //   1589: iconst_1
    //   1590: iadd
    //   1591: istore 105
    //   1593: iload 108
    //   1595: ifne +18 -> 1613
    //   1598: aload 5
    //   1600: astore 107
    //   1602: iload 105
    //   1604: istore 111
    //   1606: iload 108
    //   1608: istore 105
    //   1610: goto -85 -> 1525
    //   1613: iload 108
    //   1615: istore 104
    //   1617: aload 5
    //   1619: astore 103
    //   1621: iload 104
    //   1623: iload 105
    //   1625: if_icmpgt -120 -> 1505
    //   1628: new 39	java/lang/String
    //   1631: dup
    //   1632: aload 103
    //   1634: invokespecial 49	java/lang/String:<init>	([C)V
    //   1637: invokevirtual 53	java/lang/String:intern	()Ljava/lang/String;
    //   1640: astore 112
    //   1642: aload_1
    //   1643: iload 102
    //   1645: aload 112
    //   1647: aastore
    //   1648: bipush 10
    //   1650: istore 113
    //   1652: ldc 73
    //   1654: invokevirtual 45	java/lang/String:toCharArray	()[C
    //   1657: astore 114
    //   1659: aload 114
    //   1661: arraylength
    //   1662: istore 115
    //   1664: iload 115
    //   1666: iconst_1
    //   1667: if_icmpgt +10967 -> 12634
    //   1670: iconst_0
    //   1671: istore 116
    //   1673: aload 114
    //   1675: astore 5
    //   1677: iload 116
    //   1679: istore 6
    //   1681: iload 115
    //   1683: istore 117
    //   1685: aload 114
    //   1687: astore 118
    //   1689: iload 117
    //   1691: istore 119
    //   1693: aload 118
    //   1695: iload 116
    //   1697: caload
    //   1698: istore 31
    //   1700: iload 6
    //   1702: iconst_5
    //   1703: irem
    //   1704: tableswitch	default:+32 -> 1736, 0:+9262->10966, 1:+9269->10973, 2:+9276->10980, 3:+9283->10987
    //   1737: irem
    //   1738: istore 120
    //   1740: iload 120
    //   1742: iload 31
    //   1744: ixor
    //   1745: i2c
    //   1746: istore 121
    //   1748: aload 118
    //   1750: iload 116
    //   1752: iload 121
    //   1754: castore
    //   1755: iload 6
    //   1757: iconst_1
    //   1758: iadd
    //   1759: istore 116
    //   1761: iload 119
    //   1763: ifne +18 -> 1781
    //   1766: aload 5
    //   1768: astore 118
    //   1770: iload 116
    //   1772: istore 122
    //   1774: iload 119
    //   1776: istore 116
    //   1778: goto -85 -> 1693
    //   1781: iload 119
    //   1783: istore 115
    //   1785: aload 5
    //   1787: astore 114
    //   1789: iload 115
    //   1791: iload 116
    //   1793: if_icmpgt -120 -> 1673
    //   1796: new 39	java/lang/String
    //   1799: dup
    //   1800: aload 114
    //   1802: invokespecial 49	java/lang/String:<init>	([C)V
    //   1805: invokevirtual 53	java/lang/String:intern	()Ljava/lang/String;
    //   1808: astore 123
    //   1810: aload_1
    //   1811: iload 113
    //   1813: aload 123
    //   1815: aastore
    //   1816: bipush 11
    //   1818: istore 124
    //   1820: ldc 75
    //   1822: invokevirtual 45	java/lang/String:toCharArray	()[C
    //   1825: astore 125
    //   1827: aload 125
    //   1829: arraylength
    //   1830: istore 126
    //   1832: iload 126
    //   1834: iconst_1
    //   1835: if_icmpgt +10793 -> 12628
    //   1838: iconst_0
    //   1839: istore 127
    //   1841: aload 125
    //   1843: astore 5
    //   1845: iload 127
    //   1847: istore 6
    //   1849: iload 126
    //   1851: istore 128
    //   1853: aload 125
    //   1855: astore 129
    //   1857: iload 128
    //   1859: istore 130
    //   1861: aload 129
    //   1863: iload 127
    //   1865: caload
    //   1866: istore 31
    //   1868: iload 6
    //   1870: iconst_5
    //   1871: irem
    //   1872: tableswitch	default:+32 -> 1904, 0:+9122->10994, 1:+9129->11001, 2:+9136->11008, 3:+9143->11015
    //   1905: irem
    //   1906: istore 131
    //   1908: iload 131
    //   1910: iload 31
    //   1912: ixor
    //   1913: i2c
    //   1914: istore 132
    //   1916: aload 129
    //   1918: iload 127
    //   1920: iload 132
    //   1922: castore
    //   1923: iload 6
    //   1925: iconst_1
    //   1926: iadd
    //   1927: istore 127
    //   1929: iload 130
    //   1931: ifne +18 -> 1949
    //   1934: aload 5
    //   1936: astore 129
    //   1938: iload 127
    //   1940: istore 133
    //   1942: iload 130
    //   1944: istore 127
    //   1946: goto -85 -> 1861
    //   1949: iload 130
    //   1951: istore 126
    //   1953: aload 5
    //   1955: astore 125
    //   1957: iload 126
    //   1959: iload 127
    //   1961: if_icmpgt -120 -> 1841
    //   1964: new 39	java/lang/String
    //   1967: dup
    //   1968: aload 125
    //   1970: invokespecial 49	java/lang/String:<init>	([C)V
    //   1973: invokevirtual 53	java/lang/String:intern	()Ljava/lang/String;
    //   1976: astore 134
    //   1978: aload_1
    //   1979: iload 124
    //   1981: aload 134
    //   1983: aastore
    //   1984: bipush 12
    //   1986: istore 135
    //   1988: ldc 77
    //   1990: invokevirtual 45	java/lang/String:toCharArray	()[C
    //   1993: astore 136
    //   1995: aload 136
    //   1997: arraylength
    //   1998: istore 137
    //   2000: iload 137
    //   2002: iconst_1
    //   2003: if_icmpgt +10619 -> 12622
    //   2006: iconst_0
    //   2007: istore 138
    //   2009: aload 136
    //   2011: astore 5
    //   2013: iload 138
    //   2015: istore 6
    //   2017: iload 137
    //   2019: istore 139
    //   2021: aload 136
    //   2023: astore 140
    //   2025: iload 139
    //   2027: istore 141
    //   2029: aload 140
    //   2031: iload 138
    //   2033: caload
    //   2034: istore 31
    //   2036: iload 6
    //   2038: iconst_5
    //   2039: irem
    //   2040: tableswitch	default:+32 -> 2072, 0:+8982->11022, 1:+8989->11029, 2:+8996->11036, 3:+9003->11043
    //   2073: irem
    //   2074: istore 142
    //   2076: iload 142
    //   2078: iload 31
    //   2080: ixor
    //   2081: i2c
    //   2082: istore 143
    //   2084: aload 140
    //   2086: iload 138
    //   2088: iload 143
    //   2090: castore
    //   2091: iload 6
    //   2093: iconst_1
    //   2094: iadd
    //   2095: istore 138
    //   2097: iload 141
    //   2099: ifne +18 -> 2117
    //   2102: aload 5
    //   2104: astore 140
    //   2106: iload 138
    //   2108: istore 144
    //   2110: iload 141
    //   2112: istore 138
    //   2114: goto -85 -> 2029
    //   2117: iload 141
    //   2119: istore 137
    //   2121: aload 5
    //   2123: astore 136
    //   2125: iload 137
    //   2127: iload 138
    //   2129: if_icmpgt -120 -> 2009
    //   2132: new 39	java/lang/String
    //   2135: dup
    //   2136: aload 136
    //   2138: invokespecial 49	java/lang/String:<init>	([C)V
    //   2141: invokevirtual 53	java/lang/String:intern	()Ljava/lang/String;
    //   2144: astore 145
    //   2146: aload_1
    //   2147: iload 135
    //   2149: aload 145
    //   2151: aastore
    //   2152: bipush 13
    //   2154: istore 146
    //   2156: ldc 79
    //   2158: invokevirtual 45	java/lang/String:toCharArray	()[C
    //   2161: astore 147
    //   2163: aload 147
    //   2165: arraylength
    //   2166: istore 148
    //   2168: iload 148
    //   2170: iconst_1
    //   2171: if_icmpgt +10445 -> 12616
    //   2174: iconst_0
    //   2175: istore 149
    //   2177: aload 147
    //   2179: astore 5
    //   2181: iload 149
    //   2183: istore 6
    //   2185: iload 148
    //   2187: istore 150
    //   2189: aload 147
    //   2191: astore 151
    //   2193: iload 150
    //   2195: istore 152
    //   2197: aload 151
    //   2199: iload 149
    //   2201: caload
    //   2202: istore 31
    //   2204: iload 6
    //   2206: iconst_5
    //   2207: irem
    //   2208: tableswitch	default:+32 -> 2240, 0:+8842->11050, 1:+8849->11057, 2:+8856->11064, 3:+8863->11071
    //   2241: irem
    //   2242: istore 153
    //   2244: iload 153
    //   2246: iload 31
    //   2248: ixor
    //   2249: i2c
    //   2250: istore 154
    //   2252: aload 151
    //   2254: iload 149
    //   2256: iload 154
    //   2258: castore
    //   2259: iload 6
    //   2261: iconst_1
    //   2262: iadd
    //   2263: istore 149
    //   2265: iload 152
    //   2267: ifne +18 -> 2285
    //   2270: aload 5
    //   2272: astore 151
    //   2274: iload 149
    //   2276: istore 155
    //   2278: iload 152
    //   2280: istore 149
    //   2282: goto -85 -> 2197
    //   2285: iload 152
    //   2287: istore 148
    //   2289: aload 5
    //   2291: astore 147
    //   2293: iload 148
    //   2295: iload 149
    //   2297: if_icmpgt -120 -> 2177
    //   2300: new 39	java/lang/String
    //   2303: dup
    //   2304: aload 147
    //   2306: invokespecial 49	java/lang/String:<init>	([C)V
    //   2309: invokevirtual 53	java/lang/String:intern	()Ljava/lang/String;
    //   2312: astore 156
    //   2314: aload_1
    //   2315: iload 146
    //   2317: aload 156
    //   2319: aastore
    //   2320: bipush 14
    //   2322: istore 157
    //   2324: ldc 81
    //   2326: invokevirtual 45	java/lang/String:toCharArray	()[C
    //   2329: astore 158
    //   2331: aload 158
    //   2333: arraylength
    //   2334: istore 159
    //   2336: iload 159
    //   2338: iconst_1
    //   2339: if_icmpgt +10271 -> 12610
    //   2342: iconst_0
    //   2343: istore 160
    //   2345: aload 158
    //   2347: astore 5
    //   2349: iload 160
    //   2351: istore 6
    //   2353: iload 159
    //   2355: istore 161
    //   2357: aload 158
    //   2359: astore 162
    //   2361: iload 161
    //   2363: istore 163
    //   2365: aload 162
    //   2367: iload 160
    //   2369: caload
    //   2370: istore 31
    //   2372: iload 6
    //   2374: iconst_5
    //   2375: irem
    //   2376: tableswitch	default:+32 -> 2408, 0:+8702->11078, 1:+8709->11085, 2:+8716->11092, 3:+8723->11099
    //   2409: irem
    //   2410: istore 164
    //   2412: iload 164
    //   2414: iload 31
    //   2416: ixor
    //   2417: i2c
    //   2418: istore 165
    //   2420: aload 162
    //   2422: iload 160
    //   2424: iload 165
    //   2426: castore
    //   2427: iload 6
    //   2429: iconst_1
    //   2430: iadd
    //   2431: istore 160
    //   2433: iload 163
    //   2435: ifne +18 -> 2453
    //   2438: aload 5
    //   2440: astore 162
    //   2442: iload 160
    //   2444: istore 166
    //   2446: iload 163
    //   2448: istore 160
    //   2450: goto -85 -> 2365
    //   2453: iload 163
    //   2455: istore 159
    //   2457: aload 5
    //   2459: astore 158
    //   2461: iload 159
    //   2463: iload 160
    //   2465: if_icmpgt -120 -> 2345
    //   2468: new 39	java/lang/String
    //   2471: dup
    //   2472: aload 158
    //   2474: invokespecial 49	java/lang/String:<init>	([C)V
    //   2477: invokevirtual 53	java/lang/String:intern	()Ljava/lang/String;
    //   2480: astore 167
    //   2482: aload_1
    //   2483: iload 157
    //   2485: aload 167
    //   2487: aastore
    //   2488: bipush 15
    //   2490: istore 168
    //   2492: ldc 83
    //   2494: invokevirtual 45	java/lang/String:toCharArray	()[C
    //   2497: astore 169
    //   2499: aload 169
    //   2501: arraylength
    //   2502: istore 170
    //   2504: iload 170
    //   2506: iconst_1
    //   2507: if_icmpgt +10097 -> 12604
    //   2510: iconst_0
    //   2511: istore 171
    //   2513: aload 169
    //   2515: astore 5
    //   2517: iload 171
    //   2519: istore 6
    //   2521: iload 170
    //   2523: istore 172
    //   2525: aload 169
    //   2527: astore 173
    //   2529: iload 172
    //   2531: istore 174
    //   2533: aload 173
    //   2535: iload 171
    //   2537: caload
    //   2538: istore 31
    //   2540: iload 6
    //   2542: iconst_5
    //   2543: irem
    //   2544: tableswitch	default:+32 -> 2576, 0:+8562->11106, 1:+8569->11113, 2:+8576->11120, 3:+8583->11127
    //   2577: irem
    //   2578: istore 175
    //   2580: iload 175
    //   2582: iload 31
    //   2584: ixor
    //   2585: i2c
    //   2586: istore 176
    //   2588: aload 173
    //   2590: iload 171
    //   2592: iload 176
    //   2594: castore
    //   2595: iload 6
    //   2597: iconst_1
    //   2598: iadd
    //   2599: istore 171
    //   2601: iload 174
    //   2603: ifne +18 -> 2621
    //   2606: aload 5
    //   2608: astore 173
    //   2610: iload 171
    //   2612: istore 177
    //   2614: iload 174
    //   2616: istore 171
    //   2618: goto -85 -> 2533
    //   2621: iload 174
    //   2623: istore 170
    //   2625: aload 5
    //   2627: astore 169
    //   2629: iload 170
    //   2631: iload 171
    //   2633: if_icmpgt -120 -> 2513
    //   2636: new 39	java/lang/String
    //   2639: dup
    //   2640: aload 169
    //   2642: invokespecial 49	java/lang/String:<init>	([C)V
    //   2645: invokevirtual 53	java/lang/String:intern	()Ljava/lang/String;
    //   2648: astore 178
    //   2650: aload_1
    //   2651: iload 168
    //   2653: aload 178
    //   2655: aastore
    //   2656: bipush 16
    //   2658: istore 179
    //   2660: ldc 85
    //   2662: invokevirtual 45	java/lang/String:toCharArray	()[C
    //   2665: astore 180
    //   2667: aload 180
    //   2669: arraylength
    //   2670: istore 181
    //   2672: iload 181
    //   2674: iconst_1
    //   2675: if_icmpgt +9923 -> 12598
    //   2678: iconst_0
    //   2679: istore 182
    //   2681: aload 180
    //   2683: astore 5
    //   2685: iload 182
    //   2687: istore 6
    //   2689: iload 181
    //   2691: istore 183
    //   2693: aload 180
    //   2695: astore 184
    //   2697: iload 183
    //   2699: istore 185
    //   2701: aload 184
    //   2703: iload 182
    //   2705: caload
    //   2706: istore 31
    //   2708: iload 6
    //   2710: iconst_5
    //   2711: irem
    //   2712: tableswitch	default:+32 -> 2744, 0:+8422->11134, 1:+8429->11141, 2:+8436->11148, 3:+8443->11155
    //   2745: irem
    //   2746: istore 186
    //   2748: iload 186
    //   2750: iload 31
    //   2752: ixor
    //   2753: i2c
    //   2754: istore 187
    //   2756: aload 184
    //   2758: iload 182
    //   2760: iload 187
    //   2762: castore
    //   2763: iload 6
    //   2765: iconst_1
    //   2766: iadd
    //   2767: istore 182
    //   2769: iload 185
    //   2771: ifne +18 -> 2789
    //   2774: aload 5
    //   2776: astore 184
    //   2778: iload 182
    //   2780: istore 188
    //   2782: iload 185
    //   2784: istore 182
    //   2786: goto -85 -> 2701
    //   2789: iload 185
    //   2791: istore 181
    //   2793: aload 5
    //   2795: astore 180
    //   2797: iload 181
    //   2799: iload 182
    //   2801: if_icmpgt -120 -> 2681
    //   2804: new 39	java/lang/String
    //   2807: dup
    //   2808: aload 180
    //   2810: invokespecial 49	java/lang/String:<init>	([C)V
    //   2813: invokevirtual 53	java/lang/String:intern	()Ljava/lang/String;
    //   2816: astore 189
    //   2818: aload_1
    //   2819: iload 179
    //   2821: aload 189
    //   2823: aastore
    //   2824: bipush 17
    //   2826: istore 190
    //   2828: ldc 87
    //   2830: invokevirtual 45	java/lang/String:toCharArray	()[C
    //   2833: astore 191
    //   2835: aload 191
    //   2837: arraylength
    //   2838: istore 192
    //   2840: iload 192
    //   2842: iconst_1
    //   2843: if_icmpgt +9749 -> 12592
    //   2846: iconst_0
    //   2847: istore 193
    //   2849: aload 191
    //   2851: astore 5
    //   2853: iload 193
    //   2855: istore 6
    //   2857: iload 192
    //   2859: istore 194
    //   2861: aload 191
    //   2863: astore 195
    //   2865: iload 194
    //   2867: istore 196
    //   2869: aload 195
    //   2871: iload 193
    //   2873: caload
    //   2874: istore 31
    //   2876: iload 6
    //   2878: iconst_5
    //   2879: irem
    //   2880: tableswitch	default:+32 -> 2912, 0:+8282->11162, 1:+8289->11169, 2:+8296->11176, 3:+8303->11183
    //   2913: irem
    //   2914: istore 197
    //   2916: iload 197
    //   2918: iload 31
    //   2920: ixor
    //   2921: i2c
    //   2922: istore 198
    //   2924: aload 195
    //   2926: iload 193
    //   2928: iload 198
    //   2930: castore
    //   2931: iload 6
    //   2933: iconst_1
    //   2934: iadd
    //   2935: istore 193
    //   2937: iload 196
    //   2939: ifne +18 -> 2957
    //   2942: aload 5
    //   2944: astore 195
    //   2946: iload 193
    //   2948: istore 199
    //   2950: iload 196
    //   2952: istore 193
    //   2954: goto -85 -> 2869
    //   2957: iload 196
    //   2959: istore 192
    //   2961: aload 5
    //   2963: astore 191
    //   2965: iload 192
    //   2967: iload 193
    //   2969: if_icmpgt -120 -> 2849
    //   2972: new 39	java/lang/String
    //   2975: dup
    //   2976: aload 191
    //   2978: invokespecial 49	java/lang/String:<init>	([C)V
    //   2981: invokevirtual 53	java/lang/String:intern	()Ljava/lang/String;
    //   2984: astore 200
    //   2986: aload_1
    //   2987: iload 190
    //   2989: aload 200
    //   2991: aastore
    //   2992: bipush 18
    //   2994: istore 201
    //   2996: ldc 89
    //   2998: invokevirtual 45	java/lang/String:toCharArray	()[C
    //   3001: astore 202
    //   3003: aload 202
    //   3005: arraylength
    //   3006: istore 203
    //   3008: iload 203
    //   3010: iconst_1
    //   3011: if_icmpgt +9575 -> 12586
    //   3014: iconst_0
    //   3015: istore 204
    //   3017: aload 202
    //   3019: astore 5
    //   3021: iload 204
    //   3023: istore 6
    //   3025: iload 203
    //   3027: istore 205
    //   3029: aload 202
    //   3031: astore 206
    //   3033: iload 205
    //   3035: istore 207
    //   3037: aload 206
    //   3039: iload 204
    //   3041: caload
    //   3042: istore 31
    //   3044: iload 6
    //   3046: iconst_5
    //   3047: irem
    //   3048: tableswitch	default:+32 -> 3080, 0:+8142->11190, 1:+8149->11197, 2:+8156->11204, 3:+8163->11211
    //   3081: irem
    //   3082: istore 208
    //   3084: iload 208
    //   3086: iload 31
    //   3088: ixor
    //   3089: i2c
    //   3090: istore 209
    //   3092: aload 206
    //   3094: iload 204
    //   3096: iload 209
    //   3098: castore
    //   3099: iload 6
    //   3101: iconst_1
    //   3102: iadd
    //   3103: istore 204
    //   3105: iload 207
    //   3107: ifne +18 -> 3125
    //   3110: aload 5
    //   3112: astore 206
    //   3114: iload 204
    //   3116: istore 210
    //   3118: iload 207
    //   3120: istore 204
    //   3122: goto -85 -> 3037
    //   3125: iload 207
    //   3127: istore 203
    //   3129: aload 5
    //   3131: astore 202
    //   3133: iload 203
    //   3135: iload 204
    //   3137: if_icmpgt -120 -> 3017
    //   3140: new 39	java/lang/String
    //   3143: dup
    //   3144: aload 202
    //   3146: invokespecial 49	java/lang/String:<init>	([C)V
    //   3149: invokevirtual 53	java/lang/String:intern	()Ljava/lang/String;
    //   3152: astore 211
    //   3154: aload_1
    //   3155: iload 201
    //   3157: aload 211
    //   3159: aastore
    //   3160: bipush 19
    //   3162: istore 212
    //   3164: ldc 91
    //   3166: invokevirtual 45	java/lang/String:toCharArray	()[C
    //   3169: astore 213
    //   3171: aload 213
    //   3173: arraylength
    //   3174: istore 214
    //   3176: iload 214
    //   3178: iconst_1
    //   3179: if_icmpgt +9401 -> 12580
    //   3182: iconst_0
    //   3183: istore 215
    //   3185: aload 213
    //   3187: astore 5
    //   3189: iload 215
    //   3191: istore 6
    //   3193: iload 214
    //   3195: istore 216
    //   3197: aload 213
    //   3199: astore 217
    //   3201: iload 216
    //   3203: istore 218
    //   3205: aload 217
    //   3207: iload 215
    //   3209: caload
    //   3210: istore 31
    //   3212: iload 6
    //   3214: iconst_5
    //   3215: irem
    //   3216: tableswitch	default:+32 -> 3248, 0:+8002->11218, 1:+8009->11225, 2:+8016->11232, 3:+8023->11239
    //   3249: irem
    //   3250: istore 219
    //   3252: iload 219
    //   3254: iload 31
    //   3256: ixor
    //   3257: i2c
    //   3258: istore 220
    //   3260: aload 217
    //   3262: iload 215
    //   3264: iload 220
    //   3266: castore
    //   3267: iload 6
    //   3269: iconst_1
    //   3270: iadd
    //   3271: istore 215
    //   3273: iload 218
    //   3275: ifne +18 -> 3293
    //   3278: aload 5
    //   3280: astore 217
    //   3282: iload 215
    //   3284: istore 221
    //   3286: iload 218
    //   3288: istore 215
    //   3290: goto -85 -> 3205
    //   3293: iload 218
    //   3295: istore 214
    //   3297: aload 5
    //   3299: astore 213
    //   3301: iload 214
    //   3303: iload 215
    //   3305: if_icmpgt -120 -> 3185
    //   3308: new 39	java/lang/String
    //   3311: dup
    //   3312: aload 213
    //   3314: invokespecial 49	java/lang/String:<init>	([C)V
    //   3317: invokevirtual 53	java/lang/String:intern	()Ljava/lang/String;
    //   3320: astore 222
    //   3322: aload_1
    //   3323: iload 212
    //   3325: aload 222
    //   3327: aastore
    //   3328: bipush 20
    //   3330: istore 223
    //   3332: ldc 93
    //   3334: invokevirtual 45	java/lang/String:toCharArray	()[C
    //   3337: astore 224
    //   3339: aload 224
    //   3341: arraylength
    //   3342: istore 225
    //   3344: iload 225
    //   3346: iconst_1
    //   3347: if_icmpgt +9227 -> 12574
    //   3350: iconst_0
    //   3351: istore 226
    //   3353: aload 224
    //   3355: astore 5
    //   3357: iload 226
    //   3359: istore 6
    //   3361: iload 225
    //   3363: istore 227
    //   3365: aload 224
    //   3367: astore 228
    //   3369: iload 227
    //   3371: istore 229
    //   3373: aload 228
    //   3375: iload 226
    //   3377: caload
    //   3378: istore 31
    //   3380: iload 6
    //   3382: iconst_5
    //   3383: irem
    //   3384: tableswitch	default:+32 -> 3416, 0:+7862->11246, 1:+7869->11253, 2:+7876->11260, 3:+7883->11267
    //   3417: irem
    //   3418: istore 230
    //   3420: iload 230
    //   3422: iload 31
    //   3424: ixor
    //   3425: i2c
    //   3426: istore 231
    //   3428: aload 228
    //   3430: iload 226
    //   3432: iload 231
    //   3434: castore
    //   3435: iload 6
    //   3437: iconst_1
    //   3438: iadd
    //   3439: istore 226
    //   3441: iload 229
    //   3443: ifne +18 -> 3461
    //   3446: aload 5
    //   3448: astore 228
    //   3450: iload 226
    //   3452: istore 232
    //   3454: iload 229
    //   3456: istore 226
    //   3458: goto -85 -> 3373
    //   3461: iload 229
    //   3463: istore 225
    //   3465: aload 5
    //   3467: astore 224
    //   3469: iload 225
    //   3471: iload 226
    //   3473: if_icmpgt -120 -> 3353
    //   3476: new 39	java/lang/String
    //   3479: dup
    //   3480: aload 224
    //   3482: invokespecial 49	java/lang/String:<init>	([C)V
    //   3485: invokevirtual 53	java/lang/String:intern	()Ljava/lang/String;
    //   3488: astore 233
    //   3490: aload_1
    //   3491: iload 223
    //   3493: aload 233
    //   3495: aastore
    //   3496: bipush 21
    //   3498: istore 234
    //   3500: ldc 95
    //   3502: invokevirtual 45	java/lang/String:toCharArray	()[C
    //   3505: astore 235
    //   3507: aload 235
    //   3509: arraylength
    //   3510: istore 236
    //   3512: iload 236
    //   3514: iconst_1
    //   3515: if_icmpgt +9053 -> 12568
    //   3518: iconst_0
    //   3519: istore 237
    //   3521: aload 235
    //   3523: astore 5
    //   3525: iload 237
    //   3527: istore 6
    //   3529: iload 236
    //   3531: istore 238
    //   3533: aload 235
    //   3535: astore 239
    //   3537: iload 238
    //   3539: istore 240
    //   3541: aload 239
    //   3543: iload 237
    //   3545: caload
    //   3546: istore 31
    //   3548: iload 6
    //   3550: iconst_5
    //   3551: irem
    //   3552: tableswitch	default:+32 -> 3584, 0:+7722->11274, 1:+7729->11281, 2:+7736->11288, 3:+7743->11295
    //   3585: irem
    //   3586: istore 241
    //   3588: iload 241
    //   3590: iload 31
    //   3592: ixor
    //   3593: i2c
    //   3594: istore 242
    //   3596: aload 239
    //   3598: iload 237
    //   3600: iload 242
    //   3602: castore
    //   3603: iload 6
    //   3605: iconst_1
    //   3606: iadd
    //   3607: istore 237
    //   3609: iload 240
    //   3611: ifne +18 -> 3629
    //   3614: aload 5
    //   3616: astore 239
    //   3618: iload 237
    //   3620: istore 243
    //   3622: iload 240
    //   3624: istore 237
    //   3626: goto -85 -> 3541
    //   3629: iload 240
    //   3631: istore 236
    //   3633: aload 5
    //   3635: astore 235
    //   3637: iload 236
    //   3639: iload 237
    //   3641: if_icmpgt -120 -> 3521
    //   3644: new 39	java/lang/String
    //   3647: dup
    //   3648: aload 235
    //   3650: invokespecial 49	java/lang/String:<init>	([C)V
    //   3653: invokevirtual 53	java/lang/String:intern	()Ljava/lang/String;
    //   3656: astore 244
    //   3658: aload_1
    //   3659: iload 234
    //   3661: aload 244
    //   3663: aastore
    //   3664: bipush 22
    //   3666: istore 245
    //   3668: ldc 97
    //   3670: invokevirtual 45	java/lang/String:toCharArray	()[C
    //   3673: astore 246
    //   3675: aload 246
    //   3677: arraylength
    //   3678: istore 247
    //   3680: iload 247
    //   3682: iconst_1
    //   3683: if_icmpgt +8879 -> 12562
    //   3686: iconst_0
    //   3687: istore 248
    //   3689: aload 246
    //   3691: astore 5
    //   3693: iload 248
    //   3695: istore 6
    //   3697: iload 247
    //   3699: istore 249
    //   3701: aload 246
    //   3703: astore 250
    //   3705: iload 249
    //   3707: istore 251
    //   3709: aload 250
    //   3711: iload 248
    //   3713: caload
    //   3714: istore 31
    //   3716: iload 6
    //   3718: iconst_5
    //   3719: irem
    //   3720: tableswitch	default:+32 -> 3752, 0:+7582->11302, 1:+7589->11309, 2:+7596->11316, 3:+7603->11323
    //   3753: irem
    //   3754: istore 252
    //   3756: iload 252
    //   3758: iload 31
    //   3760: ixor
    //   3761: i2c
    //   3762: istore 253
    //   3764: aload 250
    //   3766: iload 248
    //   3768: iload 253
    //   3770: castore
    //   3771: iload 6
    //   3773: iconst_1
    //   3774: iadd
    //   3775: istore 248
    //   3777: iload 251
    //   3779: ifne +18 -> 3797
    //   3782: aload 5
    //   3784: astore 250
    //   3786: iload 248
    //   3788: istore 254
    //   3790: iload 251
    //   3792: istore 248
    //   3794: goto -85 -> 3709
    //   3797: iload 251
    //   3799: istore 247
    //   3801: aload 5
    //   3803: astore 246
    //   3805: iload 247
    //   3807: iload 248
    //   3809: if_icmpgt -120 -> 3689
    //   3812: new 39	java/lang/String
    //   3815: dup
    //   3816: aload 246
    //   3818: invokespecial 49	java/lang/String:<init>	([C)V
    //   3821: invokevirtual 53	java/lang/String:intern	()Ljava/lang/String;
    //   3824: astore 255
    //   3826: aload_1
    //   3827: iload 245
    //   3829: aload 255
    //   3831: aastore
    //   3832: bipush 23
    //   3834: wide
    //   3838: ldc 99
    //   3840: invokevirtual 45	java/lang/String:toCharArray	()[C
    //   3843: wide
    //   3847: wide
    //   3851: arraylength
    //   3852: wide
    //   3856: wide
    //   3860: iconst_1
    //   3861: if_icmpgt +8693 -> 12554
    //   3864: iconst_0
    //   3865: wide
    //   3869: wide
    //   3873: astore 5
    //   3875: wide
    //   3879: istore 6
    //   3881: wide
    //   3885: wide
    //   3889: wide
    //   3893: wide
    //   3897: wide
    //   3901: wide
    //   3905: wide
    //   3909: wide
    //   3913: caload
    //   3914: istore 31
    //   3916: iload 6
    //   3918: iconst_5
    //   3919: irem
    //   3920: tableswitch	default:+32 -> 3952, 0:+7410->11330, 1:+7419->11339, 2:+7428->11348, 3:+7437->11357
    //   3953: irem
    //   3954: wide
    //   3958: wide
    //   3962: iload 31
    //   3964: ixor
    //   3965: i2c
    //   3966: wide
    //   3970: wide
    //   3974: wide
    //   3978: wide
    //   3982: castore
    //   3983: iload 6
    //   3985: iconst_1
    //   3986: iadd
    //   3987: wide
    //   3991: wide
    //   3995: ifne +28 -> 4023
    //   3998: aload 5
    //   4000: wide
    //   4004: wide
    //   4008: wide
    //   4012: wide
    //   4016: wide
    //   4020: goto -115 -> 3905
    //   4023: wide
    //   4027: wide
    //   4031: aload 5
    //   4033: wide
    //   4037: wide
    //   4041: wide
    //   4045: if_icmpgt -176 -> 3869
    //   4048: new 39	java/lang/String
    //   4051: dup
    //   4052: wide
    //   4056: invokespecial 49	java/lang/String:<init>	([C)V
    //   4059: invokevirtual 53	java/lang/String:intern	()Ljava/lang/String;
    //   4062: wide
    //   4066: aload_1
    //   4067: wide
    //   4071: wide
    //   4075: aastore
    //   4076: bipush 24
    //   4078: wide
    //   4082: ldc 101
    //   4084: invokevirtual 45	java/lang/String:toCharArray	()[C
    //   4087: wide
    //   4091: wide
    //   4095: arraylength
    //   4096: wide
    //   4100: wide
    //   4104: iconst_1
    //   4105: if_icmpgt +8441 -> 12546
    //   4108: iconst_0
    //   4109: wide
    //   4113: wide
    //   4117: astore 5
    //   4119: wide
    //   4123: istore 6
    //   4125: wide
    //   4129: wide
    //   4133: wide
    //   4137: wide
    //   4141: wide
    //   4145: wide
    //   4149: wide
    //   4153: wide
    //   4157: caload
    //   4158: istore 31
    //   4160: iload 6
    //   4162: iconst_5
    //   4163: irem
    //   4164: tableswitch	default:+32 -> 4196, 0:+7202->11366, 1:+7211->11375, 2:+7220->11384, 3:+7229->11393
    //   4197: irem
    //   4198: wide
    //   4202: wide
    //   4206: iload 31
    //   4208: ixor
    //   4209: i2c
    //   4210: wide
    //   4214: wide
    //   4218: wide
    //   4222: wide
    //   4226: castore
    //   4227: iload 6
    //   4229: iconst_1
    //   4230: iadd
    //   4231: wide
    //   4235: wide
    //   4239: ifne +28 -> 4267
    //   4242: aload 5
    //   4244: wide
    //   4248: wide
    //   4252: wide
    //   4256: wide
    //   4260: wide
    //   4264: goto -115 -> 4149
    //   4267: wide
    //   4271: wide
    //   4275: aload 5
    //   4277: wide
    //   4281: wide
    //   4285: wide
    //   4289: if_icmpgt -176 -> 4113
    //   4292: new 39	java/lang/String
    //   4295: dup
    //   4296: wide
    //   4300: invokespecial 49	java/lang/String:<init>	([C)V
    //   4303: invokevirtual 53	java/lang/String:intern	()Ljava/lang/String;
    //   4306: wide
    //   4310: aload_1
    //   4311: wide
    //   4315: wide
    //   4319: aastore
    //   4320: bipush 25
    //   4322: wide
    //   4326: ldc 103
    //   4328: invokevirtual 45	java/lang/String:toCharArray	()[C
    //   4331: wide
    //   4335: wide
    //   4339: arraylength
    //   4340: wide
    //   4344: wide
    //   4348: iconst_1
    //   4349: if_icmpgt +8189 -> 12538
    //   4352: iconst_0
    //   4353: wide
    //   4357: wide
    //   4361: astore 5
    //   4363: wide
    //   4367: istore 6
    //   4369: wide
    //   4373: wide
    //   4377: wide
    //   4381: wide
    //   4385: wide
    //   4389: wide
    //   4393: wide
    //   4397: wide
    //   4401: caload
    //   4402: istore 31
    //   4404: iload 6
    //   4406: iconst_5
    //   4407: irem
    //   4408: tableswitch	default:+32 -> 4440, 0:+6994->11402, 1:+7003->11411, 2:+7012->11420, 3:+7021->11429
    //   4441: irem
    //   4442: wide
    //   4446: wide
    //   4450: iload 31
    //   4452: ixor
    //   4453: i2c
    //   4454: wide
    //   4458: wide
    //   4462: wide
    //   4466: wide
    //   4470: castore
    //   4471: iload 6
    //   4473: iconst_1
    //   4474: iadd
    //   4475: wide
    //   4479: wide
    //   4483: ifne +28 -> 4511
    //   4486: aload 5
    //   4488: wide
    //   4492: wide
    //   4496: wide
    //   4500: wide
    //   4504: wide
    //   4508: goto -115 -> 4393
    //   4511: wide
    //   4515: wide
    //   4519: aload 5
    //   4521: wide
    //   4525: wide
    //   4529: wide
    //   4533: if_icmpgt -176 -> 4357
    //   4536: new 39	java/lang/String
    //   4539: dup
    //   4540: wide
    //   4544: invokespecial 49	java/lang/String:<init>	([C)V
    //   4547: invokevirtual 53	java/lang/String:intern	()Ljava/lang/String;
    //   4550: wide
    //   4554: aload_1
    //   4555: wide
    //   4559: wide
    //   4563: aastore
    //   4564: bipush 26
    //   4566: wide
    //   4570: ldc 105
    //   4572: invokevirtual 45	java/lang/String:toCharArray	()[C
    //   4575: wide
    //   4579: wide
    //   4583: arraylength
    //   4584: wide
    //   4588: wide
    //   4592: iconst_1
    //   4593: if_icmpgt +7937 -> 12530
    //   4596: iconst_0
    //   4597: wide
    //   4601: wide
    //   4605: astore 5
    //   4607: wide
    //   4611: istore 6
    //   4613: wide
    //   4617: wide
    //   4621: wide
    //   4625: wide
    //   4629: wide
    //   4633: wide
    //   4637: wide
    //   4641: wide
    //   4645: caload
    //   4646: istore 31
    //   4648: iload 6
    //   4650: iconst_5
    //   4651: irem
    //   4652: tableswitch	default:+32 -> 4684, 0:+6786->11438, 1:+6795->11447, 2:+6804->11456, 3:+6813->11465
    //   4685: irem
    //   4686: wide
    //   4690: wide
    //   4694: iload 31
    //   4696: ixor
    //   4697: i2c
    //   4698: wide
    //   4702: wide
    //   4706: wide
    //   4710: wide
    //   4714: castore
    //   4715: iload 6
    //   4717: iconst_1
    //   4718: iadd
    //   4719: wide
    //   4723: wide
    //   4727: ifne +28 -> 4755
    //   4730: aload 5
    //   4732: wide
    //   4736: wide
    //   4740: wide
    //   4744: wide
    //   4748: wide
    //   4752: goto -115 -> 4637
    //   4755: wide
    //   4759: wide
    //   4763: aload 5
    //   4765: wide
    //   4769: wide
    //   4773: wide
    //   4777: if_icmpgt -176 -> 4601
    //   4780: new 39	java/lang/String
    //   4783: dup
    //   4784: wide
    //   4788: invokespecial 49	java/lang/String:<init>	([C)V
    //   4791: invokevirtual 53	java/lang/String:intern	()Ljava/lang/String;
    //   4794: wide
    //   4798: aload_1
    //   4799: wide
    //   4803: wide
    //   4807: aastore
    //   4808: bipush 27
    //   4810: wide
    //   4814: ldc 107
    //   4816: invokevirtual 45	java/lang/String:toCharArray	()[C
    //   4819: wide
    //   4823: wide
    //   4827: arraylength
    //   4828: wide
    //   4832: wide
    //   4836: iconst_1
    //   4837: if_icmpgt +7685 -> 12522
    //   4840: iconst_0
    //   4841: wide
    //   4845: wide
    //   4849: astore 5
    //   4851: wide
    //   4855: istore 6
    //   4857: wide
    //   4861: wide
    //   4865: wide
    //   4869: wide
    //   4873: wide
    //   4877: wide
    //   4881: wide
    //   4885: wide
    //   4889: caload
    //   4890: istore 31
    //   4892: iload 6
    //   4894: iconst_5
    //   4895: irem
    //   4896: tableswitch	default:+32 -> 4928, 0:+6578->11474, 1:+6587->11483, 2:+6596->11492, 3:+6605->11501
    //   4929: irem
    //   4930: wide
    //   4934: wide
    //   4938: iload 31
    //   4940: ixor
    //   4941: i2c
    //   4942: wide
    //   4946: wide
    //   4950: wide
    //   4954: wide
    //   4958: castore
    //   4959: iload 6
    //   4961: iconst_1
    //   4962: iadd
    //   4963: wide
    //   4967: wide
    //   4971: ifne +28 -> 4999
    //   4974: aload 5
    //   4976: wide
    //   4980: wide
    //   4984: wide
    //   4988: wide
    //   4992: wide
    //   4996: goto -115 -> 4881
    //   4999: wide
    //   5003: wide
    //   5007: aload 5
    //   5009: wide
    //   5013: wide
    //   5017: wide
    //   5021: if_icmpgt -176 -> 4845
    //   5024: new 39	java/lang/String
    //   5027: dup
    //   5028: wide
    //   5032: invokespecial 49	java/lang/String:<init>	([C)V
    //   5035: invokevirtual 53	java/lang/String:intern	()Ljava/lang/String;
    //   5038: wide
    //   5042: aload_1
    //   5043: wide
    //   5047: wide
    //   5051: aastore
    //   5052: bipush 28
    //   5054: wide
    //   5058: ldc 109
    //   5060: invokevirtual 45	java/lang/String:toCharArray	()[C
    //   5063: wide
    //   5067: wide
    //   5071: arraylength
    //   5072: wide
    //   5076: wide
    //   5080: iconst_1
    //   5081: if_icmpgt +7433 -> 12514
    //   5084: iconst_0
    //   5085: wide
    //   5089: wide
    //   5093: astore 5
    //   5095: wide
    //   5099: istore 6
    //   5101: wide
    //   5105: wide
    //   5109: wide
    //   5113: wide
    //   5117: wide
    //   5121: wide
    //   5125: wide
    //   5129: wide
    //   5133: caload
    //   5134: istore 31
    //   5136: iload 6
    //   5138: iconst_5
    //   5139: irem
    //   5140: tableswitch	default:+32 -> 5172, 0:+6370->11510, 1:+6379->11519, 2:+6388->11528, 3:+6397->11537
    //   5173: irem
    //   5174: wide
    //   5178: wide
    //   5182: iload 31
    //   5184: ixor
    //   5185: i2c
    //   5186: wide
    //   5190: wide
    //   5194: wide
    //   5198: wide
    //   5202: castore
    //   5203: iload 6
    //   5205: iconst_1
    //   5206: iadd
    //   5207: wide
    //   5211: wide
    //   5215: ifne +28 -> 5243
    //   5218: aload 5
    //   5220: wide
    //   5224: wide
    //   5228: wide
    //   5232: wide
    //   5236: wide
    //   5240: goto -115 -> 5125
    //   5243: wide
    //   5247: wide
    //   5251: aload 5
    //   5253: wide
    //   5257: wide
    //   5261: wide
    //   5265: if_icmpgt -176 -> 5089
    //   5268: new 39	java/lang/String
    //   5271: dup
    //   5272: wide
    //   5276: invokespecial 49	java/lang/String:<init>	([C)V
    //   5279: invokevirtual 53	java/lang/String:intern	()Ljava/lang/String;
    //   5282: wide
    //   5286: aload_1
    //   5287: wide
    //   5291: wide
    //   5295: aastore
    //   5296: bipush 29
    //   5298: wide
    //   5302: ldc 111
    //   5304: invokevirtual 45	java/lang/String:toCharArray	()[C
    //   5307: wide
    //   5311: wide
    //   5315: arraylength
    //   5316: wide
    //   5320: wide
    //   5324: iconst_1
    //   5325: if_icmpgt +7181 -> 12506
    //   5328: iconst_0
    //   5329: wide
    //   5333: wide
    //   5337: astore 5
    //   5339: wide
    //   5343: istore 6
    //   5345: wide
    //   5349: wide
    //   5353: wide
    //   5357: wide
    //   5361: wide
    //   5365: wide
    //   5369: wide
    //   5373: wide
    //   5377: caload
    //   5378: istore 31
    //   5380: iload 6
    //   5382: iconst_5
    //   5383: irem
    //   5384: tableswitch	default:+32 -> 5416, 0:+6162->11546, 1:+6171->11555, 2:+6180->11564, 3:+6189->11573
    //   5417: irem
    //   5418: wide
    //   5422: wide
    //   5426: iload 31
    //   5428: ixor
    //   5429: i2c
    //   5430: wide
    //   5434: wide
    //   5438: wide
    //   5442: wide
    //   5446: castore
    //   5447: iload 6
    //   5449: iconst_1
    //   5450: iadd
    //   5451: wide
    //   5455: wide
    //   5459: ifne +28 -> 5487
    //   5462: aload 5
    //   5464: wide
    //   5468: wide
    //   5472: wide
    //   5476: wide
    //   5480: wide
    //   5484: goto -115 -> 5369
    //   5487: wide
    //   5491: wide
    //   5495: aload 5
    //   5497: wide
    //   5501: wide
    //   5505: wide
    //   5509: if_icmpgt -176 -> 5333
    //   5512: new 39	java/lang/String
    //   5515: dup
    //   5516: wide
    //   5520: invokespecial 49	java/lang/String:<init>	([C)V
    //   5523: invokevirtual 53	java/lang/String:intern	()Ljava/lang/String;
    //   5526: wide
    //   5530: aload_1
    //   5531: wide
    //   5535: wide
    //   5539: aastore
    //   5540: bipush 30
    //   5542: wide
    //   5546: ldc 113
    //   5548: invokevirtual 45	java/lang/String:toCharArray	()[C
    //   5551: wide
    //   5555: wide
    //   5559: arraylength
    //   5560: wide
    //   5564: wide
    //   5568: iconst_1
    //   5569: if_icmpgt +6929 -> 12498
    //   5572: iconst_0
    //   5573: wide
    //   5577: wide
    //   5581: astore 5
    //   5583: wide
    //   5587: istore 6
    //   5589: wide
    //   5593: wide
    //   5597: wide
    //   5601: wide
    //   5605: wide
    //   5609: wide
    //   5613: wide
    //   5617: wide
    //   5621: caload
    //   5622: istore 31
    //   5624: iload 6
    //   5626: iconst_5
    //   5627: irem
    //   5628: tableswitch	default:+32 -> 5660, 0:+5954->11582, 1:+5963->11591, 2:+5972->11600, 3:+5981->11609
    //   5661: irem
    //   5662: wide
    //   5666: wide
    //   5670: iload 31
    //   5672: ixor
    //   5673: i2c
    //   5674: wide
    //   5678: wide
    //   5682: wide
    //   5686: wide
    //   5690: castore
    //   5691: iload 6
    //   5693: iconst_1
    //   5694: iadd
    //   5695: wide
    //   5699: wide
    //   5703: ifne +28 -> 5731
    //   5706: aload 5
    //   5708: wide
    //   5712: wide
    //   5716: wide
    //   5720: wide
    //   5724: wide
    //   5728: goto -115 -> 5613
    //   5731: wide
    //   5735: wide
    //   5739: aload 5
    //   5741: wide
    //   5745: wide
    //   5749: wide
    //   5753: if_icmpgt -176 -> 5577
    //   5756: new 39	java/lang/String
    //   5759: dup
    //   5760: wide
    //   5764: invokespecial 49	java/lang/String:<init>	([C)V
    //   5767: invokevirtual 53	java/lang/String:intern	()Ljava/lang/String;
    //   5770: wide
    //   5774: aload_1
    //   5775: wide
    //   5779: wide
    //   5783: aastore
    //   5784: bipush 31
    //   5786: wide
    //   5790: ldc 115
    //   5792: invokevirtual 45	java/lang/String:toCharArray	()[C
    //   5795: wide
    //   5799: wide
    //   5803: arraylength
    //   5804: wide
    //   5808: wide
    //   5812: iconst_1
    //   5813: if_icmpgt +6677 -> 12490
    //   5816: iconst_0
    //   5817: wide
    //   5821: wide
    //   5825: astore 5
    //   5827: wide
    //   5831: istore 6
    //   5833: wide
    //   5837: wide
    //   5841: wide
    //   5845: wide
    //   5849: wide
    //   5853: wide
    //   5857: wide
    //   5861: wide
    //   5865: caload
    //   5866: istore 31
    //   5868: iload 6
    //   5870: iconst_5
    //   5871: irem
    //   5872: tableswitch	default:+32 -> 5904, 0:+5746->11618, 1:+5755->11627, 2:+5764->11636, 3:+5773->11645
    //   5905: irem
    //   5906: wide
    //   5910: wide
    //   5914: iload 31
    //   5916: ixor
    //   5917: i2c
    //   5918: wide
    //   5922: wide
    //   5926: wide
    //   5930: wide
    //   5934: castore
    //   5935: iload 6
    //   5937: iconst_1
    //   5938: iadd
    //   5939: wide
    //   5943: wide
    //   5947: ifne +28 -> 5975
    //   5950: aload 5
    //   5952: wide
    //   5956: wide
    //   5960: wide
    //   5964: wide
    //   5968: wide
    //   5972: goto -115 -> 5857
    //   5975: wide
    //   5979: wide
    //   5983: aload 5
    //   5985: wide
    //   5989: wide
    //   5993: wide
    //   5997: if_icmpgt -176 -> 5821
    //   6000: new 39	java/lang/String
    //   6003: dup
    //   6004: wide
    //   6008: invokespecial 49	java/lang/String:<init>	([C)V
    //   6011: invokevirtual 53	java/lang/String:intern	()Ljava/lang/String;
    //   6014: wide
    //   6018: aload_1
    //   6019: wide
    //   6023: wide
    //   6027: aastore
    //   6028: bipush 32
    //   6030: wide
    //   6034: ldc 117
    //   6036: invokevirtual 45	java/lang/String:toCharArray	()[C
    //   6039: wide
    //   6043: wide
    //   6047: arraylength
    //   6048: wide
    //   6052: wide
    //   6056: iconst_1
    //   6057: if_icmpgt +6425 -> 12482
    //   6060: iconst_0
    //   6061: wide
    //   6065: wide
    //   6069: astore 5
    //   6071: wide
    //   6075: istore 6
    //   6077: wide
    //   6081: wide
    //   6085: wide
    //   6089: wide
    //   6093: wide
    //   6097: wide
    //   6101: wide
    //   6105: wide
    //   6109: caload
    //   6110: istore 31
    //   6112: iload 6
    //   6114: iconst_5
    //   6115: irem
    //   6116: tableswitch	default:+32 -> 6148, 0:+5538->11654, 1:+5547->11663, 2:+5556->11672, 3:+5565->11681
    //   6149: irem
    //   6150: wide
    //   6154: wide
    //   6158: iload 31
    //   6160: ixor
    //   6161: i2c
    //   6162: wide
    //   6166: wide
    //   6170: wide
    //   6174: wide
    //   6178: castore
    //   6179: iload 6
    //   6181: iconst_1
    //   6182: iadd
    //   6183: wide
    //   6187: wide
    //   6191: ifne +28 -> 6219
    //   6194: aload 5
    //   6196: wide
    //   6200: wide
    //   6204: wide
    //   6208: wide
    //   6212: wide
    //   6216: goto -115 -> 6101
    //   6219: wide
    //   6223: wide
    //   6227: aload 5
    //   6229: wide
    //   6233: wide
    //   6237: wide
    //   6241: if_icmpgt -176 -> 6065
    //   6244: new 39	java/lang/String
    //   6247: dup
    //   6248: wide
    //   6252: invokespecial 49	java/lang/String:<init>	([C)V
    //   6255: invokevirtual 53	java/lang/String:intern	()Ljava/lang/String;
    //   6258: wide
    //   6262: aload_1
    //   6263: wide
    //   6267: wide
    //   6271: aastore
    //   6272: bipush 33
    //   6274: wide
    //   6278: ldc 119
    //   6280: invokevirtual 45	java/lang/String:toCharArray	()[C
    //   6283: wide
    //   6287: wide
    //   6291: arraylength
    //   6292: wide
    //   6296: wide
    //   6300: iconst_1
    //   6301: if_icmpgt +6173 -> 12474
    //   6304: iconst_0
    //   6305: wide
    //   6309: wide
    //   6313: astore 5
    //   6315: wide
    //   6319: istore 6
    //   6321: wide
    //   6325: wide
    //   6329: wide
    //   6333: wide
    //   6337: wide
    //   6341: wide
    //   6345: wide
    //   6349: wide
    //   6353: caload
    //   6354: istore 31
    //   6356: iload 6
    //   6358: iconst_5
    //   6359: irem
    //   6360: tableswitch	default:+32 -> 6392, 0:+5330->11690, 1:+5339->11699, 2:+5348->11708, 3:+5357->11717
    //   6393: irem
    //   6394: wide
    //   6398: wide
    //   6402: iload 31
    //   6404: ixor
    //   6405: i2c
    //   6406: wide
    //   6410: wide
    //   6414: wide
    //   6418: wide
    //   6422: castore
    //   6423: iload 6
    //   6425: iconst_1
    //   6426: iadd
    //   6427: wide
    //   6431: wide
    //   6435: ifne +28 -> 6463
    //   6438: aload 5
    //   6440: wide
    //   6444: wide
    //   6448: wide
    //   6452: wide
    //   6456: wide
    //   6460: goto -115 -> 6345
    //   6463: wide
    //   6467: wide
    //   6471: aload 5
    //   6473: wide
    //   6477: wide
    //   6481: wide
    //   6485: if_icmpgt -176 -> 6309
    //   6488: new 39	java/lang/String
    //   6491: dup
    //   6492: wide
    //   6496: invokespecial 49	java/lang/String:<init>	([C)V
    //   6499: invokevirtual 53	java/lang/String:intern	()Ljava/lang/String;
    //   6502: wide
    //   6506: aload_1
    //   6507: wide
    //   6511: wide
    //   6515: aastore
    //   6516: bipush 34
    //   6518: wide
    //   6522: ldc 121
    //   6524: invokevirtual 45	java/lang/String:toCharArray	()[C
    //   6527: wide
    //   6531: wide
    //   6535: arraylength
    //   6536: wide
    //   6540: wide
    //   6544: iconst_1
    //   6545: if_icmpgt +5921 -> 12466
    //   6548: iconst_0
    //   6549: wide
    //   6553: wide
    //   6557: astore 5
    //   6559: wide
    //   6563: istore 6
    //   6565: wide
    //   6569: wide
    //   6573: wide
    //   6577: wide
    //   6581: wide
    //   6585: wide
    //   6589: wide
    //   6593: wide
    //   6597: caload
    //   6598: istore 31
    //   6600: iload 6
    //   6602: iconst_5
    //   6603: irem
    //   6604: tableswitch	default:+32 -> 6636, 0:+5122->11726, 1:+5131->11735, 2:+5140->11744, 3:+5149->11753
    //   6637: irem
    //   6638: wide
    //   6642: wide
    //   6646: iload 31
    //   6648: ixor
    //   6649: i2c
    //   6650: wide
    //   6654: wide
    //   6658: wide
    //   6662: wide
    //   6666: castore
    //   6667: iload 6
    //   6669: iconst_1
    //   6670: iadd
    //   6671: wide
    //   6675: wide
    //   6679: ifne +28 -> 6707
    //   6682: aload 5
    //   6684: wide
    //   6688: wide
    //   6692: wide
    //   6696: wide
    //   6700: wide
    //   6704: goto -115 -> 6589
    //   6707: wide
    //   6711: wide
    //   6715: aload 5
    //   6717: wide
    //   6721: wide
    //   6725: wide
    //   6729: if_icmpgt -176 -> 6553
    //   6732: new 39	java/lang/String
    //   6735: dup
    //   6736: wide
    //   6740: invokespecial 49	java/lang/String:<init>	([C)V
    //   6743: invokevirtual 53	java/lang/String:intern	()Ljava/lang/String;
    //   6746: wide
    //   6750: aload_1
    //   6751: wide
    //   6755: wide
    //   6759: aastore
    //   6760: bipush 35
    //   6762: wide
    //   6766: ldc 123
    //   6768: invokevirtual 45	java/lang/String:toCharArray	()[C
    //   6771: wide
    //   6775: wide
    //   6779: arraylength
    //   6780: wide
    //   6784: wide
    //   6788: iconst_1
    //   6789: if_icmpgt +5669 -> 12458
    //   6792: iconst_0
    //   6793: wide
    //   6797: wide
    //   6801: astore 5
    //   6803: wide
    //   6807: istore 6
    //   6809: wide
    //   6813: wide
    //   6817: wide
    //   6821: wide
    //   6825: wide
    //   6829: wide
    //   6833: wide
    //   6837: wide
    //   6841: caload
    //   6842: istore 31
    //   6844: iload 6
    //   6846: iconst_5
    //   6847: irem
    //   6848: tableswitch	default:+32 -> 6880, 0:+4914->11762, 1:+4923->11771, 2:+4932->11780, 3:+4941->11789
    //   6881: irem
    //   6882: wide
    //   6886: wide
    //   6890: iload 31
    //   6892: ixor
    //   6893: i2c
    //   6894: wide
    //   6898: wide
    //   6902: wide
    //   6906: wide
    //   6910: castore
    //   6911: iload 6
    //   6913: iconst_1
    //   6914: iadd
    //   6915: wide
    //   6919: wide
    //   6923: ifne +28 -> 6951
    //   6926: aload 5
    //   6928: wide
    //   6932: wide
    //   6936: wide
    //   6940: wide
    //   6944: wide
    //   6948: goto -115 -> 6833
    //   6951: wide
    //   6955: wide
    //   6959: aload 5
    //   6961: wide
    //   6965: wide
    //   6969: wide
    //   6973: if_icmpgt -176 -> 6797
    //   6976: new 39	java/lang/String
    //   6979: dup
    //   6980: wide
    //   6984: invokespecial 49	java/lang/String:<init>	([C)V
    //   6987: invokevirtual 53	java/lang/String:intern	()Ljava/lang/String;
    //   6990: wide
    //   6994: aload_1
    //   6995: wide
    //   6999: wide
    //   7003: aastore
    //   7004: bipush 36
    //   7006: wide
    //   7010: ldc 125
    //   7012: invokevirtual 45	java/lang/String:toCharArray	()[C
    //   7015: wide
    //   7019: wide
    //   7023: arraylength
    //   7024: wide
    //   7028: wide
    //   7032: iconst_1
    //   7033: if_icmpgt +5417 -> 12450
    //   7036: iconst_0
    //   7037: wide
    //   7041: wide
    //   7045: astore 5
    //   7047: wide
    //   7051: istore 6
    //   7053: wide
    //   7057: wide
    //   7061: wide
    //   7065: wide
    //   7069: wide
    //   7073: wide
    //   7077: wide
    //   7081: wide
    //   7085: caload
    //   7086: istore 31
    //   7088: iload 6
    //   7090: iconst_5
    //   7091: irem
    //   7092: tableswitch	default:+32 -> 7124, 0:+4706->11798, 1:+4715->11807, 2:+4724->11816, 3:+4733->11825
    //   7125: irem
    //   7126: wide
    //   7130: wide
    //   7134: iload 31
    //   7136: ixor
    //   7137: i2c
    //   7138: wide
    //   7142: wide
    //   7146: wide
    //   7150: wide
    //   7154: castore
    //   7155: iload 6
    //   7157: iconst_1
    //   7158: iadd
    //   7159: wide
    //   7163: wide
    //   7167: ifne +28 -> 7195
    //   7170: aload 5
    //   7172: wide
    //   7176: wide
    //   7180: wide
    //   7184: wide
    //   7188: wide
    //   7192: goto -115 -> 7077
    //   7195: wide
    //   7199: wide
    //   7203: aload 5
    //   7205: wide
    //   7209: wide
    //   7213: wide
    //   7217: if_icmpgt -176 -> 7041
    //   7220: new 39	java/lang/String
    //   7223: dup
    //   7224: wide
    //   7228: invokespecial 49	java/lang/String:<init>	([C)V
    //   7231: invokevirtual 53	java/lang/String:intern	()Ljava/lang/String;
    //   7234: wide
    //   7238: aload_1
    //   7239: wide
    //   7243: wide
    //   7247: aastore
    //   7248: bipush 37
    //   7250: wide
    //   7254: ldc 127
    //   7256: invokevirtual 45	java/lang/String:toCharArray	()[C
    //   7259: wide
    //   7263: wide
    //   7267: arraylength
    //   7268: wide
    //   7272: wide
    //   7276: iconst_1
    //   7277: if_icmpgt +5165 -> 12442
    //   7280: iconst_0
    //   7281: wide
    //   7285: wide
    //   7289: astore 5
    //   7291: wide
    //   7295: istore 6
    //   7297: wide
    //   7301: wide
    //   7305: wide
    //   7309: wide
    //   7313: wide
    //   7317: wide
    //   7321: wide
    //   7325: wide
    //   7329: caload
    //   7330: istore 31
    //   7332: iload 6
    //   7334: iconst_5
    //   7335: irem
    //   7336: tableswitch	default:+32 -> 7368, 0:+4498->11834, 1:+4507->11843, 2:+4516->11852, 3:+4525->11861
    //   7369: irem
    //   7370: wide
    //   7374: wide
    //   7378: iload 31
    //   7380: ixor
    //   7381: i2c
    //   7382: wide
    //   7386: wide
    //   7390: wide
    //   7394: wide
    //   7398: castore
    //   7399: iload 6
    //   7401: iconst_1
    //   7402: iadd
    //   7403: wide
    //   7407: wide
    //   7411: ifne +28 -> 7439
    //   7414: aload 5
    //   7416: wide
    //   7420: wide
    //   7424: wide
    //   7428: wide
    //   7432: wide
    //   7436: goto -115 -> 7321
    //   7439: wide
    //   7443: wide
    //   7447: aload 5
    //   7449: wide
    //   7453: wide
    //   7457: wide
    //   7461: if_icmpgt -176 -> 7285
    //   7464: new 39	java/lang/String
    //   7467: dup
    //   7468: wide
    //   7472: invokespecial 49	java/lang/String:<init>	([C)V
    //   7475: invokevirtual 53	java/lang/String:intern	()Ljava/lang/String;
    //   7478: wide
    //   7482: aload_1
    //   7483: wide
    //   7487: wide
    //   7491: aastore
    //   7492: bipush 38
    //   7494: wide
    //   7498: ldc 129
    //   7500: invokevirtual 45	java/lang/String:toCharArray	()[C
    //   7503: wide
    //   7507: wide
    //   7511: arraylength
    //   7512: wide
    //   7516: wide
    //   7520: iconst_1
    //   7521: if_icmpgt +4913 -> 12434
    //   7524: iconst_0
    //   7525: wide
    //   7529: wide
    //   7533: astore 5
    //   7535: wide
    //   7539: istore 6
    //   7541: wide
    //   7545: wide
    //   7549: wide
    //   7553: wide
    //   7557: wide
    //   7561: wide
    //   7565: wide
    //   7569: wide
    //   7573: caload
    //   7574: istore 31
    //   7576: iload 6
    //   7578: iconst_5
    //   7579: irem
    //   7580: tableswitch	default:+32 -> 7612, 0:+4290->11870, 1:+4299->11879, 2:+4308->11888, 3:+4317->11897
    //   7613: irem
    //   7614: wide
    //   7618: wide
    //   7622: iload 31
    //   7624: ixor
    //   7625: i2c
    //   7626: wide
    //   7630: wide
    //   7634: wide
    //   7638: wide
    //   7642: castore
    //   7643: iload 6
    //   7645: iconst_1
    //   7646: iadd
    //   7647: wide
    //   7651: wide
    //   7655: ifne +28 -> 7683
    //   7658: aload 5
    //   7660: wide
    //   7664: wide
    //   7668: wide
    //   7672: wide
    //   7676: wide
    //   7680: goto -115 -> 7565
    //   7683: wide
    //   7687: wide
    //   7691: aload 5
    //   7693: wide
    //   7697: wide
    //   7701: wide
    //   7705: if_icmpgt -176 -> 7529
    //   7708: new 39	java/lang/String
    //   7711: dup
    //   7712: wide
    //   7716: invokespecial 49	java/lang/String:<init>	([C)V
    //   7719: invokevirtual 53	java/lang/String:intern	()Ljava/lang/String;
    //   7722: wide
    //   7726: aload_1
    //   7727: wide
    //   7731: wide
    //   7735: aastore
    //   7736: bipush 39
    //   7738: wide
    //   7742: ldc 131
    //   7744: invokevirtual 45	java/lang/String:toCharArray	()[C
    //   7747: wide
    //   7751: wide
    //   7755: arraylength
    //   7756: wide
    //   7760: wide
    //   7764: iconst_1
    //   7765: if_icmpgt +4661 -> 12426
    //   7768: iconst_0
    //   7769: wide
    //   7773: wide
    //   7777: astore 5
    //   7779: wide
    //   7783: istore 6
    //   7785: wide
    //   7789: wide
    //   7793: wide
    //   7797: wide
    //   7801: wide
    //   7805: wide
    //   7809: wide
    //   7813: wide
    //   7817: caload
    //   7818: istore 31
    //   7820: iload 6
    //   7822: iconst_5
    //   7823: irem
    //   7824: tableswitch	default:+32 -> 7856, 0:+4082->11906, 1:+4091->11915, 2:+4100->11924, 3:+4109->11933
    //   7857: irem
    //   7858: wide
    //   7862: wide
    //   7866: iload 31
    //   7868: ixor
    //   7869: i2c
    //   7870: wide
    //   7874: wide
    //   7878: wide
    //   7882: wide
    //   7886: castore
    //   7887: iload 6
    //   7889: iconst_1
    //   7890: iadd
    //   7891: wide
    //   7895: wide
    //   7899: ifne +28 -> 7927
    //   7902: aload 5
    //   7904: wide
    //   7908: wide
    //   7912: wide
    //   7916: wide
    //   7920: wide
    //   7924: goto -115 -> 7809
    //   7927: wide
    //   7931: wide
    //   7935: aload 5
    //   7937: wide
    //   7941: wide
    //   7945: wide
    //   7949: if_icmpgt -176 -> 7773
    //   7952: new 39	java/lang/String
    //   7955: dup
    //   7956: wide
    //   7960: invokespecial 49	java/lang/String:<init>	([C)V
    //   7963: invokevirtual 53	java/lang/String:intern	()Ljava/lang/String;
    //   7966: wide
    //   7970: aload_1
    //   7971: wide
    //   7975: wide
    //   7979: aastore
    //   7980: bipush 40
    //   7982: wide
    //   7986: ldc 133
    //   7988: invokevirtual 45	java/lang/String:toCharArray	()[C
    //   7991: wide
    //   7995: wide
    //   7999: arraylength
    //   8000: wide
    //   8004: wide
    //   8008: iconst_1
    //   8009: if_icmpgt +4409 -> 12418
    //   8012: iconst_0
    //   8013: wide
    //   8017: wide
    //   8021: astore 5
    //   8023: wide
    //   8027: istore 6
    //   8029: wide
    //   8033: wide
    //   8037: wide
    //   8041: wide
    //   8045: wide
    //   8049: wide
    //   8053: wide
    //   8057: wide
    //   8061: caload
    //   8062: istore 31
    //   8064: iload 6
    //   8066: iconst_5
    //   8067: irem
    //   8068: tableswitch	default:+32 -> 8100, 0:+3874->11942, 1:+3883->11951, 2:+3892->11960, 3:+3901->11969
    //   8101: irem
    //   8102: wide
    //   8106: wide
    //   8110: iload 31
    //   8112: ixor
    //   8113: i2c
    //   8114: wide
    //   8118: wide
    //   8122: wide
    //   8126: wide
    //   8130: castore
    //   8131: iload 6
    //   8133: iconst_1
    //   8134: iadd
    //   8135: wide
    //   8139: wide
    //   8143: ifne +28 -> 8171
    //   8146: aload 5
    //   8148: wide
    //   8152: wide
    //   8156: wide
    //   8160: wide
    //   8164: wide
    //   8168: goto -115 -> 8053
    //   8171: wide
    //   8175: wide
    //   8179: aload 5
    //   8181: wide
    //   8185: wide
    //   8189: wide
    //   8193: if_icmpgt -176 -> 8017
    //   8196: new 39	java/lang/String
    //   8199: dup
    //   8200: wide
    //   8204: invokespecial 49	java/lang/String:<init>	([C)V
    //   8207: invokevirtual 53	java/lang/String:intern	()Ljava/lang/String;
    //   8210: wide
    //   8214: aload_1
    //   8215: wide
    //   8219: wide
    //   8223: aastore
    //   8224: bipush 41
    //   8226: wide
    //   8230: ldc 135
    //   8232: invokevirtual 45	java/lang/String:toCharArray	()[C
    //   8235: wide
    //   8239: wide
    //   8243: arraylength
    //   8244: wide
    //   8248: wide
    //   8252: iconst_1
    //   8253: if_icmpgt +4157 -> 12410
    //   8256: iconst_0
    //   8257: wide
    //   8261: wide
    //   8265: astore 5
    //   8267: wide
    //   8271: istore 6
    //   8273: wide
    //   8277: wide
    //   8281: wide
    //   8285: wide
    //   8289: wide
    //   8293: wide
    //   8297: wide
    //   8301: wide
    //   8305: caload
    //   8306: istore 31
    //   8308: iload 6
    //   8310: iconst_5
    //   8311: irem
    //   8312: tableswitch	default:+32 -> 8344, 0:+3666->11978, 1:+3675->11987, 2:+3684->11996, 3:+3693->12005
    //   8345: irem
    //   8346: wide
    //   8350: wide
    //   8354: iload 31
    //   8356: ixor
    //   8357: i2c
    //   8358: wide
    //   8362: wide
    //   8366: wide
    //   8370: wide
    //   8374: castore
    //   8375: iload 6
    //   8377: iconst_1
    //   8378: iadd
    //   8379: wide
    //   8383: wide
    //   8387: ifne +28 -> 8415
    //   8390: aload 5
    //   8392: wide
    //   8396: wide
    //   8400: wide
    //   8404: wide
    //   8408: wide
    //   8412: goto -115 -> 8297
    //   8415: wide
    //   8419: wide
    //   8423: aload 5
    //   8425: wide
    //   8429: wide
    //   8433: wide
    //   8437: if_icmpgt -176 -> 8261
    //   8440: new 39	java/lang/String
    //   8443: dup
    //   8444: wide
    //   8448: invokespecial 49	java/lang/String:<init>	([C)V
    //   8451: invokevirtual 53	java/lang/String:intern	()Ljava/lang/String;
    //   8454: wide
    //   8458: aload_1
    //   8459: wide
    //   8463: wide
    //   8467: aastore
    //   8468: bipush 42
    //   8470: wide
    //   8474: ldc 137
    //   8476: invokevirtual 45	java/lang/String:toCharArray	()[C
    //   8479: wide
    //   8483: wide
    //   8487: arraylength
    //   8488: wide
    //   8492: wide
    //   8496: iconst_1
    //   8497: if_icmpgt +3905 -> 12402
    //   8500: iconst_0
    //   8501: wide
    //   8505: wide
    //   8509: astore 5
    //   8511: wide
    //   8515: istore 6
    //   8517: wide
    //   8521: wide
    //   8525: wide
    //   8529: wide
    //   8533: wide
    //   8537: wide
    //   8541: wide
    //   8545: wide
    //   8549: caload
    //   8550: istore 31
    //   8552: iload 6
    //   8554: iconst_5
    //   8555: irem
    //   8556: tableswitch	default:+32 -> 8588, 0:+3458->12014, 1:+3467->12023, 2:+3476->12032, 3:+3485->12041
    //   8589: irem
    //   8590: wide
    //   8594: wide
    //   8598: iload 31
    //   8600: ixor
    //   8601: i2c
    //   8602: wide
    //   8606: wide
    //   8610: wide
    //   8614: wide
    //   8618: castore
    //   8619: iload 6
    //   8621: iconst_1
    //   8622: iadd
    //   8623: wide
    //   8627: wide
    //   8631: ifne +28 -> 8659
    //   8634: aload 5
    //   8636: wide
    //   8640: wide
    //   8644: wide
    //   8648: wide
    //   8652: wide
    //   8656: goto -115 -> 8541
    //   8659: wide
    //   8663: wide
    //   8667: aload 5
    //   8669: wide
    //   8673: wide
    //   8677: wide
    //   8681: if_icmpgt -176 -> 8505
    //   8684: new 39	java/lang/String
    //   8687: dup
    //   8688: wide
    //   8692: invokespecial 49	java/lang/String:<init>	([C)V
    //   8695: invokevirtual 53	java/lang/String:intern	()Ljava/lang/String;
    //   8698: wide
    //   8702: aload_1
    //   8703: wide
    //   8707: wide
    //   8711: aastore
    //   8712: bipush 43
    //   8714: wide
    //   8718: ldc 139
    //   8720: invokevirtual 45	java/lang/String:toCharArray	()[C
    //   8723: wide
    //   8727: wide
    //   8731: arraylength
    //   8732: wide
    //   8736: wide
    //   8740: iconst_1
    //   8741: if_icmpgt +3653 -> 12394
    //   8744: iconst_0
    //   8745: wide
    //   8749: wide
    //   8753: astore 5
    //   8755: wide
    //   8759: istore 6
    //   8761: wide
    //   8765: wide
    //   8769: wide
    //   8773: wide
    //   8777: wide
    //   8781: wide
    //   8785: wide
    //   8789: wide
    //   8793: caload
    //   8794: istore 31
    //   8796: iload 6
    //   8798: iconst_5
    //   8799: irem
    //   8800: tableswitch	default:+32 -> 8832, 0:+3250->12050, 1:+3259->12059, 2:+3268->12068, 3:+3277->12077
    //   8833: irem
    //   8834: wide
    //   8838: wide
    //   8842: iload 31
    //   8844: ixor
    //   8845: i2c
    //   8846: wide
    //   8850: wide
    //   8854: wide
    //   8858: wide
    //   8862: castore
    //   8863: iload 6
    //   8865: iconst_1
    //   8866: iadd
    //   8867: wide
    //   8871: wide
    //   8875: ifne +28 -> 8903
    //   8878: aload 5
    //   8880: wide
    //   8884: wide
    //   8888: wide
    //   8892: wide
    //   8896: wide
    //   8900: goto -115 -> 8785
    //   8903: wide
    //   8907: wide
    //   8911: aload 5
    //   8913: wide
    //   8917: wide
    //   8921: wide
    //   8925: if_icmpgt -176 -> 8749
    //   8928: new 39	java/lang/String
    //   8931: dup
    //   8932: wide
    //   8936: invokespecial 49	java/lang/String:<init>	([C)V
    //   8939: invokevirtual 53	java/lang/String:intern	()Ljava/lang/String;
    //   8942: wide
    //   8946: aload_1
    //   8947: wide
    //   8951: wide
    //   8955: aastore
    //   8956: bipush 44
    //   8958: wide
    //   8962: ldc 141
    //   8964: invokevirtual 45	java/lang/String:toCharArray	()[C
    //   8967: wide
    //   8971: wide
    //   8975: arraylength
    //   8976: wide
    //   8980: wide
    //   8984: iconst_1
    //   8985: if_icmpgt +3401 -> 12386
    //   8988: iconst_0
    //   8989: wide
    //   8993: wide
    //   8997: astore 5
    //   8999: wide
    //   9003: istore 6
    //   9005: wide
    //   9009: wide
    //   9013: wide
    //   9017: wide
    //   9021: wide
    //   9025: wide
    //   9029: wide
    //   9033: wide
    //   9037: caload
    //   9038: istore 31
    //   9040: iload 6
    //   9042: iconst_5
    //   9043: irem
    //   9044: tableswitch	default:+32 -> 9076, 0:+3042->12086, 1:+3051->12095, 2:+3060->12104, 3:+3069->12113
    //   9077: irem
    //   9078: wide
    //   9082: wide
    //   9086: iload 31
    //   9088: ixor
    //   9089: i2c
    //   9090: wide
    //   9094: wide
    //   9098: wide
    //   9102: wide
    //   9106: castore
    //   9107: iload 6
    //   9109: iconst_1
    //   9110: iadd
    //   9111: wide
    //   9115: wide
    //   9119: ifne +28 -> 9147
    //   9122: aload 5
    //   9124: wide
    //   9128: wide
    //   9132: wide
    //   9136: wide
    //   9140: wide
    //   9144: goto -115 -> 9029
    //   9147: wide
    //   9151: wide
    //   9155: aload 5
    //   9157: wide
    //   9161: wide
    //   9165: wide
    //   9169: if_icmpgt -176 -> 8993
    //   9172: new 39	java/lang/String
    //   9175: dup
    //   9176: wide
    //   9180: invokespecial 49	java/lang/String:<init>	([C)V
    //   9183: invokevirtual 53	java/lang/String:intern	()Ljava/lang/String;
    //   9186: wide
    //   9190: aload_1
    //   9191: wide
    //   9195: wide
    //   9199: aastore
    //   9200: bipush 45
    //   9202: wide
    //   9206: ldc 143
    //   9208: invokevirtual 45	java/lang/String:toCharArray	()[C
    //   9211: wide
    //   9215: wide
    //   9219: arraylength
    //   9220: wide
    //   9224: wide
    //   9228: iconst_1
    //   9229: if_icmpgt +3149 -> 12378
    //   9232: iconst_0
    //   9233: wide
    //   9237: wide
    //   9241: astore 5
    //   9243: wide
    //   9247: istore 6
    //   9249: wide
    //   9253: wide
    //   9257: wide
    //   9261: wide
    //   9265: wide
    //   9269: wide
    //   9273: wide
    //   9277: wide
    //   9281: caload
    //   9282: istore 31
    //   9284: iload 6
    //   9286: iconst_5
    //   9287: irem
    //   9288: tableswitch	default:+32 -> 9320, 0:+2834->12122, 1:+2843->12131, 2:+2852->12140, 3:+2861->12149
    //   9321: irem
    //   9322: wide
    //   9326: wide
    //   9330: iload 31
    //   9332: ixor
    //   9333: i2c
    //   9334: wide
    //   9338: wide
    //   9342: wide
    //   9346: wide
    //   9350: castore
    //   9351: iload 6
    //   9353: iconst_1
    //   9354: iadd
    //   9355: wide
    //   9359: wide
    //   9363: ifne +28 -> 9391
    //   9366: aload 5
    //   9368: wide
    //   9372: wide
    //   9376: wide
    //   9380: wide
    //   9384: wide
    //   9388: goto -115 -> 9273
    //   9391: wide
    //   9395: wide
    //   9399: aload 5
    //   9401: wide
    //   9405: wide
    //   9409: wide
    //   9413: if_icmpgt -176 -> 9237
    //   9416: new 39	java/lang/String
    //   9419: dup
    //   9420: wide
    //   9424: invokespecial 49	java/lang/String:<init>	([C)V
    //   9427: invokevirtual 53	java/lang/String:intern	()Ljava/lang/String;
    //   9430: wide
    //   9434: aload_1
    //   9435: wide
    //   9439: wide
    //   9443: aastore
    //   9444: bipush 46
    //   9446: wide
    //   9450: ldc 145
    //   9452: invokevirtual 45	java/lang/String:toCharArray	()[C
    //   9455: wide
    //   9459: wide
    //   9463: arraylength
    //   9464: wide
    //   9468: wide
    //   9472: iconst_1
    //   9473: if_icmpgt +2897 -> 12370
    //   9476: iconst_0
    //   9477: wide
    //   9481: wide
    //   9485: astore 5
    //   9487: wide
    //   9491: istore 6
    //   9493: wide
    //   9497: wide
    //   9501: wide
    //   9505: wide
    //   9509: wide
    //   9513: wide
    //   9517: wide
    //   9521: wide
    //   9525: caload
    //   9526: istore 31
    //   9528: iload 6
    //   9530: iconst_5
    //   9531: irem
    //   9532: tableswitch	default:+32 -> 9564, 0:+2626->12158, 1:+2635->12167, 2:+2644->12176, 3:+2653->12185
    //   9565: irem
    //   9566: wide
    //   9570: wide
    //   9574: iload 31
    //   9576: ixor
    //   9577: i2c
    //   9578: wide
    //   9582: wide
    //   9586: wide
    //   9590: wide
    //   9594: castore
    //   9595: iload 6
    //   9597: iconst_1
    //   9598: iadd
    //   9599: wide
    //   9603: wide
    //   9607: ifne +28 -> 9635
    //   9610: aload 5
    //   9612: wide
    //   9616: wide
    //   9620: wide
    //   9624: wide
    //   9628: wide
    //   9632: goto -115 -> 9517
    //   9635: wide
    //   9639: wide
    //   9643: aload 5
    //   9645: wide
    //   9649: wide
    //   9653: wide
    //   9657: if_icmpgt -176 -> 9481
    //   9660: new 39	java/lang/String
    //   9663: dup
    //   9664: wide
    //   9668: invokespecial 49	java/lang/String:<init>	([C)V
    //   9671: invokevirtual 53	java/lang/String:intern	()Ljava/lang/String;
    //   9674: wide
    //   9678: aload_1
    //   9679: wide
    //   9683: wide
    //   9687: aastore
    //   9688: bipush 47
    //   9690: wide
    //   9694: ldc 147
    //   9696: invokevirtual 45	java/lang/String:toCharArray	()[C
    //   9699: wide
    //   9703: wide
    //   9707: arraylength
    //   9708: wide
    //   9712: wide
    //   9716: iconst_1
    //   9717: if_icmpgt +2645 -> 12362
    //   9720: iconst_0
    //   9721: wide
    //   9725: wide
    //   9729: astore 5
    //   9731: wide
    //   9735: istore 6
    //   9737: wide
    //   9741: wide
    //   9745: wide
    //   9749: wide
    //   9753: wide
    //   9757: wide
    //   9761: wide
    //   9765: wide
    //   9769: caload
    //   9770: istore 31
    //   9772: iload 6
    //   9774: iconst_5
    //   9775: irem
    //   9776: tableswitch	default:+32 -> 9808, 0:+2418->12194, 1:+2427->12203, 2:+2436->12212, 3:+2445->12221
    //   9809: irem
    //   9810: wide
    //   9814: wide
    //   9818: iload 31
    //   9820: ixor
    //   9821: i2c
    //   9822: wide
    //   9826: wide
    //   9830: wide
    //   9834: wide
    //   9838: castore
    //   9839: iload 6
    //   9841: iconst_1
    //   9842: iadd
    //   9843: wide
    //   9847: wide
    //   9851: ifne +28 -> 9879
    //   9854: aload 5
    //   9856: wide
    //   9860: wide
    //   9864: wide
    //   9868: wide
    //   9872: wide
    //   9876: goto -115 -> 9761
    //   9879: wide
    //   9883: wide
    //   9887: aload 5
    //   9889: wide
    //   9893: wide
    //   9897: wide
    //   9901: if_icmpgt -176 -> 9725
    //   9904: new 39	java/lang/String
    //   9907: dup
    //   9908: wide
    //   9912: invokespecial 49	java/lang/String:<init>	([C)V
    //   9915: invokevirtual 53	java/lang/String:intern	()Ljava/lang/String;
    //   9918: wide
    //   9922: aload_1
    //   9923: wide
    //   9927: wide
    //   9931: aastore
    //   9932: bipush 48
    //   9934: wide
    //   9938: ldc 149
    //   9940: invokevirtual 45	java/lang/String:toCharArray	()[C
    //   9943: wide
    //   9947: wide
    //   9951: arraylength
    //   9952: wide
    //   9956: wide
    //   9960: iconst_1
    //   9961: if_icmpgt +2393 -> 12354
    //   9964: iconst_0
    //   9965: wide
    //   9969: wide
    //   9973: astore 5
    //   9975: wide
    //   9979: istore 6
    //   9981: wide
    //   9985: wide
    //   9989: wide
    //   9993: wide
    //   9997: wide
    //   10001: wide
    //   10005: wide
    //   10009: wide
    //   10013: caload
    //   10014: istore 31
    //   10016: iload 6
    //   10018: iconst_5
    //   10019: irem
    //   10020: tableswitch	default:+32 -> 10052, 0:+2210->12230, 1:+2219->12239, 2:+2228->12248, 3:+2237->12257
    //   10053: irem
    //   10054: wide
    //   10058: wide
    //   10062: iload 31
    //   10064: ixor
    //   10065: i2c
    //   10066: wide
    //   10070: wide
    //   10074: wide
    //   10078: wide
    //   10082: castore
    //   10083: iload 6
    //   10085: iconst_1
    //   10086: iadd
    //   10087: wide
    //   10091: wide
    //   10095: ifne +28 -> 10123
    //   10098: aload 5
    //   10100: wide
    //   10104: wide
    //   10108: wide
    //   10112: wide
    //   10116: wide
    //   10120: goto -115 -> 10005
    //   10123: wide
    //   10127: wide
    //   10131: aload 5
    //   10133: wide
    //   10137: wide
    //   10141: wide
    //   10145: if_icmpgt -176 -> 9969
    //   10148: new 39	java/lang/String
    //   10151: dup
    //   10152: wide
    //   10156: invokespecial 49	java/lang/String:<init>	([C)V
    //   10159: invokevirtual 53	java/lang/String:intern	()Ljava/lang/String;
    //   10162: wide
    //   10166: aload_1
    //   10167: wide
    //   10171: wide
    //   10175: aastore
    //   10176: bipush 49
    //   10178: wide
    //   10182: ldc 151
    //   10184: invokevirtual 45	java/lang/String:toCharArray	()[C
    //   10187: wide
    //   10191: wide
    //   10195: arraylength
    //   10196: wide
    //   10200: wide
    //   10204: iconst_1
    //   10205: if_icmpgt +2141 -> 12346
    //   10208: iconst_0
    //   10209: wide
    //   10213: wide
    //   10217: astore 5
    //   10219: wide
    //   10223: istore 6
    //   10225: wide
    //   10229: wide
    //   10233: wide
    //   10237: wide
    //   10241: wide
    //   10245: wide
    //   10249: wide
    //   10253: wide
    //   10257: caload
    //   10258: istore 31
    //   10260: iload 6
    //   10262: iconst_5
    //   10263: irem
    //   10264: tableswitch	default:+32 -> 10296, 0:+2002->12266, 1:+2011->12275, 2:+2020->12284, 3:+2029->12293
    //   10297: irem
    //   10298: wide
    //   10302: wide
    //   10306: iload 31
    //   10308: ixor
    //   10309: i2c
    //   10310: wide
    //   10314: wide
    //   10318: wide
    //   10322: wide
    //   10326: castore
    //   10327: iload 6
    //   10329: iconst_1
    //   10330: iadd
    //   10331: wide
    //   10335: wide
    //   10339: ifne +28 -> 10367
    //   10342: aload 5
    //   10344: wide
    //   10348: wide
    //   10352: wide
    //   10356: wide
    //   10360: wide
    //   10364: goto -115 -> 10249
    //   10367: wide
    //   10371: wide
    //   10375: aload 5
    //   10377: wide
    //   10381: wide
    //   10385: wide
    //   10389: if_icmpgt -176 -> 10213
    //   10392: new 39	java/lang/String
    //   10395: dup
    //   10396: wide
    //   10400: invokespecial 49	java/lang/String:<init>	([C)V
    //   10403: invokevirtual 53	java/lang/String:intern	()Ljava/lang/String;
    //   10406: wide
    //   10410: aload_1
    //   10411: wide
    //   10415: wide
    //   10419: aastore
    //   10420: bipush 50
    //   10422: wide
    //   10426: ldc 153
    //   10428: invokevirtual 45	java/lang/String:toCharArray	()[C
    //   10431: wide
    //   10435: wide
    //   10439: arraylength
    //   10440: wide
    //   10444: wide
    //   10448: iconst_1
    //   10449: if_icmpgt +1889 -> 12338
    //   10452: iconst_0
    //   10453: wide
    //   10457: wide
    //   10461: astore 5
    //   10463: wide
    //   10467: istore 6
    //   10469: wide
    //   10473: wide
    //   10477: wide
    //   10481: wide
    //   10485: wide
    //   10489: wide
    //   10493: wide
    //   10497: wide
    //   10501: caload
    //   10502: istore 31
    //   10504: iload 6
    //   10506: iconst_5
    //   10507: irem
    //   10508: tableswitch	default:+32 -> 10540, 0:+1794->12302, 1:+1803->12311, 2:+1812->12320, 3:+1821->12329
    //   10541: irem
    //   10542: wide
    //   10546: wide
    //   10550: iload 31
    //   10552: ixor
    //   10553: i2c
    //   10554: wide
    //   10558: wide
    //   10562: wide
    //   10566: wide
    //   10570: castore
    //   10571: iload 6
    //   10573: iconst_1
    //   10574: iadd
    //   10575: wide
    //   10579: wide
    //   10583: ifne +28 -> 10611
    //   10586: aload 5
    //   10588: wide
    //   10592: wide
    //   10596: wide
    //   10600: wide
    //   10604: wide
    //   10608: goto -115 -> 10493
    //   10611: wide
    //   10615: wide
    //   10619: aload 5
    //   10621: wide
    //   10625: wide
    //   10629: wide
    //   10633: if_icmpgt -176 -> 10457
    //   10636: new 39	java/lang/String
    //   10639: dup
    //   10640: wide
    //   10644: invokespecial 49	java/lang/String:<init>	([C)V
    //   10647: invokevirtual 53	java/lang/String:intern	()Ljava/lang/String;
    //   10650: wide
    //   10654: aload_1
    //   10655: wide
    //   10659: wide
    //   10663: aastore
    //   10664: aload_1
    //   10665: putstatic 155	com/skyhookwireless/wps/XPSSwitchingAlgorithm:z	[Ljava/lang/String;
    //   10668: ldc 2
    //   10670: invokevirtual 161	java/lang/Class:desiredAssertionStatus	()Z
    //   10673: ifne +8 -> 10681
    //   10676: iload_0
    //   10677: putstatic 163	com/skyhookwireless/wps/XPSSwitchingAlgorithm:_sdkq	Z
    //   10680: return
    //   10681: iconst_0
    //   10682: istore_0
    //   10683: goto -7 -> 10676
    //   10686: bipush 111
    //   10688: istore 11
    //   10690: goto -10602 -> 88
    //   10693: bipush 115
    //   10695: istore 11
    //   10697: goto -10609 -> 88
    //   10700: bipush 90
    //   10702: istore 11
    //   10704: goto -10616 -> 88
    //   10707: bipush 57
    //   10709: istore 11
    //   10711: goto -10623 -> 88
    //   10714: bipush 111
    //   10716: istore 20
    //   10718: goto -10474 -> 244
    //   10721: bipush 115
    //   10723: istore 20
    //   10725: goto -10481 -> 244
    //   10728: bipush 90
    //   10730: istore 20
    //   10732: goto -10488 -> 244
    //   10735: bipush 57
    //   10737: istore 20
    //   10739: goto -10495 -> 244
    //   10742: bipush 111
    //   10744: istore 32
    //   10746: goto -10338 -> 408
    //   10749: bipush 115
    //   10751: istore 32
    //   10753: goto -10345 -> 408
    //   10756: bipush 90
    //   10758: istore 32
    //   10760: goto -10352 -> 408
    //   10763: bipush 57
    //   10765: istore 32
    //   10767: goto -10359 -> 408
    //   10770: bipush 111
    //   10772: istore 43
    //   10774: goto -10202 -> 572
    //   10777: bipush 115
    //   10779: istore 43
    //   10781: goto -10209 -> 572
    //   10784: bipush 90
    //   10786: istore 43
    //   10788: goto -10216 -> 572
    //   10791: bipush 57
    //   10793: istore 43
    //   10795: goto -10223 -> 572
    //   10798: bipush 111
    //   10800: istore 54
    //   10802: goto -10066 -> 736
    //   10805: bipush 115
    //   10807: istore 54
    //   10809: goto -10073 -> 736
    //   10812: bipush 90
    //   10814: istore 54
    //   10816: goto -10080 -> 736
    //   10819: bipush 57
    //   10821: istore 54
    //   10823: goto -10087 -> 736
    //   10826: bipush 111
    //   10828: istore 65
    //   10830: goto -9930 -> 900
    //   10833: bipush 115
    //   10835: istore 65
    //   10837: goto -9937 -> 900
    //   10840: bipush 90
    //   10842: istore 65
    //   10844: goto -9944 -> 900
    //   10847: bipush 57
    //   10849: istore 65
    //   10851: goto -9951 -> 900
    //   10854: bipush 111
    //   10856: istore 76
    //   10858: goto -9790 -> 1068
    //   10861: bipush 115
    //   10863: istore 76
    //   10865: goto -9797 -> 1068
    //   10868: bipush 90
    //   10870: istore 76
    //   10872: goto -9804 -> 1068
    //   10875: bipush 57
    //   10877: istore 76
    //   10879: goto -9811 -> 1068
    //   10882: bipush 111
    //   10884: istore 87
    //   10886: goto -9650 -> 1236
    //   10889: bipush 115
    //   10891: istore 87
    //   10893: goto -9657 -> 1236
    //   10896: bipush 90
    //   10898: istore 87
    //   10900: goto -9664 -> 1236
    //   10903: bipush 57
    //   10905: istore 87
    //   10907: goto -9671 -> 1236
    //   10910: bipush 111
    //   10912: istore 98
    //   10914: goto -9510 -> 1404
    //   10917: bipush 115
    //   10919: istore 98
    //   10921: goto -9517 -> 1404
    //   10924: bipush 90
    //   10926: istore 98
    //   10928: goto -9524 -> 1404
    //   10931: bipush 57
    //   10933: istore 98
    //   10935: goto -9531 -> 1404
    //   10938: bipush 111
    //   10940: istore 109
    //   10942: goto -9370 -> 1572
    //   10945: bipush 115
    //   10947: istore 109
    //   10949: goto -9377 -> 1572
    //   10952: bipush 90
    //   10954: istore 109
    //   10956: goto -9384 -> 1572
    //   10959: bipush 57
    //   10961: istore 109
    //   10963: goto -9391 -> 1572
    //   10966: bipush 111
    //   10968: istore 120
    //   10970: goto -9230 -> 1740
    //   10973: bipush 115
    //   10975: istore 120
    //   10977: goto -9237 -> 1740
    //   10980: bipush 90
    //   10982: istore 120
    //   10984: goto -9244 -> 1740
    //   10987: bipush 57
    //   10989: istore 120
    //   10991: goto -9251 -> 1740
    //   10994: bipush 111
    //   10996: istore 131
    //   10998: goto -9090 -> 1908
    //   11001: bipush 115
    //   11003: istore 131
    //   11005: goto -9097 -> 1908
    //   11008: bipush 90
    //   11010: istore 131
    //   11012: goto -9104 -> 1908
    //   11015: bipush 57
    //   11017: istore 131
    //   11019: goto -9111 -> 1908
    //   11022: bipush 111
    //   11024: istore 142
    //   11026: goto -8950 -> 2076
    //   11029: bipush 115
    //   11031: istore 142
    //   11033: goto -8957 -> 2076
    //   11036: bipush 90
    //   11038: istore 142
    //   11040: goto -8964 -> 2076
    //   11043: bipush 57
    //   11045: istore 142
    //   11047: goto -8971 -> 2076
    //   11050: bipush 111
    //   11052: istore 153
    //   11054: goto -8810 -> 2244
    //   11057: bipush 115
    //   11059: istore 153
    //   11061: goto -8817 -> 2244
    //   11064: bipush 90
    //   11066: istore 153
    //   11068: goto -8824 -> 2244
    //   11071: bipush 57
    //   11073: istore 153
    //   11075: goto -8831 -> 2244
    //   11078: bipush 111
    //   11080: istore 164
    //   11082: goto -8670 -> 2412
    //   11085: bipush 115
    //   11087: istore 164
    //   11089: goto -8677 -> 2412
    //   11092: bipush 90
    //   11094: istore 164
    //   11096: goto -8684 -> 2412
    //   11099: bipush 57
    //   11101: istore 164
    //   11103: goto -8691 -> 2412
    //   11106: bipush 111
    //   11108: istore 175
    //   11110: goto -8530 -> 2580
    //   11113: bipush 115
    //   11115: istore 175
    //   11117: goto -8537 -> 2580
    //   11120: bipush 90
    //   11122: istore 175
    //   11124: goto -8544 -> 2580
    //   11127: bipush 57
    //   11129: istore 175
    //   11131: goto -8551 -> 2580
    //   11134: bipush 111
    //   11136: istore 186
    //   11138: goto -8390 -> 2748
    //   11141: bipush 115
    //   11143: istore 186
    //   11145: goto -8397 -> 2748
    //   11148: bipush 90
    //   11150: istore 186
    //   11152: goto -8404 -> 2748
    //   11155: bipush 57
    //   11157: istore 186
    //   11159: goto -8411 -> 2748
    //   11162: bipush 111
    //   11164: istore 197
    //   11166: goto -8250 -> 2916
    //   11169: bipush 115
    //   11171: istore 197
    //   11173: goto -8257 -> 2916
    //   11176: bipush 90
    //   11178: istore 197
    //   11180: goto -8264 -> 2916
    //   11183: bipush 57
    //   11185: istore 197
    //   11187: goto -8271 -> 2916
    //   11190: bipush 111
    //   11192: istore 208
    //   11194: goto -8110 -> 3084
    //   11197: bipush 115
    //   11199: istore 208
    //   11201: goto -8117 -> 3084
    //   11204: bipush 90
    //   11206: istore 208
    //   11208: goto -8124 -> 3084
    //   11211: bipush 57
    //   11213: istore 208
    //   11215: goto -8131 -> 3084
    //   11218: bipush 111
    //   11220: istore 219
    //   11222: goto -7970 -> 3252
    //   11225: bipush 115
    //   11227: istore 219
    //   11229: goto -7977 -> 3252
    //   11232: bipush 90
    //   11234: istore 219
    //   11236: goto -7984 -> 3252
    //   11239: bipush 57
    //   11241: istore 219
    //   11243: goto -7991 -> 3252
    //   11246: bipush 111
    //   11248: istore 230
    //   11250: goto -7830 -> 3420
    //   11253: bipush 115
    //   11255: istore 230
    //   11257: goto -7837 -> 3420
    //   11260: bipush 90
    //   11262: istore 230
    //   11264: goto -7844 -> 3420
    //   11267: bipush 57
    //   11269: istore 230
    //   11271: goto -7851 -> 3420
    //   11274: bipush 111
    //   11276: istore 241
    //   11278: goto -7690 -> 3588
    //   11281: bipush 115
    //   11283: istore 241
    //   11285: goto -7697 -> 3588
    //   11288: bipush 90
    //   11290: istore 241
    //   11292: goto -7704 -> 3588
    //   11295: bipush 57
    //   11297: istore 241
    //   11299: goto -7711 -> 3588
    //   11302: bipush 111
    //   11304: istore 252
    //   11306: goto -7550 -> 3756
    //   11309: bipush 115
    //   11311: istore 252
    //   11313: goto -7557 -> 3756
    //   11316: bipush 90
    //   11318: istore 252
    //   11320: goto -7564 -> 3756
    //   11323: bipush 57
    //   11325: istore 252
    //   11327: goto -7571 -> 3756
    //   11330: bipush 111
    //   11332: wide
    //   11336: goto -7378 -> 3958
    //   11339: bipush 115
    //   11341: wide
    //   11345: goto -7387 -> 3958
    //   11348: bipush 90
    //   11350: wide
    //   11354: goto -7396 -> 3958
    //   11357: bipush 57
    //   11359: wide
    //   11363: goto -7405 -> 3958
    //   11366: bipush 111
    //   11368: wide
    //   11372: goto -7170 -> 4202
    //   11375: bipush 115
    //   11377: wide
    //   11381: goto -7179 -> 4202
    //   11384: bipush 90
    //   11386: wide
    //   11390: goto -7188 -> 4202
    //   11393: bipush 57
    //   11395: wide
    //   11399: goto -7197 -> 4202
    //   11402: bipush 111
    //   11404: wide
    //   11408: goto -6962 -> 4446
    //   11411: bipush 115
    //   11413: wide
    //   11417: goto -6971 -> 4446
    //   11420: bipush 90
    //   11422: wide
    //   11426: goto -6980 -> 4446
    //   11429: bipush 57
    //   11431: wide
    //   11435: goto -6989 -> 4446
    //   11438: bipush 111
    //   11440: wide
    //   11444: goto -6754 -> 4690
    //   11447: bipush 115
    //   11449: wide
    //   11453: goto -6763 -> 4690
    //   11456: bipush 90
    //   11458: wide
    //   11462: goto -6772 -> 4690
    //   11465: bipush 57
    //   11467: wide
    //   11471: goto -6781 -> 4690
    //   11474: bipush 111
    //   11476: wide
    //   11480: goto -6546 -> 4934
    //   11483: bipush 115
    //   11485: wide
    //   11489: goto -6555 -> 4934
    //   11492: bipush 90
    //   11494: wide
    //   11498: goto -6564 -> 4934
    //   11501: bipush 57
    //   11503: wide
    //   11507: goto -6573 -> 4934
    //   11510: bipush 111
    //   11512: wide
    //   11516: goto -6338 -> 5178
    //   11519: bipush 115
    //   11521: wide
    //   11525: goto -6347 -> 5178
    //   11528: bipush 90
    //   11530: wide
    //   11534: goto -6356 -> 5178
    //   11537: bipush 57
    //   11539: wide
    //   11543: goto -6365 -> 5178
    //   11546: bipush 111
    //   11548: wide
    //   11552: goto -6130 -> 5422
    //   11555: bipush 115
    //   11557: wide
    //   11561: goto -6139 -> 5422
    //   11564: bipush 90
    //   11566: wide
    //   11570: goto -6148 -> 5422
    //   11573: bipush 57
    //   11575: wide
    //   11579: goto -6157 -> 5422
    //   11582: bipush 111
    //   11584: wide
    //   11588: goto -5922 -> 5666
    //   11591: bipush 115
    //   11593: wide
    //   11597: goto -5931 -> 5666
    //   11600: bipush 90
    //   11602: wide
    //   11606: goto -5940 -> 5666
    //   11609: bipush 57
    //   11611: wide
    //   11615: goto -5949 -> 5666
    //   11618: bipush 111
    //   11620: wide
    //   11624: goto -5714 -> 5910
    //   11627: bipush 115
    //   11629: wide
    //   11633: goto -5723 -> 5910
    //   11636: bipush 90
    //   11638: wide
    //   11642: goto -5732 -> 5910
    //   11645: bipush 57
    //   11647: wide
    //   11651: goto -5741 -> 5910
    //   11654: bipush 111
    //   11656: wide
    //   11660: goto -5506 -> 6154
    //   11663: bipush 115
    //   11665: wide
    //   11669: goto -5515 -> 6154
    //   11672: bipush 90
    //   11674: wide
    //   11678: goto -5524 -> 6154
    //   11681: bipush 57
    //   11683: wide
    //   11687: goto -5533 -> 6154
    //   11690: bipush 111
    //   11692: wide
    //   11696: goto -5298 -> 6398
    //   11699: bipush 115
    //   11701: wide
    //   11705: goto -5307 -> 6398
    //   11708: bipush 90
    //   11710: wide
    //   11714: goto -5316 -> 6398
    //   11717: bipush 57
    //   11719: wide
    //   11723: goto -5325 -> 6398
    //   11726: bipush 111
    //   11728: wide
    //   11732: goto -5090 -> 6642
    //   11735: bipush 115
    //   11737: wide
    //   11741: goto -5099 -> 6642
    //   11744: bipush 90
    //   11746: wide
    //   11750: goto -5108 -> 6642
    //   11753: bipush 57
    //   11755: wide
    //   11759: goto -5117 -> 6642
    //   11762: bipush 111
    //   11764: wide
    //   11768: goto -4882 -> 6886
    //   11771: bipush 115
    //   11773: wide
    //   11777: goto -4891 -> 6886
    //   11780: bipush 90
    //   11782: wide
    //   11786: goto -4900 -> 6886
    //   11789: bipush 57
    //   11791: wide
    //   11795: goto -4909 -> 6886
    //   11798: bipush 111
    //   11800: wide
    //   11804: goto -4674 -> 7130
    //   11807: bipush 115
    //   11809: wide
    //   11813: goto -4683 -> 7130
    //   11816: bipush 90
    //   11818: wide
    //   11822: goto -4692 -> 7130
    //   11825: bipush 57
    //   11827: wide
    //   11831: goto -4701 -> 7130
    //   11834: bipush 111
    //   11836: wide
    //   11840: goto -4466 -> 7374
    //   11843: bipush 115
    //   11845: wide
    //   11849: goto -4475 -> 7374
    //   11852: bipush 90
    //   11854: wide
    //   11858: goto -4484 -> 7374
    //   11861: bipush 57
    //   11863: wide
    //   11867: goto -4493 -> 7374
    //   11870: bipush 111
    //   11872: wide
    //   11876: goto -4258 -> 7618
    //   11879: bipush 115
    //   11881: wide
    //   11885: goto -4267 -> 7618
    //   11888: bipush 90
    //   11890: wide
    //   11894: goto -4276 -> 7618
    //   11897: bipush 57
    //   11899: wide
    //   11903: goto -4285 -> 7618
    //   11906: bipush 111
    //   11908: wide
    //   11912: goto -4050 -> 7862
    //   11915: bipush 115
    //   11917: wide
    //   11921: goto -4059 -> 7862
    //   11924: bipush 90
    //   11926: wide
    //   11930: goto -4068 -> 7862
    //   11933: bipush 57
    //   11935: wide
    //   11939: goto -4077 -> 7862
    //   11942: bipush 111
    //   11944: wide
    //   11948: goto -3842 -> 8106
    //   11951: bipush 115
    //   11953: wide
    //   11957: goto -3851 -> 8106
    //   11960: bipush 90
    //   11962: wide
    //   11966: goto -3860 -> 8106
    //   11969: bipush 57
    //   11971: wide
    //   11975: goto -3869 -> 8106
    //   11978: bipush 111
    //   11980: wide
    //   11984: goto -3634 -> 8350
    //   11987: bipush 115
    //   11989: wide
    //   11993: goto -3643 -> 8350
    //   11996: bipush 90
    //   11998: wide
    //   12002: goto -3652 -> 8350
    //   12005: bipush 57
    //   12007: wide
    //   12011: goto -3661 -> 8350
    //   12014: bipush 111
    //   12016: wide
    //   12020: goto -3426 -> 8594
    //   12023: bipush 115
    //   12025: wide
    //   12029: goto -3435 -> 8594
    //   12032: bipush 90
    //   12034: wide
    //   12038: goto -3444 -> 8594
    //   12041: bipush 57
    //   12043: wide
    //   12047: goto -3453 -> 8594
    //   12050: bipush 111
    //   12052: wide
    //   12056: goto -3218 -> 8838
    //   12059: bipush 115
    //   12061: wide
    //   12065: goto -3227 -> 8838
    //   12068: bipush 90
    //   12070: wide
    //   12074: goto -3236 -> 8838
    //   12077: bipush 57
    //   12079: wide
    //   12083: goto -3245 -> 8838
    //   12086: bipush 111
    //   12088: wide
    //   12092: goto -3010 -> 9082
    //   12095: bipush 115
    //   12097: wide
    //   12101: goto -3019 -> 9082
    //   12104: bipush 90
    //   12106: wide
    //   12110: goto -3028 -> 9082
    //   12113: bipush 57
    //   12115: wide
    //   12119: goto -3037 -> 9082
    //   12122: bipush 111
    //   12124: wide
    //   12128: goto -2802 -> 9326
    //   12131: bipush 115
    //   12133: wide
    //   12137: goto -2811 -> 9326
    //   12140: bipush 90
    //   12142: wide
    //   12146: goto -2820 -> 9326
    //   12149: bipush 57
    //   12151: wide
    //   12155: goto -2829 -> 9326
    //   12158: bipush 111
    //   12160: wide
    //   12164: goto -2594 -> 9570
    //   12167: bipush 115
    //   12169: wide
    //   12173: goto -2603 -> 9570
    //   12176: bipush 90
    //   12178: wide
    //   12182: goto -2612 -> 9570
    //   12185: bipush 57
    //   12187: wide
    //   12191: goto -2621 -> 9570
    //   12194: bipush 111
    //   12196: wide
    //   12200: goto -2386 -> 9814
    //   12203: bipush 115
    //   12205: wide
    //   12209: goto -2395 -> 9814
    //   12212: bipush 90
    //   12214: wide
    //   12218: goto -2404 -> 9814
    //   12221: bipush 57
    //   12223: wide
    //   12227: goto -2413 -> 9814
    //   12230: bipush 111
    //   12232: wide
    //   12236: goto -2178 -> 10058
    //   12239: bipush 115
    //   12241: wide
    //   12245: goto -2187 -> 10058
    //   12248: bipush 90
    //   12250: wide
    //   12254: goto -2196 -> 10058
    //   12257: bipush 57
    //   12259: wide
    //   12263: goto -2205 -> 10058
    //   12266: bipush 111
    //   12268: wide
    //   12272: goto -1970 -> 10302
    //   12275: bipush 115
    //   12277: wide
    //   12281: goto -1979 -> 10302
    //   12284: bipush 90
    //   12286: wide
    //   12290: goto -1988 -> 10302
    //   12293: bipush 57
    //   12295: wide
    //   12299: goto -1997 -> 10302
    //   12302: bipush 111
    //   12304: wide
    //   12308: goto -1762 -> 10546
    //   12311: bipush 115
    //   12313: wide
    //   12317: goto -1771 -> 10546
    //   12320: bipush 90
    //   12322: wide
    //   12326: goto -1780 -> 10546
    //   12329: bipush 57
    //   12331: wide
    //   12335: goto -1789 -> 10546
    //   12338: iconst_0
    //   12339: wide
    //   12343: goto -1718 -> 10625
    //   12346: iconst_0
    //   12347: wide
    //   12351: goto -1970 -> 10381
    //   12354: iconst_0
    //   12355: wide
    //   12359: goto -2222 -> 10137
    //   12362: iconst_0
    //   12363: wide
    //   12367: goto -2474 -> 9893
    //   12370: iconst_0
    //   12371: wide
    //   12375: goto -2726 -> 9649
    //   12378: iconst_0
    //   12379: wide
    //   12383: goto -2978 -> 9405
    //   12386: iconst_0
    //   12387: wide
    //   12391: goto -3230 -> 9161
    //   12394: iconst_0
    //   12395: wide
    //   12399: goto -3482 -> 8917
    //   12402: iconst_0
    //   12403: wide
    //   12407: goto -3734 -> 8673
    //   12410: iconst_0
    //   12411: wide
    //   12415: goto -3986 -> 8429
    //   12418: iconst_0
    //   12419: wide
    //   12423: goto -4238 -> 8185
    //   12426: iconst_0
    //   12427: wide
    //   12431: goto -4490 -> 7941
    //   12434: iconst_0
    //   12435: wide
    //   12439: goto -4742 -> 7697
    //   12442: iconst_0
    //   12443: wide
    //   12447: goto -4994 -> 7453
    //   12450: iconst_0
    //   12451: wide
    //   12455: goto -5246 -> 7209
    //   12458: iconst_0
    //   12459: wide
    //   12463: goto -5498 -> 6965
    //   12466: iconst_0
    //   12467: wide
    //   12471: goto -5750 -> 6721
    //   12474: iconst_0
    //   12475: wide
    //   12479: goto -6002 -> 6477
    //   12482: iconst_0
    //   12483: wide
    //   12487: goto -6254 -> 6233
    //   12490: iconst_0
    //   12491: wide
    //   12495: goto -6506 -> 5989
    //   12498: iconst_0
    //   12499: wide
    //   12503: goto -6758 -> 5745
    //   12506: iconst_0
    //   12507: wide
    //   12511: goto -7010 -> 5501
    //   12514: iconst_0
    //   12515: wide
    //   12519: goto -7262 -> 5257
    //   12522: iconst_0
    //   12523: wide
    //   12527: goto -7514 -> 5013
    //   12530: iconst_0
    //   12531: wide
    //   12535: goto -7766 -> 4769
    //   12538: iconst_0
    //   12539: wide
    //   12543: goto -8018 -> 4525
    //   12546: iconst_0
    //   12547: wide
    //   12551: goto -8270 -> 4281
    //   12554: iconst_0
    //   12555: wide
    //   12559: goto -8522 -> 4037
    //   12562: iconst_0
    //   12563: istore 248
    //   12565: goto -8760 -> 3805
    //   12568: iconst_0
    //   12569: istore 237
    //   12571: goto -8934 -> 3637
    //   12574: iconst_0
    //   12575: istore 226
    //   12577: goto -9108 -> 3469
    //   12580: iconst_0
    //   12581: istore 215
    //   12583: goto -9282 -> 3301
    //   12586: iconst_0
    //   12587: istore 204
    //   12589: goto -9456 -> 3133
    //   12592: iconst_0
    //   12593: istore 193
    //   12595: goto -9630 -> 2965
    //   12598: iconst_0
    //   12599: istore 182
    //   12601: goto -9804 -> 2797
    //   12604: iconst_0
    //   12605: istore 171
    //   12607: goto -9978 -> 2629
    //   12610: iconst_0
    //   12611: istore 160
    //   12613: goto -10152 -> 2461
    //   12616: iconst_0
    //   12617: istore 149
    //   12619: goto -10326 -> 2293
    //   12622: iconst_0
    //   12623: istore 138
    //   12625: goto -10500 -> 2125
    //   12628: iconst_0
    //   12629: istore 127
    //   12631: goto -10674 -> 1957
    //   12634: iconst_0
    //   12635: istore 116
    //   12637: goto -10848 -> 1789
    //   12640: iconst_0
    //   12641: istore 105
    //   12643: goto -11022 -> 1621
    //   12646: iconst_0
    //   12647: istore 94
    //   12649: goto -11196 -> 1453
    //   12652: iconst_0
    //   12653: istore 83
    //   12655: goto -11370 -> 1285
    //   12658: iconst_0
    //   12659: istore 72
    //   12661: goto -11544 -> 1117
    //   12664: iconst_0
    //   12665: istore 61
    //   12667: goto -11718 -> 949
    //   12670: iconst_0
    //   12671: istore 50
    //   12673: goto -11888 -> 785
    //   12676: iconst_0
    //   12677: istore 39
    //   12679: goto -12058 -> 621
    //   12682: iconst_0
    //   12683: istore 27
    //   12685: goto -12228 -> 457
    //   12688: iconst_0
    //   12689: istore 16
    //   12691: goto -12398 -> 293
    //   12694: iconst_0
    //   12695: istore 4
    //   12697: goto -12562 -> 135
  }

  public XPSSwitchingAlgorithm()
  {
    com.skyhookwireless._sdkhb local_sdkhb = com.skyhookwireless._sdkhb._sdkb(XPSSwitchingAlgorithm.class);
    this._sdka = local_sdkhb;
    _sdkpb local_sdkpb1 = new _sdkpb(40000L);
    this._sdkb = local_sdkpb1;
    _sdks local_sdks = new _sdks(10000L);
    this._sdkc = local_sdks;
    ScanObservation localScanObservation1 = new ScanObservation();
    this._sdkd = localScanObservation1;
    ScanObservation localScanObservation2 = this._sdkd;
    _sdkpb local_sdkpb2 = this._sdkb;
    _sdktc local_sdktc = new _sdktc(localScanObservation2, local_sdkpb2);
    this._sdke = local_sdktc;
    _sdkub local_sdkub = new _sdkub();
    this._sdkf = local_sdkub;
    ScanObservation localScanObservation3 = this._sdkd;
    _sdkpb local_sdkpb3 = this._sdkb;
    _sdkdc local_sdkdc = new _sdkdc(localScanObservation3, local_sdkpb3);
    this._sdkg = local_sdkdc;
    _sdkec local_sdkec = new _sdkec();
    this._sdkh = local_sdkec;
    this._sdkn = false;
    this._sdko = false;
    this._sdkp = false;
    this._sdkj = null;
    this._sdkk = null;
    this._sdkm = false;
    this._sdkl = false;
  }

  private _sdktd<_sdkd, String> _sdka(int paramInt, _sdkib param_sdkib1, _sdkib param_sdkib2, com.skyhookwireless._sdkec param_sdkec)
  {
    _sdkib local_sdkib = this._sdkb._sdkb();
    _sdkd local_sdkd1;
    _sdktd local_sdktd;
    if (param_sdkib2 != null)
    {
      if (local_sdkib != null)
      {
        com.skyhookwireless._sdkec local_sdkec1 = param_sdkib2.getAge();
        com.skyhookwireless._sdkec local_sdkec2 = local_sdkib.getAge();
        if (local_sdkec1._sdkc(local_sdkec2) <= 0);
      }
    }
    else if (param_sdkib1 != null)
    {
      local_sdkd1 = _sdkd.USE_WPS;
      String str1 = z[21];
      local_sdktd = _sdktd._sdka(local_sdkd1, str1);
    }
    while (true)
    {
      return local_sdktd;
      local_sdkd1 = _sdkd.USE_NONE;
      break;
      if (param_sdkib2.getSatellites() > 5)
      {
        _sdkd local_sdkd2 = _sdkd.USE_GPS_RAW;
        String str2 = z[11];
        local_sdktd = _sdktd._sdka(local_sdkd2, str2);
      }
      else if (_sdka())
      {
        _sdkd local_sdkd3 = _sdkd.USE_GPS_SMOOTHED;
        String str3 = z[14];
        local_sdktd = _sdktd._sdka(local_sdkd3, str3);
      }
      else if (param_sdkib1 == null)
      {
        _sdkd local_sdkd4 = _sdkd.USE_GPS_SMOOTHED;
        String str4 = z[16];
        local_sdktd = _sdktd._sdka(local_sdkd4, str4);
      }
      else if (param_sdkib1.getNAP() == 0)
      {
        com.skyhookwireless._sdkhb local_sdkhb = this._sdka;
        String str5 = z[8];
        local_sdkhb._sdkb(str5);
        if (this._sdkn)
        {
          _sdkd local_sdkd5 = _sdkd.USE_GPS_SMOOTHED;
          String str6 = z[19];
          local_sdktd = _sdktd._sdka(local_sdkd5, str6);
        }
        else if (param_sdkib1.getAge()._sdka(param_sdkec) > 5000L)
        {
          _sdkd local_sdkd6 = _sdkd.USE_GPS_SMOOTHED;
          String str7 = z[20];
          local_sdktd = _sdktd._sdka(local_sdkd6, str7);
        }
        else if (((param_sdkib2.hasSpeed()) && (!param_sdkib2._sdkf())) || (!this._sdkd._sdka()) || (!this._sdkd._sdkd()))
        {
          _sdkd local_sdkd7 = _sdkd.USE_GPS_SMOOTHED;
          String str8 = z[6];
          local_sdktd = _sdktd._sdka(local_sdkd7, str8);
        }
      }
      else if (_sdksd._sdka(param_sdkib1, param_sdkib2) >= 500.0D)
      {
        _sdkd local_sdkd8 = _sdkd.USE_GPS_SMOOTHED;
        String str9 = z[15];
        local_sdktd = _sdktd._sdka(local_sdkd8, str9);
      }
      else if (param_sdkib1.getHPE() > 250)
      {
        _sdkd local_sdkd9 = _sdkd.USE_GPS_SMOOTHED;
        String str10 = z[12];
        local_sdktd = _sdktd._sdka(local_sdkd9, str10);
      }
      else if (_sdka(param_sdkib1, paramInt))
      {
        _sdkd local_sdkd10 = _sdkd.USE_WPS;
        String str11 = z[13];
        local_sdktd = _sdktd._sdka(local_sdkd10, str11);
      }
      else if (param_sdkib2.getSatellites() <= 3)
      {
        _sdkd local_sdkd11 = _sdkd.USE_WPS;
        String str12 = z[18];
        local_sdktd = _sdktd._sdka(local_sdkd11, str12);
      }
      else if (param_sdkib2.getHPE() / 10.0F < 2.0F)
      {
        _sdkd local_sdkd12 = _sdkd.USE_GPS_SMOOTHED;
        String str13 = z[9];
        local_sdktd = _sdktd._sdka(local_sdkd12, str13);
      }
      else if ((paramInt > 8) && (param_sdkib1.getHPE() < 150))
      {
        _sdkd local_sdkd13 = _sdkd.USE_WPS;
        String str14 = z[5];
        local_sdktd = _sdktd._sdka(local_sdkd13, str14);
      }
      else if (param_sdkib2.getSatellites() == 5)
      {
        _sdkd local_sdkd14 = _sdkd.USE_GPS_SMOOTHED;
        String str15 = z[10];
        local_sdktd = _sdktd._sdka(local_sdkd14, str15);
      }
      else if ((param_sdkib2.hasSpeed()) && (param_sdkib2._sdkf()))
      {
        _sdkd local_sdkd15 = _sdkd.USE_WPS;
        String str16 = z[7];
        local_sdktd = _sdktd._sdka(local_sdkd15, str16);
      }
      else
      {
        _sdkd local_sdkd16 = _sdkd.USE_XPS;
        String str17 = z[17];
        local_sdktd = _sdktd._sdka(local_sdkd16, str17);
      }
    }
  }

  private _sdktd<WPSReturnCode, _sdkib> _sdka(_sdktd<_sdkd, String> param_sdktd, int paramInt, _sdktd<WPSReturnCode, _sdkib> param_sdktd1, _sdkib param_sdkib, com.skyhookwireless._sdkec param_sdkec)
  {
    int[] arrayOfInt = _sdkwc._sdka;
    int i = ((_sdkd)param_sdktd.first).ordinal();
    switch (arrayOfInt[i])
    {
    default:
      if (!_sdkq)
        throw new AssertionError();
      break;
    case 1:
      StringBuilder localStringBuilder1 = new StringBuilder();
      String str1 = z[34];
      StringBuilder localStringBuilder2 = localStringBuilder1.append(str1);
      String str2 = (String)param_sdktd.second;
      String str3 = str2;
      param_sdktd1 = _sdka(param_sdkib, param_sdkec, str3);
    case 5:
    case 2:
    case 3:
    case 4:
    }
    while (true)
    {
      return param_sdktd1;
      StringBuilder localStringBuilder3 = new StringBuilder();
      String str4 = z[32];
      StringBuilder localStringBuilder4 = localStringBuilder3.append(str4);
      String str5 = (String)param_sdktd.second;
      String str6 = str5;
      param_sdktd1 = _sdkb(param_sdkib, param_sdkec, str6);
      continue;
      StringBuilder localStringBuilder5 = new StringBuilder();
      String str7 = z[31];
      StringBuilder localStringBuilder6 = localStringBuilder5.append(str7);
      String str8 = (String)param_sdktd.second;
      String str9 = str8;
      XPSSwitchingAlgorithm localXPSSwitchingAlgorithm = this;
      _sdktd<WPSReturnCode, _sdkib> local_sdktd = param_sdktd1;
      _sdkib local_sdkib1 = param_sdkib;
      int j = paramInt;
      com.skyhookwireless._sdkec local_sdkec = param_sdkec;
      param_sdktd1 = localXPSSwitchingAlgorithm._sdka(local_sdktd, local_sdkib1, j, local_sdkec, str9);
      continue;
      _sdkib local_sdkib2 = (_sdkib)param_sdktd1.second;
      StringBuilder localStringBuilder7 = new StringBuilder();
      String str10 = z[33];
      StringBuilder localStringBuilder8 = localStringBuilder7.append(str10);
      String str11 = (String)param_sdktd.second;
      String str12 = str11;
      param_sdktd1 = _sdka(param_sdkib, local_sdkib2, param_sdkec, str12);
      continue;
      param_sdktd1 = _sdktd._sdka(WPSReturnCode.WPS_ERROR, null);
    }
  }

  private _sdktd<WPSReturnCode, _sdkib> _sdka(_sdktd<WPSReturnCode, _sdkib> param_sdktd, _sdkib param_sdkib, int paramInt, com.skyhookwireless._sdkec param_sdkec, String paramString)
  {
    com.skyhookwireless._sdkhb local_sdkhb1 = null;
    int i = Location._sdki;
    if (this._sdka._sdkb())
      _sdka(2, paramString);
    _sdkib local_sdkib1 = (_sdkib)param_sdktd.second;
    if (local_sdkib1 == null)
    {
      com.skyhookwireless._sdkhb local_sdkhb2 = this._sdka;
      String str1 = z[28];
      local_sdkhb2._sdkb(str1);
      if (_sdka(local_sdkib1, param_sdkec))
        param_sdktd = _sdktd._sdka(WPSReturnCode.WPS_ERROR_LOCATION_CANNOT_BE_DETERMINED, null);
    }
    while (true)
    {
      return param_sdktd;
      int j;
      label92: StringBuilder localStringBuilder2;
      String str4;
      if (local_sdkib1.getNAP() > 0)
      {
        j = 1;
        if (j != 0)
        {
          this._sdkn = false;
          this._sdko = false;
          com.skyhookwireless._sdkhb local_sdkhb3 = this._sdka;
          String str2 = z[26];
          local_sdkhb3._sdkb(str2);
          if (i == 0);
        }
        else if (this._sdka._sdkb())
        {
          local_sdkhb1 = this._sdka;
          StringBuilder localStringBuilder1 = new StringBuilder();
          String str3 = z[25];
          localStringBuilder2 = localStringBuilder1.append(str3);
          if (!this._sdkn)
            break label237;
          str4 = z[24];
        }
      }
      while (true)
      {
        String str5 = str4;
        local_sdkhb1._sdkb(str5);
        if (!_sdka(local_sdkib1, param_sdkec))
          break label266;
        param_sdktd = _sdktd._sdka(WPSReturnCode.WPS_ERROR_LOCATION_CANNOT_BE_DETERMINED, null);
        break;
        j = 0;
        break label92;
        label237: if (this._sdko)
          str4 = z[27];
        else
          str4 = z[30];
      }
      label266: _sdka(param_sdkec);
      if ((_sdka(local_sdkib1, paramInt)) && (this._sdkb._sdka(param_sdkec, 10000L) != null))
      {
        _sdkib local_sdkib2 = this._sdkb._sdkc();
        if (_sdksd._sdka(local_sdkib1, local_sdkib2) >= 150.0D)
        {
          com.skyhookwireless._sdkhb local_sdkhb4 = this._sdka;
          String str6 = z[29];
          local_sdkhb4._sdkb(str6);
          this._sdkb._sdka();
        }
      }
      _sdkib local_sdkib3 = local_sdkib1.clone();
      _sdkb(local_sdkib1, local_sdkib3, param_sdkec);
      if (param_sdkib != null)
      {
        if (j != 0)
        {
          int k = param_sdkib.getSatellites();
          local_sdkib3.setSatellites(k);
        }
        if (param_sdkib.hasAltitude())
        {
          double d1 = param_sdkib.getAltitude();
          local_sdkib3.setAltitude(d1);
        }
      }
      if ((param_sdkib != null) && (param_sdkib.hasBearing()))
      {
        double d2 = param_sdkib.getBearing();
        local_sdkib3.setBearing(d2);
        if (i == 0);
      }
      else if (local_sdkib1.hasBearing())
      {
        this._sdkg._sdkb(local_sdkib1, local_sdkib3, param_sdkec);
      }
      if ((param_sdkib != null) && (param_sdkib.hasSpeed()))
      {
        double d3 = param_sdkib.getSpeed();
        local_sdkib3.setSpeed(d3);
        if (i == 0);
      }
      else
      {
        this._sdkg._sdka(local_sdkib1, local_sdkib3);
      }
      param_sdktd = _sdka(local_sdkib1, local_sdkib3, param_sdkec);
    }
  }

  private _sdktd<WPSReturnCode, _sdkib> _sdka(_sdkib param_sdkib, com.skyhookwireless._sdkec param_sdkec, String paramString)
  {
    if (this._sdka._sdkb())
      _sdka(1, paramString);
    this._sdkn = true;
    this._sdko = false;
    if (_sdka(param_sdkib, param_sdkec));
    _sdkib local_sdkib;
    for (_sdktd local_sdktd = _sdktd._sdka(WPSReturnCode.WPS_ERROR_LOCATION_CANNOT_BE_DETERMINED, null); ; local_sdktd = _sdka(local_sdkib, local_sdkib, param_sdkec))
    {
      return local_sdktd;
      if (this._sdkp)
      {
        this._sdkp = false;
        com.skyhookwireless._sdkhb local_sdkhb = this._sdka;
        String str = z[3];
        local_sdkhb._sdkb(str);
        this._sdkb._sdka();
      }
      local_sdkib = _sdkb(param_sdkib);
    }
  }

  private _sdktd<WPSReturnCode, _sdkib> _sdka(_sdkib param_sdkib1, _sdkib param_sdkib2, com.skyhookwireless._sdkec param_sdkec)
  {
    this._sdkb._sdka(param_sdkib1, param_sdkib2, param_sdkec);
    WPSReturnCode localWPSReturnCode = WPSReturnCode.WPS_OK;
    _sdkib local_sdkib = this._sdkb._sdkc().clone();
    return _sdktd._sdka(localWPSReturnCode, local_sdkib);
  }

  private _sdktd<WPSReturnCode, _sdkib> _sdka(_sdkib param_sdkib1, _sdkib param_sdkib2, com.skyhookwireless._sdkec param_sdkec, String paramString)
  {
    if (this._sdka._sdkb())
      _sdka(3, paramString);
    this._sdkn = false;
    this._sdko = true;
    _sdkib local_sdkib1 = param_sdkib1.clone();
    int i = param_sdkib2.getNAP();
    local_sdkib1.setNAP(i);
    double d1 = param_sdkib1.getLatitude();
    double d2 = param_sdkib2.getLatitude();
    double d3 = (d1 + d2) / 2.0D;
    local_sdkib1.setLatitude(d3);
    double d4 = param_sdkib1.getLongitude();
    double d5 = param_sdkib2.getLongitude();
    double d6 = (d4 + d5) / 2.0D;
    local_sdkib1.setLongitude(d6);
    Integer localInteger1 = Integer.valueOf(param_sdkib1.getHPE());
    Integer localInteger2 = Integer.valueOf(param_sdkib2.getHPE());
    int j = ((Integer)_sdkhd._sdka(localInteger1, localInteger2)).intValue();
    local_sdkib1.setHPE(j);
    com.skyhookwireless._sdkec local_sdkec1 = param_sdkib1.getAge();
    com.skyhookwireless._sdkec local_sdkec2 = param_sdkib2.getAge();
    com.skyhookwireless._sdkec local_sdkec3 = (com.skyhookwireless._sdkec)_sdkhd._sdkb(local_sdkec1, local_sdkec2);
    local_sdkib1.setAge(local_sdkec3);
    local_sdkib1.setTime(0L);
    if (_sdka(local_sdkib1, param_sdkec));
    _sdkib local_sdkib2;
    for (_sdktd local_sdktd = _sdktd._sdka(WPSReturnCode.WPS_ERROR_LOCATION_CANNOT_BE_DETERMINED, null); ; local_sdktd = _sdka(local_sdkib1, local_sdkib2, param_sdkec))
    {
      return local_sdktd;
      _sdka(param_sdkec);
      local_sdkib2 = local_sdkib1.clone();
      _sdkb(local_sdkib1, local_sdkib2, param_sdkec);
    }
  }

  private void _sdka(int paramInt, String paramString)
  {
    StringBuilder localStringBuilder = new StringBuilder();
    String str1 = z[22];
    String str2 = str1 + paramInt;
    this._sdka._sdkb(str2);
  }

  private void _sdka(com.skyhookwireless._sdkec param_sdkec)
  {
    if (!_sdkb(this._sdkk, param_sdkec))
      return;
    if (this._sdkb._sdka(param_sdkec, 20000L) != null)
      return;
    com.skyhookwireless._sdkhb local_sdkhb = this._sdka;
    String str = z[35];
    local_sdkhb._sdkb(str);
    _sdkpb local_sdkpb = this._sdkb;
    _sdkib local_sdkib1 = this._sdkk;
    _sdkib local_sdkib2 = this._sdkk;
    local_sdkpb._sdka(local_sdkib1, local_sdkib2, param_sdkec);
  }

  private void _sdka(_sdkib param_sdkib)
  {
    if (param_sdkib == null)
      return;
    _sdkbb local_sdkbb = this._sdkc._sdkc();
    if (param_sdkib.equals(local_sdkbb))
      return;
    _sdks local_sdks = this._sdkc;
    _sdkib local_sdkib = param_sdkib.clone();
    local_sdks._sdka(local_sdkib);
  }

  private boolean _sdka()
  {
    int i = Location._sdki;
    Iterator localIterator = this._sdkc.iterator();
    if (localIterator.hasNext())
      if (((_sdkib)localIterator.next()).getSatellites() <= 5);
    for (boolean bool = true; ; bool = false)
    {
      return bool;
      if (i == 0)
        break;
    }
  }

  private boolean _sdka(long paramLong, com.skyhookwireless._sdkec param_sdkec)
  {
    int i = Location._sdki;
    Iterator localIterator = this._sdkb._sdkb(param_sdkec, paramLong).iterator();
    if (localIterator.hasNext())
      if (((_sdkib)localIterator.next()).getNAP() <= 0);
    for (boolean bool = true; ; bool = false)
    {
      return bool;
      if (i == 0)
        break;
    }
  }

  private static boolean _sdka(_sdkib param_sdkib, int paramInt)
  {
    if ((param_sdkib.getHPE() < 75) && (paramInt > 12));
    for (boolean bool = true; ; bool = false)
      return bool;
  }

  private boolean _sdka(_sdkib param_sdkib, com.skyhookwireless._sdkec param_sdkec)
  {
    if ((_sdkb()) && (param_sdkib != null) && ((param_sdkib._sdkd()) || (this._sdkj._sdka(param_sdkec) >= 10000L) || ((this._sdkl) && (this._sdkm))))
      _sdkc();
    boolean bool = _sdkb();
    if (bool)
    {
      com.skyhookwireless._sdkhb local_sdkhb = this._sdka;
      String str = z[23];
      local_sdkhb._sdkb(str);
    }
    return bool;
  }

  private _sdktd<WPSReturnCode, _sdkib> _sdkb(_sdkib param_sdkib, com.skyhookwireless._sdkec param_sdkec, String paramString)
  {
    if (this._sdka._sdkb())
      _sdka(4, paramString);
    this._sdkn = true;
    this._sdko = false;
    if (_sdka(param_sdkib, param_sdkec));
    _sdkib local_sdkib2;
    _sdkib local_sdkib3;
    for (_sdktd local_sdktd = _sdktd._sdka(WPSReturnCode.WPS_ERROR_LOCATION_CANNOT_BE_DETERMINED, null); ; local_sdktd = _sdka(local_sdkib2, local_sdkib3, param_sdkec))
    {
      return local_sdktd;
      _sdka(param_sdkec);
      if ((this._sdkb._sdka(param_sdkec, 10000L) != null) && (!this._sdkb._sdkc()._sdke()))
      {
        _sdkib local_sdkib1 = this._sdkb._sdkc();
        if (_sdksd._sdka(param_sdkib, local_sdkib1) >= 500.0D)
        {
          com.skyhookwireless._sdkhb local_sdkhb1 = this._sdka;
          String str1 = z[1];
          local_sdkhb1._sdkb(str1);
          this._sdkb._sdka();
        }
      }
      local_sdkib2 = _sdkb(param_sdkib);
      local_sdkib3 = local_sdkib2.clone();
      if (_sdka(10000L, param_sdkec))
      {
        com.skyhookwireless._sdkhb local_sdkhb2 = this._sdka;
        String str2 = z[0];
        local_sdkhb2._sdkb(str2);
        _sdkb(local_sdkib2, local_sdkib3, param_sdkec);
        if (Location._sdki == 0);
      }
      else if (this._sdkp)
      {
        com.skyhookwireless._sdkhb local_sdkhb3 = this._sdka;
        String str3 = z[2];
        local_sdkhb3._sdkb(str3);
        this._sdkp = false;
      }
    }
  }

  private _sdkib _sdkb(_sdkib param_sdkib)
  {
    if (this._sdkf._sdka() == 0L);
    while (true)
    {
      return param_sdkib;
      com.skyhookwireless._sdkhb local_sdkhb = this._sdka;
      String str = z[50];
      local_sdkhb._sdkb(str);
      _sdkib local_sdkib = param_sdkib.clone();
      int i = Math.max(param_sdkib.getHPE(), 85);
      local_sdkib.setHPE(i);
      param_sdkib = local_sdkib;
    }
  }

  private void _sdkb(com.skyhookwireless._sdkec param_sdkec)
  {
    if ((!_sdkq) && (_sdkb()))
      throw new AssertionError();
    com.skyhookwireless._sdkhb local_sdkhb = this._sdka;
    String str = z[49];
    local_sdkhb._sdkb(str);
    this._sdkj = param_sdkec;
  }

  private void _sdkb(_sdkib param_sdkib1, _sdkib param_sdkib2, com.skyhookwireless._sdkec param_sdkec)
  {
    this._sdkg._sdka(param_sdkib1, param_sdkib2, param_sdkec);
    this._sdkp = true;
  }

  private boolean _sdkb()
  {
    if (this._sdkj != null);
    for (boolean bool = true; ; bool = false)
      return bool;
  }

  private static boolean _sdkb(_sdkib param_sdkib, com.skyhookwireless._sdkec param_sdkec)
  {
    if ((param_sdkib != null) && (param_sdkib._sdkd()) && (param_sdkib.getAge()._sdka(param_sdkec) <= 10000L));
    for (boolean bool = true; ; bool = false)
      return bool;
  }

  private void _sdkc()
  {
    if ((!_sdkq) && (!_sdkb()))
      throw new AssertionError();
    com.skyhookwireless._sdkhb local_sdkhb = this._sdka;
    String str = z[4];
    local_sdkhb._sdkb(str);
    this._sdkj = null;
  }

  public _sdktd<WPSReturnCode, _sdkib> calculateLocation(ArrayList<_sdkjc> paramArrayList, ArrayList<_sdkhb> paramArrayList1, _sdkib param_sdkib, boolean paramBoolean1, boolean paramBoolean2, long paramLong, List<_sdkwb> paramList, com.skyhookwireless._sdkec param_sdkec)
  {
    int i = Location._sdki;
    _sdkpb local_sdkpb1 = this._sdkb;
    com.skyhookwireless._sdkec local_sdkec1 = param_sdkec;
    local_sdkpb1._sdka(local_sdkec1);
    if (param_sdkib != null)
      if (this._sdki != null)
      {
        com.skyhookwireless._sdkec local_sdkec2 = this._sdki;
        com.skyhookwireless._sdkec local_sdkec3 = param_sdkib.getAge();
        if (local_sdkec2.equals(local_sdkec3));
      }
      else
      {
        com.skyhookwireless._sdkec local_sdkec4 = param_sdkib.getAge();
        this._sdki = local_sdkec4;
        XPSSwitchingAlgorithm localXPSSwitchingAlgorithm1 = this;
        _sdkib local_sdkib1 = param_sdkib;
        localXPSSwitchingAlgorithm1._sdka(local_sdkib1);
        if (i == 0)
          break label120;
        if (!com.skyhookwireless._sdkhb._sdkd)
          break label263;
      }
    label263: for (boolean bool1 = false; ; bool1 = true)
    {
      com.skyhookwireless._sdkhb._sdkd = bool1;
      com.skyhookwireless._sdkhb local_sdkhb1 = this._sdka;
      String str1 = z[43];
      local_sdkhb1._sdkb(str1);
      label120: com.skyhookwireless._sdkec local_sdkec5 = param_sdkib.getAge();
      com.skyhookwireless._sdkec local_sdkec6 = param_sdkec;
      if (local_sdkec5._sdka(local_sdkec6) > 2000L)
      {
        com.skyhookwireless._sdkhb local_sdkhb2 = this._sdka;
        String str2 = z[41];
        local_sdkhb2._sdkb(str2);
        param_sdkib = null;
      }
      _sdks local_sdks1 = this._sdkc;
      com.skyhookwireless._sdkec local_sdkec7 = param_sdkec;
      int j = local_sdks1._sdka(local_sdkec7);
      if (!_sdkb())
      {
        _sdkpb local_sdkpb2 = this._sdkb;
        com.skyhookwireless._sdkec local_sdkec8 = param_sdkec;
        if (local_sdkpb2._sdka(local_sdkec8, 20000L) == null)
        {
          XPSSwitchingAlgorithm localXPSSwitchingAlgorithm2 = this;
          com.skyhookwireless._sdkec local_sdkec9 = param_sdkec;
          localXPSSwitchingAlgorithm2._sdkb(local_sdkec9);
        }
      }
      if (_sdkq)
        break;
      int k = paramArrayList1.size();
      int m = paramArrayList.size();
      if (k <= m)
        break;
      throw new AssertionError();
    }
    ArrayList<_sdkjc> localArrayList = paramArrayList;
    Object localObject1 = new ArrayList(localArrayList);
    ArrayList<_sdkhb> localArrayList1 = paramArrayList1;
    ArrayList localArrayList2 = new ArrayList(localArrayList1);
    Collections.sort((List)localObject1);
    Collections.sort(localArrayList2);
    ArrayList localArrayList3 = new ArrayList();
    ScanObservation localScanObservation = this._sdkd;
    List<_sdkwb> localList = paramList;
    com.skyhookwireless._sdkec local_sdkec10 = param_sdkec;
    int n = localScanObservation._sdka((List)localObject1, localList, local_sdkec10, localArrayList3);
    if (!_sdkb())
    {
      com.skyhookwireless._sdkhb local_sdkhb3 = this._sdka;
      String str3 = z[44];
      local_sdkhb3._sdkb(str3);
      if (i != 0)
        localObject1 = localArrayList3;
    }
    else
    {
      com.skyhookwireless._sdkhb local_sdkhb4 = this._sdka;
      String str4 = z[47];
      local_sdkhb4._sdkb(str4);
    }
    for (Object localObject2 = localObject1; ; localObject2 = localArrayList3)
    {
      if (this._sdka._sdkb())
      {
        com.skyhookwireless._sdkhb local_sdkhb5 = this._sdka;
        StringBuilder localStringBuilder1 = new StringBuilder();
        String str5 = z[46];
        StringBuilder localStringBuilder2 = localStringBuilder1.append(str5);
        int i1 = localArrayList3.size();
        String str6 = i1;
        local_sdkhb5._sdkb(str6);
        com.skyhookwireless._sdkhb local_sdkhb6 = this._sdka;
        StringBuilder localStringBuilder3 = new StringBuilder();
        String str7 = z[48];
        String str8 = str7 + n;
        local_sdkhb6._sdkb(str8);
      }
      boolean bool3;
      _sdktd local_sdktd1;
      _sdkib local_sdkib3;
      _sdkib local_sdkib4;
      if (!localArrayList3.isEmpty())
      {
        boolean bool2 = this._sdkl;
        this._sdkm = bool2;
        if (n <= 0)
        {
          bool3 = true;
          this._sdkl = bool3;
        }
      }
      else
      {
        _sdktc local_sdktc = this._sdke;
        _sdkib local_sdkib2 = this._sdkk;
        ArrayList localArrayList4 = new ArrayList((Collection)localObject2);
        com.skyhookwireless._sdkec local_sdkec11 = param_sdkec;
        local_sdktd1 = local_sdktc.calculateLocation(local_sdkib2, localArrayList4, localArrayList2, local_sdkec11);
        if (param_sdkib != null)
          break label1078;
        _sdks local_sdks2 = this._sdkc;
        com.skyhookwireless._sdkec local_sdkec12 = param_sdkec;
        local_sdkib3 = (_sdkib)local_sdks2._sdkb(local_sdkec12, 5000L);
        if (local_sdkib3 == null)
          break label1071;
        if (local_sdkib3.getSatellites() >= 1)
        {
          com.skyhookwireless._sdkhb local_sdkhb7 = this._sdka;
          String str9 = z[42];
          local_sdkhb7._sdkb(str9);
          if (i == 0)
            break label1071;
        }
        local_sdkib4 = null;
      }
      while (true)
      {
        int i2 = ((ArrayList)localObject2).size();
        _sdkib local_sdkib5 = (_sdkib)local_sdktd1.second;
        XPSSwitchingAlgorithm localXPSSwitchingAlgorithm3 = this;
        com.skyhookwireless._sdkec local_sdkec13 = param_sdkec;
        _sdktd local_sdktd2 = localXPSSwitchingAlgorithm3._sdka(i2, local_sdkib5, local_sdkib4, local_sdkec13);
        _sdkub local_sdkub = this._sdkf;
        _sdkib local_sdkib6 = (_sdkib)local_sdktd1.second;
        int i3 = localArrayList3.size();
        boolean bool4;
        label755: boolean bool5;
        label796: _sdktd local_sdktd5;
        boolean bool8;
        if ((this._sdkd._sdka()) && (this._sdkd._sdkd()))
        {
          bool4 = true;
          Object localObject3 = local_sdktd2.first;
          _sdkd local_sdkd1 = _sdkd.USE_GPS_RAW;
          if (localObject3 != local_sdkd1)
          {
            Object localObject4 = local_sdktd2.first;
            _sdkd local_sdkd2 = _sdkd.USE_GPS_SMOOTHED;
            if (localObject4 != local_sdkd2)
              break label1052;
          }
          bool5 = true;
          boolean bool6 = paramBoolean1;
          boolean bool7 = paramBoolean2;
          long l = paramLong;
          com.skyhookwireless._sdkec local_sdkec14 = param_sdkec;
          local_sdkub._sdka(local_sdkib6, local_sdkib4, i3, bool6, bool7, bool4, l, bool5, local_sdkec14);
          int i4 = ((ArrayList)localObject2).size();
          XPSSwitchingAlgorithm localXPSSwitchingAlgorithm4 = this;
          _sdktd local_sdktd3 = local_sdktd2;
          _sdktd local_sdktd4 = local_sdktd1;
          _sdkib local_sdkib7 = local_sdkib4;
          com.skyhookwireless._sdkec local_sdkec15 = param_sdkec;
          local_sdktd5 = localXPSSwitchingAlgorithm4._sdka(local_sdktd3, i4, local_sdktd4, local_sdkib7, local_sdkec15);
          if ((local_sdkib4 != null) && (local_sdkib4.hasSpeed()))
          {
            bool8 = local_sdkib4._sdkf();
            if (i == 0)
              break label1064;
          }
          if ((this._sdkd._sdka()) && (!this._sdkd._sdkd()))
            break label1058;
          bool8 = true;
        }
        label926: label1058: label1064: for (boolean bool9 = bool8; ; bool9 = bool8)
        {
          com.skyhookwireless._sdkhb local_sdkhb8 = this._sdka;
          StringBuilder localStringBuilder4 = new StringBuilder();
          String str10 = z[45];
          StringBuilder localStringBuilder5 = localStringBuilder4.append(str10);
          Object localObject5 = local_sdktd5.second;
          String str11 = localObject5;
          local_sdkhb8._sdkb(str11);
          _sdkec local_sdkec = this._sdkh;
          _sdkib local_sdkib8 = (_sdkib)local_sdktd5.second;
          com.skyhookwireless._sdkec local_sdkec16 = param_sdkec;
          _sdkib local_sdkib9 = local_sdkec._sdka(bool9, local_sdkib8, local_sdkec16);
          Object localObject6 = local_sdktd5.first;
          return new _sdktd(localObject6, local_sdkib9);
          bool3 = false;
          break;
          bool4 = false;
          break label755;
          bool5 = false;
          break label796;
          bool8 = false;
          break label926;
        }
        label1052: label1071: local_sdkib4 = local_sdkib3;
        continue;
        label1078: local_sdkib4 = param_sdkib;
      }
    }
  }

  public long getGpsPeriod()
  {
    return this._sdkf._sdkb();
  }

  public long getWifiPeriod()
  {
    return this._sdkf._sdka();
  }

  public void saveRemoteLocation(_sdkib param_sdkib)
  {
    boolean bool1 = true;
    if (param_sdkib == null)
    {
      com.skyhookwireless._sdkhb local_sdkhb1 = this._sdka;
      String str1 = z[37];
      local_sdkhb1._sdkb(str1);
      return;
    }
    if (param_sdkib.getNAP() <= 0)
    {
      com.skyhookwireless._sdkhb local_sdkhb2 = this._sdka;
      String str2 = z[36];
      local_sdkhb2._sdkb(str2);
      return;
    }
    if (this._sdkk == null)
    {
      com.skyhookwireless._sdkhb local_sdkhb3 = this._sdka;
      String str3 = z[39];
      local_sdkhb3._sdkb(str3);
      this._sdkk = param_sdkib;
      return;
    }
    com.skyhookwireless._sdkec local_sdkec1 = com.skyhookwireless._sdkec._sdkd();
    boolean bool2;
    _sdkud local_sdkud1;
    if (!_sdkb(param_sdkib, local_sdkec1))
    {
      bool2 = true;
      Boolean localBoolean1 = Boolean.valueOf(bool2);
      com.skyhookwireless._sdkec local_sdkec2 = param_sdkib.getAge();
      local_sdkud1 = _sdkud._sdka(localBoolean1, local_sdkec2);
      if (_sdkb(this._sdkk, local_sdkec1))
        break label207;
    }
    while (true)
    {
      Boolean localBoolean2 = Boolean.valueOf(bool1);
      com.skyhookwireless._sdkec local_sdkec3 = this._sdkk.getAge();
      _sdkud local_sdkud2 = _sdkud._sdka(localBoolean2, local_sdkec3);
      if (local_sdkud1._sdka(local_sdkud2) > 0)
        break label212;
      com.skyhookwireless._sdkhb local_sdkhb4 = this._sdka;
      String str4 = z[38];
      local_sdkhb4._sdkb(str4);
      this._sdkk = param_sdkib;
      return;
      bool2 = false;
      break;
      label207: bool1 = false;
    }
    label212: com.skyhookwireless._sdkhb local_sdkhb5 = this._sdka;
    String str5 = z[40];
    local_sdkhb5._sdkb(str5);
  }
}

/* Location:           D:\Tools\extractapktools\extractapktools\dex2jar-0.0.7.11-SNAPSHOT\classes_dex2jar.jar
 * Qualified Name:     com.skyhookwireless.wps.XPSSwitchingAlgorithm
 * JD-Core Version:    0.6.2
 */